a cv (III)Ljava/lang/String;L1
    iload 1
    iload 0
    isub
    istore 3
    goto L2
L3
    ldc 16723968 (java.lang.Integer)
    bipush -8
    invokestatic p e:(IB)Ljava/lang/String;
    areturn
L4
    ldc 16711680 (java.lang.Integer)
    bipush -35
    invokestatic p e:(IB)Ljava/lang/String;
    areturn
L5
    iload 3
    bipush -6
    if_icmpge L6
    goto L3
L7
    ldc 16740352 (java.lang.Integer)
    bipush -46
    invokestatic p e:(IB)Ljava/lang/String;
    areturn
L6
    iload 3
    bipush -3
    if_icmpge L8
    goto L7
L9
    ldc 12648192 (java.lang.Integer)
    bipush -22
    invokestatic p e:(IB)Ljava/lang/String;
    areturn
L2
    iload 3
    bipush -9
    if_icmpge L5
    iload 2
    ldc -126503352 (java.lang.Integer)
    if_icmpgt L4
    new java/lang/IllegalStateException
    dup
    invokespecial java/lang/IllegalStateException <init>:()V
    athrow
L10
    ldc 16756736 (java.lang.Integer)
    bipush -83
    invokestatic p e:(IB)Ljava/lang/String;
    areturn
L11
    iload 3
    bipush 9
    if_icmple L12
    iload 2
    ldc -126503352 (java.lang.Integer)
    if_icmpgt L13
    new java/lang/IllegalStateException
    dup
    invokespecial java/lang/IllegalStateException <init>:()V
    athrow
L14
    ldc 8453888 (java.lang.Integer)
    bipush -3
    invokestatic p e:(IB)Ljava/lang/String;
    areturn
L12
    iload 3
    bipush 6
    if_icmple L15
    iload 2
    ldc -126503352 (java.lang.Integer)
    if_icmpgt L16
    new java/lang/IllegalStateException
    dup
    invokespecial java/lang/IllegalStateException <init>:()V
    athrow
L16
    ldc 4259584 (java.lang.Integer)
    bipush -9
    invokestatic p e:(IB)Ljava/lang/String;
    areturn
L15
    iload 3
    iconst_3
    if_icmple L17
    iload 2
    ldc -126503352 (java.lang.Integer)
    if_icmpgt L14
    new java/lang/IllegalStateException
    dup
    invokespecial java/lang/IllegalStateException <init>:()V
    athrow
L8
    iload 3
    ifge L11
    goto L10
L17
    iload 3
    ifle L18
    iload 2
    ldc -126503352 (java.lang.Integer)
    if_icmpgt L9
    new java/lang/IllegalStateException
    dup
    invokespecial java/lang/IllegalStateException <init>:()V
    athrow
L13
    ldc 65280 (java.lang.Integer)
    bipush -19
    invokestatic p e:(IB)Ljava/lang/String;
    areturn
L18
    ldc 16776960 (java.lang.Integer)
    bipush -19
    invokestatic p e:(IB)Ljava/lang/String;
    areturn
L19
    new java/lang/StringBuilder
    dup
    invokespecial java/lang/StringBuilder <init>:()V
    ldc "a.cv(" (java.lang.String)
    invokevirtual java/lang/StringBuilder append:(Ljava/lang/String;)Ljava/lang/StringBuilder;
    ldc 41 (java.lang.Integer)
    invokevirtual java/lang/StringBuilder append:(C)Ljava/lang/StringBuilder;
    invokevirtual java/lang/StringBuilder toString:()Ljava/lang/String;
    invokestatic k a:(Ljava/lang/Throwable;Ljava/lang/String;)Lee;
    athrow
