ab t (IIZI)VL1
    iconst_m1
    ldc 1048158519 (java.lang.Integer)
    aload 0
    getfield ab bl:I
    imul
    if_icmpeq L2
    iload 4
    ldc 420040634 (java.lang.Integer)
    if_icmpgt L3
    new java/lang/IllegalStateException
    dup
    invokespecial java/lang/IllegalStateException <init>:()V
    athrow
L4
    aload 0
    ldc -2003952775 (java.lang.Integer)
    putfield ab bl:I
    goto L2
L5
    aload 0
    iconst_0
    putfield ab ch:I
    goto L6
L2
    iload 3
    ifne L7
    iload 4
    ldc 420040634 (java.lang.Integer)
    if_icmpgt L8
    new java/lang/IllegalStateException
    dup
    invokespecial java/lang/IllegalStateException <init>:()V
    athrow
L3
    aload 0
    getfield ab bl:I
    ldc 1048158519 (java.lang.Integer)
    imul
    ldc 152969838 (java.lang.Integer)
    invokestatic cd e:(II)Lah;
    getfield ah y:I
    ldc 687350469 (java.lang.Integer)
    imul
    iconst_1
    if_icmpne L2
    iload 4
    ldc 420040634 (java.lang.Integer)
    if_icmpgt L4
    new java/lang/IllegalStateException
    dup
    invokespecial java/lang/IllegalStateException <init>:()V
    athrow
L9
    iload 2
    aload 0
    getfield ab bo:[I
    iconst_0
    iaload
    isub
    istore 6
L10
    iload 5
    bipush -8
    if_icmplt L7
    iload 4
    ldc 420040634 (java.lang.Integer)
    if_icmpgt L11
    new java/lang/IllegalStateException
    dup
    invokespecial java/lang/IllegalStateException <init>:()V
    athrow
L11
    iload 5
    bipush 8
    if_icmpgt L7
    iload 4
    ldc 420040634 (java.lang.Integer)
    if_icmpgt L12
    return
L8
    iload 1
    aload 0
    getfield ab bs:[I
    iconst_0
    iaload
    isub
    istore 5
    goto L9
L13
    iload 6
    bipush 8
    if_icmpgt L7
    iload 4
    ldc 420040634 (java.lang.Integer)
    if_icmpgt L14
    new java/lang/IllegalStateException
    dup
    invokespecial java/lang/IllegalStateException <init>:()V
    athrow
L15
    aload 0
    ldc -325767552 (java.lang.Integer)
    aload 0
    getfield ab bs:[I
    iconst_0
    iaload
    imul
    aload 0
    getfield ab p:I
    ldc 586821952 (java.lang.Integer)
    imul
    iadd
    putfield ab b:I
    goto L16
L7
    aload 0
    iconst_0
    putfield ab bt:I
    goto L5
L17
    aload 0
    getfield ab bt:I
    ldc -426846849 (java.lang.Integer)
    imul
    istore 7
L18
    iload 7
    ifle L19
    iload 4
    ldc 420040634 (java.lang.Integer)
    if_icmpgt L20
    new java/lang/IllegalStateException
    dup
    invokespecial java/lang/IllegalStateException <init>:()V
    athrow
L20
    aload 0
    getfield ab bs:[I
    iload 7
    aload 0
    getfield ab bs:[I
    iload 7
    iconst_1
    isub
    iaload
    iastore
    goto L21
L22
    aload 0
    dup
    getfield ab bt:I
    ldc 453175935 (java.lang.Integer)
    iadd
    putfield ab bt:I
    goto L17
L23
    aload 0
    getfield ab bg:[Z
    iload 7
    aload 0
    getfield ab bg:[Z
    iload 7
    iconst_1
    isub
    baload
    bastore
    goto L24
L16
    aload 0
    aload 0
    getfield ab p:I
    ldc -695165120 (java.lang.Integer)
    imul
    aload 0
    getfield ab bo:[I
    iconst_0
    iaload
    ldc -303027584 (java.lang.Integer)
    imul
    iadd
    putfield ab x:I
    goto L25
L19
    aload 0
    getfield ab bs:[I
    iconst_0
    iload 1
    iastore
L26
    aload 0
    getfield ab bo:[I
    iconst_0
    iload 2
    iastore
    goto L27
L24
    iinc 7 -1
    goto L18
L28
    return
L14
    aload 0
    getfield ab bt:I
    ldc -426846849 (java.lang.Integer)
    imul
    bipush 9
    if_icmpge L17
    iload 4
    ldc 420040634 (java.lang.Integer)
    if_icmpgt L22
    new java/lang/IllegalStateException
    dup
    invokespecial java/lang/IllegalStateException <init>:()V
    athrow
L27
    aload 0
    getfield ab bg:[Z
    iconst_0
    iconst_0
    bastore
    goto L28
L6
    aload 0
    iconst_0
    putfield ab cf:I
L29
    aload 0
    getfield ab bs:[I
    iconst_0
    iload 1
    iastore
L30
    aload 0
    getfield ab bo:[I
    iconst_0
    iload 2
    iastore
    goto L15
L12
    iload 6
    bipush -8
    if_icmplt L7
    iload 4
    ldc 420040634 (java.lang.Integer)
    if_icmpgt L13
    new java/lang/IllegalStateException
    dup
    invokespecial java/lang/IllegalStateException <init>:()V
    athrow
L21
    aload 0
    getfield ab bo:[I
    iload 7
    aload 0
    getfield ab bo:[I
    iload 7
    iconst_1
    isub
    iaload
    iastore
    goto L23
L25
    return
L31
    new java/lang/StringBuilder
    dup
    invokespecial java/lang/StringBuilder <init>:()V
    ldc "ab.t(" (java.lang.String)
    invokevirtual java/lang/StringBuilder append:(Ljava/lang/String;)Ljava/lang/StringBuilder;
    ldc 41 (java.lang.Integer)
    invokevirtual java/lang/StringBuilder append:(C)Ljava/lang/StringBuilder;
    invokevirtual java/lang/StringBuilder toString:()Ljava/lang/String;
    invokestatic k a:(Ljava/lang/Throwable;Ljava/lang/String;)Lee;
    athrow
