ac r (IIIIIILcb;Lhk;B)VL1
    getstatic client h:Z
    ifeq L2
    iload 8
    iconst_0
    if_icmpne L3
    new java/lang/IllegalStateException
    dup
    invokespecial java/lang/IllegalStateException <init>:()V
    athrow
L4
    iload 4
    iconst_2
    if_icmpne L5
    iload 8
    iconst_0
    if_icmpne L6
    new java/lang/IllegalStateException
    dup
    invokespecial java/lang/IllegalStateException <init>:()V
    athrow
L7
    getstatic w a:[[[B
    iload 0
    aaload
    iload 1
    aaload
    iload 2
    baload
    bipush 16
    iand
    ifeq L8
    iload 8
    iconst_0
    if_icmpne L9
    return
L9
    return
L10
    aload 6
    iload 0
    iload 1
    iload 2
    invokevirtual cb ax:(III)I
    istore 23
    goto L11
L12
    iload 9
    getstatic client ca:I
    ldc 633325001 (java.lang.Integer)
    imul
    if_icmpeq L2
    iload 8
    iconst_0
    if_icmpne L13
    new java/lang/IllegalStateException
    dup
    invokespecial java/lang/IllegalStateException <init>:()V
    athrow
L14
    goto L12
L15
    iload 0
    ifle L16
    iload 8
    iconst_0
    if_icmpne L17
    return
L17
    iconst_0
    getstatic w a:[[[B
    iconst_1
    aaload
    iload 1
    aaload
    iload 2
    baload
    iconst_2
    iand
    if_icmpeq L16
    iload 8
    iconst_0
    if_icmpne L18
    new java/lang/IllegalStateException
    dup
    invokespecial java/lang/IllegalStateException <init>:()V
    athrow
L18
    iload 0
    iconst_1
    isub
    istore 9
    goto L19
L20
    iload 23
    getstatic w r:[[[B
    iload 0
    aaload
    iload 1
    iload 24
    iadd
    aaload
    iload 25
    iload 2
    iadd
    baload
    if_icmple L21
    iload 8
    iconst_0
    if_icmpne L22
    new java/lang/IllegalStateException
    dup
    invokespecial java/lang/IllegalStateException <init>:()V
    athrow
L23
    aconst_null
    aload 9
    getfield ag ak:[I
    if_acmpne L24
    iload 8
    iconst_0
    if_icmpne L25
    new java/lang/IllegalStateException
    dup
    invokespecial java/lang/IllegalStateException <init>:()V
    athrow
L26
    iload 10
    iconst_1
    ishr
    iload 1
    iadd
    istore 12
    goto L27
L13
    return
L2
    iload 0
    ldc -887971499 (java.lang.Integer)
    getstatic w l:I
    imul
    if_icmpge L28
    iload 8
    iconst_0
    if_icmpne L29
    return
L30
    aload 6
    iload 0
    iload 1
    iload 2
    iload 17
    aload 24
    aconst_null
    getstatic w q:[I
    iload 4
    iaload
    iconst_0
    getstatic w b:[I
    iload 4
    iaload
    iload 22
    imul
    iload 22
    getstatic w x:[I
    iload 4
    iaload
    imul
    iload 20
    iload 21
    invokevirtual cb g:(IIIILch;Lch;IIIIII)V
    goto L31
L28
    iload 3
    bipush -25
    invokestatic m e:(IB)Lag;
    astore 9
    goto L32
L33
    aload 9
    iconst_4
    iload 4
    aload 16
    iload 18
    iload 17
    iload 19
    ldc -1492115715 (java.lang.Integer)
    invokevirtual ag i:(II[[IIIII)Lch;
    astore 24
    goto L30
L34
    aconst_null
    aload 7
    if_acmpeq L35
    iload 8
    iconst_0
    if_icmpne L36
    new java/lang/IllegalStateException
    dup
    invokespecial java/lang/IllegalStateException <init>:()V
    athrow
L37
    ldc -1050702509 (java.lang.Integer)
    aload 9
    getfield ag y:I
    imul
    istore 10
    goto L38
L39
    iload 11
    iconst_1
    ishr
    iload 2
    iadd
    istore 14
    goto L40
L41
    ldc 1527764841 (java.lang.Integer)
    aload 9
    getfield ag z:I
    imul
    istore 10
    goto L42
L43
    new h
    dup
    iload 3
    iconst_2
    iload 22
    iload 0
    iload 1
    iload 2
    aload 9
    getfield ag p:I
    ldc -175609259 (java.lang.Integer)
    imul
    iconst_1
    aconst_null
    invokespecial h <init>:(IIIIIIIZLch;)V
    astore 24
    goto L44
L45
    aload 7
    iload 1
    iload 2
    iload 5
    iload 4
    aload 9
    getfield ag d:Z
    ldc -1236478086 (java.lang.Integer)
    invokevirtual hk a:(IIIIZI)V
    goto L46
L47
    new h
    dup
    iload 3
    iconst_4
    iconst_4
    iload 26
    iadd
    iload 0
    iload 1
    iload 2
    aload 9
    getfield ag p:I
    ldc -175609259 (java.lang.Integer)
    imul
    iconst_1
    aconst_null
    invokespecial h <init>:(IIIIIIIZLch;)V
    astore 25
    goto L48
L27
    iconst_1
    iload 10
    iadd
    iconst_1
    ishr
    iload 1
    iadd
    istore 13
    goto L49
L50
    iload 23
    ifeq L51
    iload 8
    iconst_0
    if_icmpne L52
    new java/lang/IllegalStateException
    dup
    invokespecial java/lang/IllegalStateException <init>:()V
    athrow
L53
    return
L49
    iload 2
    iload 11
    iadd
    bipush 104
    if_icmpgt L54
    iload 8
    iconst_0
    if_icmpne L39
    new java/lang/IllegalStateException
    dup
    invokespecial java/lang/IllegalStateException <init>:()V
    athrow
L55
    iload 1
    iload 10
    iadd
    bipush 104
    if_icmpgt L56
    iload 8
    iconst_0
    if_icmpne L26
    new java/lang/IllegalStateException
    dup
    invokespecial java/lang/IllegalStateException <init>:()V
    athrow
L40
    iload 11
    iconst_1
    iadd
    iconst_1
    ishr
    iload 2
    iadd
    istore 15
    goto L57
L54
    iload 2
    istore 14
L58
    iconst_1
    iload 2
    iadd
    istore 15
    goto L57
L59
    iload 4
    bipush 6
    ishl
    iload 5
    iadd
    istore 21
    goto L60
L19
    goto L12
L61
    iload 1
    bipush 7
    ishl
    iload 10
    bipush 6
    ishl
    iadd
    istore 18
L62
    iload 11
    bipush 6
    ishl
    iload 2
    bipush 7
    ishl
    iadd
    istore 19
L63
    iload 2
    bipush 7
    ishl
    iload 1
    iadd
    iload 3
    bipush 14
    ishl
    iadd
    ldc 1073741824 (java.lang.Integer)
    iadd
    istore 20
    goto L64
L16
    iload 0
    istore 9
    goto L12
L65
    iload 20
    ldc -2147483648 (java.lang.Integer)
    isub
    istore 20
    goto L59
L66
    aload 9
    getfield ag q:I
    ldc -1945821617 (java.lang.Integer)
    imul
    ifeq L67
    iload 8
    iconst_0
    if_icmpne L68
    new java/lang/IllegalStateException
    dup
    invokespecial java/lang/IllegalStateException <init>:()V
    athrow
L60
    iconst_1
    aload 9
    getfield ag al:I
    ldc 970437277 (java.lang.Integer)
    imul
    if_icmpne L69
    iload 8
    iconst_0
    if_icmpne L70
    new java/lang/IllegalStateException
    dup
    invokespecial java/lang/IllegalStateException <init>:()V
    athrow
L70
    iinc 21 256
L69
    aload 9
    ldc -580442393 (java.lang.Integer)
    invokevirtual ag h:(I)Z
    ifeq L71
    goto L72
L46
    return
L71
    iload 5
    bipush 22
    if_icmpne L73
    goto L74
L75
    getstatic w r:[[[B
    iload 0
    aaload
    iload 1
    aaload
    iload 2
    bipush 50
    bastore
    goto L76
L77
    aload 9
    getfield ag b:I
    ldc 1715787739 (java.lang.Integer)
    imul
    ifne L78
    iload 8
    iconst_0
    if_icmpne L79
    new java/lang/IllegalStateException
    dup
    invokespecial java/lang/IllegalStateException <init>:()V
    athrow
L79
    iconst_1
    ldc -1945821617 (java.lang.Integer)
    aload 9
    getfield ag q:I
    imul
    if_icmpeq L78
    iload 8
    iconst_0
    if_icmpne L80
    new java/lang/IllegalStateException
    dup
    invokespecial java/lang/IllegalStateException <init>:()V
    athrow
L57
    getstatic w e:[[[I
    iload 0
    aaload
    astore 16
    goto L81
L82
    aload 22
    instanceof cy
    ifeq L83
    goto L84
L78
    aload 9
    getfield ag p:I
    ldc -175609259 (java.lang.Integer)
    imul
    iconst_m1
    if_icmpne L85
    iload 8
    iconst_0
    if_icmpne L86
    new java/lang/IllegalStateException
    dup
    invokespecial java/lang/IllegalStateException <init>:()V
    athrow
L87
    iload 5
    bipush 12
    if_icmplt L88
    iload 8
    iconst_0
    if_icmpne L89
    new java/lang/IllegalStateException
    dup
    invokespecial java/lang/IllegalStateException <init>:()V
    athrow
L90
    aload 9
    bipush 22
    iload 4
    aload 16
    iload 18
    iload 17
    iload 19
    ldc -987679107 (java.lang.Integer)
    invokevirtual ag i:(II[[IIIII)Lch;
    astore 22
    goto L91
L85
    new h
    dup
    iload 3
    bipush 22
    iload 4
    iload 0
    iload 1
    iload 2
    aload 9
    getfield ag p:I
    ldc -175609259 (java.lang.Integer)
    imul
    iconst_1
    aconst_null
    invokespecial h <init>:(IIIIIIIZLch;)V
    astore 22
    goto L91
L72
    iload 0
    iload 1
    iload 2
    aload 9
    iload 4
    ldc -184087689 (java.lang.Integer)
    invokestatic l l:(IIILag;II)V
    goto L71
L92
    iconst_m1
    ldc -175609259 (java.lang.Integer)
    aload 9
    getfield ag p:I
    imul
    if_icmpne L93
    iload 8
    iconst_0
    if_icmpne L94
    new java/lang/IllegalStateException
    dup
    invokespecial java/lang/IllegalStateException <init>:()V
    athrow
L95
    aload 7
    ifnull L53
    aload 7
    iload 1
    iload 2
    ldc 1769995303 (java.lang.Integer)
    invokevirtual hk u:(III)V
    goto L53
L96
    aload 6
    iload 0
    iload 1
    iload 2
    iload 17
    aload 24
    aconst_null
    sipush 256
    iload 4
    getstatic w n:[I
    iload 4
    iaload
    iload 22
    imul
    getstatic w v:[I
    iload 4
    iaload
    iload 22
    imul
    iload 20
    iload 21
    invokevirtual cb g:(IIIILch;Lch;IIIIII)V
    goto L97
L73
    bipush 10
    iload 5
    if_icmpeq L98
    iload 8
    iconst_0
    if_icmpne L99
    return
L80
    aload 9
    getfield ag ah:Z
    ifne L78
    iload 8
    iconst_0
    if_icmpne L100
    new java/lang/IllegalStateException
    dup
    invokespecial java/lang/IllegalStateException <init>:()V
    athrow
L98
    iconst_m1
    aload 9
    getfield ag p:I
    ldc -175609259 (java.lang.Integer)
    imul
    if_icmpne L101
    iload 8
    iconst_0
    if_icmpne L102
    new java/lang/IllegalStateException
    dup
    invokespecial java/lang/IllegalStateException <init>:()V
    athrow
L103
    aload 9
    iconst_1
    iload 4
    aload 16
    iload 18
    iload 17
    iload 19
    ldc -394846542 (java.lang.Integer)
    invokevirtual ag i:(II[[IIIII)Lch;
    astore 22
    goto L104
L105
    aload 9
    bipush 10
    iload 4
    aload 16
    iload 18
    iload 17
    iload 19
    ldc -1295684280 (java.lang.Integer)
    invokevirtual ag i:(II[[IIIII)Lch;
    astore 22
    goto L106
L101
    new h
    dup
    iload 3
    bipush 10
    iload 4
    iload 0
    iload 1
    iload 2
    ldc -175609259 (java.lang.Integer)
    aload 9
    getfield ag p:I
    imul
    iconst_1
    aconst_null
    invokespecial h <init>:(IIIIIIIZLch;)V
    astore 22
    goto L106
L107
    iconst_2
    iload 5
    if_icmpne L108
    iload 8
    iconst_0
    if_icmpne L109
    new java/lang/IllegalStateException
    dup
    invokespecial java/lang/IllegalStateException <init>:()V
    athrow
L110
    aload 6
    iload 0
    iload 1
    iload 2
    iload 17
    iload 10
    iload 11
    aload 22
    iload 5
    bipush 11
    if_icmpne L111
    iload 8
    iconst_0
    if_icmpne L112
    new java/lang/IllegalStateException
    dup
    invokespecial java/lang/IllegalStateException <init>:()V
    athrow
L112
    sipush 256
    goto L113
L111
    iconst_0
    goto L113
L114
    iconst_0
    iload 4
    if_icmpne L115
    iload 8
    iconst_0
    if_icmpne L116
    new java/lang/IllegalStateException
    dup
    invokespecial java/lang/IllegalStateException <init>:()V
    athrow
L117
    aload 6
    iload 0
    iload 1
    iload 2
    iload 17
    aload 22
    aconst_null
    getstatic w q:[I
    iload 4
    iaload
    iconst_0
    iconst_0
    iconst_0
    iload 20
    iload 21
    invokevirtual cb g:(IIIILch;Lch;IIIIII)V
    goto L118
L86
    aconst_null
    aload 9
    getfield ag ak:[I
    if_acmpne L85
    iload 8
    iconst_0
    if_icmpne L90
    new java/lang/IllegalStateException
    dup
    invokespecial java/lang/IllegalStateException <init>:()V
    athrow
L56
    iload 1
    istore 12
    goto L119
L120
    aload 7
    iload 1
    iload 2
    iload 10
    iload 11
    aload 9
    getfield ag d:Z
    bipush -57
    invokevirtual hk l:(IIIIZB)V
    goto L121
L122
    iload 23
    bipush 30
    if_icmple L83
    iload 8
    iconst_0
    if_icmpne L123
    new java/lang/IllegalStateException
    dup
    invokespecial java/lang/IllegalStateException <init>:()V
    athrow
L123
    bipush 30
    istore 23
L83
    iconst_0
    istore 24
L124
    iload 24
    iload 10
    if_icmpgt L125
    iload 8
    iconst_0
    if_icmpne L126
    return
L127
    aload 7
    ifnull L46
    iload 8
    iconst_0
    if_icmpne L45
    new java/lang/IllegalStateException
    dup
    invokespecial java/lang/IllegalStateException <init>:()V
    athrow
L91
    aload 6
    iload 0
    iload 1
    iload 2
    iload 17
    aload 22
    iload 20
    iload 21
    invokevirtual cb i:(IIIILch;II)V
    goto L128
L42
    ldc -1050702509 (java.lang.Integer)
    aload 9
    getfield ag y:I
    imul
    istore 11
    goto L55
L22
    getstatic w r:[[[B
    iload 0
    aaload
    iload 24
    iload 1
    iadd
    aaload
    iload 25
    iload 2
    iadd
    iload 23
    i2b
    bastore
L21
    iinc 25 1
    goto L129
L130
    iinc 24 1
    goto L124
L125
    iconst_0
    aload 9
    getfield ag q:I
    ldc -1945821617 (java.lang.Integer)
    imul
    if_icmpeq L131
    iload 8
    iconst_0
    if_icmpne L132
    new java/lang/IllegalStateException
    dup
    invokespecial java/lang/IllegalStateException <init>:()V
    athrow
L132
    aload 7
    ifnull L131
    iload 8
    iconst_0
    if_icmpne L133
    new java/lang/IllegalStateException
    dup
    invokespecial java/lang/IllegalStateException <init>:()V
    athrow
L133
    aload 7
    iload 1
    iload 2
    iload 10
    iload 11
    aload 9
    getfield ag d:Z
    bipush -61
    invokevirtual hk l:(IIIIZB)V
    goto L131
L134
    iload 5
    bipush 8
    if_icmpne L135
    iload 8
    iconst_0
    if_icmpne L136
    new java/lang/IllegalStateException
    dup
    invokespecial java/lang/IllegalStateException <init>:()V
    athrow
L137
    iload 5
    iconst_4
    if_icmpne L138
    iload 8
    iconst_0
    if_icmpne L139
    new java/lang/IllegalStateException
    dup
    invokespecial java/lang/IllegalStateException <init>:()V
    athrow
L140
    ldc -175609259 (java.lang.Integer)
    aload 9
    getfield ag p:I
    imul
    iconst_m1
    if_icmpne L24
    iload 8
    iconst_0
    if_icmpne L23
    new java/lang/IllegalStateException
    dup
    invokespecial java/lang/IllegalStateException <init>:()V
    athrow
L138
    iload 5
    iconst_5
    if_icmpne L141
    iload 8
    iconst_0
    if_icmpne L142
    return
L25
    aload 9
    iload 5
    iload 4
    aload 16
    iload 18
    iload 17
    iload 19
    ldc 785432839 (java.lang.Integer)
    invokevirtual ag i:(II[[IIIII)Lch;
    astore 22
    goto L143
L24
    new h
    dup
    iload 3
    iload 5
    iload 4
    iload 0
    iload 1
    iload 2
    ldc -175609259 (java.lang.Integer)
    aload 9
    getfield ag p:I
    imul
    iconst_1
    aconst_null
    invokespecial h <init>:(IIIIIIIZLch;)V
    astore 22
L143
    aload 6
    iload 0
    iload 1
    iload 2
    iload 17
    iconst_1
    iconst_1
    aload 22
    iconst_0
    iload 20
    iload 21
    invokevirtual cb o:(IIIIIILch;III)Z
    pop
    goto L87
L144
    aload 9
    iconst_0
    iload 4
    aload 16
    iload 18
    iload 17
    iload 19
    ldc -1663067797 (java.lang.Integer)
    invokevirtual ag i:(II[[IIIII)Lch;
    astore 22
    goto L145
L146
    new h
    dup
    iload 3
    iconst_0
    iload 4
    iload 0
    iload 1
    iload 2
    ldc -175609259 (java.lang.Integer)
    aload 9
    getfield ag p:I
    imul
    iconst_1
    aconst_null
    invokespecial h <init>:(IIIIIIIZLch;)V
    astore 22
    goto L145
L147
    bipush 13
    iload 5
    if_icmpeq L88
    iload 8
    iconst_0
    if_icmpne L148
    new java/lang/IllegalStateException
    dup
    invokespecial java/lang/IllegalStateException <init>:()V
    athrow
L64
    iconst_0
    ldc 1715787739 (java.lang.Integer)
    aload 9
    getfield ag b:I
    imul
    if_icmpne L59
    iload 8
    iconst_0
    if_icmpne L65
    new java/lang/IllegalStateException
    dup
    invokespecial java/lang/IllegalStateException <init>:()V
    athrow
L142
    bipush 16
    istore 22
    goto L149
L88
    iconst_0
    aload 9
    getfield ag q:I
    ldc -1945821617 (java.lang.Integer)
    imul
    if_icmpeq L150
    iload 8
    iconst_0
    if_icmpne L151
    new java/lang/IllegalStateException
    dup
    invokespecial java/lang/IllegalStateException <init>:()V
    athrow
L151
    aconst_null
    aload 7
    if_acmpeq L150
    iload 8
    iconst_0
    if_icmpne L152
    new java/lang/IllegalStateException
    dup
    invokespecial java/lang/IllegalStateException <init>:()V
    athrow
L152
    aload 7
    iload 1
    iload 2
    iload 10
    iload 11
    aload 9
    getfield ag d:Z
    bipush -18
    invokevirtual hk l:(IIIIZB)V
L150
    return
L153
    iload 5
    ifne L154
L155
    aload 9
    getfield ag p:I
    ldc -175609259 (java.lang.Integer)
    imul
    iconst_m1
    if_icmpne L146
    iload 8
    iconst_0
    if_icmpne L156
    new java/lang/IllegalStateException
    dup
    invokespecial java/lang/IllegalStateException <init>:()V
    athrow
L156
    aconst_null
    aload 9
    getfield ag ak:[I
    if_acmpne L146
    iload 8
    iconst_0
    if_icmpne L144
    new java/lang/IllegalStateException
    dup
    invokespecial java/lang/IllegalStateException <init>:()V
    athrow
L128
    iconst_1
    ldc -1945821617 (java.lang.Integer)
    aload 9
    getfield ag q:I
    imul
    if_icmpne L53
    iload 8
    iconst_0
    if_icmpne L95
    new java/lang/IllegalStateException
    dup
    invokespecial java/lang/IllegalStateException <init>:()V
    athrow
L100
    return
L157
    aload 9
    getfield ag ak:[I
    ifnonnull L158
    iload 8
    iconst_0
    if_icmpne L159
    return
L160
    iload 4
    ifne L161
    iload 8
    iconst_0
    if_icmpne L162
    new java/lang/IllegalStateException
    dup
    invokespecial java/lang/IllegalStateException <init>:()V
    athrow
L162
    aload 9
    getfield ag au:Z
    ifeq L163
L164
    getstatic w r:[[[B
    iload 0
    aaload
    iload 1
    aaload
    iload 2
    bipush 50
    bastore
L165
    getstatic w r:[[[B
    iload 0
    aaload
    iload 1
    aaload
    iconst_1
    iload 2
    iadd
    bipush 50
    bastore
L163
    aload 9
    getfield ag v:Z
    ifeq L166
    iload 8
    iconst_0
    if_icmpne L167
    return
L104
    aload 6
    iload 0
    iload 1
    iload 2
    iload 17
    aload 22
    aconst_null
    getstatic w d:[I
    iload 4
    iaload
    iconst_0
    iload 20
    iload 21
    invokevirtual cb f:(IIIILch;Lch;IIII)V
    goto L168
L161
    iload 4
    iconst_1
    if_icmpne L169
    iload 8
    iconst_0
    if_icmpne L170
    new java/lang/IllegalStateException
    dup
    invokespecial java/lang/IllegalStateException <init>:()V
    athrow
L170
    aload 9
    getfield ag au:Z
    ifeq L171
    iload 8
    iconst_0
    if_icmpne L172
    new java/lang/IllegalStateException
    dup
    invokespecial java/lang/IllegalStateException <init>:()V
    athrow
L172
    getstatic w r:[[[B
    iload 0
    aaload
    iload 1
    aaload
    iload 2
    iconst_1
    iadd
    bipush 50
    bastore
    goto L173
L159
    aload 9
    iconst_3
    iload 4
    aload 16
    iload 18
    iload 17
    iload 19
    ldc 1419765119 (java.lang.Integer)
    invokevirtual ag i:(II[[IIIII)Lch;
    astore 22
    goto L174
L175
    iconst_0
    iload 4
    if_icmpne L176
    iload 8
    iconst_0
    if_icmpne L177
    return
L178
    iconst_m1
    aload 9
    getfield ag p:I
    ldc -175609259 (java.lang.Integer)
    imul
    if_icmpne L179
    iload 8
    iconst_0
    if_icmpne L180
    new java/lang/IllegalStateException
    dup
    invokespecial java/lang/IllegalStateException <init>:()V
    athrow
L169
    iload 4
    iconst_2
    if_icmpne L181
    iload 8
    iconst_0
    if_icmpne L182
    new java/lang/IllegalStateException
    dup
    invokespecial java/lang/IllegalStateException <init>:()V
    athrow
L182
    aload 9
    getfield ag au:Z
    ifeq L183
    iload 8
    iconst_0
    if_icmpne L184
    new java/lang/IllegalStateException
    dup
    invokespecial java/lang/IllegalStateException <init>:()V
    athrow
L184
    getstatic w r:[[[B
    iload 0
    aaload
    iload 1
    iconst_1
    iadd
    aaload
    iload 2
    bipush 50
    bastore
L185
    getstatic w r:[[[B
    iload 0
    aaload
    iconst_1
    iload 1
    iadd
    aaload
    iload 2
    iconst_1
    iadd
    bipush 50
    bastore
    goto L183
L186
    aconst_null
    aload 9
    getfield ag ak:[I
    if_acmpne L187
    iload 8
    iconst_0
    if_icmpne L188
    return
L189
    getstatic gp m:[[[I
    iload 0
    aaload
    iload 1
    iconst_1
    iadd
    aaload
    iload 2
    dup2
    iaload
    sipush 585
    ior
    iastore
    goto L166
L89
    iload 5
    bipush 17
    if_icmpgt L88
    iload 8
    iconst_0
    if_icmpne L147
    new java/lang/IllegalStateException
    dup
    invokespecial java/lang/IllegalStateException <init>:()V
    athrow
L190
    aload 9
    getfield ag au:Z
    ifeq L191
    iload 8
    iconst_0
    if_icmpne L192
    new java/lang/IllegalStateException
    dup
    invokespecial java/lang/IllegalStateException <init>:()V
    athrow
L192
    getstatic w r:[[[B
    iload 0
    aaload
    iload 1
    aaload
    iload 2
    bipush 50
    bastore
    goto L193
L194
    aload 9
    iconst_4
    iconst_4
    iload 26
    iadd
    aload 16
    iload 18
    iload 17
    iload 19
    ldc -1803695593 (java.lang.Integer)
    invokevirtual ag i:(II[[IIIII)Lch;
    astore 25
    goto L48
L191
    aload 9
    getfield ag v:Z
    ifeq L166
    iload 8
    iconst_0
    if_icmpne L195
    new java/lang/IllegalStateException
    dup
    invokespecial java/lang/IllegalStateException <init>:()V
    athrow
L32
    iload 4
    iconst_1
    if_icmpeq L37
    goto L196
L166
    ldc -1945821617 (java.lang.Integer)
    aload 9
    getfield ag q:I
    imul
    ifeq L35
    iload 8
    iconst_0
    if_icmpne L34
    return
L197
    getstatic w r:[[[B
    iload 0
    aaload
    iload 1
    iconst_1
    iadd
    aaload
    iconst_1
    iload 2
    iadd
    bipush 50
    bastore
    goto L198
L36
    aload 7
    iload 1
    iload 2
    iload 5
    iload 4
    aload 9
    getfield ag d:Z
    ldc -2110190735 (java.lang.Integer)
    invokevirtual hk a:(IIIIZI)V
L35
    bipush 16
    ldc 1127355445 (java.lang.Integer)
    aload 9
    getfield ag k:I
    imul
    if_icmpeq L199
    iload 8
    iconst_0
    if_icmpne L200
    new java/lang/IllegalStateException
    dup
    invokespecial java/lang/IllegalStateException <init>:()V
    athrow
L38
    aload 9
    getfield ag z:I
    ldc 1527764841 (java.lang.Integer)
    imul
    istore 11
    goto L55
L135
    return
L154
    iconst_1
    iload 5
    if_icmpne L107
L201
    iconst_m1
    ldc -175609259 (java.lang.Integer)
    aload 9
    getfield ag p:I
    imul
    if_icmpne L202
    iload 8
    iconst_0
    if_icmpne L203
    return
L203
    aconst_null
    aload 9
    getfield ag ak:[I
    if_acmpne L202
    iload 8
    iconst_0
    if_icmpne L103
    new java/lang/IllegalStateException
    dup
    invokespecial java/lang/IllegalStateException <init>:()V
    athrow
L167
    getstatic gp m:[[[I
    iload 0
    aaload
    iload 1
    aaload
    iload 2
    dup2
    iaload
    sipush 585
    ior
    iastore
    goto L166
L202
    new h
    dup
    iload 3
    iconst_1
    iload 4
    iload 0
    iload 1
    iload 2
    aload 9
    getfield ag p:I
    ldc -175609259 (java.lang.Integer)
    imul
    iconst_1
    aconst_null
    invokespecial h <init>:(IIIIIIIZLch;)V
    astore 22
    goto L104
L204
    aconst_null
    aload 9
    getfield ag ak:[I
    if_acmpne L205
    iload 8
    iconst_0
    if_icmpne L206
    new java/lang/IllegalStateException
    dup
    invokespecial java/lang/IllegalStateException <init>:()V
    athrow
L168
    aload 9
    getfield ag au:Z
    ifeq L76
    iload 8
    iconst_0
    if_icmpne L175
    return
L207
    iload 4
    iconst_2
    if_icmpne L208
    iload 8
    iconst_0
    if_icmpne L209
    new java/lang/IllegalStateException
    dup
    invokespecial java/lang/IllegalStateException <init>:()V
    athrow
L177
    getstatic w r:[[[B
    iload 0
    aaload
    iload 1
    aaload
    iload 2
    iconst_1
    iadd
    bipush 50
    bastore
    goto L76
L176
    iload 4
    iconst_1
    if_icmpne L207
    iload 8
    iconst_0
    if_icmpne L210
    new java/lang/IllegalStateException
    dup
    invokespecial java/lang/IllegalStateException <init>:()V
    athrow
L210
    getstatic w r:[[[B
    iload 0
    aaload
    iconst_1
    iload 1
    iadd
    aaload
    iload 2
    iconst_1
    iadd
    bipush 50
    bastore
    goto L76
L211
    ldc -175609259 (java.lang.Integer)
    aload 9
    getfield ag p:I
    imul
    iconst_m1
    if_icmpne L158
    goto L157
L209
    getstatic w r:[[[B
    iload 0
    aaload
    iload 1
    iconst_1
    iadd
    aaload
    iload 2
    bipush 50
    bastore
    goto L76
L212
    iload 4
    iconst_1
    if_icmpne L4
    iload 8
    iconst_0
    if_icmpne L197
    return
L158
    new h
    dup
    iload 3
    iconst_3
    iload 4
    iload 0
    iload 1
    iload 2
    aload 9
    getfield ag p:I
    ldc -175609259 (java.lang.Integer)
    imul
    iconst_1
    aconst_null
    invokespecial h <init>:(IIIIIIIZLch;)V
    astore 22
    goto L174
L76
    iconst_0
    ldc -1945821617 (java.lang.Integer)
    aload 9
    getfield ag q:I
    imul
    if_icmpeq L46
    iload 8
    iconst_0
    if_icmpne L127
    new java/lang/IllegalStateException
    dup
    invokespecial java/lang/IllegalStateException <init>:()V
    athrow
L181
    iload 4
    iconst_3
    if_icmpne L166
    iload 8
    iconst_0
    if_icmpne L190
    new java/lang/IllegalStateException
    dup
    invokespecial java/lang/IllegalStateException <init>:()V
    athrow
L183
    aload 9
    getfield ag v:Z
    ifeq L166
    goto L189
L213
    iload 5
    bipush 12
    if_icmplt L153
    iload 8
    iconst_0
    if_icmpne L140
    new java/lang/IllegalStateException
    dup
    invokespecial java/lang/IllegalStateException <init>:()V
    athrow
L102
    aconst_null
    aload 9
    getfield ag ak:[I
    if_acmpne L101
    iload 8
    iconst_0
    if_icmpne L105
    new java/lang/IllegalStateException
    dup
    invokespecial java/lang/IllegalStateException <init>:()V
    athrow
L109
    iload 4
    iconst_1
    iadd
    iconst_3
    iand
    istore 22
L214
    iconst_m1
    ldc -175609259 (java.lang.Integer)
    aload 9
    getfield ag p:I
    imul
    if_icmpne L215
    iload 8
    iconst_0
    if_icmpne L216
    new java/lang/IllegalStateException
    dup
    invokespecial java/lang/IllegalStateException <init>:()V
    athrow
L217
    aload 9
    iconst_4
    iload 4
    iconst_4
    iadd
    aload 16
    iload 18
    iload 17
    iload 19
    ldc 244091590 (java.lang.Integer)
    invokevirtual ag i:(II[[IIIII)Lch;
    astore 24
    goto L194
L218
    aload 9
    iconst_2
    iconst_4
    iload 4
    iadd
    aload 16
    iload 18
    iload 17
    iload 19
    ldc 1171195187 (java.lang.Integer)
    invokevirtual ag i:(II[[IIIII)Lch;
    astore 23
    goto L219
L84
    aload 22
    checkcast cy
    invokevirtual cy o:()I
    iconst_4
    idiv
    istore 23
    goto L122
L215
    new h
    dup
    iload 3
    iconst_2
    iload 4
    iconst_4
    iadd
    iload 0
    iload 1
    iload 2
    aload 9
    getfield ag p:I
    ldc -175609259 (java.lang.Integer)
    imul
    iconst_1
    aconst_null
    invokespecial h <init>:(IIIIIIIZLch;)V
    astore 23
    goto L43
L119
    iconst_1
    iload 1
    iadd
    istore 13
    goto L49
L44
    aload 6
    iload 0
    iload 1
    iload 2
    iload 17
    aload 23
    aload 24
    getstatic w q:[I
    iload 4
    iaload
    getstatic w q:[I
    iload 22
    iaload
    iload 20
    iload 21
    invokevirtual cb f:(IIIILch;Lch;IIII)V
L220
    aload 9
    getfield ag v:Z
    ifeq L66
    iload 8
    iconst_0
    if_icmpne L114
    new java/lang/IllegalStateException
    dup
    invokespecial java/lang/IllegalStateException <init>:()V
    athrow
L221
    bipush 8
    istore 22
    goto L222
L116
    getstatic gp m:[[[I
    iload 0
    aaload
    iload 1
    aaload
    iload 2
    dup2
    iaload
    sipush 585
    ior
    iastore
    goto L223
L219
    aload 9
    iconst_2
    iload 22
    aload 16
    iload 18
    iload 17
    iload 19
    ldc -596020688 (java.lang.Integer)
    invokevirtual ag i:(II[[IIIII)Lch;
    astore 24
    goto L44
L115
    iconst_1
    iload 4
    if_icmpne L224
    iload 8
    iconst_0
    if_icmpne L225
    return
L225
    getstatic gp m:[[[I
    iload 0
    aaload
    iload 1
    aaload
    iconst_1
    iload 2
    iadd
    dup2
    iaload
    sipush 1170
    ior
    iastore
L226
    getstatic gp m:[[[I
    iload 0
    aaload
    iload 1
    iconst_1
    iadd
    aaload
    iload 2
    dup2
    iaload
    sipush 585
    ior
    iastore
    goto L66
L224
    iload 4
    iconst_2
    if_icmpne L227
    iload 8
    iconst_0
    if_icmpne L228
    return
L228
    getstatic gp m:[[[I
    iload 0
    aaload
    iload 1
    iconst_1
    iadd
    aaload
    iload 2
    dup2
    iaload
    sipush 585
    ior
    iastore
    goto L229
L173
    getstatic w r:[[[B
    iload 0
    aaload
    iconst_1
    iload 1
    iadd
    aaload
    iconst_1
    iload 2
    iadd
    bipush 50
    bastore
    goto L171
L227
    iconst_3
    iload 4
    if_icmpne L66
    iload 8
    iconst_0
    if_icmpne L230
    new java/lang/IllegalStateException
    dup
    invokespecial java/lang/IllegalStateException <init>:()V
    athrow
L230
    getstatic gp m:[[[I
    iload 0
    aaload
    iload 1
    aaload
    iload 2
    dup2
    iaload
    sipush 1170
    ior
    iastore
L231
    getstatic gp m:[[[I
    iload 0
    aaload
    iload 1
    aaload
    iload 2
    dup2
    iaload
    sipush 585
    ior
    iastore
    goto L66
L74
    getstatic client h:Z
    ifeq L78
    iload 8
    iconst_0
    if_icmpne L77
    new java/lang/IllegalStateException
    dup
    invokespecial java/lang/IllegalStateException <init>:()V
    athrow
L68
    aconst_null
    aload 7
    if_acmpeq L67
    goto L232
L223
    getstatic gp m:[[[I
    iload 0
    aaload
    iload 1
    aaload
    iconst_1
    iload 2
    iadd
    dup2
    iaload
    sipush 1170
    ior
    iastore
    goto L66
L67
    bipush 16
    ldc 1127355445 (java.lang.Integer)
    aload 9
    getfield ag k:I
    imul
    if_icmpeq L233
    goto L234
L235
    bipush 15
    istore 23
    goto L82
L233
    return
L108
    iload 5
    iconst_3
    if_icmpne L236
    goto L211
L196
    iload 4
    iconst_3
    if_icmpne L41
    iload 8
    iconst_0
    if_icmpne L37
    new java/lang/IllegalStateException
    dup
    invokespecial java/lang/IllegalStateException <init>:()V
    athrow
L237
    iconst_0
    istore 9
    goto L14
L234
    aload 6
    iload 0
    iload 1
    iload 2
    aload 9
    getfield ag k:I
    ldc 1127355445 (java.lang.Integer)
    imul
    invokevirtual cb z:(IIII)V
    goto L233
L216
    aconst_null
    aload 9
    getfield ag ak:[I
    if_acmpne L215
    iload 8
    iconst_0
    if_icmpne L218
    new java/lang/IllegalStateException
    dup
    invokespecial java/lang/IllegalStateException <init>:()V
    athrow
L174
    aload 6
    iload 0
    iload 1
    iload 2
    iload 17
    aload 22
    aconst_null
    getstatic w d:[I
    iload 4
    iaload
    iconst_0
    iload 20
    iload 21
    invokevirtual cb f:(IIIILch;Lch;IIII)V
L238
    aload 9
    getfield ag au:Z
    ifeq L198
L239
    iconst_0
    iload 4
    if_icmpne L212
    iload 8
    iconst_0
    if_icmpne L240
    new java/lang/IllegalStateException
    dup
    invokespecial java/lang/IllegalStateException <init>:()V
    athrow
L240
    getstatic w r:[[[B
    iload 0
    aaload
    iload 1
    aaload
    iconst_1
    iload 2
    iadd
    bipush 50
    bastore
    goto L198
L8
    getstatic w a:[[[B
    iload 0
    aaload
    iload 1
    aaload
    iload 2
    baload
    bipush 8
    iand
    ifeq L15
    iload 8
    iconst_0
    if_icmpne L237
    new java/lang/IllegalStateException
    dup
    invokespecial java/lang/IllegalStateException <init>:()V
    athrow
L113
    iload 20
    iload 21
    invokevirtual cb o:(IIIIIILch;III)Z
    ifeq L125
    iload 8
    iconst_0
    if_icmpne L241
    new java/lang/IllegalStateException
    dup
    invokespecial java/lang/IllegalStateException <init>:()V
    athrow
L31
    return
L6
    getstatic w r:[[[B
    iload 0
    aaload
    iconst_1
    iload 1
    iadd
    aaload
    iload 2
    bipush 50
    bastore
    goto L198
L5
    iconst_3
    iload 4
    if_icmpne L198
    iload 8
    iconst_0
    if_icmpne L242
    new java/lang/IllegalStateException
    dup
    invokespecial java/lang/IllegalStateException <init>:()V
    athrow
L242
    getstatic w r:[[[B
    iload 0
    aaload
    iload 1
    aaload
    iload 2
    bipush 50
    bastore
L198
    ldc -1945821617 (java.lang.Integer)
    aload 9
    getfield ag q:I
    imul
    ifeq L243
    iload 8
    iconst_0
    if_icmpne L244
    new java/lang/IllegalStateException
    dup
    invokespecial java/lang/IllegalStateException <init>:()V
    athrow
L244
    aload 7
    ifnull L243
    iload 8
    iconst_0
    if_icmpne L245
    return
L245
    aload 7
    iload 1
    iload 2
    iload 5
    iload 4
    aload 9
    getfield ag d:Z
    ldc -1325841075 (java.lang.Integer)
    invokevirtual hk a:(IIIIZI)V
L243
    return
L236
    bipush 9
    iload 5
    if_icmpne L137
    iload 8
    iconst_0
    if_icmpne L178
    return
L246
    getstatic gp m:[[[I
    iload 0
    aaload
    iload 1
    aaload
    iload 2
    dup2
    iaload
    sipush 2340
    ior
    iastore
    goto L88
L180
    aconst_null
    aload 9
    getfield ag ak:[I
    if_acmpne L179
    iload 8
    iconst_0
    if_icmpne L247
    return
L247
    aload 9
    iload 5
    iload 4
    aload 16
    iload 18
    iload 17
    iload 19
    ldc 1259343052 (java.lang.Integer)
    invokevirtual ag i:(II[[IIIII)Lch;
    astore 22
    goto L248
L179
    new h
    dup
    iload 3
    iload 5
    iload 4
    iload 0
    iload 1
    iload 2
    aload 9
    getfield ag p:I
    ldc -175609259 (java.lang.Integer)
    imul
    iconst_1
    aconst_null
    invokespecial h <init>:(IIIIIIIZLch;)V
    astore 22
L248
    aload 6
    iload 0
    iload 1
    iload 2
    iload 17
    iconst_1
    iconst_1
    aload 22
    iconst_0
    iload 20
    iload 21
    invokevirtual cb o:(IIIIIILch;III)Z
    pop
L249
    iconst_0
    ldc -1945821617 (java.lang.Integer)
    aload 9
    getfield ag q:I
    imul
    if_icmpeq L121
    iload 8
    iconst_0
    if_icmpne L250
    return
L250
    aload 7
    ifnull L121
    iload 8
    iconst_0
    if_icmpne L120
    new java/lang/IllegalStateException
    dup
    invokespecial java/lang/IllegalStateException <init>:()V
    athrow
L141
    bipush 6
    iload 5
    if_icmpne L251
    iload 8
    iconst_0
    if_icmpne L221
    new java/lang/IllegalStateException
    dup
    invokespecial java/lang/IllegalStateException <init>:()V
    athrow
L121
    bipush 16
    aload 9
    getfield ag k:I
    ldc 1127355445 (java.lang.Integer)
    imul
    if_icmpeq L252
    iload 8
    iconst_0
    if_icmpne L253
    new java/lang/IllegalStateException
    dup
    invokespecial java/lang/IllegalStateException <init>:()V
    athrow
L253
    aload 6
    iload 0
    iload 1
    iload 2
    ldc 1127355445 (java.lang.Integer)
    aload 9
    getfield ag k:I
    imul
    invokevirtual cb z:(IIII)V
L252
    return
L208
    iload 4
    iconst_3
    if_icmpne L76
    iload 8
    iconst_0
    if_icmpne L75
    new java/lang/IllegalStateException
    dup
    invokespecial java/lang/IllegalStateException <init>:()V
    athrow
L139
    ldc -175609259 (java.lang.Integer)
    aload 9
    getfield ag p:I
    imul
    iconst_m1
    if_icmpne L205
    goto L204
L3
    getstatic w a:[[[B
    iconst_0
    aaload
    iload 1
    aaload
    iload 2
    baload
    iconst_2
    iand
    ifne L2
    iload 8
    iconst_0
    if_icmpne L7
    new java/lang/IllegalStateException
    dup
    invokespecial java/lang/IllegalStateException <init>:()V
    athrow
L206
    aload 9
    iconst_4
    iload 4
    aload 16
    iload 18
    iload 17
    iload 19
    ldc -248609300 (java.lang.Integer)
    invokevirtual ag i:(II[[IIIII)Lch;
    astore 22
    goto L117
L205
    new h
    dup
    iload 3
    iconst_4
    iload 4
    iload 0
    iload 1
    iload 2
    aload 9
    getfield ag p:I
    ldc -175609259 (java.lang.Integer)
    imul
    iconst_1
    aconst_null
    invokespecial h <init>:(IIIIIIIZLch;)V
    astore 22
    goto L117
L81
    aload 16
    iload 13
    aaload
    iload 14
    iaload
    aload 16
    iload 12
    aaload
    iload 14
    iaload
    iadd
    aload 16
    iload 12
    aaload
    iload 15
    iaload
    iadd
    aload 16
    iload 13
    aaload
    iload 15
    iaload
    iadd
    iconst_2
    ishr
    istore 17
    goto L61
L118
    return
L126
    iconst_0
    istore 25
    goto L129
L229
    getstatic gp m:[[[I
    iload 0
    aaload
    iload 1
    aaload
    iload 2
    dup2
    iaload
    sipush 1170
    ior
    iastore
    goto L66
L149
    aload 6
    iload 0
    iload 1
    iload 2
    invokevirtual cb ax:(III)I
    istore 23
    goto L50
L131
    return
L52
    iload 23
    bipush 14
    ishr
    sipush 32767
    iand
    iconst_4
    invokestatic m e:(IB)Lag;
    getfield ag k:I
    ldc 1127355445 (java.lang.Integer)
    imul
    istore 22
L51
    iconst_m1
    ldc -175609259 (java.lang.Integer)
    aload 9
    getfield ag p:I
    imul
    if_icmpne L254
    iload 8
    iconst_0
    if_icmpne L255
    return
L255
    aload 9
    getfield ag ak:[I
    ifnonnull L254
    iload 8
    iconst_0
    if_icmpne L33
    return
L29
    ldc -752331779 (java.lang.Integer)
    iload 0
    imul
    putstatic w l:I
    goto L28
L254
    new h
    dup
    iload 3
    iconst_4
    iload 4
    iload 0
    iload 1
    iload 2
    ldc -175609259 (java.lang.Integer)
    aload 9
    getfield ag p:I
    imul
    iconst_1
    aconst_null
    invokespecial h <init>:(IIIIIIIZLch;)V
    astore 24
    goto L30
L129
    iload 25
    iload 11
    if_icmpgt L130
    iload 8
    iconst_0
    if_icmpne L20
    new java/lang/IllegalStateException
    dup
    invokespecial java/lang/IllegalStateException <init>:()V
    athrow
L171
    aload 9
    getfield ag v:Z
    ifeq L166
    iload 8
    iconst_0
    if_icmpne L256
    new java/lang/IllegalStateException
    dup
    invokespecial java/lang/IllegalStateException <init>:()V
    athrow
L145
    aload 6
    iload 0
    iload 1
    iload 2
    iload 17
    aload 22
    aconst_null
    getstatic w q:[I
    iload 4
    iaload
    iconst_0
    iload 20
    iload 21
    invokevirtual cb f:(IIIILch;Lch;IIII)V
    goto L160
L256
    getstatic gp m:[[[I
    iload 0
    aaload
    iload 1
    aaload
    iconst_1
    iload 2
    iadd
    dup2
    iaload
    sipush 1170
    ior
    iastore
    goto L166
L222
    aload 6
    iload 0
    iload 1
    iload 2
    invokevirtual cb ax:(III)I
    istore 23
L257
    iconst_0
    iload 23
    if_icmpeq L258
    iload 8
    iconst_0
    if_icmpne L259
    new java/lang/IllegalStateException
    dup
    invokespecial java/lang/IllegalStateException <init>:()V
    athrow
L259
    iload 23
    bipush 14
    ishr
    sipush 32767
    iand
    bipush -9
    invokestatic m e:(IB)Lag;
    getfield ag k:I
    ldc 1127355445 (java.lang.Integer)
    imul
    iconst_2
    idiv
    istore 22
L258
    ldc -175609259 (java.lang.Integer)
    aload 9
    getfield ag p:I
    imul
    iconst_m1
    if_icmpne L260
    iload 8
    iconst_0
    if_icmpne L261
    new java/lang/IllegalStateException
    dup
    invokespecial java/lang/IllegalStateException <init>:()V
    athrow
L261
    aload 9
    getfield ag ak:[I
    ifnonnull L260
    iload 8
    iconst_0
    if_icmpne L262
    new java/lang/IllegalStateException
    dup
    invokespecial java/lang/IllegalStateException <init>:()V
    athrow
L262
    aload 9
    iconst_4
    iconst_4
    iload 4
    iadd
    aload 16
    iload 18
    iload 17
    iload 19
    ldc -1446620183 (java.lang.Integer)
    invokevirtual ag i:(II[[IIIII)Lch;
    astore 24
    goto L96
L260
    new h
    dup
    iload 3
    iconst_4
    iconst_4
    iload 4
    iadd
    iload 0
    iload 1
    iload 2
    aload 9
    getfield ag p:I
    ldc -175609259 (java.lang.Integer)
    imul
    iconst_1
    aconst_null
    invokespecial h <init>:(IIIIIIIZLch;)V
    astore 24
    goto L96
L200
    aload 6
    iload 0
    iload 1
    iload 2
    ldc 1127355445 (java.lang.Integer)
    aload 9
    getfield ag k:I
    imul
    invokevirtual cb z:(IIII)V
    goto L199
L97
    return
L251
    iload 5
    bipush 7
    if_icmpne L134
    iload 8
    iconst_0
    if_icmpne L263
    new java/lang/IllegalStateException
    dup
    invokespecial java/lang/IllegalStateException <init>:()V
    athrow
L263
    iload 4
    iconst_2
    iadd
    iconst_3
    iand
    istore 23
L264
    aload 9
    getfield ag p:I
    ldc -175609259 (java.lang.Integer)
    imul
    iconst_m1
    if_icmpne L187
    iload 8
    iconst_0
    if_icmpne L186
    return
L241
    aload 9
    getfield ag au:Z
    ifeq L125
    iload 8
    iconst_0
    if_icmpne L235
    new java/lang/IllegalStateException
    dup
    invokespecial java/lang/IllegalStateException <init>:()V
    athrow
L188
    aload 9
    iconst_4
    iload 23
    iconst_4
    iadd
    aload 16
    iload 18
    iload 17
    iload 19
    ldc 1620435438 (java.lang.Integer)
    invokevirtual ag i:(II[[IIIII)Lch;
    astore 22
    goto L265
L193
    getstatic w r:[[[B
    iload 0
    aaload
    iload 1
    iconst_1
    iadd
    aaload
    iload 2
    bipush 50
    bastore
    goto L191
L265
    aload 6
    iload 0
    iload 1
    iload 2
    iload 17
    aload 22
    aconst_null
    sipush 256
    iload 23
    iconst_0
    iconst_0
    iload 20
    iload 21
    invokevirtual cb g:(IIIILch;Lch;IIIIII)V
    goto L266
L232
    aload 7
    iload 1
    iload 2
    iload 5
    iload 4
    aload 9
    getfield ag d:Z
    ldc -1799396600 (java.lang.Integer)
    invokevirtual hk a:(IIIIZI)V
    goto L67
L266
    return
L136
    bipush 8
    istore 22
    goto L10
L195
    getstatic gp m:[[[I
    iload 0
    aaload
    iload 1
    aaload
    iload 2
    dup2
    iaload
    sipush 1170
    ior
    iastore
    goto L166
L11
    iload 23
    ifeq L267
    iload 8
    iconst_0
    if_icmpne L268
    new java/lang/IllegalStateException
    dup
    invokespecial java/lang/IllegalStateException <init>:()V
    athrow
L268
    iload 23
    bipush 14
    ishr
    sipush 32767
    iand
    bipush -9
    invokestatic m e:(IB)Lag;
    getfield ag k:I
    ldc 1127355445 (java.lang.Integer)
    imul
    iconst_2
    idiv
    istore 22
L267
    iconst_2
    iload 4
    iadd
    iconst_3
    iand
    istore 26
    goto L92
L99
    iload 5
    bipush 11
    if_icmpne L213
    iload 8
    iconst_0
    if_icmpne L98
    new java/lang/IllegalStateException
    dup
    invokespecial java/lang/IllegalStateException <init>:()V
    athrow
L94
    aload 9
    getfield ag ak:[I
    ifnonnull L93
    iload 8
    iconst_0
    if_icmpne L217
    new java/lang/IllegalStateException
    dup
    invokespecial java/lang/IllegalStateException <init>:()V
    athrow
L199
    return
L106
    aconst_null
    aload 22
    if_acmpeq L125
    goto L110
L93
    new h
    dup
    iload 3
    iconst_4
    iload 4
    iconst_4
    iadd
    iload 0
    iload 1
    iload 2
    aload 9
    getfield ag p:I
    ldc -175609259 (java.lang.Integer)
    imul
    iconst_1
    aconst_null
    invokespecial h <init>:(IIIIIIIZLch;)V
    astore 24
    goto L47
L187
    new h
    dup
    iload 3
    iconst_4
    iconst_4
    iload 23
    iadd
    iload 0
    iload 1
    iload 2
    aload 9
    getfield ag p:I
    ldc -175609259 (java.lang.Integer)
    imul
    iconst_1
    aconst_null
    invokespecial h <init>:(IIIIIIIZLch;)V
    astore 22
    goto L265
L48
    aload 6
    iload 0
    iload 1
    iload 2
    iload 17
    aload 24
    aload 25
    sipush 256
    iload 4
    iload 22
    getstatic w n:[I
    iload 4
    iaload
    imul
    getstatic w v:[I
    iload 4
    iaload
    iload 22
    imul
    iload 20
    iload 21
    invokevirtual cb g:(IIIILch;Lch;IIIIII)V
L269
    return
L148
    iload 0
    ifle L88
    iload 8
    iconst_0
    if_icmpne L246
    new java/lang/IllegalStateException
    dup
    invokespecial java/lang/IllegalStateException <init>:()V
    athrow
L270
    new java/lang/StringBuilder
    dup
    invokespecial java/lang/StringBuilder <init>:()V
    ldc "ac.r(" (java.lang.String)
    invokevirtual java/lang/StringBuilder append:(Ljava/lang/String;)Ljava/lang/StringBuilder;
    ldc 41 (java.lang.Integer)
    invokevirtual java/lang/StringBuilder append:(C)Ljava/lang/StringBuilder;
    invokevirtual java/lang/StringBuilder toString:()Ljava/lang/String;
    invokestatic k a:(Ljava/lang/Throwable;Ljava/lang/String;)Lee;
    athrow
