ad c (Ldh;IB)VL1
    iconst_1
    iload 2
    if_icmpne L2
    iload 3
    iconst_0
    if_icmpgt L3
    return
L4
    aload 0
    iconst_1
    putfield ad ax:Z
    goto L5
L2
    iconst_2
    iload 2
    if_icmpne L6
    iload 3
    iconst_0
    if_icmpgt L7
    new java/lang/IllegalStateException
    dup
    invokespecial java/lang/IllegalStateException <init>:()V
    athrow
L8
    aload 1
    ldc 1829150868 (java.lang.Integer)
    invokevirtual dh z:(I)I
    istore 4
    goto L9
L6
    iload 2
    iconst_4
    if_icmpne L10
    iload 3
    iconst_0
    if_icmpgt L11
    new java/lang/IllegalStateException
    dup
    invokespecial java/lang/IllegalStateException <init>:()V
    athrow
L11
    aload 0
    aload 1
    ldc 777793404 (java.lang.Integer)
    invokevirtual dh q:(I)I
    ldc -1258217075 (java.lang.Integer)
    imul
    putfield ad q:I
    goto L5
L10
    iconst_5
    iload 2
    if_icmpne L12
    iload 3
    iconst_0
    if_icmpgt L13
    new java/lang/IllegalStateException
    dup
    invokespecial java/lang/IllegalStateException <init>:()V
    athrow
L13
    aload 0
    aload 1
    ldc 1515890852 (java.lang.Integer)
    invokevirtual dh q:(I)I
    ldc -155396295 (java.lang.Integer)
    imul
    putfield ad d:I
    goto L5
L14
    aload 0
    aload 1
    ldc -1384014780 (java.lang.Integer)
    invokevirtual dh q:(I)I
    ldc 253573543 (java.lang.Integer)
    imul
    putfield ad ai:I
    goto L15
L16
    aload 0
    aload 1
    ldc 981609823 (java.lang.Integer)
    invokevirtual dh q:(I)I
    ldc -1554328225 (java.lang.Integer)
    imul
    putfield ad ar:I
    goto L5
L17
    bipush 7
    iload 2
    if_icmpne L18
    iload 3
    iconst_0
    if_icmpgt L19
    return
L19
    aload 0
    aload 1
    ldc 1380058353 (java.lang.Integer)
    invokevirtual dh q:(I)I
    ldc 1243058105 (java.lang.Integer)
    imul
    putfield ad n:I
L20
    aload 0
    getfield ad n:I
    ldc -510409079 (java.lang.Integer)
    imul
    sipush 32767
    if_icmple L5
    iload 3
    iconst_0
    if_icmpgt L21
    return
L21
    aload 0
    dup
    getfield ad n:I
    ldc -1883701248 (java.lang.Integer)
    isub
    putfield ad n:I
    goto L5
L22
    aload 0
    aload 1
    ldc 856951332 (java.lang.Integer)
    invokevirtual dh q:(I)I
    ldc 1891574871 (java.lang.Integer)
    imul
    putfield ad aw:I
    goto L5
L23
    aload 0
    aload 1
    ldc 1754418236 (java.lang.Integer)
    invokevirtual dh q:(I)I
    ldc -677069623 (java.lang.Integer)
    imul
    putfield ad v:I
    goto L24
L5
    return
L25
    iload 2
    bipush 35
    if_icmplt L26
    iload 3
    iconst_0
    if_icmpgt L27
    new java/lang/IllegalStateException
    dup
    invokespecial java/lang/IllegalStateException <init>:()V
    athrow
L28
    iload 2
    bipush 11
    if_icmpne L29
    iload 3
    iconst_0
    if_icmpgt L30
    return
L30
    aload 0
    ldc 1560203389 (java.lang.Integer)
    putfield ad p:I
    goto L5
L31
    aload 0
    aload 1
    bipush 118
    invokevirtual dh y:(B)B
    ldc -181009005 (java.lang.Integer)
    imul
    putfield ad az:I
    goto L5
L32
    aload 0
    aload 1
    ldc -2120934312 (java.lang.Integer)
    invokevirtual dh x:(I)I
    ldc -449000595 (java.lang.Integer)
    imul
    putfield ad k:I
    goto L5
L33
    bipush 112
    iload 2
    if_icmpne L34
    iload 3
    iconst_0
    if_icmpgt L35
    new java/lang/IllegalStateException
    dup
    invokespecial java/lang/IllegalStateException <init>:()V
    athrow
L36
    iload 2
    bipush 114
    if_icmpne L37
    iload 3
    iconst_0
    if_icmpgt L38
    new java/lang/IllegalStateException
    dup
    invokespecial java/lang/IllegalStateException <init>:()V
    athrow
L39
    bipush 23
    iload 2
    if_icmpne L40
    iload 3
    iconst_0
    if_icmpgt L14
    new java/lang/IllegalStateException
    dup
    invokespecial java/lang/IllegalStateException <init>:()V
    athrow
L41
    aload 0
    aload 1
    ldc 1213732529 (java.lang.Integer)
    invokevirtual dh z:(I)I
    ldc 1133869131 (java.lang.Integer)
    imul
    putfield ad as:I
    goto L5
L42
    aload 0
    aload 1
    ldc 1615611181 (java.lang.Integer)
    invokevirtual dh z:(I)I
    ldc -1034077141 (java.lang.Integer)
    imul
    putfield ad ab:I
    goto L5
L7
    aload 0
    aload 1
    ldc -1925996699 (java.lang.Integer)
    invokevirtual dh p:(I)Ljava/lang/String;
    putfield ad j:Ljava/lang/String;
    goto L5
L24
    aload 0
    getfield ad v:I
    ldc -1145037447 (java.lang.Integer)
    imul
    sipush 32767
    if_icmple L5
    goto L43
L44
    bipush 25
    iload 2
    if_icmpne L45
    iload 3
    iconst_0
    if_icmpgt L46
    new java/lang/IllegalStateException
    dup
    invokespecial java/lang/IllegalStateException <init>:()V
    athrow
L46
    aload 0
    aload 1
    ldc -1347748512 (java.lang.Integer)
    invokevirtual dh q:(I)I
    ldc -1128721917 (java.lang.Integer)
    imul
    putfield ad au:I
    goto L42
L3
    aload 0
    aload 1
    ldc 1750641359 (java.lang.Integer)
    invokevirtual dh q:(I)I
    ldc -1380360863 (java.lang.Integer)
    imul
    putfield ad s:I
    goto L5
L45
    bipush 26
    iload 2
    if_icmpne L47
    iload 3
    iconst_0
    if_icmpgt L48
    new java/lang/IllegalStateException
    dup
    invokespecial java/lang/IllegalStateException <init>:()V
    athrow
L48
    aload 0
    aload 1
    ldc -1101212461 (java.lang.Integer)
    invokevirtual dh q:(I)I
    ldc 1875992899 (java.lang.Integer)
    imul
    putfield ad ae:I
    goto L5
L29
    bipush 12
    iload 2
    if_icmpne L49
    iload 3
    iconst_0
    if_icmpgt L32
    new java/lang/IllegalStateException
    dup
    invokespecial java/lang/IllegalStateException <init>:()V
    athrow
L50
    aload 0
    getfield ad z:[S
    iload 5
    aload 1
    ldc -825709683 (java.lang.Integer)
    invokevirtual dh q:(I)I
    i2s
    sastore
    goto L51
L52
    aload 0
    getfield ad ap:[Ljava/lang/String;
    iload 2
    bipush 30
    isub
    aload 1
    ldc -970849503 (java.lang.Integer)
    invokevirtual dh p:(I)Ljava/lang/String;
    aastore
    goto L53
L54
    bipush 90
    iload 2
    if_icmpne L55
    iload 3
    iconst_0
    if_icmpgt L56
    return
L57
    aload 0
    getfield ad ap:[Ljava/lang/String;
    iload 2
    bipush 30
    isub
    aconst_null
    aastore
    goto L5
L58
    aload 0
    aload 1
    ldc 1170160980 (java.lang.Integer)
    invokevirtual dh q:(I)I
    ldc -1244495369 (java.lang.Integer)
    imul
    putfield ad av:I
    goto L5
L27
    iload 2
    bipush 40
    if_icmpge L26
    iload 3
    iconst_0
    if_icmpgt L59
    return
L59
    aload 0
    getfield ad ao:[Ljava/lang/String;
    iload 2
    bipush 35
    isub
    aload 1
    ldc 596475835 (java.lang.Integer)
    invokevirtual dh p:(I)Ljava/lang/String;
    aastore
    goto L5
L26
    bipush 40
    iload 2
    if_icmpne L60
    iload 3
    iconst_0
    if_icmpgt L8
    new java/lang/IllegalStateException
    dup
    invokespecial java/lang/IllegalStateException <init>:()V
    athrow
L47
    iload 2
    bipush 30
    if_icmplt L25
    iload 3
    iconst_0
    if_icmpgt L61
    return
L9
    aload 0
    iload 4
    newarray 9
    putfield ad m:[S
    goto L62
L63
    aload 0
    aload 1
    ldc 1035916640 (java.lang.Integer)
    invokevirtual dh q:(I)I
    ldc 1497178931 (java.lang.Integer)
    imul
    putfield ad ac:I
    goto L5
L64
    aload 0
    iconst_1
    putfield ad aa:Z
    goto L5
L65
    iload 5
    iload 4
    if_icmpge L66
    iload 3
    iconst_0
    if_icmpgt L67
    new java/lang/IllegalStateException
    dup
    invokespecial java/lang/IllegalStateException <init>:()V
    athrow
L68
    iload 2
    bipush 97
    if_icmpne L69
    iload 3
    iconst_0
    if_icmpgt L16
    new java/lang/IllegalStateException
    dup
    invokespecial java/lang/IllegalStateException <init>:()V
    athrow
L70
    aload 0
    getfield ad t:[S
    iload 5
    aload 1
    ldc -815170721 (java.lang.Integer)
    invokevirtual dh q:(I)I
    i2s
    sastore
    goto L71
L53
    aload 0
    getfield ad ap:[Ljava/lang/String;
    iload 2
    bipush 30
    isub
    aaload
    getstatic et c:Ljava/lang/String;
    invokevirtual java/lang/String equalsIgnoreCase:(Ljava/lang/String;)Z
    ifeq L5
    goto L57
L66
    goto L5
L72
    aload 0
    aload 1
    ldc -2059774863 (java.lang.Integer)
    invokevirtual dh q:(I)I
    ldc 1418451025 (java.lang.Integer)
    imul
    putfield ad b:I
    goto L5
L73
    aload 1
    ldc 1259125265 (java.lang.Integer)
    invokevirtual dh z:(I)I
    istore 4
L74
    aload 0
    iload 4
    newarray 9
    putfield ad z:[S
L75
    aload 0
    iload 4
    newarray 9
    putfield ad y:[S
L76
    iconst_0
    istore 5
    goto L77
L78
    aload 0
    bipush 10
    newarray 10
    putfield ad al:[I
    goto L79
L43
    aload 0
    dup
    getfield ad v:I
    ldc -1127677952 (java.lang.Integer)
    isub
    putfield ad v:I
    goto L5
L51
    aload 0
    getfield ad y:[S
    iload 5
    aload 1
    ldc 983354213 (java.lang.Integer)
    invokevirtual dh q:(I)I
    i2s
    sastore
    goto L80
L81
    aload 0
    aload 1
    ldc -9526744 (java.lang.Integer)
    invokevirtual dh q:(I)I
    ldc -673524353 (java.lang.Integer)
    imul
    putfield ad ah:I
    goto L5
L82
    goto L5
L83
    iload 2
    bipush 65
    if_icmpne L84
    iload 3
    iconst_0
    if_icmpgt L64
    new java/lang/IllegalStateException
    dup
    invokespecial java/lang/IllegalStateException <init>:()V
    athrow
L71
    iinc 5 1
    goto L65
L85
    iload 2
    sipush 139
    if_icmpne L86
    goto L87
L67
    aload 0
    getfield ad m:[S
    iload 5
    aload 1
    ldc 1766372310 (java.lang.Integer)
    invokevirtual dh q:(I)I
    i2s
    sastore
    goto L70
L88
    iload 2
    bipush 79
    if_icmpne L54
    iload 3
    iconst_0
    if_icmpgt L89
    return
L89
    aload 0
    aload 1
    ldc 1757239311 (java.lang.Integer)
    invokevirtual dh q:(I)I
    ldc -1047668921 (java.lang.Integer)
    imul
    putfield ad ay:I
    goto L5
L90
    aload 0
    aload 1
    ldc 1507504430 (java.lang.Integer)
    invokevirtual dh q:(I)I
    ldc 661504209 (java.lang.Integer)
    imul
    putfield ad at:I
    goto L5
L84
    bipush 78
    iload 2
    if_icmpne L88
    goto L58
L55
    iload 2
    bipush 91
    if_icmpne L91
    iload 3
    iconst_0
    if_icmpgt L81
    return
L56
    aload 0
    aload 1
    ldc 12874871 (java.lang.Integer)
    invokevirtual dh q:(I)I
    ldc 176328601 (java.lang.Integer)
    imul
    putfield ad ag:I
    goto L5
L91
    iload 2
    bipush 92
    if_icmpne L92
    aload 0
    aload 1
    ldc 448142662 (java.lang.Integer)
    invokevirtual dh q:(I)I
    ldc 534497361 (java.lang.Integer)
    imul
    putfield ad aj:I
    goto L5
L92
    bipush 93
    iload 2
    if_icmpne L93
    iload 3
    iconst_0
    if_icmpgt L90
    new java/lang/IllegalStateException
    dup
    invokespecial java/lang/IllegalStateException <init>:()V
    athrow
L12
    bipush 6
    iload 2
    if_icmpne L17
    iload 3
    iconst_0
    if_icmpgt L72
    new java/lang/IllegalStateException
    dup
    invokespecial java/lang/IllegalStateException <init>:()V
    athrow
L93
    bipush 95
    iload 2
    if_icmpne L68
    iload 3
    iconst_0
    if_icmpgt L94
    new java/lang/IllegalStateException
    dup
    invokespecial java/lang/IllegalStateException <init>:()V
    athrow
L94
    aload 0
    aload 1
    ldc 1514286255 (java.lang.Integer)
    invokevirtual dh q:(I)I
    ldc -1318122521 (java.lang.Integer)
    imul
    putfield ad x:I
    goto L5
L77
    iload 5
    iload 4
    if_icmpge L82
    iload 3
    iconst_0
    if_icmpgt L50
    return
L15
    aload 0
    aload 1
    ldc 1385664945 (java.lang.Integer)
    invokevirtual dh z:(I)I
    ldc 1151955687 (java.lang.Integer)
    imul
    putfield ad am:I
    goto L5
L69
    bipush 98
    iload 2
    if_icmpne L95
    aload 0
    aload 1
    ldc 1195774148 (java.lang.Integer)
    invokevirtual dh q:(I)I
    ldc 611227417 (java.lang.Integer)
    imul
    putfield ad aq:I
    goto L5
L95
    iload 2
    bipush 100
    if_icmplt L96
    iload 3
    iconst_0
    if_icmpgt L97
    new java/lang/IllegalStateException
    dup
    invokespecial java/lang/IllegalStateException <init>:()V
    athrow
L97
    iload 2
    bipush 110
    if_icmpge L96
    iload 3
    iconst_0
    if_icmpgt L98
    new java/lang/IllegalStateException
    dup
    invokespecial java/lang/IllegalStateException <init>:()V
    athrow
L98
    aconst_null
    aload 0
    getfield ad al:[I
    if_acmpne L99
    iload 3
    iconst_0
    if_icmpgt L78
    new java/lang/IllegalStateException
    dup
    invokespecial java/lang/IllegalStateException <init>:()V
    athrow
L60
    iload 2
    bipush 41
    if_icmpne L83
    iload 3
    iconst_0
    if_icmpgt L73
    return
L79
    aload 0
    bipush 10
    newarray 10
    putfield ad ak:[I
L99
    aload 0
    getfield ad al:[I
    iload 2
    bipush 100
    isub
    aload 1
    ldc -1099298100 (java.lang.Integer)
    invokevirtual dh q:(I)I
    iastore
L100
    aload 0
    getfield ad ak:[I
    iload 2
    bipush 100
    isub
    aload 1
    ldc -1110934954 (java.lang.Integer)
    invokevirtual dh q:(I)I
    iastore
    goto L5
L96
    iload 2
    bipush 110
    if_icmpne L101
    iload 3
    iconst_0
    if_icmpgt L63
    new java/lang/IllegalStateException
    dup
    invokespecial java/lang/IllegalStateException <init>:()V
    athrow
L80
    iinc 5 1
    goto L77
L101
    iload 2
    bipush 111
    if_icmpne L33
    iload 3
    iconst_0
    if_icmpgt L102
    new java/lang/IllegalStateException
    dup
    invokespecial java/lang/IllegalStateException <init>:()V
    athrow
L102
    aload 0
    aload 1
    ldc -149147784 (java.lang.Integer)
    invokevirtual dh q:(I)I
    ldc 332553927 (java.lang.Integer)
    imul
    putfield ad ad:I
    goto L5
L103
    aload 0
    aload 1
    ldc -511965040 (java.lang.Integer)
    invokevirtual dh q:(I)I
    ldc -909077479 (java.lang.Integer)
    imul
    putfield ad bk:I
    goto L5
L35
    aload 0
    aload 1
    ldc -1665749503 (java.lang.Integer)
    invokevirtual dh q:(I)I
    ldc -1346135193 (java.lang.Integer)
    imul
    putfield ad an:I
    goto L5
L34
    bipush 113
    iload 2
    if_icmpne L36
    goto L31
L49
    iload 2
    bipush 16
    if_icmpne L39
    iload 3
    iconst_0
    if_icmpgt L4
    new java/lang/IllegalStateException
    dup
    invokespecial java/lang/IllegalStateException <init>:()V
    athrow
L104
    iconst_0
    istore 5
    goto L65
L38
    aload 0
    aload 1
    bipush 75
    invokevirtual dh y:(B)B
    ldc 1472705505 (java.lang.Integer)
    imul
    putfield ad af:I
    goto L5
L37
    bipush 115
    iload 2
    if_icmpne L85
    iload 3
    iconst_0
    if_icmpgt L41
    new java/lang/IllegalStateException
    dup
    invokespecial java/lang/IllegalStateException <init>:()V
    athrow
L40
    iload 2
    bipush 24
    if_icmpne L44
    iload 3
    iconst_0
    if_icmpgt L22
    new java/lang/IllegalStateException
    dup
    invokespecial java/lang/IllegalStateException <init>:()V
    athrow
L18
    iload 2
    bipush 8
    if_icmpne L28
    goto L23
L87
    aload 0
    aload 1
    ldc 840136475 (java.lang.Integer)
    invokevirtual dh q:(I)I
    ldc -280820947 (java.lang.Integer)
    imul
    putfield ad bl:I
    goto L5
L86
    iload 2
    sipush 140
    if_icmpne L5
    iload 3
    iconst_0
    if_icmpgt L103
    new java/lang/IllegalStateException
    dup
    invokespecial java/lang/IllegalStateException <init>:()V
    athrow
L62
    aload 0
    iload 4
    newarray 9
    putfield ad t:[S
    goto L104
L61
    iload 2
    bipush 35
    if_icmpge L25
    iload 3
    iconst_0
    if_icmpgt L52
    return
L105
    new java/lang/StringBuilder
    dup
    invokespecial java/lang/StringBuilder <init>:()V
    ldc "ad.c(" (java.lang.String)
    invokevirtual java/lang/StringBuilder append:(Ljava/lang/String;)Ljava/lang/StringBuilder;
    ldc 41 (java.lang.Integer)
    invokevirtual java/lang/StringBuilder append:(C)Ljava/lang/StringBuilder;
    invokevirtual java/lang/StringBuilder toString:()Ljava/lang/String;
    invokestatic k a:(Ljava/lang/Throwable;Ljava/lang/String;)Lee;
    athrow
