ad f (II)Lad;L1
    aconst_null
    aload 0
    getfield ad al:[I
    if_acmpeq L2
    iload 2
    ldc -100126598 (java.lang.Integer)
    if_icmpeq L3
    new java/lang/IllegalStateException
    dup
    invokespecial java/lang/IllegalStateException <init>:()V
    athrow
L4
    iconst_m1
    istore 3
    goto L5
L6
    iload 4
    bipush 10
    if_icmpge L7
    iload 2
    ldc -100126598 (java.lang.Integer)
    if_icmpeq L8
    new java/lang/IllegalStateException
    dup
    invokespecial java/lang/IllegalStateException <init>:()V
    athrow
L5
    iconst_0
    istore 4
    goto L6
L3
    iload 1
    iconst_1
    if_icmple L2
    iload 2
    ldc -100126598 (java.lang.Integer)
    if_icmpeq L4
    new java/lang/IllegalStateException
    dup
    invokespecial java/lang/IllegalStateException <init>:()V
    athrow
L7
    iconst_m1
    iload 3
    if_icmpeq L2
    goto L9
L10
    aload 0
    getfield ad ak:[I
    iload 4
    iaload
    ifeq L11
    iload 2
    ldc -100126598 (java.lang.Integer)
    if_icmpeq L12
    new java/lang/IllegalStateException
    dup
    invokespecial java/lang/IllegalStateException <init>:()V
    athrow
L8
    iload 1
    aload 0
    getfield ad ak:[I
    iload 4
    iaload
    if_icmplt L11
    iload 2
    ldc -100126598 (java.lang.Integer)
    if_icmpeq L10
    new java/lang/IllegalStateException
    dup
    invokespecial java/lang/IllegalStateException <init>:()V
    athrow
L11
    iinc 4 1
    goto L6
L9
    iload 3
    bipush 43
    invokestatic dj e:(IB)Lad;
    areturn
L12
    aload 0
    getfield ad al:[I
    iload 4
    iaload
    istore 3
    goto L11
L2
    aload 0
    areturn
L13
    new java/lang/StringBuilder
    dup
    invokespecial java/lang/StringBuilder <init>:()V
    ldc "ad.f(" (java.lang.String)
    invokevirtual java/lang/StringBuilder append:(Ljava/lang/String;)Ljava/lang/StringBuilder;
    ldc 41 (java.lang.Integer)
    invokevirtual java/lang/StringBuilder append:(C)Ljava/lang/StringBuilder;
    invokevirtual java/lang/StringBuilder toString:()Ljava/lang/String;
    invokestatic k a:(Ljava/lang/Throwable;Ljava/lang/String;)Lee;
    athrow
