ad h (ZI)Lcr;L1
    aload 0
    getfield ad ai:I
    ldc -88613353 (java.lang.Integer)
    imul
    istore 3
    goto L2
L3
    iconst_0
    istore 7
    goto L4
L5
    iconst_3
    anewarray cr
    dup
    iconst_0
    aload 6
    aastore
    dup
    iconst_1
    aload 7
    aastore
    dup
    iconst_2
    aload 8
    aastore
    astore 9
    goto L6
L7
    iload 1
    ifeq L8
    iload 2
    ldc -1908198710 (java.lang.Integer)
    if_icmplt L9
    new java/lang/IllegalStateException
    dup
    invokespecial java/lang/IllegalStateException <init>:()V
    athrow
L10
    new cr
    dup
    aload 8
    iconst_2
    invokespecial cr <init>:([Lcr;I)V
    astore 6
    goto L11
L12
    ldc -1900792981 (java.lang.Integer)
    aload 0
    getfield ad ae:I
    imul
    istore 4
    goto L13
L14
    iconst_m1
    iload 5
    if_icmpeq L15
    iload 2
    ldc -1908198710 (java.lang.Integer)
    if_icmplt L16
    new java/lang/IllegalStateException
    dup
    invokespecial java/lang/IllegalStateException <init>:()V
    athrow
L8
    iconst_m1
    iload 3
    if_icmpne L17
    iload 2
    ldc -1908198710 (java.lang.Integer)
    if_icmplt L18
    new java/lang/IllegalStateException
    dup
    invokespecial java/lang/IllegalStateException <init>:()V
    athrow
L18
    aconst_null
    areturn
L17
    getstatic c u:Lfv;
    iload 3
    iconst_0
    invokestatic cr e:(Lfv;II)Lcr;
    astore 6
L19
    iload 4
    iconst_m1
    if_icmpeq L11
    iload 2
    ldc -1908198710 (java.lang.Integer)
    if_icmplt L20
    new java/lang/IllegalStateException
    dup
    invokespecial java/lang/IllegalStateException <init>:()V
    athrow
L20
    getstatic c u:Lfv;
    iload 4
    iconst_0
    invokestatic cr e:(Lfv;II)Lcr;
    astore 7
    goto L14
L21
    ldc 308056007 (java.lang.Integer)
    aload 0
    getfield ad av:I
    imul
    istore 5
    goto L7
L16
    getstatic c u:Lfv;
    iload 5
    iconst_0
    invokestatic cr e:(Lfv;II)Lcr;
    astore 8
    goto L5
L22
    ldc -1220837161 (java.lang.Integer)
    aload 0
    getfield ad am:I
    imul
    ifeq L23
    iload 2
    ldc -1908198710 (java.lang.Integer)
    if_icmplt L24
    new java/lang/IllegalStateException
    dup
    invokespecial java/lang/IllegalStateException <init>:()V
    athrow
L6
    new cr
    dup
    aload 9
    iconst_3
    invokespecial cr <init>:([Lcr;I)V
    astore 6
    goto L25
L13
    aload 0
    getfield ad ay:I
    ldc 1803199095 (java.lang.Integer)
    imul
    istore 5
    goto L8
L15
    iconst_2
    anewarray cr
    dup
    iconst_0
    aload 6
    aastore
    dup
    iconst_1
    aload 7
    aastore
    astore 8
    goto L10
L25
    goto L11
L26
    aload 6
    aload 0
    getfield ad m:[S
    iload 7
    saload
    aload 0
    getfield ad t:[S
    iload 7
    saload
    invokevirtual cr z:(SS)V
    goto L27
L28
    aload 6
    areturn
L24
    aload 6
    iconst_0
    ldc -1220837161 (java.lang.Integer)
    aload 0
    getfield ad am:I
    imul
    iconst_0
    invokevirtual cr t:(III)V
L23
    iload 1
    ifeq L29
    iload 2
    ldc -1908198710 (java.lang.Integer)
    if_icmplt L30
    new java/lang/IllegalStateException
    dup
    invokespecial java/lang/IllegalStateException <init>:()V
    athrow
L30
    aload 0
    getfield ad ab:I
    ldc -2010799485 (java.lang.Integer)
    imul
    ifeq L29
    iload 2
    ldc -1908198710 (java.lang.Integer)
    if_icmplt L31
    new java/lang/IllegalStateException
    dup
    invokespecial java/lang/IllegalStateException <init>:()V
    athrow
L31
    aload 6
    iconst_0
    aload 0
    getfield ad ab:I
    ldc -2010799485 (java.lang.Integer)
    imul
    iconst_0
    invokevirtual cr t:(III)V
L29
    aconst_null
    aload 0
    getfield ad m:[S
    if_acmpeq L32
    iload 2
    ldc -1908198710 (java.lang.Integer)
    if_icmplt L33
    new java/lang/IllegalStateException
    dup
    invokespecial java/lang/IllegalStateException <init>:()V
    athrow
L33
    iconst_0
    istore 7
L34
    iload 7
    aload 0
    getfield ad m:[S
    arraylength
    if_icmpge L32
    goto L26
L2
    ldc -9042073 (java.lang.Integer)
    aload 0
    getfield ad aw:I
    imul
    istore 4
    goto L21
L27
    iinc 7 1
    goto L34
L32
    aload 0
    getfield ad z:[S
    ifnull L28
    iload 2
    ldc -1908198710 (java.lang.Integer)
    if_icmplt L3
    new java/lang/IllegalStateException
    dup
    invokespecial java/lang/IllegalStateException <init>:()V
    athrow
L35
    iinc 7 1
L4
    iload 7
    aload 0
    getfield ad z:[S
    arraylength
    if_icmpge L28
    iload 2
    ldc -1908198710 (java.lang.Integer)
    if_icmplt L36
    new java/lang/IllegalStateException
    dup
    invokespecial java/lang/IllegalStateException <init>:()V
    athrow
L36
    aload 6
    aload 0
    getfield ad z:[S
    iload 7
    saload
    aload 0
    getfield ad y:[S
    iload 7
    saload
    invokevirtual cr y:(SS)V
    goto L35
L9
    ldc 193308843 (java.lang.Integer)
    aload 0
    getfield ad au:I
    imul
    istore 3
    goto L12
L11
    iload 1
    ifne L23
    goto L22
L37
    new java/lang/StringBuilder
    dup
    invokespecial java/lang/StringBuilder <init>:()V
    ldc "ad.h(" (java.lang.String)
    invokevirtual java/lang/StringBuilder append:(Ljava/lang/String;)Ljava/lang/StringBuilder;
    ldc 41 (java.lang.Integer)
    invokevirtual java/lang/StringBuilder append:(C)Ljava/lang/StringBuilder;
    invokevirtual java/lang/StringBuilder toString:()Ljava/lang/String;
    invokestatic k a:(Ljava/lang/Throwable;Ljava/lang/String;)Lee;
    athrow
