ad o (ZI)ZL1
    ldc -88613353 (java.lang.Integer)
    aload 0
    getfield ad ai:I
    imul
    istore 3
    goto L2
L3
    getstatic c u:Lfv;
    iload 5
    iconst_0
    bipush -17
    invokevirtual fv u:(IIB)Z
    ifne L4
    iload 2
    ldc -1629166975 (java.lang.Integer)
    if_icmpeq L5
    new java/lang/IllegalStateException
    dup
    invokespecial java/lang/IllegalStateException <init>:()V
    athrow
L6
    iconst_m1
    iload 3
    if_icmpne L7
    iload 2
    ldc -1629166975 (java.lang.Integer)
    if_icmpeq L8
    new java/lang/IllegalStateException
    dup
    invokespecial java/lang/IllegalStateException <init>:()V
    athrow
L9
    getstatic c u:Lfv;
    iload 3
    iconst_0
    bipush -37
    invokevirtual fv u:(IIB)Z
    ifne L10
    iload 2
    ldc -1629166975 (java.lang.Integer)
    if_icmpeq L11
    new java/lang/IllegalStateException
    dup
    invokespecial java/lang/IllegalStateException <init>:()V
    athrow
L12
    ldc 193308843 (java.lang.Integer)
    aload 0
    getfield ad au:I
    imul
    istore 3
L13
    aload 0
    getfield ad ae:I
    ldc -1900792981 (java.lang.Integer)
    imul
    istore 4
L14
    aload 0
    getfield ad ay:I
    ldc 1803199095 (java.lang.Integer)
    imul
    istore 5
    goto L6
L5
    iconst_0
    istore 6
    goto L4
L8
    iconst_1
    ireturn
L7
    iconst_1
    istore 6
    goto L9
L15
    getstatic c u:Lfv;
    iload 4
    iconst_0
    bipush -55
    invokevirtual fv u:(IIB)Z
    ifne L16
    iload 2
    ldc -1629166975 (java.lang.Integer)
    if_icmpeq L17
    new java/lang/IllegalStateException
    dup
    invokespecial java/lang/IllegalStateException <init>:()V
    athrow
L11
    iconst_0
    istore 6
L10
    iload 4
    iconst_m1
    if_icmpeq L16
    iload 2
    ldc -1629166975 (java.lang.Integer)
    if_icmpeq L15
    new java/lang/IllegalStateException
    dup
    invokespecial java/lang/IllegalStateException <init>:()V
    athrow
L18
    aload 0
    getfield ad av:I
    ldc 308056007 (java.lang.Integer)
    imul
    istore 5
    goto L19
L17
    iconst_0
    istore 6
    goto L16
L2
    ldc -9042073 (java.lang.Integer)
    aload 0
    getfield ad aw:I
    imul
    istore 4
    goto L18
L16
    iconst_m1
    iload 5
    if_icmpeq L4
    iload 2
    ldc -1629166975 (java.lang.Integer)
    if_icmpeq L3
    new java/lang/IllegalStateException
    dup
    invokespecial java/lang/IllegalStateException <init>:()V
    athrow
L4
    iload 6
    ireturn
L19
    iload 1
    ifeq L6
    goto L12
L20
    new java/lang/StringBuilder
    dup
    invokespecial java/lang/StringBuilder <init>:()V
    ldc "ad.o(" (java.lang.String)
    invokevirtual java/lang/StringBuilder append:(Ljava/lang/String;)Ljava/lang/StringBuilder;
    ldc 41 (java.lang.Integer)
    invokevirtual java/lang/StringBuilder append:(C)Ljava/lang/StringBuilder;
    invokevirtual java/lang/StringBuilder toString:()Ljava/lang/String;
    invokestatic k a:(Ljava/lang/Throwable;Ljava/lang/String;)Lee;
    athrow
