ad r (IB)Lcy;L1
    aconst_null
    aload 0
    getfield ad al:[I
    if_acmpeq L2
    iload 2
    iconst_1
    if_icmpgt L3
    new java/lang/IllegalStateException
    dup
    invokespecial java/lang/IllegalStateException <init>:()V
    athrow
L4
    aconst_null
    aload 0
    getfield ad z:[S
    if_acmpeq L5
    goto L6
L7
    aload 3
    areturn
L8
    iconst_0
    istore 4
    goto L9
L10
    aload 0
    getfield ad ak:[I
    iload 4
    iaload
    ifeq L11
    iload 2
    iconst_1
    if_icmpgt L12
    new java/lang/IllegalStateException
    dup
    invokespecial java/lang/IllegalStateException <init>:()V
    athrow
L13
    iload 1
    aload 0
    getfield ad ak:[I
    iload 4
    iaload
    if_icmplt L11
    iload 2
    iconst_1
    if_icmpgt L10
    new java/lang/IllegalStateException
    dup
    invokespecial java/lang/IllegalStateException <init>:()V
    athrow
L3
    iload 1
    iconst_1
    if_icmple L2
    iload 2
    iconst_1
    if_icmpgt L14
    new java/lang/IllegalStateException
    dup
    invokespecial java/lang/IllegalStateException <init>:()V
    athrow
L15
    iconst_0
    istore 5
    goto L16
L14
    iconst_m1
    istore 3
    goto L8
L17
    iload 3
    iconst_m1
    if_icmpeq L2
    iload 2
    iconst_1
    if_icmpgt L18
    new java/lang/IllegalStateException
    dup
    invokespecial java/lang/IllegalStateException <init>:()V
    athrow
L18
    iload 3
    bipush -20
    invokestatic dj e:(IB)Lad;
    iconst_1
    bipush 53
    invokevirtual ad r:(IB)Lcy;
    areturn
L11
    iinc 4 1
    goto L9
L19
    aload 3
    ifnull L20
    iload 2
    iconst_1
    if_icmpgt L21
    new java/lang/IllegalStateException
    dup
    invokespecial java/lang/IllegalStateException <init>:()V
    athrow
L21
    aload 3
    areturn
L20
    getstatic c u:Lfv;
    ldc -1279523167 (java.lang.Integer)
    aload 0
    getfield ad s:I
    imul
    iconst_0
    invokestatic cr e:(Lfv;II)Lcr;
    astore 4
L22
    aconst_null
    aload 4
    if_acmpne L23
    iload 2
    iconst_1
    if_icmpgt L24
    new java/lang/IllegalStateException
    dup
    invokespecial java/lang/IllegalStateException <init>:()V
    athrow
L24
    aconst_null
    areturn
L23
    sipush 128
    aload 0
    getfield ad ac:I
    ldc 201822203 (java.lang.Integer)
    imul
    if_icmpne L25
    iload 2
    iconst_1
    if_icmpgt L26
    new java/lang/IllegalStateException
    dup
    invokespecial java/lang/IllegalStateException <init>:()V
    athrow
L26
    sipush 128
    aload 0
    getfield ad ad:I
    ldc -982580489 (java.lang.Integer)
    imul
    if_icmpne L25
    iload 2
    iconst_1
    if_icmpgt L27
    new java/lang/IllegalStateException
    dup
    invokespecial java/lang/IllegalStateException <init>:()V
    athrow
L5
    aload 4
    aload 0
    getfield ad az:I
    ldc -1859198821 (java.lang.Integer)
    imul
    bipush 64
    iadd
    ldc 40571045 (java.lang.Integer)
    aload 0
    getfield ad af:I
    imul
    sipush 768
    iadd
    bipush -50
    bipush -10
    bipush -50
    invokevirtual cr p:(IIIII)Lcy;
    astore 3
    goto L28
L25
    aload 4
    ldc 201822203 (java.lang.Integer)
    aload 0
    getfield ad ac:I
    imul
    aload 0
    getfield ad ad:I
    ldc -982580489 (java.lang.Integer)
    imul
    aload 0
    getfield ad an:I
    ldc 412766295 (java.lang.Integer)
    imul
    invokevirtual cr d:(III)V
    goto L29
L9
    iload 4
    bipush 10
    if_icmpge L17
    iload 2
    iconst_1
    if_icmpgt L13
    new java/lang/IllegalStateException
    dup
    invokespecial java/lang/IllegalStateException <init>:()V
    athrow
L27
    aload 0
    getfield ad an:I
    ldc 412766295 (java.lang.Integer)
    imul
    sipush 128
    if_icmpeq L29
    iload 2
    iconst_1
    if_icmpgt L25
    new java/lang/IllegalStateException
    dup
    invokespecial java/lang/IllegalStateException <init>:()V
    athrow
L16
    iload 5
    aload 0
    getfield ad m:[S
    arraylength
    if_icmpge L4
    iload 2
    iconst_1
    if_icmpgt L30
    new java/lang/IllegalStateException
    dup
    invokespecial java/lang/IllegalStateException <init>:()V
    athrow
L30
    aload 4
    aload 0
    getfield ad m:[S
    iload 5
    saload
    aload 0
    getfield ad t:[S
    iload 5
    saload
    invokevirtual cr z:(SS)V
L31
    iinc 5 1
    goto L16
L2
    getstatic ad f:Lgr;
    ldc 1822592743 (java.lang.Integer)
    aload 0
    getfield ad h:I
    imul
    i2l
    invokevirtual gr e:(J)Lgd;
    checkcast cy
    astore 3
    goto L19
L6
    iconst_0
    istore 5
L32
    iload 5
    aload 0
    getfield ad z:[S
    arraylength
    if_icmpge L5
    iload 2
    iconst_1
    if_icmpgt L33
    new java/lang/IllegalStateException
    dup
    invokespecial java/lang/IllegalStateException <init>:()V
    athrow
L33
    aload 4
    aload 0
    getfield ad z:[S
    iload 5
    saload
    aload 0
    getfield ad y:[S
    iload 5
    saload
    invokevirtual cr y:(SS)V
L34
    iinc 5 1
    goto L32
L12
    aload 0
    getfield ad al:[I
    iload 4
    iaload
    istore 3
    goto L11
L28
    aload 3
    iconst_1
    putfield cy ax:Z
L35
    getstatic ad f:Lgr;
    aload 3
    ldc 1822592743 (java.lang.Integer)
    aload 0
    getfield ad h:I
    imul
    i2l
    invokevirtual gr l:(Lgd;J)V
    goto L7
L29
    aload 0
    getfield ad m:[S
    ifnull L4
    iload 2
    iconst_1
    if_icmpgt L15
    new java/lang/IllegalStateException
    dup
    invokespecial java/lang/IllegalStateException <init>:()V
    athrow
L36
    new java/lang/StringBuilder
    dup
    invokespecial java/lang/StringBuilder <init>:()V
    ldc "ad.r(" (java.lang.String)
    invokevirtual java/lang/StringBuilder append:(Ljava/lang/String;)Ljava/lang/StringBuilder;
    ldc 41 (java.lang.Integer)
    invokevirtual java/lang/StringBuilder append:(C)Ljava/lang/StringBuilder;
    invokevirtual java/lang/StringBuilder toString:()Ljava/lang/String;
    invokestatic k a:(Ljava/lang/Throwable;Ljava/lang/String;)Lee;
    athrow
