ag c (Ldh;II)VL1
    iconst_1
    iload 2
    if_icmpne L2
    iload 3
    ldc -268686749 (java.lang.Integer)
    if_icmpne L3
    new java/lang/IllegalStateException
    dup
    invokespecial java/lang/IllegalStateException <init>:()V
    athrow
L4
    iload 4
    ifle L5
    goto L6
L7
    iload 4
    ifle L8
    iload 3
    ldc -268686749 (java.lang.Integer)
    if_icmpne L9
    return
L10
    aload 0
    iconst_0
    putfield ag q:I
    goto L11
L12
    getstatic ag e:Z
    ifeq L13
    iload 3
    ldc -268686749 (java.lang.Integer)
    if_icmpne L14
    new java/lang/IllegalStateException
    dup
    invokespecial java/lang/IllegalStateException <init>:()V
    athrow
L15
    aload 0
    ldc -176616621 (java.lang.Integer)
    putfield ag aq:I
    goto L16
L17
    aload 0
    iload 4
    newarray 10
    putfield ag g:[I
    goto L18
L19
    iinc 5 1
    goto L20
L21
    iconst_0
    istore 5
    goto L20
L22
    aload 0
    aload 1
    ldc 657934353 (java.lang.Integer)
    invokevirtual dh q:(I)I
    ldc 176616621 (java.lang.Integer)
    imul
    putfield ag aq:I
    goto L23
L24
    bipush 77
    iload 2
    if_icmpne L25
    iload 3
    ldc -268686749 (java.lang.Integer)
    if_icmpne L26
    new java/lang/IllegalStateException
    dup
    invokespecial java/lang/IllegalStateException <init>:()V
    athrow
L27
    iinc 5 1
    goto L28
L29
    iload 2
    bipush 60
    if_icmpne L30
    iload 3
    ldc -268686749 (java.lang.Integer)
    if_icmpne L31
    new java/lang/IllegalStateException
    dup
    invokespecial java/lang/IllegalStateException <init>:()V
    athrow
L32
    aload 0
    getfield ag j:[S
    iload 5
    aload 1
    ldc -2071995650 (java.lang.Integer)
    invokevirtual dh q:(I)I
    i2s
    sastore
    goto L33
L8
    goto L34
L2
    iconst_2
    iload 2
    if_icmpne L35
    iload 3
    ldc -268686749 (java.lang.Integer)
    if_icmpne L36
    new java/lang/IllegalStateException
    dup
    invokespecial java/lang/IllegalStateException <init>:()V
    athrow
L36
    aload 0
    aload 1
    ldc -575960389 (java.lang.Integer)
    invokevirtual dh p:(I)Ljava/lang/String;
    putfield ag h:Ljava/lang/String;
    goto L34
L35
    iconst_5
    iload 2
    if_icmpne L37
    iload 3
    ldc -268686749 (java.lang.Integer)
    if_icmpne L38
    new java/lang/IllegalStateException
    dup
    invokespecial java/lang/IllegalStateException <init>:()V
    athrow
L38
    aload 1
    ldc 1289662993 (java.lang.Integer)
    invokevirtual dh z:(I)I
    istore 4
    goto L4
L39
    aload 0
    getfield ag m:[S
    iload 5
    aload 1
    ldc 898543426 (java.lang.Integer)
    invokevirtual dh q:(I)I
    i2s
    sastore
    goto L40
L6
    aconst_null
    aload 0
    getfield ag g:[I
    if_acmpeq L41
    iload 3
    ldc -268686749 (java.lang.Integer)
    if_icmpne L42
    new java/lang/IllegalStateException
    dup
    invokespecial java/lang/IllegalStateException <init>:()V
    athrow
L42
    getstatic ag e:Z
    ifeq L43
    goto L41
L44
    aload 0
    getfield ag s:[S
    iload 5
    aload 1
    ldc 1269316134 (java.lang.Integer)
    invokevirtual dh q:(I)I
    i2s
    sastore
    goto L32
L20
    iload 5
    iload 4
    if_icmpgt L45
    iload 3
    ldc -268686749 (java.lang.Integer)
    if_icmpne L46
    new java/lang/IllegalStateException
    dup
    invokespecial java/lang/IllegalStateException <init>:()V
    athrow
L3
    aload 1
    ldc 593231186 (java.lang.Integer)
    invokevirtual dh z:(I)I
    istore 4
    goto L7
L47
    iload 5
    iload 4
    if_icmpge L48
    iload 3
    ldc -268686749 (java.lang.Integer)
    if_icmpne L49
    return
L49
    aload 0
    getfield ag g:[I
    iload 5
    aload 1
    ldc -680345171 (java.lang.Integer)
    invokevirtual dh q:(I)I
    iastore
    iinc 5 1
    goto L47
L48
    goto L5
L28
    iload 5
    iload 4
    if_icmpge L50
    iload 3
    ldc -268686749 (java.lang.Integer)
    if_icmpne L51
    return
L5
    goto L34
L30
    iload 2
    bipush 62
    if_icmpne L52
    goto L53
L54
    aload 0
    aload 1
    ldc 584843942 (java.lang.Integer)
    invokevirtual dh z:(I)I
    ldc 1666853081 (java.lang.Integer)
    imul
    putfield ag z:I
    goto L34
L55
    iload 2
    bipush 70
    if_icmpne L56
    iload 3
    ldc -268686749 (java.lang.Integer)
    if_icmpne L57
    new java/lang/IllegalStateException
    dup
    invokespecial java/lang/IllegalStateException <init>:()V
    athrow
L58
    aload 0
    aload 1
    ldc 831628176 (java.lang.Integer)
    invokevirtual dh z:(I)I
    ldc -338149669 (java.lang.Integer)
    imul
    putfield ag y:I
    goto L34
L59
    iload 2
    bipush 75
    if_icmpne L24
    iload 3
    ldc -268686749 (java.lang.Integer)
    if_icmpne L60
    new java/lang/IllegalStateException
    dup
    invokespecial java/lang/IllegalStateException <init>:()V
    athrow
L61
    aload 0
    aload 1
    ldc -662781403 (java.lang.Integer)
    invokevirtual dh d:(I)I
    ldc -1214420091 (java.lang.Integer)
    imul
    putfield ag aj:I
    goto L34
L11
    aload 0
    iconst_0
    putfield ag d:Z
    goto L34
L62
    bipush 18
    iload 2
    if_icmpne L63
    iload 3
    ldc -268686749 (java.lang.Integer)
    if_icmpne L64
    new java/lang/IllegalStateException
    dup
    invokespecial java/lang/IllegalStateException <init>:()V
    athrow
L64
    aload 0
    iconst_0
    putfield ag d:Z
    goto L34
L63
    iload 2
    bipush 19
    if_icmpne L65
    iload 3
    ldc -268686749 (java.lang.Integer)
    if_icmpne L66
    return
L66
    aload 0
    aload 1
    ldc 1432963957 (java.lang.Integer)
    invokevirtual dh z:(I)I
    ldc 43732051 (java.lang.Integer)
    imul
    putfield ag b:I
    goto L34
L13
    aload 1
    dup
    getfield dh a:I
    iload 4
    ldc 1053797423 (java.lang.Integer)
    imul
    iadd
    putfield dh a:I
    goto L8
L67
    aload 0
    iconst_0
    putfield ag x:I
    goto L34
L65
    bipush 21
    iload 2
    if_icmpne L68
    iload 3
    ldc -268686749 (java.lang.Integer)
    if_icmpne L67
    new java/lang/IllegalStateException
    dup
    invokespecial java/lang/IllegalStateException <init>:()V
    athrow
L68
    bipush 22
    iload 2
    if_icmpne L69
    goto L70
L69
    bipush 23
    iload 2
    if_icmpne L71
    iload 3
    ldc -268686749 (java.lang.Integer)
    if_icmpne L72
    new java/lang/IllegalStateException
    dup
    invokespecial java/lang/IllegalStateException <init>:()V
    athrow
L72
    aload 0
    iconst_1
    putfield ag v:Z
    goto L34
L71
    bipush 24
    iload 2
    if_icmpne L73
    iload 3
    ldc -268686749 (java.lang.Integer)
    if_icmpne L74
    new java/lang/IllegalStateException
    dup
    invokespecial java/lang/IllegalStateException <init>:()V
    athrow
L75
    aload 0
    ldc -145834749 (java.lang.Integer)
    putfield ag p:I
    goto L34
L76
    bipush 15
    iload 2
    if_icmpne L77
    iload 3
    ldc -268686749 (java.lang.Integer)
    if_icmpne L58
    new java/lang/IllegalStateException
    dup
    invokespecial java/lang/IllegalStateException <init>:()V
    athrow
L78
    iconst_0
    istore 5
    goto L47
L73
    bipush 27
    iload 2
    if_icmpne L79
    goto L80
L74
    aload 0
    aload 1
    ldc -570810056 (java.lang.Integer)
    invokevirtual dh q:(I)I
    ldc 145834749 (java.lang.Integer)
    imul
    putfield ag p:I
    goto L81
L79
    iload 2
    bipush 28
    if_icmpne L82
    goto L83
L40
    aload 0
    getfield ag t:[S
    iload 5
    aload 1
    ldc -1773212138 (java.lang.Integer)
    invokevirtual dh q:(I)I
    i2s
    sastore
    goto L84
L37
    iload 2
    bipush 14
    if_icmpne L76
    iload 3
    ldc -268686749 (java.lang.Integer)
    if_icmpne L54
    new java/lang/IllegalStateException
    dup
    invokespecial java/lang/IllegalStateException <init>:()V
    athrow
L81
    ldc -175609259 (java.lang.Integer)
    aload 0
    getfield ag p:I
    imul
    ldc 65535 (java.lang.Integer)
    if_icmpne L34
    goto L75
L85
    iload 2
    bipush 39
    if_icmpne L86
    iload 3
    ldc -268686749 (java.lang.Integer)
    if_icmpne L87
    new java/lang/IllegalStateException
    dup
    invokespecial java/lang/IllegalStateException <init>:()V
    athrow
L88
    aload 0
    getfield ag o:[I
    iload 5
    aload 1
    ldc 2021560760 (java.lang.Integer)
    invokevirtual dh z:(I)I
    iastore
    goto L27
L86
    iload 2
    bipush 30
    if_icmplt L89
    iload 3
    ldc -268686749 (java.lang.Integer)
    if_icmpne L90
    new java/lang/IllegalStateException
    dup
    invokespecial java/lang/IllegalStateException <init>:()V
    athrow
L90
    iload 2
    bipush 35
    if_icmpge L89
    iload 3
    ldc -268686749 (java.lang.Integer)
    if_icmpne L91
    new java/lang/IllegalStateException
    dup
    invokespecial java/lang/IllegalStateException <init>:()V
    athrow
L91
    aload 0
    getfield ag ao:[Ljava/lang/String;
    iload 2
    bipush 30
    isub
    aload 1
    ldc 1523289225 (java.lang.Integer)
    invokevirtual dh p:(I)Ljava/lang/String;
    aastore
    goto L92
L18
    iconst_0
    istore 5
    goto L28
L93
    aload 0
    getfield ag ao:[Ljava/lang/String;
    iload 2
    bipush 30
    isub
    aconst_null
    aastore
    goto L34
L94
    iconst_0
    istore 5
    goto L95
L26
    aload 0
    aload 1
    ldc 1405391794 (java.lang.Integer)
    invokevirtual dh q:(I)I
    ldc 1604107113 (java.lang.Integer)
    imul
    putfield ag ar:I
    goto L96
L97
    aload 0
    iload 4
    newarray 9
    putfield ag s:[S
L98
    aload 0
    iload 4
    newarray 9
    putfield ag j:[S
    goto L94
L50
    goto L8
L95
    iload 5
    iload 4
    if_icmpge L99
    iload 3
    ldc -268686749 (java.lang.Integer)
    if_icmpne L44
    new java/lang/IllegalStateException
    dup
    invokespecial java/lang/IllegalStateException <init>:()V
    athrow
L83
    aload 0
    aload 1
    ldc 1452271262 (java.lang.Integer)
    invokevirtual dh z:(I)I
    ldc 349150749 (java.lang.Integer)
    imul
    putfield ag k:I
    goto L34
L77
    bipush 17
    iload 2
    if_icmpne L62
    goto L10
L33
    iinc 5 1
    goto L95
L99
    goto L34
L100
    iload 2
    bipush 41
    if_icmpne L29
    iload 3
    ldc -268686749 (java.lang.Integer)
    if_icmpne L101
    new java/lang/IllegalStateException
    dup
    invokespecial java/lang/IllegalStateException <init>:()V
    athrow
L101
    aload 1
    ldc 683842738 (java.lang.Integer)
    invokevirtual dh z:(I)I
    istore 4
L102
    aload 0
    iload 4
    newarray 9
    putfield ag m:[S
L103
    aload 0
    iload 4
    newarray 9
    putfield ag t:[S
L104
    iconst_0
    istore 5
L105
    iload 5
    iload 4
    if_icmpge L106
    iload 3
    ldc -268686749 (java.lang.Integer)
    if_icmpne L39
    new java/lang/IllegalStateException
    dup
    invokespecial java/lang/IllegalStateException <init>:()V
    athrow
L70
    aload 0
    iconst_1
    putfield ag n:Z
    goto L34
L107
    aload 0
    iconst_1
    iload 4
    iadd
    newarray 10
    putfield ag ak:[I
    goto L21
L84
    iinc 5 1
    goto L105
L106
    goto L34
L25
    iload 2
    bipush 78
    if_icmpne L108
    iload 3
    ldc -268686749 (java.lang.Integer)
    if_icmpne L109
    return
L31
    aload 0
    aload 1
    ldc -914730014 (java.lang.Integer)
    invokevirtual dh q:(I)I
    ldc 1364492859 (java.lang.Integer)
    imul
    putfield ag ai:I
    goto L34
L110
    aload 0
    aload 1
    ldc 1885938546 (java.lang.Integer)
    invokevirtual dh q:(I)I
    ldc 741458567 (java.lang.Integer)
    imul
    putfield ag aw:I
    goto L34
L53
    aload 0
    iconst_1
    putfield ag am:Z
    goto L34
L52
    iload 2
    bipush 64
    if_icmpne L111
    iload 3
    ldc -268686749 (java.lang.Integer)
    if_icmpne L112
    new java/lang/IllegalStateException
    dup
    invokespecial java/lang/IllegalStateException <init>:()V
    athrow
L112
    aload 0
    iconst_0
    putfield ag au:Z
    goto L34
L111
    iload 2
    bipush 65
    if_icmpne L113
    iload 3
    ldc -268686749 (java.lang.Integer)
    if_icmpne L114
    return
L114
    aload 0
    aload 1
    ldc -2117924702 (java.lang.Integer)
    invokevirtual dh q:(I)I
    ldc 1831297463 (java.lang.Integer)
    imul
    putfield ag ae:I
    goto L34
L113
    iload 2
    bipush 66
    if_icmpne L115
    aload 0
    aload 1
    ldc -2003239567 (java.lang.Integer)
    invokevirtual dh q:(I)I
    ldc -880259997 (java.lang.Integer)
    imul
    putfield ag ab:I
    goto L34
L115
    iload 2
    bipush 67
    if_icmpne L116
    iload 3
    ldc -268686749 (java.lang.Integer)
    if_icmpne L117
    new java/lang/IllegalStateException
    dup
    invokespecial java/lang/IllegalStateException <init>:()V
    athrow
L117
    aload 0
    aload 1
    ldc 37018874 (java.lang.Integer)
    invokevirtual dh q:(I)I
    ldc 314145533 (java.lang.Integer)
    imul
    putfield ag av:I
    goto L34
L116
    bipush 68
    iload 2
    if_icmpne L118
    iload 3
    ldc -268686749 (java.lang.Integer)
    if_icmpne L110
    new java/lang/IllegalStateException
    dup
    invokespecial java/lang/IllegalStateException <init>:()V
    athrow
L119
    aload 0
    iload 4
    newarray 10
    putfield ag g:[I
    goto L78
L118
    iload 2
    bipush 69
    if_icmpne L55
    iload 3
    ldc -268686749 (java.lang.Integer)
    if_icmpne L120
    return
L120
    aload 1
    ldc 1677537604 (java.lang.Integer)
    invokevirtual dh z:(I)I
    pop
    goto L34
L51
    aload 0
    getfield ag g:[I
    iload 5
    aload 1
    ldc -886004287 (java.lang.Integer)
    invokevirtual dh q:(I)I
    iastore
    goto L88
L57
    aload 0
    aload 1
    ldc 285731167 (java.lang.Integer)
    invokevirtual dh d:(I)I
    ldc 1006017097 (java.lang.Integer)
    imul
    putfield ag ay:I
    goto L34
L56
    iload 2
    bipush 71
    if_icmpne L121
    iload 3
    ldc -268686749 (java.lang.Integer)
    if_icmpne L122
    return
L122
    aload 0
    aload 1
    ldc -1976066275 (java.lang.Integer)
    invokevirtual dh d:(I)I
    ldc -1695800327 (java.lang.Integer)
    imul
    putfield ag ag:I
    goto L34
L121
    iload 2
    bipush 72
    if_icmpne L123
    iload 3
    ldc -268686749 (java.lang.Integer)
    if_icmpne L61
    return
L9
    aload 0
    getfield ag g:[I
    ifnull L14
    iload 3
    ldc -268686749 (java.lang.Integer)
    if_icmpne L12
    new java/lang/IllegalStateException
    dup
    invokespecial java/lang/IllegalStateException <init>:()V
    athrow
L124
    aload 0
    aload 1
    ldc -1098920641 (java.lang.Integer)
    invokevirtual dh q:(I)I
    ldc -1043370487 (java.lang.Integer)
    imul
    putfield ag an:I
    goto L125
L126
    aload 0
    iconst_1
    putfield ag ah:Z
    goto L34
L127
    iload 2
    bipush 74
    if_icmpne L59
    iload 3
    ldc -268686749 (java.lang.Integer)
    if_icmpne L128
    new java/lang/IllegalStateException
    dup
    invokespecial java/lang/IllegalStateException <init>:()V
    athrow
L128
    aload 0
    iconst_1
    putfield ag at:Z
    goto L34
L129
    aload 0
    getfield ag ak:[I
    iload 5
    iconst_m1
    iastore
    goto L19
L60
    aload 0
    aload 1
    ldc 591395325 (java.lang.Integer)
    invokevirtual dh z:(I)I
    ldc -2141428811 (java.lang.Integer)
    imul
    putfield ag al:I
    goto L34
L80
    aload 0
    ldc 1735473327 (java.lang.Integer)
    putfield ag q:I
    goto L34
L130
    aload 0
    getfield ag af:[I
    iload 5
    aload 1
    ldc 974864663 (java.lang.Integer)
    invokevirtual dh q:(I)I
    iastore
    iinc 5 1
    goto L131
L96
    aload 0
    getfield ag ar:I
    ldc -1509194535 (java.lang.Integer)
    imul
    ldc 65535 (java.lang.Integer)
    if_icmpne L22
    iload 3
    ldc -268686749 (java.lang.Integer)
    if_icmpne L132
    new java/lang/IllegalStateException
    dup
    invokespecial java/lang/IllegalStateException <init>:()V
    athrow
L132
    aload 0
    ldc -1604107113 (java.lang.Integer)
    putfield ag ar:I
    goto L22
L89
    bipush 40
    iload 2
    if_icmpne L100
    goto L133
L41
    aload 0
    aconst_null
    putfield ag o:[I
    goto L119
L134
    aload 0
    aload 1
    ldc 1144951973 (java.lang.Integer)
    invokevirtual dh z:(I)I
    ldc -1727300864 (java.lang.Integer)
    imul
    putfield ag x:I
    goto L34
L16
    aload 1
    ldc 1268281210 (java.lang.Integer)
    invokevirtual dh z:(I)I
    istore 4
    goto L107
L43
    aload 1
    dup
    getfield dh a:I
    iload 4
    ldc -729124150 (java.lang.Integer)
    imul
    iadd
    putfield dh a:I
    goto L5
L82
    bipush 29
    iload 2
    if_icmpne L85
    iload 3
    ldc -268686749 (java.lang.Integer)
    if_icmpne L135
    return
L14
    aload 0
    iload 4
    newarray 10
    putfield ag o:[I
    goto L17
L46
    aload 0
    getfield ag ak:[I
    iload 5
    aload 1
    ldc -824226127 (java.lang.Integer)
    invokevirtual dh q:(I)I
    iastore
L136
    ldc 65535 (java.lang.Integer)
    aload 0
    getfield ag ak:[I
    iload 5
    iaload
    if_icmpne L19
    iload 3
    ldc -268686749 (java.lang.Integer)
    if_icmpne L129
    new java/lang/IllegalStateException
    dup
    invokespecial java/lang/IllegalStateException <init>:()V
    athrow
L135
    aload 0
    aload 1
    bipush 31
    invokevirtual dh y:(B)B
    ldc -1994059321 (java.lang.Integer)
    imul
    putfield ag ax:I
    goto L34
L109
    aload 0
    aload 1
    ldc 1660901815 (java.lang.Integer)
    invokevirtual dh q:(I)I
    ldc 2138003241 (java.lang.Integer)
    imul
    putfield ag ac:I
    goto L137
L45
    goto L34
L123
    iload 2
    bipush 73
    if_icmpne L127
    iload 3
    ldc -268686749 (java.lang.Integer)
    if_icmpne L126
    new java/lang/IllegalStateException
    dup
    invokespecial java/lang/IllegalStateException <init>:()V
    athrow
L92
    aload 0
    getfield ag ao:[Ljava/lang/String;
    iload 2
    bipush 30
    isub
    aaload
    getstatic et c:Ljava/lang/String;
    invokevirtual java/lang/String equalsIgnoreCase:(Ljava/lang/String;)Z
    ifeq L34
    iload 3
    ldc -268686749 (java.lang.Integer)
    if_icmpne L93
    return
L137
    aload 0
    aload 1
    ldc 1556439561 (java.lang.Integer)
    invokevirtual dh z:(I)I
    ldc 129214287 (java.lang.Integer)
    imul
    putfield ag ad:I
    goto L34
L108
    bipush 79
    iload 2
    if_icmpne L138
    iload 3
    ldc -268686749 (java.lang.Integer)
    if_icmpne L124
    return
L133
    aload 1
    ldc 1959505758 (java.lang.Integer)
    invokevirtual dh z:(I)I
    istore 4
    goto L97
L125
    aload 0
    aload 1
    ldc 374906253 (java.lang.Integer)
    invokevirtual dh q:(I)I
    ldc -908728135 (java.lang.Integer)
    imul
    putfield ag az:I
L139
    aload 0
    aload 1
    ldc 1660084339 (java.lang.Integer)
    invokevirtual dh z:(I)I
    ldc 129214287 (java.lang.Integer)
    imul
    putfield ag ad:I
L140
    aload 1
    ldc 1508561981 (java.lang.Integer)
    invokevirtual dh z:(I)I
    istore 4
L141
    aload 0
    iload 4
    newarray 10
    putfield ag af:[I
    goto L142
L87
    aload 0
    aload 1
    bipush 84
    invokevirtual dh y:(B)B
    ldc -329342779 (java.lang.Integer)
    imul
    putfield ag ap:I
    goto L34
L131
    iload 5
    iload 4
    if_icmpge L143
    iload 3
    ldc -268686749 (java.lang.Integer)
    if_icmpne L130
    new java/lang/IllegalStateException
    dup
    invokespecial java/lang/IllegalStateException <init>:()V
    athrow
L142
    iconst_0
    istore 5
    goto L131
L143
    goto L34
L138
    iload 2
    bipush 81
    if_icmpne L34
    iload 3
    ldc -268686749 (java.lang.Integer)
    if_icmpne L134
    new java/lang/IllegalStateException
    dup
    invokespecial java/lang/IllegalStateException <init>:()V
    athrow
L23
    ldc 65535 (java.lang.Integer)
    ldc -1084584155 (java.lang.Integer)
    aload 0
    getfield ag aq:I
    imul
    if_icmpne L16
    goto L15
L34
    return
L144
    new java/lang/StringBuilder
    dup
    invokespecial java/lang/StringBuilder <init>:()V
    ldc "ag.c(" (java.lang.String)
    invokevirtual java/lang/StringBuilder append:(Ljava/lang/String;)Ljava/lang/StringBuilder;
    ldc 41 (java.lang.Integer)
    invokevirtual java/lang/StringBuilder append:(C)Ljava/lang/StringBuilder;
    invokevirtual java/lang/StringBuilder toString:()Ljava/lang/String;
    invokestatic k a:(Ljava/lang/Throwable;Ljava/lang/String;)Lee;
    athrow
