ag f (II[[IIIILah;II)Lcy;L1
    aload 0
    getfield ag o:[I
    ifnonnull L2
    iload 9
    ldc -473437325 (java.lang.Integer)
    if_icmpgt L3
    new java/lang/IllegalStateException
    dup
    invokespecial java/lang/IllegalStateException <init>:()V
    athrow
L4
    aload 7
    aload 12
    iload 8
    iload 2
    ldc 2059415982 (java.lang.Integer)
    invokevirtual ah w:(Lcy;III)Lcy;
    astore 12
    goto L5
L6
    aconst_null
    aload 7
    if_acmpne L7
    iload 9
    ldc -473437325 (java.lang.Integer)
    if_icmpgt L8
    new java/lang/IllegalStateException
    dup
    invokespecial java/lang/IllegalStateException <init>:()V
    athrow
L5
    ldc 1931811763 (java.lang.Integer)
    aload 0
    getfield ag x:I
    imul
    iflt L9
    iload 9
    ldc -473437325 (java.lang.Integer)
    if_icmpgt L10
    new java/lang/IllegalStateException
    dup
    invokespecial java/lang/IllegalStateException <init>:()V
    athrow
L11
    getstatic ag i:Lgr;
    lload 10
    invokevirtual gr e:(J)Lgd;
    checkcast cy
    astore 12
    goto L12
L13
    aload 0
    iload 1
    iload 2
    bipush -62
    invokevirtual ag g:(IIB)Lcr;
    astore 13
L14
    aload 13
    ifnonnull L15
    goto L16
L15
    aload 13
    aload 0
    getfield ag ax:I
    ldc -683319305 (java.lang.Integer)
    imul
    bipush 64
    iadd
    ldc -1447514299 (java.lang.Integer)
    aload 0
    getfield ag ap:I
    imul
    sipush 768
    iadd
    bipush -50
    bipush -10
    bipush -50
    invokevirtual cr p:(IIIII)Lcy;
    astore 12
    goto L17
L12
    aload 12
    ifnonnull L6
    goto L13
L17
    getstatic ag i:Lgr;
    aload 12
    lload 10
    invokevirtual gr l:(Lgd;J)V
    goto L6
L2
    iload 1
    iconst_3
    ishl
    ldc -840218945 (java.lang.Integer)
    aload 0
    getfield ag f:I
    imul
    bipush 10
    ishl
    iadd
    iload 2
    iadd
    i2l
    lstore 10
    goto L11
L8
    iconst_m1
    ldc 1931811763 (java.lang.Integer)
    aload 0
    getfield ag x:I
    imul
    if_icmpne L7
    iload 9
    ldc -473437325 (java.lang.Integer)
    if_icmpgt L18
    new java/lang/IllegalStateException
    dup
    invokespecial java/lang/IllegalStateException <init>:()V
    athrow
L18
    aload 12
    areturn
L3
    ldc -840218945 (java.lang.Integer)
    aload 0
    getfield ag f:I
    imul
    bipush 10
    ishl
    iload 2
    iadd
    i2l
    lstore 10
    goto L11
L7
    aconst_null
    aload 7
    if_acmpeq L19
    iload 9
    ldc -473437325 (java.lang.Integer)
    if_icmpgt L4
    new java/lang/IllegalStateException
    dup
    invokespecial java/lang/IllegalStateException <init>:()V
    athrow
L19
    aload 12
    iconst_1
    invokevirtual cy l:(Z)Lcy;
    astore 12
    goto L5
L16
    aconst_null
    areturn
L10
    aload 12
    aload 3
    iload 4
    iload 5
    iload 6
    iconst_0
    ldc 1931811763 (java.lang.Integer)
    aload 0
    getfield ag x:I
    imul
    invokevirtual cy e:([[IIIIZI)Lcy;
    astore 12
L9
    aload 12
    areturn
L20
    new java/lang/StringBuilder
    dup
    invokespecial java/lang/StringBuilder <init>:()V
    ldc "ag.f(" (java.lang.String)
    invokevirtual java/lang/StringBuilder append:(Ljava/lang/String;)Ljava/lang/StringBuilder;
    ldc 41 (java.lang.Integer)
    invokevirtual java/lang/StringBuilder append:(C)Ljava/lang/StringBuilder;
    invokevirtual java/lang/StringBuilder toString:()Ljava/lang/String;
    invokestatic k a:(Ljava/lang/Throwable;Ljava/lang/String;)Lee;
    athrow
