ag g (IIB)Lcr;L1
    aconst_null
    astore 4
    goto L2
L3
    iconst_0
    goto L4
L5
    aload 7
    bipush 45
    iconst_0
    bipush -45
    invokevirtual cr t:(III)V
    goto L6
L7
    aconst_null
    areturn
L8
    iload 6
    iconst_1
    if_icmple L9
    iload 3
    iconst_1
    if_icmpne L10
    new java/lang/IllegalStateException
    dup
    invokespecial java/lang/IllegalStateException <init>:()V
    athrow
L11
    aconst_null
    areturn
L12
    aload 0
    getfield ag am:Z
    istore 5
L13
    iconst_2
    iload 1
    if_icmpne L14
    iload 2
    iconst_3
    if_icmple L14
    iload 5
    ifne L3
    iload 3
    iconst_1
    if_icmpne L15
    new java/lang/IllegalStateException
    dup
    invokespecial java/lang/IllegalStateException <init>:()V
    athrow
L15
    iconst_1
    goto L4
L16
    sipush 128
    ldc -990645675 (java.lang.Integer)
    aload 0
    getfield ag av:I
    imul
    if_icmpeq L17
    iload 3
    iconst_1
    if_icmpne L18
    new java/lang/IllegalStateException
    dup
    invokespecial java/lang/IllegalStateException <init>:()V
    athrow
L2
    aload 0
    getfield ag o:[I
    ifnonnull L19
    iload 3
    iconst_1
    if_icmpne L20
    new java/lang/IllegalStateException
    dup
    invokespecial java/lang/IllegalStateException <init>:()V
    athrow
L14
    aload 0
    getfield ag g:[I
    arraylength
    istore 6
L21
    iconst_0
    istore 7
    goto L22
L23
    aconst_null
    areturn
L20
    iload 1
    bipush 10
    if_icmpeq L24
    goto L7
L25
    iload 5
    ifne L26
    iload 3
    iconst_1
    if_icmpne L27
    new java/lang/IllegalStateException
    dup
    invokespecial java/lang/IllegalStateException <init>:()V
    athrow
L28
    iload 8
    ldc 65536 (java.lang.Integer)
    iadd
    istore 8
L29
    getstatic ag u:Lgr;
    iload 8
    i2l
    invokevirtual gr e:(J)Lgd;
    checkcast cr
    astore 4
L30
    aload 4
    ifnonnull L8
L31
    getstatic ag l:Lfv;
    iload 8
    ldc 65535 (java.lang.Integer)
    iand
    iconst_0
    invokestatic cr e:(Lfv;II)Lcr;
    astore 4
L32
    aconst_null
    aload 4
    if_acmpne L33
    iload 3
    iconst_1
    if_icmpne L34
    new java/lang/IllegalStateException
    dup
    invokespecial java/lang/IllegalStateException <init>:()V
    athrow
L34
    aconst_null
    areturn
L33
    iload 5
    ifeq L35
    iload 3
    iconst_1
    if_icmpne L36
    new java/lang/IllegalStateException
    dup
    invokespecial java/lang/IllegalStateException <init>:()V
    athrow
L36
    aload 4
    invokevirtual cr q:()V
    goto L35
L37
    iload 5
    ifeq L29
    iload 3
    iconst_1
    if_icmpne L28
    new java/lang/IllegalStateException
    dup
    invokespecial java/lang/IllegalStateException <init>:()V
    athrow
L24
    aconst_null
    aload 0
    getfield ag g:[I
    if_acmpne L12
    iload 3
    iconst_1
    if_icmpne L11
    new java/lang/IllegalStateException
    dup
    invokespecial java/lang/IllegalStateException <init>:()V
    athrow
L10
    getstatic ag r:[Lcr;
    iload 7
    aload 4
    aastore
L9
    iinc 7 1
    goto L22
L38
    new cr
    dup
    aload 4
    iload 2
    ifne L26
    iload 3
    iconst_1
    if_icmpne L25
    new java/lang/IllegalStateException
    dup
    invokespecial java/lang/IllegalStateException <init>:()V
    athrow
L39
    new cr
    dup
    getstatic ag r:[Lcr;
    iload 6
    invokespecial cr <init>:([Lcr;I)V
    astore 4
L40
    goto L41
L19
    iconst_m1
    istore 5
L42
    iconst_0
    istore 6
L43
    iload 6
    aload 0
    getfield ag o:[I
    arraylength
    if_icmpge L44
    iload 3
    iconst_1
    if_icmpne L45
    new java/lang/IllegalStateException
    dup
    invokespecial java/lang/IllegalStateException <init>:()V
    athrow
L45
    iload 1
    aload 0
    getfield ag o:[I
    iload 6
    iaload
    if_icmpne L46
    iload 3
    iconst_1
    if_icmpne L47
    new java/lang/IllegalStateException
    dup
    invokespecial java/lang/IllegalStateException <init>:()V
    athrow
L47
    iload 6
    istore 5
L48
    goto L44
L46
    iinc 6 1
    goto L43
L44
    iload 5
    iconst_m1
    if_icmpne L49
    iload 3
    iconst_1
    if_icmpne L23
    new java/lang/IllegalStateException
    dup
    invokespecial java/lang/IllegalStateException <init>:()V
    athrow
L50
    iinc 8 1
    goto L51
L49
    aload 0
    getfield ag g:[I
    iload 5
    iaload
    istore 6
    goto L52
L35
    getstatic ag u:Lgr;
    aload 4
    iload 8
    i2l
    invokevirtual gr l:(Lgd;J)V
    goto L8
L53
    iconst_1
    goto L54
L55
    iconst_0
    goto L56
L54
    ixor
    istore 7
    goto L57
L58
    iconst_0
    goto L54
L59
    iload 6
    ldc 65536 (java.lang.Integer)
    iadd
    istore 6
    goto L60
L61
    getstatic ag u:Lgr;
    aload 4
    iload 6
    i2l
    invokevirtual gr l:(Lgd;J)V
    goto L41
L27
    iload 6
    ifne L26
    iload 3
    iconst_1
    if_icmpne L62
    new java/lang/IllegalStateException
    dup
    invokespecial java/lang/IllegalStateException <init>:()V
    athrow
L63
    getstatic ag l:Lfv;
    iload 6
    ldc 65535 (java.lang.Integer)
    iand
    iconst_0
    invokestatic cr e:(Lfv;II)Lcr;
    astore 4
    goto L64
L62
    iconst_1
    goto L65
L66
    aconst_null
    areturn
L67
    iload 7
    ifeq L61
    iload 3
    iconst_1
    if_icmpne L68
    new java/lang/IllegalStateException
    dup
    invokespecial java/lang/IllegalStateException <init>:()V
    athrow
L68
    aload 4
    invokevirtual cr q:()V
    goto L61
L69
    iconst_0
    istore 8
    goto L51
L4
    istore 5
    goto L14
L70
    aload 7
    ldc 1342994425 (java.lang.Integer)
    aload 0
    getfield ag ay:I
    imul
    ldc -1131729335 (java.lang.Integer)
    aload 0
    getfield ag ag:I
    imul
    aload 0
    getfield ag aj:I
    ldc -490875571 (java.lang.Integer)
    imul
    invokevirtual cr t:(III)V
    goto L71
L72
    iconst_1
    goto L56
L52
    aload 0
    getfield ag am:Z
    iload 2
    iconst_3
    if_icmple L58
    goto L53
L17
    iconst_0
    istore 5
L73
    aload 0
    getfield ag ay:I
    ldc 1342994425 (java.lang.Integer)
    imul
    ifne L74
    iconst_0
    ldc -1131729335 (java.lang.Integer)
    aload 0
    getfield ag ag:I
    imul
    if_icmpne L74
    iload 3
    iconst_1
    if_icmpne L75
    new java/lang/IllegalStateException
    dup
    invokespecial java/lang/IllegalStateException <init>:()V
    athrow
L75
    iconst_0
    ldc -490875571 (java.lang.Integer)
    aload 0
    getfield ag aj:I
    imul
    if_icmpeq L76
    iload 3
    iconst_1
    if_icmpne L74
    new java/lang/IllegalStateException
    dup
    invokespecial java/lang/IllegalStateException <init>:()V
    athrow
L74
    iconst_1
    istore 6
    goto L38
L76
    iconst_0
    istore 6
    goto L38
L57
    iload 7
    ifeq L60
    goto L59
L22
    iload 7
    iload 6
    if_icmpge L77
    iload 3
    iconst_1
    if_icmpne L78
    new java/lang/IllegalStateException
    dup
    invokespecial java/lang/IllegalStateException <init>:()V
    athrow
L60
    getstatic ag u:Lgr;
    iload 6
    i2l
    invokevirtual gr e:(J)Lgd;
    checkcast cr
    astore 4
    goto L79
L80
    aload 0
    getfield ag s:[S
    ifnull L81
    iload 3
    iconst_1
    if_icmpne L82
    new java/lang/IllegalStateException
    dup
    invokespecial java/lang/IllegalStateException <init>:()V
    athrow
L26
    iconst_0
L65
    aconst_null
    aload 0
    getfield ag s:[S
    if_acmpne L83
    iload 3
    iconst_1
    if_icmpne L84
    new java/lang/IllegalStateException
    dup
    invokespecial java/lang/IllegalStateException <init>:()V
    athrow
L84
    iconst_1
    goto L85
L83
    iconst_0
L85
    aconst_null
    aload 0
    getfield ag m:[S
    if_acmpne L55
    iload 3
    iconst_1
    if_icmpne L72
    new java/lang/IllegalStateException
    dup
    invokespecial java/lang/IllegalStateException <init>:()V
    athrow
L77
    iload 6
    iconst_1
    if_icmple L40
    iload 3
    iconst_1
    if_icmpne L39
    new java/lang/IllegalStateException
    dup
    invokespecial java/lang/IllegalStateException <init>:()V
    athrow
L64
    aconst_null
    aload 4
    if_acmpne L67
    goto L66
L56
    iconst_1
    invokespecial cr <init>:(Lcr;ZZZZ)V
    astore 7
L86
    iload 1
    iconst_4
    if_icmpne L6
    iload 3
    iconst_1
    if_icmpne L87
    new java/lang/IllegalStateException
    dup
    invokespecial java/lang/IllegalStateException <init>:()V
    athrow
L87
    iload 2
    iconst_3
    if_icmple L6
    iload 3
    iconst_1
    if_icmpne L88
    new java/lang/IllegalStateException
    dup
    invokespecial java/lang/IllegalStateException <init>:()V
    athrow
L88
    aload 7
    sipush 256
    invokevirtual cr m:(I)V
    goto L5
L71
    aload 7
    areturn
L6
    iload 2
    iconst_3
    iand
    istore 2
L89
    iload 2
    iconst_1
    if_icmpne L90
    iload 3
    iconst_1
    if_icmpne L91
    new java/lang/IllegalStateException
    dup
    invokespecial java/lang/IllegalStateException <init>:()V
    athrow
L91
    aload 7
    invokevirtual cr h:()V
    goto L80
L90
    iload 2
    iconst_2
    if_icmpne L92
    iload 3
    iconst_1
    if_icmpne L93
    new java/lang/IllegalStateException
    dup
    invokespecial java/lang/IllegalStateException <init>:()V
    athrow
L93
    aload 7
    invokevirtual cr s:()V
    goto L80
L92
    iconst_3
    iload 2
    if_icmpne L80
    iload 3
    iconst_1
    if_icmpne L94
    new java/lang/IllegalStateException
    dup
    invokespecial java/lang/IllegalStateException <init>:()V
    athrow
L94
    aload 7
    invokevirtual cr j:()V
    goto L80
L95
    sipush 128
    ldc -407595701 (java.lang.Integer)
    aload 0
    getfield ag ab:I
    imul
    if_icmpne L18
    iload 3
    iconst_1
    if_icmpne L16
    new java/lang/IllegalStateException
    dup
    invokespecial java/lang/IllegalStateException <init>:()V
    athrow
L78
    aload 0
    getfield ag g:[I
    iload 7
    iaload
    istore 8
    goto L37
L96
    iload 8
    aload 0
    getfield ag s:[S
    arraylength
    if_icmpge L81
L97
    aload 7
    aload 0
    getfield ag s:[S
    iload 8
    saload
    aload 0
    getfield ag j:[S
    iload 8
    saload
    invokevirtual cr z:(SS)V
L98
    iinc 8 1
    goto L96
L81
    aconst_null
    aload 0
    getfield ag m:[S
    if_acmpeq L99
    iload 3
    iconst_1
    if_icmpne L69
    new java/lang/IllegalStateException
    dup
    invokespecial java/lang/IllegalStateException <init>:()V
    athrow
L18
    iconst_1
    istore 5
    goto L73
L51
    iload 8
    aload 0
    getfield ag m:[S
    arraylength
    if_icmpge L99
    iload 3
    iconst_1
    if_icmpne L100
    new java/lang/IllegalStateException
    dup
    invokespecial java/lang/IllegalStateException <init>:()V
    athrow
L100
    aload 7
    aload 0
    getfield ag m:[S
    iload 8
    saload
    aload 0
    getfield ag t:[S
    iload 8
    saload
    invokevirtual cr y:(SS)V
    goto L50
L82
    iconst_0
    istore 8
    goto L96
L99
    iload 5
    ifeq L101
    iload 3
    iconst_1
    if_icmpne L102
    new java/lang/IllegalStateException
    dup
    invokespecial java/lang/IllegalStateException <init>:()V
    athrow
L102
    aload 7
    ldc -1134146553 (java.lang.Integer)
    aload 0
    getfield ag ae:I
    imul
    aload 0
    getfield ag ab:I
    ldc -407595701 (java.lang.Integer)
    imul
    aload 0
    getfield ag av:I
    ldc -990645675 (java.lang.Integer)
    imul
    invokevirtual cr d:(III)V
L101
    iload 6
    ifeq L71
    iload 3
    iconst_1
    if_icmpne L70
    new java/lang/IllegalStateException
    dup
    invokespecial java/lang/IllegalStateException <init>:()V
    athrow
L79
    aconst_null
    aload 4
    if_acmpne L41
    iload 3
    iconst_1
    if_icmpne L63
    new java/lang/IllegalStateException
    dup
    invokespecial java/lang/IllegalStateException <init>:()V
    athrow
L41
    aload 0
    getfield ag ae:I
    ldc -1134146553 (java.lang.Integer)
    imul
    sipush 128
    if_icmpne L18
    iload 3
    iconst_1
    if_icmpne L95
    new java/lang/IllegalStateException
    dup
    invokespecial java/lang/IllegalStateException <init>:()V
    athrow
L103
    new java/lang/StringBuilder
    dup
    invokespecial java/lang/StringBuilder <init>:()V
    ldc "ag.g(" (java.lang.String)
    invokevirtual java/lang/StringBuilder append:(Ljava/lang/String;)Ljava/lang/StringBuilder;
    ldc 41 (java.lang.Integer)
    invokevirtual java/lang/StringBuilder append:(C)Ljava/lang/StringBuilder;
    invokevirtual java/lang/StringBuilder toString:()Ljava/lang/String;
    invokestatic k a:(Ljava/lang/Throwable;Ljava/lang/String;)Lee;
    athrow
