ag i (II[[IIIII)Lch;L1
    aload 0
    getfield ag o:[I
    ifnonnull L2
    iload 7
    ldc 1779120208 (java.lang.Integer)
    if_icmpne L3
    new java/lang/IllegalStateException
    dup
    invokespecial java/lang/IllegalStateException <init>:()V
    athrow
L4
    aload 10
    checkcast cr
    invokevirtual cr w:()Lcr;
    astore 10
    goto L5
L6
    aload 11
    astore 10
    goto L7
L8
    getstatic ag w:Lgr;
    lload 8
    invokevirtual gr e:(J)Lgd;
    checkcast ch
    astore 10
L9
    aload 10
    ifnonnull L10
    iload 7
    ldc 1779120208 (java.lang.Integer)
    if_icmpne L11
    new java/lang/IllegalStateException
    dup
    invokespecial java/lang/IllegalStateException <init>:()V
    athrow
L10
    aload 0
    getfield ag n:Z
    ifeq L5
    iload 7
    ldc 1779120208 (java.lang.Integer)
    if_icmpne L4
    new java/lang/IllegalStateException
    dup
    invokespecial java/lang/IllegalStateException <init>:()V
    athrow
L12
    aload 11
    ifnonnull L13
    iload 7
    ldc 1779120208 (java.lang.Integer)
    if_icmpne L14
    new java/lang/IllegalStateException
    dup
    invokespecial java/lang/IllegalStateException <init>:()V
    athrow
L14
    aconst_null
    areturn
L13
    aload 0
    getfield ag n:Z
    ifne L15
    aload 11
    bipush 64
    ldc -683319305 (java.lang.Integer)
    aload 0
    getfield ag ax:I
    imul
    iadd
    aload 0
    getfield ag ap:I
    ldc -1447514299 (java.lang.Integer)
    imul
    sipush 768
    iadd
    bipush -50
    bipush -10
    bipush -50
    invokevirtual cr p:(IIIII)Lcy;
    astore 10
    goto L7
L15
    aload 11
    aload 0
    getfield ag ax:I
    ldc -683319305 (java.lang.Integer)
    imul
    bipush 64
    iadd
    i2s
    putfield cr ab:S
L16
    aload 11
    aload 0
    getfield ag ap:I
    ldc -1447514299 (java.lang.Integer)
    imul
    sipush 768
    iadd
    i2s
    putfield cr av:S
L17
    aload 11
    invokevirtual cr b:()V
    goto L6
L18
    aload 10
    instanceof cy
    ifeq L19
    iload 7
    ldc 1779120208 (java.lang.Integer)
    if_icmpne L20
    new java/lang/IllegalStateException
    dup
    invokespecial java/lang/IllegalStateException <init>:()V
    athrow
L7
    getstatic ag w:Lgr;
    aload 10
    lload 8
    invokevirtual gr l:(Lgd;J)V
    goto L10
L3
    iload 2
    aload 0
    getfield ag f:I
    ldc -840218945 (java.lang.Integer)
    imul
    bipush 10
    ishl
    iadd
    i2l
    lstore 8
    goto L8
L11
    aload 0
    iload 1
    iload 2
    bipush 84
    invokevirtual ag g:(IIB)Lcr;
    astore 11
    goto L12
L5
    aload 0
    getfield ag x:I
    ldc 1931811763 (java.lang.Integer)
    imul
    iflt L21
    iload 7
    ldc 1779120208 (java.lang.Integer)
    if_icmpne L18
    new java/lang/IllegalStateException
    dup
    invokespecial java/lang/IllegalStateException <init>:()V
    athrow
L2
    iload 1
    iconst_3
    ishl
    ldc -840218945 (java.lang.Integer)
    aload 0
    getfield ag f:I
    imul
    bipush 10
    ishl
    iadd
    iload 2
    iadd
    i2l
    lstore 8
    goto L8
L20
    aload 10
    checkcast cy
    aload 3
    iload 4
    iload 5
    iload 6
    iconst_1
    aload 0
    getfield ag x:I
    ldc 1931811763 (java.lang.Integer)
    imul
    invokevirtual cy e:([[IIIIZI)Lcy;
    astore 10
    goto L21
L22
    aload 10
    checkcast cr
    aload 3
    iload 4
    iload 5
    iload 6
    iconst_1
    aload 0
    getfield ag x:I
    ldc 1931811763 (java.lang.Integer)
    imul
    invokevirtual cr g:([[IIIIZI)Lcr;
    astore 10
    goto L21
L19
    aload 10
    instanceof cr
    ifeq L21
    iload 7
    ldc 1779120208 (java.lang.Integer)
    if_icmpne L22
    new java/lang/IllegalStateException
    dup
    invokespecial java/lang/IllegalStateException <init>:()V
    athrow
L21
    aload 10
    areturn
L23
    new java/lang/StringBuilder
    dup
    invokespecial java/lang/StringBuilder <init>:()V
    ldc "ag.i(" (java.lang.String)
    invokevirtual java/lang/StringBuilder append:(Ljava/lang/String;)Ljava/lang/StringBuilder;
    ldc 41 (java.lang.Integer)
    invokevirtual java/lang/StringBuilder append:(C)Ljava/lang/StringBuilder;
    invokevirtual java/lang/StringBuilder toString:()Ljava/lang/String;
    invokestatic k a:(Ljava/lang/Throwable;Ljava/lang/String;)Lee;
    athrow
