ah f (Lcy;II)Lcy;L1
    aload 0
    getfield ah w:[I
    iload 2
    iaload
    istore 4
    goto L2
L3
    iload 2
    aload 0
    getfield ah i:[I
    arraylength
    if_icmpge L4
    iload 3
    ldc -825208733 (java.lang.Integer)
    if_icmpgt L5
    new java/lang/IllegalStateException
    dup
    invokespecial java/lang/IllegalStateException <init>:()V
    athrow
L6
    iload 4
    ldc 65535 (java.lang.Integer)
    iand
    istore 4
    goto L7
L8
    iload 7
    bipush 16
    ishr
    bipush -16
    invokestatic dd g:(IB)Lco;
    astore 6
    goto L9
L10
    aload 1
    aload 5
    iload 4
    ldc -1135201251 (java.lang.Integer)
    invokevirtual co e:(II)Z
    ifne L11
    goto L12
L13
    aconst_null
    astore 6
    goto L14
L7
    aconst_null
    aload 5
    if_acmpne L13
    iload 3
    ldc -825208733 (java.lang.Integer)
    if_icmpgt L15
    new java/lang/IllegalStateException
    dup
    invokespecial java/lang/IllegalStateException <init>:()V
    athrow
L16
    aload 0
    getfield ah i:[I
    ifnull L4
    iload 3
    ldc -825208733 (java.lang.Integer)
    if_icmpgt L3
    new java/lang/IllegalStateException
    dup
    invokespecial java/lang/IllegalStateException <init>:()V
    athrow
L15
    aload 1
    iconst_1
    invokevirtual cy l:(Z)Lcy;
    areturn
L5
    aload 0
    getfield ah i:[I
    iload 2
    iaload
    istore 7
    goto L8
L9
    iload 7
    ldc 65535 (java.lang.Integer)
    iand
    istore 7
    goto L4
L17
    iload 7
    ldc 65535 (java.lang.Integer)
    if_icmpne L18
    iload 3
    ldc -825208733 (java.lang.Integer)
    if_icmpgt L10
    new java/lang/IllegalStateException
    dup
    invokespecial java/lang/IllegalStateException <init>:()V
    athrow
L4
    aload 6
    ifnull L10
    iload 3
    ldc -825208733 (java.lang.Integer)
    if_icmpgt L17
    new java/lang/IllegalStateException
    dup
    invokespecial java/lang/IllegalStateException <init>:()V
    athrow
L19
    aload 8
    aload 5
    iload 4
    invokevirtual cy h:(Lco;I)V
L20
    aload 8
    areturn
L12
    iconst_1
    goto L21
L11
    iconst_0
L21
    invokevirtual cy l:(Z)Lcy;
    astore 8
    goto L19
L2
    iload 4
    bipush 16
    ishr
    bipush -70
    invokestatic dd g:(IB)Lco;
    astore 5
    goto L6
L18
    aload 1
    aload 5
    iload 4
    ldc -1545154166 (java.lang.Integer)
    invokevirtual co e:(II)Z
    ifne L22
    goto L23
L24
    aload 8
    aload 6
    iload 7
    invokevirtual cy h:(Lco;I)V
    goto L25
L14
    iconst_0
    istore 7
    goto L16
L22
    iconst_0
L26
    aload 6
    iload 7
    ldc -1927396761 (java.lang.Integer)
    invokevirtual co e:(II)Z
    ifne L27
    iload 3
    ldc -825208733 (java.lang.Integer)
    if_icmpgt L28
    new java/lang/IllegalStateException
    dup
    invokespecial java/lang/IllegalStateException <init>:()V
    athrow
L28
    iconst_1
    goto L29
L27
    iconst_0
L29
    iand
    invokevirtual cy l:(Z)Lcy;
    astore 8
L30
    aload 8
    aload 5
    iload 4
    invokevirtual cy h:(Lco;I)V
    goto L24
L23
    iconst_1
    goto L26
L25
    aload 8
    areturn
L31
    new java/lang/StringBuilder
    dup
    invokespecial java/lang/StringBuilder <init>:()V
    ldc "ah.f(" (java.lang.String)
    invokevirtual java/lang/StringBuilder append:(Ljava/lang/String;)Ljava/lang/StringBuilder;
    ldc 41 (java.lang.Integer)
    invokevirtual java/lang/StringBuilder append:(C)Ljava/lang/StringBuilder;
    invokevirtual java/lang/StringBuilder toString:()Ljava/lang/String;
    invokestatic k a:(Ljava/lang/Throwable;Ljava/lang/String;)Lee;
    athrow
