ah l (Ldh;II)VL1
    iconst_1
    iload 2
    if_icmpne L2
    iload 3
    ldc 934809294 (java.lang.Integer)
    if_icmpgt L3
    new java/lang/IllegalStateException
    dup
    invokespecial java/lang/IllegalStateException <init>:()V
    athrow
L4
    iconst_0
    istore 5
    goto L5
L6
    aload 0
    getfield ah f:[I
    iload 5
    aload 1
    ldc -1960712849 (java.lang.Integer)
    invokevirtual dh b:(I)I
    iastore
    iinc 5 1
    goto L7
L8
    iload 5
    iload 4
    if_icmpge L9
    iload 3
    ldc 934809294 (java.lang.Integer)
    if_icmpgt L10
    new java/lang/IllegalStateException
    dup
    invokespecial java/lang/IllegalStateException <init>:()V
    athrow
L11
    aload 0
    getfield ah w:[I
    iload 5
    aload 1
    ldc -1875389281 (java.lang.Integer)
    invokevirtual dh q:(I)I
    iastore
    iinc 5 1
    goto L12
L10
    aload 0
    getfield ah r:[I
    iload 5
    aload 1
    ldc 1620284670 (java.lang.Integer)
    invokevirtual dh q:(I)I
    iastore
    iinc 5 1
    goto L8
L9
    aload 0
    iload 4
    newarray 10
    putfield ah w:[I
L13
    iconst_0
    istore 5
L12
    iload 5
    iload 4
    if_icmpge L14
    iload 3
    ldc 934809294 (java.lang.Integer)
    if_icmpgt L11
    return
L15
    aload 0
    getfield ah i:[I
    iload 5
    aload 1
    ldc -733482633 (java.lang.Integer)
    invokevirtual dh q:(I)I
    iastore
    iinc 5 1
    goto L16
L17
    aload 0
    aload 1
    ldc 1160217385 (java.lang.Integer)
    invokevirtual dh z:(I)I
    ldc -756774745 (java.lang.Integer)
    imul
    putfield ah z:I
    goto L18
L19
    iload 5
    iload 4
    if_icmpge L20
    iload 3
    ldc 934809294 (java.lang.Integer)
    if_icmpgt L21
    new java/lang/IllegalStateException
    dup
    invokespecial java/lang/IllegalStateException <init>:()V
    athrow
L21
    aload 0
    getfield ah w:[I
    iload 5
    aload 1
    ldc 618670008 (java.lang.Integer)
    invokevirtual dh q:(I)I
    bipush 16
    ishl
    aload 0
    getfield ah w:[I
    iload 5
    iaload
    iadd
    iastore
    iinc 5 1
    goto L19
L20
    goto L18
L2
    iload 2
    iconst_2
    if_icmpne L22
    iload 3
    ldc 934809294 (java.lang.Integer)
    if_icmpgt L23
    new java/lang/IllegalStateException
    dup
    invokespecial java/lang/IllegalStateException <init>:()V
    athrow
L23
    aload 0
    aload 1
    ldc -403291904 (java.lang.Integer)
    invokevirtual dh q:(I)I
    ldc 1694530661 (java.lang.Integer)
    imul
    putfield ah g:I
    goto L18
L24
    aload 0
    iload 4
    iconst_1
    iadd
    newarray 10
    putfield ah o:[I
    goto L4
L25
    aload 1
    ldc 835401572 (java.lang.Integer)
    invokevirtual dh z:(I)I
    istore 4
    goto L24
L3
    aload 1
    ldc 867679927 (java.lang.Integer)
    invokevirtual dh q:(I)I
    istore 4
    goto L26
L22
    iconst_3
    iload 2
    if_icmpne L27
    goto L25
L28
    aload 0
    getfield ah o:[I
    iload 4
    ldc 9999999 (java.lang.Integer)
    iastore
    goto L29
L30
    iconst_0
    istore 5
    goto L8
L31
    aload 0
    getfield ah o:[I
    iload 5
    aload 1
    ldc 1774994772 (java.lang.Integer)
    invokevirtual dh z:(I)I
    iastore
    iinc 5 1
    goto L5
L29
    goto L18
L32
    aload 0
    aload 1
    ldc 638456006 (java.lang.Integer)
    invokevirtual dh z:(I)I
    ldc -1039290891 (java.lang.Integer)
    imul
    putfield ah q:I
    goto L18
L33
    aload 0
    iconst_1
    putfield ah h:Z
    goto L18
L34
    iconst_0
    istore 5
    goto L35
L36
    aload 0
    aload 1
    ldc 1580966981 (java.lang.Integer)
    invokevirtual dh z:(I)I
    ldc 683108359 (java.lang.Integer)
    imul
    putfield ah s:I
    goto L18
L37
    iload 2
    bipush 6
    if_icmpne L38
    aload 0
    aload 1
    ldc -446608854 (java.lang.Integer)
    invokevirtual dh q:(I)I
    ldc 292869967 (java.lang.Integer)
    imul
    putfield ah j:I
    goto L18
L38
    bipush 7
    iload 2
    if_icmpne L39
    iload 3
    ldc 934809294 (java.lang.Integer)
    if_icmpgt L40
    new java/lang/IllegalStateException
    dup
    invokespecial java/lang/IllegalStateException <init>:()V
    athrow
L40
    aload 0
    aload 1
    ldc -237359882 (java.lang.Integer)
    invokevirtual dh q:(I)I
    ldc -388330813 (java.lang.Integer)
    imul
    putfield ah m:I
    goto L18
L39
    bipush 8
    iload 2
    if_icmpne L41
    iload 3
    ldc 934809294 (java.lang.Integer)
    if_icmpgt L42
    new java/lang/IllegalStateException
    dup
    invokespecial java/lang/IllegalStateException <init>:()V
    athrow
L42
    aload 0
    aload 1
    ldc 685869663 (java.lang.Integer)
    invokevirtual dh z:(I)I
    ldc -2127940289 (java.lang.Integer)
    imul
    putfield ah t:I
    goto L18
L41
    bipush 9
    iload 2
    if_icmpne L43
    goto L17
L26
    aload 0
    iload 4
    newarray 10
    putfield ah r:[I
    goto L30
L43
    bipush 10
    iload 2
    if_icmpne L44
    iload 3
    ldc 934809294 (java.lang.Integer)
    if_icmpgt L45
    return
L35
    iload 5
    iload 4
    if_icmpge L46
    goto L47
L44
    iload 2
    bipush 11
    if_icmpne L48
    iload 3
    ldc 934809294 (java.lang.Integer)
    if_icmpgt L32
    new java/lang/IllegalStateException
    dup
    invokespecial java/lang/IllegalStateException <init>:()V
    athrow
L45
    aload 0
    aload 1
    ldc 1712080803 (java.lang.Integer)
    invokevirtual dh z:(I)I
    ldc -83817459 (java.lang.Integer)
    imul
    putfield ah y:I
    goto L18
L48
    bipush 12
    iload 2
    if_icmpne L49
    iload 3
    ldc 934809294 (java.lang.Integer)
    if_icmpgt L50
    new java/lang/IllegalStateException
    dup
    invokespecial java/lang/IllegalStateException <init>:()V
    athrow
L50
    aload 1
    ldc 1222988898 (java.lang.Integer)
    invokevirtual dh z:(I)I
    istore 4
L51
    aload 0
    iload 4
    newarray 10
    putfield ah i:[I
L52
    iconst_0
    istore 5
L16
    iload 5
    iload 4
    if_icmpge L34
    iload 3
    ldc 934809294 (java.lang.Integer)
    if_icmpgt L15
    new java/lang/IllegalStateException
    dup
    invokespecial java/lang/IllegalStateException <init>:()V
    athrow
L53
    iconst_5
    iload 2
    if_icmpne L37
    iload 3
    ldc 934809294 (java.lang.Integer)
    if_icmpgt L36
    new java/lang/IllegalStateException
    dup
    invokespecial java/lang/IllegalStateException <init>:()V
    athrow
L14
    iconst_0
    istore 5
    goto L19
L54
    aload 0
    iload 4
    newarray 10
    putfield ah f:[I
    goto L55
L47
    aload 0
    getfield ah i:[I
    iload 5
    aload 1
    ldc 1740733773 (java.lang.Integer)
    invokevirtual dh q:(I)I
    bipush 16
    ishl
    aload 0
    getfield ah i:[I
    iload 5
    iaload
    iadd
    iastore
    iinc 5 1
    goto L35
L46
    goto L18
L49
    bipush 13
    iload 2
    if_icmpne L18
    iload 3
    ldc 934809294 (java.lang.Integer)
    if_icmpgt L56
    new java/lang/IllegalStateException
    dup
    invokespecial java/lang/IllegalStateException <init>:()V
    athrow
L56
    aload 1
    ldc 1393163562 (java.lang.Integer)
    invokevirtual dh z:(I)I
    istore 4
    goto L54
L5
    iload 5
    iload 4
    if_icmpge L28
    iload 3
    ldc 934809294 (java.lang.Integer)
    if_icmpgt L31
    return
L55
    iconst_0
    istore 5
L7
    iload 5
    iload 4
    if_icmpge L18
    iload 3
    ldc 934809294 (java.lang.Integer)
    if_icmpgt L6
    new java/lang/IllegalStateException
    dup
    invokespecial java/lang/IllegalStateException <init>:()V
    athrow
L27
    iload 2
    iconst_4
    if_icmpne L53
    iload 3
    ldc 934809294 (java.lang.Integer)
    if_icmpgt L33
    new java/lang/IllegalStateException
    dup
    invokespecial java/lang/IllegalStateException <init>:()V
    athrow
L18
    return
L57
    new java/lang/StringBuilder
    dup
    invokespecial java/lang/StringBuilder <init>:()V
    ldc "ah.l(" (java.lang.String)
    invokevirtual java/lang/StringBuilder append:(Ljava/lang/String;)Ljava/lang/StringBuilder;
    ldc 41 (java.lang.Integer)
    invokevirtual java/lang/StringBuilder append:(C)Ljava/lang/StringBuilder;
    invokevirtual java/lang/StringBuilder toString:()Ljava/lang/String;
    invokestatic k a:(Ljava/lang/Throwable;Ljava/lang/String;)Lee;
    athrow
