ai at (Lab;IIIIIB)VL1
    aload 0
    ifnull L2
    iload 6
    bipush 9
    if_icmplt L3
    new java/lang/IllegalStateException
    dup
    invokespecial java/lang/IllegalStateException <init>:()V
    athrow
L4
    iload 1
    getstatic client hr:I
    ldc 308668811 (java.lang.Integer)
    imul
    if_icmpge L5
    iload 6
    bipush 9
    if_icmplt L6
    new java/lang/IllegalStateException
    dup
    invokespecial java/lang/IllegalStateException <init>:()V
    athrow
L7
    getstatic n cl:Lhh;
    aload 0
    getfield ab at:[I
    iload 7
    iaload
    invokestatic java/lang/Integer toString:(I)Ljava/lang/String;
    getstatic client gh:I
    ldc 1273855029 (java.lang.Integer)
    imul
    iload 2
    iadd
    iconst_1
    isub
    getstatic client gi:I
    ldc 1995677465 (java.lang.Integer)
    imul
    iload 3
    iadd
    iconst_3
    iadd
    ldc 16777215 (java.lang.Integer)
    iconst_0
    invokevirtual hh o:(Ljava/lang/String;IIII)V
    goto L8
L9
    aload 0
    getfield ab aq:I
    ldc -1246048179 (java.lang.Integer)
    imul
    ifle L10
    iload 6
    bipush 9
    if_icmplt L11
    new java/lang/IllegalStateException
    dup
    invokespecial java/lang/IllegalStateException <init>:()V
    athrow
L12
    aload 0
    checkcast am
    getfield am e:Lay;
    astore 7
L13
    aload 7
    getfield ay aw:[I
    ifnull L14
    iload 6
    bipush 9
    if_icmplt L15
    return
L15
    aload 7
    ldc -835234631 (java.lang.Integer)
    invokevirtual ay i:(I)Lay;
    astore 7
L14
    aload 7
    ifnonnull L4
    iload 6
    bipush 9
    if_icmplt L16
    new java/lang/IllegalStateException
    dup
    invokespecial java/lang/IllegalStateException <init>:()V
    athrow
L16
    return
L3
    aload 0
    ldc 1465666791 (java.lang.Integer)
    invokevirtual ab l:(I)Z
    ifne L17
    iload 6
    bipush 9
    if_icmplt L2
    new java/lang/IllegalStateException
    dup
    invokespecial java/lang/IllegalStateException <init>:()V
    athrow
L6
    bipush 30
    istore 7
    goto L18
L19
    aload 8
    getfield l l:I
    ldc 1543628041 (java.lang.Integer)
    imul
    iconst_m1
    if_icmpne L20
    iload 6
    bipush 9
    if_icmplt L21
    new java/lang/IllegalStateException
    dup
    invokespecial java/lang/IllegalStateException <init>:()V
    athrow
L22
    aload 8
    getfield l d:Z
    ifeq L19
    return
L23
    getstatic client am:I
    ldc -1416594727 (java.lang.Integer)
    imul
    getstatic client cb:[I
    iload 1
    ldc 308668811 (java.lang.Integer)
    getstatic client hr:I
    imul
    isub
    iaload
    if_icmpne L24
    goto L25
L21
    aload 8
    getfield l c:I
    ldc 1990806809 (java.lang.Integer)
    imul
    iconst_m1
    if_icmpeq L26
    iload 6
    bipush 9
    if_icmplt L20
    new java/lang/IllegalStateException
    dup
    invokespecial java/lang/IllegalStateException <init>:()V
    athrow
L20
    aload 0
    ldc -1952356685 (java.lang.Integer)
    aload 0
    getfield ab bi:I
    imul
    bipush 15
    iadd
    bipush 6
    invokestatic fe al:(Lab;IB)V
    goto L27
L28
    aload 0
    bipush 15
    aload 0
    getfield ab bi:I
    ldc -1952356685 (java.lang.Integer)
    imul
    iadd
    bipush 6
    invokestatic fe al:(Lab;IB)V
    goto L29
L30
    aload 8
    getfield l l:I
    ldc 1543628041 (java.lang.Integer)
    imul
    iconst_m1
    if_icmpeq L31
    iload 6
    bipush 9
    if_icmplt L32
    new java/lang/IllegalStateException
    dup
    invokespecial java/lang/IllegalStateException <init>:()V
    athrow
L32
    getstatic m em:[Lbh;
    ldc 1543628041 (java.lang.Integer)
    aload 8
    getfield l l:I
    imul
    aaload
    iload 2
    getstatic client gh:I
    ldc 1273855029 (java.lang.Integer)
    imul
    iadd
    bipush 12
    isub
    getstatic client gi:I
    ldc 1995677465 (java.lang.Integer)
    imul
    iload 3
    iadd
    iload 7
    isub
    invokevirtual bh h:(II)V
    goto L33
L34
    getstatic client gi:I
    ldc -287505510 (java.lang.Integer)
    isub
    putstatic client gi:I
    goto L35
L36
    getstatic client gg:[I
    ldc 168556945 (java.lang.Integer)
    getstatic client fm:I
    imul
    ldc -983705973 (java.lang.Integer)
    aload 0
    getfield ab ay:I
    imul
    iastore
    goto L37
L38
    getstatic cd ea:[Lbh;
    ldc 1990806809 (java.lang.Integer)
    aload 8
    getfield l c:I
    imul
    aaload
    iload 2
    ldc 1273855029 (java.lang.Integer)
    getstatic client gh:I
    imul
    iadd
    bipush 12
    isub
    iload 3
    ldc 1995677465 (java.lang.Integer)
    getstatic client gi:I
    imul
    iadd
    iload 7
    isub
    invokevirtual bh h:(II)V
L39
    iinc 7 25
L26
    iload 1
    iflt L40
    iload 6
    bipush 9
    if_icmplt L41
    new java/lang/IllegalStateException
    dup
    invokespecial java/lang/IllegalStateException <init>:()V
    athrow
L41
    ldc 577949343 (java.lang.Integer)
    getstatic client aw:I
    imul
    bipush 10
    if_icmpne L40
    iload 6
    bipush 9
    if_icmplt L42
    new java/lang/IllegalStateException
    dup
    invokespecial java/lang/IllegalStateException <init>:()V
    athrow
L42
    getstatic client au:I
    ldc 72113091 (java.lang.Integer)
    imul
    getstatic client hw:[I
    iload 1
    iaload
    if_icmpne L40
    iload 6
    bipush 9
    if_icmplt L43
    new java/lang/IllegalStateException
    dup
    invokespecial java/lang/IllegalStateException <init>:()V
    athrow
L44
    aload 7
    getfield ay ao:I
    ldc 1555160611 (java.lang.Integer)
    imul
    getstatic cd ea:[Lbh;
    arraylength
    if_icmpge L45
    iload 6
    bipush 9
    if_icmplt L28
    new java/lang/IllegalStateException
    dup
    invokespecial java/lang/IllegalStateException <init>:()V
    athrow
L46
    getstatic client gh:I
    ldc 1273855029 (java.lang.Integer)
    imul
    iconst_m1
    if_icmple L40
    iload 6
    bipush 9
    if_icmplt L47
    new java/lang/IllegalStateException
    dup
    invokespecial java/lang/IllegalStateException <init>:()V
    athrow
L47
    getstatic u es:[Lbh;
    iconst_1
    aaload
    iload 2
    ldc 1273855029 (java.lang.Integer)
    getstatic client gh:I
    imul
    iadd
    bipush 12
    isub
    ldc 1995677465 (java.lang.Integer)
    getstatic client gi:I
    imul
    iload 3
    iadd
    iload 7
    isub
    invokevirtual bh h:(II)V
    goto L40
L35
    iload 7
    iconst_3
    if_icmpne L48
    iload 6
    bipush 9
    if_icmplt L49
    new java/lang/IllegalStateException
    dup
    invokespecial java/lang/IllegalStateException <init>:()V
    athrow
L50
    iconst_4
    ldc -465280765 (java.lang.Integer)
    getstatic client lo:I
    imul
    if_icmpeq L51
    iload 6
    bipush 9
    if_icmplt L52
    new java/lang/IllegalStateException
    dup
    invokespecial java/lang/IllegalStateException <init>:()V
    athrow
L53
    aload 7
    getfield ay aw:[I
    ifnull L54
    iload 6
    bipush 9
    if_icmplt L55
    new java/lang/IllegalStateException
    dup
    invokespecial java/lang/IllegalStateException <init>:()V
    athrow
L55
    aload 7
    ldc -1016617148 (java.lang.Integer)
    invokevirtual ay i:(I)Lay;
    astore 7
    goto L54
L5
    aload 0
    checkcast am
    getfield am e:Lay;
    astore 7
    goto L53
L33
    iinc 7 25
    goto L31
L29
    getstatic client gh:I
    ldc 1273855029 (java.lang.Integer)
    imul
    iconst_m1
    if_icmple L45
    iload 6
    bipush 9
    if_icmplt L56
    new java/lang/IllegalStateException
    dup
    invokespecial java/lang/IllegalStateException <init>:()V
    athrow
L57
    getstatic client fn:[I
    ldc 168556945 (java.lang.Integer)
    getstatic client fm:I
    imul
    getstatic hg cn:Lhh;
    getfield hh i:I
    iastore
    goto L58
L56
    getstatic cd ea:[Lbh;
    aload 7
    getfield ay ao:I
    ldc 1555160611 (java.lang.Integer)
    imul
    aaload
    ldc 1273855029 (java.lang.Integer)
    getstatic client gh:I
    imul
    iload 2
    iadd
    bipush 12
    isub
    iload 3
    ldc 1995677465 (java.lang.Integer)
    getstatic client gi:I
    imul
    iadd
    bipush 30
    isub
    invokevirtual bh h:(II)V
L45
    ldc 577949343 (java.lang.Integer)
    getstatic client aw:I
    imul
    iconst_1
    if_icmpne L24
    iload 6
    bipush 9
    if_icmplt L23
    return
L2
    return
L59
    getstatic client gi:I
    ldc -575011020 (java.lang.Integer)
    isub
    putstatic client gi:I
    goto L60
L24
    aconst_null
    aload 0
    getfield ab ae:Ljava/lang/String;
    if_acmpeq L61
    iload 6
    bipush 9
    if_icmplt L62
    new java/lang/IllegalStateException
    dup
    invokespecial java/lang/IllegalStateException <init>:()V
    athrow
L63
    aload 0
    aload 0
    getfield ab bi:I
    ldc -1952356685 (java.lang.Integer)
    imul
    iconst_2
    idiv
    bipush 6
    invokestatic fe al:(Lab;IB)V
    goto L64
L65
    getstatic u es:[Lbh;
    iconst_0
    aaload
    getstatic client gh:I
    ldc 1273855029 (java.lang.Integer)
    imul
    iload 2
    iadd
    bipush 12
    isub
    iload 3
    getstatic client gi:I
    ldc 1995677465 (java.lang.Integer)
    imul
    iadd
    bipush 28
    isub
    invokevirtual bh h:(II)V
    goto L24
L66
    getstatic client gi:I
    ldc -287505510 (java.lang.Integer)
    isub
    putstatic client gi:I
    goto L48
L62
    iload 1
    getstatic client hr:I
    ldc 308668811 (java.lang.Integer)
    imul
    if_icmpge L51
    goto L67
L27
    getstatic client gh:I
    ldc 1273855029 (java.lang.Integer)
    imul
    iconst_m1
    if_icmple L26
    iload 6
    bipush 9
    if_icmplt L30
    return
L17
    aload 0
    instanceof am
    ifeq L4
    goto L12
L52
    aload 0
    getfield ab ab:Z
    ifne L61
    iload 6
    bipush 9
    if_icmplt L68
    return
L69
    iload 7
    iconst_4
    if_icmpge L70
    iload 6
    bipush 9
    if_icmplt L71
    return
L72
    getstatic client lo:I
    ldc -465280765 (java.lang.Integer)
    imul
    iconst_3
    if_icmpeq L51
    goto L73
L51
    aload 0
    aload 0
    getfield ab bi:I
    ldc -1952356685 (java.lang.Integer)
    imul
    bipush 6
    invokestatic fe al:(Lab;IB)V
    goto L74
L75
    aload 0
    checkcast l
    getfield l e:Ljava/lang/String;
    iconst_0
    ldc -810037741 (java.lang.Integer)
    invokestatic w dc:(Ljava/lang/String;ZI)Z
    ifeq L61
    iload 6
    bipush 9
    if_icmplt L51
    new java/lang/IllegalStateException
    dup
    invokespecial java/lang/IllegalStateException <init>:()V
    athrow
L73
    getstatic client lo:I
    ldc -465280765 (java.lang.Integer)
    imul
    iconst_1
    if_icmpne L61
    iload 6
    bipush 9
    if_icmplt L75
    new java/lang/IllegalStateException
    dup
    invokespecial java/lang/IllegalStateException <init>:()V
    athrow
L74
    ldc 1273855029 (java.lang.Integer)
    getstatic client gh:I
    imul
    iconst_m1
    if_icmple L61
    iload 6
    bipush 9
    if_icmplt L76
    new java/lang/IllegalStateException
    dup
    invokespecial java/lang/IllegalStateException <init>:()V
    athrow
L76
    getstatic client fm:I
    ldc 168556945 (java.lang.Integer)
    imul
    ldc -566421135 (java.lang.Integer)
    getstatic client fi:I
    imul
    if_icmpge L61
L77
    getstatic client fs:[I
    getstatic client fm:I
    ldc 168556945 (java.lang.Integer)
    imul
    getstatic hg cn:Lhh;
    aload 0
    getfield ab ae:Ljava/lang/String;
    invokevirtual hh c:(Ljava/lang/String;)I
    iconst_2
    idiv
    iastore
    goto L57
L70
    return
L58
    getstatic client ft:[I
    getstatic client fm:I
    ldc 168556945 (java.lang.Integer)
    imul
    getstatic client gh:I
    ldc 1273855029 (java.lang.Integer)
    imul
    iastore
L78
    getstatic client fa:[I
    ldc 168556945 (java.lang.Integer)
    getstatic client fm:I
    imul
    getstatic client gi:I
    ldc 1995677465 (java.lang.Integer)
    imul
    iastore
L79
    getstatic client gr:[I
    getstatic client fm:I
    ldc 168556945 (java.lang.Integer)
    imul
    ldc 252935655 (java.lang.Integer)
    aload 0
    getfield ab ag:I
    imul
    iastore
L80
    getstatic client gq:[I
    ldc 168556945 (java.lang.Integer)
    getstatic client fm:I
    imul
    ldc -1085867599 (java.lang.Integer)
    aload 0
    getfield ab aj:I
    imul
    iastore
    goto L36
L67
    aload 0
    getfield ab av:Z
    ifne L61
    iload 6
    bipush 9
    if_icmplt L50
    new java/lang/IllegalStateException
    dup
    invokespecial java/lang/IllegalStateException <init>:()V
    athrow
L37
    getstatic client gf:[Ljava/lang/String;
    getstatic client fm:I
    ldc 168556945 (java.lang.Integer)
    imul
    aload 0
    getfield ab ae:Ljava/lang/String;
    aastore
L81
    getstatic client fm:I
    ldc -541726863 (java.lang.Integer)
    iadd
    putstatic client fm:I
L61
    ldc 94507795 (java.lang.Integer)
    aload 0
    getfield ab ar:I
    imul
    ldc -117546507 (java.lang.Integer)
    getstatic client b:I
    imul
    if_icmple L82
    iload 6
    bipush 9
    if_icmplt L83
    new java/lang/IllegalStateException
    dup
    invokespecial java/lang/IllegalStateException <init>:()V
    athrow
L25
    getstatic client b:I
    ldc -117546507 (java.lang.Integer)
    imul
    bipush 20
    irem
    bipush 10
    if_icmpge L24
    iload 6
    bipush 9
    if_icmplt L84
    return
L85
    ldc 1273855029 (java.lang.Integer)
    getstatic client gh:I
    imul
    iconst_m1
    if_icmple L82
    iload 6
    bipush 9
    if_icmplt L86
    return
L86
    iload 1
    ldc 308668811 (java.lang.Integer)
    getstatic client hr:I
    imul
    if_icmpge L87
    iload 6
    bipush 9
    if_icmplt L88
    new java/lang/IllegalStateException
    dup
    invokespecial java/lang/IllegalStateException <init>:()V
    athrow
L88
    bipush 30
    istore 7
    goto L89
L87
    aload 0
    checkcast am
    getfield am e:Lay;
    astore 8
L90
    aload 8
    getfield ay ay:I
    ldc 1261320223 (java.lang.Integer)
    imul
    istore 7
L89
    aload 0
    getfield ab aq:I
    ldc -1246048179 (java.lang.Integer)
    imul
    iload 7
    imul
    aload 0
    getfield ab ac:I
    ldc 1064445695 (java.lang.Integer)
    imul
    idiv
    istore 8
L91
    iload 8
    iload 7
    if_icmple L92
    iload 6
    bipush 9
    if_icmplt L93
    new java/lang/IllegalStateException
    dup
    invokespecial java/lang/IllegalStateException <init>:()V
    athrow
L93
    iload 7
    istore 8
    goto L10
L92
    iconst_0
    iload 8
    if_icmpne L10
    iload 6
    bipush 9
    if_icmplt L9
    new java/lang/IllegalStateException
    dup
    invokespecial java/lang/IllegalStateException <init>:()V
    athrow
L94
    getstatic client gh:I
    ldc 1273855029 (java.lang.Integer)
    imul
    iconst_m1
    if_icmple L24
    iload 6
    bipush 9
    if_icmplt L65
    new java/lang/IllegalStateException
    dup
    invokespecial java/lang/IllegalStateException <init>:()V
    athrow
L11
    iconst_1
    istore 8
L10
    ldc 1273855029 (java.lang.Integer)
    getstatic client gh:I
    imul
    iload 2
    iadd
    iload 7
    iconst_2
    idiv
    isub
    iload 3
    getstatic client gi:I
    ldc 1995677465 (java.lang.Integer)
    imul
    iadd
    iconst_3
    isub
    iload 8
    iconst_5
    ldc 65280 (java.lang.Integer)
    invokestatic bt cs:(IIIII)V
L95
    iload 8
    ldc 1273855029 (java.lang.Integer)
    getstatic client gh:I
    imul
    iload 2
    iadd
    iload 7
    iconst_2
    idiv
    isub
    iadd
    iload 3
    getstatic client gi:I
    ldc 1995677465 (java.lang.Integer)
    imul
    iadd
    iconst_3
    isub
    iload 7
    iload 8
    isub
    iconst_5
    ldc 16711680 (java.lang.Integer)
    invokestatic bt cs:(IIIII)V
L82
    iconst_0
    istore 7
    goto L69
L54
    aload 7
    getfield ay ao:I
    ldc 1555160611 (java.lang.Integer)
    imul
    iflt L45
    iload 6
    bipush 9
    if_icmplt L44
    new java/lang/IllegalStateException
    dup
    invokespecial java/lang/IllegalStateException <init>:()V
    athrow
L71
    aload 0
    getfield ab ak:[I
    iload 7
    iaload
    getstatic client b:I
    ldc -117546507 (java.lang.Integer)
    imul
    if_icmple L8
    iload 6
    bipush 9
    if_icmplt L63
    new java/lang/IllegalStateException
    dup
    invokespecial java/lang/IllegalStateException <init>:()V
    athrow
L84
    aload 0
    bipush 15
    aload 0
    getfield ab bi:I
    ldc -1952356685 (java.lang.Integer)
    imul
    iadd
    bipush 6
    invokestatic fe al:(Lab;IB)V
    goto L94
L64
    ldc 1273855029 (java.lang.Integer)
    getstatic client gh:I
    imul
    iconst_m1
    if_icmple L8
    iload 6
    bipush 9
    if_icmplt L96
    new java/lang/IllegalStateException
    dup
    invokespecial java/lang/IllegalStateException <init>:()V
    athrow
L96
    iconst_1
    iload 7
    if_icmpne L60
    iload 6
    bipush 9
    if_icmplt L59
    return
L43
    aload 0
    ldc -1952356685 (java.lang.Integer)
    aload 0
    getfield ab bi:I
    imul
    bipush 15
    iadd
    bipush 6
    invokestatic fe al:(Lab;IB)V
    goto L46
L60
    iload 7
    iconst_2
    if_icmpne L35
    iload 6
    bipush 9
    if_icmplt L97
    new java/lang/IllegalStateException
    dup
    invokespecial java/lang/IllegalStateException <init>:()V
    athrow
L97
    getstatic client gh:I
    ldc 2129161139 (java.lang.Integer)
    isub
    putstatic client gh:I
    goto L34
L83
    aload 0
    aload 0
    getfield ab bi:I
    ldc -1952356685 (java.lang.Integer)
    imul
    bipush 15
    iadd
    bipush 6
    invokestatic fe al:(Lab;IB)V
    goto L85
L68
    iconst_0
    getstatic client lo:I
    ldc -465280765 (java.lang.Integer)
    imul
    if_icmpeq L51
    iload 6
    bipush 9
    if_icmplt L72
    return
L49
    getstatic client gh:I
    ldc 2129161139 (java.lang.Integer)
    iadd
    putstatic client gh:I
    goto L66
L18
    aload 0
    checkcast l
    astore 8
    goto L22
L48
    getstatic k ek:[Lbh;
    aload 0
    getfield ab al:[I
    iload 7
    iaload
    aaload
    iload 2
    ldc 1273855029 (java.lang.Integer)
    getstatic client gh:I
    imul
    iadd
    bipush 12
    isub
    iload 3
    getstatic client gi:I
    ldc 1995677465 (java.lang.Integer)
    imul
    iadd
    bipush 12
    isub
    invokevirtual bh h:(II)V
    goto L7
L31
    iconst_m1
    aload 8
    getfield l c:I
    ldc 1990806809 (java.lang.Integer)
    imul
    if_icmpeq L26
    iload 6
    bipush 9
    if_icmplt L38
    new java/lang/IllegalStateException
    dup
    invokespecial java/lang/IllegalStateException <init>:()V
    athrow
L8
    iinc 7 1
    goto L69
L40
    goto L24
L98
    new java/lang/StringBuilder
    dup
    invokespecial java/lang/StringBuilder <init>:()V
    ldc "ai.at(" (java.lang.String)
    invokevirtual java/lang/StringBuilder append:(Ljava/lang/String;)Ljava/lang/StringBuilder;
    ldc 41 (java.lang.Integer)
    invokevirtual java/lang/StringBuilder append:(C)Ljava/lang/StringBuilder;
    invokevirtual java/lang/StringBuilder toString:()Ljava/lang/String;
    invokestatic k a:(Ljava/lang/Throwable;Ljava/lang/String;)Lee;
    athrow
