aj bw (IIIII)VL1
    iconst_0
    istore 5
    goto L2
L3
    return
L4
    getstatic client lb:[Z
    iload 5
    iconst_1
    bastore
    goto L5
L6
    getstatic client lf:[I
    iload 5
    iaload
    iload 0
    iload 2
    iadd
    if_icmpge L5
    iload 4
    ldc -1651506497 (java.lang.Integer)
    if_icmplt L7
    new java/lang/IllegalStateException
    dup
    invokespecial java/lang/IllegalStateException <init>:()V
    athrow
L7
    getstatic client ln:[I
    iload 5
    iaload
    getstatic client lm:[I
    iload 5
    iaload
    iadd
    iload 1
    if_icmple L5
    iload 4
    ldc -1651506497 (java.lang.Integer)
    if_icmplt L8
    new java/lang/IllegalStateException
    dup
    invokespecial java/lang/IllegalStateException <init>:()V
    athrow
L2
    iload 5
    ldc -2129577205 (java.lang.Integer)
    getstatic client lv:I
    imul
    if_icmpge L3
    iload 4
    ldc -1651506497 (java.lang.Integer)
    if_icmplt L9
    new java/lang/IllegalStateException
    dup
    invokespecial java/lang/IllegalStateException <init>:()V
    athrow
L8
    getstatic client ln:[I
    iload 5
    iaload
    iload 1
    iload 3
    iadd
    if_icmpge L5
    iload 4
    ldc -1651506497 (java.lang.Integer)
    if_icmplt L4
    new java/lang/IllegalStateException
    dup
    invokespecial java/lang/IllegalStateException <init>:()V
    athrow
L5
    iinc 5 1
    goto L2
L9
    getstatic client lt:[I
    iload 5
    iaload
    getstatic client lf:[I
    iload 5
    iaload
    iadd
    iload 0
    if_icmple L5
    iload 4
    ldc -1651506497 (java.lang.Integer)
    if_icmplt L6
    new java/lang/IllegalStateException
    dup
    invokespecial java/lang/IllegalStateException <init>:()V
    athrow
L10
    new java/lang/StringBuilder
    dup
    invokespecial java/lang/StringBuilder <init>:()V
    ldc "aj.bw(" (java.lang.String)
    invokevirtual java/lang/StringBuilder append:(Ljava/lang/String;)Ljava/lang/StringBuilder;
    ldc 41 (java.lang.Integer)
    invokevirtual java/lang/StringBuilder append:(C)Ljava/lang/StringBuilder;
    invokevirtual java/lang/StringBuilder toString:()Ljava/lang/String;
    invokestatic ai j:(Ljava/lang/Throwable;Ljava/lang/String;)Lex;
    athrow
