aj u (IS)VL1
    iload 1
    bipush 16
    ishr
    sipush 255
    iand
    i2d
    ldc 256.0 (java.lang.Double)
    ddiv
    dstore 3
    goto L2
L3
    ldc 628928555 (java.lang.Integer)
    aload 0
    getfield aj w:I
    imul
    sipush 255
    if_icmple L4
    goto L5
L6
    iload 1
    sipush 255
    iand
    i2d
    ldc 256.0 (java.lang.Double)
    ddiv
    dstore 7
L7
    dload 3
    dstore 9
L8
    dload 5
    dload 9
    dcmpg
    ifge L9
    iload 2
    sipush 1338
    if_icmpgt L10
    return
L10
    dload 5
    dstore 9
    goto L9
L11
    aload 0
    ldc -393119095 (java.lang.Integer)
    aload 0
    getfield aj i:I
    imul
    i2d
    dload 13
    dmul
    d2i
    ldc -1853100675 (java.lang.Integer)
    imul
    putfield aj c:I
    goto L12
L13
    dload 7
    dstore 9
    goto L14
L15
    dload 11
    dload 9
    dsub
    ldc 2.0 (java.lang.Double)
    dload 11
    dsub
    dload 9
    dsub
    ddiv
    dstore 15
    goto L16
L17
    dload 5
    dload 11
    dcmpl
    ifle L18
    iload 2
    sipush 1338
    if_icmpgt L19
    return
L19
    dload 5
    dstore 11
    goto L18
L20
    aload 0
    iconst_0
    putfield aj w:I
    goto L4
L21
    dload 7
    dstore 11
L22
    dconst_0
    dstore 13
L23
    dconst_0
    dstore 15
    goto L24
L25
    aload 0
    ldc 512.0 (java.lang.Double)
    dload 15
    dconst_1
    dload 17
    dsub
    dmul
    dmul
    d2i
    ldc -1696457799 (java.lang.Integer)
    imul
    putfield aj i:I
    goto L26
L9
    dload 7
    dload 9
    dcmpg
    ifge L14
    iload 2
    sipush 1338
    if_icmpgt L13
    return
L2
    iload 1
    bipush 8
    ishr
    sipush 255
    iand
    i2d
    ldc 256.0 (java.lang.Double)
    ddiv
    dstore 5
    goto L6
L27
    dload 11
    dload 9
    dsub
    dload 9
    dload 11
    dadd
    ddiv
    dstore 15
    goto L28
L29
    aload 0
    getfield aj w:I
    ldc 628928555 (java.lang.Integer)
    imul
    ifge L3
    iload 2
    sipush 1338
    if_icmpgt L20
    new java/lang/IllegalStateException
    dup
    invokespecial java/lang/IllegalStateException <init>:()V
    athrow
L30
    dload 17
    ldc 0.5 (java.lang.Double)
    dcmpg
    ifge L28
    iload 2
    sipush 1338
    if_icmpgt L27
    new java/lang/IllegalStateException
    dup
    invokespecial java/lang/IllegalStateException <init>:()V
    athrow
L16
    dload 3
    dload 11
    dcmpl
    ifne L31
    iload 2
    sipush 1338
    if_icmpgt L32
    return
L12
    return
L33
    aload 0
    ldc 1598575521 (java.lang.Integer)
    putfield aj u:I
    goto L29
L34
    ldc 2.0 (java.lang.Double)
    dload 7
    dload 3
    dsub
    dload 11
    dload 9
    dsub
    ddiv
    dadd
    dstore 13
    goto L35
L36
    dload 7
    dload 11
    dcmpl
    ifne L35
    iload 2
    sipush 1338
    if_icmpgt L37
    new java/lang/IllegalStateException
    dup
    invokespecial java/lang/IllegalStateException <init>:()V
    athrow
L37
    ldc 4.0 (java.lang.Double)
    dload 3
    dload 5
    dsub
    dload 11
    dload 9
    dsub
    ddiv
    dadd
    dstore 13
L35
    dload 13
    ldc 6.0 (java.lang.Double)
    ddiv
    dstore 13
L38
    aload 0
    ldc 256.0 (java.lang.Double)
    dload 15
    dmul
    d2i
    ldc 1673726815 (java.lang.Integer)
    imul
    putfield aj u:I
L39
    aload 0
    dload 17
    ldc 256.0 (java.lang.Double)
    dmul
    d2i
    ldc 1601080963 (java.lang.Integer)
    imul
    putfield aj w:I
L40
    ldc 1050284191 (java.lang.Integer)
    aload 0
    getfield aj u:I
    imul
    ifge L41
    iload 2
    sipush 1338
    if_icmpgt L42
    return
L18
    dload 7
    dload 11
    dcmpl
    ifle L22
    iload 2
    sipush 1338
    if_icmpgt L21
    return
L41
    ldc 1050284191 (java.lang.Integer)
    aload 0
    getfield aj u:I
    imul
    sipush 255
    if_icmple L29
    iload 2
    sipush 1338
    if_icmpgt L33
    return
L43
    dload 11
    dload 9
    dcmpl
    ifeq L35
    iload 2
    sipush 1338
    if_icmpgt L30
    new java/lang/IllegalStateException
    dup
    invokespecial java/lang/IllegalStateException <init>:()V
    athrow
L42
    aload 0
    iconst_0
    putfield aj u:I
    goto L29
L24
    dload 11
    dload 9
    dadd
    ldc 2.0 (java.lang.Double)
    ddiv
    dstore 17
    goto L43
L28
    dload 17
    ldc 0.5 (java.lang.Double)
    dcmpl
    iflt L16
    iload 2
    sipush 1338
    if_icmpgt L15
    new java/lang/IllegalStateException
    dup
    invokespecial java/lang/IllegalStateException <init>:()V
    athrow
L5
    aload 0
    ldc 253752445 (java.lang.Integer)
    putfield aj w:I
L4
    dload 17
    ldc 0.5 (java.lang.Double)
    dcmpl
    ifle L44
    goto L25
L44
    aload 0
    ldc 512.0 (java.lang.Double)
    dload 15
    dload 17
    dmul
    dmul
    d2i
    ldc -1696457799 (java.lang.Integer)
    imul
    putfield aj i:I
    goto L26
L32
    dload 5
    dload 7
    dsub
    dload 11
    dload 9
    dsub
    ddiv
    dstore 13
    goto L35
L26
    aload 0
    getfield aj i:I
    ldc -393119095 (java.lang.Integer)
    imul
    iconst_1
    if_icmpge L11
    iload 2
    sipush 1338
    if_icmpgt L45
    return
L45
    aload 0
    ldc -1696457799 (java.lang.Integer)
    putfield aj i:I
    goto L11
L31
    dload 11
    dload 5
    dcmpl
    ifne L36
    iload 2
    sipush 1338
    if_icmpgt L34
    new java/lang/IllegalStateException
    dup
    invokespecial java/lang/IllegalStateException <init>:()V
    athrow
L14
    dload 3
    dstore 11
    goto L17
L46
    new java/lang/StringBuilder
    dup
    invokespecial java/lang/StringBuilder <init>:()V
    ldc "aj.u(" (java.lang.String)
    invokevirtual java/lang/StringBuilder append:(Ljava/lang/String;)Ljava/lang/StringBuilder;
    ldc 41 (java.lang.Integer)
    invokevirtual java/lang/StringBuilder append:(C)Ljava/lang/StringBuilder;
    invokevirtual java/lang/StringBuilder toString:()Ljava/lang/String;
    invokestatic k a:(Ljava/lang/Throwable;Ljava/lang/String;)Lee;
    athrow
