ak o (Lv;I)VL1
    aload 0
    ldc 2136511178 (java.lang.Integer)
    invokevirtual v e:(I)Z
    getstatic client o:Z
    if_icmpeq L2
    iload 1
    ldc -708614931 (java.lang.Integer)
    if_icmpgt L3
    new java/lang/IllegalStateException
    dup
    invokespecial java/lang/IllegalStateException <init>:()V
    athrow
L4
    imul
    putstatic au bh:I
    goto L5
L6
    aload 0
    ldc 1868840686 (java.lang.Integer)
    invokevirtual v e:(I)Z
    istore 2
    goto L7
L8
    ldc -2000942883 (java.lang.Integer)
    aload 0
    getfield v e:I
    imul
    putstatic client c:I
    goto L9
L10
    ldc -140792485 (java.lang.Integer)
    getstatic client r:I
    ldc -708614931 (java.lang.Integer)
    imul
    ifne L11
    iload 1
    ldc -708614931 (java.lang.Integer)
    if_icmpgt L12
    new java/lang/IllegalStateException
    dup
    invokespecial java/lang/IllegalStateException <init>:()V
    athrow
L13
    getstatic ad f:Lgr;
    invokevirtual gr c:()V
    goto L14
L15
    getstatic ad r:Lgr;
    invokevirtual gr c:()V
    goto L13
L16
    iload 2
    putstatic dx w:Z
    goto L2
L9
    aload 0
    getfield v a:I
    ldc 1984015289 (java.lang.Integer)
    imul
    putstatic client u:I
    goto L17
L3
    aload 0
    ldc 1690712983 (java.lang.Integer)
    invokevirtual v e:(I)Z
    putstatic client o:Z
    goto L6
L18
    ldc 43594 (java.lang.Integer)
    goto L19
L17
    getstatic client r:I
    ldc -708614931 (java.lang.Integer)
    imul
    ifne L20
    iload 1
    ldc -708614931 (java.lang.Integer)
    if_icmpgt L18
    new java/lang/IllegalStateException
    dup
    invokespecial java/lang/IllegalStateException <init>:()V
    athrow
L7
    getstatic dx w:Z
    iload 2
    if_icmpeq L2
    iload 1
    ldc -708614931 (java.lang.Integer)
    if_icmpgt L15
    new java/lang/IllegalStateException
    dup
    invokespecial java/lang/IllegalStateException <init>:()V
    athrow
L20
    ldc 40000 (java.lang.Integer)
    aload 0
    getfield v e:I
    ldc 1985134815 (java.lang.Integer)
    imul
    iadd
L19
    ldc -312353989 (java.lang.Integer)
    imul
    putstatic o bz:I
    goto L10
L2
    aload 0
    getfield v c:Ljava/lang/String;
    putstatic k by:Ljava/lang/String;
    goto L8
L12
    sipush 443
    goto L4
L11
    ldc 50000 (java.lang.Integer)
    aload 0
    getfield v e:I
    ldc 1985134815 (java.lang.Integer)
    imul
    iadd
    goto L4
L14
    getstatic ad g:Lgr;
    invokevirtual gr c:()V
    goto L16
L5
    getstatic o bz:I
    ldc -669377421 (java.lang.Integer)
    imul
    putstatic ck bt:I
L21
    return
L22
    new java/lang/StringBuilder
    dup
    invokespecial java/lang/StringBuilder <init>:()V
    ldc "ak.o(" (java.lang.String)
    invokevirtual java/lang/StringBuilder append:(Ljava/lang/String;)Ljava/lang/StringBuilder;
    ldc 41 (java.lang.Integer)
    invokevirtual java/lang/StringBuilder append:(C)Ljava/lang/StringBuilder;
    invokevirtual java/lang/StringBuilder toString:()Ljava/lang/String;
    invokestatic k a:(Ljava/lang/Throwable;Ljava/lang/String;)Lee;
    athrow
