al by (ILjava/lang/String;B)VL1
    iconst_0
    istore 3
    goto L2
L3
    getstatic client cd:Ldj;
    getstatic client hw:[I
    iload 4
    iaload
    ldc 2102497782 (java.lang.Integer)
    invokevirtual dj af:(II)V
    goto L4
L5
    iload 4
    getstatic client hr:I
    ldc 308668811 (java.lang.Integer)
    imul
    if_icmpge L6
    iload 2
    bipush 8
    if_icmpne L7
    return
L7
    getstatic client hg:[Ll;
    getstatic client hw:[I
    iload 4
    iaload
    aaload
    astore 5
    goto L8
L9
    getstatic client cd:Ldj;
    iconst_0
    ldc -2035234054 (java.lang.Integer)
    invokevirtual dj at:(II)V
    goto L10
L11
    aload 5
    getfield l e:Ljava/lang/String;
    ifnull L12
    aload 5
    getfield l e:Ljava/lang/String;
    aload 1
    invokevirtual java/lang/String equalsIgnoreCase:(Ljava/lang/String;)Z
    ifeq L12
    goto L13
L8
    aload 5
    ifnull L12
    iload 2
    bipush 8
    if_icmpne L11
    new java/lang/IllegalStateException
    dup
    invokespecial java/lang/IllegalStateException <init>:()V
    athrow
L14
    getstatic client cd:Ldj;
    bipush 29
    ldc -1463274417 (java.lang.Integer)
    invokevirtual dj hl:(II)V
    goto L15
L16
    getstatic client cd:Ldj;
    getstatic client hw:[I
    iload 4
    iaload
    bipush -47
    invokevirtual dj a:(IB)V
L17
    getstatic client cd:Ldj;
    iconst_0
    ldc -193370051 (java.lang.Integer)
    invokevirtual dj at:(II)V
    goto L10
L18
    iload 0
    iconst_4
    if_icmpne L19
    iload 2
    bipush 8
    if_icmpne L14
    new java/lang/IllegalStateException
    dup
    invokespecial java/lang/IllegalStateException <init>:()V
    athrow
L20
    bipush 7
    iload 0
    if_icmpne L10
    iload 2
    bipush 8
    if_icmpne L21
    new java/lang/IllegalStateException
    dup
    invokespecial java/lang/IllegalStateException <init>:()V
    athrow
L15
    getstatic client cd:Ldj;
    iconst_0
    bipush 13
    invokevirtual dj e:(IB)V
L22
    getstatic client cd:Ldj;
    getstatic client hw:[I
    iload 4
    iaload
    bipush 98
    invokevirtual dj an:(IB)V
    goto L10
L23
    getstatic client cd:Ldj;
    getstatic client hw:[I
    iload 4
    iaload
    ldc 2096871098 (java.lang.Integer)
    invokevirtual dj af:(II)V
    goto L9
L24
    getstatic client cd:Ldj;
    sipush 248
    ldc -365121683 (java.lang.Integer)
    invokevirtual dj hl:(II)V
    goto L23
L25
    goto L6
L2
    iconst_0
    istore 4
    goto L5
L13
    iload 0
    iconst_1
    if_icmpne L18
    iload 2
    bipush 8
    if_icmpne L26
    new java/lang/IllegalStateException
    dup
    invokespecial java/lang/IllegalStateException <init>:()V
    athrow
L21
    getstatic client cd:Ldj;
    bipush 80
    ldc -1462510945 (java.lang.Integer)
    invokevirtual dj hl:(II)V
    goto L3
L6
    iload 3
    ifne L27
    iload 2
    bipush 8
    if_icmpne L28
    new java/lang/IllegalStateException
    dup
    invokespecial java/lang/IllegalStateException <init>:()V
    athrow
L4
    getstatic client cd:Ldj;
    iconst_0
    iconst_0
    invokevirtual dj ah:(IB)V
    goto L10
L19
    bipush 6
    iload 0
    if_icmpne L20
    iload 2
    bipush 8
    if_icmpne L24
    new java/lang/IllegalStateException
    dup
    invokespecial java/lang/IllegalStateException <init>:()V
    athrow
L26
    getstatic client cd:Ldj;
    sipush 219
    ldc 299248316 (java.lang.Integer)
    invokevirtual dj hl:(II)V
    goto L16
L12
    iinc 4 1
    goto L5
L10
    iconst_1
    istore 3
    goto L25
L28
    iconst_4
    ldc "" (java.lang.String)
    new java/lang/StringBuilder
    dup
    invokespecial java/lang/StringBuilder <init>:()V
    getstatic et er:Ljava/lang/String;
    invokevirtual java/lang/StringBuilder append:(Ljava/lang/String;)Ljava/lang/StringBuilder;
    aload 1
    invokevirtual java/lang/StringBuilder append:(Ljava/lang/String;)Ljava/lang/StringBuilder;
    invokevirtual java/lang/StringBuilder toString:()Ljava/lang/String;
    ldc -983202829 (java.lang.Integer)
    invokestatic c a:(ILjava/lang/String;Ljava/lang/String;I)V
L27
    return
L29
    new java/lang/StringBuilder
    dup
    invokespecial java/lang/StringBuilder <init>:()V
    ldc "al.by(" (java.lang.String)
    invokevirtual java/lang/StringBuilder append:(Ljava/lang/String;)Ljava/lang/StringBuilder;
    ldc 41 (java.lang.Integer)
    invokevirtual java/lang/StringBuilder append:(C)Ljava/lang/StringBuilder;
    invokevirtual java/lang/StringBuilder toString:()Ljava/lang/String;
    invokestatic k a:(Ljava/lang/Throwable;Ljava/lang/String;)Lee;
    athrow
