an dd (Lfb;I)ZL1
    aload 0
    getfield fb t:I
    ldc 937329469 (java.lang.Integer)
    imul
    istore 2
    goto L2
L3
    getstatic client oy:Lfq;
    iconst_1
    ldc 1507296006 (java.lang.Integer)
    invokevirtual fq c:(ZI)V
    goto L4
L5
    iload 2
    iconst_1
    iand
    istore 4
    goto L6
L7
    iconst_1
    ireturn
L8
    iload 2
    sipush 300
    if_icmplt L9
    iload 1
    ldc -1029179149 (java.lang.Integer)
    if_icmpgt L10
    new java/lang/IllegalStateException
    dup
    invokespecial java/lang/IllegalStateException <init>:()V
    athrow
L11
    getstatic client cd:Ldj;
    bipush 86
    ldc -1818950913 (java.lang.Integer)
    invokevirtual dj hl:(II)V
    goto L12
L13
    iload 2
    sipush 300
    isub
    iconst_2
    idiv
    istore 3
    goto L5
L14
    iconst_0
    goto L15
L16
    getstatic client oy:Lfq;
    iconst_0
    ldc 1475527256 (java.lang.Integer)
    invokevirtual fq c:(ZI)V
    goto L17
L18
    iconst_1
    ireturn
L19
    iconst_0
L20
    bipush -21
    invokevirtual fq a:(IZB)V
L9
    iload 2
    sipush 314
    if_icmplt L21
    iload 2
    sipush 323
    if_icmpgt L21
    iload 1
    ldc -1029179149 (java.lang.Integer)
    if_icmpgt L22
    new java/lang/IllegalStateException
    dup
    invokespecial java/lang/IllegalStateException <init>:()V
    athrow
L22
    iload 2
    sipush 314
    isub
    iconst_2
    idiv
    istore 3
L23
    iload 2
    iconst_1
    iand
    istore 4
L24
    getstatic client oy:Lfq;
    iload 3
    iload 4
    iconst_1
    if_icmpne L14
    iload 1
    ldc -1029179149 (java.lang.Integer)
    if_icmpgt L25
    new java/lang/IllegalStateException
    dup
    invokespecial java/lang/IllegalStateException <init>:()V
    athrow
L25
    iconst_1
    goto L15
L6
    getstatic client oy:Lfq;
    iload 3
    iconst_1
    iload 4
    if_icmpne L19
    iload 1
    ldc -1029179149 (java.lang.Integer)
    if_icmpgt L26
    new java/lang/IllegalStateException
    dup
    invokespecial java/lang/IllegalStateException <init>:()V
    athrow
L15
    bipush -35
    invokevirtual fq l:(IZB)V
L21
    iload 2
    sipush 324
    if_icmpne L17
    iload 1
    ldc -1029179149 (java.lang.Integer)
    if_icmpgt L16
    new java/lang/IllegalStateException
    dup
    invokespecial java/lang/IllegalStateException <init>:()V
    athrow
L12
    getstatic client oy:Lfq;
    getstatic client cd:Ldj;
    ldc -1508260577 (java.lang.Integer)
    invokevirtual fq u:(Ldh;I)V
    goto L18
L17
    iload 2
    sipush 325
    if_icmpne L4
    iload 1
    ldc -1029179149 (java.lang.Integer)
    if_icmpgt L3
    new java/lang/IllegalStateException
    dup
    invokespecial java/lang/IllegalStateException <init>:()V
    athrow
L10
    iload 2
    sipush 313
    if_icmpgt L9
    iload 1
    ldc -1029179149 (java.lang.Integer)
    if_icmpgt L13
    new java/lang/IllegalStateException
    dup
    invokespecial java/lang/IllegalStateException <init>:()V
    athrow
L4
    sipush 326
    iload 2
    if_icmpne L27
    iload 1
    ldc -1029179149 (java.lang.Integer)
    if_icmpgt L11
    new java/lang/IllegalStateException
    dup
    invokespecial java/lang/IllegalStateException <init>:()V
    athrow
L28
    ldc -1278880042 (java.lang.Integer)
    putstatic client cx:I
    goto L7
L2
    sipush 205
    iload 2
    if_icmpne L8
    goto L28
L26
    iconst_1
    goto L20
L27
    iconst_0
    ireturn
L29
    new java/lang/StringBuilder
    dup
    invokespecial java/lang/StringBuilder <init>:()V
    ldc "an.dd(" (java.lang.String)
    invokevirtual java/lang/StringBuilder append:(Ljava/lang/String;)Ljava/lang/StringBuilder;
    ldc 41 (java.lang.Integer)
    invokevirtual java/lang/StringBuilder append:(C)Ljava/lang/StringBuilder;
    invokevirtual java/lang/StringBuilder toString:()Ljava/lang/String;
    invokestatic k a:(Ljava/lang/Throwable;Ljava/lang/String;)Lee;
    athrow
