ap l (Lew;I)VL1
    getstatic ai ad:Z
    ifeq L2
    iload 1
    ldc 125277993 (java.lang.Integer)
    if_icmpgt L3
    new java/lang/IllegalStateException
    dup
    invokespecial java/lang/IllegalStateException <init>:()V
    athrow
L4
    getstatic et dx:Ljava/lang/String;
    getstatic et do:Ljava/lang/String;
    getstatic et dy:Ljava/lang/String;
    sipush 8502
    invokestatic dd w:(Ljava/lang/String;Ljava/lang/String;Ljava/lang/String;S)V
    goto L5
L6
    iload 4
    iload 5
    if_icmpge L7
    goto L8
L2
    getstatic ep s:I
    ldc -1750678861 (java.lang.Integer)
    imul
    iconst_1
    if_icmpeq L9
    iload 1
    ldc 125277993 (java.lang.Integer)
    if_icmpgt L10
    new java/lang/IllegalStateException
    dup
    invokespecial java/lang/IllegalStateException <init>:()V
    athrow
L10
    getstatic q at:Z
    ifne L11
    iload 1
    ldc 125277993 (java.lang.Integer)
    if_icmpgt L12
    new java/lang/IllegalStateException
    dup
    invokespecial java/lang/IllegalStateException <init>:()V
    athrow
L13
    getstatic dn at:Ljava/lang/String;
    iconst_0
    getstatic dn at:Ljava/lang/String;
    invokevirtual java/lang/String length:()I
    iconst_1
    isub
    invokevirtual java/lang/String substring:(II)Ljava/lang/String;
    putstatic dn at:Ljava/lang/String;
    goto L14
L9
    ldc -642165313 (java.lang.Integer)
    getstatic ep j:I
    imul
    sipush 715
    if_icmplt L11
    iload 1
    ldc 125277993 (java.lang.Integer)
    if_icmpgt L15
    return
L15
    getstatic ep m:I
    ldc 1563808941 (java.lang.Integer)
    imul
    sipush 453
    if_icmplt L11
    iload 1
    ldc 125277993 (java.lang.Integer)
    if_icmpgt L16
    new java/lang/IllegalStateException
    dup
    invokespecial java/lang/IllegalStateException <init>:()V
    athrow
L17
    ldc -327990299 (java.lang.Integer)
    getstatic t cj:I
    imul
    bipush 84
    if_icmpne L18
    goto L19
L20
    ldc "" (java.lang.String)
    putstatic ai ay:Ljava/lang/String;
    goto L21
L22
    iconst_0
    goto L23
L24
    aconst_null
    getstatic da an:Ly;
    if_acmpeq L25
    iload 1
    ldc 125277993 (java.lang.Integer)
    if_icmpgt L26
    new java/lang/IllegalStateException
    dup
    invokespecial java/lang/IllegalStateException <init>:()V
    athrow
L27
    new java/lang/StringBuilder
    dup
    invokespecial java/lang/StringBuilder <init>:()V
    getstatic ai ay:Ljava/lang/String;
    invokevirtual java/lang/StringBuilder append:(Ljava/lang/String;)Ljava/lang/StringBuilder;
    getstatic x cm:C
    invokevirtual java/lang/StringBuilder append:(C)Ljava/lang/StringBuilder;
    invokevirtual java/lang/StringBuilder toString:()Ljava/lang/String;
    putstatic ai ay:Ljava/lang/String;
    goto L28
L29
    getstatic dk ol:Lf;
    getfield f c:Z
    ifne L30
    iload 1
    ldc 125277993 (java.lang.Integer)
    if_icmpgt L31
    new java/lang/IllegalStateException
    dup
    invokespecial java/lang/IllegalStateException <init>:()V
    athrow
L31
    getstatic eo bw:Lfo;
    ldc "scape main" (java.lang.String)
    ldc "" (java.lang.String)
    sipush 255
    iconst_0
    bipush 117
    invokestatic client e:(Lfv;Ljava/lang/String;Ljava/lang/String;IZB)V
    goto L11
L30
    ldc 1388308481 (java.lang.Integer)
    invokestatic l c:(I)V
    goto L11
L32
    getstatic et hc:Ljava/lang/String;
    putstatic ai av:Ljava/lang/String;
    goto L33
L34
    ldc -327990299 (java.lang.Integer)
    getstatic t cj:I
    imul
    bipush 84
    if_icmpne L35
    iload 1
    ldc 125277993 (java.lang.Integer)
    if_icmpgt L36
    return
L37
    getstatic ai ao:I
    ldc -1935446173 (java.lang.Integer)
    iadd
    putstatic ai ao:I
    goto L38
L39
    return
L40
    iload 4
    iload 6
    bipush 20
    isub
    if_icmplt L41
    goto L42
L43
    return
L44
    ldc 1136922049 (java.lang.Integer)
    getstatic client s:I
    imul
    ifne L25
    iload 1
    ldc 125277993 (java.lang.Integer)
    if_icmpgt L45
    new java/lang/IllegalStateException
    dup
    invokespecial java/lang/IllegalStateException <init>:()V
    athrow
L46
    putstatic ai aj:Lez;
    goto L47
L48
    getstatic q at:Z
    ifne L24
    iload 1
    ldc 125277993 (java.lang.Integer)
    if_icmpgt L49
    return
L49
    ldc -1750678861 (java.lang.Integer)
    getstatic ep s:I
    imul
    iconst_4
    if_icmpne L24
    iload 1
    ldc 125277993 (java.lang.Integer)
    if_icmpgt L50
    new java/lang/IllegalStateException
    dup
    invokespecial java/lang/IllegalStateException <init>:()V
    athrow
L50
    iconst_5
    istore 2
L51
    sipush 463
    istore 3
L52
    bipush 100
    istore 4
L53
    bipush 35
    istore 5
    goto L54
L55
    iconst_0
    putstatic ai ak:I
    goto L56
L57
    ldc -642165313 (java.lang.Integer)
    getstatic ep j:I
    imul
    iload 4
    iload 2
    iadd
    if_icmpgt L24
    iload 1
    ldc 125277993 (java.lang.Integer)
    if_icmpgt L58
    return
L59
    iload 3
    iload 6
    bipush 75
    isub
    if_icmplt L60
    iload 1
    ldc 125277993 (java.lang.Integer)
    if_icmpgt L61
    new java/lang/IllegalStateException
    dup
    invokespecial java/lang/IllegalStateException <init>:()V
    athrow
L62
    ldc 1563808941 (java.lang.Integer)
    getstatic ep m:I
    imul
    iload 5
    iload 3
    iadd
    if_icmpgt L24
    iload 1
    ldc 125277993 (java.lang.Integer)
    if_icmpgt L63
    new java/lang/IllegalStateException
    dup
    invokespecial java/lang/IllegalStateException <init>:()V
    athrow
L63
    sipush -10051
    invokestatic cc h:(S)V
L64
    return
L65
    bipush 85
    getstatic t cj:I
    ldc -327990299 (java.lang.Integer)
    imul
    if_icmpne L17
    iload 1
    ldc 125277993 (java.lang.Integer)
    if_icmpgt L66
    return
L67
    iconst_0
    putstatic aq ah:I
    goto L68
L25
    ldc -1750678861 (java.lang.Integer)
    getstatic ep s:I
    imul
    istore 2
L69
    ldc -642165313 (java.lang.Integer)
    getstatic ep j:I
    imul
    istore 3
L70
    getstatic ep m:I
    ldc 1563808941 (java.lang.Integer)
    imul
    istore 4
L71
    getstatic q at:Z
    ifne L72
    iload 2
    iconst_4
    if_icmpne L72
    iload 1
    ldc 125277993 (java.lang.Integer)
    if_icmpgt L73
    new java/lang/IllegalStateException
    dup
    invokespecial java/lang/IllegalStateException <init>:()V
    athrow
L73
    iconst_1
    istore 2
L72
    getstatic ai au:I
    ldc -47454393 (java.lang.Integer)
    imul
    ifne L74
    goto L75
L76
    putstatic ai aj:Lez;
    goto L77
L78
    sipush 291
    istore 6
L79
    iload 2
    iconst_1
    if_icmpne L80
    iload 1
    ldc 125277993 (java.lang.Integer)
    if_icmpgt L81
    new java/lang/IllegalStateException
    dup
    invokespecial java/lang/IllegalStateException <init>:()V
    athrow
L82
    iload 3
    sipush 512
    if_icmpgt L83
    iload 1
    ldc 125277993 (java.lang.Integer)
    if_icmpgt L84
    new java/lang/IllegalStateException
    dup
    invokespecial java/lang/IllegalStateException <init>:()V
    athrow
L85
    iload 3
    bipush 75
    iload 5
    iadd
    if_icmpgt L80
    iload 1
    ldc 125277993 (java.lang.Integer)
    if_icmpgt L86
    new java/lang/IllegalStateException
    dup
    invokespecial java/lang/IllegalStateException <init>:()V
    athrow
L86
    iload 4
    iload 6
    bipush 20
    isub
    if_icmplt L80
    iload 1
    ldc 125277993 (java.lang.Integer)
    if_icmpgt L87
    return
L87
    iload 4
    bipush 20
    iload 6
    iadd
    if_icmpgt L80
    iload 1
    ldc 125277993 (java.lang.Integer)
    if_icmpgt L88
    new java/lang/IllegalStateException
    dup
    invokespecial java/lang/IllegalStateException <init>:()V
    athrow
L89
    ldc -327990299 (java.lang.Integer)
    getstatic t cj:I
    imul
    bipush 13
    if_icmpne L90
    iload 1
    ldc 125277993 (java.lang.Integer)
    if_icmpgt L91
    new java/lang/IllegalStateException
    dup
    invokespecial java/lang/IllegalStateException <init>:()V
    athrow
L92
    getstatic ai al:Z
    ifeq L93
    iload 1
    ldc 125277993 (java.lang.Integer)
    if_icmpgt L94
    new java/lang/IllegalStateException
    dup
    invokespecial java/lang/IllegalStateException <init>:()V
    athrow
L75
    sipush 302
    istore 5
    goto L78
L95
    iload 3
    iload 5
    bipush 75
    isub
    if_icmplt L96
    iload 1
    ldc 125277993 (java.lang.Integer)
    if_icmpgt L97
    return
L97
    iload 3
    bipush 75
    iload 5
    iadd
    if_icmpgt L96
    iload 1
    ldc 125277993 (java.lang.Integer)
    if_icmpgt L98
    new java/lang/IllegalStateException
    dup
    invokespecial java/lang/IllegalStateException <init>:()V
    athrow
L66
    getstatic ai ay:Ljava/lang/String;
    invokevirtual java/lang/String length:()I
    ifle L17
    goto L99
L100
    iload 4
    iload 6
    bipush 20
    iadd
    if_icmpgt L96
    iload 1
    ldc 125277993 (java.lang.Integer)
    if_icmpgt L101
    new java/lang/IllegalStateException
    dup
    invokespecial java/lang/IllegalStateException <init>:()V
    athrow
L101
    ldc 2113057499 (java.lang.Integer)
    getstatic client u:I
    imul
    iconst_4
    iand
    ifeq L102
    iload 1
    ldc 125277993 (java.lang.Integer)
    if_icmpgt L103
    new java/lang/IllegalStateException
    dup
    invokespecial java/lang/IllegalStateException <init>:()V
    athrow
L104
    iconst_0
    putstatic ai au:I
    goto L20
L105
    getstatic et hy:Ljava/lang/String;
    putstatic ai ae:Ljava/lang/String;
    goto L106
L107
    getstatic t cj:I
    ldc -327990299 (java.lang.Integer)
    imul
    bipush 85
    if_icmpne L108
    goto L109
L110
    sipush 361
    istore 5
    goto L111
L83
    iconst_1
    iload 2
    if_icmpne L112
    iload 1
    ldc 125277993 (java.lang.Integer)
    if_icmpgt L113
    new java/lang/IllegalStateException
    dup
    invokespecial java/lang/IllegalStateException <init>:()V
    athrow
L114
    iconst_0
    putstatic ai ak:I
    goto L115
L116
    getstatic et hz:Ljava/lang/String;
    putstatic ai av:Ljava/lang/String;
    goto L117
L118
    getstatic et hz:Ljava/lang/String;
    putstatic ai av:Ljava/lang/String;
    goto L119
L120
    getstatic dn at:Ljava/lang/String;
    invokevirtual java/lang/String length:()I
    bipush 6
    if_icmpeq L121
    goto L122
L102
    getstatic client u:I
    ldc 2113057499 (java.lang.Integer)
    imul
    sipush 1024
    iand
    ifeq L123
    iload 1
    ldc 125277993 (java.lang.Integer)
    if_icmpgt L124
    new java/lang/IllegalStateException
    dup
    invokespecial java/lang/IllegalStateException <init>:()V
    athrow
L124
    getstatic et hm:Ljava/lang/String;
    putstatic ai ae:Ljava/lang/String;
L125
    getstatic et he:Ljava/lang/String;
    putstatic ai ab:Ljava/lang/String;
L126
    getstatic et hn:Ljava/lang/String;
    putstatic ai av:Ljava/lang/String;
    goto L127
L128
    iconst_0
    putstatic aq ah:I
    goto L129
L130
    iconst_0
    putstatic ai ak:I
    goto L96
L112
    sipush 462
    istore 5
    goto L131
L132
    getstatic et hh:Ljava/lang/String;
    putstatic ai ab:Ljava/lang/String;
L133
    getstatic et hz:Ljava/lang/String;
    putstatic ai av:Ljava/lang/String;
L134
    ldc -1668340498 (java.lang.Integer)
    putstatic ai au:I
L135
    iconst_0
    putstatic ai ak:I
L96
    goto L136
L137
    iload 3
    iload 5
    bipush 75
    iadd
    if_icmpgt L138
    iload 1
    ldc 125277993 (java.lang.Integer)
    if_icmpgt L139
    new java/lang/IllegalStateException
    dup
    invokespecial java/lang/IllegalStateException <init>:()V
    athrow
L140
    getstatic dn at:Ljava/lang/String;
    invokevirtual java/lang/String trim:()Ljava/lang/String;
    pop
    goto L141
L142
    iconst_0
    putstatic ai au:I
    goto L138
L36
    getstatic et ha:Ljava/lang/String;
    putstatic ai ae:Ljava/lang/String;
L143
    getstatic et hh:Ljava/lang/String;
    putstatic ai ab:Ljava/lang/String;
L144
    getstatic et hz:Ljava/lang/String;
    putstatic ai av:Ljava/lang/String;
L145
    ldc -1668340498 (java.lang.Integer)
    putstatic ai au:I
L146
    iconst_0
    putstatic ai ak:I
    goto L147
L35
    getstatic t cj:I
    ldc -327990299 (java.lang.Integer)
    imul
    bipush 13
    if_icmpne L147
    iload 1
    ldc 125277993 (java.lang.Integer)
    if_icmpgt L148
    return
L148
    iconst_0
    putstatic ai au:I
    goto L147
L149
    sipush 302
    istore 5
L150
    sipush 321
    istore 6
    goto L151
L152
    ldc 423886265 (java.lang.Integer)
    getstatic ai ak:I
    imul
    iconst_1
    if_icmpne L28
    iload 1
    ldc 125277993 (java.lang.Integer)
    if_icmpgt L153
    return
L154
    iload 3
    iload 5
    bipush 75
    isub
    if_icmplt L56
    iload 1
    ldc 125277993 (java.lang.Integer)
    if_icmpgt L155
    new java/lang/IllegalStateException
    dup
    invokespecial java/lang/IllegalStateException <init>:()V
    athrow
L127
    ldc -834170249 (java.lang.Integer)
    putstatic ai au:I
    goto L130
L156
    iload 4
    iload 6
    bipush 20
    isub
    if_icmplt L56
    iload 1
    ldc 125277993 (java.lang.Integer)
    if_icmpgt L157
    new java/lang/IllegalStateException
    dup
    invokespecial java/lang/IllegalStateException <init>:()V
    athrow
L157
    iload 4
    iload 6
    bipush 20
    iadd
    if_icmpgt L56
    iload 1
    ldc 125277993 (java.lang.Integer)
    if_icmpgt L158
    new java/lang/IllegalStateException
    dup
    invokespecial java/lang/IllegalStateException <init>:()V
    athrow
L158
    getstatic et ha:Ljava/lang/String;
    putstatic ai ae:Ljava/lang/String;
    goto L159
L160
    ldc 1532705327 (java.lang.Integer)
    getstatic client q:I
    imul
    bipush 11
    if_icmpeq L44
    iload 1
    ldc 125277993 (java.lang.Integer)
    if_icmpgt L43
    new java/lang/IllegalStateException
    dup
    invokespecial java/lang/IllegalStateException <init>:()V
    athrow
L161
    getstatic et hz:Ljava/lang/String;
    putstatic ai av:Ljava/lang/String;
L162
    ldc -1668340498 (java.lang.Integer)
    putstatic ai au:I
    goto L55
L163
    ldc -47454393 (java.lang.Integer)
    getstatic ai au:I
    imul
    iconst_4
    if_icmpne L164
    iload 1
    ldc 125277993 (java.lang.Integer)
    if_icmpgt L165
    new java/lang/IllegalStateException
    dup
    invokespecial java/lang/IllegalStateException <init>:()V
    athrow
L56
    sipush 462
    istore 5
L166
    iload 2
    iconst_1
    if_icmpne L138
    iload 1
    ldc 125277993 (java.lang.Integer)
    if_icmpgt L167
    new java/lang/IllegalStateException
    dup
    invokespecial java/lang/IllegalStateException <init>:()V
    athrow
L167
    iload 3
    iload 5
    bipush 75
    isub
    if_icmplt L138
    iload 1
    ldc 125277993 (java.lang.Integer)
    if_icmpgt L137
    new java/lang/IllegalStateException
    dup
    invokespecial java/lang/IllegalStateException <init>:()V
    athrow
L81
    iload 3
    iload 5
    bipush 75
    isub
    if_icmplt L80
    iload 1
    ldc 125277993 (java.lang.Integer)
    if_icmpgt L85
    new java/lang/IllegalStateException
    dup
    invokespecial java/lang/IllegalStateException <init>:()V
    athrow
L139
    iload 4
    iload 6
    bipush 20
    isub
    if_icmplt L138
    iload 4
    bipush 20
    iload 6
    iadd
    if_icmpgt L138
    iload 1
    ldc 125277993 (java.lang.Integer)
    if_icmpgt L142
    new java/lang/IllegalStateException
    dup
    invokespecial java/lang/IllegalStateException <init>:()V
    athrow
L168
    getstatic t cj:I
    ldc -327990299 (java.lang.Integer)
    imul
    bipush 80
    if_icmpne L169
    iload 1
    ldc 125277993 (java.lang.Integer)
    if_icmpgt L170
    new java/lang/IllegalStateException
    dup
    invokespecial java/lang/IllegalStateException <init>:()V
    athrow
L138
    goto L136
L171
    iconst_2
    ldc -47454393 (java.lang.Integer)
    getstatic ai au:I
    imul
    if_icmpne L163
    iload 1
    ldc 125277993 (java.lang.Integer)
    if_icmpgt L172
    new java/lang/IllegalStateException
    dup
    invokespecial java/lang/IllegalStateException <init>:()V
    athrow
L172
    sipush 231
    istore 5
L173
    iinc 5 30
L174
    iload 2
    iconst_1
    if_icmpne L7
    iload 1
    ldc 125277993 (java.lang.Integer)
    if_icmpgt L175
    return
L175
    iload 4
    iload 5
    bipush 15
    isub
    if_icmplt L7
    goto L6
L26
    sipush -12615
    invokestatic cc h:(S)V
    goto L25
L176
    iload 2
    iconst_1
    if_icmpne L177
    iload 1
    ldc 125277993 (java.lang.Integer)
    if_icmpgt L178
    new java/lang/IllegalStateException
    dup
    invokespecial java/lang/IllegalStateException <init>:()V
    athrow
L103
    ldc 2113057499 (java.lang.Integer)
    getstatic client u:I
    imul
    sipush 1024
    iand
    ifeq L179
    iload 1
    ldc 125277993 (java.lang.Integer)
    if_icmpgt L105
    return
L180
    getstatic et hz:Ljava/lang/String;
    putstatic ai av:Ljava/lang/String;
    goto L181
L98
    iload 4
    iload 6
    bipush 20
    isub
    if_icmplt L96
    iload 1
    ldc 125277993 (java.lang.Integer)
    if_icmpgt L100
    return
L182
    iload 4
    iload 5
    if_icmpge L183
    iload 1
    ldc 125277993 (java.lang.Integer)
    if_icmpgt L184
    new java/lang/IllegalStateException
    dup
    invokespecial java/lang/IllegalStateException <init>:()V
    athrow
L184
    ldc 1549990025 (java.lang.Integer)
    putstatic ai ak:I
L183
    iinc 5 15
    goto L110
L185
    bipush -15
    invokestatic am c:(B)V
    goto L186
L187
    ldc "" (java.lang.String)
    putstatic ai ay:Ljava/lang/String;
    goto L188
L189
    iload 4
    iload 5
    bipush 15
    isub
    if_icmplt L190
    iload 1
    ldc 125277993 (java.lang.Integer)
    if_icmpgt L191
    new java/lang/IllegalStateException
    dup
    invokespecial java/lang/IllegalStateException <init>:()V
    athrow
L191
    iload 4
    iload 5
    if_icmpge L190
    iload 1
    ldc 125277993 (java.lang.Integer)
    if_icmpgt L192
    new java/lang/IllegalStateException
    dup
    invokespecial java/lang/IllegalStateException <init>:()V
    athrow
L192
    getstatic et ik:Ljava/lang/String;
    getstatic et ig:Ljava/lang/String;
    getstatic et ia:Ljava/lang/String;
    sipush 22067
    invokestatic dd w:(Ljava/lang/String;Ljava/lang/String;Ljava/lang/String;S)V
L193
    ldc 124116051 (java.lang.Integer)
    putstatic ai au:I
L194
    return
L190
    sipush 302
    istore 6
L195
    sipush 321
    istore 7
L196
    iconst_1
    iload 2
    if_icmpne L197
    iload 3
    iload 6
    bipush 75
    isub
    if_icmplt L197
    iload 3
    iload 6
    bipush 75
    iadd
    if_icmpgt L197
    iload 4
    iload 7
    bipush 20
    isub
    if_icmplt L197
    iload 4
    iload 7
    bipush 20
    iadd
    if_icmpgt L197
    iload 1
    ldc 125277993 (java.lang.Integer)
    if_icmpgt L198
    new java/lang/IllegalStateException
    dup
    invokespecial java/lang/IllegalStateException <init>:()V
    athrow
L74
    iconst_1
    ldc -47454393 (java.lang.Integer)
    getstatic ai au:I
    imul
    if_icmpne L171
    iload 1
    ldc 125277993 (java.lang.Integer)
    if_icmpgt L147
    new java/lang/IllegalStateException
    dup
    invokespecial java/lang/IllegalStateException <init>:()V
    athrow
L199
    getstatic ai ay:Ljava/lang/String;
    invokevirtual java/lang/String length:()I
    ifne L200
    iload 1
    ldc 125277993 (java.lang.Integer)
    if_icmpgt L201
    new java/lang/IllegalStateException
    dup
    invokespecial java/lang/IllegalStateException <init>:()V
    athrow
L201
    getstatic et db:Ljava/lang/String;
    getstatic et de:Ljava/lang/String;
    getstatic et dn:Ljava/lang/String;
    sipush 13223
    invokestatic dd w:(Ljava/lang/String;Ljava/lang/String;Ljava/lang/String;S)V
    goto L202
L106
    getstatic et hb:Ljava/lang/String;
    putstatic ai ab:Ljava/lang/String;
    goto L32
L200
    getstatic ai ag:Ljava/lang/String;
    invokevirtual java/lang/String length:()I
    ifne L203
    iload 1
    ldc 125277993 (java.lang.Integer)
    if_icmpgt L4
    new java/lang/IllegalStateException
    dup
    invokespecial java/lang/IllegalStateException <init>:()V
    athrow
L23
    putfield f c:Z
    goto L204
L5
    return
L205
    getstatic ez l:Lez;
    goto L206
L207
    getstatic et dx:Ljava/lang/String;
    getstatic et do:Ljava/lang/String;
    getstatic et dy:Ljava/lang/String;
    sipush 8713
    invokestatic dd w:(Ljava/lang/String;Ljava/lang/String;Ljava/lang/String;S)V
    goto L208
L209
    getstatic ez e:Lez;
    goto L76
L210
    getstatic ez l:Lez;
    goto L76
L186
    return
L77
    bipush 20
    bipush 80
    invokestatic dh g:(IB)V
L211
    return
L197
    sipush 462
    istore 6
L212
    iload 2
    iconst_1
    if_icmpne L60
    iload 1
    ldc 125277993 (java.lang.Integer)
    if_icmpgt L59
    new java/lang/IllegalStateException
    dup
    invokespecial java/lang/IllegalStateException <init>:()V
    athrow
L213
    iload 4
    sipush 296
    if_icmpgt L83
    iload 1
    ldc 125277993 (java.lang.Integer)
    if_icmpgt L214
    new java/lang/IllegalStateException
    dup
    invokespecial java/lang/IllegalStateException <init>:()V
    athrow
L61
    iload 3
    iload 6
    bipush 75
    iadd
    if_icmpgt L60
    iload 1
    ldc 125277993 (java.lang.Integer)
    if_icmpgt L215
    return
L99
    getstatic ai ay:Ljava/lang/String;
    iconst_0
    getstatic ai ay:Ljava/lang/String;
    invokevirtual java/lang/String length:()I
    iconst_1
    isub
    invokevirtual java/lang/String substring:(II)Ljava/lang/String;
    putstatic ai ay:Ljava/lang/String;
    goto L17
L216
    iload 3
    sipush 373
    if_icmplt L83
    iload 1
    ldc 125277993 (java.lang.Integer)
    if_icmpgt L82
    new java/lang/IllegalStateException
    dup
    invokespecial java/lang/IllegalStateException <init>:()V
    athrow
L217
    iconst_0
    putstatic ai au:I
    goto L218
L219
    return
L218
    ldc "" (java.lang.String)
    putstatic ai ay:Ljava/lang/String;
    goto L220
L221
    getstatic t cj:I
    ldc -327990299 (java.lang.Integer)
    imul
    bipush 80
    if_icmpne L222
    iload 1
    ldc 125277993 (java.lang.Integer)
    if_icmpgt L223
    new java/lang/IllegalStateException
    dup
    invokespecial java/lang/IllegalStateException <init>:()V
    athrow
L68
    ldc "" (java.lang.String)
    putstatic dn at:Ljava/lang/String;
    goto L224
L225
    return
L11
    ldc 1532705327 (java.lang.Integer)
    getstatic client q:I
    imul
    iconst_5
    if_icmpne L37
    goto L226
L227
    iconst_0
    istore 8
L228
    iconst_0
    istore 9
L229
    iload 9
    getstatic ai ar:Ljava/lang/String;
    invokevirtual java/lang/String length:()I
    if_icmpge L230
L231
    getstatic x cm:C
    getstatic ai ar:Ljava/lang/String;
    iload 9
    invokevirtual java/lang/String charAt:(I)C
    if_icmpne L232
    goto L233
L38
    bipush 10
    ldc 1532705327 (java.lang.Integer)
    getstatic client q:I
    imul
    if_icmpeq L44
    iload 1
    ldc 125277993 (java.lang.Integer)
    if_icmpgt L160
    new java/lang/IllegalStateException
    dup
    invokespecial java/lang/IllegalStateException <init>:()V
    athrow
L234
    goto L230
L232
    iinc 9 1
    goto L229
L230
    bipush 13
    ldc -327990299 (java.lang.Integer)
    getstatic t cj:I
    imul
    if_icmpne L235
    iload 1
    ldc 125277993 (java.lang.Integer)
    if_icmpgt L236
    new java/lang/IllegalStateException
    dup
    invokespecial java/lang/IllegalStateException <init>:()V
    athrow
L236
    iconst_0
    putstatic ai au:I
L237
    ldc "" (java.lang.String)
    putstatic ai ay:Ljava/lang/String;
L238
    ldc "" (java.lang.String)
    putstatic ai ag:Ljava/lang/String;
L239
    iconst_0
    putstatic aq ah:I
L240
    ldc "" (java.lang.String)
    putstatic dn at:Ljava/lang/String;
L241
    iconst_1
    putstatic ai al:Z
    goto L28
L242
    getstatic ai ag:Ljava/lang/String;
    iconst_0
    getstatic ai ag:Ljava/lang/String;
    invokevirtual java/lang/String length:()I
    iconst_1
    isub
    invokevirtual java/lang/String substring:(II)Ljava/lang/String;
    putstatic ai ag:Ljava/lang/String;
    goto L243
L244
    bipush 20
    bipush 39
    invokestatic dh g:(IB)V
    goto L39
L115
    ldc "" (java.lang.String)
    putstatic ai ag:Ljava/lang/String;
    goto L136
L245
    getstatic ai ay:Ljava/lang/String;
    iconst_0
    getstatic ai ay:Ljava/lang/String;
    invokevirtual java/lang/String length:()I
    iconst_1
    isub
    invokevirtual java/lang/String substring:(II)Ljava/lang/String;
    putstatic ai ay:Ljava/lang/String;
L108
    ldc -327990299 (java.lang.Integer)
    getstatic t cj:I
    imul
    bipush 84
    if_icmpeq L223
    iload 1
    ldc 125277993 (java.lang.Integer)
    if_icmpgt L221
    new java/lang/IllegalStateException
    dup
    invokespecial java/lang/IllegalStateException <init>:()V
    athrow
L159
    getstatic et hh:Ljava/lang/String;
    putstatic ai ab:Ljava/lang/String;
    goto L161
L223
    ldc 1549990025 (java.lang.Integer)
    putstatic ai ak:I
    goto L222
L84
    iload 4
    sipush 263
    if_icmplt L83
    iload 1
    ldc 125277993 (java.lang.Integer)
    if_icmpgt L213
    return
L246
    getstatic et hk:Ljava/lang/String;
    putstatic ai av:Ljava/lang/String;
    goto L33
L111
    iload 2
    iconst_1
    if_icmpne L190
    iload 1
    ldc 125277993 (java.lang.Integer)
    if_icmpgt L189
    new java/lang/IllegalStateException
    dup
    invokespecial java/lang/IllegalStateException <init>:()V
    athrow
L88
    new java/lang/StringBuilder
    dup
    invokespecial java/lang/StringBuilder <init>:()V
    ldc "secure" (java.lang.String)
    iconst_1
    bipush -101
    invokestatic ac dv:(Ljava/lang/String;ZB)Ljava/lang/String;
    invokevirtual java/lang/StringBuilder append:(Ljava/lang/String;)Ljava/lang/StringBuilder;
    ldc "m=account-creation/g=oldscape/create_account_funnel.ws" (java.lang.String)
    invokevirtual java/lang/StringBuilder append:(Ljava/lang/String;)Ljava/lang/StringBuilder;
    invokevirtual java/lang/StringBuilder toString:()Ljava/lang/String;
    iconst_1
    iconst_0
    ldc 462828307 (java.lang.Integer)
    invokestatic fo e:(Ljava/lang/String;ZZI)V
    goto L80
L153
    ldc -327990299 (java.lang.Integer)
    getstatic t cj:I
    imul
    bipush 85
    if_icmpne L243
    iload 1
    ldc 125277993 (java.lang.Integer)
    if_icmpgt L247
    new java/lang/IllegalStateException
    dup
    invokespecial java/lang/IllegalStateException <init>:()V
    athrow
L247
    getstatic ai ag:Ljava/lang/String;
    invokevirtual java/lang/String length:()I
    ifle L243
    iload 1
    ldc 125277993 (java.lang.Integer)
    if_icmpgt L242
    new java/lang/IllegalStateException
    dup
    invokespecial java/lang/IllegalStateException <init>:()V
    athrow
L91
    iconst_0
    putstatic ai au:I
    goto L187
L129
    ldc "" (java.lang.String)
    putstatic dn at:Ljava/lang/String;
    goto L248
L109
    getstatic ai ay:Ljava/lang/String;
    invokevirtual java/lang/String length:()I
    ifle L108
    iload 1
    ldc 125277993 (java.lang.Integer)
    if_icmpgt L245
    return
L170
    iconst_0
    putstatic ai ak:I
    goto L169
L249
    iload 3
    iload 5
    bipush 75
    iadd
    if_icmpgt L248
    goto L250
L251
    getstatic ai ay:Ljava/lang/String;
    invokevirtual java/lang/String trim:()Ljava/lang/String;
    putstatic ai ay:Ljava/lang/String;
L252
    getstatic ai ay:Ljava/lang/String;
    invokevirtual java/lang/String length:()I
    ifne L253
    iload 1
    ldc 125277993 (java.lang.Integer)
    if_icmpgt L254
    new java/lang/IllegalStateException
    dup
    invokespecial java/lang/IllegalStateException <init>:()V
    athrow
L254
    getstatic et db:Ljava/lang/String;
    getstatic et de:Ljava/lang/String;
    getstatic et dn:Ljava/lang/String;
    sipush 9003
    invokestatic dd w:(Ljava/lang/String;Ljava/lang/String;Ljava/lang/String;S)V
L255
    return
L253
    getstatic ai ag:Ljava/lang/String;
    invokevirtual java/lang/String length:()I
    ifne L256
    goto L207
L151
    iconst_1
    iload 2
    if_icmpne L56
    goto L154
L257
    iload 4
    iload 5
    bipush 15
    isub
    if_icmplt L183
    iload 1
    ldc 125277993 (java.lang.Integer)
    if_icmpgt L182
    new java/lang/IllegalStateException
    dup
    invokespecial java/lang/IllegalStateException <init>:()V
    athrow
L256
    getstatic et hl:Ljava/lang/String;
    getstatic et ho:Ljava/lang/String;
    getstatic et hi:Ljava/lang/String;
    sipush 10476
    invokestatic dd w:(Ljava/lang/String;Ljava/lang/String;Ljava/lang/String;S)V
L258
    getstatic dk ol:Lf;
    getfield f u:Ljava/util/LinkedHashMap;
    getstatic ai ay:Ljava/lang/String;
    sipush 12500
    invokestatic aw r:(Ljava/lang/CharSequence;S)I
    invokestatic java/lang/Integer valueOf:(I)Ljava/lang/Integer;
    invokevirtual java/util/LinkedHashMap containsKey:(Ljava/lang/Object;)Z
    ifeq L205
    iload 1
    ldc 125277993 (java.lang.Integer)
    if_icmpgt L259
    new java/lang/IllegalStateException
    dup
    invokespecial java/lang/IllegalStateException <init>:()V
    athrow
L33
    ldc -834170249 (java.lang.Integer)
    putstatic ai au:I
    goto L260
L261
    getstatic dk ol:Lf;
    getfield f u:Ljava/util/LinkedHashMap;
    getstatic ai ay:Ljava/lang/String;
    sipush 31383
    invokestatic aw r:(Ljava/lang/CharSequence;S)I
    invokestatic java/lang/Integer valueOf:(I)Ljava/lang/Integer;
    invokevirtual java/util/LinkedHashMap containsKey:(Ljava/lang/Object;)Z
    ifeq L210
    iload 1
    ldc 125277993 (java.lang.Integer)
    if_icmpgt L209
    new java/lang/IllegalStateException
    dup
    invokespecial java/lang/IllegalStateException <init>:()V
    athrow
L16
    getstatic dk ol:Lf;
    getstatic dk ol:Lf;
    getfield f c:Z
    ifne L22
    iload 1
    ldc 125277993 (java.lang.Integer)
    if_icmpgt L262
    new java/lang/IllegalStateException
    dup
    invokespecial java/lang/IllegalStateException <init>:()V
    athrow
L263
    bipush 13
    getstatic t cj:I
    ldc -327990299 (java.lang.Integer)
    imul
    if_icmpne L264
    iload 1
    ldc 125277993 (java.lang.Integer)
    if_icmpgt L265
    new java/lang/IllegalStateException
    dup
    invokespecial java/lang/IllegalStateException <init>:()V
    athrow
L233
    iconst_1
    istore 8
    goto L234
L266
    iload 8
    ifeq L28
    iload 1
    ldc 125277993 (java.lang.Integer)
    if_icmpgt L267
    new java/lang/IllegalStateException
    dup
    invokespecial java/lang/IllegalStateException <init>:()V
    athrow
L267
    getstatic ai ag:Ljava/lang/String;
    invokevirtual java/lang/String length:()I
    bipush 20
    if_icmpge L28
    iload 1
    ldc 125277993 (java.lang.Integer)
    if_icmpgt L268
    new java/lang/IllegalStateException
    dup
    invokespecial java/lang/IllegalStateException <init>:()V
    athrow
L268
    new java/lang/StringBuilder
    dup
    invokespecial java/lang/StringBuilder <init>:()V
    getstatic ai ag:Ljava/lang/String;
    invokevirtual java/lang/StringBuilder append:(Ljava/lang/String;)Ljava/lang/StringBuilder;
    getstatic x cm:C
    invokevirtual java/lang/StringBuilder append:(C)Ljava/lang/StringBuilder;
    invokevirtual java/lang/StringBuilder toString:()Ljava/lang/String;
    putstatic ai ag:Ljava/lang/String;
L28
    goto L60
L269
    goto L136
L123
    getstatic et ha:Ljava/lang/String;
    putstatic ai ae:Ljava/lang/String;
    goto L132
L165
    sipush 302
    istore 5
L270
    sipush 321
    istore 6
L271
    iconst_1
    iload 2
    if_icmpne L41
    iload 1
    ldc 125277993 (java.lang.Integer)
    if_icmpgt L272
    new java/lang/IllegalStateException
    dup
    invokespecial java/lang/IllegalStateException <init>:()V
    athrow
L273
    getstatic ai ay:Ljava/lang/String;
    invokevirtual java/lang/String length:()I
    sipush 320
    if_icmpge L28
    goto L27
L274
    iload 3
    bipush 75
    iload 5
    iadd
    if_icmpgt L41
    goto L40
L275
    iload 4
    iload 6
    bipush 20
    isub
    if_icmplt L276
    iload 1
    ldc 125277993 (java.lang.Integer)
    if_icmpgt L277
    new java/lang/IllegalStateException
    dup
    invokespecial java/lang/IllegalStateException <init>:()V
    athrow
L42
    iload 4
    bipush 20
    iload 6
    iadd
    if_icmpgt L41
    iload 1
    ldc 125277993 (java.lang.Integer)
    if_icmpgt L140
    return
L278
    sipush 302
    istore 5
    goto L279
L141
    getstatic dn at:Ljava/lang/String;
    invokevirtual java/lang/String length:()I
    bipush 6
    if_icmpeq L280
    iload 1
    ldc 125277993 (java.lang.Integer)
    if_icmpgt L281
    new java/lang/IllegalStateException
    dup
    invokespecial java/lang/IllegalStateException <init>:()V
    athrow
L281
    getstatic et ab:Ljava/lang/String;
    getstatic et av:Ljava/lang/String;
    getstatic et ay:Ljava/lang/String;
    sipush 27995
    invokestatic dd w:(Ljava/lang/String;Ljava/lang/String;Ljava/lang/String;S)V
L282
    return
L280
    getstatic dn at:Ljava/lang/String;
    invokestatic java/lang/Integer parseInt:(Ljava/lang/String;)I
    ldc 1455632759 (java.lang.Integer)
    imul
    putstatic aq ah:I
L283
    ldc "" (java.lang.String)
    putstatic dn at:Ljava/lang/String;
L284
    getstatic ai al:Z
    ifeq L285
    getstatic ez a:Lez;
    goto L286
L285
    getstatic ez c:Lez;
L286
    putstatic ai aj:Lez;
    goto L287
L226
    return
L288
    bipush 20
    bipush 71
    invokestatic dh g:(IB)V
L289
    return
L54
    getstatic ep j:I
    ldc -642165313 (java.lang.Integer)
    imul
    iload 2
    if_icmplt L24
    iload 1
    ldc 125277993 (java.lang.Integer)
    if_icmpgt L57
    new java/lang/IllegalStateException
    dup
    invokespecial java/lang/IllegalStateException <init>:()V
    athrow
L290
    goto L136
L7
    iinc 5 15
    goto L291
L202
    return
L292
    getstatic et hv:Ljava/lang/String;
    putstatic ai ab:Ljava/lang/String;
    goto L246
L214
    getstatic ai al:Z
    ifne L293
    iconst_1
    goto L294
L293
    iconst_0
L294
    putstatic ai al:Z
    goto L83
L8
    iconst_0
    putstatic ai ak:I
    goto L7
L113
    iload 3
    sipush 348
    if_icmplt L112
    iload 3
    sipush 416
    if_icmpgt L112
    iload 1
    ldc 125277993 (java.lang.Integer)
    if_icmpgt L295
    return
L295
    iload 4
    sipush 351
    if_icmplt L112
    iload 1
    ldc 125277993 (java.lang.Integer)
    if_icmpgt L296
    new java/lang/IllegalStateException
    dup
    invokespecial java/lang/IllegalStateException <init>:()V
    athrow
L296
    iload 4
    sipush 363
    if_icmpgt L112
    iload 1
    ldc 125277993 (java.lang.Integer)
    if_icmpgt L297
    new java/lang/IllegalStateException
    dup
    invokespecial java/lang/IllegalStateException <init>:()V
    athrow
L297
    new java/lang/StringBuilder
    dup
    invokespecial java/lang/StringBuilder <init>:()V
    ldc "secure" (java.lang.String)
    iconst_1
    bipush -39
    invokestatic ac dv:(Ljava/lang/String;ZB)Ljava/lang/String;
    invokevirtual java/lang/StringBuilder append:(Ljava/lang/String;)Ljava/lang/StringBuilder;
    ldc "m=totp-authenticator/disableTOTPRequest" (java.lang.String)
    invokevirtual java/lang/StringBuilder append:(Ljava/lang/String;)Ljava/lang/StringBuilder;
    invokevirtual java/lang/StringBuilder toString:()Ljava/lang/String;
    iconst_1
    iconst_0
    ldc 462828307 (java.lang.Integer)
    invokestatic fo e:(Ljava/lang/String;ZZI)V
    goto L112
L14
    ldc -327990299 (java.lang.Integer)
    getstatic t cj:I
    imul
    bipush 84
    if_icmpne L298
    goto L299
L131
    iconst_1
    iload 2
    if_icmpne L248
    goto L300
L155
    iload 3
    bipush 75
    iload 5
    iadd
    if_icmpgt L56
    iload 1
    ldc 125277993 (java.lang.Integer)
    if_icmpgt L156
    return
L188
    ldc "" (java.lang.String)
    putstatic ai ag:Ljava/lang/String;
    goto L301
L250
    iload 4
    iload 6
    bipush 20
    isub
    if_icmplt L248
    iload 1
    ldc 125277993 (java.lang.Integer)
    if_icmpgt L302
    new java/lang/IllegalStateException
    dup
    invokespecial java/lang/IllegalStateException <init>:()V
    athrow
L302
    iload 4
    bipush 20
    iload 6
    iadd
    if_icmpgt L248
    iload 1
    ldc 125277993 (java.lang.Integer)
    if_icmpgt L104
    new java/lang/IllegalStateException
    dup
    invokespecial java/lang/IllegalStateException <init>:()V
    athrow
L58
    ldc 1563808941 (java.lang.Integer)
    getstatic ep m:I
    imul
    iload 3
    if_icmplt L24
    iload 1
    ldc 125277993 (java.lang.Integer)
    if_icmpgt L62
    new java/lang/IllegalStateException
    dup
    invokespecial java/lang/IllegalStateException <init>:()V
    athrow
L303
    goto L304
L21
    ldc "" (java.lang.String)
    putstatic ai ag:Ljava/lang/String;
    goto L128
L291
    iload 2
    iconst_1
    if_icmpne L183
    goto L257
L305
    getstatic et ha:Ljava/lang/String;
    putstatic ai ae:Ljava/lang/String;
    goto L306
L248
    bipush -25
    invokestatic cm c:(B)Z
    ifeq L307
L308
    iconst_0
    istore 7
L309
    iconst_0
    istore 8
L310
    iload 8
    getstatic ai aq:Ljava/lang/String;
    invokevirtual java/lang/String length:()I
    if_icmpge L89
    iload 1
    ldc 125277993 (java.lang.Integer)
    if_icmpgt L311
    return
L311
    getstatic x cm:C
    getstatic ai aq:Ljava/lang/String;
    iload 8
    invokevirtual java/lang/String charAt:(I)C
    if_icmpne L312
    iload 1
    ldc 125277993 (java.lang.Integer)
    if_icmpgt L313
    new java/lang/IllegalStateException
    dup
    invokespecial java/lang/IllegalStateException <init>:()V
    athrow
L313
    iconst_1
    istore 7
L314
    goto L89
L312
    iinc 8 1
    goto L310
L315
    iconst_0
    istore 8
    goto L316
L299
    getstatic dn at:Ljava/lang/String;
    invokevirtual java/lang/String trim:()Ljava/lang/String;
    pop
    goto L120
L169
    getstatic t cj:I
    ldc -327990299 (java.lang.Integer)
    imul
    bipush 84
    if_icmpne L266
    iload 1
    ldc 125277993 (java.lang.Integer)
    if_icmpgt L251
    new java/lang/IllegalStateException
    dup
    invokespecial java/lang/IllegalStateException <init>:()V
    athrow
L317
    iload 4
    iload 6
    bipush 20
    iadd
    if_icmpgt L177
    iload 1
    ldc 125277993 (java.lang.Integer)
    if_icmpgt L185
    new java/lang/IllegalStateException
    dup
    invokespecial java/lang/IllegalStateException <init>:()V
    athrow
L301
    iconst_0
    putstatic aq ah:I
L318
    ldc "" (java.lang.String)
    putstatic dn at:Ljava/lang/String;
    goto L319
L90
    bipush 85
    ldc -327990299 (java.lang.Integer)
    getstatic t cj:I
    imul
    if_icmpne L14
    iload 1
    ldc 125277993 (java.lang.Integer)
    if_icmpgt L320
    return
L320
    getstatic dn at:Ljava/lang/String;
    invokevirtual java/lang/String length:()I
    ifle L14
    goto L13
L321
    iconst_1
    iload 2
    if_icmpne L96
    iload 1
    ldc 125277993 (java.lang.Integer)
    if_icmpgt L95
    new java/lang/IllegalStateException
    dup
    invokespecial java/lang/IllegalStateException <init>:()V
    athrow
L260
    iconst_0
    putstatic ai ak:I
    goto L96
L179
    getstatic et hq:Ljava/lang/String;
    putstatic ai ae:Ljava/lang/String;
    goto L292
L322
    return
L122
    getstatic et ab:Ljava/lang/String;
    getstatic et av:Ljava/lang/String;
    getstatic et ay:Ljava/lang/String;
    sipush 2683
    invokestatic dd w:(Ljava/lang/String;Ljava/lang/String;Ljava/lang/String;S)V
    goto L225
L323
    getstatic et hh:Ljava/lang/String;
    putstatic ai ab:Ljava/lang/String;
    goto L324
L121
    getstatic dn at:Ljava/lang/String;
    invokestatic java/lang/Integer parseInt:(Ljava/lang/String;)I
    ldc 1455632759 (java.lang.Integer)
    imul
    putstatic aq ah:I
L325
    ldc "" (java.lang.String)
    putstatic dn at:Ljava/lang/String;
    goto L92
L222
    iload 8
    ifeq L28
    iload 1
    ldc 125277993 (java.lang.Integer)
    if_icmpgt L273
    new java/lang/IllegalStateException
    dup
    invokespecial java/lang/IllegalStateException <init>:()V
    athrow
L94
    getstatic ez a:Lez;
    goto L46
L93
    getstatic ez c:Lez;
    goto L46
L12
    iconst_4
    getstatic ep s:I
    ldc -1750678861 (java.lang.Integer)
    imul
    if_icmpne L11
    iload 1
    ldc 125277993 (java.lang.Integer)
    if_icmpgt L9
    new java/lang/IllegalStateException
    dup
    invokespecial java/lang/IllegalStateException <init>:()V
    athrow
L47
    getstatic et hl:Ljava/lang/String;
    getstatic et ho:Ljava/lang/String;
    getstatic et hi:Ljava/lang/String;
    sipush 6401
    invokestatic dd w:(Ljava/lang/String;Ljava/lang/String;Ljava/lang/String;S)V
    goto L326
L243
    ldc -327990299 (java.lang.Integer)
    getstatic t cj:I
    imul
    bipush 84
    if_icmpeq L170
    iload 1
    ldc 125277993 (java.lang.Integer)
    if_icmpgt L168
    new java/lang/IllegalStateException
    dup
    invokespecial java/lang/IllegalStateException <init>:()V
    athrow
L327
    return
L298
    iload 7
    ifeq L319
    iload 1
    ldc 125277993 (java.lang.Integer)
    if_icmpgt L328
    new java/lang/IllegalStateException
    dup
    invokespecial java/lang/IllegalStateException <init>:()V
    athrow
L328
    getstatic dn at:Ljava/lang/String;
    invokevirtual java/lang/String length:()I
    bipush 6
    if_icmpge L319
    iload 1
    ldc 125277993 (java.lang.Integer)
    if_icmpgt L329
    new java/lang/IllegalStateException
    dup
    invokespecial java/lang/IllegalStateException <init>:()V
    athrow
L329
    new java/lang/StringBuilder
    dup
    invokespecial java/lang/StringBuilder <init>:()V
    getstatic dn at:Ljava/lang/String;
    invokevirtual java/lang/StringBuilder append:(Ljava/lang/String;)Ljava/lang/StringBuilder;
    getstatic x cm:C
    invokevirtual java/lang/StringBuilder append:(C)Ljava/lang/StringBuilder;
    invokevirtual java/lang/StringBuilder toString:()Ljava/lang/String;
    putstatic dn at:Ljava/lang/String;
L319
    goto L248
L307
    goto L136
L164
    iconst_5
    ldc -47454393 (java.lang.Integer)
    getstatic ai au:I
    imul
    if_icmpne L330
    iload 1
    ldc 125277993 (java.lang.Integer)
    if_icmpgt L278
    return
L203
    getstatic et hl:Ljava/lang/String;
    getstatic et ho:Ljava/lang/String;
    getstatic et hi:Ljava/lang/String;
    sipush 5494
    invokestatic dd w:(Ljava/lang/String;Ljava/lang/String;Ljava/lang/String;S)V
    goto L261
L279
    sipush 321
    istore 6
    goto L176
L272
    iload 3
    iload 5
    bipush 75
    isub
    if_icmplt L41
    iload 1
    ldc 125277993 (java.lang.Integer)
    if_icmpgt L274
    new java/lang/IllegalStateException
    dup
    invokespecial java/lang/IllegalStateException <init>:()V
    athrow
L178
    iload 3
    iload 5
    bipush 75
    isub
    if_icmplt L177
    iload 1
    ldc 125277993 (java.lang.Integer)
    if_icmpgt L331
    new java/lang/IllegalStateException
    dup
    invokespecial java/lang/IllegalStateException <init>:()V
    athrow
L331
    iload 3
    bipush 75
    iload 5
    iadd
    if_icmpgt L177
    iload 1
    ldc 125277993 (java.lang.Integer)
    if_icmpgt L332
    new java/lang/IllegalStateException
    dup
    invokespecial java/lang/IllegalStateException <init>:()V
    athrow
L332
    iload 4
    iload 6
    bipush 20
    isub
    if_icmplt L177
    iload 1
    ldc 125277993 (java.lang.Integer)
    if_icmpgt L317
    new java/lang/IllegalStateException
    dup
    invokespecial java/lang/IllegalStateException <init>:()V
    athrow
L181
    ldc -1668340498 (java.lang.Integer)
    putstatic ai au:I
    goto L114
L235
    getstatic ai ak:I
    ldc 423886265 (java.lang.Integer)
    imul
    ifne L152
    iload 1
    ldc 125277993 (java.lang.Integer)
    if_icmpgt L107
    return
L3
    aload 0
    bipush -128
    invokestatic r g:(Lew;B)V
    goto L219
L177
    sipush 462
    istore 5
L333
    iconst_1
    iload 2
    if_icmpne L276
    iload 3
    iload 5
    bipush 75
    isub
    if_icmplt L276
    iload 1
    ldc 125277993 (java.lang.Integer)
    if_icmpgt L334
    new java/lang/IllegalStateException
    dup
    invokespecial java/lang/IllegalStateException <init>:()V
    athrow
L334
    iload 3
    bipush 75
    iload 5
    iadd
    if_icmpgt L276
    iload 1
    ldc 125277993 (java.lang.Integer)
    if_icmpgt L275
    new java/lang/IllegalStateException
    dup
    invokespecial java/lang/IllegalStateException <init>:()V
    athrow
L206
    putstatic ai aj:Lez;
    goto L244
L277
    iload 4
    iload 6
    bipush 20
    iadd
    if_icmpgt L276
    iload 1
    ldc 125277993 (java.lang.Integer)
    if_icmpgt L335
    new java/lang/IllegalStateException
    dup
    invokespecial java/lang/IllegalStateException <init>:()V
    athrow
L335
    getstatic et ha:Ljava/lang/String;
    putstatic ai ae:Ljava/lang/String;
    goto L336
L265
    getstatic et ha:Ljava/lang/String;
    putstatic ai ae:Ljava/lang/String;
    goto L323
L215
    iload 4
    iload 7
    bipush 20
    isub
    if_icmplt L60
    iload 1
    ldc 125277993 (java.lang.Integer)
    if_icmpgt L337
    new java/lang/IllegalStateException
    dup
    invokespecial java/lang/IllegalStateException <init>:()V
    athrow
L117
    ldc -1668340498 (java.lang.Integer)
    putstatic ai au:I
L338
    iconst_0
    putstatic ai ak:I
L339
    ldc "" (java.lang.String)
    putstatic ai ag:Ljava/lang/String;
L276
    bipush -120
    invokestatic cm c:(B)Z
    ifeq L290
L340
    iconst_0
    istore 7
    goto L315
L204
    ldc 211669360 (java.lang.Integer)
    invokestatic aa l:(I)V
    goto L29
L316
    iload 8
    getstatic ai ar:Ljava/lang/String;
    invokevirtual java/lang/String length:()I
    if_icmpge L304
    iload 1
    ldc 125277993 (java.lang.Integer)
    if_icmpgt L341
    new java/lang/IllegalStateException
    dup
    invokespecial java/lang/IllegalStateException <init>:()V
    athrow
L341
    getstatic x cm:C
    getstatic ai ar:Ljava/lang/String;
    iload 8
    invokevirtual java/lang/String charAt:(I)C
    if_icmpne L342
L343
    iconst_1
    istore 7
    goto L303
L337
    iload 4
    bipush 20
    iload 7
    iadd
    if_icmpgt L60
    iload 1
    ldc 125277993 (java.lang.Integer)
    if_icmpgt L217
    new java/lang/IllegalStateException
    dup
    invokespecial java/lang/IllegalStateException <init>:()V
    athrow
L342
    iinc 8 1
    goto L316
L147
    bipush -29
    invokestatic cm c:(B)Z
    ifeq L149
    iload 1
    ldc 125277993 (java.lang.Integer)
    if_icmpgt L34
    new java/lang/IllegalStateException
    dup
    invokespecial java/lang/IllegalStateException <init>:()V
    athrow
L344
    getstatic et ha:Ljava/lang/String;
    putstatic ai ae:Ljava/lang/String;
L345
    getstatic et hh:Ljava/lang/String;
    putstatic ai ab:Ljava/lang/String;
    goto L118
L136
    return
L119
    ldc -1668340498 (java.lang.Integer)
    putstatic ai au:I
L346
    iconst_0
    putstatic ai ak:I
L347
    ldc "" (java.lang.String)
    putstatic ai ag:Ljava/lang/String;
    goto L348
L304
    ldc -327990299 (java.lang.Integer)
    getstatic t cj:I
    imul
    bipush 13
    if_icmpne L65
    iload 1
    ldc 125277993 (java.lang.Integer)
    if_icmpgt L344
    new java/lang/IllegalStateException
    dup
    invokespecial java/lang/IllegalStateException <init>:()V
    athrow
L262
    iconst_1
    goto L23
L224
    iconst_1
    putstatic ai al:Z
    goto L60
L300
    iload 3
    iload 5
    bipush 75
    isub
    if_icmplt L248
    goto L249
L19
    bipush 8
    invokestatic am c:(B)V
    goto L322
L80
    sipush 462
    istore 5
    goto L321
L18
    iload 7
    ifeq L348
    iload 1
    ldc 125277993 (java.lang.Integer)
    if_icmpgt L349
    new java/lang/IllegalStateException
    dup
    invokespecial java/lang/IllegalStateException <init>:()V
    athrow
L349
    getstatic ai ay:Ljava/lang/String;
    invokevirtual java/lang/String length:()I
    sipush 320
    if_icmpge L348
    iload 1
    ldc 125277993 (java.lang.Integer)
    if_icmpgt L350
    new java/lang/IllegalStateException
    dup
    invokespecial java/lang/IllegalStateException <init>:()V
    athrow
L350
    new java/lang/StringBuilder
    dup
    invokespecial java/lang/StringBuilder <init>:()V
    getstatic ai ay:Ljava/lang/String;
    invokevirtual java/lang/StringBuilder append:(Ljava/lang/String;)Ljava/lang/StringBuilder;
    getstatic x cm:C
    invokevirtual java/lang/StringBuilder append:(C)Ljava/lang/StringBuilder;
    invokevirtual java/lang/StringBuilder toString:()Ljava/lang/String;
    putstatic ai ay:Ljava/lang/String;
L348
    goto L276
L287
    getstatic et hl:Ljava/lang/String;
    getstatic et ho:Ljava/lang/String;
    getstatic et hi:Ljava/lang/String;
    sipush 31572
    invokestatic dd w:(Ljava/lang/String;Ljava/lang/String;Ljava/lang/String;S)V
    goto L288
L330
    getstatic ai au:I
    ldc -47454393 (java.lang.Integer)
    imul
    bipush 6
    if_icmpne L136
    iload 1
    ldc 125277993 (java.lang.Integer)
    if_icmpgt L264
    new java/lang/IllegalStateException
    dup
    invokespecial java/lang/IllegalStateException <init>:()V
    athrow
L264
    bipush -12
    invokestatic cm c:(B)Z
    ifeq L351
    iload 1
    ldc 125277993 (java.lang.Integer)
    if_icmpgt L352
    return
L352
    bipush 84
    getstatic t cj:I
    ldc -327990299 (java.lang.Integer)
    imul
    if_icmpeq L265
    goto L263
L45
    getstatic ep s:I
    ldc -1750678861 (java.lang.Integer)
    imul
    iconst_1
    if_icmpeq L50
    iload 1
    ldc 125277993 (java.lang.Integer)
    if_icmpgt L48
    new java/lang/IllegalStateException
    dup
    invokespecial java/lang/IllegalStateException <init>:()V
    athrow
L220
    ldc "" (java.lang.String)
    putstatic ai ag:Ljava/lang/String;
    goto L67
L259
    getstatic ez e:Lez;
    goto L206
L60
    bipush -17
    invokestatic cm c:(B)Z
    ifeq L269
    iload 1
    ldc 125277993 (java.lang.Integer)
    if_icmpgt L227
    return
L353
    ldc -1668340498 (java.lang.Integer)
    putstatic ai au:I
L354
    iconst_0
    putstatic ai ak:I
L355
    ldc "" (java.lang.String)
    putstatic ai ag:Ljava/lang/String;
    goto L264
L351
    sipush 321
    istore 5
L356
    iload 2
    iconst_1
    if_icmpne L136
    iload 1
    ldc 125277993 (java.lang.Integer)
    if_icmpgt L357
    new java/lang/IllegalStateException
    dup
    invokespecial java/lang/IllegalStateException <init>:()V
    athrow
L357
    iload 4
    iload 5
    bipush 20
    isub
    if_icmplt L136
    iload 4
    iload 5
    bipush 20
    iadd
    if_icmpgt L136
    goto L305
L208
    return
L306
    getstatic et hh:Ljava/lang/String;
    putstatic ai ab:Ljava/lang/String;
    goto L180
L324
    getstatic et hz:Ljava/lang/String;
    putstatic ai av:Ljava/lang/String;
    goto L353
L41
    iconst_1
    iload 2
    if_icmpne L83
    iload 1
    ldc 125277993 (java.lang.Integer)
    if_icmpgt L216
    new java/lang/IllegalStateException
    dup
    invokespecial java/lang/IllegalStateException <init>:()V
    athrow
L336
    getstatic et hh:Ljava/lang/String;
    putstatic ai ab:Ljava/lang/String;
    goto L116
L326
    bipush 20
    bipush 13
    invokestatic dh g:(IB)V
    goto L327
L198
    getstatic ai ay:Ljava/lang/String;
    invokevirtual java/lang/String trim:()Ljava/lang/String;
    putstatic ai ay:Ljava/lang/String;
    goto L199
L358
    new java/lang/StringBuilder
    dup
    invokespecial java/lang/StringBuilder <init>:()V
    ldc "ap.l(" (java.lang.String)
    invokevirtual java/lang/StringBuilder append:(Ljava/lang/String;)Ljava/lang/StringBuilder;
    ldc 41 (java.lang.Integer)
    invokevirtual java/lang/StringBuilder append:(C)Ljava/lang/StringBuilder;
    invokevirtual java/lang/StringBuilder toString:()Ljava/lang/String;
    invokestatic k a:(Ljava/lang/Throwable;Ljava/lang/String;)Lee;
    athrow
