aq e (II)Ld;L1
    getstatic d e:Lgr;
    iload 0
    i2l
    invokevirtual gr e:(J)Lgd;
    checkcast d
    astore 2
    goto L2
L3
    aload 4
    ldc 1782921573 (java.lang.Integer)
    aload 4
    getfield dh e:[B
    arraylength
    bipush 12
    isub
    imul
    putfield dh a:I
    goto L4
L5
    aload 2
    getfield d l:[I
    iload 6
    aload 4
    ldc 1182180508 (java.lang.Integer)
    invokevirtual dh z:(I)I
    iastore
    goto L6
L7
    getstatic a bu:Lfo;
    iload 0
    iconst_0
    ldc -457907038 (java.lang.Integer)
    invokevirtual fo l:(III)[B
    astore 3
L8
    aconst_null
    aload 3
    if_acmpne L9
    iload 1
    ldc -310341683 (java.lang.Integer)
    if_icmpne L10
    new java/lang/IllegalStateException
    dup
    invokespecial java/lang/IllegalStateException <init>:()V
    athrow
L11
    new dh
    dup
    aload 3
    invokespecial dh <init>:([B)V
    astore 4
    goto L3
L9
    new d
    dup
    invokespecial d <init>:()V
    astore 2
    goto L11
L2
    aload 2
    ifnull L7
    aload 2
    areturn
L12
    aload 2
    getfield d l:[I
    iload 6
    aload 4
    ldc -2125820976 (java.lang.Integer)
    invokevirtual dh x:(I)I
    iastore
    goto L6
L13
    aload 2
    iload 5
    newarray 10
    putfield d a:[I
    goto L14
L15
    aload 2
    aload 4
    ldc 199395834 (java.lang.Integer)
    invokevirtual dh q:(I)I
    ldc -1842969547 (java.lang.Integer)
    imul
    putfield d u:I
    goto L16
L17
    aload 2
    aload 4
    ldc -2064274698 (java.lang.Integer)
    invokevirtual dh q:(I)I
    ldc -1002530823 (java.lang.Integer)
    imul
    putfield d i:I
L18
    aload 2
    aload 4
    ldc 127393056 (java.lang.Integer)
    invokevirtual dh q:(I)I
    ldc -1751075569 (java.lang.Integer)
    imul
    putfield d r:I
L19
    aload 4
    iconst_0
    putfield dh a:I
L20
    aload 4
    ldc -645701925 (java.lang.Integer)
    invokevirtual dh v:(I)Ljava/lang/String;
    pop
    goto L13
L4
    aload 4
    ldc -2023319473 (java.lang.Integer)
    invokevirtual dh x:(I)I
    istore 5
    goto L15
L14
    aload 2
    iload 5
    newarray 10
    putfield d l:[I
L21
    aload 2
    iload 5
    anewarray java/lang/String
    putfield d c:[Ljava/lang/String;
L22
    iconst_0
    istore 6
L23
    aload 4
    getfield dh a:I
    ldc 910905453 (java.lang.Integer)
    imul
    aload 4
    getfield dh e:[B
    arraylength
    bipush 12
    isub
    if_icmpge L24
    iload 1
    ldc -310341683 (java.lang.Integer)
    if_icmpne L25
    new java/lang/IllegalStateException
    dup
    invokespecial java/lang/IllegalStateException <init>:()V
    athrow
L25
    aload 4
    ldc -1662403069 (java.lang.Integer)
    invokevirtual dh q:(I)I
    istore 7
    goto L26
L27
    aload 2
    areturn
L28
    aload 2
    getfield d c:[Ljava/lang/String;
    iload 6
    aload 4
    ldc 1846981790 (java.lang.Integer)
    invokevirtual dh p:(I)Ljava/lang/String;
    aastore
    goto L6
L29
    iload 7
    bipush 100
    if_icmpge L5
    iload 1
    ldc -310341683 (java.lang.Integer)
    if_icmpne L30
    new java/lang/IllegalStateException
    dup
    invokespecial java/lang/IllegalStateException <init>:()V
    athrow
L16
    aload 2
    aload 4
    ldc -413222847 (java.lang.Integer)
    invokevirtual dh q:(I)I
    ldc -1636230453 (java.lang.Integer)
    imul
    putfield d w:I
    goto L17
L31
    bipush 38
    iload 7
    if_icmpeq L5
    iload 1
    ldc -310341683 (java.lang.Integer)
    if_icmpne L32
    new java/lang/IllegalStateException
    dup
    invokespecial java/lang/IllegalStateException <init>:()V
    athrow
L26
    iconst_3
    iload 7
    if_icmpne L29
    iload 1
    ldc -310341683 (java.lang.Integer)
    if_icmpne L28
    new java/lang/IllegalStateException
    dup
    invokespecial java/lang/IllegalStateException <init>:()V
    athrow
L30
    iload 7
    bipush 21
    if_icmpeq L5
    iload 1
    ldc -310341683 (java.lang.Integer)
    if_icmpne L31
    new java/lang/IllegalStateException
    dup
    invokespecial java/lang/IllegalStateException <init>:()V
    athrow
L32
    bipush 39
    iload 7
    if_icmpeq L5
    iload 1
    ldc -310341683 (java.lang.Integer)
    if_icmpne L12
    new java/lang/IllegalStateException
    dup
    invokespecial java/lang/IllegalStateException <init>:()V
    athrow
L6
    aload 2
    getfield d a:[I
    iload 6
    iinc 6 1
    iload 7
    iastore
L33
    goto L23
L24
    getstatic d e:Lgr;
    aload 2
    iload 0
    i2l
    invokevirtual gr l:(Lgd;J)V
    goto L27
L10
    aconst_null
    areturn
L34
    new java/lang/StringBuilder
    dup
    invokespecial java/lang/StringBuilder <init>:()V
    ldc "aq.e(" (java.lang.String)
    invokevirtual java/lang/StringBuilder append:(Ljava/lang/String;)Ljava/lang/StringBuilder;
    ldc 41 (java.lang.Integer)
    invokevirtual java/lang/StringBuilder append:(C)Ljava/lang/StringBuilder;
    invokevirtual java/lang/StringBuilder toString:()Ljava/lang/String;
    invokestatic k a:(Ljava/lang/Throwable;Ljava/lang/String;)Lee;
    athrow
