at c (Ldh;II)VL1
    iload 2
    iconst_1
    if_icmpne L2
    iload 3
    ldc 418566775 (java.lang.Integer)
    if_icmplt L3
    new java/lang/IllegalStateException
    dup
    invokespecial java/lang/IllegalStateException <init>:()V
    athrow
L2
    iload 2
    iconst_2
    if_icmpne L4
    iload 3
    ldc 418566775 (java.lang.Integer)
    if_icmplt L5
    return
L6
    iinc 5 1
    goto L7
L5
    aload 0
    aload 1
    ldc -1672878726 (java.lang.Integer)
    invokevirtual dh q:(I)I
    ldc -709767215 (java.lang.Integer)
    imul
    putfield at i:I
    goto L8
L9
    bipush 8
    iload 2
    if_icmpne L10
    iload 3
    ldc 418566775 (java.lang.Integer)
    if_icmplt L11
    new java/lang/IllegalStateException
    dup
    invokespecial java/lang/IllegalStateException <init>:()V
    athrow
L12
    aload 0
    aload 1
    ldc 423660292 (java.lang.Integer)
    invokevirtual dh q:(I)I
    ldc -1812790579 (java.lang.Integer)
    imul
    putfield at h:I
    goto L8
L13
    aload 0
    getfield at o:[S
    iload 5
    aload 1
    ldc 2008648691 (java.lang.Integer)
    invokevirtual dh q:(I)I
    i2s
    sastore
    goto L14
L4
    iload 2
    iconst_4
    if_icmpne L15
    iload 3
    ldc 418566775 (java.lang.Integer)
    if_icmplt L12
    new java/lang/IllegalStateException
    dup
    invokespecial java/lang/IllegalStateException <init>:()V
    athrow
L16
    iload 2
    bipush 6
    if_icmpne L17
    iload 3
    ldc 418566775 (java.lang.Integer)
    if_icmplt L18
    new java/lang/IllegalStateException
    dup
    invokespecial java/lang/IllegalStateException <init>:()V
    athrow
L15
    iload 2
    iconst_5
    if_icmpne L16
    aload 0
    aload 1
    ldc -1995731661 (java.lang.Integer)
    invokevirtual dh q:(I)I
    ldc -2066570425 (java.lang.Integer)
    imul
    putfield at s:I
    goto L8
L19
    aload 0
    aload 1
    ldc 2076215288 (java.lang.Integer)
    invokevirtual dh z:(I)I
    ldc -1173673053 (java.lang.Integer)
    imul
    putfield at m:I
    goto L8
L10
    iload 2
    bipush 40
    if_icmpne L20
    goto L21
L11
    aload 0
    aload 1
    ldc 1710520012 (java.lang.Integer)
    invokevirtual dh z:(I)I
    ldc 391685045 (java.lang.Integer)
    imul
    putfield at t:I
    goto L8
L3
    aload 0
    aload 1
    ldc -1580992177 (java.lang.Integer)
    invokevirtual dh q:(I)I
    ldc -175394465 (java.lang.Integer)
    imul
    putfield at w:I
    goto L8
L21
    aload 1
    ldc 913765533 (java.lang.Integer)
    invokevirtual dh z:(I)I
    istore 4
    goto L22
L23
    iconst_0
    istore 5
    goto L7
L24
    aload 0
    iload 4
    newarray 9
    putfield at f:[S
    goto L23
L14
    iinc 5 1
    goto L25
L7
    iload 5
    iload 4
    if_icmpge L26
    iload 3
    ldc 418566775 (java.lang.Integer)
    if_icmplt L27
    new java/lang/IllegalStateException
    dup
    invokespecial java/lang/IllegalStateException <init>:()V
    athrow
L27
    aload 0
    getfield at r:[S
    iload 5
    aload 1
    ldc -1725666664 (java.lang.Integer)
    invokevirtual dh q:(I)I
    i2s
    sastore
L28
    aload 0
    getfield at f:[S
    iload 5
    aload 1
    ldc -1709029606 (java.lang.Integer)
    invokevirtual dh q:(I)I
    i2s
    sastore
    goto L6
L29
    aload 0
    getfield at g:[S
    iload 5
    aload 1
    ldc 1508399653 (java.lang.Integer)
    invokevirtual dh q:(I)I
    i2s
    sastore
    goto L13
L26
    goto L8
L20
    bipush 41
    iload 2
    if_icmpne L8
L30
    aload 1
    ldc 1598004041 (java.lang.Integer)
    invokevirtual dh z:(I)I
    istore 4
    goto L31
L18
    aload 0
    aload 1
    ldc 262625199 (java.lang.Integer)
    invokevirtual dh q:(I)I
    ldc 647479905 (java.lang.Integer)
    imul
    putfield at j:I
    goto L8
L32
    aload 0
    iload 4
    newarray 9
    putfield at o:[S
L33
    iconst_0
    istore 5
L25
    iload 5
    iload 4
    if_icmpge L8
    iload 3
    ldc 418566775 (java.lang.Integer)
    if_icmplt L29
    new java/lang/IllegalStateException
    dup
    invokespecial java/lang/IllegalStateException <init>:()V
    athrow
L17
    iload 2
    bipush 7
    if_icmpne L9
    goto L19
L31
    aload 0
    iload 4
    newarray 9
    putfield at g:[S
    goto L32
L22
    aload 0
    iload 4
    newarray 9
    putfield at r:[S
    goto L24
L8
    return
L34
    new java/lang/StringBuilder
    dup
    invokespecial java/lang/StringBuilder <init>:()V
    ldc "at.c(" (java.lang.String)
    invokevirtual java/lang/StringBuilder append:(Ljava/lang/String;)Ljava/lang/StringBuilder;
    ldc 41 (java.lang.Integer)
    invokevirtual java/lang/StringBuilder append:(C)Ljava/lang/StringBuilder;
    invokevirtual java/lang/StringBuilder toString:()Ljava/lang/String;
    invokestatic k a:(Ljava/lang/Throwable;Ljava/lang/String;)Lee;
    athrow
