at c (Ljava/lang/String;I)Ljava/lang/Class;L1
    aload 0
    ldc "B" (java.lang.String)
    invokevirtual java/lang/String equals:(Ljava/lang/Object;)Z
    ifeq L2
    iload 1
    ldc 150073907 (java.lang.Integer)
    if_icmplt L3
    new java/lang/IllegalStateException
    dup
    invokespecial java/lang/IllegalStateException <init>:()V
    athrow
L4
    aload 0
    ldc "D" (java.lang.String)
    invokevirtual java/lang/String equals:(Ljava/lang/Object;)Z
    ifeq L5
    goto L6
L7
    getstatic java/lang/Character TYPE:Ljava/lang/Class;
    areturn
L8
    getstatic java/lang/Integer TYPE:Ljava/lang/Class;
    areturn
L9
    aload 0
    ldc "S" (java.lang.String)
    invokevirtual java/lang/String equals:(Ljava/lang/Object;)Z
    ifeq L10
    iload 1
    ldc 150073907 (java.lang.Integer)
    if_icmplt L11
    new java/lang/IllegalStateException
    dup
    invokespecial java/lang/IllegalStateException <init>:()V
    athrow
L11
    getstatic java/lang/Short TYPE:Ljava/lang/Class;
    areturn
L10
    aload 0
    ldc "J" (java.lang.String)
    invokevirtual java/lang/String equals:(Ljava/lang/Object;)Z
    ifeq L12
    iload 1
    ldc 150073907 (java.lang.Integer)
    if_icmplt L13
    new java/lang/IllegalStateException
    dup
    invokespecial java/lang/IllegalStateException <init>:()V
    athrow
L6
    getstatic java/lang/Double TYPE:Ljava/lang/Class;
    areturn
L14
    getstatic java/lang/Float TYPE:Ljava/lang/Class;
    areturn
L3
    getstatic java/lang/Byte TYPE:Ljava/lang/Class;
    areturn
L15
    aload 0
    ldc "F" (java.lang.String)
    invokevirtual java/lang/String equals:(Ljava/lang/Object;)Z
    ifeq L4
    iload 1
    ldc 150073907 (java.lang.Integer)
    if_icmplt L14
    new java/lang/IllegalStateException
    dup
    invokespecial java/lang/IllegalStateException <init>:()V
    athrow
L16
    aload 0
    invokestatic java/lang/Class forName:(Ljava/lang/String;)Ljava/lang/Class;
    areturn
L2
    aload 0
    ldc "I" (java.lang.String)
    invokevirtual java/lang/String equals:(Ljava/lang/Object;)Z
    ifeq L9
    iload 1
    ldc 150073907 (java.lang.Integer)
    if_icmplt L8
    new java/lang/IllegalStateException
    dup
    invokespecial java/lang/IllegalStateException <init>:()V
    athrow
L5
    aload 0
    ldc "C" (java.lang.String)
    invokevirtual java/lang/String equals:(Ljava/lang/Object;)Z
    ifeq L17
    goto L7
L13
    getstatic java/lang/Long TYPE:Ljava/lang/Class;
    areturn
L12
    aload 0
    ldc "Z" (java.lang.String)
    invokevirtual java/lang/String equals:(Ljava/lang/Object;)Z
    ifeq L15
    goto L18
L17
    aload 0
    ldc "void" (java.lang.String)
    invokevirtual java/lang/String equals:(Ljava/lang/Object;)Z
    ifeq L16
    iload 1
    ldc 150073907 (java.lang.Integer)
    if_icmplt L19
    new java/lang/IllegalStateException
    dup
    invokespecial java/lang/IllegalStateException <init>:()V
    athrow
L19
    getstatic java/lang/Void TYPE:Ljava/lang/Class;
    areturn
L18
    getstatic java/lang/Boolean TYPE:Ljava/lang/Class;
    areturn
L20
    new java/lang/StringBuilder
    dup
    invokespecial java/lang/StringBuilder <init>:()V
    ldc "at.c(" (java.lang.String)
    invokevirtual java/lang/StringBuilder append:(Ljava/lang/String;)Ljava/lang/StringBuilder;
    ldc 41 (java.lang.Integer)
    invokevirtual java/lang/StringBuilder append:(C)Ljava/lang/StringBuilder;
    invokevirtual java/lang/StringBuilder toString:()Ljava/lang/String;
    invokestatic k a:(Ljava/lang/Throwable;Ljava/lang/String;)Lee;
    athrow
