at e (Ljava/lang/String;Ljava/lang/String;II)Ljava/io/File;L1
    iconst_0
    iload 2
    if_icmpne L2
    iload 3
    ldc -1637107141 (java.lang.Integer)
    if_icmpne L3
    new java/lang/IllegalStateException
    dup
    invokespecial java/lang/IllegalStateException <init>:()V
    athrow
L3
    ldc "" (java.lang.String)
    goto L4
L2
    new java/lang/StringBuilder
    dup
    invokespecial java/lang/StringBuilder <init>:()V
    ldc "" (java.lang.String)
    invokevirtual java/lang/StringBuilder append:(Ljava/lang/String;)Ljava/lang/StringBuilder;
    iload 2
    invokevirtual java/lang/StringBuilder append:(I)Ljava/lang/StringBuilder;
    invokevirtual java/lang/StringBuilder toString:()Ljava/lang/String;
L4
    astore 4
L5
    new java/io/File
    dup
    getstatic bi x:Ljava/lang/String;
    new java/lang/StringBuilder
    dup
    invokespecial java/lang/StringBuilder <init>:()V
    ldc "jagex_cl_" (java.lang.String)
    invokevirtual java/lang/StringBuilder append:(Ljava/lang/String;)Ljava/lang/StringBuilder;
    aload 0
    invokevirtual java/lang/StringBuilder append:(Ljava/lang/String;)Ljava/lang/StringBuilder;
    ldc "_" (java.lang.String)
    invokevirtual java/lang/StringBuilder append:(Ljava/lang/String;)Ljava/lang/StringBuilder;
    aload 1
    invokevirtual java/lang/StringBuilder append:(Ljava/lang/String;)Ljava/lang/StringBuilder;
    aload 4
    invokevirtual java/lang/StringBuilder append:(Ljava/lang/String;)Ljava/lang/StringBuilder;
    ldc ".dat" (java.lang.String)
    invokevirtual java/lang/StringBuilder append:(Ljava/lang/String;)Ljava/lang/StringBuilder;
    invokevirtual java/lang/StringBuilder toString:()Ljava/lang/String;
    invokespecial java/io/File <init>:(Ljava/lang/String;Ljava/lang/String;)V
    putstatic ek c:Ljava/io/File;
L6
    aconst_null
    astore 5
L7
    aconst_null
    astore 6
L8
    iconst_0
    istore 7
L9
    getstatic ek c:Ljava/io/File;
    invokevirtual java/io/File exists:()Z
    ifeq L10
    iload 3
    ldc -1637107141 (java.lang.Integer)
    if_icmpne L11
    new java/lang/IllegalStateException
    dup
    invokespecial java/lang/IllegalStateException <init>:()V
    athrow
L11
    new hq
    dup
    getstatic ek c:Ljava/io/File;
    ldc "rw" (java.lang.String)
    ldc 10000 (java.lang.Long)
    invokespecial hq <init>:(Ljava/io/File;Ljava/lang/String;J)V
    astore 8
L12
    new dh
    dup
    aload 8
    bipush 25
    invokevirtual hq c:(B)J
    l2i
    invokespecial dh <init>:(I)V
    astore 9
L13
    aload 9
    getfield dh a:I
    ldc 910905453 (java.lang.Integer)
    imul
    aload 9
    getfield dh e:[B
    arraylength
    if_icmpge L14
    iload 3
    ldc -1637107141 (java.lang.Integer)
    if_icmpne L15
    new java/lang/IllegalStateException
    dup
    invokespecial java/lang/IllegalStateException <init>:()V
    athrow
L15
    aload 8
    aload 9
    getfield dh e:[B
    ldc 910905453 (java.lang.Integer)
    aload 9
    getfield dh a:I
    imul
    aload 9
    getfield dh e:[B
    arraylength
    ldc 910905453 (java.lang.Integer)
    aload 9
    getfield dh a:I
    imul
    isub
    ldc -1002919729 (java.lang.Integer)
    invokevirtual hq u:([BIII)I
    istore 10
L16
    iload 10
    iconst_m1
    if_icmpne L17
    iload 3
    ldc -1637107141 (java.lang.Integer)
    if_icmpne L18
    new java/lang/IllegalStateException
    dup
    invokespecial java/lang/IllegalStateException <init>:()V
    athrow
L18
    new java/io/IOException
    dup
    invokespecial java/io/IOException <init>:()V
    athrow
L17
    aload 9
    dup
    getfield dh a:I
    ldc 1782921573 (java.lang.Integer)
    iload 10
    imul
    iadd
    putfield dh a:I
L19
    goto L13
L14
    aload 9
    iconst_0
    putfield dh a:I
L20
    aload 9
    ldc 1081669042 (java.lang.Integer)
    invokevirtual dh z:(I)I
    istore 10
L21
    iload 10
    iconst_1
    if_icmplt L22
    iload 3
    ldc -1637107141 (java.lang.Integer)
    if_icmpne L23
    new java/lang/IllegalStateException
    dup
    invokespecial java/lang/IllegalStateException <init>:()V
    athrow
L23
    iload 10
    iconst_3
    if_icmple L24
    iload 3
    ldc -1637107141 (java.lang.Integer)
    if_icmpne L22
    new java/lang/IllegalStateException
    dup
    invokespecial java/lang/IllegalStateException <init>:()V
    athrow
L22
    new java/io/IOException
    dup
    new java/lang/StringBuilder
    dup
    invokespecial java/lang/StringBuilder <init>:()V
    ldc "" (java.lang.String)
    invokevirtual java/lang/StringBuilder append:(Ljava/lang/String;)Ljava/lang/StringBuilder;
    iload 10
    invokevirtual java/lang/StringBuilder append:(I)Ljava/lang/StringBuilder;
    invokevirtual java/lang/StringBuilder toString:()Ljava/lang/String;
    invokespecial java/io/IOException <init>:(Ljava/lang/String;)V
    athrow
L24
    iconst_0
    istore 11
L25
    iload 10
    iconst_1
    if_icmple L26
    iload 3
    ldc -1637107141 (java.lang.Integer)
    if_icmpne L27
    new java/lang/IllegalStateException
    dup
    invokespecial java/lang/IllegalStateException <init>:()V
    athrow
L27
    aload 9
    ldc 1582984615 (java.lang.Integer)
    invokevirtual dh z:(I)I
    istore 11
L26
    iload 10
    iconst_2
    if_icmpgt L28
    iload 3
    ldc -1637107141 (java.lang.Integer)
    if_icmpne L29
    new java/lang/IllegalStateException
    dup
    invokespecial java/lang/IllegalStateException <init>:()V
    athrow
L29
    aload 9
    ldc -1782064896 (java.lang.Integer)
    invokevirtual dh k:(I)Ljava/lang/String;
    astore 5
L30
    iconst_1
    iload 11
    if_icmpne L31
    iload 3
    ldc -1637107141 (java.lang.Integer)
    if_icmpne L32
    new java/lang/IllegalStateException
    dup
    invokespecial java/lang/IllegalStateException <init>:()V
    athrow
L32
    aload 9
    ldc 42323185 (java.lang.Integer)
    invokevirtual dh k:(I)Ljava/lang/String;
    astore 6
    goto L31
L28
    aload 9
    ldc 474346313 (java.lang.Integer)
    invokevirtual dh ax:(I)Ljava/lang/String;
    astore 5
L33
    iconst_1
    iload 11
    if_icmpne L31
    aload 9
    ldc 159574471 (java.lang.Integer)
    invokevirtual dh ax:(I)Ljava/lang/String;
    astore 6
L31
    aload 8
    ldc 1792136399 (java.lang.Integer)
    invokevirtual hq l:(I)V
L34
    goto L35
L36
    astore 9
L37
    aload 9
    invokevirtual java/io/IOException printStackTrace:()V
L35
    aconst_null
    aload 5
    if_acmpeq L38
L39
    new java/io/File
    dup
    aload 5
    invokespecial java/io/File <init>:(Ljava/lang/String;)V
    astore 9
L40
    aload 9
    invokevirtual java/io/File exists:()Z
    ifne L38
    iload 3
    ldc -1637107141 (java.lang.Integer)
    if_icmpne L41
    new java/lang/IllegalStateException
    dup
    invokespecial java/lang/IllegalStateException <init>:()V
    athrow
L41
    aconst_null
    astore 5
L38
    aload 5
    ifnull L10
L42
    new java/io/File
    dup
    aload 5
    ldc "test.dat" (java.lang.String)
    invokespecial java/io/File <init>:(Ljava/lang/String;Ljava/lang/String;)V
    astore 9
L43
    aload 9
    iconst_1
    ldc -948810413 (java.lang.Integer)
    invokestatic ax a:(Ljava/io/File;ZI)Z
    ifne L10
    iload 3
    ldc -1637107141 (java.lang.Integer)
    if_icmpne L44
    new java/lang/IllegalStateException
    dup
    invokespecial java/lang/IllegalStateException <init>:()V
    athrow
L44
    aconst_null
    astore 5
L10
    aload 5
    ifnonnull L45
    iload 3
    ldc -1637107141 (java.lang.Integer)
    if_icmpne L46
    new java/lang/IllegalStateException
    dup
    invokespecial java/lang/IllegalStateException <init>:()V
    athrow
L46
    iload 2
    ifne L45
    iload 3
    ldc -1637107141 (java.lang.Integer)
    if_icmpne L47
    new java/lang/IllegalStateException
    dup
    invokespecial java/lang/IllegalStateException <init>:()V
    athrow
L47
    iconst_0
    istore 8
L48
    iload 8
    getstatic ee z:[Ljava/lang/String;
    arraylength
    if_icmpge L45
L49
    iconst_0
    istore 9
L50
    iload 9
    getstatic u t:[Ljava/lang/String;
    arraylength
    if_icmpge L51
    iload 3
    ldc -1637107141 (java.lang.Integer)
    if_icmpne L52
    new java/lang/IllegalStateException
    dup
    invokespecial java/lang/IllegalStateException <init>:()V
    athrow
L52
    new java/io/File
    dup
    new java/lang/StringBuilder
    dup
    invokespecial java/lang/StringBuilder <init>:()V
    getstatic u t:[Ljava/lang/String;
    iload 9
    aaload
    invokevirtual java/lang/StringBuilder append:(Ljava/lang/String;)Ljava/lang/StringBuilder;
    getstatic ee z:[Ljava/lang/String;
    iload 8
    aaload
    invokevirtual java/lang/StringBuilder append:(Ljava/lang/String;)Ljava/lang/StringBuilder;
    getstatic java/io/File separatorChar:C
    invokevirtual java/lang/StringBuilder append:(C)Ljava/lang/StringBuilder;
    aload 0
    invokevirtual java/lang/StringBuilder append:(Ljava/lang/String;)Ljava/lang/StringBuilder;
    getstatic java/io/File separatorChar:C
    invokevirtual java/lang/StringBuilder append:(C)Ljava/lang/StringBuilder;
    invokevirtual java/lang/StringBuilder toString:()Ljava/lang/String;
    invokespecial java/io/File <init>:(Ljava/lang/String;)V
    astore 10
L53
    aload 10
    invokevirtual java/io/File exists:()Z
    ifeq L54
    iload 3
    ldc -1637107141 (java.lang.Integer)
    if_icmpne L55
    new java/lang/IllegalStateException
    dup
    invokespecial java/lang/IllegalStateException <init>:()V
    athrow
L55
    new java/io/File
    dup
    aload 10
    ldc "test.dat" (java.lang.String)
    invokespecial java/io/File <init>:(Ljava/io/File;Ljava/lang/String;)V
    iconst_1
    ldc -948810413 (java.lang.Integer)
    invokestatic ax a:(Ljava/io/File;ZI)Z
    ifeq L54
    iload 3
    ldc -1637107141 (java.lang.Integer)
    if_icmpne L56
    new java/lang/IllegalStateException
    dup
    invokespecial java/lang/IllegalStateException <init>:()V
    athrow
L56
    aload 10
    invokevirtual java/io/File toString:()Ljava/lang/String;
    astore 5
L57
    iconst_1
    istore 7
L58
    goto L45
L54
    iinc 9 1
    goto L50
L51
    iinc 8 1
    goto L48
L45
    aconst_null
    aload 5
    if_acmpne L59
    iload 3
    ldc -1637107141 (java.lang.Integer)
    if_icmpne L60
    new java/lang/IllegalStateException
    dup
    invokespecial java/lang/IllegalStateException <init>:()V
    athrow
L60
    new java/lang/StringBuilder
    dup
    invokespecial java/lang/StringBuilder <init>:()V
    getstatic bi x:Ljava/lang/String;
    invokevirtual java/lang/StringBuilder append:(Ljava/lang/String;)Ljava/lang/StringBuilder;
    getstatic java/io/File separatorChar:C
    invokevirtual java/lang/StringBuilder append:(C)Ljava/lang/StringBuilder;
    ldc "jagexcache" (java.lang.String)
    invokevirtual java/lang/StringBuilder append:(Ljava/lang/String;)Ljava/lang/StringBuilder;
    aload 4
    invokevirtual java/lang/StringBuilder append:(Ljava/lang/String;)Ljava/lang/StringBuilder;
    getstatic java/io/File separatorChar:C
    invokevirtual java/lang/StringBuilder append:(C)Ljava/lang/StringBuilder;
    aload 0
    invokevirtual java/lang/StringBuilder append:(Ljava/lang/String;)Ljava/lang/StringBuilder;
    getstatic java/io/File separatorChar:C
    invokevirtual java/lang/StringBuilder append:(C)Ljava/lang/StringBuilder;
    aload 1
    invokevirtual java/lang/StringBuilder append:(Ljava/lang/String;)Ljava/lang/StringBuilder;
    getstatic java/io/File separatorChar:C
    invokevirtual java/lang/StringBuilder append:(C)Ljava/lang/StringBuilder;
    invokevirtual java/lang/StringBuilder toString:()Ljava/lang/String;
    astore 5
L61
    iconst_1
    istore 7
L59
    aconst_null
    aload 6
    if_acmpeq L62
L63
    new java/io/File
    dup
    aload 6
    invokespecial java/io/File <init>:(Ljava/lang/String;)V
    astore 8
L64
    new java/io/File
    dup
    aload 5
    invokespecial java/io/File <init>:(Ljava/lang/String;)V
    astore 9
L65
    aload 8
    invokevirtual java/io/File listFiles:()[Ljava/io/File;
    astore 10
L66
    aload 10
    astore 11
L67
    iconst_0
    istore 12
L68
    iload 12
    aload 11
    arraylength
    if_icmpge L69
L70
    aload 11
    iload 12
    aaload
    astore 13
L71
    new java/io/File
    dup
    aload 9
    aload 13
    invokevirtual java/io/File getName:()Ljava/lang/String;
    invokespecial java/io/File <init>:(Ljava/io/File;Ljava/lang/String;)V
    astore 14
L72
    aload 13
    aload 14
    invokevirtual java/io/File renameTo:(Ljava/io/File;)Z
    istore 15
L73
    iload 15
    ifne L74
    iload 3
    ldc -1637107141 (java.lang.Integer)
    if_icmpne L75
    new java/lang/IllegalStateException
    dup
    invokespecial java/lang/IllegalStateException <init>:()V
    athrow
L75
    new java/io/IOException
    dup
    invokespecial java/io/IOException <init>:()V
    athrow
L74
    iinc 12 1
    goto L68
L69
    goto L76
L77
    astore 10
L78
    aload 10
    invokevirtual java/lang/Exception printStackTrace:()V
L76
    iconst_1
    istore 7
L62
    iload 7
    ifeq L79
    iload 3
    ldc -1637107141 (java.lang.Integer)
    if_icmpne L80
    new java/lang/IllegalStateException
    dup
    invokespecial java/lang/IllegalStateException <init>:()V
    athrow
L80
    new java/io/File
    dup
    aload 5
    invokespecial java/io/File <init>:(Ljava/lang/String;)V
    astore 8
L81
    aconst_null
    astore 9
L82
    new hq
    dup
    getstatic ek c:Ljava/io/File;
    ldc "rw" (java.lang.String)
    ldc 10000 (java.lang.Long)
    invokespecial hq <init>:(Ljava/io/File;Ljava/lang/String;J)V
    astore 10
L83
    new dh
    dup
    sipush 500
    invokespecial dh <init>:(I)V
    astore 11
L84
    aload 11
    iconst_3
    bipush -30
    invokevirtual dh e:(IB)V
L85
    aload 11
    aconst_null
    aload 9
    if_acmpeq L86
    iload 3
    ldc -1637107141 (java.lang.Integer)
    if_icmpne L87
    new java/lang/IllegalStateException
    dup
    invokespecial java/lang/IllegalStateException <init>:()V
    athrow
L87
    iconst_1
    goto L88
L86
    iconst_0
L88
    bipush 71
    invokevirtual dh e:(IB)V
L89
    aload 11
    aload 8
    invokevirtual java/io/File getPath:()Ljava/lang/String;
    iconst_m1
    invokevirtual dh g:(Ljava/lang/CharSequence;B)V
L90
    aload 9
    ifnull L91
    iload 3
    ldc -1637107141 (java.lang.Integer)
    if_icmpne L92
    new java/lang/IllegalStateException
    dup
    invokespecial java/lang/IllegalStateException <init>:()V
    athrow
L92
    aload 11
    aload 9
    invokevirtual java/io/File getPath:()Ljava/lang/String;
    bipush -99
    invokevirtual dh g:(Ljava/lang/CharSequence;B)V
L91
    aload 10
    aload 11
    getfield dh e:[B
    iconst_0
    ldc 910905453 (java.lang.Integer)
    aload 11
    getfield dh a:I
    imul
    iconst_1
    invokevirtual hq a:([BIIB)V
L93
    aload 10
    ldc 2076501490 (java.lang.Integer)
    invokevirtual hq l:(I)V
L94
    goto L79
L95
    astore 11
L96
    aload 11
    invokevirtual java/io/IOException printStackTrace:()V
L79
    new java/io/File
    dup
    aload 5
    invokespecial java/io/File <init>:(Ljava/lang/String;)V
    areturn
L97
    new java/lang/StringBuilder
    dup
    invokespecial java/lang/StringBuilder <init>:()V
    ldc "at.e(" (java.lang.String)
    invokevirtual java/lang/StringBuilder append:(Ljava/lang/String;)Ljava/lang/StringBuilder;
    ldc 41 (java.lang.Integer)
    invokevirtual java/lang/StringBuilder append:(C)Ljava/lang/StringBuilder;
    invokevirtual java/lang/StringBuilder toString:()Ljava/lang/String;
    invokestatic k a:(Ljava/lang/Throwable;Ljava/lang/String;)Lee;
    athrow
