at u (II)Lcy;L1
    getstatic at c:Lgr;
    aload 0
    getfield at u:I
    ldc -473058987 (java.lang.Integer)
    imul
    i2l
    invokevirtual gr e:(J)Lgd;
    checkcast cy
    astore 3
L2
    aload 3
    ifnonnull L3
    goto L4
L5
    aload 4
    ldc 1830337029 (java.lang.Integer)
    aload 0
    getfield at h:I
    imul
    aload 0
    getfield at s:I
    ldc -763226505 (java.lang.Integer)
    imul
    aload 0
    getfield at h:I
    ldc 1830337029 (java.lang.Integer)
    imul
    invokevirtual cy d:(III)V
    goto L6
L7
    aconst_null
    aload 4
    if_acmpne L8
    goto L9
L10
    ldc -332207823 (java.lang.Integer)
    aload 0
    getfield at i:I
    imul
    ldc 152969838 (java.lang.Integer)
    invokestatic cd e:(II)Lah;
    aload 3
    iload 1
    ldc -1929858268 (java.lang.Integer)
    invokevirtual ah i:(Lcy;II)Lcy;
    astore 4
    goto L11
L8
    aload 0
    getfield at r:[S
    ifnull L12
    goto L13
L14
    iinc 5 1
    goto L15
L16
    iload 5
    aload 0
    getfield at r:[S
    arraylength
    if_icmpge L12
    iload 2
    ldc 35025418 (java.lang.Integer)
    if_icmpne L17
    new java/lang/IllegalStateException
    dup
    invokespecial java/lang/IllegalStateException <init>:()V
    athrow
L4
    getstatic at a:Lfv;
    ldc -1687885153 (java.lang.Integer)
    aload 0
    getfield at w:I
    imul
    iconst_0
    invokestatic cr e:(Lfv;II)Lcr;
    astore 4
    goto L7
L18
    iinc 5 1
    goto L16
L12
    aconst_null
    aload 0
    getfield at g:[S
    if_acmpeq L19
    iload 2
    ldc 35025418 (java.lang.Integer)
    if_icmpne L20
    new java/lang/IllegalStateException
    dup
    invokespecial java/lang/IllegalStateException <init>:()V
    athrow
L20
    iconst_0
    istore 5
    goto L15
L21
    sipush 128
    aload 0
    getfield at s:I
    ldc -763226505 (java.lang.Integer)
    imul
    if_icmpeq L6
    iload 2
    ldc 35025418 (java.lang.Integer)
    if_icmpne L5
    new java/lang/IllegalStateException
    dup
    invokespecial java/lang/IllegalStateException <init>:()V
    athrow
L9
    aconst_null
    areturn
L17
    aload 4
    aload 0
    getfield at r:[S
    iload 5
    saload
    aload 0
    getfield at f:[S
    iload 5
    saload
    invokevirtual cr z:(SS)V
    goto L18
L19
    aload 4
    ldc -55025653 (java.lang.Integer)
    aload 0
    getfield at m:I
    imul
    bipush 64
    iadd
    ldc 518615709 (java.lang.Integer)
    aload 0
    getfield at t:I
    imul
    sipush 850
    iadd
    bipush -30
    bipush -50
    bipush -30
    invokevirtual cr p:(IIIII)Lcy;
    astore 3
L22
    getstatic at c:Lgr;
    aload 3
    ldc -473058987 (java.lang.Integer)
    aload 0
    getfield at u:I
    imul
    i2l
    invokevirtual gr l:(Lgd;J)V
L3
    iconst_m1
    aload 0
    getfield at i:I
    ldc -332207823 (java.lang.Integer)
    imul
    if_icmpeq L23
    iload 2
    ldc 35025418 (java.lang.Integer)
    if_icmpne L24
    new java/lang/IllegalStateException
    dup
    invokespecial java/lang/IllegalStateException <init>:()V
    athrow
L25
    aload 4
    aload 0
    getfield at g:[S
    iload 5
    saload
    aload 0
    getfield at o:[S
    iload 5
    saload
    invokevirtual cr y:(SS)V
    goto L14
L24
    iconst_m1
    iload 1
    if_icmpeq L23
    iload 2
    ldc 35025418 (java.lang.Integer)
    if_icmpne L10
    new java/lang/IllegalStateException
    dup
    invokespecial java/lang/IllegalStateException <init>:()V
    athrow
L23
    aload 3
    iconst_1
    invokevirtual cy c:(Z)Lcy;
    astore 4
L11
    ldc 1830337029 (java.lang.Integer)
    aload 0
    getfield at h:I
    imul
    sipush 128
    if_icmpne L5
    iload 2
    ldc 35025418 (java.lang.Integer)
    if_icmpne L21
    new java/lang/IllegalStateException
    dup
    invokespecial java/lang/IllegalStateException <init>:()V
    athrow
L13
    iconst_0
    istore 5
    goto L16
L15
    iload 5
    aload 0
    getfield at g:[S
    arraylength
    if_icmpge L19
    iload 2
    ldc 35025418 (java.lang.Integer)
    if_icmpne L25
    new java/lang/IllegalStateException
    dup
    invokespecial java/lang/IllegalStateException <init>:()V
    athrow
L6
    aload 0
    getfield at j:I
    ldc 1390961057 (java.lang.Integer)
    imul
    ifeq L26
L27
    aload 0
    getfield at j:I
    ldc 1390961057 (java.lang.Integer)
    imul
    bipush 90
    if_icmpne L28
    iload 2
    ldc 35025418 (java.lang.Integer)
    if_icmpne L29
    new java/lang/IllegalStateException
    dup
    invokespecial java/lang/IllegalStateException <init>:()V
    athrow
L29
    aload 4
    invokevirtual cy m:()V
L28
    aload 0
    getfield at j:I
    ldc 1390961057 (java.lang.Integer)
    imul
    sipush 180
    if_icmpne L30
    iload 2
    ldc 35025418 (java.lang.Integer)
    if_icmpne L31
    new java/lang/IllegalStateException
    dup
    invokespecial java/lang/IllegalStateException <init>:()V
    athrow
L31
    aload 4
    invokevirtual cy m:()V
L32
    aload 4
    invokevirtual cy m:()V
L30
    ldc 1390961057 (java.lang.Integer)
    aload 0
    getfield at j:I
    imul
    sipush 270
    if_icmpne L26
    iload 2
    ldc 35025418 (java.lang.Integer)
    if_icmpne L33
    new java/lang/IllegalStateException
    dup
    invokespecial java/lang/IllegalStateException <init>:()V
    athrow
L33
    aload 4
    invokevirtual cy m:()V
L34
    aload 4
    invokevirtual cy m:()V
L35
    aload 4
    invokevirtual cy m:()V
L26
    aload 4
    areturn
L36
    new java/lang/StringBuilder
    dup
    invokespecial java/lang/StringBuilder <init>:()V
    ldc "at.u(" (java.lang.String)
    invokevirtual java/lang/StringBuilder append:(Ljava/lang/String;)Ljava/lang/StringBuilder;
    ldc 41 (java.lang.Integer)
    invokevirtual java/lang/StringBuilder append:(C)Ljava/lang/StringBuilder;
    invokevirtual java/lang/StringBuilder toString:()Ljava/lang/String;
    invokestatic k a:(Ljava/lang/Throwable;Ljava/lang/String;)Lee;
    athrow
