au as (IIIIII)VL1
    getstatic n ds:Lcb;
    iload 0
    iload 1
    iload 2
    invokevirtual cb ax:(III)I
    istore 6
    goto L2
L3
    aconst_null
    aload 12
    if_acmpeq L4
    iload 5
    ldc 1389541124 (java.lang.Integer)
    if_icmplt L5
    return
L5
    aload 11
    getfield ag z:I
    ldc 1816092068 (java.lang.Integer)
    imul
    aload 12
    getfield bs l:I
    isub
    iconst_2
    idiv
    istore 13
    goto L6
L7
    iload 7
    bipush 6
    ishr
    iconst_3
    iand
    istore 8
L8
    iload 7
    bipush 31
    iand
    istore 9
    goto L9
L10
    aload 11
    iload 12
    iload 10
    iastore
    goto L11
L12
    bipush 103
    iload 2
    isub
    sipush 2048
    imul
    sipush 24624
    iload 1
    iconst_4
    imul
    iadd
    iadd
    istore 14
    goto L13
L14
    iload 6
    bipush 14
    ishr
    sipush 32767
    iand
    istore 7
    goto L15
L16
    getstatic al my:Lbh;
    getfield bh e:[I
    astore 11
    goto L17
L18
    iconst_0
    iload 8
    if_icmpne L19
    goto L20
L21
    iload 6
    bipush 14
    ishr
    sipush 32767
    iand
    istore 13
    goto L22
L23
    iconst_0
    iload 9
    if_icmpeq L24
    iload 5
    ldc 1389541124 (java.lang.Integer)
    if_icmplt L25
    new java/lang/IllegalStateException
    dup
    invokespecial java/lang/IllegalStateException <init>:()V
    athrow
L26
    aload 13
    iload 14
    iload 12
    iastore
    goto L27
L28
    getstatic fr ey:[Lbs;
    aload 14
    getfield ag aw:I
    ldc -2004655305 (java.lang.Integer)
    imul
    aaload
    astore 15
L29
    aconst_null
    aload 15
    if_acmpeq L30
    iload 5
    ldc 1389541124 (java.lang.Integer)
    if_icmplt L31
    new java/lang/IllegalStateException
    dup
    invokespecial java/lang/IllegalStateException <init>:()V
    athrow
L32
    aconst_null
    aload 9
    if_acmpeq L33
    iload 5
    ldc 1389541124 (java.lang.Integer)
    if_icmplt L34
    new java/lang/IllegalStateException
    dup
    invokespecial java/lang/IllegalStateException <init>:()V
    athrow
L6
    ldc 92157260 (java.lang.Integer)
    aload 11
    getfield ag y:I
    imul
    aload 12
    getfield bs c:I
    isub
    iconst_2
    idiv
    istore 14
    goto L35
L36
    aload 15
    iload 16
    bipush 48
    iconst_4
    iload 1
    imul
    iadd
    iadd
    bipush 48
    iconst_4
    bipush 104
    iload 2
    isub
    aload 14
    getfield ag y:I
    ldc -1050702509 (java.lang.Integer)
    imul
    isub
    imul
    iadd
    iload 17
    iadd
    invokevirtual bs l:(II)V
    goto L30
L37
    aload 13
    sipush 1536
    iload 14
    iadd
    iload 12
    iastore
    goto L38
L30
    goto L39
L25
    iconst_2
    iload 9
    if_icmpne L40
    iload 5
    ldc 1389541124 (java.lang.Integer)
    if_icmplt L24
    return
L24
    iload 8
    ifne L41
    iload 5
    ldc 1389541124 (java.lang.Integer)
    if_icmplt L42
    new java/lang/IllegalStateException
    dup
    invokespecial java/lang/IllegalStateException <init>:()V
    athrow
L43
    iconst_m1
    ldc -2004655305 (java.lang.Integer)
    aload 14
    getfield ag aw:I
    imul
    if_icmpeq L23
    iload 5
    ldc 1389541124 (java.lang.Integer)
    if_icmplt L28
    new java/lang/IllegalStateException
    dup
    invokespecial java/lang/IllegalStateException <init>:()V
    athrow
L44
    aload 11
    iload 12
    sipush 512
    iadd
    iload 10
    iastore
    goto L45
L46
    ldc -2004655305 (java.lang.Integer)
    aload 11
    getfield ag aw:I
    imul
    iconst_m1
    if_icmpeq L47
    iload 5
    ldc 1389541124 (java.lang.Integer)
    if_icmplt L48
    return
L49
    aload 11
    sipush 1536
    iload 12
    iadd
    iload 10
    iastore
    goto L40
L41
    iconst_1
    iload 8
    if_icmpne L50
    iload 5
    ldc 1389541124 (java.lang.Integer)
    if_icmplt L51
    new java/lang/IllegalStateException
    dup
    invokespecial java/lang/IllegalStateException <init>:()V
    athrow
L51
    aload 11
    iload 12
    iload 10
    iastore
L52
    aload 11
    iload 12
    iconst_1
    iadd
    iload 10
    iastore
L53
    aload 11
    iconst_2
    iload 12
    iadd
    iload 10
    iastore
L54
    aload 11
    iload 12
    iconst_3
    iadd
    iload 10
    iastore
    goto L40
L50
    iconst_2
    iload 8
    if_icmpne L55
    iload 5
    ldc 1389541124 (java.lang.Integer)
    if_icmplt L56
    return
L57
    aload 11
    iconst_3
    sipush 1536
    iload 12
    iadd
    iadd
    iload 10
    iastore
    goto L40
L58
    aload 11
    iconst_3
    iload 12
    iadd
    sipush 1536
    iadd
    iload 10
    iastore
    goto L39
L59
    iload 6
    ifeq L60
    iload 5
    ldc 1389541124 (java.lang.Integer)
    if_icmplt L61
    new java/lang/IllegalStateException
    dup
    invokespecial java/lang/IllegalStateException <init>:()V
    athrow
L62
    aload 11
    sipush 1536
    iconst_3
    iload 12
    iadd
    iadd
    iload 10
    iastore
    goto L40
L55
    iload 8
    iconst_3
    if_icmpne L40
    iload 5
    ldc 1389541124 (java.lang.Integer)
    if_icmplt L63
    return
L63
    aload 11
    iload 12
    sipush 1536
    iadd
    iload 10
    iastore
L64
    aload 11
    iconst_1
    sipush 1536
    iload 12
    iadd
    iadd
    iload 10
    iastore
L65
    aload 11
    iload 12
    sipush 1536
    iadd
    iconst_2
    iadd
    iload 10
    iastore
    goto L57
L31
    ldc 1816092068 (java.lang.Integer)
    aload 14
    getfield ag z:I
    imul
    aload 15
    getfield bs l:I
    isub
    iconst_2
    idiv
    istore 16
    goto L66
L40
    iload 9
    iconst_3
    if_icmpne L67
    iload 5
    ldc 1389541124 (java.lang.Integer)
    if_icmplt L18
    new java/lang/IllegalStateException
    dup
    invokespecial java/lang/IllegalStateException <init>:()V
    athrow
L2
    iconst_0
    iload 6
    if_icmpeq L39
    iload 5
    ldc 1389541124 (java.lang.Integer)
    if_icmplt L68
    new java/lang/IllegalStateException
    dup
    invokespecial java/lang/IllegalStateException <init>:()V
    athrow
L69
    aload 11
    iconst_1
    sipush 1536
    iload 12
    iadd
    iadd
    iload 10
    iastore
    goto L70
L19
    iconst_1
    iload 8
    if_icmpne L71
    iload 5
    ldc 1389541124 (java.lang.Integer)
    if_icmplt L72
    new java/lang/IllegalStateException
    dup
    invokespecial java/lang/IllegalStateException <init>:()V
    athrow
L72
    aload 11
    iconst_3
    iload 12
    iadd
    iload 10
    iastore
    goto L67
L71
    iload 8
    iconst_2
    if_icmpne L73
    iload 5
    ldc 1389541124 (java.lang.Integer)
    if_icmplt L74
    new java/lang/IllegalStateException
    dup
    invokespecial java/lang/IllegalStateException <init>:()V
    athrow
L74
    aload 11
    sipush 1536
    iconst_3
    iload 12
    iadd
    iadd
    iload 10
    iastore
    goto L67
L73
    iconst_3
    iload 8
    if_icmpne L67
    iload 5
    ldc 1389541124 (java.lang.Integer)
    if_icmplt L75
    new java/lang/IllegalStateException
    dup
    invokespecial java/lang/IllegalStateException <init>:()V
    athrow
L75
    aload 11
    iload 12
    sipush 1536
    iadd
    iload 10
    iastore
L67
    iload 9
    iconst_2
    if_icmpne L39
    goto L76
L77
    aload 11
    iload 12
    iconst_2
    iadd
    iload 10
    iastore
    goto L78
L38
    aload 13
    iconst_1
    iload 14
    sipush 1024
    iadd
    iadd
    iload 12
    iastore
    goto L79
L11
    aload 11
    sipush 512
    iload 12
    iadd
    iload 10
    iastore
L80
    aload 11
    sipush 1024
    iload 12
    iadd
    iload 10
    iastore
    goto L81
L76
    iload 8
    iconst_3
    if_icmpne L82
    iload 5
    ldc 1389541124 (java.lang.Integer)
    if_icmplt L10
    new java/lang/IllegalStateException
    dup
    invokespecial java/lang/IllegalStateException <init>:()V
    athrow
L82
    iload 8
    ifne L83
L84
    aload 11
    iload 12
    iload 10
    iastore
L85
    aload 11
    iload 12
    iconst_1
    iadd
    iload 10
    iastore
    goto L77
L86
    aload 11
    iload 12
    iconst_3
    iadd
    sipush 512
    iadd
    iload 10
    iastore
    goto L87
L78
    aload 11
    iload 12
    iconst_3
    iadd
    iload 10
    iastore
    goto L39
L88
    ldc 92157260 (java.lang.Integer)
    aload 8
    getfield ag y:I
    imul
    aload 9
    getfield bs c:I
    isub
    iconst_2
    idiv
    istore 11
    goto L89
L90
    aload 11
    iconst_3
    iload 12
    iadd
    iload 10
    iastore
L91
    aload 11
    iconst_3
    iload 12
    iadd
    sipush 512
    iadd
    iload 10
    iastore
L92
    aload 11
    sipush 1024
    iload 12
    iconst_3
    iadd
    iadd
    iload 10
    iastore
    goto L58
L56
    aload 11
    iconst_3
    iload 12
    iadd
    iload 10
    iastore
    goto L86
L93
    iload 8
    iconst_2
    if_icmpne L39
    iload 5
    ldc 1389541124 (java.lang.Integer)
    if_icmplt L94
    new java/lang/IllegalStateException
    dup
    invokespecial java/lang/IllegalStateException <init>:()V
    athrow
L94
    aload 11
    sipush 1536
    iload 12
    iadd
    iload 10
    iastore
    goto L69
L95
    iload 10
    bipush -98
    invokestatic m e:(IB)Lag;
    astore 11
    goto L46
L70
    aload 11
    sipush 1536
    iload 12
    iadd
    iconst_2
    iadd
    iload 10
    iastore
L96
    aload 11
    sipush 1536
    iload 12
    iadd
    iconst_3
    iadd
    iload 10
    iastore
L39
    getstatic n ds:Lcb;
    iload 0
    iload 1
    iload 2
    invokevirtual cb ao:(III)I
    istore 6
    goto L59
L97
    aload 13
    iconst_3
    sipush 1536
    iload 14
    iadd
    iadd
    iload 12
    iastore
    goto L60
L81
    aload 11
    iload 12
    sipush 1536
    iadd
    iload 10
    iastore
    goto L39
L98
    iload 7
    bipush 6
    ishr
    iconst_3
    iand
    istore 8
L99
    iload 7
    bipush 31
    iand
    istore 9
L100
    iload 6
    bipush 14
    ishr
    sipush 32767
    iand
    istore 10
    goto L95
L20
    aload 11
    iload 12
    iload 10
    iastore
    goto L67
L17
    sipush 24624
    iload 1
    iconst_4
    imul
    iadd
    sipush 2048
    bipush 103
    iload 2
    isub
    imul
    iadd
    istore 12
    goto L21
L48
    getstatic fr ey:[Lbs;
    aload 11
    getfield ag aw:I
    ldc -2004655305 (java.lang.Integer)
    imul
    aaload
    astore 12
    goto L3
L33
    return
L101
    aload 13
    iconst_2
    iload 14
    sipush 1024
    iadd
    iadd
    iload 12
    iastore
    goto L97
L61
    getstatic n ds:Lcb;
    iload 0
    iload 1
    iload 2
    iload 6
    invokevirtual cb aw:(IIII)I
    istore 7
    goto L98
L35
    aload 12
    iload 13
    bipush 48
    iload 1
    iconst_4
    imul
    iadd
    iadd
    bipush 104
    iload 2
    isub
    aload 11
    getfield ag y:I
    ldc -1050702509 (java.lang.Integer)
    imul
    isub
    iconst_4
    imul
    bipush 48
    iadd
    iload 14
    iadd
    invokevirtual bs l:(II)V
L4
    goto L60
L47
    bipush 9
    iload 9
    if_icmpne L60
    iload 5
    ldc 1389541124 (java.lang.Integer)
    if_icmplt L102
    new java/lang/IllegalStateException
    dup
    invokespecial java/lang/IllegalStateException <init>:()V
    athrow
L102
    ldc 15658734 (java.lang.Integer)
    istore 12
L103
    iload 6
    ifle L104
    iload 5
    ldc 1389541124 (java.lang.Integer)
    if_icmplt L105
    return
L105
    ldc 15597568 (java.lang.Integer)
    istore 12
L104
    getstatic al my:Lbh;
    getfield bh e:[I
    astore 13
    goto L12
L87
    aload 11
    iload 12
    iconst_3
    iadd
    sipush 1024
    iadd
    iload 10
    iastore
    goto L62
L13
    iconst_0
    iload 8
    if_icmpeq L37
    iload 5
    ldc 1389541124 (java.lang.Integer)
    if_icmplt L106
    new java/lang/IllegalStateException
    dup
    invokespecial java/lang/IllegalStateException <init>:()V
    athrow
L83
    iload 8
    iconst_1
    if_icmpne L93
    iload 5
    ldc 1389541124 (java.lang.Integer)
    if_icmplt L90
    new java/lang/IllegalStateException
    dup
    invokespecial java/lang/IllegalStateException <init>:()V
    athrow
L106
    iconst_2
    iload 8
    if_icmpne L26
    iload 5
    ldc 1389541124 (java.lang.Integer)
    if_icmplt L37
    new java/lang/IllegalStateException
    dup
    invokespecial java/lang/IllegalStateException <init>:()V
    athrow
L15
    iload 7
    bipush -118
    invokestatic m e:(IB)Lag;
    astore 8
    goto L107
L79
    aload 13
    iconst_2
    sipush 512
    iload 14
    iadd
    iadd
    iload 12
    iastore
L108
    aload 13
    iload 14
    iconst_3
    iadd
    iload 12
    iastore
L60
    getstatic n ds:Lcb;
    iload 0
    iload 1
    iload 2
    invokevirtual cb ai:(III)I
    istore 6
    goto L109
L27
    aload 13
    iconst_1
    sipush 512
    iload 14
    iadd
    iadd
    iload 12
    iastore
    goto L101
L110
    iload 6
    ifle L16
    iload 5
    ldc 1389541124 (java.lang.Integer)
    if_icmplt L111
    new java/lang/IllegalStateException
    dup
    invokespecial java/lang/IllegalStateException <init>:()V
    athrow
L112
    getstatic fr ey:[Lbs;
    aload 8
    getfield ag aw:I
    ldc -2004655305 (java.lang.Integer)
    imul
    aaload
    astore 9
    goto L32
L22
    iload 13
    bipush 49
    invokestatic m e:(IB)Lag;
    astore 14
    goto L43
L109
    iload 6
    ifeq L33
    iload 5
    ldc 1389541124 (java.lang.Integer)
    if_icmplt L14
    new java/lang/IllegalStateException
    dup
    invokespecial java/lang/IllegalStateException <init>:()V
    athrow
L45
    aload 11
    iload 12
    sipush 1024
    iadd
    iload 10
    iastore
    goto L49
L66
    aload 14
    getfield ag y:I
    ldc 92157260 (java.lang.Integer)
    imul
    aload 15
    getfield bs c:I
    isub
    iconst_2
    idiv
    istore 17
    goto L36
L107
    iconst_m1
    ldc -2004655305 (java.lang.Integer)
    aload 8
    getfield ag aw:I
    imul
    if_icmpeq L33
    iload 5
    ldc 1389541124 (java.lang.Integer)
    if_icmplt L112
    new java/lang/IllegalStateException
    dup
    invokespecial java/lang/IllegalStateException <init>:()V
    athrow
L68
    getstatic n ds:Lcb;
    iload 0
    iload 1
    iload 2
    iload 6
    invokevirtual cb aw:(IIII)I
    istore 7
    goto L7
L9
    iload 3
    istore 10
    goto L110
L34
    aload 8
    getfield ag z:I
    ldc 1816092068 (java.lang.Integer)
    imul
    aload 9
    getfield bs l:I
    isub
    iconst_2
    idiv
    istore 10
    goto L88
L111
    iload 4
    istore 10
    goto L16
L89
    aload 9
    iload 1
    iconst_4
    imul
    bipush 48
    iadd
    iload 10
    iadd
    bipush 104
    iload 2
    isub
    ldc -1050702509 (java.lang.Integer)
    aload 8
    getfield ag y:I
    imul
    isub
    iconst_4
    imul
    bipush 48
    iadd
    iload 11
    iadd
    invokevirtual bs l:(II)V
    goto L33
L42
    aload 11
    iload 12
    iload 10
    iastore
    goto L44
L113
    new java/lang/StringBuilder
    dup
    invokespecial java/lang/StringBuilder <init>:()V
    ldc "au.as(" (java.lang.String)
    invokevirtual java/lang/StringBuilder append:(Ljava/lang/String;)Ljava/lang/StringBuilder;
    ldc 41 (java.lang.Integer)
    invokevirtual java/lang/StringBuilder append:(C)Ljava/lang/StringBuilder;
    invokevirtual java/lang/StringBuilder toString:()Ljava/lang/String;
    invokestatic k a:(Ljava/lang/Throwable;Ljava/lang/String;)Lee;
    athrow
