aw e (Lfv;Lfv;I)IL1
    iconst_0
    istore 3
    goto L2
L3
    aload 1
    ldc "sl_arrows" (java.lang.String)
    ldc "" (java.lang.String)
    ldc 1056635430 (java.lang.Integer)
    invokevirtual fv b:(Ljava/lang/String;Ljava/lang/String;I)Z
    pop
    goto L4
L5
    iinc 3 1
    goto L6
L7
    iinc 3 1
    goto L8
L9
    iinc 3 1
L10
    aload 1
    ldc "titlebox" (java.lang.String)
    ldc "" (java.lang.String)
    ldc 1056635430 (java.lang.Integer)
    invokevirtual fv b:(Ljava/lang/String;Ljava/lang/String;I)Z
    ifeq L11
    iload 2
    ldc 188042812 (java.lang.Integer)
    if_icmpne L12
    new java/lang/IllegalStateException
    dup
    invokespecial java/lang/IllegalStateException <init>:()V
    athrow
L12
    iinc 3 1
L11
    aload 1
    ldc "titlebutton" (java.lang.String)
    ldc "" (java.lang.String)
    ldc 1056635430 (java.lang.Integer)
    invokevirtual fv b:(Ljava/lang/String;Ljava/lang/String;I)Z
    ifeq L13
    iload 2
    ldc 188042812 (java.lang.Integer)
    if_icmpne L14
    new java/lang/IllegalStateException
    dup
    invokespecial java/lang/IllegalStateException <init>:()V
    athrow
L14
    iinc 3 1
    goto L13
L15
    iinc 3 1
    goto L16
L13
    aload 1
    ldc "runes" (java.lang.String)
    ldc "" (java.lang.String)
    ldc 1056635430 (java.lang.Integer)
    invokevirtual fv b:(Ljava/lang/String;Ljava/lang/String;I)Z
    ifeq L16
    iload 2
    ldc 188042812 (java.lang.Integer)
    if_icmpne L15
    new java/lang/IllegalStateException
    dup
    invokespecial java/lang/IllegalStateException <init>:()V
    athrow
L17
    iinc 3 1
L18
    aload 1
    ldc "sl_back" (java.lang.String)
    ldc "" (java.lang.String)
    ldc 1056635430 (java.lang.Integer)
    invokevirtual fv b:(Ljava/lang/String;Ljava/lang/String;I)Z
    pop
    goto L19
L8
    aload 1
    ldc "options_radio_buttons,0" (java.lang.String)
    bipush 6
    invokevirtual fv x:(Ljava/lang/String;B)Z
    ifeq L20
    iload 2
    ldc 188042812 (java.lang.Integer)
    if_icmpne L21
    new java/lang/IllegalStateException
    dup
    invokespecial java/lang/IllegalStateException <init>:()V
    athrow
L21
    iinc 3 1
L20
    aload 1
    ldc "options_radio_buttons,2" (java.lang.String)
    bipush 6
    invokevirtual fv x:(Ljava/lang/String;B)Z
    ifeq L18
    goto L17
L2
    aload 0
    ldc "title.jpg" (java.lang.String)
    ldc "" (java.lang.String)
    ldc 1056635430 (java.lang.Integer)
    invokevirtual fv b:(Ljava/lang/String;Ljava/lang/String;I)Z
    ifeq L6
    iload 2
    ldc 188042812 (java.lang.Integer)
    if_icmpne L5
    new java/lang/IllegalStateException
    dup
    invokespecial java/lang/IllegalStateException <init>:()V
    athrow
L16
    aload 1
    ldc "title_mute" (java.lang.String)
    ldc "" (java.lang.String)
    ldc 1056635430 (java.lang.Integer)
    invokevirtual fv b:(Ljava/lang/String;Ljava/lang/String;I)Z
    ifeq L8
    iload 2
    ldc 188042812 (java.lang.Integer)
    if_icmpne L7
    new java/lang/IllegalStateException
    dup
    invokespecial java/lang/IllegalStateException <init>:()V
    athrow
L19
    aload 1
    ldc "sl_flags" (java.lang.String)
    ldc "" (java.lang.String)
    ldc 1056635430 (java.lang.Integer)
    invokevirtual fv b:(Ljava/lang/String;Ljava/lang/String;I)Z
    pop
    goto L3
L6
    aload 1
    ldc "logo" (java.lang.String)
    ldc "" (java.lang.String)
    ldc 1056635430 (java.lang.Integer)
    invokevirtual fv b:(Ljava/lang/String;Ljava/lang/String;I)Z
    ifeq L10
    goto L9
L4
    aload 1
    ldc "sl_stars" (java.lang.String)
    ldc "" (java.lang.String)
    ldc 1056635430 (java.lang.Integer)
    invokevirtual fv b:(Ljava/lang/String;Ljava/lang/String;I)Z
    pop
L22
    aload 1
    ldc "sl_button" (java.lang.String)
    ldc "" (java.lang.String)
    ldc 1056635430 (java.lang.Integer)
    invokevirtual fv b:(Ljava/lang/String;Ljava/lang/String;I)Z
    pop
L23
    iload 3
    ireturn
L24
    new java/lang/StringBuilder
    dup
    invokespecial java/lang/StringBuilder <init>:()V
    ldc "aw.e(" (java.lang.String)
    invokevirtual java/lang/StringBuilder append:(Ljava/lang/String;)Ljava/lang/StringBuilder;
    ldc 41 (java.lang.Integer)
    invokevirtual java/lang/StringBuilder append:(C)Ljava/lang/StringBuilder;
    invokevirtual java/lang/StringBuilder toString:()Ljava/lang/String;
    invokestatic k a:(Ljava/lang/Throwable;Ljava/lang/String;)Lee;
    athrow
