ay c (Ldh;II)VL1
    iload 2
    iconst_1
    if_icmpne L2
    goto L3
L4
    aload 0
    iload 4
    newarray 9
    putfield ay y:[S
    goto L5
L6
    aload 0
    getfield ay aw:[I
    iload 5
    iconst_m1
    iastore
    goto L7
L8
    iconst_0
    istore 5
L9
    iload 5
    iload 4
    if_icmpge L10
    iload 3
    ldc 1060992664 (java.lang.Integer)
    if_icmpeq L11
    new java/lang/IllegalStateException
    dup
    invokespecial java/lang/IllegalStateException <init>:()V
    athrow
L12
    bipush 12
    iload 2
    if_icmpne L13
    iload 3
    ldc 1060992664 (java.lang.Integer)
    if_icmpeq L14
    new java/lang/IllegalStateException
    dup
    invokespecial java/lang/IllegalStateException <init>:()V
    athrow
L15
    iconst_0
    istore 5
    goto L16
L2
    iload 2
    iconst_2
    if_icmpne L12
    iload 3
    ldc 1060992664 (java.lang.Integer)
    if_icmpeq L17
    new java/lang/IllegalStateException
    dup
    invokespecial java/lang/IllegalStateException <init>:()V
    athrow
L18
    aload 1
    ldc 589202926 (java.lang.Integer)
    invokevirtual dh z:(I)I
    istore 4
    goto L19
L20
    aload 0
    ldc 1701138747 (java.lang.Integer)
    putfield ay au:I
    goto L21
L14
    aload 0
    aload 1
    ldc 1412850409 (java.lang.Integer)
    invokevirtual dh z:(I)I
    ldc -1993838141 (java.lang.Integer)
    imul
    putfield ay i:I
    goto L22
L13
    iload 2
    bipush 13
    if_icmpne L23
    iload 3
    ldc 1060992664 (java.lang.Integer)
    if_icmpeq L24
    return
L24
    aload 0
    aload 1
    ldc -1760411927 (java.lang.Integer)
    invokevirtual dh q:(I)I
    ldc 1607814391 (java.lang.Integer)
    imul
    putfield ay g:I
    goto L22
L25
    aload 0
    iconst_0
    putfield ay ab:Z
    goto L22
L26
    aload 0
    aload 1
    ldc -2023307939 (java.lang.Integer)
    invokevirtual dh q:(I)I
    ldc -368719071 (java.lang.Integer)
    imul
    putfield ay n:I
    goto L22
L27
    iload 2
    bipush 60
    if_icmpne L28
    iload 3
    ldc 1060992664 (java.lang.Integer)
    if_icmpeq L29
    new java/lang/IllegalStateException
    dup
    invokespecial java/lang/IllegalStateException <init>:()V
    athrow
L30
    aload 0
    aload 1
    ldc -192300708 (java.lang.Integer)
    invokevirtual dh q:(I)I
    ldc -1490656701 (java.lang.Integer)
    imul
    putfield ay o:I
    goto L22
L31
    iload 5
    iload 4
    if_icmpge L32
    iload 3
    ldc 1060992664 (java.lang.Integer)
    if_icmpeq L33
    new java/lang/IllegalStateException
    dup
    invokespecial java/lang/IllegalStateException <init>:()V
    athrow
L34
    aload 0
    aload 1
    ldc -74968590 (java.lang.Integer)
    invokevirtual dh q:(I)I
    ldc 1153609343 (java.lang.Integer)
    imul
    putfield ay h:I
    goto L22
L35
    iload 2
    bipush 17
    if_icmpne L36
    iload 3
    ldc 1060992664 (java.lang.Integer)
    if_icmpeq L37
    new java/lang/IllegalStateException
    dup
    invokespecial java/lang/IllegalStateException <init>:()V
    athrow
L38
    iload 2
    bipush 107
    if_icmpne L39
    iload 3
    ldc 1060992664 (java.lang.Integer)
    if_icmpeq L40
    new java/lang/IllegalStateException
    dup
    invokespecial java/lang/IllegalStateException <init>:()V
    athrow
L41
    aload 0
    aload 1
    ldc 1184792149 (java.lang.Integer)
    invokevirtual dh q:(I)I
    ldc -1560119777 (java.lang.Integer)
    imul
    putfield ay j:I
L42
    aload 0
    aload 1
    ldc -1485166022 (java.lang.Integer)
    invokevirtual dh q:(I)I
    ldc -957352651 (java.lang.Integer)
    imul
    putfield ay m:I
L43
    aload 0
    aload 1
    ldc -2079629524 (java.lang.Integer)
    invokevirtual dh q:(I)I
    ldc -1568555477 (java.lang.Integer)
    imul
    putfield ay t:I
    goto L22
L36
    iload 2
    bipush 30
    if_icmplt L44
    iload 3
    ldc 1060992664 (java.lang.Integer)
    if_icmpeq L45
    new java/lang/IllegalStateException
    dup
    invokespecial java/lang/IllegalStateException <init>:()V
    athrow
L45
    iload 2
    bipush 35
    if_icmpge L44
    iload 3
    ldc 1060992664 (java.lang.Integer)
    if_icmpeq L46
    new java/lang/IllegalStateException
    dup
    invokespecial java/lang/IllegalStateException <init>:()V
    athrow
L46
    aload 0
    getfield ay b:[Ljava/lang/String;
    iload 2
    bipush 30
    isub
    aload 1
    ldc -129754454 (java.lang.Integer)
    invokevirtual dh p:(I)Ljava/lang/String;
    aastore
    goto L47
L16
    iload 5
    iload 4
    if_icmpge L48
    goto L49
L50
    aload 0
    getfield ay b:[Ljava/lang/String;
    iload 2
    bipush 30
    isub
    aconst_null
    aastore
    goto L22
L51
    aload 0
    aload 1
    ldc -436551237 (java.lang.Integer)
    invokevirtual dh q:(I)I
    ldc -1957209155 (java.lang.Integer)
    imul
    putfield ay p:I
    goto L22
L52
    aload 0
    iconst_0
    putfield ay x:Z
    goto L22
L19
    aload 0
    iload 4
    newarray 9
    putfield ay z:[S
    goto L4
L47
    aload 0
    getfield ay b:[Ljava/lang/String;
    iload 2
    bipush 30
    isub
    aaload
    getstatic et c:Ljava/lang/String;
    invokevirtual java/lang/String equalsIgnoreCase:(Ljava/lang/String;)Z
    ifeq L22
    iload 3
    ldc 1060992664 (java.lang.Integer)
    if_icmpeq L50
    new java/lang/IllegalStateException
    dup
    invokespecial java/lang/IllegalStateException <init>:()V
    athrow
L5
    iconst_0
    istore 5
    goto L53
L54
    bipush 102
    iload 2
    if_icmpne L55
    goto L56
L57
    aload 0
    getfield ay z:[S
    iload 5
    aload 1
    ldc -220426021 (java.lang.Integer)
    invokevirtual dh q:(I)I
    i2s
    sastore
    goto L58
L59
    aload 0
    aload 1
    ldc 749040778 (java.lang.Integer)
    invokevirtual dh q:(I)I
    ldc -1701138747 (java.lang.Integer)
    imul
    putfield ay au:I
    goto L60
L61
    iinc 5 1
    goto L53
L62
    goto L22
L63
    iload 2
    bipush 41
    if_icmpne L27
    iload 3
    ldc 1060992664 (java.lang.Integer)
    if_icmpeq L64
    return
L65
    iload 2
    bipush 16
    if_icmpne L35
    iload 3
    ldc 1060992664 (java.lang.Integer)
    if_icmpeq L34
    new java/lang/IllegalStateException
    dup
    invokespecial java/lang/IllegalStateException <init>:()V
    athrow
L66
    aload 0
    iload 4
    newarray 9
    putfield ay q:[S
L67
    aload 0
    iload 4
    newarray 9
    putfield ay d:[S
    goto L15
L3
    aload 1
    ldc 1355724050 (java.lang.Integer)
    invokevirtual dh z:(I)I
    istore 4
    goto L68
L49
    aload 0
    getfield ay q:[S
    iload 5
    aload 1
    ldc -718849293 (java.lang.Integer)
    invokevirtual dh q:(I)I
    i2s
    sastore
    goto L69
L70
    iload 2
    bipush 99
    if_icmpne L71
    iload 3
    ldc 1060992664 (java.lang.Integer)
    if_icmpeq L72
    new java/lang/IllegalStateException
    dup
    invokespecial java/lang/IllegalStateException <init>:()V
    athrow
L69
    aload 0
    getfield ay d:[S
    iload 5
    aload 1
    ldc -521652258 (java.lang.Integer)
    invokevirtual dh q:(I)I
    i2s
    sastore
L73
    iinc 5 1
    goto L16
L39
    bipush 109
    iload 2
    if_icmpne L74
    iload 3
    ldc 1060992664 (java.lang.Integer)
    if_icmpeq L25
    new java/lang/IllegalStateException
    dup
    invokespecial java/lang/IllegalStateException <init>:()V
    athrow
L75
    iload 2
    bipush 112
    if_icmpne L22
    iload 3
    ldc 1060992664 (java.lang.Integer)
    if_icmpeq L76
    new java/lang/IllegalStateException
    dup
    invokespecial java/lang/IllegalStateException <init>:()V
    athrow
L29
    aload 1
    ldc 1483289142 (java.lang.Integer)
    invokevirtual dh z:(I)I
    istore 4
L77
    aload 0
    iload 4
    newarray 10
    putfield ay f:[I
L78
    iconst_0
    istore 5
    goto L31
L79
    aload 0
    aload 1
    ldc 773604972 (java.lang.Integer)
    invokevirtual dh q:(I)I
    ldc -572240757 (java.lang.Integer)
    imul
    putfield ay s:I
    goto L22
L33
    aload 0
    getfield ay f:[I
    iload 5
    aload 1
    ldc -1852502589 (java.lang.Integer)
    invokevirtual dh q:(I)I
    iastore
    iinc 5 1
    goto L31
L32
    goto L22
L28
    iload 2
    bipush 93
    if_icmpne L80
    iload 3
    ldc 1060992664 (java.lang.Integer)
    if_icmpeq L52
    new java/lang/IllegalStateException
    dup
    invokespecial java/lang/IllegalStateException <init>:()V
    athrow
L58
    aload 0
    getfield ay y:[S
    iload 5
    aload 1
    ldc -196087935 (java.lang.Integer)
    invokevirtual dh q:(I)I
    i2s
    sastore
    goto L61
L80
    iload 2
    bipush 95
    if_icmpne L81
    iload 3
    ldc 1060992664 (java.lang.Integer)
    if_icmpeq L26
    new java/lang/IllegalStateException
    dup
    invokespecial java/lang/IllegalStateException <init>:()V
    athrow
L68
    aload 0
    iload 4
    newarray 10
    putfield ay r:[I
    goto L8
L81
    bipush 97
    iload 2
    if_icmpne L82
    iload 3
    ldc 1060992664 (java.lang.Integer)
    if_icmpeq L83
    new java/lang/IllegalStateException
    dup
    invokespecial java/lang/IllegalStateException <init>:()V
    athrow
L83
    aload 0
    aload 1
    ldc 338360324 (java.lang.Integer)
    invokevirtual dh q:(I)I
    ldc -1760539885 (java.lang.Integer)
    imul
    putfield ay v:I
    goto L22
L82
    bipush 98
    iload 2
    if_icmpne L70
    iload 3
    ldc 1060992664 (java.lang.Integer)
    if_icmpeq L51
    return
L53
    iload 5
    iload 4
    if_icmpge L62
    iload 3
    ldc 1060992664 (java.lang.Integer)
    if_icmpeq L57
    new java/lang/IllegalStateException
    dup
    invokespecial java/lang/IllegalStateException <init>:()V
    athrow
L11
    aload 0
    getfield ay r:[I
    iload 5
    aload 1
    ldc -1157461365 (java.lang.Integer)
    invokevirtual dh q:(I)I
    iastore
    iinc 5 1
    goto L9
L72
    aload 0
    iconst_1
    putfield ay k:Z
    goto L22
L71
    bipush 100
    iload 2
    if_icmpne L84
    iload 3
    ldc 1060992664 (java.lang.Integer)
    if_icmpeq L85
    new java/lang/IllegalStateException
    dup
    invokespecial java/lang/IllegalStateException <init>:()V
    athrow
L85
    aload 0
    aload 1
    bipush 64
    invokevirtual dh y:(B)B
    ldc -984554669 (java.lang.Integer)
    imul
    putfield ay ax:I
    goto L22
L84
    bipush 101
    iload 2
    if_icmpne L54
    iload 3
    ldc 1060992664 (java.lang.Integer)
    if_icmpeq L86
    new java/lang/IllegalStateException
    dup
    invokespecial java/lang/IllegalStateException <init>:()V
    athrow
L44
    bipush 40
    iload 2
    if_icmpne L63
    goto L18
L10
    goto L22
L56
    aload 0
    aload 1
    ldc 1470656634 (java.lang.Integer)
    invokevirtual dh q:(I)I
    ldc -1099120245 (java.lang.Integer)
    imul
    putfield ay ao:I
    goto L22
L55
    iload 2
    bipush 103
    if_icmpne L87
    aload 0
    aload 1
    ldc -1509589914 (java.lang.Integer)
    invokevirtual dh q:(I)I
    ldc -1737786671 (java.lang.Integer)
    imul
    putfield ay ai:I
    goto L22
L87
    bipush 106
    iload 2
    if_icmpne L38
    iload 3
    ldc 1060992664 (java.lang.Integer)
    if_icmpeq L88
    new java/lang/IllegalStateException
    dup
    invokespecial java/lang/IllegalStateException <init>:()V
    athrow
L89
    bipush 15
    iload 2
    if_icmpne L65
    iload 3
    ldc 1060992664 (java.lang.Integer)
    if_icmpeq L30
    new java/lang/IllegalStateException
    dup
    invokespecial java/lang/IllegalStateException <init>:()V
    athrow
L90
    aload 0
    getfield ay am:I
    ldc -161384219 (java.lang.Integer)
    imul
    ldc 65535 (java.lang.Integer)
    if_icmpne L59
    iload 3
    ldc 1060992664 (java.lang.Integer)
    if_icmpeq L91
    new java/lang/IllegalStateException
    dup
    invokespecial java/lang/IllegalStateException <init>:()V
    athrow
L48
    goto L22
L91
    aload 0
    ldc -1508476141 (java.lang.Integer)
    putfield ay am:I
    goto L59
L60
    aload 0
    getfield ay au:I
    ldc 1675796493 (java.lang.Integer)
    imul
    ldc 65535 (java.lang.Integer)
    if_icmpne L21
    iload 3
    ldc 1060992664 (java.lang.Integer)
    if_icmpeq L20
    return
L88
    aload 0
    aload 1
    ldc 439831937 (java.lang.Integer)
    invokevirtual dh q:(I)I
    ldc 1508476141 (java.lang.Integer)
    imul
    putfield ay am:I
    goto L90
L21
    aload 1
    ldc 1211429485 (java.lang.Integer)
    invokevirtual dh z:(I)I
    istore 4
L92
    aload 0
    iconst_1
    iload 4
    iadd
    newarray 10
    putfield ay aw:[I
L93
    iconst_0
    istore 5
L94
    iload 5
    iload 4
    if_icmpgt L95
L96
    aload 0
    getfield ay aw:[I
    iload 5
    aload 1
    ldc 450332058 (java.lang.Integer)
    invokevirtual dh q:(I)I
    iastore
L97
    aload 0
    getfield ay aw:[I
    iload 5
    iaload
    ldc 65535 (java.lang.Integer)
    if_icmpne L7
    iload 3
    ldc 1060992664 (java.lang.Integer)
    if_icmpeq L6
    new java/lang/IllegalStateException
    dup
    invokespecial java/lang/IllegalStateException <init>:()V
    athrow
L17
    aload 0
    aload 1
    ldc 1168483222 (java.lang.Integer)
    invokevirtual dh p:(I)Ljava/lang/String;
    putfield ay w:Ljava/lang/String;
    goto L22
L7
    iinc 5 1
    goto L94
L95
    goto L22
L86
    aload 0
    aload 1
    bipush 80
    invokevirtual dh y:(B)B
    ldc -2025364061 (java.lang.Integer)
    imul
    putfield ay ap:I
    goto L22
L40
    aload 0
    iconst_0
    putfield ay ae:Z
    goto L22
L23
    bipush 14
    iload 2
    if_icmpne L89
    goto L79
L64
    aload 1
    ldc 1849706343 (java.lang.Integer)
    invokevirtual dh z:(I)I
    istore 4
    goto L66
L74
    iload 2
    bipush 111
    if_icmpne L75
    iload 3
    ldc 1060992664 (java.lang.Integer)
    if_icmpeq L98
    new java/lang/IllegalStateException
    dup
    invokespecial java/lang/IllegalStateException <init>:()V
    athrow
L98
    aload 0
    iconst_1
    putfield ay av:Z
    goto L22
L37
    aload 0
    aload 1
    ldc -284527174 (java.lang.Integer)
    invokevirtual dh q:(I)I
    ldc -572240757 (java.lang.Integer)
    imul
    putfield ay s:I
    goto L41
L76
    aload 0
    aload 1
    ldc 1889707818 (java.lang.Integer)
    invokevirtual dh z:(I)I
    ldc -934067233 (java.lang.Integer)
    imul
    putfield ay ay:I
L22
    return
L99
    new java/lang/StringBuilder
    dup
    invokespecial java/lang/StringBuilder <init>:()V
    ldc "ay.c(" (java.lang.String)
    invokevirtual java/lang/StringBuilder append:(Ljava/lang/String;)Ljava/lang/StringBuilder;
    ldc 41 (java.lang.Integer)
    invokevirtual java/lang/StringBuilder append:(C)Ljava/lang/StringBuilder;
    invokevirtual java/lang/StringBuilder toString:()Ljava/lang/String;
    invokestatic k a:(Ljava/lang/Throwable;Ljava/lang/String;)Lee;
    athrow
