ay l ([BIIIIIII[Lhk;I)VL1
    iconst_0
    istore 10
    goto L2
L3
    iload 19
    istore 17
    goto L4
L5
    iconst_0
    istore 11
L6
    iload 11
    bipush 8
    if_icmpge L7
    iload 9
    ldc -1760826082 (java.lang.Integer)
    if_icmpeq L8
    return
L8
    iload 10
    iload 2
    iadd
    ifle L9
    iload 9
    ldc -1760826082 (java.lang.Integer)
    if_icmpeq L10
    return
L10
    iload 2
    iload 10
    iadd
    bipush 103
    if_icmpge L9
    iload 3
    iload 11
    iadd
    ifle L9
    iload 9
    ldc -1760826082 (java.lang.Integer)
    if_icmpeq L11
    new java/lang/IllegalStateException
    dup
    invokespecial java/lang/IllegalStateException <init>:()V
    athrow
L12
    iload 12
    iload 5
    if_icmplt L13
    iload 9
    ldc -1760826082 (java.lang.Integer)
    if_icmpeq L14
    new java/lang/IllegalStateException
    dup
    invokespecial java/lang/IllegalStateException <init>:()V
    athrow
L15
    aload 8
    iload 1
    aaload
    getfield hk ai:[[I
    iload 10
    iload 2
    iadd
    aaload
    iload 3
    iload 11
    iadd
    dup2
    iaload
    ldc -16777217 (java.lang.Integer)
    iand
    iastore
    goto L9
L16
    aload 21
    iload 22
    iload 23
    iload 24
    iload 25
    iadd
    iconst_0
    iconst_0
    iload 7
    bipush 16
    invokestatic bz u:(Ldh;IIIIIIB)V
    goto L17
L18
    iconst_0
    istore 13
    goto L19
L20
    new dh
    dup
    aload 0
    invokespecial dh <init>:([B)V
    astore 10
L21
    iconst_0
    istore 11
    goto L22
L23
    goto L16
L24
    iconst_0
    istore 12
L25
    iload 12
    bipush 64
    if_icmpge L26
    goto L18
L9
    iinc 11 1
    goto L6
L19
    iload 13
    bipush 64
    if_icmpge L27
    iload 9
    ldc -1760826082 (java.lang.Integer)
    if_icmpeq L28
    new java/lang/IllegalStateException
    dup
    invokespecial java/lang/IllegalStateException <init>:()V
    athrow
L13
    aload 10
    iconst_0
    iconst_m1
    iconst_m1
    iconst_0
    iconst_0
    iconst_0
    bipush 16
    invokestatic bz u:(Ldh;IIIIIIB)V
    goto L29
L30
    iload 12
    bipush 7
    iand
    istore 18
    goto L31
L14
    iload 12
    iload 5
    bipush 8
    iadd
    if_icmpge L13
    iload 9
    ldc -1760826082 (java.lang.Integer)
    if_icmpeq L32
    return
L32
    iload 13
    iload 6
    if_icmplt L13
    iload 9
    ldc -1760826082 (java.lang.Integer)
    if_icmpeq L33
    return
L33
    iload 13
    iload 6
    bipush 8
    iadd
    if_icmpge L13
    iload 9
    ldc -1760826082 (java.lang.Integer)
    if_icmpeq L34
    new java/lang/IllegalStateException
    dup
    invokespecial java/lang/IllegalStateException <init>:()V
    athrow
L34
    aload 10
    astore 14
    goto L35
L7
    iinc 10 1
    goto L2
L36
    iload 7
    istore 28
    goto L37
L38
    iconst_2
    iload 20
    if_icmpne L39
    iload 9
    ldc -1760826082 (java.lang.Integer)
    if_icmpeq L40
    return
L31
    iload 13
    bipush 7
    iand
    istore 19
L41
    iload 7
    istore 20
L42
    iload 20
    iconst_3
    iand
    istore 20
L43
    iconst_0
    iload 20
    if_icmpne L44
    goto L45
L46
    iload 13
    bipush 7
    iand
    istore 27
    goto L36
L47
    goto L48
L44
    iconst_1
    iload 20
    if_icmpne L38
    iload 9
    ldc -1760826082 (java.lang.Integer)
    if_icmpeq L3
    new java/lang/IllegalStateException
    dup
    invokespecial java/lang/IllegalStateException <init>:()V
    athrow
L35
    iload 1
    istore 15
    goto L49
L4
    goto L48
L45
    iload 18
    istore 17
    goto L47
L40
    bipush 7
    iload 18
    isub
    istore 17
    goto L50
L28
    iload 4
    iload 11
    if_icmpne L13
    iload 9
    ldc -1760826082 (java.lang.Integer)
    if_icmpeq L12
    new java/lang/IllegalStateException
    dup
    invokespecial java/lang/IllegalStateException <init>:()V
    athrow
L39
    bipush 7
    iload 19
    isub
    istore 17
L48
    aload 14
    astore 21
    goto L51
L2
    iload 10
    bipush 8
    if_icmpge L20
    iload 9
    ldc -1760826082 (java.lang.Integer)
    if_icmpeq L5
    new java/lang/IllegalStateException
    dup
    invokespecial java/lang/IllegalStateException <init>:()V
    athrow
L49
    iload 2
    istore 16
    goto L30
L52
    iload 3
    istore 24
L53
    iload 12
    bipush 7
    iand
    istore 26
    goto L46
L17
    goto L29
L11
    iload 3
    iload 11
    iadd
    bipush 103
    if_icmpge L9
    iload 9
    ldc -1760826082 (java.lang.Integer)
    if_icmpeq L15
    new java/lang/IllegalStateException
    dup
    invokespecial java/lang/IllegalStateException <init>:()V
    athrow
L37
    iload 28
    iconst_3
    iand
    istore 28
L54
    iconst_0
    iload 28
    if_icmpne L55
    iload 9
    ldc -1760826082 (java.lang.Integer)
    if_icmpeq L56
    new java/lang/IllegalStateException
    dup
    invokespecial java/lang/IllegalStateException <init>:()V
    athrow
L56
    iload 27
    istore 25
L57
    goto L16
L55
    iconst_1
    iload 28
    if_icmpne L58
    iload 9
    ldc -1760826082 (java.lang.Integer)
    if_icmpeq L59
    new java/lang/IllegalStateException
    dup
    invokespecial java/lang/IllegalStateException <init>:()V
    athrow
L51
    iload 15
    istore 22
    goto L60
L61
    goto L16
L58
    iconst_2
    iload 28
    if_icmpne L62
    iload 9
    ldc -1760826082 (java.lang.Integer)
    if_icmpeq L63
    new java/lang/IllegalStateException
    dup
    invokespecial java/lang/IllegalStateException <init>:()V
    athrow
L50
    goto L48
L59
    bipush 7
    iload 26
    isub
    istore 25
    goto L61
L62
    iload 26
    istore 25
    goto L16
L27
    iinc 12 1
    goto L25
L60
    iload 17
    iload 16
    iadd
    istore 23
    goto L52
L63
    bipush 7
    iload 27
    isub
    istore 25
    goto L23
L29
    iinc 13 1
    goto L19
L22
    iload 11
    iconst_4
    if_icmpge L64
    iload 9
    ldc -1760826082 (java.lang.Integer)
    if_icmpeq L24
    new java/lang/IllegalStateException
    dup
    invokespecial java/lang/IllegalStateException <init>:()V
    athrow
L26
    iinc 11 1
    goto L22
L64
    return
L65
    new java/lang/StringBuilder
    dup
    invokespecial java/lang/StringBuilder <init>:()V
    ldc "ay.l(" (java.lang.String)
    invokevirtual java/lang/StringBuilder append:(Ljava/lang/String;)Ljava/lang/StringBuilder;
    ldc 41 (java.lang.Integer)
    invokevirtual java/lang/StringBuilder append:(C)Ljava/lang/StringBuilder;
    invokevirtual java/lang/StringBuilder toString:()Ljava/lang/String;
    invokestatic k a:(Ljava/lang/Throwable;Ljava/lang/String;)Lee;
    athrow
