ay u (Lah;ILah;IB)Lcy;L1
    aconst_null
    aload 0
    getfield ay aw:[I
    if_acmpeq L2
    iload 5
    bipush 102
    if_icmplt L3
    new java/lang/IllegalStateException
    dup
    invokespecial java/lang/IllegalStateException <init>:()V
    athrow
L4
    iinc 10 1
    goto L5
L6
    aload 6
    ifnonnull L7
    iload 5
    bipush 102
    if_icmplt L8
    new java/lang/IllegalStateException
    dup
    invokespecial java/lang/IllegalStateException <init>:()V
    athrow
L9
    iinc 8 1
    goto L10
L7
    aload 6
    aload 1
    iload 2
    aload 3
    iload 4
    bipush -6
    invokevirtual ay u:(Lah;ILah;IB)Lcy;
    areturn
L2
    getstatic ay c:Lgr;
    ldc -1471228279 (java.lang.Integer)
    aload 0
    getfield ay u:I
    imul
    i2l
    invokevirtual gr e:(J)Lgd;
    checkcast cy
    astore 6
    goto L11
L8
    aconst_null
    areturn
L12
    iconst_0
    istore 7
L13
    iconst_0
    istore 8
    goto L10
L3
    aload 0
    ldc -1152297705 (java.lang.Integer)
    invokevirtual ay i:(I)Lay;
    astore 6
    goto L6
L14
    getstatic ay a:Lfv;
    aload 0
    getfield ay r:[I
    iload 8
    iaload
    iconst_0
    bipush -121
    invokevirtual fv u:(IIB)Z
    ifne L9
    iload 5
    bipush 102
    if_icmplt L15
    new java/lang/IllegalStateException
    dup
    invokespecial java/lang/IllegalStateException <init>:()V
    athrow
L15
    iconst_1
    istore 7
    goto L9
L16
    aload 1
    ifnull L17
    iload 5
    bipush 102
    if_icmplt L18
    new java/lang/IllegalStateException
    dup
    invokespecial java/lang/IllegalStateException <init>:()V
    athrow
L19
    aconst_null
    aload 0
    getfield ay q:[S
    if_acmpeq L20
    iload 5
    bipush 102
    if_icmplt L21
    new java/lang/IllegalStateException
    dup
    invokespecial java/lang/IllegalStateException <init>:()V
    athrow
L22
    aconst_null
    areturn
L23
    aload 0
    getfield ay r:[I
    arraylength
    anewarray cr
    astore 9
L24
    iconst_0
    istore 10
L25
    iload 10
    aload 0
    getfield ay r:[I
    arraylength
    if_icmpge L26
    iload 5
    bipush 102
    if_icmplt L27
    new java/lang/IllegalStateException
    dup
    invokespecial java/lang/IllegalStateException <init>:()V
    athrow
L28
    aload 1
    aload 6
    iload 2
    aload 3
    iload 4
    ldc -1346520529 (java.lang.Integer)
    invokevirtual ah r:(Lcy;ILah;II)Lcy;
    astore 7
    goto L29
L30
    aload 9
    iconst_0
    aaload
    astore 8
    goto L31
L29
    aload 0
    getfield ay v:I
    ldc -1340262629 (java.lang.Integer)
    imul
    sipush 128
    if_icmpne L32
    iload 5
    bipush 102
    if_icmplt L33
    new java/lang/IllegalStateException
    dup
    invokespecial java/lang/IllegalStateException <init>:()V
    athrow
L17
    aload 3
    ifnull L34
    iload 5
    bipush 102
    if_icmplt L35
    new java/lang/IllegalStateException
    dup
    invokespecial java/lang/IllegalStateException <init>:()V
    athrow
L36
    new cr
    dup
    aload 9
    aload 9
    arraylength
    invokespecial cr <init>:([Lcr;I)V
    astore 8
    goto L31
L37
    iconst_0
    istore 10
L5
    iload 10
    aload 0
    getfield ay z:[S
    arraylength
    if_icmpge L19
    iload 5
    bipush 102
    if_icmplt L38
    new java/lang/IllegalStateException
    dup
    invokespecial java/lang/IllegalStateException <init>:()V
    athrow
L38
    aload 8
    aload 0
    getfield ay z:[S
    iload 10
    saload
    aload 0
    getfield ay y:[S
    iload 10
    saload
    invokevirtual cr z:(SS)V
    goto L4
L39
    aload 8
    aload 0
    getfield ay q:[S
    iload 10
    saload
    aload 0
    getfield ay d:[S
    iload 10
    saload
    invokevirtual cr y:(SS)V
    goto L40
L10
    iload 8
    aload 0
    getfield ay r:[I
    arraylength
    if_icmpge L41
    iload 5
    bipush 102
    if_icmplt L14
    new java/lang/IllegalStateException
    dup
    invokespecial java/lang/IllegalStateException <init>:()V
    athrow
L27
    aload 9
    iload 10
    getstatic ay a:Lfv;
    aload 0
    getfield ay r:[I
    iload 10
    iaload
    iconst_0
    invokestatic cr e:(Lfv;II)Lcr;
    aastore
    iinc 10 1
    goto L25
L31
    aconst_null
    aload 0
    getfield ay z:[S
    if_acmpeq L19
    goto L37
L32
    aload 7
    ldc -1340262629 (java.lang.Integer)
    aload 0
    getfield ay v:I
    imul
    aload 0
    getfield ay p:I
    ldc -178636907 (java.lang.Integer)
    imul
    aload 0
    getfield ay v:I
    ldc -1340262629 (java.lang.Integer)
    imul
    invokevirtual cy d:(III)V
    goto L42
L40
    iinc 10 1
    goto L43
L20
    aload 8
    aload 0
    getfield ay ax:I
    ldc 261314779 (java.lang.Integer)
    imul
    bipush 64
    iadd
    aload 0
    getfield ay ap:I
    ldc -1834955209 (java.lang.Integer)
    imul
    sipush 850
    iadd
    bipush -30
    bipush -50
    bipush -30
    invokevirtual cr p:(IIIII)Lcy;
    astore 6
L44
    getstatic ay c:Lgr;
    aload 6
    aload 0
    getfield ay u:I
    ldc -1471228279 (java.lang.Integer)
    imul
    i2l
    invokevirtual gr l:(Lgd;J)V
L45
    aconst_null
    aload 1
    if_acmpeq L16
    iload 5
    bipush 102
    if_icmplt L46
    new java/lang/IllegalStateException
    dup
    invokespecial java/lang/IllegalStateException <init>:()V
    athrow
L46
    aconst_null
    aload 3
    if_acmpeq L16
    iload 5
    bipush 102
    if_icmplt L28
    new java/lang/IllegalStateException
    dup
    invokespecial java/lang/IllegalStateException <init>:()V
    athrow
L43
    iload 10
    aload 0
    getfield ay q:[S
    arraylength
    if_icmpge L20
    iload 5
    bipush 102
    if_icmplt L39
    new java/lang/IllegalStateException
    dup
    invokespecial java/lang/IllegalStateException <init>:()V
    athrow
L41
    iload 7
    ifeq L23
    iload 5
    bipush 102
    if_icmplt L22
    new java/lang/IllegalStateException
    dup
    invokespecial java/lang/IllegalStateException <init>:()V
    athrow
L18
    aload 1
    aload 6
    iload 2
    ldc 2030992556 (java.lang.Integer)
    invokevirtual ah u:(Lcy;II)Lcy;
    astore 7
    goto L29
L11
    aload 6
    ifnonnull L45
    iload 5
    bipush 102
    if_icmplt L12
    new java/lang/IllegalStateException
    dup
    invokespecial java/lang/IllegalStateException <init>:()V
    athrow
L35
    aload 3
    aload 6
    iload 4
    ldc -1142479531 (java.lang.Integer)
    invokevirtual ah u:(Lcy;II)Lcy;
    astore 7
    goto L29
L34
    aload 6
    iconst_1
    invokevirtual cy l:(Z)Lcy;
    astore 7
    goto L29
L26
    aload 9
    arraylength
    iconst_1
    if_icmpne L36
    iload 5
    bipush 102
    if_icmplt L30
    new java/lang/IllegalStateException
    dup
    invokespecial java/lang/IllegalStateException <init>:()V
    athrow
L33
    sipush 128
    aload 0
    getfield ay p:I
    ldc -178636907 (java.lang.Integer)
    imul
    if_icmpeq L42
    iload 5
    bipush 102
    if_icmplt L32
    new java/lang/IllegalStateException
    dup
    invokespecial java/lang/IllegalStateException <init>:()V
    athrow
L21
    iconst_0
    istore 10
    goto L43
L42
    aload 7
    areturn
L47
    new java/lang/StringBuilder
    dup
    invokespecial java/lang/StringBuilder <init>:()V
    ldc "ay.u(" (java.lang.String)
    invokevirtual java/lang/StringBuilder append:(Ljava/lang/String;)Ljava/lang/StringBuilder;
    ldc 41 (java.lang.Integer)
    invokevirtual java/lang/StringBuilder append:(C)Ljava/lang/StringBuilder;
    invokevirtual java/lang/StringBuilder toString:()Ljava/lang/String;
    invokestatic k a:(Ljava/lang/Throwable;Ljava/lang/String;)Lee;
    athrow
