b z (IIIIIIILcb;Lhk;I)VL1
    iload 4
    bipush 71
    invokestatic m e:(IB)Lag;
    astore 10
    goto L2
L3
    new h
    dup
    iload 4
    iconst_0
    iload 5
    iload 1
    iload 2
    iload 3
    ldc -175609259 (java.lang.Integer)
    aload 10
    getfield ag p:I
    imul
    iconst_1
    aconst_null
    invokespecial h <init>:(IIIIIIIZLch;)V
    astore 23
    goto L4
L5
    aload 8
    iload 2
    iload 3
    iload 6
    iload 5
    aload 10
    getfield ag d:Z
    ldc -436307848 (java.lang.Integer)
    invokevirtual hk a:(IIIIZI)V
    goto L6
L7
    iinc 22 256
    goto L8
L9
    iconst_0
    goto L10
L11
    aload 10
    getfield ag z:I
    ldc 1527764841 (java.lang.Integer)
    imul
    istore 11
L12
    aload 10
    getfield ag y:I
    ldc -1050702509 (java.lang.Integer)
    imul
    istore 12
    goto L13
L14
    return
L15
    iload 11
    iconst_1
    ishr
    iload 2
    iadd
    istore 13
L16
    iconst_1
    iload 11
    iadd
    iconst_1
    ishr
    iload 2
    iadd
    istore 14
    goto L17
L18
    iload 2
    istore 13
L19
    iload 2
    iconst_1
    iadd
    istore 14
L17
    iload 3
    iload 12
    iadd
    bipush 104
    if_icmpgt L20
    iload 9
    ldc 1922003277 (java.lang.Integer)
    if_icmpeq L21
    new java/lang/IllegalStateException
    dup
    invokespecial java/lang/IllegalStateException <init>:()V
    athrow
L22
    iconst_3
    iload 5
    if_icmpne L11
    iload 9
    ldc 1922003277 (java.lang.Integer)
    if_icmpeq L23
    new java/lang/IllegalStateException
    dup
    invokespecial java/lang/IllegalStateException <init>:()V
    athrow
L24
    iload 3
    iload 12
    iconst_1
    iadd
    iconst_1
    ishr
    iadd
    istore 16
    goto L25
L20
    iload 3
    istore 15
L26
    iload 3
    iconst_1
    iadd
    istore 16
    goto L25
L27
    aload 7
    iload 0
    iload 2
    iload 3
    iload 18
    aload 23
    aconst_null
    getstatic w q:[I
    iload 5
    iaload
    iconst_0
    iconst_0
    iconst_0
    iload 21
    iload 22
    invokevirtual cb g:(IIIILch;Lch;IIIIII)V
    goto L28
L29
    iload 5
    iconst_2
    iadd
    iconst_3
    iand
    istore 24
    goto L30
L31
    iload 11
    bipush 6
    ishl
    iload 2
    bipush 7
    ishl
    iadd
    istore 19
    goto L32
L33
    aload 8
    iload 2
    iload 3
    iload 11
    iload 12
    aload 10
    getfield ag d:Z
    bipush -10
    invokevirtual hk l:(IIIIZB)V
    goto L34
L35
    aload 10
    iconst_1
    iload 5
    aload 17
    iload 19
    iload 18
    iload 20
    bipush -21
    invokevirtual ag r:(II[[IIIIB)Lcy;
    astore 23
    goto L36
L37
    aload 10
    getfield ag b:I
    ldc 1715787739 (java.lang.Integer)
    imul
    ifne L38
    iload 9
    ldc 1922003277 (java.lang.Integer)
    if_icmpeq L39
    new java/lang/IllegalStateException
    dup
    invokespecial java/lang/IllegalStateException <init>:()V
    athrow
L39
    iload 21
    ldc -2147483648 (java.lang.Integer)
    isub
    istore 21
L38
    iload 6
    iload 5
    bipush 6
    ishl
    iadd
    istore 22
L40
    aload 10
    getfield ag al:I
    ldc 970437277 (java.lang.Integer)
    imul
    iconst_1
    if_icmpne L8
    iload 9
    ldc 1922003277 (java.lang.Integer)
    if_icmpeq L7
    new java/lang/IllegalStateException
    dup
    invokespecial java/lang/IllegalStateException <init>:()V
    athrow
L41
    iconst_m1
    ldc -175609259 (java.lang.Integer)
    aload 10
    getfield ag p:I
    imul
    if_icmpne L42
    iload 9
    ldc 1922003277 (java.lang.Integer)
    if_icmpeq L43
    return
L44
    aconst_null
    aload 10
    getfield ag ak:[I
    if_acmpne L45
    goto L46
L47
    iconst_m1
    ldc -175609259 (java.lang.Integer)
    aload 10
    getfield ag p:I
    imul
    if_icmpne L48
    iload 9
    ldc 1922003277 (java.lang.Integer)
    if_icmpeq L49
    return
L49
    aconst_null
    aload 10
    getfield ag ak:[I
    if_acmpne L48
    iload 9
    ldc 1922003277 (java.lang.Integer)
    if_icmpeq L50
    new java/lang/IllegalStateException
    dup
    invokespecial java/lang/IllegalStateException <init>:()V
    athrow
L50
    aload 10
    bipush 22
    iload 5
    aload 17
    iload 19
    iload 18
    iload 20
    bipush -35
    invokevirtual ag r:(II[[IIIIB)Lcy;
    astore 23
    goto L51
L48
    new h
    dup
    iload 4
    bipush 22
    iload 5
    iload 1
    iload 2
    iload 3
    ldc -175609259 (java.lang.Integer)
    aload 10
    getfield ag p:I
    imul
    iconst_1
    aconst_null
    invokespecial h <init>:(IIIIIIIZLch;)V
    astore 23
    goto L51
L52
    ldc 1527764841 (java.lang.Integer)
    aload 10
    getfield ag z:I
    imul
    istore 12
    goto L13
L53
    iconst_1
    aload 10
    getfield ag q:I
    ldc -1945821617 (java.lang.Integer)
    imul
    if_icmpne L54
    iload 9
    ldc 1922003277 (java.lang.Integer)
    if_icmpeq L55
    new java/lang/IllegalStateException
    dup
    invokespecial java/lang/IllegalStateException <init>:()V
    athrow
L55
    aload 8
    iload 2
    iload 3
    ldc -534775903 (java.lang.Integer)
    invokevirtual hk u:(III)V
L54
    return
L56
    iload 6
    bipush 10
    if_icmpeq L41
    iload 9
    ldc 1922003277 (java.lang.Integer)
    if_icmpeq L57
    new java/lang/IllegalStateException
    dup
    invokespecial java/lang/IllegalStateException <init>:()V
    athrow
L58
    return
L59
    iload 6
    bipush 12
    if_icmplt L60
    iload 9
    ldc 1922003277 (java.lang.Integer)
    if_icmpeq L61
    new java/lang/IllegalStateException
    dup
    invokespecial java/lang/IllegalStateException <init>:()V
    athrow
L62
    iconst_0
    ldc -1945821617 (java.lang.Integer)
    aload 10
    getfield ag q:I
    imul
    if_icmpeq L14
    iload 9
    ldc 1922003277 (java.lang.Integer)
    if_icmpeq L63
    new java/lang/IllegalStateException
    dup
    invokespecial java/lang/IllegalStateException <init>:()V
    athrow
L64
    aload 10
    bipush 10
    iload 5
    aload 17
    iload 19
    iload 18
    iload 20
    iconst_m1
    invokevirtual ag r:(II[[IIIIB)Lcy;
    astore 23
    goto L65
L66
    iconst_m1
    ldc -175609259 (java.lang.Integer)
    aload 10
    getfield ag p:I
    imul
    if_icmpne L67
    iload 9
    ldc 1922003277 (java.lang.Integer)
    if_icmpeq L68
    return
L65
    aload 23
    ifnull L69
    iload 9
    ldc 1922003277 (java.lang.Integer)
    if_icmpeq L70
    new java/lang/IllegalStateException
    dup
    invokespecial java/lang/IllegalStateException <init>:()V
    athrow
L30
    iconst_m1
    aload 10
    getfield ag p:I
    ldc -175609259 (java.lang.Integer)
    imul
    if_icmpne L71
    iload 9
    ldc 1922003277 (java.lang.Integer)
    if_icmpeq L72
    return
L2
    iload 5
    iconst_1
    if_icmpeq L23
    iload 9
    ldc 1922003277 (java.lang.Integer)
    if_icmpeq L22
    new java/lang/IllegalStateException
    dup
    invokespecial java/lang/IllegalStateException <init>:()V
    athrow
L73
    aload 10
    iload 6
    iload 5
    aload 17
    iload 19
    iload 18
    iload 20
    bipush -102
    invokevirtual ag r:(II[[IIIIB)Lcy;
    astore 23
    goto L74
L10
    iload 21
    iload 22
    invokevirtual cb o:(IIIIIILch;III)Z
    pop
L69
    ldc -1945821617 (java.lang.Integer)
    aload 10
    getfield ag q:I
    imul
    ifeq L34
    iload 9
    ldc 1922003277 (java.lang.Integer)
    if_icmpeq L33
    return
L71
    new h
    dup
    iload 4
    iconst_4
    iconst_4
    iload 24
    iadd
    iload 1
    iload 2
    iload 3
    aload 10
    getfield ag p:I
    ldc -175609259 (java.lang.Integer)
    imul
    iconst_1
    aconst_null
    invokespecial h <init>:(IIIIIIIZLch;)V
    astore 23
    goto L75
L76
    aload 7
    iload 0
    iload 2
    iload 3
    iload 18
    aload 25
    aconst_null
    sipush 256
    iload 5
    getstatic w n:[I
    iload 5
    iaload
    iload 23
    imul
    getstatic w v:[I
    iload 5
    iaload
    iload 23
    imul
    iload 21
    iload 22
    invokevirtual cb g:(IIIILch;Lch;IIIIII)V
    goto L77
L78
    aload 8
    iload 2
    iload 3
    iload 6
    iload 5
    aload 10
    getfield ag d:Z
    ldc -1583620258 (java.lang.Integer)
    invokevirtual hk a:(IIIIZI)V
    goto L79
L61
    iconst_m1
    ldc -175609259 (java.lang.Integer)
    aload 10
    getfield ag p:I
    imul
    if_icmpne L80
    aconst_null
    aload 10
    getfield ag ak:[I
    if_acmpne L80
    iload 9
    ldc 1922003277 (java.lang.Integer)
    if_icmpeq L73
    return
L81
    new h
    dup
    iload 4
    iload 6
    iload 5
    iload 1
    iload 2
    iload 3
    aload 10
    getfield ag p:I
    ldc -175609259 (java.lang.Integer)
    imul
    iconst_1
    aconst_null
    invokespecial h <init>:(IIIIIIIZLch;)V
    astore 23
    goto L82
L80
    new h
    dup
    iload 4
    iload 6
    iload 5
    iload 1
    iload 2
    iload 3
    ldc -175609259 (java.lang.Integer)
    aload 10
    getfield ag p:I
    imul
    iconst_1
    aconst_null
    invokespecial h <init>:(IIIIIIIZLch;)V
    astore 23
L74
    aload 7
    iload 0
    iload 2
    iload 3
    iload 18
    iconst_1
    iconst_1
    aload 23
    iconst_0
    iload 21
    iload 22
    invokevirtual cb o:(IIIIIILch;III)Z
    pop
L83
    aload 10
    getfield ag q:I
    ldc -1945821617 (java.lang.Integer)
    imul
    ifeq L84
    iload 9
    ldc 1922003277 (java.lang.Integer)
    if_icmpeq L85
    return
L86
    sipush 256
    goto L10
L84
    return
L60
    iload 6
    ifne L87
    iload 9
    ldc 1922003277 (java.lang.Integer)
    if_icmpeq L88
    new java/lang/IllegalStateException
    dup
    invokespecial java/lang/IllegalStateException <init>:()V
    athrow
L88
    aload 10
    getfield ag p:I
    ldc -175609259 (java.lang.Integer)
    imul
    iconst_m1
    if_icmpne L3
    iload 9
    ldc 1922003277 (java.lang.Integer)
    if_icmpeq L89
    new java/lang/IllegalStateException
    dup
    invokespecial java/lang/IllegalStateException <init>:()V
    athrow
L89
    aload 10
    getfield ag ak:[I
    ifnonnull L3
    aload 10
    iconst_0
    iload 5
    aload 17
    iload 19
    iload 18
    iload 20
    bipush -14
    invokevirtual ag r:(II[[IIIIB)Lcy;
    astore 23
    goto L4
L90
    iload 6
    bipush 7
    if_icmpne L91
    iload 9
    ldc 1922003277 (java.lang.Integer)
    if_icmpeq L29
    return
L4
    aload 7
    iload 0
    iload 2
    iload 3
    iload 18
    aload 23
    aconst_null
    getstatic w q:[I
    iload 5
    iaload
    iconst_0
    iload 21
    iload 22
    invokevirtual cb f:(IIIILch;Lch;IIII)V
    goto L92
L43
    aconst_null
    aload 10
    getfield ag ak:[I
    if_acmpne L42
    iload 9
    ldc 1922003277 (java.lang.Integer)
    if_icmpeq L64
    new java/lang/IllegalStateException
    dup
    invokespecial java/lang/IllegalStateException <init>:()V
    athrow
L93
    aload 10
    getfield ag ak:[I
    ifnonnull L94
    iload 9
    ldc 1922003277 (java.lang.Integer)
    if_icmpeq L35
    new java/lang/IllegalStateException
    dup
    invokespecial java/lang/IllegalStateException <init>:()V
    athrow
L79
    return
L87
    iload 6
    iconst_1
    if_icmpne L95
    iload 9
    ldc 1922003277 (java.lang.Integer)
    if_icmpeq L96
    return
L96
    aload 10
    getfield ag p:I
    ldc -175609259 (java.lang.Integer)
    imul
    iconst_m1
    if_icmpne L94
    iload 9
    ldc 1922003277 (java.lang.Integer)
    if_icmpeq L93
    new java/lang/IllegalStateException
    dup
    invokespecial java/lang/IllegalStateException <init>:()V
    athrow
L91
    iload 6
    bipush 8
    if_icmpne L97
    iload 9
    ldc 1922003277 (java.lang.Integer)
    if_icmpeq L98
    return
L99
    iconst_5
    iload 6
    if_icmpne L100
    iload 9
    ldc 1922003277 (java.lang.Integer)
    if_icmpeq L101
    new java/lang/IllegalStateException
    dup
    invokespecial java/lang/IllegalStateException <init>:()V
    athrow
L94
    new h
    dup
    iload 4
    iconst_1
    iload 5
    iload 1
    iload 2
    iload 3
    ldc -175609259 (java.lang.Integer)
    aload 10
    getfield ag p:I
    imul
    iconst_1
    aconst_null
    invokespecial h <init>:(IIIIIIIZLch;)V
    astore 23
    goto L36
L70
    aload 7
    iload 0
    iload 2
    iload 3
    iload 18
    iload 11
    iload 12
    aload 23
    bipush 11
    iload 6
    if_icmpne L9
    iload 9
    ldc 1922003277 (java.lang.Integer)
    if_icmpeq L86
    new java/lang/IllegalStateException
    dup
    invokespecial java/lang/IllegalStateException <init>:()V
    athrow
L102
    ldc -1945821617 (java.lang.Integer)
    aload 10
    getfield ag q:I
    imul
    ifeq L103
    aload 8
    iload 2
    iload 3
    iload 6
    iload 5
    aload 10
    getfield ag d:Z
    ldc -1687873710 (java.lang.Integer)
    invokevirtual hk a:(IIIIZI)V
    goto L103
L36
    aload 7
    iload 0
    iload 2
    iload 3
    iload 18
    aload 23
    aconst_null
    getstatic w d:[I
    iload 5
    iaload
    iconst_0
    iload 21
    iload 22
    invokevirtual cb f:(IIIILch;Lch;IIII)V
    goto L102
L95
    iconst_2
    iload 6
    if_icmpne L104
    iload 9
    ldc 1922003277 (java.lang.Integer)
    if_icmpeq L105
    new java/lang/IllegalStateException
    dup
    invokespecial java/lang/IllegalStateException <init>:()V
    athrow
L105
    iconst_1
    iload 5
    iadd
    iconst_3
    iand
    istore 23
    goto L106
L92
    iconst_0
    ldc -1945821617 (java.lang.Integer)
    aload 10
    getfield ag q:I
    imul
    if_icmpeq L79
    goto L78
L21
    iload 3
    iload 12
    iconst_1
    ishr
    iadd
    istore 15
    goto L24
L103
    return
L107
    aload 10
    iconst_2
    iload 23
    aload 17
    iload 19
    iload 18
    iload 20
    bipush -80
    invokevirtual ag r:(II[[IIIIB)Lcy;
    astore 25
    goto L108
L109
    new h
    dup
    iload 4
    iconst_2
    iconst_4
    iload 5
    iadd
    iload 1
    iload 2
    iload 3
    ldc -175609259 (java.lang.Integer)
    aload 10
    getfield ag p:I
    imul
    iconst_1
    aconst_null
    invokespecial h <init>:(IIIIIIIZLch;)V
    astore 24
L110
    new h
    dup
    iload 4
    iconst_2
    iload 23
    iload 1
    iload 2
    iload 3
    ldc -175609259 (java.lang.Integer)
    aload 10
    getfield ag p:I
    imul
    iconst_1
    aconst_null
    invokespecial h <init>:(IIIIIIIZLch;)V
    astore 25
L108
    aload 7
    iload 0
    iload 2
    iload 3
    iload 18
    aload 24
    aload 25
    getstatic w q:[I
    iload 5
    iaload
    getstatic w q:[I
    iload 23
    iaload
    iload 21
    iload 22
    invokevirtual cb f:(IIIILch;Lch;IIII)V
L111
    iconst_0
    aload 10
    getfield ag q:I
    ldc -1945821617 (java.lang.Integer)
    imul
    if_icmpeq L58
    iload 9
    ldc 1922003277 (java.lang.Integer)
    if_icmpeq L112
    new java/lang/IllegalStateException
    dup
    invokespecial java/lang/IllegalStateException <init>:()V
    athrow
L112
    aload 8
    iload 2
    iload 3
    iload 6
    iload 5
    aload 10
    getfield ag d:Z
    ldc -462332273 (java.lang.Integer)
    invokevirtual hk a:(IIIIZI)V
    goto L58
L57
    iload 6
    bipush 11
    if_icmpne L59
    iload 9
    ldc 1922003277 (java.lang.Integer)
    if_icmpeq L41
    new java/lang/IllegalStateException
    dup
    invokespecial java/lang/IllegalStateException <init>:()V
    athrow
L104
    iconst_3
    iload 6
    if_icmpne L113
    iload 9
    ldc 1922003277 (java.lang.Integer)
    if_icmpeq L114
    new java/lang/IllegalStateException
    dup
    invokespecial java/lang/IllegalStateException <init>:()V
    athrow
L114
    ldc -175609259 (java.lang.Integer)
    aload 10
    getfield ag p:I
    imul
    iconst_m1
    if_icmpne L115
    iload 9
    ldc 1922003277 (java.lang.Integer)
    if_icmpeq L116
    new java/lang/IllegalStateException
    dup
    invokespecial java/lang/IllegalStateException <init>:()V
    athrow
L75
    aload 7
    iload 0
    iload 2
    iload 3
    iload 18
    aload 23
    aconst_null
    sipush 256
    iload 24
    iconst_0
    iconst_0
    iload 21
    iload 22
    invokevirtual cb g:(IIIILch;Lch;IIIIII)V
    goto L117
L51
    aload 7
    iload 0
    iload 2
    iload 3
    iload 18
    aload 23
    iload 21
    iload 22
    invokevirtual cb i:(IIIILch;II)V
    goto L53
L115
    new h
    dup
    iload 4
    iconst_3
    iload 5
    iload 1
    iload 2
    iload 3
    ldc -175609259 (java.lang.Integer)
    aload 10
    getfield ag p:I
    imul
    iconst_1
    aconst_null
    invokespecial h <init>:(IIIIIIIZLch;)V
    astore 23
    goto L118
L42
    new h
    dup
    iload 4
    bipush 10
    iload 5
    iload 1
    iload 2
    iload 3
    aload 10
    getfield ag p:I
    ldc -175609259 (java.lang.Integer)
    imul
    iconst_1
    aconst_null
    invokespecial h <init>:(IIIIIIIZLch;)V
    astore 23
    goto L65
L119
    iconst_0
    ldc -1945821617 (java.lang.Integer)
    aload 10
    getfield ag q:I
    imul
    if_icmpeq L6
    goto L5
L120
    return
L6
    return
L67
    new h
    dup
    iload 4
    iconst_4
    iconst_4
    iload 5
    iadd
    iload 1
    iload 2
    iload 3
    aload 10
    getfield ag p:I
    ldc -175609259 (java.lang.Integer)
    imul
    iconst_1
    aconst_null
    invokespecial h <init>:(IIIIIIIZLch;)V
    astore 25
    goto L76
L121
    aload 10
    iconst_2
    iconst_4
    iload 5
    iadd
    aload 17
    iload 19
    iload 18
    iload 20
    bipush -21
    invokevirtual ag r:(II[[IIIIB)Lcy;
    astore 24
    goto L107
L122
    aconst_null
    aload 10
    getfield ag ak:[I
    if_acmpne L81
    iload 9
    ldc 1922003277 (java.lang.Integer)
    if_icmpeq L123
    new java/lang/IllegalStateException
    dup
    invokespecial java/lang/IllegalStateException <init>:()V
    athrow
L25
    getstatic w e:[[[I
    iload 1
    aaload
    astore 17
    goto L124
L125
    aload 10
    getfield ag ak:[I
    ifnonnull L126
    iload 9
    ldc 1922003277 (java.lang.Integer)
    if_icmpeq L127
    new java/lang/IllegalStateException
    dup
    invokespecial java/lang/IllegalStateException <init>:()V
    athrow
L128
    ldc -175609259 (java.lang.Integer)
    aload 10
    getfield ag p:I
    imul
    iconst_m1
    if_icmpne L81
    iload 9
    ldc 1922003277 (java.lang.Integer)
    if_icmpeq L122
    new java/lang/IllegalStateException
    dup
    invokespecial java/lang/IllegalStateException <init>:()V
    athrow
L46
    aload 10
    iconst_4
    iconst_4
    iload 5
    iadd
    aload 17
    iload 19
    iload 18
    iload 20
    bipush -18
    invokevirtual ag r:(II[[IIIIB)Lcy;
    astore 25
    goto L129
L63
    aload 8
    iload 2
    iload 3
    iload 11
    iload 12
    aload 10
    getfield ag d:Z
    bipush -74
    invokevirtual hk l:(IIIIZB)V
    goto L14
L113
    iload 6
    bipush 9
    if_icmpne L130
    iload 9
    ldc 1922003277 (java.lang.Integer)
    if_icmpeq L128
    new java/lang/IllegalStateException
    dup
    invokespecial java/lang/IllegalStateException <init>:()V
    athrow
L130
    iconst_4
    iload 6
    if_icmpne L99
    iload 9
    ldc 1922003277 (java.lang.Integer)
    if_icmpeq L131
    return
L131
    iconst_m1
    aload 10
    getfield ag p:I
    ldc -175609259 (java.lang.Integer)
    imul
    if_icmpne L132
    iload 9
    ldc 1922003277 (java.lang.Integer)
    if_icmpeq L133
    new java/lang/IllegalStateException
    dup
    invokespecial java/lang/IllegalStateException <init>:()V
    athrow
L133
    aload 10
    getfield ag ak:[I
    ifnonnull L132
    iload 9
    ldc 1922003277 (java.lang.Integer)
    if_icmpeq L134
    return
L134
    aload 10
    iconst_4
    iload 5
    aload 17
    iload 19
    iload 18
    iload 20
    bipush -52
    invokevirtual ag r:(II[[IIIIB)Lcy;
    astore 23
    goto L27
L132
    new h
    dup
    iload 4
    iconst_4
    iload 5
    iload 1
    iload 2
    iload 3
    ldc -175609259 (java.lang.Integer)
    aload 10
    getfield ag p:I
    imul
    iconst_1
    aconst_null
    invokespecial h <init>:(IIIIIIIZLch;)V
    astore 23
    goto L27
L23
    ldc -1050702509 (java.lang.Integer)
    aload 10
    getfield ag y:I
    imul
    istore 11
    goto L52
L28
    return
L123
    aload 10
    iload 6
    iload 5
    aload 17
    iload 19
    iload 18
    iload 20
    bipush -88
    invokevirtual ag r:(II[[IIIIB)Lcy;
    astore 23
    goto L82
L101
    bipush 16
    istore 23
L135
    aload 7
    iload 0
    iload 2
    iload 3
    invokevirtual cb ax:(III)I
    istore 24
L136
    iload 24
    ifeq L137
    iload 9
    ldc 1922003277 (java.lang.Integer)
    if_icmpeq L138
    return
L32
    iload 12
    bipush 6
    ishl
    iload 3
    bipush 7
    ishl
    iadd
    istore 20
    goto L139
L137
    iconst_m1
    ldc -175609259 (java.lang.Integer)
    aload 10
    getfield ag p:I
    imul
    if_icmpne L126
    iload 9
    ldc 1922003277 (java.lang.Integer)
    if_icmpeq L125
    new java/lang/IllegalStateException
    dup
    invokespecial java/lang/IllegalStateException <init>:()V
    athrow
L140
    return
L127
    aload 10
    iconst_4
    iload 5
    aload 17
    iload 19
    iload 18
    iload 20
    bipush -115
    invokevirtual ag r:(II[[IIIIB)Lcy;
    astore 25
    goto L141
L126
    new h
    dup
    iload 4
    iconst_4
    iload 5
    iload 1
    iload 2
    iload 3
    aload 10
    getfield ag p:I
    ldc -175609259 (java.lang.Integer)
    imul
    iconst_1
    aconst_null
    invokespecial h <init>:(IIIIIIIZLch;)V
    astore 25
L141
    aload 7
    iload 0
    iload 2
    iload 3
    iload 18
    aload 25
    aconst_null
    getstatic w q:[I
    iload 5
    iaload
    iconst_0
    getstatic w b:[I
    iload 5
    iaload
    iload 23
    imul
    getstatic w x:[I
    iload 5
    iaload
    iload 23
    imul
    iload 21
    iload 22
    invokevirtual cb g:(IIIILch;Lch;IIIIII)V
    goto L120
L68
    aload 10
    getfield ag ak:[I
    ifnonnull L67
    goto L142
L100
    iload 6
    bipush 6
    if_icmpne L90
    goto L143
L144
    iload 5
    iconst_2
    iadd
    iconst_3
    iand
    istore 27
    goto L145
L146
    aload 7
    iload 0
    iload 2
    iload 3
    invokevirtual cb ax:(III)I
    istore 24
L147
    iconst_0
    iload 24
    if_icmpeq L66
    iload 9
    ldc 1922003277 (java.lang.Integer)
    if_icmpeq L148
    new java/lang/IllegalStateException
    dup
    invokespecial java/lang/IllegalStateException <init>:()V
    athrow
L148
    iload 24
    bipush 14
    ishr
    sipush 32767
    iand
    bipush -53
    invokestatic m e:(IB)Lag;
    getfield ag k:I
    ldc 1127355445 (java.lang.Integer)
    imul
    iconst_2
    idiv
    istore 23
    goto L66
L82
    aload 7
    iload 0
    iload 2
    iload 3
    iload 18
    iconst_1
    iconst_1
    aload 23
    iconst_0
    iload 21
    iload 22
    invokevirtual cb o:(IIIIIILch;III)Z
    pop
    goto L62
L116
    aload 10
    getfield ag ak:[I
    ifnonnull L115
    goto L149
L142
    aload 10
    iconst_4
    iconst_4
    iload 5
    iadd
    aload 17
    iload 19
    iload 18
    iload 20
    bipush -109
    invokevirtual ag r:(II[[IIIIB)Lcy;
    astore 25
    goto L76
L139
    ldc 1073741824 (java.lang.Integer)
    iload 4
    bipush 14
    ishl
    iload 2
    iload 3
    bipush 7
    ishl
    iadd
    iadd
    iadd
    istore 21
    goto L37
L106
    aload 10
    getfield ag p:I
    ldc -175609259 (java.lang.Integer)
    imul
    iconst_m1
    if_icmpne L109
    iload 9
    ldc 1922003277 (java.lang.Integer)
    if_icmpeq L150
    new java/lang/IllegalStateException
    dup
    invokespecial java/lang/IllegalStateException <init>:()V
    athrow
L77
    return
L8
    bipush 22
    iload 6
    if_icmpne L56
    iload 9
    ldc 1922003277 (java.lang.Integer)
    if_icmpeq L47
    new java/lang/IllegalStateException
    dup
    invokespecial java/lang/IllegalStateException <init>:()V
    athrow
L143
    bipush 8
    istore 23
    goto L146
L138
    iload 24
    bipush 14
    ishr
    sipush 32767
    iand
    bipush 54
    invokestatic m e:(IB)Lag;
    getfield ag k:I
    ldc 1127355445 (java.lang.Integer)
    imul
    istore 23
    goto L137
L72
    aconst_null
    aload 10
    getfield ag ak:[I
    if_acmpne L71
    iload 9
    ldc 1922003277 (java.lang.Integer)
    if_icmpeq L151
    return
L151
    aload 10
    iconst_4
    iload 24
    iconst_4
    iadd
    aload 17
    iload 19
    iload 18
    iload 20
    bipush -101
    invokevirtual ag r:(II[[IIIIB)Lcy;
    astore 23
    goto L75
L124
    aload 17
    iload 13
    aaload
    iload 15
    iaload
    aload 17
    iload 14
    aaload
    iload 15
    iaload
    iadd
    aload 17
    iload 13
    aaload
    iload 16
    iaload
    iadd
    aload 17
    iload 14
    aaload
    iload 16
    iaload
    iadd
    iconst_2
    ishr
    istore 18
    goto L31
L149
    aload 10
    iconst_3
    iload 5
    aload 17
    iload 19
    iload 18
    iload 20
    bipush -39
    invokevirtual ag r:(II[[IIIIB)Lcy;
    astore 23
    goto L118
L117
    return
L34
    return
L98
    bipush 8
    istore 23
L152
    aload 7
    iload 0
    iload 2
    iload 3
    invokevirtual cb ax:(III)I
    istore 24
L153
    iconst_0
    iload 24
    if_icmpeq L144
    iload 24
    bipush 14
    ishr
    sipush 32767
    iand
    bipush 40
    invokestatic m e:(IB)Lag;
    getfield ag k:I
    ldc 1127355445 (java.lang.Integer)
    imul
    iconst_2
    idiv
    istore 23
    goto L144
L85
    aload 8
    iload 2
    iload 3
    iload 11
    iload 12
    aload 10
    getfield ag d:Z
    bipush -31
    invokevirtual hk l:(IIIIZB)V
    goto L84
L145
    aload 10
    getfield ag p:I
    ldc -175609259 (java.lang.Integer)
    imul
    iconst_m1
    if_icmpne L45
    iload 9
    ldc 1922003277 (java.lang.Integer)
    if_icmpeq L44
    new java/lang/IllegalStateException
    dup
    invokespecial java/lang/IllegalStateException <init>:()V
    athrow
L13
    iload 11
    iload 2
    iadd
    bipush 104
    if_icmpgt L18
    goto L15
L150
    aconst_null
    aload 10
    getfield ag ak:[I
    if_acmpne L109
    iload 9
    ldc 1922003277 (java.lang.Integer)
    if_icmpeq L121
    return
L129
    aload 10
    iconst_4
    iconst_4
    iload 27
    iadd
    aload 17
    iload 19
    iload 18
    iload 20
    bipush -4
    invokevirtual ag r:(II[[IIIIB)Lcy;
    astore 26
    goto L154
L45
    new h
    dup
    iload 4
    iconst_4
    iload 5
    iconst_4
    iadd
    iload 1
    iload 2
    iload 3
    aload 10
    getfield ag p:I
    ldc -175609259 (java.lang.Integer)
    imul
    iconst_1
    aconst_null
    invokespecial h <init>:(IIIIIIIZLch;)V
    astore 25
L155
    new h
    dup
    iload 4
    iconst_4
    iload 27
    iconst_4
    iadd
    iload 1
    iload 2
    iload 3
    aload 10
    getfield ag p:I
    ldc -175609259 (java.lang.Integer)
    imul
    iconst_1
    aconst_null
    invokespecial h <init>:(IIIIIIIZLch;)V
    astore 26
L154
    aload 7
    iload 0
    iload 2
    iload 3
    iload 18
    aload 25
    aload 26
    sipush 256
    iload 5
    getstatic w n:[I
    iload 5
    iaload
    iload 23
    imul
    iload 23
    getstatic w v:[I
    iload 5
    iaload
    imul
    iload 21
    iload 22
    invokevirtual cb g:(IIIILch;Lch;IIIIII)V
    goto L140
L118
    aload 7
    iload 0
    iload 2
    iload 3
    iload 18
    aload 23
    aconst_null
    getstatic w d:[I
    iload 5
    iaload
    iconst_0
    iload 21
    iload 22
    invokevirtual cb f:(IIIILch;Lch;IIII)V
    goto L119
L97
    return
L156
    new java/lang/StringBuilder
    dup
    invokespecial java/lang/StringBuilder <init>:()V
    ldc "b.z(" (java.lang.String)
    invokevirtual java/lang/StringBuilder append:(Ljava/lang/String;)Ljava/lang/StringBuilder;
    ldc 41 (java.lang.Integer)
    invokevirtual java/lang/StringBuilder append:(C)Ljava/lang/StringBuilder;
    invokevirtual java/lang/StringBuilder toString:()Ljava/lang/String;
    invokestatic k a:(Ljava/lang/Throwable;Ljava/lang/String;)Lee;
    athrow
