bi du (Ljava/lang/String;I)VL1
    aconst_null
    aload 0
    if_acmpne L2
    iload 1
    ldc 696397772 (java.lang.Integer)
    if_icmpeq L3
    new java/lang/IllegalStateException
    dup
    invokespecial java/lang/IllegalStateException <init>:()V
    athrow
L4
    getstatic client or:[Lz;
    iload 7
    getstatic client or:[Lz;
    iconst_1
    iload 7
    iadd
    aaload
    aastore
    goto L5
L6
    goto L7
L8
    aconst_null
    aload 2
    if_acmpne L9
    goto L10
L11
    ldc 114005179 (java.lang.Integer)
    getstatic client ki:I
    imul
    putstatic client kt:I
    goto L12
L13
    aload 5
    getstatic dj g:Lge;
    ldc -2048272163 (java.lang.Integer)
    invokestatic dp l:(Ljava/lang/CharSequence;Lge;I)Ljava/lang/String;
    astore 6
    goto L14
L5
    iinc 7 1
    goto L15
L16
    getstatic client or:[Lz;
    iload 3
    aaload
    astore 4
L17
    aload 4
    getfield z e:Ljava/lang/String;
    astore 5
    goto L13
L2
    aload 0
    getstatic dj g:Lge;
    ldc -1232599193 (java.lang.Integer)
    invokestatic dp l:(Ljava/lang/CharSequence;Lge;I)Ljava/lang/String;
    astore 2
    goto L8
L14
    aload 0
    aload 2
    aload 5
    aload 6
    ldc 1213234965 (java.lang.Integer)
    invokestatic v e:(Ljava/lang/String;Ljava/lang/String;Ljava/lang/String;Ljava/lang/String;I)Z
    ifeq L18
    iload 1
    ldc 696397772 (java.lang.Integer)
    if_icmpeq L19
    new java/lang/IllegalStateException
    dup
    invokespecial java/lang/IllegalStateException <init>:()V
    athrow
L19
    getstatic client oi:I
    ldc -1435071049 (java.lang.Integer)
    isub
    putstatic client oi:I
    goto L20
L21
    iload 3
    getstatic client oi:I
    ldc -78716921 (java.lang.Integer)
    imul
    if_icmpge L7
    iload 1
    ldc 696397772 (java.lang.Integer)
    if_icmpeq L16
    new java/lang/IllegalStateException
    dup
    invokespecial java/lang/IllegalStateException <init>:()V
    athrow
L22
    getstatic client cd:Ldj;
    aload 0
    sipush 502
    invokevirtual dj i:(Ljava/lang/String;S)V
    goto L6
L20
    iload 3
    istore 7
    goto L15
L10
    return
L9
    iconst_0
    istore 3
    goto L21
L12
    getstatic client cd:Ldj;
    bipush 108
    ldc 545187082 (java.lang.Integer)
    invokevirtual dj hl:(II)V
L23
    getstatic client cd:Ldj;
    astore 7
L24
    aload 0
    invokevirtual java/lang/String length:()I
    iconst_1
    iadd
    istore 8
L25
    aload 7
    iload 8
    bipush 85
    invokevirtual dj e:(IB)V
    goto L22
L15
    iload 7
    ldc -78716921 (java.lang.Integer)
    getstatic client oi:I
    imul
    if_icmpge L11
    goto L4
L3
    return
L18
    iinc 3 1
    goto L21
L7
    return
L26
    new java/lang/StringBuilder
    dup
    invokespecial java/lang/StringBuilder <init>:()V
    ldc "bi.du(" (java.lang.String)
    invokevirtual java/lang/StringBuilder append:(Ljava/lang/String;)Ljava/lang/StringBuilder;
    ldc 41 (java.lang.Integer)
    invokevirtual java/lang/StringBuilder append:(C)Ljava/lang/StringBuilder;
    invokevirtual java/lang/StringBuilder toString:()Ljava/lang/String;
    invokestatic k a:(Ljava/lang/Throwable;Ljava/lang/String;)Lee;
    athrow
