bj bi (IIIILjava/lang/String;Ljava/lang/String;III)VL1
    iload 2
    sipush 2000
    if_icmplt L2
    iload 8
    ldc 1590767131 (java.lang.Integer)
    if_icmpne L3
    return
L4
    ldc -100126598 (java.lang.Integer)
    putstatic client gd:I
    goto L5
L2
    iload 2
    bipush 18
    if_icmpne L6
    iload 8
    ldc 1590767131 (java.lang.Integer)
    if_icmpne L7
    new java/lang/IllegalStateException
    dup
    invokespecial java/lang/IllegalStateException <init>:()V
    athrow
L7
    iload 6
    ldc 1135862533 (java.lang.Integer)
    imul
    putstatic client gs:I
L8
    iload 7
    ldc 677850631 (java.lang.Integer)
    imul
    putstatic client gk:I
    goto L9
L10
    getstatic client cd:Ldj;
    iload 3
    bipush 42
    invokevirtual dj an:(IB)V
    goto L11
L12
    iconst_0
    putstatic client gj:I
L13
    iload 0
    ldc -467606121 (java.lang.Integer)
    imul
    putstatic client mm:I
L14
    iload 1
    ldc 1754300735 (java.lang.Integer)
    imul
    putstatic client mz:I
    goto L15
L16
    iconst_0
    putstatic client gz:I
    goto L17
L18
    getstatic client cd:Ldj;
    iload 0
    getstatic x cs:I
    ldc 616886125 (java.lang.Integer)
    imul
    iadd
    ldc 2095113423 (java.lang.Integer)
    invokevirtual dj af:(II)V
    goto L19
L20
    getstatic client hg:[Ll;
    iload 3
    aaload
    astore 9
    goto L21
L22
    getstatic client cd:Ldj;
    getstatic dr ce:[Z
    bipush 82
    baload
    ifeq L23
    iload 8
    ldc 1590767131 (java.lang.Integer)
    if_icmpne L24
    new java/lang/IllegalStateException
    dup
    invokespecial java/lang/IllegalStateException <init>:()V
    athrow
L25
    bipush 30
    iload 2
    if_icmpne L26
    iload 8
    ldc 1590767131 (java.lang.Integer)
    if_icmpne L27
    new java/lang/IllegalStateException
    dup
    invokespecial java/lang/IllegalStateException <init>:()V
    athrow
L28
    ldc -100126598 (java.lang.Integer)
    putstatic client gd:I
    goto L29
L30
    iload 0
    ldc -467606121 (java.lang.Integer)
    imul
    putstatic client mm:I
    goto L31
L32
    getstatic client cd:Ldj;
    getstatic co cz:I
    ldc 1317226893 (java.lang.Integer)
    imul
    iload 1
    iadd
    bipush 78
    invokevirtual dj an:(IB)V
L6
    iload 2
    iconst_1
    if_icmpne L33
L34
    iload 6
    ldc 1135862533 (java.lang.Integer)
    imul
    putstatic client gs:I
L35
    iload 7
    ldc 677850631 (java.lang.Integer)
    imul
    putstatic client gk:I
L36
    ldc -100126598 (java.lang.Integer)
    putstatic client gd:I
    goto L37
L38
    iload 3
    bipush 10
    if_icmpne L39
    iload 8
    ldc 1590767131 (java.lang.Integer)
    if_icmpne L40
    new java/lang/IllegalStateException
    dup
    invokespecial java/lang/IllegalStateException <init>:()V
    athrow
L41
    iload 0
    ldc -467606121 (java.lang.Integer)
    imul
    putstatic client mm:I
    goto L42
L43
    ldc 1754300735 (java.lang.Integer)
    iload 1
    imul
    putstatic client mz:I
    goto L44
L45
    iconst_5
    iload 3
    if_icmpne L46
    iload 8
    ldc 1590767131 (java.lang.Integer)
    if_icmpne L47
    new java/lang/IllegalStateException
    dup
    invokespecial java/lang/IllegalStateException <init>:()V
    athrow
L48
    getstatic client cd:Ldj;
    iload 0
    getstatic x cs:I
    ldc 616886125 (java.lang.Integer)
    imul
    iadd
    iconst_1
    invokevirtual dj az:(IB)V
L49
    getstatic client cd:Ldj;
    getstatic fp iq:I
    ldc -7450759 (java.lang.Integer)
    imul
    iconst_1
    invokevirtual dj az:(IB)V
L50
    getstatic client cd:Ldj;
    ldc 1565981493 (java.lang.Integer)
    getstatic aj ix:I
    imul
    ldc 1691578294 (java.lang.Integer)
    invokevirtual dj bv:(II)V
L51
    getstatic client cd:Ldj;
    getstatic dh iz:I
    ldc 1827663583 (java.lang.Integer)
    imul
    iconst_1
    invokevirtual dj az:(IB)V
    goto L52
L53
    getstatic client cd:Ldj;
    sipush 224
    ldc -764765417 (java.lang.Integer)
    invokevirtual dj hl:(II)V
    goto L54
L55
    getstatic client cd:Ldj;
    iload 1
    ldc -2019009785 (java.lang.Integer)
    invokevirtual dj c:(II)V
    goto L56
L57
    iconst_0
L58
    bipush 24
    invokevirtual dj e:(IB)V
L59
    getstatic client cd:Ldj;
    iload 1
    ldc 1317226893 (java.lang.Integer)
    getstatic co cz:I
    imul
    iadd
    iconst_1
    invokevirtual dj az:(IB)V
L60
    getstatic client cd:Ldj;
    iload 3
    bipush 14
    ishr
    sipush 32767
    iand
    bipush -18
    invokevirtual dj a:(IB)V
L33
    iload 2
    iconst_5
    if_icmpne L61
    iload 8
    ldc 1590767131 (java.lang.Integer)
    if_icmpne L62
    new java/lang/IllegalStateException
    dup
    invokespecial java/lang/IllegalStateException <init>:()V
    athrow
L63
    getstatic client cd:Ldj;
    ldc 1317226893 (java.lang.Integer)
    getstatic co cz:I
    imul
    iload 1
    iadd
    bipush 9
    invokevirtual dj an:(IB)V
    goto L64
L65
    iload 7
    ldc 677850631 (java.lang.Integer)
    imul
    putstatic client gk:I
    goto L66
L67
    getstatic client cd:Ldj;
    iload 1
    ldc -144334628 (java.lang.Integer)
    invokevirtual dj c:(II)V
    goto L68
L69
    new java/lang/StringBuilder
    dup
    invokespecial java/lang/StringBuilder <init>:()V
    aload 9
    getfield fb bz:Ljava/lang/String;
    invokevirtual java/lang/StringBuilder append:(Ljava/lang/String;)Ljava/lang/StringBuilder;
    ldc 16777215 (java.lang.Integer)
    bipush -46
    invokestatic p e:(IB)Ljava/lang/String;
    invokevirtual java/lang/StringBuilder append:(Ljava/lang/String;)Ljava/lang/StringBuilder;
    invokevirtual java/lang/StringBuilder toString:()Ljava/lang/String;
    putstatic client jk:Ljava/lang/String;
    goto L70
L71
    ldc -467606121 (java.lang.Integer)
    iload 0
    imul
    putstatic client mm:I
L72
    ldc 1754300735 (java.lang.Integer)
    iload 1
    imul
    putstatic client mz:I
    goto L73
L74
    getstatic client cd:Ldj;
    getstatic dr ce:[Z
    bipush 82
    baload
    ifeq L75
    iload 8
    ldc 1590767131 (java.lang.Integer)
    if_icmpne L76
    new java/lang/IllegalStateException
    dup
    invokespecial java/lang/IllegalStateException <init>:()V
    athrow
L77
    getstatic client cd:Ldj;
    iconst_1
    ldc 604036492 (java.lang.Integer)
    invokevirtual dj hl:(II)V
    goto L78
L79
    getstatic client cd:Ldj;
    ldc 616886125 (java.lang.Integer)
    getstatic x cs:I
    imul
    iload 0
    iadd
    bipush 88
    invokevirtual dj an:(IB)V
L80
    getstatic client cd:Ldj;
    iload 3
    bipush 14
    ishr
    sipush 32767
    iand
    bipush 12
    invokevirtual dj a:(IB)V
    goto L81
L82
    iconst_0
    putstatic client gj:I
    goto L83
L84
    iconst_1
    goto L85
L86
    ldc 2030483715 (java.lang.Integer)
    invokevirtual dj al:(II)V
    goto L32
L85
    bipush 6
    invokevirtual dj e:(IB)V
    goto L61
L87
    getstatic client cd:Ldj;
    sipush 210
    ldc -1978660422 (java.lang.Integer)
    invokevirtual dj hl:(II)V
    goto L88
L89
    getstatic client cd:Ldj;
    getstatic dr ce:[Z
    bipush 82
    baload
    ifeq L90
    iload 8
    ldc 1590767131 (java.lang.Integer)
    if_icmpne L91
    return
L92
    iload 2
    sipush 1005
    if_icmpne L93
    iload 8
    ldc 1590767131 (java.lang.Integer)
    if_icmpne L94
    return
L95
    iload 6
    ldc 1135862533 (java.lang.Integer)
    imul
    putstatic client gs:I
L96
    ldc 677850631 (java.lang.Integer)
    iload 7
    imul
    putstatic client gk:I
    goto L97
L98
    iload 1
    ldc -2068421293 (java.lang.Integer)
    invokestatic f a:(II)Lfb;
    putstatic dp gl:Lfb;
    goto L99
L100
    iload 1
    ldc 1754300735 (java.lang.Integer)
    imul
    putstatic client mz:I
    goto L101
L102
    ldc -467606121 (java.lang.Integer)
    iload 0
    imul
    putstatic client mm:I
L103
    ldc 1754300735 (java.lang.Integer)
    iload 1
    imul
    putstatic client mz:I
L104
    getstatic client cd:Ldj;
    bipush 93
    ldc -2058580637 (java.lang.Integer)
    invokevirtual dj hl:(II)V
    goto L105
L106
    return
L107
    iconst_1
    goto L108
L109
    iconst_1
    istore 10
    goto L110
L111
    iconst_0
    invokevirtual dj ah:(IB)V
    goto L112
L113
    aload 11
    ldc 1913801968 (java.lang.Integer)
    invokestatic an dd:(Lfb;I)Z
    istore 12
    goto L114
L115
    iload 2
    bipush 31
    if_icmpne L116
    iload 8
    ldc 1590767131 (java.lang.Integer)
    if_icmpne L117
    return
L117
    getstatic client cd:Ldj;
    sipush 175
    ldc -106860366 (java.lang.Integer)
    invokevirtual dj hl:(II)V
    goto L118
L119
    getstatic client cd:Ldj;
    iload 3
    iconst_1
    invokevirtual dj az:(IB)V
    goto L120
L121
    getstatic client cd:Ldj;
    ldc 1827663583 (java.lang.Integer)
    getstatic dh iz:I
    imul
    ldc 2093000480 (java.lang.Integer)
    invokevirtual dj af:(II)V
L122
    getstatic client cd:Ldj;
    iload 3
    ldc 2114378132 (java.lang.Integer)
    invokevirtual dj af:(II)V
L123
    getstatic client cd:Ldj;
    iload 1
    ldc 1205038516 (java.lang.Integer)
    invokevirtual dj bp:(II)V
L124
    getstatic client cd:Ldj;
    getstatic aj ix:I
    ldc 1565981493 (java.lang.Integer)
    imul
    ldc 1691578294 (java.lang.Integer)
    invokevirtual dj bv:(II)V
L125
    getstatic client cd:Ldj;
    ldc -7450759 (java.lang.Integer)
    getstatic fp iq:I
    imul
    ldc 2008310531 (java.lang.Integer)
    invokevirtual dj af:(II)V
    goto L126
L127
    getstatic client cd:Ldj;
    ldc -7450759 (java.lang.Integer)
    getstatic fp iq:I
    imul
    bipush -70
    invokevirtual dj a:(IB)V
    goto L128
L129
    getstatic client jf:Ljava/lang/String;
    ifnonnull L130
    iload 8
    ldc 1590767131 (java.lang.Integer)
    if_icmpne L131
    new java/lang/IllegalStateException
    dup
    invokespecial java/lang/IllegalStateException <init>:()V
    athrow
L132
    iload 0
    ldc -1001862243 (java.lang.Integer)
    imul
    putstatic client gw:I
    goto L116
L133
    iload 2
    bipush 38
    if_icmpne L134
    goto L135
L136
    getstatic client cd:Ldj;
    iload 3
    bipush 14
    ishr
    sipush 32767
    iand
    ldc 2145085721 (java.lang.Integer)
    invokevirtual dj af:(II)V
    goto L137
L138
    iload 7
    ldc 677850631 (java.lang.Integer)
    imul
    putstatic client gk:I
L139
    ldc -100126598 (java.lang.Integer)
    putstatic client gd:I
    goto L140
L141
    getstatic client cd:Ldj;
    bipush 68
    ldc -854045997 (java.lang.Integer)
    invokevirtual dj hl:(II)V
    goto L142
L143
    getstatic client cd:Ldj;
    sipush 129
    ldc -52970767 (java.lang.Integer)
    invokevirtual dj hl:(II)V
    goto L144
L31
    ldc 1754300735 (java.lang.Integer)
    iload 1
    imul
    putstatic client mz:I
    goto L145
L146
    iload 7
    ldc 677850631 (java.lang.Integer)
    imul
    putstatic client gk:I
    goto L147
L148
    getstatic client cd:Ldj;
    getstatic dr ce:[Z
    bipush 82
    baload
    ifeq L149
    iload 8
    ldc 1590767131 (java.lang.Integer)
    if_icmpne L150
    return
L151
    iload 0
    ldc -1001862243 (java.lang.Integer)
    imul
    putstatic client gw:I
    goto L152
L153
    getstatic client cd:Ldj;
    getstatic dr ce:[Z
    bipush 82
    baload
    ifeq L154
    iload 8
    ldc 1590767131 (java.lang.Integer)
    if_icmpne L155
    new java/lang/IllegalStateException
    dup
    invokespecial java/lang/IllegalStateException <init>:()V
    athrow
L155
    iconst_1
    goto L156
L154
    iconst_0
L156
    iconst_0
    invokevirtual dj ah:(IB)V
L157
    getstatic client cd:Ldj;
    getstatic x cs:I
    ldc 616886125 (java.lang.Integer)
    imul
    iload 0
    iadd
    bipush 48
    invokevirtual dj a:(IB)V
    goto L158
L159
    bipush 14
    iload 2
    if_icmpne L160
    iload 8
    ldc 1590767131 (java.lang.Integer)
    if_icmpne L161
    new java/lang/IllegalStateException
    dup
    invokespecial java/lang/IllegalStateException <init>:()V
    athrow
L162
    iload 6
    ldc 1135862533 (java.lang.Integer)
    imul
    putstatic client gs:I
    goto L163
L164
    getstatic client cd:Ldj;
    iload 1
    ldc 571431819 (java.lang.Integer)
    invokevirtual dj c:(II)V
    goto L16
L165
    ldc -100126598 (java.lang.Integer)
    putstatic client gd:I
L166
    iconst_0
    putstatic client gj:I
L167
    ldc -467606121 (java.lang.Integer)
    iload 0
    imul
    putstatic client mm:I
L168
    ldc 1754300735 (java.lang.Integer)
    iload 1
    imul
    putstatic client mz:I
L169
    getstatic client cd:Ldj;
    sipush 227
    ldc 496853528 (java.lang.Integer)
    invokevirtual dj hl:(II)V
    goto L170
L171
    getstatic client cd:Ldj;
    sipush 164
    ldc -566810158 (java.lang.Integer)
    invokevirtual dj hl:(II)V
    goto L55
L172
    getstatic client cd:Ldj;
    iload 0
    ldc 616886125 (java.lang.Integer)
    getstatic x cs:I
    imul
    iadd
    iconst_1
    invokevirtual dj az:(IB)V
    goto L89
L173
    getstatic client cd:Ldj;
    sipush 140
    ldc 394648052 (java.lang.Integer)
    invokevirtual dj hl:(II)V
    goto L148
L174
    iload 2
    bipush 20
    if_icmpne L11
    iload 8
    ldc 1590767131 (java.lang.Integer)
    if_icmpne L175
    new java/lang/IllegalStateException
    dup
    invokespecial java/lang/IllegalStateException <init>:()V
    athrow
L176
    getstatic client cd:Ldj;
    iload 3
    bipush 14
    ishr
    sipush 32767
    iand
    iconst_1
    invokevirtual dj az:(IB)V
    goto L177
L178
    ldc -1312627742 (java.lang.Integer)
    invokevirtual dj at:(II)V
L179
    getstatic client cd:Ldj;
    iload 3
    ldc 2136497014 (java.lang.Integer)
    invokevirtual dj af:(II)V
    goto L180
L181
    aload 9
    getfield am e:Lay;
    astore 10
    goto L182
L24
    iconst_1
    goto L86
L183
    aload 9
    ifnull L184
    iload 8
    ldc 1590767131 (java.lang.Integer)
    if_icmpne L185
    new java/lang/IllegalStateException
    dup
    invokespecial java/lang/IllegalStateException <init>:()V
    athrow
L185
    iload 6
    ldc 1135862533 (java.lang.Integer)
    imul
    putstatic client gs:I
L186
    ldc 677850631 (java.lang.Integer)
    iload 7
    imul
    putstatic client gk:I
L187
    ldc -100126598 (java.lang.Integer)
    putstatic client gd:I
L188
    iconst_0
    putstatic client gj:I
L189
    ldc -467606121 (java.lang.Integer)
    iload 0
    imul
    putstatic client mm:I
L190
    ldc 1754300735 (java.lang.Integer)
    iload 1
    imul
    putstatic client mz:I
L191
    getstatic client cd:Ldj;
    sipush 165
    ldc -1196950803 (java.lang.Integer)
    invokevirtual dj hl:(II)V
L192
    getstatic client cd:Ldj;
    getstatic dr ce:[Z
    bipush 82
    baload
    ifeq L193
    iload 8
    ldc 1590767131 (java.lang.Integer)
    if_icmpne L194
    new java/lang/IllegalStateException
    dup
    invokespecial java/lang/IllegalStateException <init>:()V
    athrow
L194
    iconst_1
    goto L195
L193
    iconst_0
L195
    ldc -690607133 (java.lang.Integer)
    invokevirtual dj at:(II)V
    goto L196
L197
    getstatic client cd:Ldj;
    iload 0
    bipush -110
    invokevirtual dj a:(IB)V
    goto L198
L184
    iload 2
    bipush 37
    if_icmpne L199
    iload 8
    ldc 1590767131 (java.lang.Integer)
    if_icmpne L200
    new java/lang/IllegalStateException
    dup
    invokespecial java/lang/IllegalStateException <init>:()V
    athrow
L200
    getstatic client cd:Ldj;
    bipush 45
    ldc -1023259475 (java.lang.Integer)
    invokevirtual dj hl:(II)V
L201
    getstatic client cd:Ldj;
    iload 3
    iconst_1
    invokevirtual dj az:(IB)V
L202
    getstatic client cd:Ldj;
    iload 1
    ldc 1447406671 (java.lang.Integer)
    invokevirtual dj c:(II)V
L203
    getstatic client cd:Ldj;
    iload 0
    iconst_1
    invokevirtual dj az:(IB)V
L204
    iconst_0
    putstatic client gz:I
    goto L205
L206
    ldc 1565981493 (java.lang.Integer)
    getstatic aj ix:I
    imul
    ldc -2068421293 (java.lang.Integer)
    invokestatic f a:(II)Lfb;
    ldc -1023277750 (java.lang.Integer)
    invokestatic dh cr:(Lfb;I)V
    goto L207
L208
    iconst_0
    invokevirtual dj ah:(IB)V
    goto L209
L210
    ldc -100126598 (java.lang.Integer)
    putstatic client gd:I
    goto L211
L212
    getstatic client cd:Ldj;
    ldc -1424280981 (java.lang.Integer)
    getstatic client ja:I
    imul
    iconst_1
    invokevirtual dj az:(IB)V
    goto L213
L214
    getstatic client cd:Ldj;
    iload 1
    ldc -1850490310 (java.lang.Integer)
    invokevirtual dj be:(II)V
    goto L215
L216
    iconst_0
    putstatic client gz:I
    goto L217
L218
    aconst_null
    aload 9
    if_acmpeq L219
    iload 8
    ldc 1590767131 (java.lang.Integer)
    if_icmpne L181
    return
L220
    iconst_0
    putstatic client gz:I
L221
    iload 1
    ldc -2068421293 (java.lang.Integer)
    invokestatic f a:(II)Lfb;
    putstatic dp gl:Lfb;
L222
    ldc -1001862243 (java.lang.Integer)
    iload 0
    imul
    putstatic client gw:I
L223
    bipush 48
    iload 2
    if_icmpne L224
    iload 8
    ldc 1590767131 (java.lang.Integer)
    if_icmpne L225
    new java/lang/IllegalStateException
    dup
    invokespecial java/lang/IllegalStateException <init>:()V
    athrow
L226
    iconst_1
    goto L58
L227
    aload 9
    ifnull L224
    iload 8
    ldc 1590767131 (java.lang.Integer)
    if_icmpne L228
    return
L228
    iload 6
    ldc 1135862533 (java.lang.Integer)
    imul
    putstatic client gs:I
L229
    iload 7
    ldc 677850631 (java.lang.Integer)
    imul
    putstatic client gk:I
L230
    ldc -100126598 (java.lang.Integer)
    putstatic client gd:I
L231
    iconst_0
    putstatic client gj:I
    goto L232
L233
    getstatic client cd:Ldj;
    iload 1
    ldc 959123735 (java.lang.Integer)
    invokevirtual dj c:(II)V
    goto L234
L235
    ldc 1754300735 (java.lang.Integer)
    iload 1
    imul
    putstatic client mz:I
    goto L236
L237
    bipush 6
    iload 2
    if_icmpne L238
    iload 8
    ldc 1590767131 (java.lang.Integer)
    if_icmpne L239
    return
L240
    getstatic client cd:Ldj;
    iload 3
    bipush 35
    invokevirtual dj an:(IB)V
L241
    getstatic client cd:Ldj;
    getstatic dr ce:[Z
    bipush 82
    baload
    ifeq L242
    iconst_1
    goto L243
L244
    iload 10
    bipush 60
    invokestatic db cc:(IB)V
    goto L245
L243
    iconst_1
    invokevirtual dj e:(IB)V
L224
    bipush 42
    iload 2
    if_icmpne L246
L247
    getstatic client cd:Ldj;
    sipush 194
    ldc -32131003 (java.lang.Integer)
    invokevirtual dj hl:(II)V
    goto L248
L249
    ldc 2116502173 (java.lang.Integer)
    invokevirtual dj al:(II)V
    goto L250
L251
    getstatic client cd:Ldj;
    iload 3
    iconst_1
    invokevirtual dj az:(IB)V
L252
    getstatic client cd:Ldj;
    iload 1
    ldc 1691578294 (java.lang.Integer)
    invokevirtual dj bv:(II)V
    goto L253
L254
    iload 1
    ldc 1754300735 (java.lang.Integer)
    imul
    putstatic client mz:I
    goto L255
L256
    iload 1
    ldc -2068421293 (java.lang.Integer)
    invokestatic f a:(II)Lfb;
    putstatic dp gl:Lfb;
L257
    iload 0
    ldc -1001862243 (java.lang.Integer)
    imul
    putstatic client gw:I
L246
    bipush 7
    iload 2
    if_icmpne L258
    iload 8
    ldc 1590767131 (java.lang.Integer)
    if_icmpne L259
    new java/lang/IllegalStateException
    dup
    invokespecial java/lang/IllegalStateException <init>:()V
    athrow
L259
    getstatic client cf:[Lam;
    iload 3
    aaload
    astore 9
L260
    aload 9
    ifnull L258
    iload 8
    ldc 1590767131 (java.lang.Integer)
    if_icmpne L261
    new java/lang/IllegalStateException
    dup
    invokespecial java/lang/IllegalStateException <init>:()V
    athrow
L261
    ldc 1135862533 (java.lang.Integer)
    iload 6
    imul
    putstatic client gs:I
    goto L262
L180
    iload 2
    bipush 9
    if_icmpne L184
    iload 8
    ldc 1590767131 (java.lang.Integer)
    if_icmpne L263
    return
L264
    iconst_0
    goto L265
L266
    iconst_0
    putstatic client gj:I
L267
    iload 0
    ldc -467606121 (java.lang.Integer)
    imul
    putstatic client mm:I
    goto L268
L269
    iconst_0
    putstatic client gj:I
    goto L270
L271
    getstatic client cd:Ldj;
    sipush 214
    ldc 160793309 (java.lang.Integer)
    invokevirtual dj hl:(II)V
L272
    getstatic client cd:Ldj;
    ldc 1827663583 (java.lang.Integer)
    getstatic dh iz:I
    imul
    bipush 27
    invokevirtual dj a:(IB)V
    goto L74
L232
    ldc -467606121 (java.lang.Integer)
    iload 0
    imul
    putstatic client mm:I
    goto L235
L273
    ldc 1878875957 (java.lang.Integer)
    invokevirtual dj at:(II)V
    goto L274
L44
    getstatic client cd:Ldj;
    sipush 169
    ldc -1897269450 (java.lang.Integer)
    invokevirtual dj hl:(II)V
    goto L48
L275
    bipush 54
    invokevirtual dj e:(IB)V
    goto L276
L15
    getstatic client cd:Ldj;
    bipush 118
    ldc -1919178649 (java.lang.Integer)
    invokevirtual dj hl:(II)V
    goto L119
L277
    getstatic client cd:Ldj;
    iload 1
    ldc 1125304548 (java.lang.Integer)
    invokevirtual dj bp:(II)V
    goto L278
L128
    getstatic client cd:Ldj;
    getstatic aj ix:I
    ldc 1565981493 (java.lang.Integer)
    imul
    ldc 1691578294 (java.lang.Integer)
    invokevirtual dj bv:(II)V
L258
    sipush 1001
    iload 2
    if_icmpne L279
    iload 8
    ldc 1590767131 (java.lang.Integer)
    if_icmpne L280
    new java/lang/IllegalStateException
    dup
    invokespecial java/lang/IllegalStateException <init>:()V
    athrow
L280
    ldc 1135862533 (java.lang.Integer)
    iload 6
    imul
    putstatic client gs:I
L281
    iload 7
    ldc 677850631 (java.lang.Integer)
    imul
    putstatic client gk:I
L282
    ldc -100126598 (java.lang.Integer)
    putstatic client gd:I
L283
    iconst_0
    putstatic client gj:I
L284
    ldc -467606121 (java.lang.Integer)
    iload 0
    imul
    putstatic client mm:I
L285
    ldc 1754300735 (java.lang.Integer)
    iload 1
    imul
    putstatic client mz:I
    goto L286
L287
    aload 11
    getfield fb t:I
    ldc 937329469 (java.lang.Integer)
    imul
    ifle L114
    iload 8
    ldc 1590767131 (java.lang.Integer)
    if_icmpne L113
    new java/lang/IllegalStateException
    dup
    invokespecial java/lang/IllegalStateException <init>:()V
    athrow
L288
    getstatic client cd:Ldj;
    getstatic dr ce:[Z
    bipush 82
    baload
    ifeq L289
    iload 8
    ldc 1590767131 (java.lang.Integer)
    if_icmpne L290
    return
L131
    ldc "Null" (java.lang.String)
    putstatic client jf:Ljava/lang/String;
    goto L130
L291
    aload 12
    aload 11
    getfield fb cy:[Ljava/lang/Object;
    putfield e e:[Ljava/lang/Object;
    goto L292
L293
    ldc 1955223375 (java.lang.Integer)
    invokevirtual dj al:(II)V
L294
    getstatic client cd:Ldj;
    iload 3
    bipush 14
    ishr
    sipush 32767
    iand
    ldc 2142013849 (java.lang.Integer)
    invokevirtual dj af:(II)V
L295
    getstatic client cd:Ldj;
    iload 0
    ldc 616886125 (java.lang.Integer)
    getstatic x cs:I
    imul
    iadd
    iconst_1
    invokevirtual dj az:(IB)V
L296
    getstatic client cd:Ldj;
    getstatic co cz:I
    ldc 1317226893 (java.lang.Integer)
    imul
    iload 1
    iadd
    bipush 57
    invokevirtual dj an:(IB)V
L279
    iload 2
    bipush 58
    if_icmpne L297
    iload 8
    ldc 1590767131 (java.lang.Integer)
    if_icmpne L298
    new java/lang/IllegalStateException
    dup
    invokespecial java/lang/IllegalStateException <init>:()V
    athrow
L298
    iload 1
    iload 0
    ldc -2012490612 (java.lang.Integer)
    invokestatic ed l:(III)Lfb;
    astore 9
L299
    aconst_null
    aload 9
    if_acmpeq L297
    iload 8
    ldc 1590767131 (java.lang.Integer)
    if_icmpne L300
    new java/lang/IllegalStateException
    dup
    invokespecial java/lang/IllegalStateException <init>:()V
    athrow
L300
    getstatic client cd:Ldj;
    bipush 104
    ldc -8893794 (java.lang.Integer)
    invokevirtual dj hl:(II)V
    goto L301
L302
    getstatic client cd:Ldj;
    ldc -1424280981 (java.lang.Integer)
    getstatic client ja:I
    imul
    ldc 2029012295 (java.lang.Integer)
    invokevirtual dj af:(II)V
    goto L303
L304
    bipush -12
    invokevirtual dj e:(IB)V
    goto L305
L306
    aload 9
    getfield fb ds:[I
    iload 0
    iaload
    ldc 100000 (java.lang.Integer)
    if_icmplt L53
    iload 8
    ldc 1590767131 (java.lang.Integer)
    if_icmpne L307
    new java/lang/IllegalStateException
    dup
    invokespecial java/lang/IllegalStateException <init>:()V
    athrow
L308
    getstatic client cd:Ldj;
    ldc 689007975 (java.lang.Integer)
    aload 9
    getfield fb db:I
    imul
    bipush -63
    invokevirtual dj a:(IB)V
L309
    getstatic client cd:Ldj;
    ldc 1824985751 (java.lang.Integer)
    getstatic f jg:I
    imul
    ldc -1850490310 (java.lang.Integer)
    invokevirtual dj be:(II)V
    goto L310
L286
    getstatic client cd:Ldj;
    bipush 32
    ldc -2040658875 (java.lang.Integer)
    invokevirtual dj hl:(II)V
    goto L288
L311
    iload 1
    ldc -2068421293 (java.lang.Integer)
    invokestatic f a:(II)Lfb;
    putstatic dp gl:Lfb;
    goto L312
L313
    iload 6
    ldc 1135862533 (java.lang.Integer)
    imul
    putstatic client gs:I
L314
    ldc 677850631 (java.lang.Integer)
    iload 7
    imul
    putstatic client gk:I
L315
    ldc -100126598 (java.lang.Integer)
    putstatic client gd:I
L316
    iconst_0
    putstatic client gj:I
L317
    getstatic client cd:Ldj;
    sipush 224
    ldc -754599592 (java.lang.Integer)
    invokevirtual dj hl:(II)V
    goto L318
L319
    ldc 1135862533 (java.lang.Integer)
    iload 6
    imul
    putstatic client gs:I
    goto L320
L205
    iload 1
    ldc -2068421293 (java.lang.Integer)
    invokestatic f a:(II)Lfb;
    putstatic dp gl:Lfb;
    goto L321
L27
    getstatic client jz:Lfb;
    ifnonnull L26
    iload 8
    ldc 1590767131 (java.lang.Integer)
    if_icmpne L322
    return
L322
    iload 1
    iload 0
    bipush 7
    invokestatic i bt:(IIB)V
L323
    iload 1
    iload 0
    ldc -176720108 (java.lang.Integer)
    invokestatic ed l:(III)Lfb;
    putstatic client jz:Lfb;
    goto L324
L325
    aload 11
    getfield fb cy:[Ljava/lang/Object;
    ifnull L326
    iload 8
    ldc 1590767131 (java.lang.Integer)
    if_icmpne L327
    return
L26
    iload 2
    iconst_2
    if_icmpne L328
    iload 8
    ldc 1590767131 (java.lang.Integer)
    if_icmpne L329
    new java/lang/IllegalStateException
    dup
    invokespecial java/lang/IllegalStateException <init>:()V
    athrow
L329
    ldc 1135862533 (java.lang.Integer)
    iload 6
    imul
    putstatic client gs:I
    goto L330
L331
    getstatic client cd:Ldj;
    iload 10
    bipush 63
    invokevirtual dj a:(IB)V
    goto L332
L333
    ldc -100126598 (java.lang.Integer)
    putstatic client gd:I
    goto L334
L39
    bipush 40
    iload 2
    if_icmpne L174
    goto L335
L336
    iload 0
    ldc -467606121 (java.lang.Integer)
    imul
    putstatic client mm:I
L337
    ldc 1754300735 (java.lang.Integer)
    iload 1
    imul
    putstatic client mz:I
    goto L338
L339
    getstatic client in:I
    ldc 1293091945 (java.lang.Integer)
    imul
    ifeq L207
    iload 8
    ldc 1590767131 (java.lang.Integer)
    if_icmpne L340
    new java/lang/IllegalStateException
    dup
    invokespecial java/lang/IllegalStateException <init>:()V
    athrow
L341
    ldc 1754300735 (java.lang.Integer)
    iload 1
    imul
    putstatic client mz:I
    goto L342
L303
    getstatic client cd:Ldj;
    ldc 1824985751 (java.lang.Integer)
    getstatic f jg:I
    imul
    ldc -1407159816 (java.lang.Integer)
    invokevirtual dj c:(II)V
L343
    getstatic client cd:Ldj;
    getstatic x cs:I
    ldc 616886125 (java.lang.Integer)
    imul
    iload 0
    iadd
    ldc 2113063710 (java.lang.Integer)
    invokevirtual dj af:(II)V
L344
    getstatic client cd:Ldj;
    getstatic co cz:I
    ldc 1317226893 (java.lang.Integer)
    imul
    iload 1
    iadd
    ldc 1998427071 (java.lang.Integer)
    invokevirtual dj af:(II)V
    goto L345
L61
    iload 2
    bipush 11
    if_icmpne L115
    goto L346
L347
    getstatic client cd:Ldj;
    getstatic dr ce:[Z
    bipush 82
    baload
    ifeq L348
    iload 8
    ldc 1590767131 (java.lang.Integer)
    if_icmpne L349
    return
L349
    iconst_1
    goto L350
L348
    iconst_0
    goto L350
L351
    getstatic client cd:Ldj;
    bipush 31
    ldc -483659262 (java.lang.Integer)
    invokevirtual dj hl:(II)V
    goto L352
L353
    iload 0
    istore 11
    goto L354
L355
    getstatic client hg:[Ll;
    iload 3
    aaload
    astore 9
    goto L356
L357
    iconst_0
    putstatic client gj:I
    goto L71
L358
    ldc 1135862533 (java.lang.Integer)
    iload 6
    imul
    putstatic client gs:I
L359
    iload 7
    ldc 677850631 (java.lang.Integer)
    imul
    putstatic client gk:I
    goto L4
L360
    iconst_0
    goto L85
L5
    iconst_0
    putstatic client gj:I
    goto L361
L250
    getstatic client cd:Ldj;
    iload 3
    iconst_1
    invokevirtual dj az:(IB)V
    goto L362
L363
    iload 1
    ldc 1754300735 (java.lang.Integer)
    imul
    putstatic client mz:I
    goto L364
L365
    getstatic client cd:Ldj;
    bipush 29
    ldc 581372605 (java.lang.Integer)
    invokevirtual dj hl:(II)V
L366
    getstatic client cd:Ldj;
    getstatic dr ce:[Z
    bipush 82
    baload
    ifeq L367
    iload 8
    ldc 1590767131 (java.lang.Integer)
    if_icmpne L368
    new java/lang/IllegalStateException
    dup
    invokespecial java/lang/IllegalStateException <init>:()V
    athrow
L369
    iconst_0
    putstatic client gz:I
    goto L370
L367
    iconst_0
    goto L371
L182
    aconst_null
    aload 10
    getfield ay aw:[I
    if_acmpeq L372
    iload 8
    ldc 1590767131 (java.lang.Integer)
    if_icmpne L373
    new java/lang/IllegalStateException
    dup
    invokespecial java/lang/IllegalStateException <init>:()V
    athrow
L374
    getstatic client cd:Ldj;
    iload 3
    bipush 41
    invokevirtual dj an:(IB)V
    goto L133
L375
    iload 13
    bipush 11
    ishr
    bipush 63
    iand
    istore 12
    goto L376
L135
    sipush 1003
    invokestatic ai bh:(S)V
L377
    iload 1
    ldc -2068421293 (java.lang.Integer)
    invokestatic f a:(II)Lfb;
    astore 9
    goto L378
L379
    getstatic client cd:Ldj;
    iload 3
    iconst_1
    invokevirtual dj az:(IB)V
    goto L380
L381
    iconst_0
    putstatic client gj:I
    goto L382
L383
    ldc 1727381277 (java.lang.Integer)
    iload 1
    imul
    putstatic aj ix:I
L384
    ldc 1678200095 (java.lang.Integer)
    iload 3
    imul
    putstatic dh iz:I
    goto L385
L386
    ldc 1754300735 (java.lang.Integer)
    iload 1
    imul
    putstatic client mz:I
    goto L387
L66
    ldc -100126598 (java.lang.Integer)
    putstatic client gd:I
    goto L357
L215
    getstatic client cd:Ldj;
    iload 0
    bipush 24
    invokevirtual dj an:(IB)V
    goto L388
L52
    getstatic client cd:Ldj;
    getstatic dr ce:[Z
    bipush 82
    baload
    ifeq L57
    iload 8
    ldc 1590767131 (java.lang.Integer)
    if_icmpne L226
    new java/lang/IllegalStateException
    dup
    invokespecial java/lang/IllegalStateException <init>:()V
    athrow
L389
    return
L134
    iload 2
    bipush 57
    if_icmpeq L390
    iload 8
    ldc 1590767131 (java.lang.Integer)
    if_icmpne L391
    new java/lang/IllegalStateException
    dup
    invokespecial java/lang/IllegalStateException <init>:()V
    athrow
L391
    sipush 1007
    iload 2
    if_icmpne L39
    iload 8
    ldc 1590767131 (java.lang.Integer)
    if_icmpne L390
    new java/lang/IllegalStateException
    dup
    invokespecial java/lang/IllegalStateException <init>:()V
    athrow
L91
    iconst_1
    goto L178
L392
    aload 9
    ifnull L39
    goto L393
L394
    iload 6
    ldc 1135862533 (java.lang.Integer)
    imul
    putstatic client gs:I
    goto L395
L396
    iload 1
    iload 0
    ldc -694166095 (java.lang.Integer)
    invokestatic ed l:(III)Lfb;
    astore 11
    goto L397
L398
    getstatic client cd:Ldj;
    iload 1
    ldc 1208364198 (java.lang.Integer)
    invokevirtual dj c:(II)V
    goto L399
L400
    ldc 1135862533 (java.lang.Integer)
    iload 6
    imul
    putstatic client gs:I
    goto L146
L401
    ldc -100126598 (java.lang.Integer)
    putstatic client gd:I
    goto L266
L327
    new e
    dup
    invokespecial e <init>:()V
    astore 12
L402
    aload 12
    aload 11
    putfield e l:Lfb;
L403
    aload 12
    ldc 1548699391 (java.lang.Integer)
    iload 3
    imul
    putfield e w:I
L404
    aload 12
    aload 5
    putfield e g:Ljava/lang/String;
    goto L291
L405
    getstatic fl l:[I
    iload 10
    iaload
    aload 9
    getfield fb dm:[I
    iconst_0
    iaload
    if_icmpeq L245
    iload 8
    ldc 1590767131 (java.lang.Integer)
    if_icmpne L406
    new java/lang/IllegalStateException
    dup
    invokespecial java/lang/IllegalStateException <init>:()V
    athrow
L292
    aload 12
    ldc -2119225707 (java.lang.Integer)
    invokestatic k e:(Le;I)V
L326
    iconst_1
    istore 12
    goto L287
L397
    aconst_null
    aload 11
    if_acmpne L325
    iload 8
    ldc 1590767131 (java.lang.Integer)
    if_icmpne L407
    return
L408
    iload 3
    iconst_2
    if_icmpne L409
    iload 8
    ldc 1590767131 (java.lang.Integer)
    if_icmpne L410
    new java/lang/IllegalStateException
    dup
    invokespecial java/lang/IllegalStateException <init>:()V
    athrow
L114
    iload 12
    ifne L411
    iload 8
    ldc 1590767131 (java.lang.Integer)
    if_icmpne L412
    new java/lang/IllegalStateException
    dup
    invokespecial java/lang/IllegalStateException <init>:()V
    athrow
L412
    goto L39
L413
    iload 0
    ldc -467606121 (java.lang.Integer)
    imul
    putstatic client mm:I
    goto L43
L414
    getstatic client cd:Ldj;
    iload 1
    getstatic co cz:I
    ldc 1317226893 (java.lang.Integer)
    imul
    iadd
    bipush 6
    invokevirtual dj a:(IB)V
    goto L79
L415
    getstatic client cd:Ldj;
    getstatic dr ce:[Z
    bipush 82
    baload
    ifeq L416
    iload 8
    ldc 1590767131 (java.lang.Integer)
    if_icmpne L417
    new java/lang/IllegalStateException
    dup
    invokespecial java/lang/IllegalStateException <init>:()V
    athrow
L338
    getstatic client cd:Ldj;
    bipush 21
    ldc -232180512 (java.lang.Integer)
    invokevirtual dj hl:(II)V
    goto L302
L418
    iconst_0
L419
    istore 13
    goto L420
L421
    getstatic client cd:Ldj;
    iload 3
    bipush 60
    invokevirtual dj an:(IB)V
    goto L422
L423
    iload 7
    ldc 677850631 (java.lang.Integer)
    imul
    putstatic client gk:I
    goto L424
L425
    iconst_1
    iload 3
    if_icmpne L408
    iload 8
    ldc 1590767131 (java.lang.Integer)
    if_icmpne L426
    new java/lang/IllegalStateException
    dup
    invokespecial java/lang/IllegalStateException <init>:()V
    athrow
L426
    getstatic client cd:Ldj;
    sipush 189
    ldc -1972233063 (java.lang.Integer)
    invokevirtual dj hl:(II)V
    goto L398
L427
    getstatic client hg:[Ll;
    iload 3
    aaload
    astore 9
    goto L428
L399
    getstatic client cd:Ldj;
    iload 0
    bipush 113
    invokevirtual dj a:(IB)V
    goto L429
L150
    iconst_1
    goto L430
L431
    iconst_1
    goto L419
L410
    getstatic client cd:Ldj;
    bipush 83
    ldc -433588209 (java.lang.Integer)
    invokevirtual dj hl:(II)V
    goto L67
L350
    ldc -32352856 (java.lang.Integer)
    invokevirtual dj at:(II)V
    goto L328
L432
    iload 0
    ldc -1001862243 (java.lang.Integer)
    imul
    putstatic client gw:I
    goto L433
L434
    getstatic client cd:Ldj;
    iload 10
    bipush -90
    invokevirtual dj a:(IB)V
    goto L409
L245
    iload 2
    bipush 33
    if_icmpne L435
    iload 8
    ldc 1590767131 (java.lang.Integer)
    if_icmpne L436
    new java/lang/IllegalStateException
    dup
    invokespecial java/lang/IllegalStateException <init>:()V
    athrow
L437
    getstatic client cd:Ldj;
    getstatic dr ce:[Z
    bipush 82
    baload
    ifeq L438
    iload 8
    ldc 1590767131 (java.lang.Integer)
    if_icmpne L439
    return
L440
    getstatic client cd:Ldj;
    iload 1
    ldc 212808420 (java.lang.Integer)
    invokevirtual dj c:(II)V
L441
    getstatic client cd:Ldj;
    iload 0
    bipush 7
    invokevirtual dj a:(IB)V
L442
    getstatic client cd:Ldj;
    iload 10
    bipush 17
    invokevirtual dj a:(IB)V
L443
    iconst_4
    iload 3
    if_icmpne L45
    iload 8
    ldc 1590767131 (java.lang.Integer)
    if_icmpne L444
    new java/lang/IllegalStateException
    dup
    invokespecial java/lang/IllegalStateException <init>:()V
    athrow
L444
    getstatic client cd:Ldj;
    bipush 87
    ldc 358260828 (java.lang.Integer)
    invokevirtual dj hl:(II)V
L445
    getstatic client cd:Ldj;
    iload 1
    ldc 1244246769 (java.lang.Integer)
    invokevirtual dj c:(II)V
    goto L446
L447
    getstatic client cd:Ldj;
    iload 3
    ldc 2093287753 (java.lang.Integer)
    invokevirtual dj af:(II)V
    goto L216
L448
    getstatic client cd:Ldj;
    iload 10
    bipush 57
    invokevirtual dj a:(IB)V
    goto L45
L449
    iconst_0
    iload 14
    iload 15
    iconst_1
    iadd
    ishr
    iconst_1
    iand
    if_icmpeq L418
    iload 8
    ldc 1590767131 (java.lang.Integer)
    if_icmpne L431
    new java/lang/IllegalStateException
    dup
    invokespecial java/lang/IllegalStateException <init>:()V
    athrow
L47
    getstatic client cd:Ldj;
    sipush 132
    ldc -4976410 (java.lang.Integer)
    invokevirtual dj hl:(II)V
    goto L450
L451
    ldc 1754300735 (java.lang.Integer)
    iload 1
    imul
    putstatic client mz:I
    goto L452
L453
    getstatic client cd:Ldj;
    iload 0
    bipush 71
    invokevirtual dj a:(IB)V
    goto L454
L455
    ldc -467606121 (java.lang.Integer)
    iload 0
    imul
    putstatic client mm:I
    goto L456
L457
    getstatic dp gl:Lfb;
    ldc -1023277750 (java.lang.Integer)
    invokestatic dh cr:(Lfb;I)V
    goto L106
L458
    ldc 1135862533 (java.lang.Integer)
    iload 6
    imul
    putstatic client gs:I
    goto L138
L459
    getstatic client cd:Ldj;
    iload 1
    ldc -403234254 (java.lang.Integer)
    invokevirtual dj c:(II)V
L460
    getstatic client cd:Ldj;
    iload 0
    bipush 86
    invokevirtual dj a:(IB)V
    goto L461
L462
    iload 6
    ldc 1135862533 (java.lang.Integer)
    imul
    putstatic client gs:I
    goto L463
L464
    iload 1
    ldc 1754300735 (java.lang.Integer)
    imul
    putstatic client mz:I
    goto L465
L466
    getstatic client cd:Ldj;
    sipush 180
    ldc 33681026 (java.lang.Integer)
    invokevirtual dj hl:(II)V
L467
    getstatic client cd:Ldj;
    iload 1
    ldc 1146091553 (java.lang.Integer)
    invokevirtual dj c:(II)V
L468
    getstatic client cd:Ldj;
    iload 0
    bipush -7
    invokevirtual dj a:(IB)V
L469
    getstatic client cd:Ldj;
    iload 10
    bipush -66
    invokevirtual dj a:(IB)V
L470
    iload 3
    bipush 8
    if_icmpne L332
    iload 8
    ldc 1590767131 (java.lang.Integer)
    if_icmpne L471
    new java/lang/IllegalStateException
    dup
    invokespecial java/lang/IllegalStateException <init>:()V
    athrow
L471
    getstatic client cd:Ldj;
    bipush 106
    ldc -1589005139 (java.lang.Integer)
    invokevirtual dj hl:(II)V
    goto L472
L473
    getstatic client cd:Ldj;
    iload 3
    iconst_1
    invokevirtual dj az:(IB)V
    goto L474
L475
    getstatic client cd:Ldj;
    iload 0
    iconst_4
    invokevirtual dj a:(IB)V
    goto L331
L476
    getstatic client cd:Ldj;
    iload 0
    iconst_2
    invokevirtual dj a:(IB)V
    goto L477
L163
    iload 7
    ldc 677850631 (java.lang.Integer)
    imul
    putstatic client gk:I
    goto L165
L478
    getstatic client cd:Ldj;
    sipush 156
    ldc -1109323417 (java.lang.Integer)
    invokevirtual dj hl:(II)V
L479
    getstatic client cd:Ldj;
    iload 1
    ldc 1489585296 (java.lang.Integer)
    invokevirtual dj c:(II)V
    goto L476
L480
    ldc -100126598 (java.lang.Integer)
    putstatic client gd:I
    goto L481
L477
    getstatic client cd:Ldj;
    iload 10
    bipush 63
    invokevirtual dj a:(IB)V
    goto L38
L482
    getstatic client cd:Ldj;
    getstatic client ja:I
    ldc -1424280981 (java.lang.Integer)
    imul
    iconst_1
    invokevirtual dj az:(IB)V
    goto L483
L40
    getstatic client cd:Ldj;
    bipush 107
    ldc -425518253 (java.lang.Integer)
    invokevirtual dj hl:(II)V
    goto L233
L484
    iconst_0
    putstatic client gj:I
    goto L485
L234
    getstatic client cd:Ldj;
    iload 0
    bipush -64
    invokevirtual dj a:(IB)V
L486
    getstatic client cd:Ldj;
    iload 10
    bipush -68
    invokevirtual dj a:(IB)V
    goto L39
L81
    getstatic client cd:Ldj;
    getstatic dr ce:[Z
    bipush 82
    baload
    ifeq L360
    iload 8
    ldc 1590767131 (java.lang.Integer)
    if_icmpne L84
    new java/lang/IllegalStateException
    dup
    invokespecial java/lang/IllegalStateException <init>:()V
    athrow
L335
    getstatic client cd:Ldj;
    sipush 195
    ldc -1960028117 (java.lang.Integer)
    invokevirtual dj hl:(II)V
L487
    getstatic client cd:Ldj;
    iload 1
    ldc 1691578294 (java.lang.Integer)
    invokevirtual dj bv:(II)V
    goto L488
L489
    iconst_0
    putstatic client gz:I
    goto L490
L491
    getstatic client cd:Ldj;
    iload 0
    ldc 2027822729 (java.lang.Integer)
    invokevirtual dj af:(II)V
    goto L489
L378
    ldc 789760985 (java.lang.Integer)
    putstatic client in:I
    goto L492
L490
    iload 1
    ldc -2068421293 (java.lang.Integer)
    invokestatic f a:(II)Lfb;
    putstatic dp gl:Lfb;
    goto L493
L494
    aload 9
    ldc -210186597 (java.lang.Integer)
    invokestatic d dl:(Lfb;I)Ljava/lang/String;
    putstatic client jf:Ljava/lang/String;
    goto L129
L393
    ldc 689007975 (java.lang.Integer)
    aload 9
    getfield fb db:I
    imul
    istore 10
    goto L396
L175
    iload 6
    ldc 1135862533 (java.lang.Integer)
    imul
    putstatic client gs:I
L495
    iload 7
    ldc 677850631 (java.lang.Integer)
    imul
    putstatic client gk:I
L496
    ldc -100126598 (java.lang.Integer)
    putstatic client gd:I
L497
    iconst_0
    putstatic client gj:I
    goto L498
L454
    getstatic client cd:Ldj;
    iload 10
    bipush -49
    invokevirtual dj a:(IB)V
    goto L46
L334
    iconst_0
    putstatic client gj:I
    goto L336
L499
    getstatic client cd:Ldj;
    bipush 60
    ldc 329226032 (java.lang.Integer)
    invokevirtual dj hl:(II)V
    goto L500
L501
    getstatic client cd:Ldj;
    getstatic co cz:I
    ldc 1317226893 (java.lang.Integer)
    imul
    iload 1
    iadd
    bipush 40
    invokevirtual dj an:(IB)V
L502
    getstatic client cd:Ldj;
    iload 0
    ldc 616886125 (java.lang.Integer)
    getstatic x cs:I
    imul
    iadd
    bipush 86
    invokevirtual dj an:(IB)V
L503
    getstatic client cd:Ldj;
    getstatic dr ce:[Z
    bipush 82
    baload
    ifeq L504
    goto L505
L62
    ldc 1135862533 (java.lang.Integer)
    iload 6
    imul
    putstatic client gs:I
    goto L65
L504
    iconst_0
L506
    ldc 1895418786 (java.lang.Integer)
    invokevirtual dj al:(II)V
    goto L10
L507
    ldc 1754300735 (java.lang.Integer)
    iload 1
    imul
    putstatic client mz:I
    goto L365
L11
    bipush 34
    iload 2
    if_icmpne L433
L508
    getstatic client cd:Ldj;
    sipush 182
    ldc -502780892 (java.lang.Integer)
    invokevirtual dj hl:(II)V
    goto L379
L236
    getstatic client cd:Ldj;
    bipush 41
    ldc -1084495122 (java.lang.Integer)
    invokevirtual dj hl:(II)V
    goto L240
L380
    getstatic client cd:Ldj;
    iload 1
    ldc -1850490310 (java.lang.Integer)
    invokevirtual dj be:(II)V
    goto L197
L90
    iconst_0
    goto L178
L70
    return
L509
    iload 1
    ldc -2068421293 (java.lang.Integer)
    invokestatic f a:(II)Lfb;
    putstatic dp gl:Lfb;
    goto L432
L289
    iconst_0
    goto L293
L510
    getstatic client cd:Ldj;
    iload 3
    ldc 2023420595 (java.lang.Integer)
    invokevirtual dj af:(II)V
    goto L511
L512
    getstatic client cd:Ldj;
    sipush 164
    ldc -1451283509 (java.lang.Integer)
    invokevirtual dj hl:(II)V
L513
    getstatic client cd:Ldj;
    iload 1
    ldc -744044946 (java.lang.Integer)
    invokevirtual dj c:(II)V
L514
    iload 1
    ldc -2068421293 (java.lang.Integer)
    invokestatic f a:(II)Lfb;
    astore 9
    goto L515
L516
    iload 10
    bipush -79
    invokestatic db cc:(IB)V
    goto L159
L517
    aload 9
    getfield fb dh:[[I
    iconst_0
    aaload
    iconst_0
    iaload
    iconst_5
    if_icmpne L245
    goto L518
L9
    ldc -100126598 (java.lang.Integer)
    putstatic client gd:I
    goto L12
L519
    iconst_0
    putstatic client gz:I
    goto L311
L520
    sipush 1003
    invokestatic ai bh:(S)V
    goto L521
L140
    iconst_0
    putstatic client gj:I
    goto L30
L161
    getstatic client hg:[Ll;
    iload 3
    aaload
    astore 9
    goto L522
L436
    getstatic client cd:Ldj;
    bipush 42
    ldc 15951252 (java.lang.Integer)
    invokevirtual dj hl:(II)V
    goto L523
L524
    iload 0
    ldc -467606121 (java.lang.Integer)
    imul
    putstatic client mm:I
    goto L525
L526
    getstatic client cd:Ldj;
    iload 1
    ldc 1691578294 (java.lang.Integer)
    invokevirtual dj bv:(II)V
    goto L447
L433
    bipush 29
    iload 2
    if_icmpne L245
    iload 8
    ldc 1590767131 (java.lang.Integer)
    if_icmpne L512
    new java/lang/IllegalStateException
    dup
    invokespecial java/lang/IllegalStateException <init>:()V
    athrow
L527
    ldc -467606121 (java.lang.Integer)
    iload 0
    imul
    putstatic client mm:I
    goto L464
L217
    iload 1
    ldc -2068421293 (java.lang.Integer)
    invokestatic f a:(II)Lfb;
    putstatic dp gl:Lfb;
L528
    ldc -1001862243 (java.lang.Integer)
    iload 0
    imul
    putstatic client gw:I
L435
    sipush 1003
    iload 2
    if_icmpne L219
    iload 8
    ldc 1590767131 (java.lang.Integer)
    if_icmpne L529
    return
L529
    iload 6
    ldc 1135862533 (java.lang.Integer)
    imul
    putstatic client gs:I
L530
    iload 7
    ldc 677850631 (java.lang.Integer)
    imul
    putstatic client gk:I
    goto L480
L531
    iload 7
    ldc 677850631 (java.lang.Integer)
    imul
    putstatic client gk:I
    goto L532
L481
    iconst_0
    putstatic client gj:I
L533
    getstatic client cf:[Lam;
    iload 3
    aaload
    astore 9
    goto L218
L534
    ldc 677850631 (java.lang.Integer)
    iload 7
    imul
    putstatic client gk:I
    goto L535
L320
    ldc 677850631 (java.lang.Integer)
    iload 7
    imul
    putstatic client gk:I
    goto L536
L537
    getstatic client cd:Ldj;
    getstatic x cs:I
    ldc 616886125 (java.lang.Integer)
    imul
    iload 0
    iadd
    bipush 92
    invokevirtual dj an:(IB)V
    goto L538
L498
    iload 0
    ldc -467606121 (java.lang.Integer)
    imul
    putstatic client mm:I
    goto L100
L372
    aload 10
    ifnull L219
    iload 8
    ldc 1590767131 (java.lang.Integer)
    if_icmpne L141
    new java/lang/IllegalStateException
    dup
    invokespecial java/lang/IllegalStateException <init>:()V
    athrow
L539
    getstatic client cd:Ldj;
    iload 3
    bipush 14
    ishr
    sipush 32767
    iand
    iconst_1
    invokevirtual dj az:(IB)V
    goto L238
L142
    getstatic client cd:Ldj;
    aload 10
    getfield ay u:I
    ldc -1471228279 (java.lang.Integer)
    imul
    ldc 2091676815 (java.lang.Integer)
    invokevirtual dj af:(II)V
L219
    bipush 17
    iload 2
    if_icmpne L540
L541
    ldc 1135862533 (java.lang.Integer)
    iload 6
    imul
    putstatic client gs:I
L542
    iload 7
    ldc 677850631 (java.lang.Integer)
    imul
    putstatic client gk:I
L543
    ldc -100126598 (java.lang.Integer)
    putstatic client gd:I
L544
    iconst_0
    putstatic client gj:I
    goto L524
L505
    iconst_1
    goto L506
L545
    getstatic client cd:Ldj;
    ldc 1824985751 (java.lang.Integer)
    getstatic f jg:I
    imul
    ldc 943268725 (java.lang.Integer)
    invokevirtual dj bp:(II)V
    goto L546
L547
    aload 9
    ifnull L548
    iload 8
    ldc 1590767131 (java.lang.Integer)
    if_icmpne L549
    new java/lang/IllegalStateException
    dup
    invokespecial java/lang/IllegalStateException <init>:()V
    athrow
L88
    getstatic client cd:Ldj;
    iload 3
    ldc 2138243111 (java.lang.Integer)
    invokevirtual dj af:(II)V
    goto L437
L550
    iload 6
    ldc 1135862533 (java.lang.Integer)
    imul
    putstatic client gs:I
    goto L551
L439
    iconst_1
    goto L552
L438
    iconst_0
L552
    bipush -35
    invokevirtual dj e:(IB)V
    goto L482
L332
    iload 3
    bipush 9
    if_icmpne L38
    goto L478
L483
    getstatic client cd:Ldj;
    getstatic x cs:I
    ldc 616886125 (java.lang.Integer)
    imul
    iload 0
    iadd
    bipush -41
    invokevirtual dj a:(IB)V
L553
    getstatic client cd:Ldj;
    iload 1
    ldc 1317226893 (java.lang.Integer)
    getstatic co cz:I
    imul
    iadd
    iconst_4
    invokevirtual dj a:(IB)V
L554
    getstatic client cd:Ldj;
    ldc 1824985751 (java.lang.Integer)
    getstatic f jg:I
    imul
    ldc -588674151 (java.lang.Integer)
    invokevirtual dj c:(II)V
    goto L540
L37
    iconst_0
    putstatic client gj:I
    goto L413
L555
    getstatic client hg:[Ll;
    iload 3
    aaload
    astore 9
    goto L547
L409
    iload 3
    iconst_3
    if_icmpne L443
    iload 8
    ldc 1590767131 (java.lang.Integer)
    if_icmpne L556
    new java/lang/IllegalStateException
    dup
    invokespecial java/lang/IllegalStateException <init>:()V
    athrow
L549
    ldc 1135862533 (java.lang.Integer)
    iload 6
    imul
    putstatic client gs:I
    goto L557
L488
    getstatic client cd:Ldj;
    iload 3
    iconst_1
    invokevirtual dj az:(IB)V
    goto L491
L558
    iconst_0
    goto L559
L211
    iconst_0
    putstatic client gj:I
L560
    ldc -467606121 (java.lang.Integer)
    iload 0
    imul
    putstatic client mm:I
    goto L341
L561
    ldc -100126598 (java.lang.Integer)
    putstatic client gd:I
    goto L82
L342
    getstatic client cd:Ldj;
    bipush 113
    ldc -11034260 (java.lang.Integer)
    invokevirtual dj hl:(II)V
    goto L562
L147
    ldc -100126598 (java.lang.Integer)
    putstatic client gd:I
    goto L563
L390
    iload 1
    iload 0
    ldc -257790020 (java.lang.Integer)
    invokestatic ed l:(III)Lfb;
    astore 9
    goto L392
L564
    iconst_1
    goto L565
L566
    iconst_0
L565
    bipush -3
    invokevirtual dj e:(IB)V
L548
    iload 2
    bipush 15
    if_icmpne L567
    iload 8
    ldc 1590767131 (java.lang.Integer)
    if_icmpne L20
    new java/lang/IllegalStateException
    dup
    invokespecial java/lang/IllegalStateException <init>:()V
    athrow
L276
    getstatic client cd:Ldj;
    iload 3
    ldc 2146012445 (java.lang.Integer)
    invokevirtual dj af:(II)V
    goto L127
L21
    aconst_null
    aload 9
    if_acmpeq L567
    iload 8
    ldc 1590767131 (java.lang.Integer)
    if_icmpne L568
    new java/lang/IllegalStateException
    dup
    invokespecial java/lang/IllegalStateException <init>:()V
    athrow
L568
    iload 6
    ldc 1135862533 (java.lang.Integer)
    imul
    putstatic client gs:I
    goto L531
L407
    goto L39
L532
    ldc -100126598 (java.lang.Integer)
    putstatic client gd:I
    goto L569
L570
    bipush 50
    iload 2
    if_icmpne L209
    iload 8
    ldc 1590767131 (java.lang.Integer)
    if_icmpne L571
    return
L572
    iload 0
    ldc -467606121 (java.lang.Integer)
    imul
    putstatic client mm:I
L573
    ldc 1754300735 (java.lang.Integer)
    iload 1
    imul
    putstatic client mz:I
    goto L351
L395
    iload 7
    ldc 677850631 (java.lang.Integer)
    imul
    putstatic client gk:I
    goto L574
L352
    getstatic client cd:Ldj;
    ldc -1424280981 (java.lang.Integer)
    getstatic client ja:I
    imul
    iconst_1
    invokevirtual dj az:(IB)V
L575
    getstatic client cd:Ldj;
    getstatic f jg:I
    ldc 1824985751 (java.lang.Integer)
    imul
    ldc 1691578294 (java.lang.Integer)
    invokevirtual dj bv:(II)V
    goto L421
L576
    ldc 330542113 (java.lang.Integer)
    getstatic client gz:I
    imul
    ifne L106
    iload 8
    ldc 1590767131 (java.lang.Integer)
    if_icmpne L457
    new java/lang/IllegalStateException
    dup
    invokespecial java/lang/IllegalStateException <init>:()V
    athrow
L422
    getstatic client cd:Ldj;
    getstatic dr ce:[Z
    bipush 82
    baload
    ifeq L577
    iconst_1
    goto L578
L577
    iconst_0
L578
    ldc -1364409873 (java.lang.Integer)
    invokevirtual dj at:(II)V
L567
    iload 2
    bipush 8
    if_icmpne L546
L579
    getstatic client cf:[Lam;
    iload 3
    aaload
    astore 9
    goto L580
L556
    getstatic client cd:Ldj;
    sipush 209
    ldc 203565714 (java.lang.Integer)
    invokevirtual dj hl:(II)V
    goto L440
L581
    ldc 1135862533 (java.lang.Integer)
    iload 6
    imul
    putstatic client gs:I
L582
    iload 7
    ldc 677850631 (java.lang.Integer)
    imul
    putstatic client gk:I
    goto L28
L562
    getstatic client cd:Ldj;
    iload 3
    ldc 2135603223 (java.lang.Integer)
    invokevirtual dj af:(II)V
    goto L583
L64
    getstatic client cd:Ldj;
    iload 3
    bipush 87
    invokevirtual dj an:(IB)V
    goto L153
L265
    bipush -27
    invokevirtual dj e:(IB)V
    goto L584
L262
    ldc 677850631 (java.lang.Integer)
    iload 7
    imul
    putstatic client gk:I
    goto L401
L388
    getstatic client cd:Ldj;
    iload 3
    bipush 40
    invokevirtual dj an:(IB)V
    goto L220
L585
    getstatic client cd:Ldj;
    getstatic dr ce:[Z
    bipush 82
    baload
    ifeq L586
    iload 8
    ldc 1590767131 (java.lang.Integer)
    if_icmpne L587
    new java/lang/IllegalStateException
    dup
    invokespecial java/lang/IllegalStateException <init>:()V
    athrow
L587
    iconst_1
    goto L588
L586
    iconst_0
L588
    bipush -44
    invokevirtual dj e:(IB)V
L589
    getstatic client cd:Ldj;
    iload 3
    bipush 45
    invokevirtual dj an:(IB)V
    goto L590
L563
    iconst_0
    putstatic client gj:I
    goto L455
L591
    aload 9
    ifnull L92
    iload 8
    ldc 1590767131 (java.lang.Integer)
    if_icmpne L592
    return
L546
    iload 2
    bipush 26
    if_icmpne L593
    goto L594
L158
    iload 2
    bipush 21
    if_icmpne L180
    iload 8
    ldc 1590767131 (java.lang.Integer)
    if_icmpne L162
    new java/lang/IllegalStateException
    dup
    invokespecial java/lang/IllegalStateException <init>:()V
    athrow
L593
    iload 2
    bipush 10
    if_icmpne L595
    iload 8
    ldc 1590767131 (java.lang.Integer)
    if_icmpne L596
    new java/lang/IllegalStateException
    dup
    invokespecial java/lang/IllegalStateException <init>:()V
    athrow
L596
    getstatic client cf:[Lam;
    iload 3
    aaload
    astore 9
L597
    aconst_null
    aload 9
    if_acmpeq L595
    iload 8
    ldc 1590767131 (java.lang.Integer)
    if_icmpne L319
    new java/lang/IllegalStateException
    dup
    invokespecial java/lang/IllegalStateException <init>:()V
    athrow
L430
    iconst_0
    invokevirtual dj ah:(IB)V
    goto L598
L599
    iload 1
    iload 0
    ldc 555251533 (java.lang.Integer)
    invokestatic ed l:(III)Lfb;
    astore 9
    goto L600
L536
    ldc -100126598 (java.lang.Integer)
    putstatic client gd:I
L601
    iconst_0
    putstatic client gj:I
    goto L602
L603
    aconst_null
    getstatic client it:Ljava/lang/String;
    if_acmpne L389
    iload 8
    ldc 1590767131 (java.lang.Integer)
    if_icmpne L604
    return
L605
    iload 1
    ldc 1754300735 (java.lang.Integer)
    imul
    putstatic client mz:I
    goto L143
L199
    bipush 35
    iload 2
    if_icmpne L223
    iload 8
    ldc 1590767131 (java.lang.Integer)
    if_icmpne L606
    new java/lang/IllegalStateException
    dup
    invokespecial java/lang/IllegalStateException <init>:()V
    athrow
L144
    getstatic client cd:Ldj;
    getstatic dr ce:[Z
    bipush 82
    baload
    ifeq L558
    iload 8
    ldc 1590767131 (java.lang.Integer)
    if_icmpne L607
    new java/lang/IllegalStateException
    dup
    invokespecial java/lang/IllegalStateException <init>:()V
    athrow
L584
    getstatic client cd:Ldj;
    getstatic x cs:I
    ldc 616886125 (java.lang.Integer)
    imul
    iload 0
    iadd
    bipush 28
    invokevirtual dj a:(IB)V
    goto L539
L608
    ldc 677850631 (java.lang.Integer)
    iload 7
    imul
    putstatic client gk:I
    goto L609
L559
    iconst_0
    invokevirtual dj ah:(IB)V
L610
    getstatic client cd:Ldj;
    iload 3
    iconst_1
    invokevirtual dj az:(IB)V
L595
    iload 2
    bipush 45
    if_icmpne L611
    goto L427
L612
    getstatic client hg:[Ll;
    iload 3
    aaload
    astore 9
    goto L613
L428
    aload 9
    ifnull L611
    iload 8
    ldc 1590767131 (java.lang.Integer)
    if_icmpne L614
    new java/lang/IllegalStateException
    dup
    invokespecial java/lang/IllegalStateException <init>:()V
    athrow
L196
    getstatic client cd:Ldj;
    iload 3
    bipush 54
    invokevirtual dj an:(IB)V
    goto L184
L615
    iload 7
    ldc 677850631 (java.lang.Integer)
    imul
    putstatic client gk:I
    goto L561
L42
    ldc 1754300735 (java.lang.Integer)
    iload 1
    imul
    putstatic client mz:I
    goto L616
L76
    iconst_1
    goto L275
L83
    ldc -467606121 (java.lang.Integer)
    iload 0
    imul
    putstatic client mm:I
L617
    iload 1
    ldc 1754300735 (java.lang.Integer)
    imul
    putstatic client mz:I
L618
    getstatic client cd:Ldj;
    bipush 98
    ldc -2068922632 (java.lang.Integer)
    invokevirtual dj hl:(II)V
    goto L473
L120
    getstatic client cd:Ldj;
    getstatic x cs:I
    ldc 616886125 (java.lang.Integer)
    imul
    iload 0
    iadd
    bipush 86
    invokevirtual dj a:(IB)V
    goto L22
L474
    getstatic client cd:Ldj;
    getstatic dr ce:[Z
    bipush 82
    baload
    ifeq L619
    iload 8
    ldc 1590767131 (java.lang.Integer)
    if_icmpne L620
    new java/lang/IllegalStateException
    dup
    invokespecial java/lang/IllegalStateException <init>:()V
    athrow
L620
    iconst_1
    goto L621
L619
    iconst_0
L621
    ldc 2102512478 (java.lang.Integer)
    invokevirtual dj al:(II)V
L611
    iload 2
    bipush 39
    if_icmpne L622
L623
    getstatic client cd:Ldj;
    bipush 23
    ldc -796282621 (java.lang.Integer)
    invokevirtual dj hl:(II)V
L624
    getstatic client cd:Ldj;
    iload 1
    ldc -1850490310 (java.lang.Integer)
    invokevirtual dj be:(II)V
L625
    getstatic client cd:Ldj;
    iload 0
    iconst_1
    invokevirtual dj az:(IB)V
    goto L626
L411
    aload 11
    bipush 35
    invokestatic t dj:(Lfb;B)I
    istore 14
    goto L627
L628
    iconst_0
    putstatic client gz:I
    goto L98
L321
    iload 0
    ldc -1001862243 (java.lang.Integer)
    imul
    putstatic client gw:I
    goto L199
L99
    iload 0
    ldc -1001862243 (java.lang.Integer)
    imul
    putstatic client gw:I
L622
    iload 2
    bipush 43
    if_icmpne L570
    iload 8
    ldc 1590767131 (java.lang.Integer)
    if_icmpne L629
    new java/lang/IllegalStateException
    dup
    invokespecial java/lang/IllegalStateException <init>:()V
    athrow
L629
    getstatic client cd:Ldj;
    bipush 61
    ldc -432365330 (java.lang.Integer)
    invokevirtual dj hl:(II)V
L630
    getstatic client cd:Ldj;
    iload 3
    ldc 2110476141 (java.lang.Integer)
    invokevirtual dj af:(II)V
L631
    getstatic client cd:Ldj;
    iload 0
    bipush 91
    invokevirtual dj an:(IB)V
    goto L164
L632
    getstatic client cd:Ldj;
    sipush 219
    ldc -493303953 (java.lang.Integer)
    invokevirtual dj hl:(II)V
    goto L633
L614
    ldc 1135862533 (java.lang.Integer)
    iload 6
    imul
    putstatic client gs:I
    goto L615
L17
    iload 1
    ldc -2068421293 (java.lang.Integer)
    invokestatic f a:(II)Lfb;
    putstatic dp gl:Lfb;
L634
    iload 0
    ldc -1001862243 (java.lang.Integer)
    imul
    putstatic client gw:I
    goto L570
L493
    iload 0
    ldc -1001862243 (java.lang.Integer)
    imul
    putstatic client gw:I
    goto L174
L571
    getstatic client hg:[Ll;
    iload 3
    aaload
    astore 9
    goto L635
L461
    getstatic client cd:Ldj;
    iload 10
    bipush -14
    invokevirtual dj a:(IB)V
    goto L636
L637
    ldc 1135862533 (java.lang.Integer)
    iload 6
    imul
    putstatic client gs:I
    goto L608
L607
    iconst_1
    goto L559
L609
    ldc -100126598 (java.lang.Integer)
    putstatic client gd:I
L638
    iconst_0
    putstatic client gj:I
L639
    iload 0
    ldc -467606121 (java.lang.Integer)
    imul
    putstatic client mm:I
    goto L451
L382
    ldc -467606121 (java.lang.Integer)
    iload 0
    imul
    putstatic client mm:I
    goto L386
L452
    getstatic client cd:Ldj;
    bipush 80
    ldc -1056621410 (java.lang.Integer)
    invokevirtual dj hl:(II)V
    goto L510
L640
    goto L39
L511
    getstatic client cd:Ldj;
    getstatic dr ce:[Z
    bipush 82
    baload
    ifeq L641
    iload 8
    ldc 1590767131 (java.lang.Integer)
    if_icmpne L642
    new java/lang/IllegalStateException
    dup
    invokespecial java/lang/IllegalStateException <init>:()V
    athrow
L642
    iconst_1
    goto L208
L641
    iconst_0
    goto L208
L370
    iload 1
    ldc -2068421293 (java.lang.Integer)
    invokestatic f a:(II)Lfb;
    putstatic dp gl:Lfb;
    goto L643
L209
    iload 2
    bipush 23
    if_icmpne L644
    iload 8
    ldc 1590767131 (java.lang.Integer)
    if_icmpne L645
    new java/lang/IllegalStateException
    dup
    invokespecial java/lang/IllegalStateException <init>:()V
    athrow
L645
    getstatic n ds:Lcb;
    getstatic fd hz:I
    ldc -837647185 (java.lang.Integer)
    imul
    iload 0
    iload 1
    invokevirtual cb ag:(III)V
L644
    bipush 51
    iload 2
    if_icmpne L362
    iload 8
    ldc 1590767131 (java.lang.Integer)
    if_icmpne L646
    new java/lang/IllegalStateException
    dup
    invokespecial java/lang/IllegalStateException <init>:()V
    athrow
L646
    getstatic client hg:[Ll;
    iload 3
    aaload
    astore 9
L647
    aload 9
    ifnull L362
    iload 8
    ldc 1590767131 (java.lang.Integer)
    if_icmpne L648
    new java/lang/IllegalStateException
    dup
    invokespecial java/lang/IllegalStateException <init>:()V
    athrow
L648
    iload 6
    ldc 1135862533 (java.lang.Integer)
    imul
    putstatic client gs:I
L649
    ldc 677850631 (java.lang.Integer)
    iload 7
    imul
    putstatic client gk:I
L650
    ldc -100126598 (java.lang.Integer)
    putstatic client gd:I
L651
    iconst_0
    putstatic client gj:I
L652
    iload 0
    ldc -467606121 (java.lang.Integer)
    imul
    putstatic client mm:I
L653
    ldc 1754300735 (java.lang.Integer)
    iload 1
    imul
    putstatic client mz:I
L654
    getstatic client cd:Ldj;
    sipush 231
    ldc -646720177 (java.lang.Integer)
    invokevirtual dj hl:(II)V
L655
    getstatic client cd:Ldj;
    getstatic dr ce:[Z
    bipush 82
    baload
    ifeq L656
    iload 8
    ldc 1590767131 (java.lang.Integer)
    if_icmpne L657
    return
L657
    iconst_1
    goto L249
L656
    iconst_0
    goto L249
L97
    ldc -100126598 (java.lang.Integer)
    putstatic client gd:I
    goto L658
L602
    iload 0
    ldc -467606121 (java.lang.Integer)
    imul
    putstatic client mm:I
    goto L605
L362
    sipush 1002
    iload 2
    if_icmpne L659
    goto L462
L126
    iconst_0
    putstatic client gz:I
    goto L660
L463
    iload 7
    ldc 677850631 (java.lang.Integer)
    imul
    putstatic client gk:I
    goto L661
L101
    getstatic client cd:Ldj;
    sipush 150
    ldc -1833957140 (java.lang.Integer)
    invokevirtual dj hl:(II)V
    goto L501
L662
    iconst_0
    putstatic client gj:I
L663
    getstatic client cd:Ldj;
    bipush 92
    ldc -1271504210 (java.lang.Integer)
    invokevirtual dj hl:(II)V
L664
    getstatic client cd:Ldj;
    iload 3
    bipush 14
    ishr
    sipush 32767
    iand
    bipush 98
    invokevirtual dj an:(IB)V
L659
    iconst_3
    iload 2
    if_icmpne L305
L665
    iload 6
    ldc 1135862533 (java.lang.Integer)
    imul
    putstatic client gs:I
L666
    ldc 677850631 (java.lang.Integer)
    iload 7
    imul
    putstatic client gk:I
L667
    ldc -100126598 (java.lang.Integer)
    putstatic client gd:I
    goto L484
L105
    getstatic client cd:Ldj;
    getstatic dr ce:[Z
    bipush 82
    baload
    ifeq L668
    iload 8
    ldc 1590767131 (java.lang.Integer)
    if_icmpne L669
    return
L485
    iload 0
    ldc -467606121 (java.lang.Integer)
    imul
    putstatic client mm:I
    goto L254
L278
    getstatic client cd:Ldj;
    ldc 962031019 (java.lang.Integer)
    getstatic client jw:I
    imul
    ldc 2044565157 (java.lang.Integer)
    invokevirtual dj af:(II)V
    goto L308
L255
    getstatic client cd:Ldj;
    sipush 191
    ldc -268128894 (java.lang.Integer)
    invokevirtual dj hl:(II)V
    goto L136
L670
    ldc 1754300735 (java.lang.Integer)
    iload 1
    imul
    putstatic client mz:I
    goto L671
L137
    getstatic client cd:Ldj;
    getstatic co cz:I
    ldc 1317226893 (java.lang.Integer)
    imul
    iload 1
    iadd
    bipush 122
    invokevirtual dj an:(IB)V
    goto L18
L523
    getstatic client cd:Ldj;
    iload 0
    bipush 51
    invokevirtual dj an:(IB)V
    goto L526
L19
    getstatic client cd:Ldj;
    getstatic dr ce:[Z
    bipush 82
    baload
    ifeq L672
    iload 8
    ldc 1590767131 (java.lang.Integer)
    if_icmpne L673
    new java/lang/IllegalStateException
    dup
    invokespecial java/lang/IllegalStateException <init>:()V
    athrow
L673
    iconst_1
    goto L304
L672
    iconst_0
    goto L304
L669
    iconst_1
    goto L111
L330
    ldc 677850631 (java.lang.Integer)
    iload 7
    imul
    putstatic client gk:I
    goto L333
L301
    getstatic client cd:Ldj;
    iload 0
    bipush 124
    invokevirtual dj an:(IB)V
    goto L277
L674
    aload 9
    ifnull L675
    iload 8
    ldc 1590767131 (java.lang.Integer)
    if_icmpne L550
    new java/lang/IllegalStateException
    dup
    invokespecial java/lang/IllegalStateException <init>:()V
    athrow
L515
    aconst_null
    aload 9
    getfield fb dh:[[I
    if_acmpeq L245
    iload 8
    ldc 1590767131 (java.lang.Integer)
    if_icmpne L517
    return
L75
    iconst_0
    goto L275
L676
    ldc -100126598 (java.lang.Integer)
    putstatic client gd:I
    goto L269
L660
    iload 1
    ldc -2068421293 (java.lang.Integer)
    invokestatic f a:(II)Lfb;
    putstatic dp gl:Lfb;
    goto L132
L270
    ldc -467606121 (java.lang.Integer)
    iload 0
    imul
    putstatic client mm:I
L677
    iload 1
    ldc 1754300735 (java.lang.Integer)
    imul
    putstatic client mz:I
    goto L499
L626
    getstatic client cd:Ldj;
    iload 3
    bipush 60
    invokevirtual dj an:(IB)V
    goto L628
L108
    ldc 1389707147 (java.lang.Integer)
    invokevirtual dj at:(II)V
    goto L678
L679
    getstatic client cd:Ldj;
    getstatic dr ce:[Z
    bipush 82
    baload
    ifeq L680
    iload 8
    ldc 1590767131 (java.lang.Integer)
    if_icmpne L681
    new java/lang/IllegalStateException
    dup
    invokespecial java/lang/IllegalStateException <init>:()V
    athrow
L681
    iconst_1
    goto L682
L683
    iconst_0
    goto L684
L682
    bipush 23
    invokevirtual dj e:(IB)V
L675
    iload 2
    bipush 22
    if_icmpne L685
    iload 8
    ldc 1590767131 (java.lang.Integer)
    if_icmpne L394
    return
L686
    aload 9
    getfield fb dh:[[I
    iconst_0
    aaload
    iconst_0
    iaload
    iconst_5
    if_icmpne L159
    iload 8
    ldc 1590767131 (java.lang.Integer)
    if_icmpne L687
    new java/lang/IllegalStateException
    dup
    invokespecial java/lang/IllegalStateException <init>:()V
    athrow
L356
    aload 9
    ifnull L133
    iload 8
    ldc 1590767131 (java.lang.Integer)
    if_icmpne L358
    new java/lang/IllegalStateException
    dup
    invokespecial java/lang/IllegalStateException <init>:()V
    athrow
L574
    ldc -100126598 (java.lang.Integer)
    putstatic client gd:I
L688
    iconst_0
    putstatic client gj:I
L689
    ldc -467606121 (java.lang.Integer)
    iload 0
    imul
    putstatic client mm:I
L690
    ldc 1754300735 (java.lang.Integer)
    iload 1
    imul
    putstatic client mz:I
    goto L173
L590
    getstatic client cd:Ldj;
    ldc -1424280981 (java.lang.Integer)
    getstatic client ja:I
    imul
    ldc 2036826203 (java.lang.Integer)
    invokevirtual dj af:(II)V
    goto L545
L691
    getstatic client cd:Ldj;
    iload 1
    ldc 1691578294 (java.lang.Integer)
    invokevirtual dj bv:(II)V
    goto L692
L290
    iconst_1
    goto L293
L149
    iconst_0
    goto L430
L636
    bipush 7
    iload 3
    if_icmpne L470
    iload 8
    ldc 1590767131 (java.lang.Integer)
    if_icmpne L466
    new java/lang/IllegalStateException
    dup
    invokespecial java/lang/IllegalStateException <init>:()V
    athrow
L598
    getstatic client cd:Ldj;
    ldc 616886125 (java.lang.Integer)
    getstatic x cs:I
    imul
    iload 0
    iadd
    bipush -37
    invokevirtual dj a:(IB)V
L693
    getstatic client cd:Ldj;
    iload 3
    iconst_1
    invokevirtual dj az:(IB)V
L694
    getstatic client cd:Ldj;
    ldc 1317226893 (java.lang.Integer)
    getstatic co cz:I
    imul
    iload 1
    iadd
    bipush -28
    invokevirtual dj a:(IB)V
    goto L685
L345
    getstatic client cd:Ldj;
    iload 3
    bipush 14
    ishr
    sipush 32767
    iand
    iconst_1
    invokevirtual dj az:(IB)V
    goto L347
L695
    getstatic client cd:Ldj;
    sipush 164
    ldc 260584075 (java.lang.Integer)
    invokevirtual dj hl:(II)V
L696
    getstatic client cd:Ldj;
    iload 1
    ldc 1547585698 (java.lang.Integer)
    invokevirtual dj c:(II)V
L697
    iload 1
    ldc -2068421293 (java.lang.Integer)
    invokestatic f a:(II)Lfb;
    astore 9
L698
    aload 9
    getfield fb dh:[[I
    ifnull L159
    goto L686
L635
    aconst_null
    aload 9
    if_acmpeq L209
    iload 8
    ldc 1590767131 (java.lang.Integer)
    if_icmpne L637
    new java/lang/IllegalStateException
    dup
    invokespecial java/lang/IllegalStateException <init>:()V
    athrow
L687
    aload 9
    getfield fb dh:[[I
    iconst_0
    aaload
    iconst_1
    iaload
    istore 10
L699
    getstatic fl l:[I
    iload 10
    iconst_1
    getstatic fl l:[I
    iload 10
    iaload
    isub
    iastore
    goto L516
L518
    aload 9
    getfield fb dh:[[I
    iconst_0
    aaload
    iconst_1
    iaload
    istore 10
    goto L405
L429
    getstatic client cd:Ldj;
    iload 10
    bipush -7
    invokevirtual dj a:(IB)V
    goto L408
L700
    new java/lang/StringBuilder
    dup
    invokespecial java/lang/StringBuilder <init>:()V
    ldc 16748608 (java.lang.Integer)
    bipush -101
    invokestatic p e:(IB)Ljava/lang/String;
    invokevirtual java/lang/StringBuilder append:(Ljava/lang/String;)Ljava/lang/StringBuilder;
    iload 3
    bipush -23
    invokestatic dj e:(IB)Lad;
    getfield ad j:Ljava/lang/String;
    invokevirtual java/lang/StringBuilder append:(Ljava/lang/String;)Ljava/lang/StringBuilder;
    ldc 16777215 (java.lang.Integer)
    bipush -28
    invokestatic p e:(IB)Ljava/lang/String;
    invokevirtual java/lang/StringBuilder append:(Ljava/lang/String;)Ljava/lang/StringBuilder;
    invokevirtual java/lang/StringBuilder toString:()Ljava/lang/String;
    putstatic client it:Ljava/lang/String;
    goto L603
L522
    aconst_null
    aload 9
    if_acmpeq L160
    iload 8
    ldc 1590767131 (java.lang.Integer)
    if_icmpne L701
    new java/lang/IllegalStateException
    dup
    invokespecial java/lang/IllegalStateException <init>:()V
    athrow
L701
    ldc 1135862533 (java.lang.Integer)
    iload 6
    imul
    putstatic client gs:I
    goto L702
L703
    getstatic client cd:Ldj;
    getstatic dr ce:[Z
    bipush 82
    baload
    ifeq L704
    iload 8
    ldc 1590767131 (java.lang.Integer)
    if_icmpne L107
    return
L705
    ldc -100126598 (java.lang.Integer)
    putstatic client gd:I
L706
    iconst_0
    putstatic client gj:I
L707
    iload 0
    ldc -467606121 (java.lang.Integer)
    imul
    putstatic client mm:I
    goto L670
L551
    ldc 677850631 (java.lang.Integer)
    iload 7
    imul
    putstatic client gk:I
    goto L676
L671
    getstatic client cd:Ldj;
    sipush 228
    ldc 658442730 (java.lang.Integer)
    invokevirtual dj hl:(II)V
L708
    getstatic client cd:Ldj;
    getstatic dh iz:I
    ldc 1827663583 (java.lang.Integer)
    imul
    iconst_2
    invokevirtual dj an:(IB)V
L709
    getstatic client cd:Ldj;
    iload 3
    ldc 2134055921 (java.lang.Integer)
    invokevirtual dj af:(II)V
L710
    getstatic client cd:Ldj;
    getstatic aj ix:I
    ldc 1565981493 (java.lang.Integer)
    imul
    ldc 1691578294 (java.lang.Integer)
    invokevirtual dj bv:(II)V
L711
    getstatic client cd:Ldj;
    getstatic fp iq:I
    ldc -7450759 (java.lang.Integer)
    imul
    bipush 8
    invokevirtual dj a:(IB)V
L712
    getstatic client cd:Ldj;
    getstatic dr ce:[Z
    bipush 82
    baload
    ifeq L713
    iload 8
    ldc 1590767131 (java.lang.Integer)
    if_icmpne L714
    new java/lang/IllegalStateException
    dup
    invokespecial java/lang/IllegalStateException <init>:()V
    athrow
L714
    iconst_1
    goto L715
L713
    iconst_0
L715
    ldc 1469234204 (java.lang.Integer)
    invokevirtual dj al:(II)V
L160
    bipush 32
    iload 2
    if_icmpne L716
    iload 8
    ldc 1590767131 (java.lang.Integer)
    if_icmpne L717
    return
L717
    getstatic client cd:Ldj;
    bipush 24
    ldc 468202396 (java.lang.Integer)
    invokevirtual dj hl:(II)V
L718
    getstatic client cd:Ldj;
    iload 0
    ldc 2082683052 (java.lang.Integer)
    invokevirtual dj af:(II)V
    goto L212
L719
    getstatic client cd:Ldj;
    ldc -7450759 (java.lang.Integer)
    getstatic fp iq:I
    imul
    iconst_1
    invokevirtual dj az:(IB)V
    goto L720
L328
    iload 2
    bipush 47
    if_icmpne L133
    iload 8
    ldc 1590767131 (java.lang.Integer)
    if_icmpne L355
    new java/lang/IllegalStateException
    dup
    invokespecial java/lang/IllegalStateException <init>:()V
    athrow
L721
    getstatic client cd:Ldj;
    iload 3
    bipush -116
    invokevirtual dj a:(IB)V
L722
    getstatic client cd:Ldj;
    iload 1
    ldc -1850490310 (java.lang.Integer)
    invokevirtual dj be:(II)V
    goto L369
L569
    iconst_0
    putstatic client gj:I
    goto L572
L616
    getstatic client cd:Ldj;
    sipush 128
    ldc -1173124304 (java.lang.Integer)
    invokevirtual dj hl:(II)V
    goto L585
L643
    iload 0
    ldc -1001862243 (java.lang.Integer)
    imul
    putstatic client gw:I
L716
    bipush 44
    iload 2
    if_icmpne L274
L723
    getstatic client hg:[Ll;
    iload 3
    aaload
    astore 9
L724
    aconst_null
    aload 9
    if_acmpeq L274
    iload 8
    ldc 1590767131 (java.lang.Integer)
    if_icmpne L725
    new java/lang/IllegalStateException
    dup
    invokespecial java/lang/IllegalStateException <init>:()V
    athrow
L725
    ldc 1135862533 (java.lang.Integer)
    iload 6
    imul
    putstatic client gs:I
L726
    iload 7
    ldc 677850631 (java.lang.Integer)
    imul
    putstatic client gk:I
L727
    ldc -100126598 (java.lang.Integer)
    putstatic client gd:I
L728
    iconst_0
    putstatic client gj:I
L729
    ldc -467606121 (java.lang.Integer)
    iload 0
    imul
    putstatic client mm:I
L730
    iload 1
    ldc 1754300735 (java.lang.Integer)
    imul
    putstatic client mz:I
    goto L632
L731
    ldc -467606121 (java.lang.Integer)
    iload 0
    imul
    putstatic client mm:I
    goto L732
L633
    getstatic client cd:Ldj;
    iload 3
    bipush 6
    invokevirtual dj a:(IB)V
L733
    getstatic client cd:Ldj;
    getstatic dr ce:[Z
    bipush 82
    baload
    ifeq L734
    iload 8
    ldc 1590767131 (java.lang.Integer)
    if_icmpne L735
    new java/lang/IllegalStateException
    dup
    invokespecial java/lang/IllegalStateException <init>:()V
    athrow
L735
    iconst_1
    goto L273
L734
    iconst_0
    goto L273
L118
    getstatic client cd:Ldj;
    iload 0
    iconst_1
    invokevirtual dj az:(IB)V
    goto L121
L274
    iload 2
    bipush 25
    if_icmpne L736
    iload 8
    ldc 1590767131 (java.lang.Integer)
    if_icmpne L599
    return
L324
    getstatic client jz:Lfb;
    ldc -1023277750 (java.lang.Integer)
    invokestatic dh cr:(Lfb;I)V
    goto L26
L600
    aload 9
    ifnull L70
    iload 8
    ldc 1590767131 (java.lang.Integer)
    if_icmpne L520
    new java/lang/IllegalStateException
    dup
    invokespecial java/lang/IllegalStateException <init>:()V
    athrow
L557
    ldc 677850631 (java.lang.Integer)
    iload 7
    imul
    putstatic client gk:I
    goto L210
L521
    iload 1
    istore 10
    goto L353
L580
    aload 9
    ifnull L546
    iload 8
    ldc 1590767131 (java.lang.Integer)
    if_icmpne L581
    new java/lang/IllegalStateException
    dup
    invokespecial java/lang/IllegalStateException <init>:()V
    athrow
L354
    aload 9
    bipush 125
    invokestatic t dj:(Lfb;B)I
    istore 13
    goto L375
L263
    getstatic client cf:[Lam;
    iload 3
    aaload
    astore 9
    goto L183
L376
    iload 10
    iload 11
    iload 12
    ldc 689007975 (java.lang.Integer)
    aload 9
    getfield fb db:I
    imul
    ldc 699387938 (java.lang.Integer)
    invokestatic h bz:(IIIII)V
    goto L737
L583
    getstatic client cd:Ldj;
    getstatic dr ce:[Z
    bipush 82
    baload
    ifeq L566
    iload 8
    ldc 1590767131 (java.lang.Integer)
    if_icmpne L564
    new java/lang/IllegalStateException
    dup
    invokespecial java/lang/IllegalStateException <init>:()V
    athrow
L346
    getstatic client cf:[Lam;
    iload 3
    aaload
    astore 9
    goto L738
L198
    iconst_0
    putstatic client gz:I
    goto L509
L739
    getstatic client cd:Ldj;
    iload 0
    ldc 616886125 (java.lang.Integer)
    getstatic x cs:I
    imul
    iadd
    iconst_1
    invokevirtual dj az:(IB)V
    goto L740
L130
    aload 9
    getfield fb o:Z
    ifeq L741
    iload 8
    ldc 1590767131 (java.lang.Integer)
    if_icmpne L69
    new java/lang/IllegalStateException
    dup
    invokespecial java/lang/IllegalStateException <init>:()V
    athrow
L742
    getstatic client cf:[Lam;
    iload 3
    aaload
    astore 9
    goto L591
L741
    new java/lang/StringBuilder
    dup
    invokespecial java/lang/StringBuilder <init>:()V
    ldc 65280 (java.lang.Integer)
    bipush -13
    invokestatic p e:(IB)Ljava/lang/String;
    invokevirtual java/lang/StringBuilder append:(Ljava/lang/String;)Ljava/lang/StringBuilder;
    aload 9
    getfield fb dt:Ljava/lang/String;
    invokevirtual java/lang/StringBuilder append:(Ljava/lang/String;)Ljava/lang/StringBuilder;
    ldc 16777215 (java.lang.Integer)
    bipush -95
    invokestatic p e:(IB)Ljava/lang/String;
    invokevirtual java/lang/StringBuilder append:(Ljava/lang/String;)Ljava/lang/StringBuilder;
    invokevirtual java/lang/StringBuilder toString:()Ljava/lang/String;
    putstatic client jk:Ljava/lang/String;
    goto L70
L305
    iload 2
    bipush 12
    if_icmpne L675
    iload 8
    ldc 1590767131 (java.lang.Integer)
    if_icmpne L743
    new java/lang/IllegalStateException
    dup
    invokespecial java/lang/IllegalStateException <init>:()V
    athrow
L736
    iload 2
    iconst_4
    if_icmpne L744
    iload 8
    ldc 1590767131 (java.lang.Integer)
    if_icmpne L400
    new java/lang/IllegalStateException
    dup
    invokespecial java/lang/IllegalStateException <init>:()V
    athrow
L745
    getstatic client cd:Ldj;
    bipush 90
    ldc -255015432 (java.lang.Integer)
    invokevirtual dj hl:(II)V
    goto L746
L170
    getstatic client cd:Ldj;
    getstatic co cz:I
    ldc 1317226893 (java.lang.Integer)
    imul
    iload 1
    iadd
    iconst_1
    invokevirtual dj az:(IB)V
    goto L172
L747
    ldc 677850631 (java.lang.Integer)
    iload 7
    imul
    putstatic client gk:I
    goto L748
L242
    iconst_0
    goto L243
L177
    getstatic client cd:Ldj;
    iload 1
    getstatic co cz:I
    ldc 1317226893 (java.lang.Integer)
    imul
    iadd
    bipush -69
    invokevirtual dj a:(IB)V
    goto L744
L456
    iload 1
    ldc 1754300735 (java.lang.Integer)
    imul
    putstatic client mz:I
L749
    getstatic client cd:Ldj;
    bipush 100
    ldc 689664094 (java.lang.Integer)
    invokevirtual dj hl:(II)V
    goto L739
L73
    getstatic client cd:Ldj;
    bipush 55
    ldc -2146120082 (java.lang.Integer)
    invokevirtual dj hl:(II)V
    goto L414
L740
    getstatic client cd:Ldj;
    getstatic dr ce:[Z
    bipush 82
    baload
    ifeq L683
    iconst_1
    goto L684
L29
    iconst_0
    putstatic client gj:I
    goto L41
L684
    ldc 1829828013 (java.lang.Integer)
    invokevirtual dj at:(II)V
    goto L176
L678
    iload 2
    bipush 16
    if_icmpne L237
    goto L750
L46
    bipush 6
    iload 3
    if_icmpne L636
    iload 8
    ldc 1590767131 (java.lang.Integer)
    if_icmpne L751
    new java/lang/IllegalStateException
    dup
    invokespecial java/lang/IllegalStateException <init>:()V
    athrow
L744
    bipush 24
    iload 2
    if_icmpne L56
    iload 8
    ldc 1590767131 (java.lang.Integer)
    if_icmpne L752
    new java/lang/IllegalStateException
    dup
    invokespecial java/lang/IllegalStateException <init>:()V
    athrow
L752
    iload 1
    ldc -2068421293 (java.lang.Integer)
    invokestatic f a:(II)Lfb;
    astore 9
    goto L109
L604
    ldc "null" (java.lang.String)
    putstatic client it:Ljava/lang/String;
    goto L389
L110
    aload 9
    getfield fb t:I
    ldc 937329469 (java.lang.Integer)
    imul
    ifle L753
    aload 9
    ldc -863090355 (java.lang.Integer)
    invokestatic an dd:(Lfb;I)Z
    istore 10
L753
    iload 10
    ifeq L56
    iload 8
    ldc 1590767131 (java.lang.Integer)
    if_icmpne L171
    return
L737
    iconst_0
    putstatic client in:I
    goto L494
L116
    iload 2
    bipush 19
    if_icmpne L158
    iload 8
    ldc 1590767131 (java.lang.Integer)
    if_icmpne L458
    return
L56
    iload 2
    bipush 36
    if_icmpne L152
    iload 8
    ldc 1590767131 (java.lang.Integer)
    if_icmpne L754
    return
L754
    getstatic client cd:Ldj;
    bipush 64
    ldc -2084380618 (java.lang.Integer)
    invokevirtual dj hl:(II)V
L755
    getstatic client cd:Ldj;
    iload 3
    bipush 71
    invokevirtual dj a:(IB)V
    goto L691
L525
    ldc 1754300735 (java.lang.Integer)
    iload 1
    imul
    putstatic client mz:I
    goto L87
L692
    getstatic client cd:Ldj;
    iload 0
    ldc 2070371318 (java.lang.Integer)
    invokevirtual dj af:(II)V
L756
    iconst_0
    putstatic client gz:I
    goto L757
L268
    ldc 1754300735 (java.lang.Integer)
    iload 1
    imul
    putstatic client mz:I
    goto L271
L420
    iload 13
    ifne L425
    iload 8
    ldc 1590767131 (java.lang.Integer)
    if_icmpne L640
    new java/lang/IllegalStateException
    dup
    invokespecial java/lang/IllegalStateException <init>:()V
    athrow
L152
    bipush 13
    iload 2
    if_icmpne L92
    iload 8
    ldc 1590767131 (java.lang.Integer)
    if_icmpne L742
    new java/lang/IllegalStateException
    dup
    invokespecial java/lang/IllegalStateException <init>:()V
    athrow
L371
    bipush -59
    invokevirtual dj e:(IB)V
    goto L374
L492
    ldc 920120009 (java.lang.Integer)
    iload 0
    imul
    putstatic fp iq:I
    goto L383
L592
    ldc 1135862533 (java.lang.Integer)
    iload 6
    imul
    putstatic client gs:I
    goto L423
L743
    getstatic client cf:[Lam;
    iload 3
    aaload
    astore 9
    goto L674
L424
    ldc -100126598 (java.lang.Integer)
    putstatic client gd:I
L758
    iconst_0
    putstatic client gj:I
    goto L731
L472
    getstatic client cd:Ldj;
    iload 1
    ldc 1920576493 (java.lang.Integer)
    invokevirtual dj c:(II)V
    goto L475
L732
    ldc 1754300735 (java.lang.Integer)
    iload 1
    imul
    putstatic client mz:I
    goto L77
L253
    iconst_0
    putstatic client gz:I
    goto L256
L78
    getstatic client cd:Ldj;
    iload 3
    bipush -67
    invokevirtual dj a:(IB)V
    goto L415
L248
    getstatic client cd:Ldj;
    iload 0
    ldc 2021413448 (java.lang.Integer)
    invokevirtual dj af:(II)V
    goto L251
L417
    iconst_1
    goto L759
L416
    iconst_0
L759
    bipush -83
    invokevirtual dj e:(IB)V
    goto L92
L368
    iconst_1
    goto L371
L94
    iload 1
    ldc -2068421293 (java.lang.Integer)
    invokestatic f a:(II)Lfb;
    astore 9
L760
    aload 9
    ifnull L53
    iload 8
    ldc 1590767131 (java.lang.Integer)
    if_icmpne L306
    new java/lang/IllegalStateException
    dup
    invokespecial java/lang/IllegalStateException <init>:()V
    athrow
L702
    iload 7
    ldc 677850631 (java.lang.Integer)
    imul
    putstatic client gk:I
    goto L705
L307
    bipush 27
    ldc "" (java.lang.String)
    new java/lang/StringBuilder
    dup
    invokespecial java/lang/StringBuilder <init>:()V
    aload 9
    getfield fb ds:[I
    iload 0
    iaload
    invokevirtual java/lang/StringBuilder append:(I)Ljava/lang/StringBuilder;
    ldc " x " (java.lang.String)
    invokevirtual java/lang/StringBuilder append:(Ljava/lang/String;)Ljava/lang/StringBuilder;
    iload 3
    bipush -44
    invokestatic dj e:(IB)Lad;
    getfield ad j:Ljava/lang/String;
    invokevirtual java/lang/StringBuilder append:(Ljava/lang/String;)Ljava/lang/StringBuilder;
    invokevirtual java/lang/StringBuilder toString:()Ljava/lang/String;
    ldc -469509544 (java.lang.Integer)
    invokestatic c a:(ILjava/lang/String;Ljava/lang/String;I)V
    goto L519
L540
    bipush 46
    iload 2
    if_icmpne L548
    iload 8
    ldc 1590767131 (java.lang.Integer)
    if_icmpne L555
    new java/lang/IllegalStateException
    dup
    invokespecial java/lang/IllegalStateException <init>:()V
    athrow
L54
    getstatic client cd:Ldj;
    iload 3
    bipush 8
    invokevirtual dj an:(IB)V
    goto L519
L606
    getstatic client cd:Ldj;
    bipush 105
    ldc 548638077 (java.lang.Integer)
    invokevirtual dj hl:(II)V
    goto L214
L406
    getstatic fl l:[I
    iload 10
    aload 9
    getfield fb dm:[I
    iconst_0
    iaload
    iastore
    goto L244
L312
    ldc -1001862243 (java.lang.Integer)
    iload 0
    imul
    putstatic client gw:I
L93
    bipush 49
    iload 2
    if_icmpne L678
    iload 8
    ldc 1590767131 (java.lang.Integer)
    if_icmpne L612
    new java/lang/IllegalStateException
    dup
    invokespecial java/lang/IllegalStateException <init>:()V
    athrow
L594
    bipush -116
    invokestatic a cs:(B)V
    goto L593
L685
    iload 2
    bipush 28
    if_icmpne L159
    iload 8
    ldc 1590767131 (java.lang.Integer)
    if_icmpne L695
    new java/lang/IllegalStateException
    dup
    invokespecial java/lang/IllegalStateException <init>:()V
    athrow
L761
    ldc 1135862533 (java.lang.Integer)
    iload 6
    imul
    putstatic client gs:I
    goto L534
L627
    iload 3
    iconst_1
    isub
    istore 15
    goto L449
L318
    getstatic client cd:Ldj;
    iload 3
    bipush 126
    invokevirtual dj an:(IB)V
    goto L25
L762
    iconst_0
    putstatic client gj:I
L763
    ldc -467606121 (java.lang.Integer)
    iload 0
    imul
    putstatic client mm:I
    goto L363
L535
    ldc -100126598 (java.lang.Integer)
    putstatic client gd:I
    goto L762
L364
    getstatic client cd:Ldj;
    sipush 248
    ldc -1936494926 (java.lang.Integer)
    invokevirtual dj hl:(II)V
L764
    getstatic client cd:Ldj;
    iload 3
    ldc 2068942624 (java.lang.Integer)
    invokevirtual dj af:(II)V
    goto L703
L145
    getstatic client cd:Ldj;
    sipush 230
    ldc -284352849 (java.lang.Integer)
    invokevirtual dj hl:(II)V
    goto L63
L68
    getstatic client cd:Ldj;
    iload 0
    bipush -59
    invokevirtual dj a:(IB)V
    goto L434
L704
    iconst_0
    goto L108
L751
    getstatic client cd:Ldj;
    bipush 75
    ldc 342610386 (java.lang.Integer)
    invokevirtual dj hl:(II)V
    goto L459
L446
    getstatic client cd:Ldj;
    iload 0
    bipush 73
    invokevirtual dj a:(IB)V
    goto L448
L750
    ldc 1135862533 (java.lang.Integer)
    iload 6
    imul
    putstatic client gs:I
    goto L747
L310
    getstatic client cd:Ldj;
    getstatic client ja:I
    ldc -1424280981 (java.lang.Integer)
    imul
    bipush 54
    invokevirtual dj an:(IB)V
    goto L297
L748
    ldc -100126598 (java.lang.Integer)
    putstatic client gd:I
    goto L381
L738
    aconst_null
    aload 9
    if_acmpeq L115
    goto L95
L757
    iload 1
    ldc -2068421293 (java.lang.Integer)
    invokestatic f a:(II)Lfb;
    putstatic dp gl:Lfb;
    goto L151
L613
    aload 9
    ifnull L678
    goto L761
L387
    getstatic client cd:Ldj;
    bipush 71
    ldc -1384361401 (java.lang.Integer)
    invokevirtual dj hl:(II)V
L765
    getstatic client cd:Ldj;
    iload 3
    bipush 10
    invokevirtual dj an:(IB)V
    goto L537
L658
    iconst_0
    putstatic client gj:I
    goto L102
L538
    getstatic client cd:Ldj;
    ldc 1565981493 (java.lang.Integer)
    getstatic aj ix:I
    imul
    ldc 1093613557 (java.lang.Integer)
    invokevirtual dj c:(II)V
    goto L719
L385
    aload 9
    ldc -1023277750 (java.lang.Integer)
    invokestatic dh cr:(Lfb;I)V
    goto L700
L720
    getstatic client cd:Ldj;
    getstatic dh iz:I
    ldc 1827663583 (java.lang.Integer)
    imul
    iconst_1
    invokevirtual dj az:(IB)V
L766
    getstatic client cd:Ldj;
    getstatic dr ce:[Z
    bipush 82
    baload
    ifeq L767
    iload 8
    ldc 1590767131 (java.lang.Integer)
    if_icmpne L768
    new java/lang/IllegalStateException
    dup
    invokespecial java/lang/IllegalStateException <init>:()V
    athrow
L768
    iconst_1
    goto L769
L767
    iconst_0
L769
    ldc 1868106078 (java.lang.Integer)
    invokevirtual dj al:(II)V
L770
    getstatic client cd:Ldj;
    ldc 1317226893 (java.lang.Integer)
    getstatic co cz:I
    imul
    iload 1
    iadd
    bipush 78
    invokevirtual dj an:(IB)V
    goto L237
L680
    iconst_0
    goto L682
L239
    iload 6
    ldc 1135862533 (java.lang.Integer)
    imul
    putstatic client gs:I
L771
    iload 7
    ldc 677850631 (java.lang.Integer)
    imul
    putstatic client gk:I
L772
    ldc -100126598 (java.lang.Integer)
    putstatic client gd:I
L773
    iconst_0
    putstatic client gj:I
    goto L527
L112
    getstatic client cd:Ldj;
    iload 3
    ldc 2007176819 (java.lang.Integer)
    invokevirtual dj af:(II)V
    goto L115
L297
    sipush 1004
    iload 2
    if_icmpne L25
    goto L313
L465
    getstatic client cd:Ldj;
    bipush 7
    ldc -42588206 (java.lang.Integer)
    invokevirtual dj hl:(II)V
L774
    getstatic client cd:Ldj;
    iload 1
    ldc 1317226893 (java.lang.Integer)
    getstatic co cz:I
    imul
    iadd
    bipush 68
    invokevirtual dj an:(IB)V
L775
    getstatic client cd:Ldj;
    getstatic dr ce:[Z
    bipush 82
    baload
    ifeq L264
    iload 8
    ldc 1590767131 (java.lang.Integer)
    if_icmpne L776
    return
L776
    iconst_1
    goto L265
L361
    ldc -467606121 (java.lang.Integer)
    iload 0
    imul
    putstatic client mm:I
    goto L507
L225
    getstatic client hg:[Ll;
    iload 3
    aaload
    astore 9
    goto L227
L3
    iinc 2 -2000
    goto L2
L450
    getstatic client cd:Ldj;
    iload 1
    ldc 400765386 (java.lang.Integer)
    invokevirtual dj c:(II)V
    goto L453
L238
    bipush 41
    iload 2
    if_icmpne L339
    iload 8
    ldc 1590767131 (java.lang.Integer)
    if_icmpne L745
    new java/lang/IllegalStateException
    dup
    invokespecial java/lang/IllegalStateException <init>:()V
    athrow
L661
    ldc -100126598 (java.lang.Integer)
    putstatic client gd:I
    goto L662
L746
    getstatic client cd:Ldj;
    iload 1
    ldc 431799581 (java.lang.Integer)
    invokevirtual dj c:(II)V
L777
    getstatic client cd:Ldj;
    iload 0
    bipush 98
    invokevirtual dj an:(IB)V
L778
    getstatic client cd:Ldj;
    iload 3
    iconst_1
    invokevirtual dj az:(IB)V
L779
    iconst_0
    putstatic client gz:I
L780
    iload 1
    ldc -2068421293 (java.lang.Integer)
    invokestatic f a:(II)Lfb;
    putstatic dp gl:Lfb;
L781
    iload 0
    ldc -1001862243 (java.lang.Integer)
    imul
    putstatic client gw:I
    goto L339
L23
    iconst_0
    goto L86
L340
    iconst_0
    putstatic client in:I
    goto L206
L213
    getstatic client cd:Ldj;
    ldc 1824985751 (java.lang.Integer)
    getstatic f jg:I
    imul
    ldc 1923727634 (java.lang.Integer)
    invokevirtual dj bp:(II)V
    goto L721
L207
    getstatic client is:Z
    ifeq L782
    sipush 1003
    invokestatic ai bh:(S)V
L782
    getstatic dp gl:Lfb;
    ifnull L106
    iload 8
    ldc 1590767131 (java.lang.Integer)
    if_icmpne L576
    new java/lang/IllegalStateException
    dup
    invokespecial java/lang/IllegalStateException <init>:()V
    athrow
L373
    aload 10
    ldc 45338973 (java.lang.Integer)
    invokevirtual ay i:(I)Lay;
    astore 10
    goto L372
L668
    iconst_0
    goto L111
L500
    getstatic client cd:Ldj;
    iload 3
    bipush -64
    invokevirtual dj a:(IB)V
    goto L679
L783
    new java/lang/StringBuilder
    dup
    invokespecial java/lang/StringBuilder <init>:()V
    ldc "bj.bi(" (java.lang.String)
    invokevirtual java/lang/StringBuilder append:(Ljava/lang/String;)Ljava/lang/StringBuilder;
    ldc 41 (java.lang.Integer)
    invokevirtual java/lang/StringBuilder append:(C)Ljava/lang/StringBuilder;
    invokevirtual java/lang/StringBuilder toString:()Ljava/lang/String;
    invokestatic k a:(Ljava/lang/Throwable;Ljava/lang/String;)Lee;
    athrow
