bm l (I[IS)Lbe;L1
    aload 0
    getfield bm e:Lfv;
    ldc 815552527 (java.lang.Integer)
    invokevirtual fv j:(I)I
    iconst_1
    if_icmpne L2
    iload 3
    sipush 128
    if_icmplt L3
    new java/lang/IllegalStateException
    dup
    invokespecial java/lang/IllegalStateException <init>:()V
    athrow
L2
    aload 0
    getfield bm e:Lfv;
    iload 1
    ldc 1825151587 (java.lang.Integer)
    invokevirtual fv s:(II)I
    iconst_1
    if_icmpne L4
    iload 3
    sipush 128
    if_icmplt L5
    new java/lang/IllegalStateException
    dup
    invokespecial java/lang/IllegalStateException <init>:()V
    athrow
L4
    new java/lang/RuntimeException
    dup
    invokespecial java/lang/RuntimeException <init>:()V
    athrow
L3
    aload 0
    iconst_0
    iload 1
    aload 2
    ldc 1681324405 (java.lang.Integer)
    invokevirtual bm e:(II[II)Lbe;
    areturn
L5
    aload 0
    iload 1
    iconst_0
    aload 2
    ldc 1956972273 (java.lang.Integer)
    invokevirtual bm e:(II[II)Lbe;
    areturn
L6
    new java/lang/StringBuilder
    dup
    invokespecial java/lang/StringBuilder <init>:()V
    ldc "bm.l(" (java.lang.String)
    invokevirtual java/lang/StringBuilder append:(Ljava/lang/String;)Ljava/lang/StringBuilder;
    ldc 41 (java.lang.Integer)
    invokevirtual java/lang/StringBuilder append:(C)Ljava/lang/StringBuilder;
    invokevirtual java/lang/StringBuilder toString:()Ljava/lang/String;
    invokestatic k a:(Ljava/lang/Throwable;Ljava/lang/String;)Lee;
    athrow
