by af (II)VL1
    getstatic al my:Lbh;
    getfield bh e:[I
    astore 2
    goto L2
L3
    iconst_1
    iload 0
    iadd
    iload 7
    iload 6
    iload 4
    iload 5
    ldc -1176315158 (java.lang.Integer)
    invokestatic au as:(IIIIII)V
    goto L4
L5
    iconst_0
    istore 4
L6
    iload 4
    iload 3
    if_icmpge L7
    iload 1
    ldc -803009863 (java.lang.Integer)
    if_icmplt L8
    new java/lang/IllegalStateException
    dup
    invokespecial java/lang/IllegalStateException <init>:()V
    athrow
L8
    aload 2
    iload 4
    iconst_0
    iastore
    iinc 4 1
    goto L6
L7
    iconst_1
    istore 4
L9
    iload 4
    bipush 103
    if_icmpge L10
    iload 1
    ldc -803009863 (java.lang.Integer)
    if_icmplt L11
    new java/lang/IllegalStateException
    dup
    invokespecial java/lang/IllegalStateException <init>:()V
    athrow
L11
    sipush 24628
    sipush 2048
    bipush 103
    iload 4
    isub
    imul
    iadd
    istore 5
L12
    iconst_1
    istore 6
    goto L13
L14
    iload 10
    iconst_3
    iload 6
    iadd
    if_icmpge L15
    iload 1
    ldc -803009863 (java.lang.Integer)
    if_icmplt L16
    new java/lang/IllegalStateException
    dup
    invokespecial java/lang/IllegalStateException <init>:()V
    athrow
L17
    iinc 6 1
    goto L18
L19
    getstatic n ds:Lcb;
    aload 2
    iload 5
    sipush 512
    iload 0
    iload 6
    iload 4
    invokevirtual cb ab:([IIIIII)V
    goto L20
L21
    iload 6
    bipush 103
    if_icmpge L22
    goto L23
L24
    getstatic w a:[[[B
    iload 0
    iconst_1
    iadd
    aaload
    iload 6
    aaload
    iload 4
    baload
    bipush 8
    iand
    ifeq L25
    iload 1
    ldc -803009863 (java.lang.Integer)
    if_icmplt L26
    new java/lang/IllegalStateException
    dup
    invokespecial java/lang/IllegalStateException <init>:()V
    athrow
L26
    getstatic n ds:Lcb;
    aload 2
    iload 5
    sipush 512
    iload 0
    iconst_1
    iadd
    iload 6
    iload 4
    invokevirtual cb ab:([IIIIII)V
    goto L25
L27
    iinc 6 1
    goto L21
L28
    iinc 6 1
    goto L13
L29
    iinc 4 1
    goto L9
L10
    sipush 238
    invokestatic java/lang/Math random:()D
    ldc 20.0 (java.lang.Double)
    dmul
    d2i
    iadd
    bipush 10
    isub
    bipush 16
    ishl
    sipush 238
    invokestatic java/lang/Math random:()D
    ldc 20.0 (java.lang.Double)
    dmul
    d2i
    iadd
    bipush 10
    isub
    bipush 8
    ishl
    iadd
    sipush 238
    invokestatic java/lang/Math random:()D
    ldc 20.0 (java.lang.Double)
    dmul
    d2i
    iadd
    bipush 10
    isub
    iadd
    istore 4
    goto L30
L4
    iinc 7 1
    goto L31
L32
    getstatic n ds:Lcb;
    getstatic fd hz:I
    ldc -837647185 (java.lang.Integer)
    imul
    iload 6
    iload 7
    invokevirtual cb ai:(III)I
    istore 8
    goto L33
L34
    iload 10
    iload 6
    iconst_3
    isub
    if_icmple L35
    iload 1
    ldc -803009863 (java.lang.Integer)
    if_icmplt L36
    new java/lang/IllegalStateException
    dup
    invokespecial java/lang/IllegalStateException <init>:()V
    athrow
L37
    iconst_0
    istore 15
    goto L38
L23
    iconst_1
    istore 7
    goto L31
L39
    return
L40
    getstatic w a:[[[B
    iload 0
    aaload
    iload 7
    aaload
    iload 6
    baload
    bipush 24
    iand
    ifne L41
    iload 1
    ldc -803009863 (java.lang.Integer)
    if_icmplt L42
    return
L42
    iload 0
    iload 7
    iload 6
    iload 4
    iload 5
    ldc -1831115567 (java.lang.Integer)
    invokestatic au as:(IIIIII)V
    goto L41
L18
    iload 6
    bipush 104
    if_icmpge L43
    iload 1
    ldc -803009863 (java.lang.Integer)
    if_icmplt L44
    new java/lang/IllegalStateException
    dup
    invokespecial java/lang/IllegalStateException <init>:()V
    athrow
L45
    iconst_0
    getstatic w a:[[[B
    iload 0
    iconst_1
    iadd
    aaload
    iload 7
    aaload
    iload 6
    baload
    bipush 8
    iand
    if_icmpeq L4
    goto L3
L46
    getstatic client w:[Lhk;
    getstatic fd hz:I
    ldc -837647185 (java.lang.Integer)
    imul
    aaload
    getfield hk ai:[[I
    astore 14
    goto L37
L47
    bipush 29
    iload 9
    if_icmpeq L48
    iload 1
    ldc -803009863 (java.lang.Integer)
    if_icmplt L49
    new java/lang/IllegalStateException
    dup
    invokespecial java/lang/IllegalStateException <init>:()V
    athrow
L50
    iload 16
    iconst_3
    if_icmpne L51
    iload 1
    ldc -803009863 (java.lang.Integer)
    if_icmplt L52
    new java/lang/IllegalStateException
    dup
    invokespecial java/lang/IllegalStateException <init>:()V
    athrow
L22
    iconst_0
    putstatic client mw:I
L53
    iconst_0
    istore 6
    goto L18
L54
    getstatic al my:Lbh;
    invokevirtual bh a:()V
    goto L55
L44
    iconst_0
    istore 7
L56
    iload 7
    bipush 104
    if_icmpge L17
    goto L32
L57
    getstatic w a:[[[B
    iload 0
    aaload
    iload 6
    aaload
    iload 4
    baload
    bipush 24
    iand
    ifne L20
    iload 1
    ldc -803009863 (java.lang.Integer)
    if_icmplt L19
    new java/lang/IllegalStateException
    dup
    invokespecial java/lang/IllegalStateException <init>:()V
    athrow
L58
    bipush 46
    iload 9
    if_icmpeq L48
    iload 1
    ldc -803009863 (java.lang.Integer)
    if_icmplt L59
    new java/lang/IllegalStateException
    dup
    invokespecial java/lang/IllegalStateException <init>:()V
    athrow
L60
    iload 8
    bipush 14
    ishr
    sipush 32767
    iand
    istore 8
L61
    iload 8
    bipush -55
    invokestatic m e:(IB)Lag;
    getfield ag ai:I
    ldc 1988167411 (java.lang.Integer)
    imul
    istore 9
L62
    iload 9
    iflt L63
    iload 1
    ldc -803009863 (java.lang.Integer)
    if_icmplt L64
    return
L59
    bipush 47
    iload 9
    if_icmpeq L48
    iload 1
    ldc -803009863 (java.lang.Integer)
    if_icmplt L65
    new java/lang/IllegalStateException
    dup
    invokespecial java/lang/IllegalStateException <init>:()V
    athrow
L66
    iload 7
    istore 11
L67
    bipush 22
    iload 9
    if_icmpeq L48
    iload 1
    ldc -803009863 (java.lang.Integer)
    if_icmplt L47
    new java/lang/IllegalStateException
    dup
    invokespecial java/lang/IllegalStateException <init>:()V
    athrow
L30
    sipush 238
    invokestatic java/lang/Math random:()D
    ldc 20.0 (java.lang.Double)
    dmul
    d2i
    iadd
    bipush 10
    isub
    bipush 16
    ishl
    istore 5
    goto L54
L49
    bipush 34
    iload 9
    if_icmpeq L48
    goto L68
L20
    iload 0
    iconst_3
    if_icmpge L25
    iload 1
    ldc -803009863 (java.lang.Integer)
    if_icmplt L24
    new java/lang/IllegalStateException
    dup
    invokespecial java/lang/IllegalStateException <init>:()V
    athrow
L41
    iload 0
    iconst_3
    if_icmpge L4
    iload 1
    ldc -803009863 (java.lang.Integer)
    if_icmplt L45
    new java/lang/IllegalStateException
    dup
    invokespecial java/lang/IllegalStateException <init>:()V
    athrow
L65
    iload 9
    bipush 48
    if_icmpeq L48
    iload 1
    ldc -803009863 (java.lang.Integer)
    if_icmplt L46
    new java/lang/IllegalStateException
    dup
    invokespecial java/lang/IllegalStateException <init>:()V
    athrow
L69
    iinc 11 -1
    goto L50
L70
    getstatic client mb:[I
    ldc 531970677 (java.lang.Integer)
    getstatic client mw:I
    imul
    iload 10
    iastore
    goto L71
L2
    aload 2
    arraylength
    istore 3
    goto L5
L38
    iload 15
    bipush 10
    if_icmpge L48
    iload 1
    ldc -803009863 (java.lang.Integer)
    if_icmplt L72
    return
L72
    invokestatic java/lang/Math random:()D
    ldc 4.0 (java.lang.Double)
    dmul
    d2i
    istore 16
L73
    iload 16
    ifne L35
    iload 1
    ldc -803009863 (java.lang.Integer)
    if_icmplt L74
    new java/lang/IllegalStateException
    dup
    invokespecial java/lang/IllegalStateException <init>:()V
    athrow
L75
    getstatic client mw:I
    ldc 826230237 (java.lang.Integer)
    iadd
    putstatic client mw:I
    goto L63
L43
    getstatic v py:Lbz;
    ldc -690756826 (java.lang.Integer)
    invokevirtual bz ae:(I)V
    goto L39
L36
    aload 14
    iload 10
    iconst_1
    isub
    aaload
    iload 11
    iaload
    ldc 19136776 (java.lang.Integer)
    iand
    ifne L35
    iinc 10 -1
L35
    iload 16
    iconst_1
    if_icmpne L15
    iload 1
    ldc -803009863 (java.lang.Integer)
    if_icmplt L76
    new java/lang/IllegalStateException
    dup
    invokespecial java/lang/IllegalStateException <init>:()V
    athrow
L76
    iload 10
    bipush 103
    if_icmpge L15
    iload 1
    ldc -803009863 (java.lang.Integer)
    if_icmplt L14
    new java/lang/IllegalStateException
    dup
    invokespecial java/lang/IllegalStateException <init>:()V
    athrow
L68
    bipush 36
    iload 9
    if_icmpeq L48
    iload 1
    ldc -803009863 (java.lang.Integer)
    if_icmplt L58
    new java/lang/IllegalStateException
    dup
    invokespecial java/lang/IllegalStateException <init>:()V
    athrow
L16
    iconst_0
    aload 14
    iload 10
    iconst_1
    iadd
    aaload
    iload 11
    iaload
    ldc 19136896 (java.lang.Integer)
    iand
    if_icmpne L15
    iload 1
    ldc -803009863 (java.lang.Integer)
    if_icmplt L77
    new java/lang/IllegalStateException
    dup
    invokespecial java/lang/IllegalStateException <init>:()V
    athrow
L77
    iinc 10 1
L15
    iload 16
    iconst_2
    if_icmpne L50
    iload 1
    ldc -803009863 (java.lang.Integer)
    if_icmplt L78
    new java/lang/IllegalStateException
    dup
    invokespecial java/lang/IllegalStateException <init>:()V
    athrow
L78
    iload 11
    ifle L50
    iload 1
    ldc -803009863 (java.lang.Integer)
    if_icmplt L79
    new java/lang/IllegalStateException
    dup
    invokespecial java/lang/IllegalStateException <init>:()V
    athrow
L79
    iload 11
    iload 7
    iconst_3
    isub
    if_icmple L50
    iload 1
    ldc -803009863 (java.lang.Integer)
    if_icmplt L80
    new java/lang/IllegalStateException
    dup
    invokespecial java/lang/IllegalStateException <init>:()V
    athrow
L80
    iconst_0
    aload 14
    iload 10
    aaload
    iload 11
    iconst_1
    isub
    iaload
    ldc 19136770 (java.lang.Integer)
    iand
    if_icmpne L50
    iload 1
    ldc -803009863 (java.lang.Integer)
    if_icmplt L69
    new java/lang/IllegalStateException
    dup
    invokespecial java/lang/IllegalStateException <init>:()V
    athrow
L74
    iload 10
    ifle L35
    iload 1
    ldc -803009863 (java.lang.Integer)
    if_icmplt L34
    new java/lang/IllegalStateException
    dup
    invokespecial java/lang/IllegalStateException <init>:()V
    athrow
L25
    iinc 5 4
    goto L28
L52
    iload 11
    bipush 103
    if_icmpge L51
    iload 1
    ldc -803009863 (java.lang.Integer)
    if_icmplt L81
    return
L81
    iload 11
    iconst_3
    iload 7
    iadd
    if_icmpge L51
    iload 1
    ldc -803009863 (java.lang.Integer)
    if_icmplt L82
    new java/lang/IllegalStateException
    dup
    invokespecial java/lang/IllegalStateException <init>:()V
    athrow
L13
    iload 6
    bipush 103
    if_icmpge L29
    iload 1
    ldc -803009863 (java.lang.Integer)
    if_icmplt L57
    new java/lang/IllegalStateException
    dup
    invokespecial java/lang/IllegalStateException <init>:()V
    athrow
L83
    iinc 11 1
L51
    iinc 15 1
    goto L38
L48
    getstatic client mg:[Lbh;
    getstatic client mw:I
    ldc 531970677 (java.lang.Integer)
    imul
    getstatic gc ee:[Lbh;
    iload 9
    aaload
    aastore
    goto L70
L31
    iload 7
    bipush 103
    if_icmpge L27
    iload 1
    ldc -803009863 (java.lang.Integer)
    if_icmplt L40
    new java/lang/IllegalStateException
    dup
    invokespecial java/lang/IllegalStateException <init>:()V
    athrow
L71
    getstatic client me:[I
    ldc 531970677 (java.lang.Integer)
    getstatic client mw:I
    imul
    iload 11
    iastore
    goto L75
L64
    iload 6
    istore 10
    goto L66
L63
    iinc 7 1
    goto L56
L33
    iconst_0
    iload 8
    if_icmpeq L63
    iload 1
    ldc -803009863 (java.lang.Integer)
    if_icmplt L60
    new java/lang/IllegalStateException
    dup
    invokespecial java/lang/IllegalStateException <init>:()V
    athrow
L55
    iconst_1
    istore 6
    goto L21
L82
    aload 14
    iload 10
    aaload
    iconst_1
    iload 11
    iadd
    iaload
    ldc 19136800 (java.lang.Integer)
    iand
    ifne L51
    iload 1
    ldc -803009863 (java.lang.Integer)
    if_icmplt L83
    new java/lang/IllegalStateException
    dup
    invokespecial java/lang/IllegalStateException <init>:()V
    athrow
L84
    new java/lang/StringBuilder
    dup
    invokespecial java/lang/StringBuilder <init>:()V
    ldc "by.af(" (java.lang.String)
    invokevirtual java/lang/StringBuilder append:(Ljava/lang/String;)Ljava/lang/StringBuilder;
    ldc 41 (java.lang.Integer)
    invokevirtual java/lang/StringBuilder append:(C)Ljava/lang/StringBuilder;
    invokevirtual java/lang/StringBuilder toString:()Ljava/lang/String;
    invokestatic k a:(Ljava/lang/Throwable;Ljava/lang/String;)Lee;
    athrow
