by cm (Lfb;I)ZL1
    aconst_null
    aload 0
    getfield fb du:[I
    if_acmpne L2
    goto L3
L4
    iinc 2 1
    goto L5
L6
    iload 4
    iload 3
    if_icmpeq L4
    iload 1
    ldc 927312292 (java.lang.Integer)
    if_icmpgt L7
    new java/lang/IllegalStateException
    dup
    invokespecial java/lang/IllegalStateException <init>:()V
    athrow
L8
    aload 0
    getfield fb du:[I
    iload 2
    iaload
    iconst_2
    if_icmpne L9
    iload 1
    ldc 927312292 (java.lang.Integer)
    if_icmpgt L10
    new java/lang/IllegalStateException
    dup
    invokespecial java/lang/IllegalStateException <init>:()V
    athrow
L11
    iconst_0
    ireturn
L12
    aload 0
    getfield fb dm:[I
    iload 2
    iaload
    istore 4
    goto L8
L13
    iconst_1
    ireturn
L10
    iload 3
    iload 4
    if_icmplt L4
    iload 1
    ldc 927312292 (java.lang.Integer)
    if_icmpgt L14
    new java/lang/IllegalStateException
    dup
    invokespecial java/lang/IllegalStateException <init>:()V
    athrow
L14
    iconst_0
    ireturn
L9
    aload 0
    getfield fb du:[I
    iload 2
    iaload
    iconst_3
    if_icmpne L15
    iload 1
    ldc 927312292 (java.lang.Integer)
    if_icmpgt L16
    new java/lang/IllegalStateException
    dup
    invokespecial java/lang/IllegalStateException <init>:()V
    athrow
L16
    iload 3
    iload 4
    if_icmpgt L4
    goto L11
L17
    aload 0
    iload 2
    ldc -1285737891 (java.lang.Integer)
    invokestatic r cj:(Lfb;II)I
    istore 3
    goto L12
L15
    iconst_4
    aload 0
    getfield fb du:[I
    iload 2
    iaload
    if_icmpne L6
    iload 1
    ldc 927312292 (java.lang.Integer)
    if_icmpgt L18
    new java/lang/IllegalStateException
    dup
    invokespecial java/lang/IllegalStateException <init>:()V
    athrow
L18
    iload 4
    iload 3
    if_icmpne L4
    iload 1
    ldc 927312292 (java.lang.Integer)
    if_icmpgt L19
    new java/lang/IllegalStateException
    dup
    invokespecial java/lang/IllegalStateException <init>:()V
    athrow
L19
    iconst_0
    ireturn
L2
    iconst_0
    istore 2
    goto L5
L7
    iconst_0
    ireturn
L3
    iconst_0
    ireturn
L5
    iload 2
    aload 0
    getfield fb du:[I
    arraylength
    if_icmpge L13
    goto L17
L20
    new java/lang/StringBuilder
    dup
    invokespecial java/lang/StringBuilder <init>:()V
    ldc "by.cm(" (java.lang.String)
    invokevirtual java/lang/StringBuilder append:(Ljava/lang/String;)Ljava/lang/StringBuilder;
    ldc 41 (java.lang.Integer)
    invokevirtual java/lang/StringBuilder append:(C)Ljava/lang/StringBuilder;
    invokevirtual java/lang/StringBuilder toString:()Ljava/lang/String;
    invokestatic k a:(Ljava/lang/Throwable;Ljava/lang/String;)Lee;
    athrow
