bz u (Ldh;IIIIIIB)VL1
    iload 2
    iflt L2
    goto L3
L4
    iconst_1
    iload 8
    if_icmpne L5
    iload 7
    bipush 16
    if_icmpeq L6
    return
L7
    getstatic w e:[[[I
    iload 1
    aaload
    iload 2
    aaload
    iload 3
    getstatic w e:[[[I
    iload 1
    iconst_1
    isub
    aaload
    iload 2
    aaload
    iload 3
    iaload
    bipush 8
    iload 9
    imul
    isub
    iastore
    goto L8
L9
    iload 3
    bipush 104
    if_icmpge L2
    iload 7
    bipush 16
    if_icmpeq L10
    new java/lang/IllegalStateException
    dup
    invokespecial java/lang/IllegalStateException <init>:()V
    athrow
L10
    getstatic w a:[[[B
    iload 1
    aaload
    iload 2
    aaload
    iload 3
    iconst_0
    bastore
    goto L11
L12
    iload 3
    iflt L2
    iload 7
    bipush 16
    if_icmpeq L9
    new java/lang/IllegalStateException
    dup
    invokespecial java/lang/IllegalStateException <init>:()V
    athrow
L13
    iconst_0
    iload 8
    if_icmpne L4
    goto L14
L15
    getstatic bz i:[[[B
    iload 1
    aaload
    iload 2
    aaload
    iload 3
    iload 8
    iconst_2
    isub
    iload 6
    iadd
    iconst_3
    iand
    i2b
    bastore
    goto L16
L17
    getstatic w e:[[[I
    iconst_0
    aaload
    iload 2
    aaload
    iload 3
    iload 4
    iload 2
    ldc 932731 (java.lang.Integer)
    iadd
    iadd
    iload 5
    iload 3
    ldc 556238 (java.lang.Integer)
    iadd
    iadd
    ldc -1789935039 (java.lang.Integer)
    invokestatic eu f:(III)I
    ineg
    bipush 8
    imul
    iastore
    goto L18
L19
    getstatic w e:[[[I
    iload 1
    aaload
    iload 2
    aaload
    iload 3
    getstatic w e:[[[I
    iload 1
    iconst_1
    isub
    aaload
    iload 2
    aaload
    iload 3
    iaload
    sipush 240
    isub
    iastore
    goto L20
L21
    iconst_0
    iload 8
    if_icmpne L22
    goto L23
L11
    aload 0
    ldc 779451213 (java.lang.Integer)
    invokevirtual dh z:(I)I
    istore 8
    goto L13
L6
    aload 0
    ldc 905732936 (java.lang.Integer)
    invokevirtual dh z:(I)I
    istore 9
    goto L24
L25
    getstatic w a:[[[B
    iload 1
    aaload
    iload 2
    aaload
    iload 3
    iload 8
    bipush 49
    isub
    i2b
    bastore
    goto L26
L27
    iconst_0
    istore 9
L28
    iload 1
    ifne L7
    iload 7
    bipush 16
    if_icmpeq L29
    new java/lang/IllegalStateException
    dup
    invokespecial java/lang/IllegalStateException <init>:()V
    athrow
L30
    getstatic w c:[[[B
    iload 1
    aaload
    iload 2
    aaload
    iload 3
    iload 8
    bipush 81
    isub
    i2b
    bastore
    goto L31
L8
    goto L18
L32
    iload 8
    bipush 49
    if_icmpgt L33
    iload 7
    bipush 16
    if_icmpeq L34
    return
L5
    iload 8
    bipush 49
    if_icmpgt L35
    iload 7
    bipush 16
    if_icmpeq L36
    new java/lang/IllegalStateException
    dup
    invokespecial java/lang/IllegalStateException <init>:()V
    athrow
L36
    getstatic hg u:[[[B
    iload 1
    aaload
    iload 2
    aaload
    iload 3
    aload 0
    bipush 98
    invokevirtual dh y:(B)B
    bastore
L37
    getstatic w w:[[[B
    iload 1
    aaload
    iload 2
    aaload
    iload 3
    iload 8
    iconst_2
    isub
    iconst_4
    idiv
    i2b
    bastore
    goto L15
L16
    goto L11
L20
    goto L18
L35
    iload 8
    bipush 81
    if_icmpgt L30
    iload 7
    bipush 16
    if_icmpeq L25
    new java/lang/IllegalStateException
    dup
    invokespecial java/lang/IllegalStateException <init>:()V
    athrow
L29
    getstatic w e:[[[I
    iconst_0
    aaload
    iload 2
    aaload
    iload 3
    bipush 8
    iload 9
    ineg
    imul
    iastore
    goto L18
L24
    iconst_1
    iload 9
    if_icmpne L28
    iload 7
    bipush 16
    if_icmpeq L27
    new java/lang/IllegalStateException
    dup
    invokespecial java/lang/IllegalStateException <init>:()V
    athrow
L3
    iload 2
    bipush 104
    if_icmpge L2
    iload 7
    bipush 16
    if_icmpeq L12
    new java/lang/IllegalStateException
    dup
    invokespecial java/lang/IllegalStateException <init>:()V
    athrow
L31
    goto L11
L2
    aload 0
    ldc 1910132476 (java.lang.Integer)
    invokevirtual dh z:(I)I
    istore 8
    goto L21
L26
    goto L11
L23
    goto L18
L22
    iload 8
    iconst_1
    if_icmpne L32
    iload 7
    bipush 16
    if_icmpeq L38
    new java/lang/IllegalStateException
    dup
    invokespecial java/lang/IllegalStateException <init>:()V
    athrow
L38
    aload 0
    ldc 1663877556 (java.lang.Integer)
    invokevirtual dh z:(I)I
    pop
L39
    goto L18
L34
    aload 0
    ldc 1269046005 (java.lang.Integer)
    invokevirtual dh z:(I)I
    pop
    goto L33
L14
    iload 1
    ifne L19
    iload 7
    bipush 16
    if_icmpeq L17
    new java/lang/IllegalStateException
    dup
    invokespecial java/lang/IllegalStateException <init>:()V
    athrow
L33
    goto L2
L18
    return
L40
    new java/lang/StringBuilder
    dup
    invokespecial java/lang/StringBuilder <init>:()V
    ldc "bz.u(" (java.lang.String)
    invokevirtual java/lang/StringBuilder append:(Ljava/lang/String;)Ljava/lang/StringBuilder;
    ldc 41 (java.lang.Integer)
    invokevirtual java/lang/StringBuilder append:(C)Ljava/lang/StringBuilder;
    invokevirtual java/lang/StringBuilder toString:()Ljava/lang/String;
    invokestatic k a:(Ljava/lang/Throwable;Ljava/lang/String;)Lee;
    athrow
