c ad (IIIIIB)VL1
    getstatic bz dd:I
    ldc -1416841643 (java.lang.Integer)
    imul
    iload 0
    if_icmpne L2
    iload 5
    iconst_0
    if_icmplt L3
    return
L4
    iconst_0
    istore 12
    goto L5
L6
    iload 2
    getstatic client ca:I
    ldc 633325001 (java.lang.Integer)
    imul
    if_icmpeq L7
    iload 5
    iconst_0
    if_icmplt L8
    new java/lang/IllegalStateException
    dup
    invokespecial java/lang/IllegalStateException <init>:()V
    athrow
L8
    getstatic client h:Z
    ifne L2
    iload 5
    iconst_0
    if_icmplt L7
    new java/lang/IllegalStateException
    dup
    invokespecial java/lang/IllegalStateException <init>:()V
    athrow
L7
    return
L9
    getstatic client hl:Lgh;
    invokevirtual gh f:()Lgm;
    checkcast t
    astore 16
    goto L10
L11
    iconst_0
    istore 20
    goto L12
L13
    ldc 168290855 (java.lang.Integer)
    getstatic client mm:I
    imul
    ifeq L14
    goto L15
L16
    ldc 1317226893 (java.lang.Integer)
    getstatic co cz:I
    imul
    istore 7
    goto L17
L18
    iconst_0
    putstatic client ca:I
L19
    bipush 25
    bipush 70
    invokestatic dh g:(IB)V
    goto L20
L21
    iload 14
    iload 17
    if_icmpeq L22
    iload 5
    iconst_0
    if_icmplt L23
    new java/lang/IllegalStateException
    dup
    invokespecial java/lang/IllegalStateException <init>:()V
    athrow
L24
    getstatic x cs:I
    ldc 616886125 (java.lang.Integer)
    imul
    istore 6
    goto L16
L25
    iload 9
    ifge L26
    iload 5
    iconst_0
    if_icmplt L27
    new java/lang/IllegalStateException
    dup
    invokespecial java/lang/IllegalStateException <init>:()V
    athrow
L17
    iload 0
    bipush 6
    isub
    ldc 1348178728 (java.lang.Integer)
    imul
    putstatic x cs:I
    goto L28
L29
    iconst_1
    istore 12
    goto L30
L31
    getstatic x cs:I
    ldc 616886125 (java.lang.Integer)
    imul
    iload 6
    isub
    istore 8
    goto L32
L33
    getstatic client h:Z
    ifne L19
    iload 5
    iconst_0
    if_icmplt L18
    new java/lang/IllegalStateException
    dup
    invokespecial java/lang/IllegalStateException <init>:()V
    athrow
L34
    getstatic x cs:I
    ldc 616886125 (java.lang.Integer)
    imul
    istore 6
L35
    ldc 1317226893 (java.lang.Integer)
    getstatic co cz:I
    imul
    istore 7
L36
    iconst_0
    istore 10
L37
    iload 10
    ldc 32768 (java.lang.Integer)
    if_icmpge L38
    iload 5
    iconst_0
    if_icmplt L39
    new java/lang/IllegalStateException
    dup
    invokespecial java/lang/IllegalStateException <init>:()V
    athrow
L39
    getstatic client cf:[Lam;
    iload 10
    aaload
    astore 11
    goto L40
L41
    aload 11
    getfield am bs:[I
    iload 12
    dup2
    iaload
    iload 8
    isub
    iastore
    goto L42
L43
    iconst_0
    istore 12
    goto L44
L45
    getstatic client mz:I
    ldc 1754300735 (java.lang.Integer)
    iload 9
    imul
    isub
    putstatic client mz:I
    goto L14
L46
    aload 16
    invokevirtual t if:()V
    goto L9
L42
    aload 11
    getfield am bo:[I
    iload 12
    dup2
    iaload
    iload 9
    isub
    iastore
L47
    iinc 12 1
    goto L44
L48
    aload 11
    dup
    getfield am b:I
    iload 8
    ldc -325767552 (java.lang.Integer)
    imul
    isub
    putfield am b:I
L49
    aload 11
    dup
    getfield am x:I
    ldc -303027584 (java.lang.Integer)
    iload 9
    imul
    isub
    putfield am x:I
L50
    iinc 10 1
    goto L37
L51
    iconst_0
    istore 13
    goto L52
L53
    iload 10
    sipush 2048
    if_icmpge L54
    iload 5
    iconst_0
    if_icmplt L55
    new java/lang/IllegalStateException
    dup
    invokespecial java/lang/IllegalStateException <init>:()V
    athrow
L55
    getstatic client hg:[Ll;
    iload 10
    aaload
    astore 11
L56
    aconst_null
    aload 11
    if_acmpeq L57
    iload 5
    iconst_0
    if_icmplt L4
    new java/lang/IllegalStateException
    dup
    invokespecial java/lang/IllegalStateException <init>:()V
    athrow
L58
    iload 1
    ldc 1601492193 (java.lang.Integer)
    imul
    putstatic fa dk:I
    goto L59
L5
    iload 12
    bipush 10
    if_icmpge L60
    iload 5
    iconst_0
    if_icmplt L61
    new java/lang/IllegalStateException
    dup
    invokespecial java/lang/IllegalStateException <init>:()V
    athrow
L61
    aload 11
    getfield l bs:[I
    iload 12
    dup2
    iaload
    iload 8
    isub
    iastore
L62
    aload 11
    getfield l bo:[I
    iload 12
    dup2
    iaload
    iload 9
    isub
    iastore
    goto L63
L2
    iload 0
    ldc 1286772477 (java.lang.Integer)
    imul
    putstatic bz dd:I
    goto L58
L60
    aload 11
    dup
    getfield l b:I
    iload 8
    ldc -325767552 (java.lang.Integer)
    imul
    isub
    putfield l b:I
L64
    aload 11
    dup
    getfield l x:I
    ldc -303027584 (java.lang.Integer)
    iload 9
    imul
    isub
    putfield l x:I
L57
    iinc 10 1
    goto L53
L54
    ldc -150515121 (java.lang.Integer)
    iload 2
    imul
    putstatic fd hz:I
L65
    getstatic hg hv:Ll;
    iload 3
    iload 4
    iconst_0
    ldc 559114623 (java.lang.Integer)
    invokevirtual l t:(IIZI)V
    goto L66
L67
    iload 19
    iflt L68
    iload 5
    iconst_0
    if_icmplt L69
    new java/lang/IllegalStateException
    dup
    invokespecial java/lang/IllegalStateException <init>:()V
    athrow
L70
    bipush 104
    istore 11
    goto L29
L22
    iload 16
    iload 12
    iadd
    istore 16
    goto L71
L72
    return
L73
    bipush 103
    istore 10
L74
    iconst_m1
    istore 11
L75
    iconst_m1
    istore 12
    goto L51
L20
    getstatic et o:Ljava/lang/String;
    iconst_1
    ldc -714308640 (java.lang.Integer)
    invokestatic dm av:(Ljava/lang/String;ZI)V
    goto L24
L52
    bipush 104
    istore 14
L76
    iconst_1
    istore 15
    goto L25
L66
    iconst_0
    istore 10
    goto L70
L77
    getstatic client hx:[[[Lgh;
    iload 20
    aaload
    iload 16
    aaload
    iload 17
    getstatic client hx:[[[Lgh;
    iload 20
    aaload
    iload 18
    aaload
    iload 19
    aaload
    aastore
    goto L78
L79
    iconst_m1
    istore 14
    goto L80
L38
    iconst_0
    istore 10
    goto L53
L26
    iload 10
    istore 16
    goto L71
L44
    iload 12
    bipush 10
    if_icmpge L48
    goto L41
L81
    iload 13
    istore 17
    goto L21
L59
    ldc -1764662151 (java.lang.Integer)
    iload 2
    imul
    putstatic client ca:I
    goto L33
L63
    iinc 12 1
    goto L5
L23
    iload 8
    iload 16
    iadd
    istore 18
L82
    iload 9
    iload 17
    iadd
    istore 19
    goto L11
L12
    iload 20
    iconst_4
    if_icmpge L83
    iload 5
    iconst_0
    if_icmplt L84
    new java/lang/IllegalStateException
    dup
    invokespecial java/lang/IllegalStateException <init>:()V
    athrow
L84
    iload 18
    iflt L68
    iload 5
    iconst_0
    if_icmplt L67
    new java/lang/IllegalStateException
    dup
    invokespecial java/lang/IllegalStateException <init>:()V
    athrow
L30
    iload 8
    ifge L51
    iload 5
    iconst_0
    if_icmplt L73
    new java/lang/IllegalStateException
    dup
    invokespecial java/lang/IllegalStateException <init>:()V
    athrow
L40
    aconst_null
    aload 11
    if_acmpeq L50
    iload 5
    iconst_0
    if_icmplt L43
    new java/lang/IllegalStateException
    dup
    invokespecial java/lang/IllegalStateException <init>:()V
    athrow
L85
    iload 19
    bipush 104
    if_icmpge L68
    goto L77
L27
    bipush 103
    istore 13
    goto L79
L68
    getstatic client hx:[[[Lgh;
    iload 20
    aaload
    iload 16
    aaload
    iload 17
    aconst_null
    aastore
L78
    iinc 20 1
    goto L12
L83
    iload 17
    iload 15
    iadd
    istore 17
    goto L21
L32
    getstatic co cz:I
    ldc 1317226893 (java.lang.Integer)
    imul
    iload 7
    isub
    istore 9
    goto L34
L86
    getstatic client hl:Lgh;
    invokevirtual gh i:()Lgm;
    checkcast t
    astore 16
L10
    aconst_null
    aload 16
    if_acmpeq L13
    iload 5
    iconst_0
    if_icmplt L87
    return
L87
    aload 16
    dup
    getfield t l:I
    iload 8
    ldc 1857503109 (java.lang.Integer)
    imul
    isub
    putfield t l:I
L88
    aload 16
    dup
    getfield t c:I
    ldc 939494099 (java.lang.Integer)
    iload 9
    imul
    isub
    putfield t c:I
L89
    aload 16
    getfield t l:I
    ldc -1506352819 (java.lang.Integer)
    imul
    iflt L46
    aload 16
    getfield t c:I
    ldc -1485218469 (java.lang.Integer)
    imul
    iflt L46
    iload 5
    iconst_0
    if_icmplt L90
    new java/lang/IllegalStateException
    dup
    invokespecial java/lang/IllegalStateException <init>:()V
    athrow
L90
    ldc -1506352819 (java.lang.Integer)
    aload 16
    getfield t l:I
    imul
    bipush 104
    if_icmpge L46
    goto L91
L28
    iload 1
    bipush 6
    isub
    ldc -380564952 (java.lang.Integer)
    imul
    putstatic co cz:I
    goto L31
L69
    iload 18
    bipush 104
    if_icmpge L68
    iload 5
    iconst_0
    if_icmplt L85
    new java/lang/IllegalStateException
    dup
    invokespecial java/lang/IllegalStateException <init>:()V
    athrow
L3
    getstatic fa dk:I
    ldc -352096479 (java.lang.Integer)
    imul
    iload 1
    if_icmpne L2
    iload 5
    iconst_0
    if_icmplt L6
    new java/lang/IllegalStateException
    dup
    invokespecial java/lang/IllegalStateException <init>:()V
    athrow
L91
    ldc -1485218469 (java.lang.Integer)
    aload 16
    getfield t c:I
    imul
    bipush 104
    if_icmplt L9
    iload 5
    iconst_0
    if_icmplt L46
    new java/lang/IllegalStateException
    dup
    invokespecial java/lang/IllegalStateException <init>:()V
    athrow
L15
    getstatic client mm:I
    iload 8
    ldc -467606121 (java.lang.Integer)
    imul
    isub
    putstatic client mm:I
    goto L45
L92
    iconst_0
    putstatic client nz:Z
    goto L93
L14
    iconst_0
    putstatic client nb:I
    goto L92
L80
    iconst_m1
    istore 15
    goto L26
L93
    ldc -2109606023 (java.lang.Integer)
    putstatic client mc:I
L94
    getstatic client hi:Lgh;
    invokevirtual gh e:()V
L95
    getstatic client ho:Lgh;
    invokevirtual gh e:()V
    goto L72
L71
    iload 16
    iload 11
    if_icmpeq L86
    iload 5
    iconst_0
    if_icmplt L81
    new java/lang/IllegalStateException
    dup
    invokespecial java/lang/IllegalStateException <init>:()V
    athrow
L96
    new java/lang/StringBuilder
    dup
    invokespecial java/lang/StringBuilder <init>:()V
    ldc "c.ad(" (java.lang.String)
    invokevirtual java/lang/StringBuilder append:(Ljava/lang/String;)Ljava/lang/StringBuilder;
    ldc 41 (java.lang.Integer)
    invokevirtual java/lang/StringBuilder append:(C)Ljava/lang/StringBuilder;
    invokevirtual java/lang/StringBuilder toString:()Ljava/lang/String;
    invokestatic k a:(Ljava/lang/Throwable;Ljava/lang/String;)Lee;
    athrow
