c c (IIIB)VL1
    iconst_0
    istore 4
    goto L2
L3
    iload 2
    ifle L4
    iload 3
    iconst_0
    if_icmpne L5
    new java/lang/IllegalStateException
    dup
    invokespecial java/lang/IllegalStateException <init>:()V
    athrow
L2
    iload 4
    bipush 8
    if_icmpge L6
    iload 3
    iconst_0
    if_icmpne L7
    new java/lang/IllegalStateException
    dup
    invokespecial java/lang/IllegalStateException <init>:()V
    athrow
L8
    iload 5
    bipush 8
    if_icmpge L9
    iload 3
    iconst_0
    if_icmpne L10
    new java/lang/IllegalStateException
    dup
    invokespecial java/lang/IllegalStateException <init>:()V
    athrow
L10
    getstatic w e:[[[I
    iload 0
    aaload
    iload 1
    iload 4
    iadd
    aaload
    iload 2
    iload 5
    iadd
    iconst_0
    iastore
    iinc 5 1
    goto L8
L11
    getstatic w e:[[[I
    iload 0
    aaload
    iload 1
    aaload
    iload 2
    getstatic w e:[[[I
    iload 0
    aaload
    iload 1
    iconst_1
    isub
    aaload
    iload 2
    iconst_1
    isub
    iaload
    iastore
    goto L12
L13
    getstatic w e:[[[I
    iload 0
    aaload
    iload 1
    aaload
    iload 2
    iconst_1
    isub
    iaload
    ifeq L14
    iload 3
    iconst_0
    if_icmpne L15
    new java/lang/IllegalStateException
    dup
    invokespecial java/lang/IllegalStateException <init>:()V
    athrow
L16
    iconst_1
    istore 4
    goto L17
L18
    iload 2
    ifle L12
    goto L19
L20
    getstatic w e:[[[I
    iload 0
    aaload
    iload 1
    aaload
    iload 4
    iload 2
    iadd
    getstatic w e:[[[I
    iload 0
    aaload
    iload 1
    iconst_1
    isub
    aaload
    iload 4
    iload 2
    iadd
    iaload
    iastore
    iinc 4 1
    goto L17
L4
    iload 1
    ifle L21
    iload 3
    iconst_0
    if_icmpne L22
    new java/lang/IllegalStateException
    dup
    invokespecial java/lang/IllegalStateException <init>:()V
    athrow
L5
    iconst_1
    istore 4
L23
    iload 4
    bipush 8
    if_icmpge L4
    iload 3
    iconst_0
    if_icmpne L24
    new java/lang/IllegalStateException
    dup
    invokespecial java/lang/IllegalStateException <init>:()V
    athrow
L24
    getstatic w e:[[[I
    iload 0
    aaload
    iload 4
    iload 1
    iadd
    aaload
    iload 2
    getstatic w e:[[[I
    iload 0
    aaload
    iload 4
    iload 1
    iadd
    aaload
    iload 2
    iconst_1
    isub
    iaload
    iastore
    iinc 4 1
    goto L23
L9
    iinc 4 1
    goto L2
L7
    iconst_0
    istore 5
    goto L8
L25
    getstatic w e:[[[I
    iload 0
    aaload
    iload 1
    aaload
    iload 2
    getstatic w e:[[[I
    iload 0
    aaload
    iload 1
    iconst_1
    isub
    aaload
    iload 2
    iaload
    iastore
    goto L12
L21
    iload 2
    ifle L14
    goto L13
L17
    iload 4
    bipush 8
    if_icmpge L3
    iload 3
    iconst_0
    if_icmpne L20
    new java/lang/IllegalStateException
    dup
    invokespecial java/lang/IllegalStateException <init>:()V
    athrow
L15
    getstatic w e:[[[I
    iload 0
    aaload
    iload 1
    aaload
    iload 2
    getstatic w e:[[[I
    iload 0
    aaload
    iload 1
    aaload
    iload 2
    iconst_1
    isub
    iaload
    iastore
    goto L12
L14
    iload 1
    ifle L12
    iload 3
    iconst_0
    if_icmpne L18
    new java/lang/IllegalStateException
    dup
    invokespecial java/lang/IllegalStateException <init>:()V
    athrow
L22
    getstatic w e:[[[I
    iload 0
    aaload
    iload 1
    iconst_1
    isub
    aaload
    iload 2
    iaload
    ifeq L21
    iload 3
    iconst_0
    if_icmpne L25
    return
L19
    getstatic w e:[[[I
    iload 0
    aaload
    iload 1
    iconst_1
    isub
    aaload
    iload 2
    iconst_1
    isub
    iaload
    ifeq L12
    iload 3
    iconst_0
    if_icmpne L11
    new java/lang/IllegalStateException
    dup
    invokespecial java/lang/IllegalStateException <init>:()V
    athrow
L6
    iload 1
    ifle L3
    iload 3
    iconst_0
    if_icmpne L16
    return
L12
    return
L26
    new java/lang/StringBuilder
    dup
    invokespecial java/lang/StringBuilder <init>:()V
    ldc "c.c(" (java.lang.String)
    invokevirtual java/lang/StringBuilder append:(Ljava/lang/String;)Ljava/lang/StringBuilder;
    ldc 41 (java.lang.Integer)
    invokevirtual java/lang/StringBuilder append:(C)Ljava/lang/StringBuilder;
    invokevirtual java/lang/StringBuilder toString:()Ljava/lang/String;
    invokestatic k a:(Ljava/lang/Throwable;Ljava/lang/String;)Lee;
    athrow
