c w ([BIILcb;[Lhk;I)VL1
    new dh
    dup
    aload 0
    invokespecial dh <init>:([B)V
    astore 6
    goto L2
L3
    goto L4
L5
    iload 9
    iload 10
    iconst_1
    isub
    iadd
    istore 9
    goto L6
L7
    iload 17
    bipush 103
    if_icmpge L8
    iload 5
    ldc -1009594442 (java.lang.Integer)
    if_icmpgt L9
    new java/lang/IllegalStateException
    dup
    invokespecial java/lang/IllegalStateException <init>:()V
    athrow
L10
    iconst_0
    istore 9
    goto L8
L11
    iload 7
    iload 8
    iadd
    istore 7
    goto L10
L8
    aload 6
    bipush 6
    invokevirtual dh ai:(B)I
    istore 10
L12
    iload 10
    ifne L5
    iload 5
    ldc -1009594442 (java.lang.Integer)
    if_icmpgt L13
    new java/lang/IllegalStateException
    dup
    invokespecial java/lang/IllegalStateException <init>:()V
    athrow
L14
    iload 9
    bipush 12
    ishr
    istore 13
    goto L15
L16
    iload 14
    iconst_2
    ishr
    istore 15
    goto L17
L18
    aload 6
    bipush -68
    invokevirtual dh ai:(B)I
    istore 8
    goto L19
L20
    iload 9
    bipush 6
    ishr
    bipush 63
    iand
    istore 12
    goto L14
L21
    iconst_2
    getstatic w a:[[[B
    iconst_1
    aaload
    iload 17
    aaload
    iload 18
    baload
    iconst_2
    iand
    if_icmpne L22
    iload 5
    ldc -1009594442 (java.lang.Integer)
    if_icmpgt L23
    return
L15
    aload 6
    ldc 1558089342 (java.lang.Integer)
    invokevirtual dh z:(I)I
    istore 14
    goto L16
L24
    iload 18
    ifle L8
    iload 5
    ldc -1009594442 (java.lang.Integer)
    if_icmpgt L7
    new java/lang/IllegalStateException
    dup
    invokespecial java/lang/IllegalStateException <init>:()V
    athrow
L17
    iload 14
    iconst_3
    iand
    istore 16
L25
    iload 12
    iload 1
    iadd
    istore 17
L26
    iload 11
    iload 2
    iadd
    istore 18
L27
    iload 17
    ifle L8
    iload 5
    ldc -1009594442 (java.lang.Integer)
    if_icmpgt L24
    new java/lang/IllegalStateException
    dup
    invokespecial java/lang/IllegalStateException <init>:()V
    athrow
L28
    iload 13
    istore 19
    goto L21
L29
    goto L18
L9
    iload 18
    bipush 103
    if_icmpge L8
    iload 5
    ldc -1009594442 (java.lang.Integer)
    if_icmpgt L28
    new java/lang/IllegalStateException
    dup
    invokespecial java/lang/IllegalStateException <init>:()V
    athrow
L13
    goto L29
L19
    iload 8
    ifne L11
    iload 5
    ldc -1009594442 (java.lang.Integer)
    if_icmpgt L3
    new java/lang/IllegalStateException
    dup
    invokespecial java/lang/IllegalStateException <init>:()V
    athrow
L23
    iinc 19 -1
L22
    aconst_null
    astore 20
L30
    iload 19
    iflt L31
    iload 5
    ldc -1009594442 (java.lang.Integer)
    if_icmpgt L32
    new java/lang/IllegalStateException
    dup
    invokespecial java/lang/IllegalStateException <init>:()V
    athrow
L32
    aload 4
    iload 19
    aaload
    astore 20
L31
    iload 13
    iload 17
    iload 18
    iload 7
    iload 16
    iload 15
    aload 3
    aload 20
    bipush -21
    invokestatic ac r:(IIIIIILcb;Lhk;B)V
    goto L8
L6
    iload 9
    bipush 63
    iand
    istore 11
    goto L20
L2
    iconst_m1
    istore 7
    goto L18
L4
    return
L33
    new java/lang/StringBuilder
    dup
    invokespecial java/lang/StringBuilder <init>:()V
    ldc "c.w(" (java.lang.String)
    invokevirtual java/lang/StringBuilder append:(Ljava/lang/String;)Ljava/lang/StringBuilder;
    ldc 41 (java.lang.Integer)
    invokevirtual java/lang/StringBuilder append:(C)Ljava/lang/StringBuilder;
    invokevirtual java/lang/StringBuilder toString:()Ljava/lang/String;
    invokestatic k a:(Ljava/lang/Throwable;Ljava/lang/String;)Lee;
    athrow
