cc bf (ZB)VL1
    iconst_0
    putstatic client hk:I
    goto L2
L3
    getstatic client hc:[I
    getstatic client ce:Ldj;
    iconst_3
    ldc -1600620342 (java.lang.Integer)
    invokevirtual dj hs:(II)I
    iaload
    istore 5
    goto L4
L5
    getstatic client ce:Ldj;
    bipush -99
    invokevirtual dj hi:(B)V
    goto L6
L7
    return
L8
    ldc 1902960638 (java.lang.Integer)
    invokevirtual am t:(IIZI)V
    goto L9
L10
    iload 2
    istore 3
L11
    iload 3
    ldc -1048248787 (java.lang.Integer)
    getstatic client ch:I
    imul
    if_icmpge L12
    getstatic client hm:[I
    getstatic client hk:I
    ldc -528792749 (java.lang.Integer)
    iadd
    dup
    putstatic client hk:I
    ldc 1069021403 (java.lang.Integer)
    imul
    iconst_1
    isub
    getstatic client cb:[I
    iload 3
    iaload
    iastore
    iinc 3 1
    goto L11
L2
    iconst_0
    putstatic client hf:I
    goto L5
L13
    new java/lang/RuntimeException
    dup
    ldc "" (java.lang.String)
    invokespecial java/lang/RuntimeException <init>:(Ljava/lang/String;)V
    athrow
L14
    iconst_0
    putstatic client ch:I
    goto L15
L16
    iload 2
    getstatic client hf:I
    ldc 1434249399 (java.lang.Integer)
    imul
    if_icmpge L17
    iload 1
    iconst_0
    if_icmpne L18
    new java/lang/IllegalStateException
    dup
    invokespecial java/lang/IllegalStateException <init>:()V
    athrow
L19
    iload 9
    iconst_1
    if_icmpne L20
    iload 1
    iconst_0
    if_icmpne L21
    new java/lang/IllegalStateException
    dup
    invokespecial java/lang/IllegalStateException <init>:()V
    athrow
L22
    getstatic client cb:[I
    iload 3
    iaload
    istore 4
L23
    getstatic client cf:[Lam;
    iload 4
    aaload
    astore 5
    goto L24
L25
    iinc 2 1
    goto L26
L27
    iconst_0
    iload 6
    if_icmpne L28
    iload 1
    iconst_0
    if_icmpne L29
    new java/lang/IllegalStateException
    dup
    invokespecial java/lang/IllegalStateException <init>:()V
    athrow
L29
    getstatic client cb:[I
    getstatic client ch:I
    ldc 967967141 (java.lang.Integer)
    iadd
    dup
    putstatic client ch:I
    ldc -1048248787 (java.lang.Integer)
    imul
    iconst_1
    isub
    iload 4
    iastore
    goto L30
L31
    aload 4
    getstatic client ce:Ldj;
    ldc -1739668076 (java.lang.Integer)
    invokevirtual dj aa:(I)I
    ldc 1201461503 (java.lang.Integer)
    imul
    putfield am ac:I
    goto L32
L33
    iconst_1
    goto L8
L28
    getstatic client ce:Ldj;
    iconst_2
    ldc 2076823978 (java.lang.Integer)
    invokevirtual dj hs:(II)I
    istore 7
    goto L34
L4
    iload 3
    ifeq L35
    iload 1
    iconst_0
    if_icmpne L36
    new java/lang/IllegalStateException
    dup
    invokespecial java/lang/IllegalStateException <init>:()V
    athrow
L37
    getstatic client cb:[I
    getstatic client ch:I
    ldc 967967141 (java.lang.Integer)
    iadd
    dup
    putstatic client ch:I
    ldc -1048248787 (java.lang.Integer)
    imul
    iconst_1
    isub
    iload 4
    iastore
L38
    aload 5
    ldc 1417007835 (java.lang.Integer)
    getstatic client b:I
    imul
    putfield am bn:I
    goto L39
L26
    iload 2
    getstatic client ch:I
    ldc -1048248787 (java.lang.Integer)
    imul
    if_icmpge L7
    iload 1
    iconst_0
    if_icmpne L40
    new java/lang/IllegalStateException
    dup
    invokespecial java/lang/IllegalStateException <init>:()V
    athrow
L41
    goto L20
L42
    getstatic client ce:Ldj;
    ldc 1860519334 (java.lang.Integer)
    invokevirtual dj z:(I)I
    istore 5
    goto L43
L44
    getstatic client cb:[I
    getstatic client ch:I
    ldc 967967141 (java.lang.Integer)
    iadd
    dup
    putstatic client ch:I
    ldc -1048248787 (java.lang.Integer)
    imul
    iconst_1
    isub
    iload 4
    iastore
L45
    aload 5
    ldc 1417007835 (java.lang.Integer)
    getstatic client b:I
    imul
    putfield am bn:I
L46
    getstatic client ce:Ldj;
    iconst_3
    ldc 309558384 (java.lang.Integer)
    invokevirtual dj hs:(II)I
    istore 8
    goto L47
L48
    getstatic client cf:[Lam;
    iload 2
    aaload
    astore 4
    goto L49
L50
    getstatic client ce:Ldj;
    iconst_1
    ldc 181284687 (java.lang.Integer)
    invokevirtual dj hs:(II)I
    istore 9
    goto L19
L51
    getstatic client ce:Ldj;
    iconst_3
    ldc -129044271 (java.lang.Integer)
    invokevirtual dj hs:(II)I
    istore 8
    goto L52
L21
    getstatic client ha:[I
    getstatic client hf:I
    ldc -2003405561 (java.lang.Integer)
    iadd
    dup
    putstatic client hf:I
    ldc 1434249399 (java.lang.Integer)
    imul
    iconst_1
    isub
    iload 4
    iastore
    goto L20
L53
    iconst_2
    iload 7
    if_icmpne L54
    iload 1
    iconst_0
    if_icmpne L55
    new java/lang/IllegalStateException
    dup
    invokespecial java/lang/IllegalStateException <init>:()V
    athrow
L55
    getstatic client cb:[I
    getstatic client ch:I
    ldc 967967141 (java.lang.Integer)
    iadd
    dup
    putstatic client ch:I
    ldc -1048248787 (java.lang.Integer)
    imul
    iconst_1
    isub
    iload 4
    iastore
L56
    aload 5
    getstatic client b:I
    ldc 1417007835 (java.lang.Integer)
    imul
    putfield am bn:I
    goto L51
L57
    aload 4
    ldc -928063907 (java.lang.Integer)
    putfield am bv:I
    goto L58
L52
    aload 5
    iload 8
    iconst_1
    ldc 235413748 (java.lang.Integer)
    invokevirtual am z:(IZI)V
L59
    getstatic client ce:Ldj;
    iconst_3
    ldc 1584496837 (java.lang.Integer)
    invokevirtual dj hs:(II)I
    istore 9
L60
    aload 5
    iload 9
    iconst_1
    ldc -74287460 (java.lang.Integer)
    invokevirtual am z:(IZI)V
    goto L61
L62
    aload 4
    getstatic client ce:Ldj;
    bipush 91
    invokevirtual dj as:(B)I
    ldc -401521773 (java.lang.Integer)
    imul
    putfield am ad:I
    goto L63
L64
    iconst_1
    iload 10
    if_icmpne L20
    iload 1
    iconst_0
    if_icmpne L65
    new java/lang/IllegalStateException
    dup
    invokespecial java/lang/IllegalStateException <init>:()V
    athrow
L65
    getstatic client ha:[I
    getstatic client hf:I
    ldc -2003405561 (java.lang.Integer)
    iadd
    dup
    putstatic client hf:I
    ldc 1434249399 (java.lang.Integer)
    imul
    iconst_1
    isub
    iload 4
    iastore
    goto L20
L54
    iconst_3
    iload 7
    if_icmpne L20
    iload 1
    iconst_0
    if_icmpne L66
    return
L67
    getstatic client cf:[Lam;
    iload 2
    new am
    dup
    invokespecial am <init>:()V
    aastore
    goto L68
L30
    aload 5
    getstatic client b:I
    ldc 1417007835 (java.lang.Integer)
    imul
    putfield am bn:I
    goto L69
L20
    iinc 3 1
    goto L70
L71
    getstatic client ce:Ldj;
    ldc 2039932147 (java.lang.Integer)
    getstatic client cm:I
    imul
    ldc -802726802 (java.lang.Integer)
    invokevirtual dj hj:(II)I
    bipush 27
    if_icmpge L72
    iload 1
    iconst_0
    if_icmpne L73
    new java/lang/IllegalStateException
    dup
    invokespecial java/lang/IllegalStateException <init>:()V
    athrow
L74
    iconst_m1
    istore 6
    goto L75
L72
    getstatic client ce:Ldj;
    bipush 15
    ldc 483407336 (java.lang.Integer)
    invokevirtual dj hs:(II)I
    istore 2
    goto L76
L77
    aload 4
    aload 4
    getfield am e:Lay;
    getfield ay g:I
    ldc 1930993491 (java.lang.Integer)
    imul
    putfield am k:I
    goto L78
L79
    aload 4
    getfield am bl:I
    ldc 1048158519 (java.lang.Integer)
    imul
    iconst_m1
    if_icmpeq L80
    iload 1
    iconst_0
    if_icmpne L81
    new java/lang/IllegalStateException
    dup
    invokespecial java/lang/IllegalStateException <init>:()V
    athrow
L82
    iconst_0
    istore 3
    goto L83
L15
    iconst_0
    istore 3
    goto L70
L84
    iload 2
    ldc -1048248787 (java.lang.Integer)
    getstatic client ch:I
    imul
    if_icmpge L12
    iload 1
    iconst_0
    if_icmpne L10
    new java/lang/IllegalStateException
    dup
    invokespecial java/lang/IllegalStateException <init>:()V
    athrow
L40
    aconst_null
    getstatic client cf:[Lam;
    getstatic client cb:[I
    iload 2
    iaload
    aaload
    if_acmpne L25
    iload 1
    iconst_0
    if_icmpne L85
    new java/lang/IllegalStateException
    dup
    invokespecial java/lang/IllegalStateException <init>:()V
    athrow
L86
    goto L87
L49
    getstatic client cb:[I
    getstatic client ch:I
    ldc 967967141 (java.lang.Integer)
    iadd
    dup
    putstatic client ch:I
    ldc -1048248787 (java.lang.Integer)
    imul
    iconst_1
    isub
    iload 2
    iastore
L88
    aload 4
    getstatic client b:I
    ldc 1417007835 (java.lang.Integer)
    imul
    putfield am bn:I
    goto L3
L24
    getstatic client ce:Ldj;
    iconst_1
    ldc -1945466285 (java.lang.Integer)
    invokevirtual dj hs:(II)I
    istore 6
    goto L27
L70
    iload 3
    iload 2
    if_icmpge L71
    iload 1
    iconst_0
    if_icmpne L22
    new java/lang/IllegalStateException
    dup
    invokespecial java/lang/IllegalStateException <init>:()V
    athrow
L36
    aload 4
    aload 4
    ldc 1995856215 (java.lang.Integer)
    iload 5
    imul
    dup_x1
    putfield am n:I
    ldc -92900319 (java.lang.Integer)
    imul
    putfield am by:I
L35
    getstatic client ce:Ldj;
    iconst_1
    ldc -295813623 (java.lang.Integer)
    invokevirtual dj hs:(II)I
    istore 6
L89
    iconst_1
    iload 6
    if_icmpne L90
    iload 1
    iconst_0
    if_icmpne L91
    return
L91
    getstatic client ha:[I
    getstatic client hf:I
    ldc -2003405561 (java.lang.Integer)
    iadd
    dup
    putstatic client hf:I
    ldc 1434249399 (java.lang.Integer)
    imul
    iconst_1
    isub
    iload 2
    iastore
L90
    getstatic client ce:Ldj;
    iconst_1
    ldc 93412953 (java.lang.Integer)
    invokevirtual dj hs:(II)I
    istore 7
L92
    iload 0
    ifeq L93
    iload 1
    iconst_0
    if_icmpne L94
    new java/lang/IllegalStateException
    dup
    invokespecial java/lang/IllegalStateException <init>:()V
    athrow
L94
    getstatic client ce:Ldj;
    bipush 8
    ldc 1724344897 (java.lang.Integer)
    invokevirtual dj hs:(II)I
    istore 8
L95
    iload 8
    bipush 127
    if_icmple L96
    goto L97
L98
    goto L20
L93
    getstatic client ce:Ldj;
    iconst_5
    ldc 1497023161 (java.lang.Integer)
    invokevirtual dj hs:(II)I
    istore 8
L99
    iload 8
    bipush 15
    if_icmple L96
    iinc 8 -32
    goto L96
L6
    getstatic client ce:Ldj;
    bipush 8
    ldc 767400480 (java.lang.Integer)
    invokevirtual dj hs:(II)I
    istore 2
    goto L84
L83
    getstatic client cf:[Lam;
    iload 2
    aaload
    ifnonnull L48
    iload 1
    iconst_0
    if_icmpne L67
    new java/lang/IllegalStateException
    dup
    invokespecial java/lang/IllegalStateException <init>:()V
    athrow
L100
    iload 6
    ldc 65535 (java.lang.Integer)
    if_icmpne L75
    iload 1
    iconst_0
    if_icmpne L74
    new java/lang/IllegalStateException
    dup
    invokespecial java/lang/IllegalStateException <init>:()V
    athrow
L101
    iload 9
    bipush 127
    if_icmple L102
    iinc 9 -256
    goto L102
L103
    getstatic client ce:Ldj;
    iconst_5
    ldc -1876341504 (java.lang.Integer)
    invokevirtual dj hs:(II)I
    istore 9
L104
    iload 9
    bipush 15
    if_icmple L102
    iload 1
    iconst_0
    if_icmpne L105
    new java/lang/IllegalStateException
    dup
    invokespecial java/lang/IllegalStateException <init>:()V
    athrow
L105
    iinc 9 -32
    goto L102
L106
    iload 2
    getstatic client hk:I
    ldc 1069021403 (java.lang.Integer)
    imul
    if_icmpge L107
    iload 1
    iconst_0
    if_icmpne L108
    new java/lang/IllegalStateException
    dup
    invokespecial java/lang/IllegalStateException <init>:()V
    athrow
L109
    aload 4
    aload 4
    getfield am e:Lay;
    getfield ay ai:I
    ldc -696003875 (java.lang.Integer)
    imul
    putfield am bh:I
L110
    iconst_0
    aload 4
    getfield am bh:I
    ldc -913616539 (java.lang.Integer)
    imul
    if_icmpne L111
    aload 4
    iconst_0
    putfield am n:I
L111
    aload 4
    aload 4
    getfield am e:Lay;
    getfield ay s:I
    ldc 318898175 (java.lang.Integer)
    imul
    putfield am ao:I
L112
    aload 4
    aload 4
    getfield am e:Lay;
    getfield ay j:I
    ldc -2091321375 (java.lang.Integer)
    imul
    putfield am ai:I
L113
    aload 4
    ldc -1823063185 (java.lang.Integer)
    aload 4
    getfield am e:Lay;
    getfield ay m:I
    imul
    putfield am aw:I
L114
    aload 4
    ldc 416362919 (java.lang.Integer)
    aload 4
    getfield am e:Lay;
    getfield ay t:I
    imul
    putfield am am:I
    goto L77
L43
    iconst_0
    iload 5
    iconst_1
    iand
    if_icmpeq L32
    iload 1
    iconst_0
    if_icmpne L115
    new java/lang/IllegalStateException
    dup
    invokespecial java/lang/IllegalStateException <init>:()V
    athrow
L63
    ldc 65535 (java.lang.Integer)
    aload 4
    getfield am ad:I
    ldc -522366309 (java.lang.Integer)
    imul
    if_icmpne L116
    iload 1
    iconst_0
    if_icmpne L117
    return
L118
    aload 4
    aload 4
    getfield am e:Lay;
    getfield ay h:I
    ldc 1957205493 (java.lang.Integer)
    imul
    putfield am ap:I
    goto L119
L120
    iload 0
    ifeq L103
    iload 1
    iconst_0
    if_icmpne L121
    return
L122
    iload 8
    iconst_1
    if_icmpne L123
    iload 1
    iconst_0
    if_icmpne L124
    new java/lang/IllegalStateException
    dup
    invokespecial java/lang/IllegalStateException <init>:()V
    athrow
L39
    getstatic client ha:[I
    getstatic client hf:I
    ldc -2003405561 (java.lang.Integer)
    iadd
    dup
    putstatic client hf:I
    ldc 1434249399 (java.lang.Integer)
    imul
    iconst_1
    isub
    iload 4
    iastore
    goto L41
L97
    iinc 8 -256
    goto L96
L9
    goto L71
L87
    getstatic client ce:Ldj;
    bipush -48
    invokevirtual dj hu:(B)V
L125
    iconst_0
    istore 2
    goto L16
L76
    iload 2
    sipush 32767
    if_icmpne L82
    iload 1
    iconst_0
    if_icmpne L86
    new java/lang/IllegalStateException
    dup
    invokespecial java/lang/IllegalStateException <init>:()V
    athrow
L18
    getstatic client ha:[I
    iload 2
    iaload
    istore 3
    goto L126
L124
    aload 4
    iconst_0
    putfield am bk:I
    goto L127
L96
    aload 4
    getstatic client ce:Ldj;
    bipush 14
    ldc -703486792 (java.lang.Integer)
    invokevirtual dj hs:(II)I
    bipush 18
    invokestatic ar e:(IB)Lay;
    putfield am e:Lay;
    goto L120
L102
    aload 4
    aload 4
    getfield am e:Lay;
    getfield ay i:I
    ldc 1166461907 (java.lang.Integer)
    imul
    putfield am p:I
    goto L109
L128
    aload 4
    getstatic client b:I
    ldc 1748815831 (java.lang.Integer)
    imul
    ldc -1190841436 (java.lang.Integer)
    iadd
    putfield am ar:I
    goto L129
L130
    getstatic client ce:Ldj;
    ldc -1542440417 (java.lang.Integer)
    invokevirtual dj ar:(I)I
    istore 7
    goto L131
L132
    aload 4
    iload 6
    iload 7
    getstatic client b:I
    ldc -117546507 (java.lang.Integer)
    imul
    iconst_3
    invokevirtual am q:(IIIB)V
L133
    aload 4
    getstatic client b:I
    ldc 1748815831 (java.lang.Integer)
    imul
    ldc -1190841436 (java.lang.Integer)
    iadd
    putfield am ar:I
L134
    aload 4
    getstatic client ce:Ldj;
    ldc -303993339 (java.lang.Integer)
    invokevirtual dj q:(I)I
    ldc -472061819 (java.lang.Integer)
    imul
    putfield am aq:I
    goto L31
L135
    getstatic client ce:Ldj;
    ldc -1197600762 (java.lang.Integer)
    invokevirtual dj ak:(I)I
    istore 7
    goto L132
L32
    iconst_0
    iload 5
    bipush 16
    iand
    if_icmpeq L136
    iload 1
    iconst_0
    if_icmpne L137
    return
L137
    aload 4
    getstatic client ce:Ldj;
    ldc -140206574 (java.lang.Integer)
    invokevirtual dj p:(I)Ljava/lang/String;
    putfield am ae:Ljava/lang/String;
L138
    aload 4
    ldc 72479148 (java.lang.Integer)
    putfield am ay:I
L136
    iconst_0
    iload 5
    iconst_4
    iand
    if_icmpeq L139
    iload 1
    iconst_0
    if_icmpne L140
    new java/lang/IllegalStateException
    dup
    invokespecial java/lang/IllegalStateException <init>:()V
    athrow
L140
    aload 4
    getstatic client ce:Ldj;
    bipush 69
    invokevirtual dj bl:(B)I
    bipush 100
    invokestatic ar e:(IB)Lay;
    putfield am e:Lay;
L141
    aload 4
    aload 4
    getfield am e:Lay;
    getfield ay i:I
    ldc 1166461907 (java.lang.Integer)
    imul
    putfield am p:I
L142
    aload 4
    ldc -696003875 (java.lang.Integer)
    aload 4
    getfield am e:Lay;
    getfield ay ai:I
    imul
    putfield am bh:I
L143
    aload 4
    ldc 318898175 (java.lang.Integer)
    aload 4
    getfield am e:Lay;
    getfield ay s:I
    imul
    putfield am ao:I
L144
    aload 4
    aload 4
    getfield am e:Lay;
    getfield ay j:I
    ldc -2091321375 (java.lang.Integer)
    imul
    putfield am ai:I
L145
    aload 4
    ldc -1823063185 (java.lang.Integer)
    aload 4
    getfield am e:Lay;
    getfield ay m:I
    imul
    putfield am aw:I
L146
    aload 4
    aload 4
    getfield am e:Lay;
    getfield ay t:I
    ldc 416362919 (java.lang.Integer)
    imul
    putfield am am:I
L147
    aload 4
    aload 4
    getfield am e:Lay;
    getfield ay g:I
    ldc 1930993491 (java.lang.Integer)
    imul
    putfield am k:I
L148
    aload 4
    aload 4
    getfield am e:Lay;
    getfield ay o:I
    ldc -977219291 (java.lang.Integer)
    imul
    putfield am ax:I
L149
    aload 4
    ldc 1957205493 (java.lang.Integer)
    aload 4
    getfield am e:Lay;
    getfield ay h:I
    imul
    putfield am ap:I
L139
    iconst_0
    iload 5
    iconst_2
    iand
    if_icmpeq L150
    iload 1
    iconst_0
    if_icmpne L151
    new java/lang/IllegalStateException
    dup
    invokespecial java/lang/IllegalStateException <init>:()V
    athrow
L151
    getstatic client ce:Ldj;
    ldc -915872223 (java.lang.Integer)
    invokevirtual dj aa:(I)I
    istore 6
    goto L100
L47
    aload 5
    iload 8
    iconst_0
    ldc 351332261 (java.lang.Integer)
    invokevirtual am z:(IZI)V
    goto L50
L152
    iconst_0
    goto L8
L75
    getstatic client ce:Ldj;
    ldc 1773348531 (java.lang.Integer)
    invokevirtual dj z:(I)I
    istore 7
L153
    iload 6
    aload 4
    getfield am bl:I
    ldc 1048158519 (java.lang.Integer)
    imul
    if_icmpne L154
    iconst_m1
    iload 6
    if_icmpeq L154
L155
    iload 6
    ldc 152969838 (java.lang.Integer)
    invokestatic cd e:(II)Lah;
    getfield ah q:I
    ldc -1542859171 (java.lang.Integer)
    imul
    istore 8
    goto L122
L69
    goto L20
L73
    goto L87
L127
    aload 4
    iconst_0
    putfield am bm:I
L156
    aload 4
    iload 7
    ldc -270225023 (java.lang.Integer)
    imul
    putfield am bw:I
    goto L157
L126
    getstatic client cf:[Lam;
    iload 3
    aaload
    astore 4
    goto L42
L123
    iconst_2
    iload 8
    if_icmpne L158
    iload 1
    iconst_0
    if_icmpne L159
    new java/lang/IllegalStateException
    dup
    invokespecial java/lang/IllegalStateException <init>:()V
    athrow
L159
    aload 4
    iconst_0
    putfield am bp:I
    goto L158
L116
    iconst_0
    iload 5
    bipush 32
    iand
    if_icmpeq L160
    iload 1
    iconst_0
    if_icmpne L161
    new java/lang/IllegalStateException
    dup
    invokespecial java/lang/IllegalStateException <init>:()V
    athrow
L162
    aload 4
    iconst_0
    putfield am bc:I
    goto L163
L164
    new java/lang/RuntimeException
    dup
    new java/lang/StringBuilder
    dup
    invokespecial java/lang/StringBuilder <init>:()V
    getstatic client ce:Ldj;
    getfield dj a:I
    ldc 910905453 (java.lang.Integer)
    imul
    invokevirtual java/lang/StringBuilder append:(I)Ljava/lang/StringBuilder;
    getstatic a a:Ljava/lang/String;
    invokevirtual java/lang/StringBuilder append:(Ljava/lang/String;)Ljava/lang/StringBuilder;
    ldc 2039932147 (java.lang.Integer)
    getstatic client cm:I
    imul
    invokevirtual java/lang/StringBuilder append:(I)Ljava/lang/StringBuilder;
    invokevirtual java/lang/StringBuilder toString:()Ljava/lang/String;
    invokespecial java/lang/RuntimeException <init>:(Ljava/lang/String;)V
    athrow
L121
    getstatic client ce:Ldj;
    bipush 8
    ldc -307928370 (java.lang.Integer)
    invokevirtual dj hs:(II)I
    istore 9
    goto L101
L80
    aload 4
    ldc 2003952775 (java.lang.Integer)
    iload 6
    imul
    putfield am bl:I
L165
    aload 4
    iconst_0
    putfield am bk:I
L166
    aload 4
    iconst_0
    putfield am bm:I
    goto L167
L168
    aload 4
    iconst_0
    putfield am bp:I
    goto L169
L12
    iload 2
    ldc -1048248787 (java.lang.Integer)
    getstatic client ch:I
    imul
    if_icmple L14
    iload 1
    iconst_0
    if_icmpne L13
    new java/lang/IllegalStateException
    dup
    invokespecial java/lang/IllegalStateException <init>:()V
    athrow
L169
    aload 4
    ldc 1641413967 (java.lang.Integer)
    aload 4
    getfield am bt:I
    imul
    putfield am ch:I
    goto L150
L157
    aload 4
    iconst_0
    putfield am bp:I
    goto L123
L119
    aload 4
    iload 9
    getstatic hg hv:Ll;
    getfield l bs:[I
    iconst_0
    iaload
    iadd
    iload 8
    getstatic hg hv:Ll;
    getfield l bo:[I
    iconst_0
    iaload
    iadd
    iconst_1
    iload 7
    if_icmpne L152
    iload 1
    iconst_0
    if_icmpne L33
    new java/lang/IllegalStateException
    dup
    invokespecial java/lang/IllegalStateException <init>:()V
    athrow
L34
    iconst_0
    iload 7
    if_icmpne L170
    iload 1
    iconst_0
    if_icmpne L37
    return
L117
    aload 4
    ldc 401521773 (java.lang.Integer)
    putfield am ad:I
    goto L116
L115
    getstatic client ce:Ldj;
    ldc 1062584345 (java.lang.Integer)
    invokevirtual dj z:(I)I
    istore 6
    goto L135
L154
    iconst_m1
    iload 6
    if_icmpeq L80
    iload 1
    iconst_0
    if_icmpne L79
    return
L171
    aload 4
    iconst_0
    putfield am bv:I
    goto L162
L108
    getstatic client hm:[I
    iload 2
    iaload
    istore 3
    goto L172
L61
    getstatic client ce:Ldj;
    iconst_1
    ldc -905023290 (java.lang.Integer)
    invokevirtual dj hs:(II)I
    istore 10
    goto L64
L129
    aload 4
    getstatic client ce:Ldj;
    ldc -2136998971 (java.lang.Integer)
    invokevirtual dj aa:(I)I
    ldc -472061819 (java.lang.Integer)
    imul
    putfield am aq:I
L173
    aload 4
    getstatic client ce:Ldj;
    bipush -26
    invokevirtual dj bl:(B)I
    ldc 1201461503 (java.lang.Integer)
    imul
    putfield am ac:I
L160
    iload 5
    bipush 64
    iand
    ifeq L174
L175
    aload 4
    getstatic client ce:Ldj;
    ldc -1431579458 (java.lang.Integer)
    invokevirtual dj aa:(I)I
    ldc -95224929 (java.lang.Integer)
    imul
    putfield am an:I
L176
    aload 4
    getstatic client ce:Ldj;
    bipush 39
    invokevirtual dj bl:(B)I
    ldc 752110391 (java.lang.Integer)
    imul
    putfield am az:I
L174
    iconst_0
    iload 5
    sipush 128
    iand
    if_icmpeq L177
    iload 1
    iconst_0
    if_icmpne L178
    return
L178
    aload 4
    getstatic client ce:Ldj;
    bipush -33
    invokevirtual dj bl:(B)I
    ldc -1425265329 (java.lang.Integer)
    imul
    putfield am be:I
L179
    getstatic client ce:Ldj;
    ldc 555083077 (java.lang.Integer)
    invokevirtual dj bc:(I)I
    istore 6
L180
    aload 4
    ldc 660023145 (java.lang.Integer)
    iload 6
    bipush 16
    ishr
    imul
    putfield am bu:I
L181
    aload 4
    ldc 1449551327 (java.lang.Integer)
    ldc -117546507 (java.lang.Integer)
    getstatic client b:I
    imul
    iload 6
    ldc 65535 (java.lang.Integer)
    iand
    iadd
    imul
    putfield am br:I
    goto L171
L158
    goto L150
L66
    getstatic client hm:[I
    getstatic client hk:I
    ldc -528792749 (java.lang.Integer)
    iadd
    dup
    putstatic client hk:I
    ldc 1069021403 (java.lang.Integer)
    imul
    iconst_1
    isub
    iload 4
    iastore
    goto L98
L163
    aload 4
    getfield am br:I
    ldc 959944223 (java.lang.Integer)
    imul
    getstatic client b:I
    ldc -117546507 (java.lang.Integer)
    imul
    if_icmple L58
    iload 1
    iconst_0
    if_icmpne L57
    new java/lang/IllegalStateException
    dup
    invokespecial java/lang/IllegalStateException <init>:()V
    athrow
L78
    aload 4
    aload 4
    getfield am e:Lay;
    getfield ay o:I
    ldc -977219291 (java.lang.Integer)
    imul
    putfield am ax:I
    goto L118
L58
    ldc 65535 (java.lang.Integer)
    ldc 147245487 (java.lang.Integer)
    aload 4
    getfield am be:I
    imul
    if_icmpne L177
    iload 1
    iconst_0
    if_icmpne L182
    new java/lang/IllegalStateException
    dup
    invokespecial java/lang/IllegalStateException <init>:()V
    athrow
L182
    aload 4
    ldc 1425265329 (java.lang.Integer)
    putfield am be:I
L177
    iinc 2 1
    goto L16
L17
    iconst_0
    istore 2
    goto L106
L68
    iconst_1
    istore 3
    goto L48
L167
    aload 4
    ldc -270225023 (java.lang.Integer)
    iload 7
    imul
    putfield am bw:I
    goto L168
L172
    getstatic client b:I
    ldc -117546507 (java.lang.Integer)
    imul
    ldc 601976687 (java.lang.Integer)
    getstatic client cf:[Lam;
    iload 3
    aaload
    getfield am bn:I
    imul
    if_icmpeq L183
    iload 1
    iconst_0
    if_icmpne L184
    return
L184
    getstatic client cf:[Lam;
    iload 3
    aaload
    aconst_null
    putfield am e:Lay;
L185
    getstatic client cf:[Lam;
    iload 3
    aconst_null
    aastore
L183
    iinc 2 1
    goto L106
L107
    ldc 2039932147 (java.lang.Integer)
    getstatic client cm:I
    imul
    ldc 910905453 (java.lang.Integer)
    getstatic client ce:Ldj;
    getfield dj a:I
    imul
    if_icmpeq L186
    iload 1
    iconst_0
    if_icmpne L164
    new java/lang/IllegalStateException
    dup
    invokespecial java/lang/IllegalStateException <init>:()V
    athrow
L131
    aload 4
    iload 6
    iload 7
    getstatic client b:I
    ldc -117546507 (java.lang.Integer)
    imul
    iconst_3
    invokevirtual am q:(IIIB)V
    goto L128
L186
    iconst_0
    istore 2
    goto L26
L170
    iload 7
    iconst_1
    if_icmpne L53
    goto L44
L81
    iload 6
    ldc 152969838 (java.lang.Integer)
    invokestatic cd e:(II)Lah;
    getfield ah s:I
    ldc 622822839 (java.lang.Integer)
    imul
    ldc 1048158519 (java.lang.Integer)
    aload 4
    getfield am bl:I
    imul
    ldc 152969838 (java.lang.Integer)
    invokestatic cd e:(II)Lah;
    getfield ah s:I
    ldc 622822839 (java.lang.Integer)
    imul
    if_icmplt L150
    iload 1
    iconst_0
    if_icmpne L80
    new java/lang/IllegalStateException
    dup
    invokespecial java/lang/IllegalStateException <init>:()V
    athrow
L85
    new java/lang/RuntimeException
    dup
    new java/lang/StringBuilder
    dup
    invokespecial java/lang/StringBuilder <init>:()V
    iload 2
    invokevirtual java/lang/StringBuilder append:(I)Ljava/lang/StringBuilder;
    getstatic a a:Ljava/lang/String;
    invokevirtual java/lang/StringBuilder append:(Ljava/lang/String;)Ljava/lang/StringBuilder;
    getstatic client ch:I
    ldc -1048248787 (java.lang.Integer)
    imul
    invokevirtual java/lang/StringBuilder append:(I)Ljava/lang/StringBuilder;
    invokevirtual java/lang/StringBuilder toString:()Ljava/lang/String;
    invokespecial java/lang/RuntimeException <init>:(Ljava/lang/String;)V
    athrow
L150
    iload 5
    bipush 8
    iand
    ifeq L116
    goto L62
L161
    getstatic client ce:Ldj;
    ldc -2101369861 (java.lang.Integer)
    invokevirtual dj aq:(I)I
    istore 6
    goto L130
L187
    new java/lang/StringBuilder
    dup
    invokespecial java/lang/StringBuilder <init>:()V
    ldc "cc.bf(" (java.lang.String)
    invokevirtual java/lang/StringBuilder append:(Ljava/lang/String;)Ljava/lang/StringBuilder;
    ldc 41 (java.lang.Integer)
    invokevirtual java/lang/StringBuilder append:(C)Ljava/lang/StringBuilder;
    invokevirtual java/lang/StringBuilder toString:()Ljava/lang/String;
    invokestatic k a:(Ljava/lang/Throwable;Ljava/lang/String;)Lee;
    athrow
