cf l (Lfo;IIIBZI)VL1
    iload 2
    iload 1
    bipush 16
    ishl
    iadd
    i2l
    lstore 7
    goto L2
L3
    getstatic fz g:I
    ldc 1884384453 (java.lang.Integer)
    isub
    putstatic fz g:I
    goto L4
L5
    aload 9
    ifnull L6
    iload 6
    ldc 1471990879 (java.lang.Integer)
    if_icmpeq L7
    return
L7
    return
L8
    aload 9
    invokevirtual fe en:()V
    goto L9
L10
    aload 9
    ifnull L11
    iload 6
    ldc 1471990879 (java.lang.Integer)
    if_icmpeq L12
    new java/lang/IllegalStateException
    dup
    invokespecial java/lang/IllegalStateException <init>:()V
    athrow
L12
    return
L11
    getstatic fz f:Lgf;
    lload 7
    invokevirtual gf e:(J)Lgm;
    checkcast fe
    astore 9
L13
    aconst_null
    aload 9
    if_acmpeq L14
    iload 6
    ldc 1471990879 (java.lang.Integer)
    if_icmpeq L15
    new java/lang/IllegalStateException
    dup
    invokespecial java/lang/IllegalStateException <init>:()V
    athrow
L15
    iload 5
    ifeq L16
    iload 6
    ldc 1471990879 (java.lang.Integer)
    if_icmpeq L8
    new java/lang/IllegalStateException
    dup
    invokespecial java/lang/IllegalStateException <init>:()V
    athrow
L17
    return
L9
    getstatic fz c:Lgf;
    aload 9
    lload 7
    invokevirtual gf a:(Lgm;J)V
    goto L3
L18
    aconst_null
    aload 9
    if_acmpeq L19
    iload 6
    ldc 1471990879 (java.lang.Integer)
    if_icmpeq L20
    new java/lang/IllegalStateException
    dup
    invokespecial java/lang/IllegalStateException <init>:()V
    athrow
L4
    getstatic fz u:I
    ldc -1302173919 (java.lang.Integer)
    iadd
    putstatic fz u:I
L16
    return
L14
    iload 5
    ifne L19
    iload 6
    ldc 1471990879 (java.lang.Integer)
    if_icmpeq L21
    new java/lang/IllegalStateException
    dup
    invokespecial java/lang/IllegalStateException <init>:()V
    athrow
L21
    getstatic fz o:Lgf;
    lload 7
    invokevirtual gf e:(J)Lgm;
    checkcast fe
    astore 9
    goto L18
L22
    iload 5
    ifeq L23
    goto L24
L20
    return
L19
    new fe
    dup
    invokespecial fe <init>:()V
    astore 9
L25
    aload 9
    aload 0
    putfield fe e:Lfo;
    goto L26
L27
    getstatic fz u:I
    ldc -1302173919 (java.lang.Integer)
    iadd
    putstatic fz u:I
    goto L17
L28
    aload 9
    iload 4
    putfield fe l:B
    goto L22
L29
    getstatic fz g:I
    ldc 1884384453 (java.lang.Integer)
    iadd
    putstatic fz g:I
    goto L17
L6
    getstatic fz w:Lgf;
    lload 7
    invokevirtual gf e:(J)Lgm;
    checkcast fe
    astore 9
    goto L10
L24
    getstatic fz c:Lgf;
    aload 9
    lload 7
    invokevirtual gf a:(Lgm;J)V
    goto L27
L23
    getstatic fz r:Lgj;
    aload 9
    invokevirtual gj e:(Lgd;)V
L30
    getstatic fz f:Lgf;
    aload 9
    lload 7
    invokevirtual gf a:(Lgm;J)V
    goto L29
L2
    getstatic fz c:Lgf;
    lload 7
    invokevirtual gf e:(J)Lgm;
    checkcast fe
    astore 9
    goto L5
L26
    aload 9
    iload 3
    ldc -1378065793 (java.lang.Integer)
    imul
    putfield fe a:I
    goto L28
L31
    new java/lang/StringBuilder
    dup
    invokespecial java/lang/StringBuilder <init>:()V
    ldc "cf.l(" (java.lang.String)
    invokevirtual java/lang/StringBuilder append:(Ljava/lang/String;)Ljava/lang/StringBuilder;
    ldc 41 (java.lang.Integer)
    invokevirtual java/lang/StringBuilder append:(C)Ljava/lang/StringBuilder;
    invokevirtual java/lang/StringBuilder toString:()Ljava/lang/String;
    invokestatic k a:(Ljava/lang/Throwable;Ljava/lang/String;)Lee;
    athrow
