cj aq (IIIIIIB)VL1
    sipush 2048
    iload 3
    isub
    sipush 2047
    iand
    istore 7
    goto L2
L3
    ldc 1012303081 (java.lang.Integer)
    iload 2
    iload 11
    isub
    imul
    putstatic e fe:I
    goto L4
L5
    iconst_0
    istore 9
    goto L6
L7
    iload 7
    ifeq L8
    iload 6
    bipush 22
    if_icmpgt L9
    new java/lang/IllegalStateException
    dup
    invokespecial java/lang/IllegalStateException <init>:()V
    athrow
L10
    iload 5
    istore 11
    goto L7
L6
    iconst_0
    istore 10
    goto L10
L9
    getstatic cp aw:[I
    iload 7
    iaload
    istore 12
L11
    getstatic cp am:[I
    iload 7
    iaload
    istore 13
    goto L12
L13
    iload 11
    iload 13
    imul
    iload 12
    iload 9
    imul
    isub
    bipush 16
    ishr
    istore 11
    goto L14
L15
    iload 11
    iload 13
    imul
    iload 12
    iload 10
    imul
    iadd
    bipush 16
    ishr
    istore 11
    goto L16
L17
    ldc -381465019 (java.lang.Integer)
    iload 4
    imul
    putstatic ez fk:I
    goto L18
L8
    iload 8
    ifeq L19
L20
    getstatic cp aw:[I
    iload 8
    iaload
    istore 12
L21
    getstatic cp am:[I
    iload 8
    iaload
    istore 13
L22
    iload 13
    iload 9
    imul
    iload 12
    iload 11
    imul
    iadd
    bipush 16
    ishr
    istore 14
    goto L13
L12
    iload 13
    iload 10
    imul
    iload 11
    iload 12
    imul
    isub
    bipush 16
    ishr
    istore 14
    goto L15
L14
    iload 14
    istore 9
    goto L19
L4
    iload 3
    ldc 1391672555 (java.lang.Integer)
    imul
    putstatic s fb:I
    goto L17
L23
    ldc 1416962957 (java.lang.Integer)
    iload 1
    iload 10
    isub
    imul
    putstatic ev fz:I
    goto L3
L16
    iload 14
    istore 10
    goto L8
L2
    sipush 2048
    iload 4
    isub
    sipush 2047
    iand
    istore 8
    goto L5
L19
    iload 0
    iload 9
    isub
    ldc -648340705 (java.lang.Integer)
    imul
    putstatic ev fj:I
    goto L23
L18
    return
L24
    new java/lang/StringBuilder
    dup
    invokespecial java/lang/StringBuilder <init>:()V
    ldc "cj.aq(" (java.lang.String)
    invokevirtual java/lang/StringBuilder append:(Ljava/lang/String;)Ljava/lang/StringBuilder;
    ldc 41 (java.lang.Integer)
    invokevirtual java/lang/StringBuilder append:(C)Ljava/lang/StringBuilder;
    invokevirtual java/lang/StringBuilder toString:()Ljava/lang/String;
    invokestatic k a:(Ljava/lang/Throwable;Ljava/lang/String;)Lee;
    athrow
