cl a (Leo;ZB)VL1
    getstatic fz e:Leo;
    ifnull L2
    iload 2
    bipush 22
    if_icmplt L3
    new java/lang/IllegalStateException
    dup
    invokespecial java/lang/IllegalStateException <init>:()V
    athrow
L3
    getstatic fz e:Leo;
    bipush -53
    invokevirtual eo c:(B)V
L4
    goto L5
L6
    astore 3
L5
    aconst_null
    putstatic fz e:Leo;
L2
    aload 0
    putstatic fz e:Leo;
L7
    iload 1
    bipush -104
    invokestatic y e:(ZB)V
L8
    getstatic fz m:Ldh;
    iconst_0
    putfield dh a:I
L9
    aconst_null
    putstatic cm j:Lfe;
L10
    aconst_null
    putstatic ax t:Ldh;
L11
    iconst_0
    putstatic fz z:I
L12
    getstatic fz w:Lgf;
    invokevirtual gf c:()Lgm;
    checkcast fe
    astore 3
L13
    aconst_null
    aload 3
    if_acmpne L14
    iload 2
    bipush 22
    if_icmplt L15
    new java/lang/IllegalStateException
    dup
    invokespecial java/lang/IllegalStateException <init>:()V
    athrow
L15
    goto L16
L14
    getstatic fz c:Lgf;
    aload 3
    aload 3
    getfield fe ec:J
    invokevirtual gf a:(Lgm;J)V
L17
    getstatic fz u:I
    ldc -1302173919 (java.lang.Integer)
    iadd
    putstatic fz u:I
L18
    getstatic fz i:I
    ldc -1234343637 (java.lang.Integer)
    isub
    putstatic fz i:I
L19
    goto L12
L16
    getstatic fz o:Lgf;
    invokevirtual gf c:()Lgm;
    checkcast fe
    astore 3
L20
    aconst_null
    aload 3
    if_acmpne L21
    iload 2
    bipush 22
    if_icmplt L22
    return
L22
    goto L23
L21
    getstatic fz r:Lgj;
    aload 3
    invokevirtual gj a:(Lgd;)V
L24
    getstatic fz f:Lgf;
    aload 3
    aload 3
    getfield fe ec:J
    invokevirtual gf a:(Lgm;J)V
L25
    getstatic fz g:I
    ldc 1884384453 (java.lang.Integer)
    iadd
    putstatic fz g:I
L26
    getstatic fz h:I
    ldc 782165167 (java.lang.Integer)
    isub
    putstatic fz h:I
L27
    goto L16
L23
    iconst_0
    getstatic fz x:B
    if_icmpeq L28
    iload 2
    bipush 22
    if_icmplt L29
    new java/lang/IllegalStateException
    dup
    invokespecial java/lang/IllegalStateException <init>:()V
    athrow
L29
    new dh
    dup
    iconst_4
    invokespecial dh <init>:(I)V
    astore 3
L30
    aload 3
    iconst_4
    bipush -48
    invokevirtual dh e:(IB)V
L31
    aload 3
    getstatic fz x:B
    bipush 26
    invokevirtual dh e:(IB)V
L32
    aload 3
    iconst_0
    bipush -35
    invokevirtual dh a:(IB)V
L33
    getstatic fz e:Leo;
    aload 3
    getfield dh e:[B
    iconst_0
    iconst_4
    ldc 1644768080 (java.lang.Integer)
    invokevirtual eo r:([BIII)V
L34
    goto L28
L35
    astore 3
L36
    getstatic fz e:Leo;
    bipush -86
    invokevirtual eo c:(B)V
L37
    goto L38
L39
    astore 4
L38
    getstatic fz v:I
    ldc -97197595 (java.lang.Integer)
    iadd
    putstatic fz v:I
L40
    aconst_null
    putstatic fz e:Leo;
L28
    iconst_0
    putstatic fz a:I
L41
    ldc -1484487313 (java.lang.Integer)
    invokestatic ab e:(I)J
    ldc 8152876136267467933 (java.lang.Long)
    lmul
    putstatic fz l:J
L42
    return
L43
    new java/lang/StringBuilder
    dup
    invokespecial java/lang/StringBuilder <init>:()V
    ldc "cl.a(" (java.lang.String)
    invokevirtual java/lang/StringBuilder append:(Ljava/lang/String;)Ljava/lang/StringBuilder;
    ldc 41 (java.lang.Integer)
    invokevirtual java/lang/StringBuilder append:(C)Ljava/lang/StringBuilder;
    invokevirtual java/lang/StringBuilder toString:()Ljava/lang/String;
    invokestatic k a:(Ljava/lang/Throwable;Ljava/lang/String;)Lee;
    athrow
