cl ar (IIII)IL1
    iload 0
    bipush 7
    ishr
    istore 4
    goto L2
L3
    sipush 128
    iload 7
    isub
    getstatic w e:[[[I
    iload 6
    aaload
    iload 4
    aaload
    iload 5
    iaload
    imul
    getstatic w e:[[[I
    iload 6
    aaload
    iconst_1
    iload 4
    iadd
    aaload
    iload 5
    iaload
    iload 7
    imul
    iadd
    bipush 7
    ishr
    istore 9
    goto L4
L5
    iload 4
    iflt L6
    iload 3
    ldc 1958062732 (java.lang.Integer)
    if_icmpeq L7
    new java/lang/IllegalStateException
    dup
    invokespecial java/lang/IllegalStateException <init>:()V
    athrow
L8
    iload 6
    iconst_3
    if_icmpge L9
    iload 3
    ldc 1958062732 (java.lang.Integer)
    if_icmpeq L10
    new java/lang/IllegalStateException
    dup
    invokespecial java/lang/IllegalStateException <init>:()V
    athrow
L11
    iload 4
    bipush 103
    if_icmpgt L6
    iload 3
    ldc 1958062732 (java.lang.Integer)
    if_icmpeq L12
    new java/lang/IllegalStateException
    dup
    invokespecial java/lang/IllegalStateException <init>:()V
    athrow
L12
    iload 5
    bipush 103
    if_icmple L13
    iload 3
    ldc 1958062732 (java.lang.Integer)
    if_icmpeq L6
    new java/lang/IllegalStateException
    dup
    invokespecial java/lang/IllegalStateException <init>:()V
    athrow
L6
    iconst_0
    ireturn
L13
    iload 2
    istore 6
    goto L8
L2
    iload 1
    bipush 7
    ishr
    istore 5
    goto L5
L10
    getstatic w a:[[[B
    iconst_1
    aaload
    iload 4
    aaload
    iload 5
    baload
    iconst_2
    iand
    iconst_2
    if_icmpne L9
    iload 3
    ldc 1958062732 (java.lang.Integer)
    if_icmpeq L14
    new java/lang/IllegalStateException
    dup
    invokespecial java/lang/IllegalStateException <init>:()V
    athrow
L9
    iload 0
    bipush 127
    iand
    istore 7
    goto L15
L4
    sipush 128
    iload 7
    isub
    getstatic w e:[[[I
    iload 6
    aaload
    iload 4
    aaload
    iconst_1
    iload 5
    iadd
    iaload
    imul
    getstatic w e:[[[I
    iload 6
    aaload
    iconst_1
    iload 4
    iadd
    aaload
    iconst_1
    iload 5
    iadd
    iaload
    iload 7
    imul
    iadd
    bipush 7
    ishr
    istore 10
    goto L16
L7
    iload 5
    iflt L6
    goto L11
L16
    iload 8
    iload 10
    imul
    sipush 128
    iload 8
    isub
    iload 9
    imul
    iadd
    bipush 7
    ishr
    ireturn
L14
    iinc 6 1
    goto L9
L15
    iload 1
    bipush 127
    iand
    istore 8
    goto L3
L17
    new java/lang/StringBuilder
    dup
    invokespecial java/lang/StringBuilder <init>:()V
    ldc "cl.ar(" (java.lang.String)
    invokevirtual java/lang/StringBuilder append:(Ljava/lang/String;)Ljava/lang/StringBuilder;
    ldc 41 (java.lang.Integer)
    invokevirtual java/lang/StringBuilder append:(C)Ljava/lang/StringBuilder;
    invokevirtual java/lang/StringBuilder toString:()Ljava/lang/String;
    invokestatic k a:(Ljava/lang/Throwable;Ljava/lang/String;)Lee;
    athrow
