cl bj (III)VL1
    getstatic hg cn:Lhh;
    getstatic et eg:Ljava/lang/String;
    invokevirtual hh c:(Ljava/lang/String;)I
    istore 3
    goto L2
L3
    sipush 765
    iload 3
    isub
    istore 5
    goto L4
L5
    iload 4
    getstatic client ii:I
    ldc 811532485 (java.lang.Integer)
    imul
    if_icmpge L6
L7
    getstatic hg cn:Lhh;
    astore 5
L8
    getstatic client iu:[Ljava/lang/String;
    iload 4
    aaload
    invokevirtual java/lang/String length:()I
    ifle L9
    iload 2
    ldc 1702505119 (java.lang.Integer)
    if_icmpgt L10
    new java/lang/IllegalStateException
    dup
    invokespecial java/lang/IllegalStateException <init>:()V
    athrow
L10
    new java/lang/StringBuilder
    dup
    invokespecial java/lang/StringBuilder <init>:()V
    getstatic client iy:[Ljava/lang/String;
    iload 4
    aaload
    invokevirtual java/lang/StringBuilder append:(Ljava/lang/String;)Ljava/lang/StringBuilder;
    getstatic et fz:Ljava/lang/String;
    invokevirtual java/lang/StringBuilder append:(Ljava/lang/String;)Ljava/lang/StringBuilder;
    getstatic client iu:[Ljava/lang/String;
    iload 4
    aaload
    invokevirtual java/lang/StringBuilder append:(Ljava/lang/String;)Ljava/lang/StringBuilder;
    invokevirtual java/lang/StringBuilder toString:()Ljava/lang/String;
    astore 6
    goto L11
L9
    getstatic client iy:[Ljava/lang/String;
    iload 4
    aaload
    astore 6
    goto L11
L6
    iinc 3 8
    goto L12
L13
    iconst_0
    istore 5
    goto L14
L15
    iload 7
    istore 3
L16
    iinc 4 1
    goto L5
L17
    iconst_1
    putstatic client ih:Z
    goto L18
L12
    getstatic client ii:I
    ldc -711914613 (java.lang.Integer)
    imul
    bipush 21
    iadd
    istore 4
    goto L19
L11
    aload 5
    aload 6
    invokevirtual hh c:(Ljava/lang/String;)I
    istore 7
    goto L20
L21
    iload 3
    iload 5
    iadd
    sipush 765
    if_icmple L4
    iload 2
    ldc 1702505119 (java.lang.Integer)
    if_icmpgt L3
    new java/lang/IllegalStateException
    dup
    invokespecial java/lang/IllegalStateException <init>:()V
    athrow
L19
    iload 0
    iload 3
    iconst_2
    idiv
    isub
    istore 5
    goto L21
L4
    iload 5
    ifge L14
    iload 2
    ldc 1702505119 (java.lang.Integer)
    if_icmpgt L13
    new java/lang/IllegalStateException
    dup
    invokespecial java/lang/IllegalStateException <init>:()V
    athrow
L22
    iconst_0
    istore 6
    goto L17
L14
    iload 1
    istore 6
L23
    iload 6
    iload 4
    iadd
    sipush 503
    if_icmple L24
    sipush 503
    iload 4
    isub
    istore 6
    goto L24
L20
    iload 7
    iload 3
    if_icmple L16
    goto L15
L2
    iconst_0
    istore 4
    goto L5
L24
    iload 6
    ifge L17
    iload 2
    ldc 1702505119 (java.lang.Integer)
    if_icmpgt L22
    new java/lang/IllegalStateException
    dup
    invokespecial java/lang/IllegalStateException <init>:()V
    athrow
L18
    iload 5
    ldc 1307742221 (java.lang.Integer)
    imul
    putstatic n ie:I
L25
    ldc -1395984197 (java.lang.Integer)
    iload 6
    imul
    putstatic e ic:I
L26
    ldc 1615987015 (java.lang.Integer)
    iload 3
    imul
    putstatic dx ij:I
L27
    ldc -600562454 (java.lang.Integer)
    getstatic client ii:I
    ldc 79644405 (java.lang.Integer)
    imul
    iadd
    putstatic ax il:I
L28
    return
L29
    new java/lang/StringBuilder
    dup
    invokespecial java/lang/StringBuilder <init>:()V
    ldc "cl.bj(" (java.lang.String)
    invokevirtual java/lang/StringBuilder append:(Ljava/lang/String;)Ljava/lang/StringBuilder;
    ldc 41 (java.lang.Integer)
    invokevirtual java/lang/StringBuilder append:(C)Ljava/lang/StringBuilder;
    invokevirtual java/lang/StringBuilder toString:()Ljava/lang/String;
    invokestatic k a:(Ljava/lang/Throwable;Ljava/lang/String;)Lee;
    athrow
