client s (II)VL1
    aconst_null
    putstatic ec aq:Lex;
    goto L2
L3
    aload 0
    ldc "js5connect_full" (java.lang.String)
    ldc 1166508375 (java.lang.Integer)
    invokevirtual client pf:(Ljava/lang/String;I)V
    goto L4
L5
    iconst_0
    putstatic client ad:I
    goto L6
L7
    ldc -885258088 (java.lang.Integer)
    putstatic client q:I
    goto L8
L6
    getstatic ck bt:I
    ldc 205672577 (java.lang.Integer)
    imul
    getstatic o bz:I
    ldc -944617997 (java.lang.Integer)
    imul
    if_icmpne L9
    iload 2
    ldc 1164900853 (java.lang.Integer)
    if_icmpgt L10
    return
L9
    getstatic o bz:I
    ldc -669377421 (java.lang.Integer)
    imul
    putstatic ck bt:I
L11
    getstatic client bb:I
    ldc -11167423 (java.lang.Integer)
    iadd
    putstatic client bb:I
L12
    ldc -1485572415 (java.lang.Integer)
    getstatic client bb:I
    imul
    iconst_2
    if_icmplt L13
    iload 2
    ldc 1164900853 (java.lang.Integer)
    if_icmpgt L14
    return
L14
    iload 1
    bipush 7
    if_icmpeq L15
    iload 2
    ldc 1164900853 (java.lang.Integer)
    if_icmpgt L16
    new java/lang/IllegalStateException
    dup
    invokespecial java/lang/IllegalStateException <init>:()V
    athrow
L16
    iload 1
    bipush 9
    if_icmpne L13
    iload 2
    ldc 1164900853 (java.lang.Integer)
    if_icmpgt L15
    new java/lang/IllegalStateException
    dup
    invokespecial java/lang/IllegalStateException <init>:()V
    athrow
L15
    ldc 1532705327 (java.lang.Integer)
    getstatic client q:I
    imul
    iconst_5
    if_icmpgt L17
    goto L3
L18
    aload 0
    ldc "js5connect" (java.lang.String)
    ldc 1638096532 (java.lang.Integer)
    invokevirtual client pf:(Ljava/lang/String;I)V
    goto L7
L4
    ldc -885258088 (java.lang.Integer)
    putstatic client q:I
    goto L8
L17
    ldc 140812648 (java.lang.Integer)
    putstatic client an:I
    goto L8
L13
    ldc -1485572415 (java.lang.Integer)
    getstatic client bb:I
    imul
    iconst_2
    if_icmplt L19
    iload 2
    ldc 1164900853 (java.lang.Integer)
    if_icmpgt L20
    new java/lang/IllegalStateException
    dup
    invokespecial java/lang/IllegalStateException <init>:()V
    athrow
L20
    iload 1
    bipush 6
    if_icmpne L19
    iload 2
    ldc 1164900853 (java.lang.Integer)
    if_icmpgt L21
    return
L21
    aload 0
    ldc "js5connect_outofdate" (java.lang.String)
    ldc 2080841907 (java.lang.Integer)
    invokevirtual client pf:(Ljava/lang/String;I)V
L22
    ldc -885258088 (java.lang.Integer)
    putstatic client q:I
    goto L8
L10
    ldc -1391189677 (java.lang.Integer)
    getstatic au bh:I
    imul
    putstatic ck bt:I
    goto L11
L23
    getstatic client q:I
    ldc 1532705327 (java.lang.Integer)
    imul
    iconst_5
    if_icmpgt L24
    goto L18
L2
    aconst_null
    putstatic ep ac:Leo;
    goto L5
L19
    ldc -1485572415 (java.lang.Integer)
    getstatic client bb:I
    imul
    iconst_4
    if_icmplt L8
    iload 2
    ldc 1164900853 (java.lang.Integer)
    if_icmpgt L23
    return
L24
    ldc 140812648 (java.lang.Integer)
    putstatic client an:I
L8
    return
L25
    new java/lang/StringBuilder
    dup
    invokespecial java/lang/StringBuilder <init>:()V
    ldc "client.s(" (java.lang.String)
    invokevirtual java/lang/StringBuilder append:(Ljava/lang/String;)Ljava/lang/StringBuilder;
    ldc 41 (java.lang.Integer)
    invokevirtual java/lang/StringBuilder append:(C)Ljava/lang/StringBuilder;
    invokevirtual java/lang/StringBuilder toString:()Ljava/lang/String;
    invokestatic k a:(Ljava/lang/Throwable;Ljava/lang/String;)Lee;
    athrow
