cm ak (IIIB)VL1
    iload 0
    sipush 128
    if_icmplt L2
    iload 3
    iconst_0
    if_icmpeq L3
    return
L4
    ldc -2118733097 (java.lang.Integer)
    putstatic client gi:I
    goto L5
L6
    iload 4
    iload 6
    imul
    iload 5
    iload 1
    imul
    isub
    bipush 16
    ishr
    istore 9
    goto L7
L8
    iload 0
    sipush 13056
    if_icmpgt L2
    iload 3
    iconst_0
    if_icmpeq L9
    return
L2
    ldc -428275229 (java.lang.Integer)
    putstatic client gh:I
    goto L4
L10
    ldc 2118733097 (java.lang.Integer)
    iload 4
    bipush 9
    ishl
    iload 1
    idiv
    sipush 167
    iadd
    imul
    putstatic client gi:I
    goto L11
L12
    iload 0
    getstatic ev fj:I
    ldc -514809633 (java.lang.Integer)
    imul
    isub
    istore 0
    goto L13
L3
    iload 1
    sipush 128
    if_icmplt L2
    iload 3
    iconst_0
    if_icmpeq L8
    new java/lang/IllegalStateException
    dup
    invokespecial java/lang/IllegalStateException <init>:()V
    athrow
L14
    getstatic cp aw:[I
    getstatic ez fk:I
    ldc -472476531 (java.lang.Integer)
    imul
    iaload
    istore 7
    goto L15
L13
    iload 4
    ldc -866461883 (java.lang.Integer)
    getstatic ev fz:I
    imul
    isub
    istore 4
L16
    iload 1
    ldc -494234791 (java.lang.Integer)
    getstatic e fe:I
    imul
    isub
    istore 1
L17
    getstatic cp aw:[I
    getstatic s fb:I
    ldc -827356221 (java.lang.Integer)
    imul
    iaload
    istore 5
L18
    getstatic cp am:[I
    ldc -827356221 (java.lang.Integer)
    getstatic s fb:I
    imul
    iaload
    istore 6
    goto L14
L9
    iload 1
    sipush 13056
    if_icmple L19
    goto L2
L15
    getstatic cp am:[I
    ldc -472476531 (java.lang.Integer)
    getstatic ez fk:I
    imul
    iaload
    istore 8
L20
    iload 0
    iload 8
    imul
    iload 1
    iload 7
    imul
    iadd
    bipush 16
    ishr
    istore 9
L21
    iload 8
    iload 1
    imul
    iload 7
    iload 0
    imul
    isub
    bipush 16
    ishr
    istore 1
L22
    iload 9
    istore 0
    goto L6
L5
    return
L7
    iload 5
    iload 4
    imul
    iload 6
    iload 1
    imul
    iadd
    bipush 16
    ishr
    istore 1
L23
    iload 9
    istore 4
L24
    iload 1
    bipush 50
    if_icmplt L25
    iload 3
    iconst_0
    if_icmpeq L26
    new java/lang/IllegalStateException
    dup
    invokespecial java/lang/IllegalStateException <init>:()V
    athrow
L19
    iload 0
    iload 1
    ldc -837647185 (java.lang.Integer)
    getstatic fd hz:I
    imul
    ldc 1958062732 (java.lang.Integer)
    invokestatic cl ar:(IIII)I
    iload 2
    isub
    istore 4
    goto L12
L26
    sipush 256
    iload 0
    bipush 9
    ishl
    iload 1
    idiv
    iadd
    ldc 428275229 (java.lang.Integer)
    imul
    putstatic client gh:I
    goto L10
L25
    ldc -428275229 (java.lang.Integer)
    putstatic client gh:I
L27
    ldc -2118733097 (java.lang.Integer)
    putstatic client gi:I
L11
    return
L28
    new java/lang/StringBuilder
    dup
    invokespecial java/lang/StringBuilder <init>:()V
    ldc "cm.ak(" (java.lang.String)
    invokevirtual java/lang/StringBuilder append:(Ljava/lang/String;)Ljava/lang/StringBuilder;
    ldc 41 (java.lang.Integer)
    invokevirtual java/lang/StringBuilder append:(C)Ljava/lang/StringBuilder;
    invokevirtual java/lang/StringBuilder toString:()Ljava/lang/String;
    invokestatic k a:(Ljava/lang/Throwable;Ljava/lang/String;)Lee;
    athrow
