cm l (Ldh;II)VL1
    new gu
    dup
    invokespecial gu <init>:()V
    astore 3
L2
    aload 3
    aload 0
    ldc 1499183319 (java.lang.Integer)
    invokevirtual dh z:(I)I
    ldc -241705523 (java.lang.Integer)
    imul
    putfield gu a:I
L3
    aload 3
    aload 0
    ldc -2108324590 (java.lang.Integer)
    invokevirtual dh x:(I)I
    ldc 97064677 (java.lang.Integer)
    imul
    putfield gu e:I
L4
    aload 3
    aload 3
    getfield gu a:I
    ldc 1917343493 (java.lang.Integer)
    imul
    newarray 10
    putfield gu l:[I
L5
    aload 3
    ldc 1917343493 (java.lang.Integer)
    aload 3
    getfield gu a:I
    imul
    newarray 10
    putfield gu c:[I
L6
    aload 3
    ldc 1917343493 (java.lang.Integer)
    aload 3
    getfield gu a:I
    imul
    anewarray java/lang/reflect/Field
    putfield gu u:[Ljava/lang/reflect/Field;
L7
    aload 3
    ldc 1917343493 (java.lang.Integer)
    aload 3
    getfield gu a:I
    imul
    newarray 10
    putfield gu w:[I
L8
    aload 3
    aload 3
    getfield gu a:I
    ldc 1917343493 (java.lang.Integer)
    imul
    anewarray java/lang/reflect/Method
    putfield gu i:[Ljava/lang/reflect/Method;
L9
    aload 3
    ldc 1917343493 (java.lang.Integer)
    aload 3
    getfield gu a:I
    imul
    anewarray [[B
    putfield gu r:[[[B
L10
    iconst_0
    istore 4
L11
    iload 4
    ldc 1917343493 (java.lang.Integer)
    aload 3
    getfield gu a:I
    imul
    if_icmpge L12
    iload 2
    ldc 1672104587 (java.lang.Integer)
    if_icmpeq L13
    return
L13
    aload 0
    ldc 1653060944 (java.lang.Integer)
    invokevirtual dh z:(I)I
    istore 5
L14
    iload 5
    ifeq L15
    iload 5
    iconst_1
    if_icmpeq L15
    iload 2
    ldc 1672104587 (java.lang.Integer)
    if_icmpeq L16
    return
L16
    iconst_2
    iload 5
    if_icmpne L17
    iload 2
    ldc 1672104587 (java.lang.Integer)
    if_icmpeq L15
    new java/lang/IllegalStateException
    dup
    invokespecial java/lang/IllegalStateException <init>:()V
    athrow
L15
    aload 0
    ldc 1742230118 (java.lang.Integer)
    invokevirtual dh p:(I)Ljava/lang/String;
    astore 6
L18
    aload 0
    ldc -563411516 (java.lang.Integer)
    invokevirtual dh p:(I)Ljava/lang/String;
    astore 7
L19
    iconst_0
    istore 8
L20
    iload 5
    iconst_1
    if_icmpne L21
    iload 2
    ldc 1672104587 (java.lang.Integer)
    if_icmpeq L22
    new java/lang/IllegalStateException
    dup
    invokespecial java/lang/IllegalStateException <init>:()V
    athrow
L22
    aload 0
    ldc -2141562612 (java.lang.Integer)
    invokevirtual dh x:(I)I
    istore 8
L21
    aload 3
    getfield gu l:[I
    iload 4
    iload 5
    iastore
L23
    aload 3
    getfield gu w:[I
    iload 4
    iload 8
    iastore
L24
    aload 6
    ldc -1876009004 (java.lang.Integer)
    invokestatic at c:(Ljava/lang/String;I)Ljava/lang/Class;
    invokevirtual java/lang/Class getClassLoader:()Ljava/lang/ClassLoader;
    ifnonnull L25
    iload 2
    ldc 1672104587 (java.lang.Integer)
    if_icmpeq L26
    new java/lang/IllegalStateException
    dup
    invokespecial java/lang/IllegalStateException <init>:()V
    athrow
L26
    new java/lang/SecurityException
    dup
    invokespecial java/lang/SecurityException <init>:()V
    athrow
L25
    aload 3
    getfield gu u:[Ljava/lang/reflect/Field;
    iload 4
    aload 6
    ldc -155244490 (java.lang.Integer)
    invokestatic at c:(Ljava/lang/String;I)Ljava/lang/Class;
    aload 7
    invokevirtual java/lang/Class getDeclaredField:(Ljava/lang/String;)Ljava/lang/reflect/Field;
    aastore
L27
    goto L28
L17
    iconst_3
    iload 5
    if_icmpeq L29
    iload 2
    ldc 1672104587 (java.lang.Integer)
    if_icmpeq L30
    return
L30
    iload 5
    iconst_4
    if_icmpne L28
    iload 2
    ldc 1672104587 (java.lang.Integer)
    if_icmpeq L29
    new java/lang/IllegalStateException
    dup
    invokespecial java/lang/IllegalStateException <init>:()V
    athrow
L29
    aload 0
    ldc -1115273391 (java.lang.Integer)
    invokevirtual dh p:(I)Ljava/lang/String;
    astore 6
L31
    aload 0
    ldc -204892304 (java.lang.Integer)
    invokevirtual dh p:(I)Ljava/lang/String;
    astore 7
L32
    aload 0
    ldc 820290279 (java.lang.Integer)
    invokevirtual dh z:(I)I
    istore 8
L33
    iload 8
    anewarray java/lang/String
    astore 9
L34
    iconst_0
    istore 10
L35
    iload 10
    iload 8
    if_icmpge L36
    iload 2
    ldc 1672104587 (java.lang.Integer)
    if_icmpeq L37
    return
L37
    aload 9
    iload 10
    aload 0
    ldc 222979020 (java.lang.Integer)
    invokevirtual dh p:(I)Ljava/lang/String;
    aastore
    iinc 10 1
    goto L35
L36
    aload 0
    ldc -1768517771 (java.lang.Integer)
    invokevirtual dh p:(I)Ljava/lang/String;
    astore 10
L38
    iload 8
    anewarray [B
    astore 11
L39
    iconst_3
    iload 5
    if_icmpne L40
    iload 2
    ldc 1672104587 (java.lang.Integer)
    if_icmpeq L41
    return
L41
    iconst_0
    istore 12
L42
    iload 12
    iload 8
    if_icmpge L40
    iload 2
    ldc 1672104587 (java.lang.Integer)
    if_icmpeq L43
    new java/lang/IllegalStateException
    dup
    invokespecial java/lang/IllegalStateException <init>:()V
    athrow
L43
    aload 0
    ldc -2136164284 (java.lang.Integer)
    invokevirtual dh x:(I)I
    istore 13
L44
    aload 11
    iload 12
    iload 13
    newarray 8
    aastore
L45
    aload 0
    aload 11
    iload 12
    aaload
    iconst_0
    iload 13
    bipush -26
    invokevirtual dh ap:([BIIB)V
L46
    iinc 12 1
    goto L42
L40
    aload 3
    getfield gu l:[I
    iload 4
    iload 5
    iastore
L47
    iload 8
    anewarray java/lang/Class
    astore 12
L48
    iconst_0
    istore 13
L49
    iload 13
    iload 8
    if_icmpge L50
    iload 2
    ldc 1672104587 (java.lang.Integer)
    if_icmpeq L51
    return
L51
    aload 12
    iload 13
    aload 9
    iload 13
    aaload
    ldc -1948432160 (java.lang.Integer)
    invokestatic at c:(Ljava/lang/String;I)Ljava/lang/Class;
    aastore
    iinc 13 1
    goto L49
L50
    aload 10
    ldc -443394097 (java.lang.Integer)
    invokestatic at c:(Ljava/lang/String;I)Ljava/lang/Class;
    astore 13
L52
    aload 6
    ldc -1958747627 (java.lang.Integer)
    invokestatic at c:(Ljava/lang/String;I)Ljava/lang/Class;
    invokevirtual java/lang/Class getClassLoader:()Ljava/lang/ClassLoader;
    ifnonnull L53
    iload 2
    ldc 1672104587 (java.lang.Integer)
    if_icmpeq L54
    new java/lang/IllegalStateException
    dup
    invokespecial java/lang/IllegalStateException <init>:()V
    athrow
L54
    new java/lang/SecurityException
    dup
    invokespecial java/lang/SecurityException <init>:()V
    athrow
L53
    aload 6
    ldc -202353908 (java.lang.Integer)
    invokestatic at c:(Ljava/lang/String;I)Ljava/lang/Class;
    invokevirtual java/lang/Class getDeclaredMethods:()[Ljava/lang/reflect/Method;
    astore 14
L55
    aload 14
    astore 15
L56
    iconst_0
    istore 16
L57
    iload 16
    aload 15
    arraylength
    if_icmpge L58
L59
    aload 15
    iload 16
    aaload
    astore 17
L60
    aload 17
    invokevirtual java/lang/reflect/Method getName:()Ljava/lang/String;
    aload 7
    invokevirtual java/lang/String equals:(Ljava/lang/Object;)Z
    ifeq L61
    iload 2
    ldc 1672104587 (java.lang.Integer)
    if_icmpeq L62
    new java/lang/IllegalStateException
    dup
    invokespecial java/lang/IllegalStateException <init>:()V
    athrow
L62
    aload 17
    invokevirtual java/lang/reflect/Method getParameterTypes:()[Ljava/lang/Class;
    astore 18
L63
    aload 12
    arraylength
    aload 18
    arraylength
    if_icmpne L61
    iload 2
    ldc 1672104587 (java.lang.Integer)
    if_icmpeq L64
    new java/lang/IllegalStateException
    dup
    invokespecial java/lang/IllegalStateException <init>:()V
    athrow
L64
    iconst_1
    istore 19
L65
    iconst_0
    istore 20
L66
    iload 20
    aload 12
    arraylength
    if_icmpge L67
    iload 2
    ldc 1672104587 (java.lang.Integer)
    if_icmpeq L68
    new java/lang/IllegalStateException
    dup
    invokespecial java/lang/IllegalStateException <init>:()V
    athrow
L68
    aload 12
    iload 20
    aaload
    aload 18
    iload 20
    aaload
    if_acmpeq L69
L70
    iconst_0
    istore 19
L71
    goto L67
L69
    iinc 20 1
    goto L66
L67
    iload 19
    ifeq L61
    aload 13
    aload 17
    invokevirtual java/lang/reflect/Method getReturnType:()Ljava/lang/Class;
    if_acmpne L61
    iload 2
    ldc 1672104587 (java.lang.Integer)
    if_icmpeq L72
    return
L72
    aload 3
    getfield gu i:[Ljava/lang/reflect/Method;
    iload 4
    aload 17
    aastore
L61
    iinc 16 1
    goto L57
L58
    aload 3
    getfield gu r:[[[B
    iload 4
    aload 11
    aastore
L28
    goto L73
L74
    astore 5
L75
    aload 3
    getfield gu c:[I
    iload 4
    iconst_m1
    iastore
L76
    goto L73
L77
    astore 5
L78
    aload 3
    getfield gu c:[I
    iload 4
    bipush -2
    iastore
L79
    goto L73
L80
    astore 5
L81
    aload 3
    getfield gu c:[I
    iload 4
    bipush -3
    iastore
L82
    goto L73
L83
    astore 5
L84
    aload 3
    getfield gu c:[I
    iload 4
    bipush -4
    iastore
L85
    goto L73
L86
    astore 5
L87
    aload 3
    getfield gu c:[I
    iload 4
    bipush -5
    iastore
L73
    iinc 4 1
    goto L11
L12
    getstatic ga e:Lgk;
    aload 3
    invokevirtual gk e:(Lgm;)V
L88
    return
L89
    new java/lang/StringBuilder
    dup
    invokespecial java/lang/StringBuilder <init>:()V
    ldc "cm.l(" (java.lang.String)
    invokevirtual java/lang/StringBuilder append:(Ljava/lang/String;)Ljava/lang/StringBuilder;
    ldc 41 (java.lang.Integer)
    invokevirtual java/lang/StringBuilder append:(C)Ljava/lang/StringBuilder;
    invokevirtual java/lang/StringBuilder toString:()Ljava/lang/String;
    invokestatic k a:(Ljava/lang/Throwable;Ljava/lang/String;)Lee;
    athrow
