cq au (Lab;B)VL1
    ldc -117546507 (java.lang.Integer)
    getstatic client b:I
    imul
    aload 0
    getfield ab bj:I
    ldc 842014775 (java.lang.Integer)
    imul
    if_icmpeq L2
    iload 1
    iconst_4
    if_icmpne L3
    return
L4
    aload 0
    getfield ab bm:I
    ldc 1554762601 (java.lang.Integer)
    imul
    iconst_1
    iadd
    aload 0
    getfield ab bl:I
    ldc 1048158519 (java.lang.Integer)
    imul
    ldc 152969838 (java.lang.Integer)
    invokestatic cd e:(II)Lah;
    getfield ah r:[I
    ldc -166629429 (java.lang.Integer)
    aload 0
    getfield ab bk:I
    imul
    iaload
    if_icmple L5
    iload 1
    iconst_4
    if_icmpne L2
    new java/lang/IllegalStateException
    dup
    invokespecial java/lang/IllegalStateException <init>:()V
    athrow
L6
    aload 0
    iconst_0
    putfield ab by:I
    goto L7
L8
    aload 0
    ldc 1539365888 (java.lang.Integer)
    putfield ab by:I
    goto L9
L2
    aload 0
    getfield ab bj:I
    ldc 842014775 (java.lang.Integer)
    imul
    ldc 1585316651 (java.lang.Integer)
    aload 0
    getfield ab bb:I
    imul
    isub
    istore 2
L10
    ldc -117546507 (java.lang.Integer)
    getstatic client b:I
    imul
    aload 0
    getfield ab bb:I
    ldc 1585316651 (java.lang.Integer)
    imul
    isub
    istore 3
L11
    aload 0
    getfield ab p:I
    ldc 1020813888 (java.lang.Integer)
    imul
    aload 0
    getfield ab ba:I
    ldc -1399488384 (java.lang.Integer)
    imul
    iadd
    istore 4
    goto L12
L13
    aload 0
    getfield ab bq:I
    ldc 649798987 (java.lang.Integer)
    imul
    iconst_2
    if_icmpne L7
    iload 1
    iconst_4
    if_icmpne L6
    return
L14
    aload 0
    getfield ab bf:I
    ldc -272750720 (java.lang.Integer)
    imul
    ldc 1020813888 (java.lang.Integer)
    aload 0
    getfield ab p:I
    imul
    iadd
    istore 6
L15
    aload 0
    getfield ab p:I
    ldc 1020813888 (java.lang.Integer)
    imul
    aload 0
    getfield ab bd:I
    ldc -1793232768 (java.lang.Integer)
    imul
    iadd
    istore 7
    goto L16
L3
    iconst_m1
    ldc 1048158519 (java.lang.Integer)
    aload 0
    getfield ab bl:I
    imul
    if_icmpeq L2
    iload 1
    iconst_4
    if_icmpne L17
    new java/lang/IllegalStateException
    dup
    invokespecial java/lang/IllegalStateException <init>:()V
    athrow
L18
    ldc 649798987 (java.lang.Integer)
    aload 0
    getfield ab bq:I
    imul
    ifne L9
    iload 1
    iconst_4
    if_icmpne L8
    new java/lang/IllegalStateException
    dup
    invokespecial java/lang/IllegalStateException <init>:()V
    athrow
L5
    aload 0
    iconst_0
    putfield ab cf:I
    goto L18
L19
    aload 0
    ldc -1377800704 (java.lang.Integer)
    putfield ab by:I
    goto L20
L16
    aload 0
    ldc 1306077789 (java.lang.Integer)
    iload 6
    iload 3
    imul
    iload 4
    iload 2
    iload 3
    isub
    imul
    iadd
    iload 2
    idiv
    imul
    putfield ab b:I
L21
    aload 0
    iload 7
    iload 3
    imul
    iload 5
    iload 2
    iload 3
    isub
    imul
    iadd
    iload 2
    idiv
    ldc 1172037717 (java.lang.Integer)
    imul
    putfield ab x:I
    goto L5
L22
    aload 0
    ldc 161565184 (java.lang.Integer)
    putfield ab by:I
    goto L13
L12
    aload 0
    getfield ab bx:I
    ldc -1330427520 (java.lang.Integer)
    imul
    aload 0
    getfield ab p:I
    ldc 1020813888 (java.lang.Integer)
    imul
    iadd
    istore 5
    goto L14
L9
    ldc 649798987 (java.lang.Integer)
    aload 0
    getfield ab bq:I
    imul
    iconst_1
    if_icmpne L13
    iload 1
    iconst_4
    if_icmpne L22
    new java/lang/IllegalStateException
    dup
    invokespecial java/lang/IllegalStateException <init>:()V
    athrow
L7
    ldc 649798987 (java.lang.Integer)
    aload 0
    getfield ab bq:I
    imul
    iconst_3
    if_icmpne L20
    goto L19
L17
    ldc -1613918591 (java.lang.Integer)
    aload 0
    getfield ab bw:I
    imul
    ifne L2
    goto L4
L20
    aload 0
    aload 0
    getfield ab by:I
    ldc -1437200415 (java.lang.Integer)
    imul
    putfield ab n:I
L23
    return
L24
    new java/lang/StringBuilder
    dup
    invokespecial java/lang/StringBuilder <init>:()V
    ldc "cq.au(" (java.lang.String)
    invokevirtual java/lang/StringBuilder append:(Ljava/lang/String;)Ljava/lang/StringBuilder;
    ldc 41 (java.lang.Integer)
    invokevirtual java/lang/StringBuilder append:(C)Ljava/lang/StringBuilder;
    invokevirtual java/lang/StringBuilder toString:()Ljava/lang/String;
    invokestatic k a:(Ljava/lang/Throwable;Ljava/lang/String;)Lee;
    athrow
