cw e (Ldz;Ljava/lang/Object;I)VL1
    aload 0
    getfield dz r:Ljava/awt/EventQueue;
    ifnonnull L2
    iload 2
    ldc -1274994013 (java.lang.Integer)
    if_icmpeq L3
    new java/lang/IllegalStateException
    dup
    invokespecial java/lang/IllegalStateException <init>:()V
    athrow
L4
    aload 0
    getfield dz r:Ljava/awt/EventQueue;
    new java/awt/event/ActionEvent
    dup
    aload 1
    sipush 1001
    ldc "dummy" (java.lang.String)
    invokespecial java/awt/event/ActionEvent <init>:(Ljava/lang/Object;ILjava/lang/String;)V
    invokevirtual java/awt/EventQueue postEvent:(Ljava/awt/AWTEvent;)V
    goto L5
L2
    iconst_0
    istore 3
    goto L6
L7
    aload 0
    getfield dz r:Ljava/awt/EventQueue;
    invokevirtual java/awt/EventQueue peekEvent:()Ljava/awt/AWTEvent;
    ifnull L8
    iload 2
    ldc -1274994013 (java.lang.Integer)
    if_icmpeq L9
    new java/lang/IllegalStateException
    dup
    invokespecial java/lang/IllegalStateException <init>:()V
    athrow
L6
    iload 3
    bipush 50
    if_icmpge L8
    iload 2
    ldc -1274994013 (java.lang.Integer)
    if_icmpeq L7
    return
L9
    lconst_1
    invokestatic ak e:(J)V
    iinc 3 1
    goto L6
L8
    aconst_null
    aload 1
    if_acmpeq L5
    iload 2
    ldc -1274994013 (java.lang.Integer)
    if_icmpeq L4
    new java/lang/IllegalStateException
    dup
    invokespecial java/lang/IllegalStateException <init>:()V
    athrow
L3
    return
L5
    return
L10
    new java/lang/StringBuilder
    dup
    invokespecial java/lang/StringBuilder <init>:()V
    ldc "cw.e(" (java.lang.String)
    invokevirtual java/lang/StringBuilder append:(Ljava/lang/String;)Ljava/lang/StringBuilder;
    ldc 41 (java.lang.Integer)
    invokevirtual java/lang/StringBuilder append:(C)Ljava/lang/StringBuilder;
    invokevirtual java/lang/StringBuilder toString:()Ljava/lang/String;
    invokestatic k a:(Ljava/lang/Throwable;Ljava/lang/String;)Lee;
    athrow
