cz ao (Ljava/lang/String;I)VL1
    aload 0
    ldc "toggleroof" (java.lang.String)
    invokevirtual java/lang/String equalsIgnoreCase:(Ljava/lang/String;)Z
    ifeq L2
    iload 1
    ldc 2087987050 (java.lang.Integer)
    if_icmpeq L3
    return
L4
    iconst_0
    goto L5
L6
    iconst_1
    goto L5
L7
    iconst_2
    ldc -708614931 (java.lang.Integer)
    getstatic client r:I
    imul
    if_icmpne L8
    goto L9
L5
    putfield f l:Z
L10
    ldc 211669360 (java.lang.Integer)
    invokestatic aa l:(I)V
L11
    getstatic dk ol:Lf;
    getfield f l:Z
    ifeq L12
    goto L13
L14
    aload 0
    ldc "errortest" (java.lang.String)
    invokevirtual java/lang/String equalsIgnoreCase:(Ljava/lang/String;)Z
    ifeq L8
    iload 1
    ldc 2087987050 (java.lang.Integer)
    if_icmpeq L7
    new java/lang/IllegalStateException
    dup
    invokespecial java/lang/IllegalStateException <init>:()V
    athrow
L12
    bipush 99
    ldc "" (java.lang.String)
    ldc "Roofs will only be removed selectively" (java.lang.String)
    ldc 1919708577 (java.lang.Integer)
    invokestatic c a:(ILjava/lang/String;Ljava/lang/String;I)V
L2
    getstatic client jp:I
    ldc 339448555 (java.lang.Integer)
    imul
    iconst_2
    if_icmplt L8
L15
    aload 0
    ldc "fpson" (java.lang.String)
    invokevirtual java/lang/String equalsIgnoreCase:(Ljava/lang/String;)Z
    ifeq L16
    iconst_1
    putstatic client ao:Z
L16
    aload 0
    ldc "fpsoff" (java.lang.String)
    invokevirtual java/lang/String equalsIgnoreCase:(Ljava/lang/String;)Z
    ifeq L17
    iload 1
    ldc 2087987050 (java.lang.Integer)
    if_icmpeq L18
    new java/lang/IllegalStateException
    dup
    invokespecial java/lang/IllegalStateException <init>:()V
    athrow
L19
    aload 0
    ldc "clientdrop" (java.lang.String)
    invokevirtual java/lang/String equalsIgnoreCase:(Ljava/lang/String;)Z
    ifeq L14
    iload 1
    ldc 2087987050 (java.lang.Integer)
    if_icmpeq L20
    return
L17
    aload 0
    ldc "gc" (java.lang.String)
    invokevirtual java/lang/String equalsIgnoreCase:(Ljava/lang/String;)Z
    ifeq L19
    iload 1
    ldc 2087987050 (java.lang.Integer)
    if_icmpeq L21
    new java/lang/IllegalStateException
    dup
    invokespecial java/lang/IllegalStateException <init>:()V
    athrow
L21
    invokestatic java/lang/System gc:()V
    goto L19
L13
    bipush 99
    ldc "" (java.lang.String)
    ldc "Roofs are now all hidden" (java.lang.String)
    ldc 1633342500 (java.lang.Integer)
    invokestatic c a:(ILjava/lang/String;Ljava/lang/String;I)V
    goto L2
L3
    getstatic dk ol:Lf;
    getstatic dk ol:Lf;
    getfield f l:Z
    ifne L4
    goto L6
L22
    getstatic client cd:Ldj;
    aload 0
    invokevirtual java/lang/String length:()I
    iconst_1
    iadd
    bipush 8
    invokevirtual dj e:(IB)V
    goto L23
L18
    iconst_0
    putstatic client ao:Z
    goto L17
L9
    new java/lang/RuntimeException
    dup
    invokespecial java/lang/RuntimeException <init>:()V
    athrow
L8
    getstatic client cd:Ldj;
    iconst_0
    ldc -430583147 (java.lang.Integer)
    invokevirtual dj hl:(II)V
    goto L22
L20
    ldc -79630729 (java.lang.Integer)
    invokestatic ab x:(I)V
    goto L14
L23
    getstatic client cd:Ldj;
    aload 0
    sipush 502
    invokevirtual dj i:(Ljava/lang/String;S)V
L24
    return
L25
    new java/lang/StringBuilder
    dup
    invokespecial java/lang/StringBuilder <init>:()V
    ldc "cz.ao(" (java.lang.String)
    invokevirtual java/lang/StringBuilder append:(Ljava/lang/String;)Ljava/lang/StringBuilder;
    ldc 41 (java.lang.Integer)
    invokevirtual java/lang/StringBuilder append:(C)Ljava/lang/StringBuilder;
    invokevirtual java/lang/StringBuilder toString:()Ljava/lang/String;
    invokestatic k a:(Ljava/lang/Throwable;Ljava/lang/String;)Lee;
    athrow
