d dl (Lfb;I)Ljava/lang/String;L1
    aload 0
    bipush 106
    invokestatic t dj:(Lfb;B)I
    istore 3
    goto L2
L3
    aconst_null
    areturn
L4
    iload 2
    ifne L5
    iload 1
    ldc -210186597 (java.lang.Integer)
    if_icmpeq L6
    new java/lang/IllegalStateException
    dup
    invokespecial java/lang/IllegalStateException <init>:()V
    athrow
L2
    iload 3
    bipush 11
    ishr
    bipush 63
    iand
    istore 2
    goto L4
L5
    aconst_null
    aload 0
    getfield fb cf:Ljava/lang/String;
    if_acmpeq L3
    iload 1
    ldc -210186597 (java.lang.Integer)
    if_icmpeq L7
    new java/lang/IllegalStateException
    dup
    invokespecial java/lang/IllegalStateException <init>:()V
    athrow
L7
    aload 0
    getfield fb cf:Ljava/lang/String;
    invokevirtual java/lang/String trim:()Ljava/lang/String;
    invokevirtual java/lang/String length:()I
    ifne L8
    iload 1
    ldc -210186597 (java.lang.Integer)
    if_icmpeq L3
    new java/lang/IllegalStateException
    dup
    invokespecial java/lang/IllegalStateException <init>:()V
    athrow
L6
    aconst_null
    areturn
L8
    aload 0
    getfield fb cf:Ljava/lang/String;
    areturn
L9
    new java/lang/StringBuilder
    dup
    invokespecial java/lang/StringBuilder <init>:()V
    ldc "d.dl(" (java.lang.String)
    invokevirtual java/lang/StringBuilder append:(Ljava/lang/String;)Ljava/lang/StringBuilder;
    ldc 41 (java.lang.Integer)
    invokevirtual java/lang/StringBuilder append:(C)Ljava/lang/StringBuilder;
    invokevirtual java/lang/StringBuilder toString:()Ljava/lang/String;
    invokestatic k a:(Ljava/lang/Throwable;Ljava/lang/String;)Lee;
    athrow
