db cc (IB)VL1
    bipush -37
    invokestatic i cw:(B)V
    goto L2
L3
    iconst_0
    putstatic client ne:I
    goto L4
L5
    iload 0
    ldc 1733472067 (java.lang.Integer)
    invokestatic da e:(II)Lan;
    getfield an c:I
    ldc -2081121219 (java.lang.Integer)
    imul
    istore 2
    goto L6
L7
    iconst_m1
    getstatic client mt:I
    ldc 414185843 (java.lang.Integer)
    imul
    if_icmpeq L8
    iload 1
    iconst_0
    if_icmpne L9
    new java/lang/IllegalStateException
    dup
    invokespecial java/lang/IllegalStateException <init>:()V
    athrow
L10
    return
L11
    getstatic fl l:[I
    iload 0
    iaload
    istore 3
L12
    iload 2
    iconst_1
    if_icmpne L13
    iload 1
    iconst_0
    if_icmpne L14
    new java/lang/IllegalStateException
    dup
    invokespecial java/lang/IllegalStateException <init>:()V
    athrow
L14
    iconst_1
    iload 3
    if_icmpne L15
    iload 1
    iconst_0
    if_icmpne L16
    new java/lang/IllegalStateException
    dup
    invokespecial java/lang/IllegalStateException <init>:()V
    athrow
L16
    ldc 0.9 (java.lang.Double)
    invokestatic cp w:(D)V
L17
    getstatic cp ap:Lce;
    checkcast cq
    ldc 0.9 (java.lang.Double)
    invokevirtual cq z:(D)V
L15
    iconst_2
    iload 3
    if_icmpne L18
    goto L19
L13
    iconst_3
    iload 2
    if_icmpne L20
    iload 1
    iconst_0
    if_icmpne L21
    new java/lang/IllegalStateException
    dup
    invokespecial java/lang/IllegalStateException <init>:()V
    athrow
L22
    iconst_0
    istore 4
    goto L23
L24
    ldc -763230144 (java.lang.Integer)
    putstatic client np:I
    goto L25
L26
    ldc 0.7 (java.lang.Double)
    invokestatic cp w:(D)V
L27
    getstatic cp ap:Lce;
    checkcast cq
    ldc 0.7 (java.lang.Double)
    invokevirtual cq z:(D)V
    goto L28
L29
    iload 3
    iconst_2
    if_icmpne L25
    iload 1
    iconst_0
    if_icmpne L24
    return
L30
    ldc 0.6 (java.lang.Double)
    invokestatic cp w:(D)V
    goto L31
L32
    ldc 1453968013 (java.lang.Integer)
    invokestatic o e:(I)[Lq;
    iload 3
    ldc 508662324 (java.lang.Integer)
    invokestatic d e:([Lca;II)Lca;
    checkcast q
    putstatic client al:Lq;
    goto L33
L34
    iconst_1
    invokestatic au m:(B)V
    goto L13
L35
    ldc 246790143 (java.lang.Integer)
    putstatic client ne:I
    goto L36
L21
    iconst_0
    istore 4
    goto L37
L2
    ldc 1912042153 (java.lang.Integer)
    invokestatic b e:(I)V
    goto L5
L38
    sipush 255
    istore 4
    goto L39
L40
    iload 3
    sipush 2047
    iand
    ldc 663489355 (java.lang.Integer)
    imul
    putstatic client hd:I
    goto L41
L42
    sipush 192
    istore 4
L43
    iload 3
    iconst_2
    if_icmpne L44
    iload 1
    iconst_0
    if_icmpne L45
    new java/lang/IllegalStateException
    dup
    invokespecial java/lang/IllegalStateException <init>:()V
    athrow
L45
    sipush 128
    istore 4
L44
    iconst_3
    iload 3
    if_icmpne L46
    iload 1
    iconst_0
    if_icmpne L47
    return
L23
    iload 4
    getstatic client mv:I
    ldc 1646518153 (java.lang.Integer)
    imul
    if_icmpeq L20
    iload 1
    iconst_0
    if_icmpne L48
    new java/lang/IllegalStateException
    dup
    invokespecial java/lang/IllegalStateException <init>:()V
    athrow
L46
    iload 3
    iconst_4
    if_icmpne L23
    iload 1
    iconst_0
    if_icmpne L22
    new java/lang/IllegalStateException
    dup
    invokespecial java/lang/IllegalStateException <init>:()V
    athrow
L39
    iload 3
    iconst_1
    if_icmpne L43
    iload 1
    iconst_0
    if_icmpne L42
    new java/lang/IllegalStateException
    dup
    invokespecial java/lang/IllegalStateException <init>:()V
    athrow
L49
    iload 4
    bipush 50
    invokestatic cd l:(IB)V
    goto L50
L48
    iconst_0
    getstatic client mv:I
    ldc 1646518153 (java.lang.Integer)
    imul
    if_icmpne L8
    iload 1
    iconst_0
    if_icmpne L7
    new java/lang/IllegalStateException
    dup
    invokespecial java/lang/IllegalStateException <init>:()V
    athrow
L18
    iload 3
    iconst_3
    if_icmpne L28
    iload 1
    iconst_0
    if_icmpne L26
    new java/lang/IllegalStateException
    dup
    invokespecial java/lang/IllegalStateException <init>:()V
    athrow
L9
    getstatic eo bw:Lfo;
    ldc 414185843 (java.lang.Integer)
    getstatic client mt:I
    imul
    iconst_0
    iload 4
    iconst_0
    ldc -1561762019 (java.lang.Integer)
    invokestatic ae a:(Lfv;IIIZI)V
L51
    iconst_0
    putstatic client mk:Z
    goto L50
L52
    iload 3
    iconst_2
    if_icmpne L53
    iload 1
    iconst_0
    if_icmpne L54
    new java/lang/IllegalStateException
    dup
    invokespecial java/lang/IllegalStateException <init>:()V
    athrow
L55
    ldc 1287250145 (java.lang.Integer)
    invokestatic l c:(I)V
L56
    iconst_0
    putstatic client mk:Z
    goto L50
L37
    iload 3
    ifne L39
    goto L38
L50
    ldc -1940633927 (java.lang.Integer)
    iload 4
    imul
    putstatic client mv:I
    goto L20
L28
    iconst_4
    iload 3
    if_icmpne L34
    iload 1
    iconst_0
    if_icmpne L30
    new java/lang/IllegalStateException
    dup
    invokespecial java/lang/IllegalStateException <init>:()V
    athrow
L57
    iconst_0
    iload 3
    if_icmpne L36
    iload 1
    iconst_0
    if_icmpne L35
    new java/lang/IllegalStateException
    dup
    invokespecial java/lang/IllegalStateException <init>:()V
    athrow
L58
    ldc 896741472 (java.lang.Integer)
    putstatic client ne:I
    goto L52
L36
    iload 3
    iconst_1
    if_icmpne L52
    iload 1
    iconst_0
    if_icmpne L58
    new java/lang/IllegalStateException
    dup
    invokespecial java/lang/IllegalStateException <init>:()V
    athrow
L31
    getstatic cp ap:Lce;
    checkcast cq
    ldc 0.6 (java.lang.Double)
    invokevirtual cq z:(D)V
    goto L34
L59
    ldc -1144845216 (java.lang.Integer)
    putstatic client np:I
    goto L29
L60
    getstatic cp ap:Lce;
    checkcast cq
    ldc 0.8 (java.lang.Double)
    invokevirtual cq z:(D)V
    goto L18
L20
    iconst_4
    iload 2
    if_icmpne L4
    iload 1
    iconst_0
    if_icmpne L57
    new java/lang/IllegalStateException
    dup
    invokespecial java/lang/IllegalStateException <init>:()V
    athrow
L61
    ldc 298913824 (java.lang.Integer)
    putstatic client ne:I
L62
    iconst_4
    iload 3
    if_icmpne L4
    iload 1
    iconst_0
    if_icmpne L3
    new java/lang/IllegalStateException
    dup
    invokespecial java/lang/IllegalStateException <init>:()V
    athrow
L47
    bipush 64
    istore 4
    goto L46
L4
    iload 2
    iconst_5
    if_icmpne L63
    iload 1
    iconst_0
    if_icmpne L64
    new java/lang/IllegalStateException
    dup
    invokespecial java/lang/IllegalStateException <init>:()V
    athrow
L65
    ldc -977663905 (java.lang.Integer)
    putstatic client np:I
    goto L66
L63
    bipush 6
    iload 2
    if_icmpne L67
    iload 1
    iconst_0
    if_icmpne L68
    return
L6
    iconst_0
    iload 2
    if_icmpne L11
    iload 1
    iconst_0
    if_icmpne L10
    new java/lang/IllegalStateException
    dup
    invokespecial java/lang/IllegalStateException <init>:()V
    athrow
L67
    iload 2
    bipush 9
    if_icmpne L69
    iload 1
    iconst_0
    if_icmpne L70
    new java/lang/IllegalStateException
    dup
    invokespecial java/lang/IllegalStateException <init>:()V
    athrow
L70
    ldc -2082136997 (java.lang.Integer)
    iload 3
    imul
    putstatic client jd:I
L69
    bipush 10
    iload 2
    if_icmpne L71
L72
    iload 3
    ifne L66
    goto L65
L64
    ldc -1722427159 (java.lang.Integer)
    iload 3
    imul
    putstatic client hp:I
    goto L63
L66
    iconst_1
    iload 3
    if_icmpne L29
    iload 1
    iconst_0
    if_icmpne L59
    new java/lang/IllegalStateException
    dup
    invokespecial java/lang/IllegalStateException <init>:()V
    athrow
L73
    getstatic q e:Lq;
    putstatic client al:Lq;
    goto L74
L25
    iconst_3
    iload 3
    if_icmpne L75
    iload 1
    iconst_0
    if_icmpne L76
    new java/lang/IllegalStateException
    dup
    invokespecial java/lang/IllegalStateException <init>:()V
    athrow
L77
    bipush 18
    iload 2
    if_icmpne L74
    iload 1
    iconst_0
    if_icmpne L32
    new java/lang/IllegalStateException
    dup
    invokespecial java/lang/IllegalStateException <init>:()V
    athrow
L54
    ldc 597827648 (java.lang.Integer)
    putstatic client ne:I
    goto L53
L76
    ldc -381615072 (java.lang.Integer)
    putstatic client np:I
L75
    iconst_4
    iload 3
    if_icmpne L71
    iload 1
    iconst_0
    if_icmpne L78
    return
L78
    iconst_0
    putstatic client np:I
L71
    iload 2
    bipush 17
    if_icmpne L77
    iload 1
    iconst_0
    if_icmpne L79
    return
L8
    iconst_0
    iload 4
    if_icmpne L49
    iload 1
    iconst_0
    if_icmpne L55
    new java/lang/IllegalStateException
    dup
    invokespecial java/lang/IllegalStateException <init>:()V
    athrow
L68
    iload 3
    ldc -262498401 (java.lang.Integer)
    imul
    putstatic client jt:I
    goto L67
L53
    iconst_3
    iload 3
    if_icmpne L62
    goto L61
L33
    aconst_null
    getstatic client al:Lq;
    if_acmpne L74
    iload 1
    iconst_0
    if_icmpne L73
    return
L19
    ldc 0.8 (java.lang.Double)
    invokestatic cp w:(D)V
    goto L60
L74
    bipush 19
    iload 2
    if_icmpne L41
    iload 1
    iconst_0
    if_icmpne L80
    return
L80
    iload 3
    iconst_m1
    if_icmpne L40
    iload 1
    iconst_0
    if_icmpne L81
    new java/lang/IllegalStateException
    dup
    invokespecial java/lang/IllegalStateException <init>:()V
    athrow
L81
    ldc -663489355 (java.lang.Integer)
    putstatic client hd:I
    goto L41
L79
    ldc -1932409971 (java.lang.Integer)
    iload 3
    ldc 65535 (java.lang.Integer)
    iand
    imul
    putstatic client jo:I
    goto L77
L41
    return
L82
    new java/lang/StringBuilder
    dup
    invokespecial java/lang/StringBuilder <init>:()V
    ldc "db.cc(" (java.lang.String)
    invokevirtual java/lang/StringBuilder append:(Ljava/lang/String;)Ljava/lang/StringBuilder;
    ldc 41 (java.lang.Integer)
    invokevirtual java/lang/StringBuilder append:(C)Ljava/lang/StringBuilder;
    invokevirtual java/lang/StringBuilder toString:()Ljava/lang/String;
    invokestatic k a:(Ljava/lang/Throwable;Ljava/lang/String;)Lee;
    athrow
