dd a ([BI[BIIB)IL1
    iload 5
    ifne L2
    iload 6
    bipush 104
    if_icmplt L3
    new java/lang/IllegalStateException
    dup
    invokespecial java/lang/IllegalStateException <init>:()V
    athrow
L4
    aload 3
    iload 4
    iinc 4 1
    iload 10
    iconst_m1
    ixor
    i2b
    bastore
    goto L5
L6
    aload 0
    getfield dd l:[I
    iload 7
    iaload
    dup
    istore 10
    ifge L7
    iload 6
    bipush 104
    if_icmplt L8
    new java/lang/IllegalStateException
    dup
    invokespecial java/lang/IllegalStateException <init>:()V
    athrow
L9
    iconst_0
    iload 9
    bipush 32
    iand
    if_icmpeq L10
    iload 6
    bipush 104
    if_icmplt L11
    new java/lang/IllegalStateException
    dup
    invokespecial java/lang/IllegalStateException <init>:()V
    athrow
L12
    iload 2
    istore 8
L13
    aload 1
    iload 8
    baload
    istore 9
L14
    iload 9
    ifge L15
    iload 6
    bipush 104
    if_icmplt L16
    new java/lang/IllegalStateException
    dup
    invokespecial java/lang/IllegalStateException <init>:()V
    athrow
L16
    aload 0
    getfield dd l:[I
    iload 7
    iaload
    istore 7
    goto L17
L18
    aload 0
    getfield dd l:[I
    iload 7
    iaload
    dup
    istore 10
    ifge L19
    iload 6
    bipush 104
    if_icmplt L20
    new java/lang/IllegalStateException
    dup
    invokespecial java/lang/IllegalStateException <init>:()V
    athrow
L17
    aload 0
    getfield dd l:[I
    iload 7
    iaload
    dup
    istore 10
    ifge L21
    iload 6
    bipush 104
    if_icmplt L4
    new java/lang/IllegalStateException
    dup
    invokespecial java/lang/IllegalStateException <init>:()V
    athrow
L22
    aload 0
    getfield dd l:[I
    iload 7
    iaload
    istore 7
    goto L23
L24
    aload 0
    getfield dd l:[I
    iload 7
    iaload
    istore 7
    goto L18
L25
    goto L26
L27
    iconst_0
    istore 7
L21
    iconst_0
    iload 9
    bipush 64
    iand
    if_icmpeq L28
    iload 6
    bipush 104
    if_icmplt L22
    new java/lang/IllegalStateException
    dup
    invokespecial java/lang/IllegalStateException <init>:()V
    athrow
L29
    aload 3
    iload 4
    iinc 4 1
    iload 10
    iconst_m1
    ixor
    i2b
    bastore
    goto L30
L2
    iconst_0
    istore 7
    goto L31
L23
    aload 0
    getfield dd l:[I
    iload 7
    iaload
    dup
    istore 10
    ifge L9
    goto L32
L30
    iload 4
    iload 5
    if_icmplt L33
    iload 6
    bipush 104
    if_icmplt L25
    new java/lang/IllegalStateException
    dup
    invokespecial java/lang/IllegalStateException <init>:()V
    athrow
L34
    iload 4
    iload 5
    if_icmplt L35
    goto L26
L35
    iconst_0
    istore 7
    goto L9
L36
    iinc 8 1
    goto L13
L11
    aload 0
    getfield dd l:[I
    iload 7
    iaload
    istore 7
    goto L37
L28
    iinc 7 1
    goto L23
L38
    goto L26
L39
    iconst_0
    iload 9
    bipush 16
    iand
    if_icmpeq L40
    iload 6
    bipush 104
    if_icmplt L41
    new java/lang/IllegalStateException
    dup
    invokespecial java/lang/IllegalStateException <init>:()V
    athrow
L42
    iload 4
    iload 5
    if_icmplt L43
    iload 6
    bipush 104
    if_icmplt L44
    new java/lang/IllegalStateException
    dup
    invokespecial java/lang/IllegalStateException <init>:()V
    athrow
L44
    goto L26
L43
    iconst_0
    istore 7
    goto L39
L15
    iinc 7 1
    goto L17
L20
    aload 3
    iload 4
    iinc 4 1
    iload 10
    iconst_m1
    ixor
    i2b
    bastore
    goto L45
L40
    iinc 7 1
L46
    aload 0
    getfield dd l:[I
    iload 7
    iaload
    dup
    istore 10
    ifge L47
    iload 6
    bipush 104
    if_icmplt L48
    new java/lang/IllegalStateException
    dup
    invokespecial java/lang/IllegalStateException <init>:()V
    athrow
L48
    aload 3
    iload 4
    iinc 4 1
    iload 10
    iconst_m1
    ixor
    i2b
    bastore
L49
    iload 4
    iload 5
    if_icmplt L50
    goto L26
L50
    iconst_0
    istore 7
L47
    iconst_0
    iload 9
    bipush 8
    iand
    if_icmpeq L51
    iload 6
    bipush 104
    if_icmplt L24
    new java/lang/IllegalStateException
    dup
    invokespecial java/lang/IllegalStateException <init>:()V
    athrow
L52
    iinc 7 1
    goto L53
L51
    iinc 7 1
    goto L18
L54
    aload 3
    iload 4
    iinc 4 1
    iload 10
    iconst_m1
    ixor
    i2b
    bastore
    goto L42
L31
    iload 5
    iload 4
    iadd
    istore 5
    goto L12
L45
    iload 4
    iload 5
    if_icmplt L55
    goto L56
L32
    aload 3
    iload 4
    iinc 4 1
    iload 10
    iconst_m1
    ixor
    i2b
    bastore
    goto L34
L55
    iconst_0
    istore 7
L19
    iconst_0
    iload 9
    iconst_4
    iand
    if_icmpeq L57
    iload 6
    bipush 104
    if_icmplt L58
    new java/lang/IllegalStateException
    dup
    invokespecial java/lang/IllegalStateException <init>:()V
    athrow
L58
    aload 0
    getfield dd l:[I
    iload 7
    iaload
    istore 7
    goto L6
L57
    iinc 7 1
    goto L6
L53
    aload 0
    getfield dd l:[I
    iload 7
    iaload
    dup
    istore 10
    ifge L59
    iload 6
    bipush 104
    if_icmplt L60
    new java/lang/IllegalStateException
    dup
    invokespecial java/lang/IllegalStateException <init>:()V
    athrow
L8
    aload 3
    iload 4
    iinc 4 1
    iload 10
    iconst_m1
    ixor
    i2b
    bastore
L61
    iload 4
    iload 5
    if_icmplt L62
    goto L38
L41
    aload 0
    getfield dd l:[I
    iload 7
    iaload
    istore 7
    goto L46
L62
    iconst_0
    istore 7
L7
    iconst_0
    iload 9
    iconst_2
    iand
    if_icmpeq L52
    iload 6
    bipush 104
    if_icmplt L63
    new java/lang/IllegalStateException
    dup
    invokespecial java/lang/IllegalStateException <init>:()V
    athrow
L63
    aload 0
    getfield dd l:[I
    iload 7
    iaload
    istore 7
    goto L53
L56
    goto L26
L64
    goto L26
L60
    aload 3
    iload 4
    iinc 4 1
    iload 10
    iconst_m1
    ixor
    i2b
    bastore
    goto L65
L10
    iinc 7 1
    goto L37
L66
    goto L26
L67
    iconst_0
    istore 7
L59
    iconst_0
    iload 9
    iconst_1
    iand
    if_icmpeq L68
    iload 6
    bipush 104
    if_icmplt L69
    new java/lang/IllegalStateException
    dup
    invokespecial java/lang/IllegalStateException <init>:()V
    athrow
L69
    aload 0
    getfield dd l:[I
    iload 7
    iaload
    istore 7
    goto L70
L68
    iinc 7 1
L70
    aload 0
    getfield dd l:[I
    iload 7
    iaload
    dup
    istore 10
    ifge L36
    goto L29
L5
    iload 4
    iload 5
    if_icmplt L27
    iload 6
    bipush 104
    if_icmplt L64
    new java/lang/IllegalStateException
    dup
    invokespecial java/lang/IllegalStateException <init>:()V
    athrow
L3
    iconst_0
    ireturn
L65
    iload 4
    iload 5
    if_icmplt L67
    iload 6
    bipush 104
    if_icmplt L66
    new java/lang/IllegalStateException
    dup
    invokespecial java/lang/IllegalStateException <init>:()V
    athrow
L33
    iconst_0
    istore 7
    goto L36
L37
    aload 0
    getfield dd l:[I
    iload 7
    iaload
    dup
    istore 10
    ifge L39
    iload 6
    bipush 104
    if_icmplt L54
    new java/lang/IllegalStateException
    dup
    invokespecial java/lang/IllegalStateException <init>:()V
    athrow
L26
    iload 8
    iconst_1
    iadd
    iload 2
    isub
    ireturn
L71
    new java/lang/StringBuilder
    dup
    invokespecial java/lang/StringBuilder <init>:()V
    ldc "dd.a(" (java.lang.String)
    invokevirtual java/lang/StringBuilder append:(Ljava/lang/String;)Ljava/lang/StringBuilder;
    ldc 41 (java.lang.Integer)
    invokevirtual java/lang/StringBuilder append:(C)Ljava/lang/StringBuilder;
    invokevirtual java/lang/StringBuilder toString:()Ljava/lang/String;
    invokestatic k a:(Ljava/lang/Throwable;Ljava/lang/String;)Lee;
    athrow
