dd cy ([Lfb;II)VL1
    iconst_0
    istore 3
    goto L2
L3
    aload 4
    getfield fb o:Z
    ifeq L4
    iload 2
    ldc -1547422441 (java.lang.Integer)
    if_icmpeq L5
    return
L6
    aload 0
    iload 3
    aaload
    astore 4
    goto L7
L8
    goto L9
L10
    goto L9
L11
    iload 1
    ldc 737715635 (java.lang.Integer)
    aload 4
    getfield fb n:I
    imul
    if_icmpeq L3
    iload 2
    ldc -1547422441 (java.lang.Integer)
    if_icmpeq L8
    new java/lang/IllegalStateException
    dup
    invokespecial java/lang/IllegalStateException <init>:()V
    athrow
L12
    aload 4
    getstatic fq ib:Lfb;
    if_acmpeq L13
    iload 2
    ldc -1547422441 (java.lang.Integer)
    if_icmpeq L14
    new java/lang/IllegalStateException
    dup
    invokespecial java/lang/IllegalStateException <init>:()V
    athrow
L15
    ldc 1190026755 (java.lang.Integer)
    aload 4
    getfield fb dn:I
    imul
    iflt L16
    iload 2
    ldc -1547422441 (java.lang.Integer)
    if_icmpeq L17
    new java/lang/IllegalStateException
    dup
    invokespecial java/lang/IllegalStateException <init>:()V
    athrow
L5
    aload 4
    ldc -1738715992 (java.lang.Integer)
    invokestatic ar dt:(Lfb;I)Z
    ifeq L4
    iload 2
    ldc -1547422441 (java.lang.Integer)
    if_icmpeq L18
    new java/lang/IllegalStateException
    dup
    invokespecial java/lang/IllegalStateException <init>:()V
    athrow
L18
    goto L9
L4
    iconst_0
    aload 4
    getfield fb j:I
    ldc -1547422441 (java.lang.Integer)
    imul
    if_icmpne L19
L20
    aload 4
    getfield fb o:Z
    ifne L13
    iload 2
    ldc -1547422441 (java.lang.Integer)
    if_icmpeq L21
    new java/lang/IllegalStateException
    dup
    invokespecial java/lang/IllegalStateException <init>:()V
    athrow
L21
    aload 4
    ldc -1813743767 (java.lang.Integer)
    invokestatic ar dt:(Lfb;I)Z
    ifeq L13
    iload 2
    ldc -1547422441 (java.lang.Integer)
    if_icmpeq L12
    new java/lang/IllegalStateException
    dup
    invokespecial java/lang/IllegalStateException <init>:()V
    athrow
L2
    iload 3
    aload 0
    arraylength
    if_icmpge L22
    goto L6
L19
    bipush 6
    aload 4
    getfield fb j:I
    ldc -1547422441 (java.lang.Integer)
    imul
    if_icmpne L9
    iload 2
    ldc -1547422441 (java.lang.Integer)
    if_icmpeq L23
    new java/lang/IllegalStateException
    dup
    invokespecial java/lang/IllegalStateException <init>:()V
    athrow
L13
    aload 0
    aload 4
    getfield fb h:I
    ldc 952871887 (java.lang.Integer)
    imul
    ldc -1547422441 (java.lang.Integer)
    invokestatic dd cy:([Lfb;II)V
L24
    aload 4
    getfield fb do:[Lfb;
    ifnull L25
    aload 4
    getfield fb do:[Lfb;
    ldc 952871887 (java.lang.Integer)
    aload 4
    getfield fb h:I
    imul
    ldc -1547422441 (java.lang.Integer)
    invokestatic dd cy:([Lfb;II)V
    goto L25
L17
    aload 4
    getfield fb dn:I
    ldc 1190026755 (java.lang.Integer)
    imul
    aload 7
    getfield ah w:[I
    arraylength
    if_icmplt L26
    iload 2
    ldc -1547422441 (java.lang.Integer)
    if_icmpeq L16
    new java/lang/IllegalStateException
    dup
    invokespecial java/lang/IllegalStateException <init>:()V
    athrow
L27
    aload 5
    ifnull L19
    iload 2
    ldc -1547422441 (java.lang.Integer)
    if_icmpeq L28
    new java/lang/IllegalStateException
    dup
    invokespecial java/lang/IllegalStateException <init>:()V
    athrow
L28
    aload 5
    getfield c e:I
    ldc -193401837 (java.lang.Integer)
    imul
    sipush 32767
    invokestatic h cn:(IS)V
    goto L19
L29
    iload 6
    getstatic client ew:I
    ldc 509485067 (java.lang.Integer)
    imul
    imul
    istore 6
    goto L30
L23
    aload 4
    getfield fb an:I
    ldc -1170991307 (java.lang.Integer)
    imul
    iconst_m1
    if_icmpne L31
    iload 2
    ldc -1547422441 (java.lang.Integer)
    if_icmpeq L32
    return
L32
    iconst_m1
    aload 4
    getfield fb az:I
    ldc -850817991 (java.lang.Integer)
    imul
    if_icmpeq L33
    iload 2
    ldc -1547422441 (java.lang.Integer)
    if_icmpeq L31
    new java/lang/IllegalStateException
    dup
    invokespecial java/lang/IllegalStateException <init>:()V
    athrow
L34
    aload 4
    getfield fb dn:I
    ldc 1190026755 (java.lang.Integer)
    imul
    aload 7
    getfield ah w:[I
    arraylength
    if_icmplt L26
    iload 2
    ldc -1547422441 (java.lang.Integer)
    if_icmpeq L35
    new java/lang/IllegalStateException
    dup
    invokespecial java/lang/IllegalStateException <init>:()V
    athrow
L36
    iload 5
    ifeq L37
    iload 2
    ldc -1547422441 (java.lang.Integer)
    if_icmpeq L38
    return
L39
    aload 4
    getfield fb o:Z
    ifne L9
    iload 2
    ldc -1547422441 (java.lang.Integer)
    if_icmpeq L40
    new java/lang/IllegalStateException
    dup
    invokespecial java/lang/IllegalStateException <init>:()V
    athrow
L25
    getstatic client jv:Lgf;
    aload 4
    getfield fb h:I
    ldc 952871887 (java.lang.Integer)
    imul
    i2l
    invokevirtual gf e:(J)Lgm;
    checkcast c
    astore 5
    goto L27
L41
    aload 4
    getfield fb bw:I
    ldc 281124249 (java.lang.Integer)
    imul
    bipush 16
    ishl
    bipush 16
    ishr
    istore 6
    goto L42
L43
    iload 6
    ldc 152969838 (java.lang.Integer)
    invokestatic cd e:(II)Lah;
    astore 7
L44
    aload 4
    dup
    getfield fb dx:I
    getstatic client ew:I
    ldc 1382632899 (java.lang.Integer)
    imul
    iadd
    putfield fb dx:I
L45
    ldc -1860970471 (java.lang.Integer)
    aload 4
    getfield fb dx:I
    imul
    aload 7
    getfield ah r:[I
    ldc 1190026755 (java.lang.Integer)
    aload 4
    getfield fb dn:I
    imul
    iaload
    if_icmple L33
    iload 2
    ldc -1547422441 (java.lang.Integer)
    if_icmpeq L46
    new java/lang/IllegalStateException
    dup
    invokespecial java/lang/IllegalStateException <init>:()V
    athrow
L46
    aload 4
    dup
    getfield fb dx:I
    ldc 1849820201 (java.lang.Integer)
    aload 7
    getfield ah r:[I
    aload 4
    getfield fb dn:I
    ldc 1190026755 (java.lang.Integer)
    imul
    iaload
    imul
    isub
    putfield fb dx:I
    goto L47
L14
    goto L9
L33
    iconst_0
    ldc 281124249 (java.lang.Integer)
    aload 4
    getfield fb bw:I
    imul
    if_icmpeq L9
    iload 2
    ldc -1547422441 (java.lang.Integer)
    if_icmpeq L39
    new java/lang/IllegalStateException
    dup
    invokespecial java/lang/IllegalStateException <init>:()V
    athrow
L35
    aload 4
    dup
    getfield fb dn:I
    aload 7
    getfield ah g:I
    ldc -1564304433 (java.lang.Integer)
    imul
    isub
    putfield fb dn:I
    goto L15
L42
    iload 5
    ldc 509485067 (java.lang.Integer)
    getstatic client ew:I
    imul
    imul
    istore 5
    goto L29
L47
    aload 4
    dup
    getfield fb dn:I
    ldc 624934059 (java.lang.Integer)
    iadd
    putfield fb dn:I
    goto L34
L16
    aload 4
    iconst_0
    putfield fb dn:I
L26
    aload 4
    ldc -1023277750 (java.lang.Integer)
    invokestatic dh cr:(Lfb;I)V
    goto L45
L7
    aload 4
    ifnonnull L11
    iload 2
    ldc -1547422441 (java.lang.Integer)
    if_icmpeq L10
    return
L31
    aload 4
    ldc 1430304480 (java.lang.Integer)
    invokestatic by cm:(Lfb;I)Z
    istore 5
    goto L36
L40
    ldc 281124249 (java.lang.Integer)
    aload 4
    getfield fb bw:I
    imul
    bipush 16
    ishr
    istore 5
    goto L41
L38
    ldc -850817991 (java.lang.Integer)
    aload 4
    getfield fb az:I
    imul
    istore 6
    goto L48
L37
    aload 4
    getfield fb an:I
    ldc -1170991307 (java.lang.Integer)
    imul
    istore 6
L48
    iconst_m1
    iload 6
    if_icmpeq L33
    goto L43
L30
    aload 4
    ldc -1571883189 (java.lang.Integer)
    ldc -1210951069 (java.lang.Integer)
    aload 4
    getfield fb aa:I
    imul
    iload 5
    iadd
    sipush 2047
    iand
    imul
    putfield fb aa:I
L49
    aload 4
    iload 6
    ldc -120011331 (java.lang.Integer)
    aload 4
    getfield fb bl:I
    imul
    iadd
    sipush 2047
    iand
    ldc 1003527573 (java.lang.Integer)
    imul
    putfield fb bl:I
L50
    aload 4
    ldc -1023277750 (java.lang.Integer)
    invokestatic dh cr:(Lfb;I)V
L9
    iinc 3 1
    goto L2
L22
    return
L51
    new java/lang/StringBuilder
    dup
    invokespecial java/lang/StringBuilder <init>:()V
    ldc "dd.cy(" (java.lang.String)
    invokevirtual java/lang/StringBuilder append:(Ljava/lang/String;)Ljava/lang/StringBuilder;
    ldc 41 (java.lang.Integer)
    invokevirtual java/lang/StringBuilder append:(C)Ljava/lang/StringBuilder;
    invokevirtual java/lang/StringBuilder toString:()Ljava/lang/String;
    invokestatic k a:(Ljava/lang/Throwable;Ljava/lang/String;)Lee;
    athrow
