dd e ([BII[BII)IL1
    iconst_0
    istore 7
    goto L2
L3
    iload 12
    iload 14
    if_icmplt L4
    iload 6
    ldc 1902557504 (java.lang.Integer)
    if_icmplt L5
    new java/lang/IllegalStateException
    dup
    invokespecial java/lang/IllegalStateException <init>:()V
    athrow
L6
    iload 3
    iload 2
    iadd
    istore 3
    goto L7
L8
    bipush 7
    iload 8
    iadd
    iconst_3
    ishr
    iload 5
    isub
    ireturn
L9
    aload 1
    iload 2
    baload
    sipush 255
    iand
    istore 9
L10
    aload 0
    getfield dd e:[I
    iload 9
    iaload
    istore 10
    goto L11
L12
    goto L13
L4
    iinc 12 1
    goto L14
L15
    new java/lang/RuntimeException
    dup
    ldc "" (java.lang.String)
    invokespecial java/lang/RuntimeException <init>:(Ljava/lang/String;)V
    athrow
L16
    iload 8
    iconst_3
    ishr
    istore 12
    goto L17
L18
    iinc 12 1
    goto L19
L20
    iload 7
    iload 13
    ineg
    bipush 31
    ishr
    iand
    istore 7
    goto L21
L11
    aload 0
    getfield dd a:[B
    iload 9
    baload
    istore 11
    goto L22
L14
    iinc 13 -8
    goto L23
L24
    iload 12
    iload 14
    if_icmplt L18
    iload 6
    ldc 1902557504 (java.lang.Integer)
    if_icmplt L25
    new java/lang/IllegalStateException
    dup
    invokespecial java/lang/IllegalStateException <init>:()V
    athrow
L7
    iload 2
    iload 3
    if_icmpge L8
    iload 6
    ldc 1902557504 (java.lang.Integer)
    if_icmplt L9
    new java/lang/IllegalStateException
    dup
    invokespecial java/lang/IllegalStateException <init>:()V
    athrow
L5
    goto L13
L26
    aload 4
    iload 12
    iload 7
    iload 10
    iload 13
    iushr
    ior
    dup
    istore 7
    i2b
    bastore
    goto L3
L27
    iload 12
    iload 14
    if_icmplt L28
    iload 6
    ldc 1902557504 (java.lang.Integer)
    if_icmplt L12
    new java/lang/IllegalStateException
    dup
    invokespecial java/lang/IllegalStateException <init>:()V
    athrow
L23
    aload 4
    iload 12
    iload 10
    iload 13
    iushr
    dup
    istore 7
    i2b
    bastore
L29
    iload 12
    iload 14
    if_icmplt L30
    goto L13
L30
    iinc 12 1
    goto L31
L17
    iload 8
    bipush 7
    iand
    istore 13
    goto L20
L32
    aload 4
    iload 12
    iload 10
    iload 13
    iushr
    dup
    istore 7
    i2b
    bastore
    goto L24
L31
    iinc 13 -8
    goto L32
L25
    goto L13
L2
    iload 5
    iconst_3
    ishl
    istore 8
    goto L6
L19
    iinc 13 -8
L33
    aload 4
    iload 12
    iload 10
    iload 13
    iushr
    dup
    istore 7
    i2b
    bastore
    goto L27
L22
    iload 11
    ifne L16
    goto L15
L13
    iload 8
    iload 11
    iadd
    istore 8
    goto L34
L28
    iinc 12 1
L35
    iinc 13 -8
L36
    aload 4
    iload 12
    iload 10
    iload 13
    ineg
    ishl
    dup
    istore 7
    i2b
    bastore
    goto L13
L21
    iload 12
    iload 11
    iload 13
    iadd
    iconst_1
    isub
    iconst_3
    ishr
    iadd
    istore 14
    goto L37
L34
    iinc 2 1
    goto L7
L37
    iinc 13 24
    goto L26
L38
    new java/lang/StringBuilder
    dup
    invokespecial java/lang/StringBuilder <init>:()V
    ldc "dd.e(" (java.lang.String)
    invokevirtual java/lang/StringBuilder append:(Ljava/lang/String;)Ljava/lang/StringBuilder;
    ldc 41 (java.lang.Integer)
    invokevirtual java/lang/StringBuilder append:(C)Ljava/lang/StringBuilder;
    invokevirtual java/lang/StringBuilder toString:()Ljava/lang/String;
    invokestatic k a:(Ljava/lang/Throwable;Ljava/lang/String;)Lee;
    athrow
