df a (Ljava/lang/CharSequence;B)Ljava/lang/String;L1
    lconst_0
    lstore 4
    goto L2
L3
    iload 8
    bipush 90
    if_icmpgt L4
    goto L5
L6
    iconst_0
    istore 7
    goto L7
L8
    iinc 7 1
    goto L7
L9
    lload 4
    ldc 37 (java.lang.Long)
    lmul
    lstore 4
L10
    aload 0
    iload 7
    invokeinterface java/lang/CharSequence charAt:(I)C
    istore 8
L11
    iload 8
    bipush 65
    if_icmplt L4
    iload 1
    iconst_1
    if_icmpeq L3
    new java/lang/IllegalStateException
    dup
    invokespecial java/lang/IllegalStateException <init>:()V
    athrow
L12
    lload 4
    ldc 37 (java.lang.Long)
    lrem
    lconst_0
    lcmp
    ifne L13
    iload 1
    iconst_1
    if_icmpeq L14
    new java/lang/IllegalStateException
    dup
    invokespecial java/lang/IllegalStateException <init>:()V
    athrow
L5
    lload 4
    iload 8
    iconst_1
    iadd
    bipush 65
    isub
    i2l
    ladd
    lstore 4
    goto L15
L4
    iload 8
    bipush 97
    if_icmplt L16
    iload 8
    bipush 122
    if_icmpgt L16
    iload 1
    iconst_1
    if_icmpeq L17
    new java/lang/IllegalStateException
    dup
    invokespecial java/lang/IllegalStateException <init>:()V
    athrow
L17
    lload 4
    iload 8
    iconst_1
    iadd
    bipush 97
    isub
    i2l
    ladd
    lstore 4
    goto L15
L16
    iload 8
    bipush 48
    if_icmplt L15
    iload 1
    iconst_1
    if_icmpeq L18
    new java/lang/IllegalStateException
    dup
    invokespecial java/lang/IllegalStateException <init>:()V
    athrow
L18
    iload 8
    bipush 57
    if_icmpgt L15
    iload 1
    iconst_1
    if_icmpeq L19
    new java/lang/IllegalStateException
    dup
    invokespecial java/lang/IllegalStateException <init>:()V
    athrow
L2
    aload 0
    invokeinterface java/lang/CharSequence length:()I
    istore 6
    goto L6
L19
    lload 4
    iload 8
    bipush 27
    iadd
    bipush 48
    isub
    i2l
    ladd
    lstore 4
    goto L15
L20
    goto L12
L21
    lload 4
    ldc 37 (java.lang.Long)
    ldiv
    lstore 4
    goto L12
L15
    lload 4
    ldc 177917621779460413 (java.lang.Long)
    lcmp
    iflt L8
    iload 1
    iconst_1
    if_icmpeq L20
    new java/lang/IllegalStateException
    dup
    invokespecial java/lang/IllegalStateException <init>:()V
    athrow
L14
    lconst_0
    lload 4
    lcmp
    ifeq L13
    iload 1
    iconst_1
    if_icmpeq L21
    new java/lang/IllegalStateException
    dup
    invokespecial java/lang/IllegalStateException <init>:()V
    athrow
L13
    lload 4
    lstore 2
    goto L22
L7
    iload 7
    iload 6
    if_icmpge L12
    iload 1
    iconst_1
    if_icmpeq L9
    new java/lang/IllegalStateException
    dup
    invokespecial java/lang/IllegalStateException <init>:()V
    athrow
L22
    lload 2
    invokestatic e e:(J)Ljava/lang/String;
    astore 4
L23
    aload 4
    ifnonnull L24
    iload 1
    iconst_1
    if_icmpeq L25
    new java/lang/IllegalStateException
    dup
    invokespecial java/lang/IllegalStateException <init>:()V
    athrow
L25
    ldc "" (java.lang.String)
    astore 4
L24
    aload 4
    areturn
L26
    new java/lang/StringBuilder
    dup
    invokespecial java/lang/StringBuilder <init>:()V
    ldc "df.a(" (java.lang.String)
    invokevirtual java/lang/StringBuilder append:(Ljava/lang/String;)Ljava/lang/StringBuilder;
    ldc 41 (java.lang.Integer)
    invokevirtual java/lang/StringBuilder append:(C)Ljava/lang/StringBuilder;
    invokevirtual java/lang/StringBuilder toString:()Ljava/lang/String;
    invokestatic k a:(Ljava/lang/Throwable;Ljava/lang/String;)Lee;
    athrow
