df c (II)ZL1
    getstatic fb a:[Z
    iload 0
    baload
    ifeq L2
    iload 1
    ldc 1928687330 (java.lang.Integer)
    if_icmpeq L3
    new java/lang/IllegalStateException
    dup
    invokespecial java/lang/IllegalStateException <init>:()V
    athrow
L4
    iconst_1
    ireturn
L2
    getstatic fb l:Lfv;
    iload 0
    ldc -1097991331 (java.lang.Integer)
    invokevirtual fv w:(II)Z
    ifne L5
    iload 1
    ldc 1928687330 (java.lang.Integer)
    if_icmpeq L6
    new java/lang/IllegalStateException
    dup
    invokespecial java/lang/IllegalStateException <init>:()V
    athrow
L7
    getstatic fb e:[[Lfb;
    iload 0
    iload 2
    anewarray fb
    aastore
    goto L8
L6
    iconst_0
    ireturn
L9
    iconst_0
    iload 2
    if_icmpne L10
L11
    getstatic fb a:[Z
    iload 0
    iconst_1
    bastore
    goto L4
L12
    iinc 3 1
    goto L13
L3
    iconst_1
    ireturn
L10
    getstatic fb e:[[Lfb;
    iload 0
    aaload
    ifnonnull L8
    iload 1
    ldc 1928687330 (java.lang.Integer)
    if_icmpeq L7
    new java/lang/IllegalStateException
    dup
    invokespecial java/lang/IllegalStateException <init>:()V
    athrow
L8
    iconst_0
    istore 3
    goto L13
L14
    iconst_1
    ireturn
L15
    getstatic fb e:[[Lfb;
    iload 0
    aaload
    iload 3
    aaload
    ifnonnull L12
    goto L16
L13
    iload 3
    iload 2
    if_icmpge L17
    iload 1
    ldc 1928687330 (java.lang.Integer)
    if_icmpeq L15
    new java/lang/IllegalStateException
    dup
    invokespecial java/lang/IllegalStateException <init>:()V
    athrow
L5
    getstatic fb l:Lfv;
    iload 0
    ldc -290821295 (java.lang.Integer)
    invokevirtual fv s:(II)I
    istore 2
    goto L9
L18
    getstatic fb e:[[Lfb;
    iload 0
    aaload
    iload 3
    new fb
    dup
    invokespecial fb <init>:()V
    aastore
L19
    getstatic fb e:[[Lfb;
    iload 0
    aaload
    iload 3
    aaload
    iload 0
    bipush 16
    ishl
    iload 3
    iadd
    ldc -792626385 (java.lang.Integer)
    imul
    putfield fb h:I
L20
    aload 4
    iconst_0
    baload
    iconst_m1
    if_icmpne L21
    iload 1
    ldc 1928687330 (java.lang.Integer)
    if_icmpeq L22
    new java/lang/IllegalStateException
    dup
    invokespecial java/lang/IllegalStateException <init>:()V
    athrow
L22
    getstatic fb e:[[Lfb;
    iload 0
    aaload
    iload 3
    aaload
    new dh
    dup
    aload 4
    invokespecial dh <init>:([B)V
    ldc -275814920 (java.lang.Integer)
    invokevirtual fb w:(Ldh;I)V
    goto L12
L21
    getstatic fb e:[[Lfb;
    iload 0
    aaload
    iload 3
    aaload
    new dh
    dup
    aload 4
    invokespecial dh <init>:([B)V
    ldc -129974993 (java.lang.Integer)
    invokevirtual fb u:(Ldh;I)V
    goto L12
L17
    getstatic fb a:[Z
    iload 0
    iconst_1
    bastore
    goto L14
L16
    getstatic fb l:Lfv;
    iload 0
    iload 3
    ldc -729968833 (java.lang.Integer)
    invokevirtual fv l:(III)[B
    astore 4
L23
    aload 4
    ifnull L12
    iload 1
    ldc 1928687330 (java.lang.Integer)
    if_icmpeq L18
    new java/lang/IllegalStateException
    dup
    invokespecial java/lang/IllegalStateException <init>:()V
    athrow
L24
    new java/lang/StringBuilder
    dup
    invokespecial java/lang/StringBuilder <init>:()V
    ldc "df.c(" (java.lang.String)
    invokevirtual java/lang/StringBuilder append:(Ljava/lang/String;)Ljava/lang/StringBuilder;
    ldc 41 (java.lang.Integer)
    invokevirtual java/lang/StringBuilder append:(C)Ljava/lang/StringBuilder;
    invokevirtual java/lang/StringBuilder toString:()Ljava/lang/String;
    invokestatic k a:(Ljava/lang/Throwable;Ljava/lang/String;)Lee;
    athrow
