dg e (IB)[BL1
    aload 0
    getfield dg a:Lhv;
    dup
    astore 3
    monitorenter
L2
    aload 0
    getfield dg l:Lhv;
    bipush -24
    invokevirtual hv l:(B)J
    iload 1
    bipush 6
    imul
    bipush 6
    iadd
    i2l
    lcmp
    ifge L3
    iload 2
    iconst_3
    if_icmplt L4
    new java/lang/IllegalStateException
    dup
    invokespecial java/lang/IllegalStateException <init>:()V
    athrow
L4
    aconst_null
L5
    aload 3
    monitorexit
L6
    areturn
L3
    aload 0
    getfield dg l:Lhv;
    iload 1
    bipush 6
    imul
    i2l
    invokevirtual hv a:(J)V
L7
    aload 0
    getfield dg l:Lhv;
    getstatic dg e:[B
    iconst_0
    bipush 6
    ldc 1801071573 (java.lang.Integer)
    invokevirtual hv u:([BIII)V
L8
    getstatic dg e:[B
    iconst_0
    baload
    sipush 255
    iand
    bipush 16
    ishl
    getstatic dg e:[B
    iconst_1
    baload
    sipush 255
    iand
    bipush 8
    ishl
    iadd
    getstatic dg e:[B
    iconst_2
    baload
    sipush 255
    iand
    iadd
    istore 4
L9
    getstatic dg e:[B
    iconst_3
    baload
    sipush 255
    iand
    bipush 16
    ishl
    getstatic dg e:[B
    iconst_4
    baload
    sipush 255
    iand
    bipush 8
    ishl
    iadd
    getstatic dg e:[B
    iconst_5
    baload
    sipush 255
    iand
    iadd
    istore 5
L10
    iload 4
    iflt L11
    iload 4
    ldc 461249501 (java.lang.Integer)
    aload 0
    getfield dg u:I
    imul
    if_icmple L12
L11
    aconst_null
L13
    aload 3
    monitorexit
L14
    areturn
L12
    iload 5
    ifle L15
    iload 2
    iconst_3
    if_icmplt L16
    new java/lang/IllegalStateException
    dup
    invokespecial java/lang/IllegalStateException <init>:()V
    athrow
L16
    iload 5
    i2l
    aload 0
    getfield dg a:Lhv;
    bipush 21
    invokevirtual hv l:(B)J
    ldc 520 (java.lang.Long)
    ldiv
    lcmp
    ifle L17
L15
    aconst_null
L18
    aload 3
    monitorexit
L19
    areturn
L17
    iload 4
    newarray 8
    astore 6
L20
    iconst_0
    istore 7
L21
    iconst_0
    istore 8
L22
    iload 7
    iload 4
    if_icmpge L23
    iload 2
    iconst_3
    if_icmplt L24
    new java/lang/IllegalStateException
    dup
    invokespecial java/lang/IllegalStateException <init>:()V
    athrow
L24
    iconst_0
    iload 5
    if_icmpne L25
    iload 2
    iconst_3
    if_icmplt L26
    new java/lang/IllegalStateException
    dup
    invokespecial java/lang/IllegalStateException <init>:()V
    athrow
L26
    aconst_null
L27
    aload 3
    monitorexit
L28
    areturn
L25
    aload 0
    getfield dg a:Lhv;
    sipush 520
    iload 5
    imul
    i2l
    invokevirtual hv a:(J)V
L29
    iload 4
    iload 7
    isub
    istore 9
L30
    iload 9
    sipush 512
    if_icmple L31
    iload 2
    iconst_3
    if_icmplt L32
    new java/lang/IllegalStateException
    dup
    invokespecial java/lang/IllegalStateException <init>:()V
    athrow
L32
    sipush 512
    istore 9
L31
    aload 0
    getfield dg a:Lhv;
    getstatic dg e:[B
    iconst_0
    iload 9
    bipush 8
    iadd
    ldc 2104216485 (java.lang.Integer)
    invokevirtual hv u:([BIII)V
L33
    getstatic dg e:[B
    iconst_0
    baload
    sipush 255
    iand
    bipush 8
    ishl
    getstatic dg e:[B
    iconst_1
    baload
    sipush 255
    iand
    iadd
    istore 10
L34
    getstatic dg e:[B
    iconst_2
    baload
    sipush 255
    iand
    bipush 8
    ishl
    getstatic dg e:[B
    iconst_3
    baload
    sipush 255
    iand
    iadd
    istore 11
L35
    getstatic dg e:[B
    bipush 6
    baload
    sipush 255
    iand
    getstatic dg e:[B
    iconst_5
    baload
    sipush 255
    iand
    bipush 8
    ishl
    getstatic dg e:[B
    iconst_4
    baload
    sipush 255
    iand
    bipush 16
    ishl
    iadd
    iadd
    istore 12
L36
    getstatic dg e:[B
    bipush 7
    baload
    sipush 255
    iand
    istore 13
L37
    iload 10
    iload 1
    if_icmpne L38
    iload 2
    iconst_3
    if_icmplt L39
    new java/lang/IllegalStateException
    dup
    invokespecial java/lang/IllegalStateException <init>:()V
    athrow
L39
    iload 8
    iload 11
    if_icmpne L38
    iload 2
    iconst_3
    if_icmplt L40
    new java/lang/IllegalStateException
    dup
    invokespecial java/lang/IllegalStateException <init>:()V
    athrow
L40
    ldc 1419061167 (java.lang.Integer)
    aload 0
    getfield dg c:I
    imul
    iload 13
    if_icmpeq L41
    iload 2
    iconst_3
    if_icmplt L38
    new java/lang/IllegalStateException
    dup
    invokespecial java/lang/IllegalStateException <init>:()V
    athrow
L38
    aconst_null
L42
    aload 3
    monitorexit
L43
    areturn
L41
    iload 12
    iflt L44
    iload 2
    iconst_3
    if_icmplt L45
    new java/lang/IllegalStateException
    dup
    invokespecial java/lang/IllegalStateException <init>:()V
    athrow
L45
    iload 12
    i2l
    aload 0
    getfield dg a:Lhv;
    bipush 23
    invokevirtual hv l:(B)J
    ldc 520 (java.lang.Long)
    ldiv
    lcmp
    ifle L46
    iload 2
    iconst_3
    if_icmplt L44
    new java/lang/IllegalStateException
    dup
    invokespecial java/lang/IllegalStateException <init>:()V
    athrow
L44
    aconst_null
L47
    aload 3
    monitorexit
L48
    areturn
L46
    iconst_0
    istore 14
L49
    iload 14
    iload 9
    if_icmpge L50
    iload 2
    iconst_3
    if_icmplt L51
    new java/lang/IllegalStateException
    dup
    invokespecial java/lang/IllegalStateException <init>:()V
    athrow
L51
    aload 6
    iload 7
    iinc 7 1
    getstatic dg e:[B
    iload 14
    bipush 8
    iadd
    baload
    bastore
    iinc 14 1
    goto L49
L50
    iload 12
    istore 5
L52
    iinc 8 1
L53
    goto L22
L23
    aload 6
L54
    aload 3
    monitorexit
L55
    areturn
L56
    astore 4
L57
    aconst_null
    aload 3
    monitorexit
L58
    areturn
L59
    astore 15
    aload 3
    monitorexit
L60
    aload 15
    athrow
L61
    new java/lang/StringBuilder
    dup
    invokespecial java/lang/StringBuilder <init>:()V
    ldc "dg.e(" (java.lang.String)
    invokevirtual java/lang/StringBuilder append:(Ljava/lang/String;)Ljava/lang/StringBuilder;
    ldc 41 (java.lang.Integer)
    invokevirtual java/lang/StringBuilder append:(C)Ljava/lang/StringBuilder;
    invokevirtual java/lang/StringBuilder toString:()Ljava/lang/String;
    invokestatic k a:(Ljava/lang/Throwable;Ljava/lang/String;)Lee;
    athrow
