dh ab ([IIII)VL1
    aload 0
    getfield dh a:I
    ldc 910905453 (java.lang.Integer)
    imul
    istore 5
    goto L2
L3
    iconst_0
    istore 10
    goto L4
L5
    iload 3
    iload 2
    isub
    bipush 8
    idiv
    istore 6
L6
    iconst_0
    istore 7
    goto L7
L8
    aload 0
    iload 8
    ldc -1252856775 (java.lang.Integer)
    invokevirtual dh c:(II)V
    goto L9
L10
    return
L11
    aload 0
    ldc -2035747170 (java.lang.Integer)
    invokevirtual dh x:(I)I
    istore 9
    goto L3
L7
    iload 7
    iload 6
    if_icmpge L12
    iload 4
    ldc -879883209 (java.lang.Integer)
    if_icmpgt L13
    new java/lang/IllegalStateException
    dup
    invokespecial java/lang/IllegalStateException <init>:()V
    athrow
L4
    ldc -1640531527 (java.lang.Integer)
    istore 11
L14
    bipush 32
    istore 12
L15
    iload 12
    iinc 12 -1
    ifle L16
    iload 4
    ldc -879883209 (java.lang.Integer)
    if_icmpgt L17
    new java/lang/IllegalStateException
    dup
    invokespecial java/lang/IllegalStateException <init>:()V
    athrow
L17
    iload 8
    iload 9
    iload 9
    iconst_4
    ishl
    iload 9
    iconst_5
    iushr
    ixor
    iadd
    aload 1
    iload 10
    iconst_3
    iand
    iaload
    iload 10
    iadd
    ixor
    iadd
    istore 8
    goto L18
L9
    aload 0
    iload 9
    ldc 1094500531 (java.lang.Integer)
    invokevirtual dh c:(II)V
    goto L19
L20
    iload 9
    iload 8
    iload 8
    iconst_4
    ishl
    iload 8
    iconst_5
    iushr
    ixor
    iadd
    iload 10
    aload 1
    iload 10
    bipush 11
    iushr
    iconst_3
    iand
    iaload
    iadd
    ixor
    iadd
    istore 9
    goto L15
L16
    aload 0
    dup
    getfield dh a:I
    ldc 1378470696 (java.lang.Integer)
    isub
    putfield dh a:I
    goto L8
L13
    aload 0
    ldc -2050919663 (java.lang.Integer)
    invokevirtual dh x:(I)I
    istore 8
    goto L11
L18
    iload 10
    iload 11
    iadd
    istore 10
    goto L20
L19
    iinc 7 1
    goto L7
L12
    aload 0
    iload 5
    ldc 1782921573 (java.lang.Integer)
    imul
    putfield dh a:I
    goto L10
L2
    aload 0
    iload 2
    ldc 1782921573 (java.lang.Integer)
    imul
    putfield dh a:I
    goto L5
L21
    new java/lang/StringBuilder
    dup
    invokespecial java/lang/StringBuilder <init>:()V
    ldc "dh.ab(" (java.lang.String)
    invokevirtual java/lang/StringBuilder append:(Ljava/lang/String;)Ljava/lang/StringBuilder;
    ldc 41 (java.lang.Integer)
    invokevirtual java/lang/StringBuilder append:(C)Ljava/lang/StringBuilder;
    invokevirtual java/lang/StringBuilder toString:()Ljava/lang/String;
    invokestatic k a:(Ljava/lang/Throwable;Ljava/lang/String;)Lee;
    athrow
