dh f (Ljava/lang/String;I)VL1
    aload 1
    iconst_0
    invokevirtual java/lang/String indexOf:(I)I
    istore 3
    goto L2
L3
    aload 0
    getfield dh e:[B
    aload 0
    dup
    getfield dh a:I
    ldc 1782921573 (java.lang.Integer)
    iadd
    dup_x1
    putfield dh a:I
    ldc 910905453 (java.lang.Integer)
    imul
    iconst_1
    isub
    iconst_0
    bastore
    goto L4
L2
    iload 3
    iflt L3
    iload 2
    ldc 546499967 (java.lang.Integer)
    if_icmpeq L5
    new java/lang/IllegalStateException
    dup
    invokespecial java/lang/IllegalStateException <init>:()V
    athrow
L5
    new java/lang/IllegalArgumentException
    dup
    ldc "" (java.lang.String)
    invokespecial java/lang/IllegalArgumentException <init>:(Ljava/lang/String;)V
    athrow
L4
    aload 0
    dup
    getfield dh a:I
    aload 1
    iconst_0
    aload 1
    invokevirtual java/lang/String length:()I
    aload 0
    getfield dh e:[B
    ldc 910905453 (java.lang.Integer)
    aload 0
    getfield dh a:I
    imul
    ldc -2130226944 (java.lang.Integer)
    invokestatic o c:(Ljava/lang/CharSequence;II[BII)I
    ldc 1782921573 (java.lang.Integer)
    imul
    iadd
    putfield dh a:I
L6
    aload 0
    getfield dh e:[B
    aload 0
    dup
    getfield dh a:I
    ldc 1782921573 (java.lang.Integer)
    iadd
    dup_x1
    putfield dh a:I
    ldc 910905453 (java.lang.Integer)
    imul
    iconst_1
    isub
    iconst_0
    bastore
L7
    return
L8
    new java/lang/StringBuilder
    dup
    invokespecial java/lang/StringBuilder <init>:()V
    ldc "dh.f(" (java.lang.String)
    invokevirtual java/lang/StringBuilder append:(Ljava/lang/String;)Ljava/lang/StringBuilder;
    ldc 41 (java.lang.Integer)
    invokevirtual java/lang/StringBuilder append:(C)Ljava/lang/StringBuilder;
    invokevirtual java/lang/StringBuilder toString:()Ljava/lang/String;
    invokestatic k a:(Ljava/lang/Throwable;Ljava/lang/String;)Lee;
    athrow
