dh m (II)VL1
    iload 1
    iflt L2
    iload 2
    ldc 1194586937 (java.lang.Integer)
    if_icmpne L3
    new java/lang/IllegalStateException
    dup
    invokespecial java/lang/IllegalStateException <init>:()V
    athrow
L4
    aload 0
    iload 1
    ldc 32768 (java.lang.Integer)
    iadd
    bipush -6
    invokevirtual dh a:(IB)V
    goto L5
L6
    aload 0
    iload 1
    bipush -93
    invokevirtual dh e:(IB)V
L7
    return
L2
    iload 1
    iflt L8
    iload 2
    ldc 1194586937 (java.lang.Integer)
    if_icmpne L9
    return
L9
    iload 1
    ldc 32768 (java.lang.Integer)
    if_icmpge L8
    iload 2
    ldc 1194586937 (java.lang.Integer)
    if_icmpne L4
    new java/lang/IllegalStateException
    dup
    invokespecial java/lang/IllegalStateException <init>:()V
    athrow
L5
    return
L3
    iload 1
    sipush 128
    if_icmpge L2
    iload 2
    ldc 1194586937 (java.lang.Integer)
    if_icmpne L6
    new java/lang/IllegalStateException
    dup
    invokespecial java/lang/IllegalStateException <init>:()V
    athrow
L8
    new java/lang/IllegalArgumentException
    dup
    invokespecial java/lang/IllegalArgumentException <init>:()V
    athrow
L10
    new java/lang/StringBuilder
    dup
    invokespecial java/lang/StringBuilder <init>:()V
    ldc "dh.m(" (java.lang.String)
    invokevirtual java/lang/StringBuilder append:(Ljava/lang/String;)Ljava/lang/StringBuilder;
    ldc 41 (java.lang.Integer)
    invokevirtual java/lang/StringBuilder append:(C)Ljava/lang/StringBuilder;
    invokevirtual java/lang/StringBuilder toString:()Ljava/lang/String;
    invokestatic k a:(Ljava/lang/Throwable;Ljava/lang/String;)Lee;
    athrow
