dh t (IB)VL1
    iload 1
    bipush -128
    iand
    ifeq L2
    iload 2
    iconst_4
    if_icmpeq L3
    new java/lang/IllegalStateException
    dup
    invokespecial java/lang/IllegalStateException <init>:()V
    athrow
L4
    aload 0
    iload 1
    bipush 7
    iushr
    sipush 128
    ior
    bipush -64
    invokevirtual dh e:(IB)V
    goto L2
L5
    iconst_0
    iload 1
    ldc -2097152 (java.lang.Integer)
    iand
    if_icmpeq L6
L7
    iload 1
    ldc -268435456 (java.lang.Integer)
    iand
    ifeq L8
    iload 2
    iconst_4
    if_icmpeq L9
    new java/lang/IllegalStateException
    dup
    invokespecial java/lang/IllegalStateException <init>:()V
    athrow
L9
    aload 0
    iload 1
    bipush 28
    iushr
    sipush 128
    ior
    bipush 53
    invokevirtual dh e:(IB)V
L8
    aload 0
    iload 1
    bipush 21
    iushr
    sipush 128
    ior
    bipush 12
    invokevirtual dh e:(IB)V
L6
    aload 0
    iload 1
    bipush 14
    iushr
    sipush 128
    ior
    bipush -20
    invokevirtual dh e:(IB)V
    goto L4
L3
    iload 1
    sipush -16384
    iand
    ifeq L4
    goto L5
L2
    aload 0
    iload 1
    bipush 127
    iand
    bipush 20
    invokevirtual dh e:(IB)V
L10
    return
L11
    new java/lang/StringBuilder
    dup
    invokespecial java/lang/StringBuilder <init>:()V
    ldc "dh.t(" (java.lang.String)
    invokevirtual java/lang/StringBuilder append:(Ljava/lang/String;)Ljava/lang/StringBuilder;
    ldc 41 (java.lang.Integer)
    invokevirtual java/lang/StringBuilder append:(C)Ljava/lang/StringBuilder;
    invokevirtual java/lang/StringBuilder toString:()Ljava/lang/String;
    invokestatic k a:(Ljava/lang/Throwable;Ljava/lang/String;)Lee;
    athrow
