di v ([BI)[BL1
    new dh
    dup
    aload 0
    invokespecial dh <init>:([B)V
    astore 2
    goto L2
L3
    new java/lang/RuntimeException
    dup
    invokespecial java/lang/RuntimeException <init>:()V
    athrow
L4
    aload 2
    ldc -1948717675 (java.lang.Integer)
    invokevirtual dh x:(I)I
    istore 4
    goto L5
L2
    aload 2
    ldc 736961855 (java.lang.Integer)
    invokevirtual dh z:(I)I
    istore 3
    goto L4
L6
    aload 5
    areturn
L7
    iload 4
    ldc 112979981 (java.lang.Integer)
    getstatic fv z:I
    imul
    if_icmple L8
    goto L3
L9
    iload 5
    getstatic fv z:I
    ldc 112979981 (java.lang.Integer)
    imul
    if_icmple L10
    iload 1
    ldc -716754474 (java.lang.Integer)
    if_icmpne L11
    new java/lang/IllegalStateException
    dup
    invokespecial java/lang/IllegalStateException <init>:()V
    athrow
L8
    iload 3
    ifne L12
    goto L13
L14
    iconst_0
    ldc 112979981 (java.lang.Integer)
    getstatic fv z:I
    imul
    if_icmpeq L8
    iload 1
    ldc -716754474 (java.lang.Integer)
    if_icmpne L7
    new java/lang/IllegalStateException
    dup
    invokespecial java/lang/IllegalStateException <init>:()V
    athrow
L15
    aload 2
    aload 5
    iconst_0
    iload 4
    bipush -117
    invokevirtual dh ap:([BIIB)V
    goto L6
L16
    aload 6
    iload 5
    aload 0
    iload 4
    bipush 9
    invokestatic dc e:([BI[BII)I
    pop
    goto L17
L12
    aload 2
    ldc -2053967422 (java.lang.Integer)
    invokevirtual dh x:(I)I
    istore 5
L18
    iload 5
    iflt L11
    iload 1
    ldc -716754474 (java.lang.Integer)
    if_icmpne L19
    new java/lang/IllegalStateException
    dup
    invokespecial java/lang/IllegalStateException <init>:()V
    athrow
L19
    getstatic fv z:I
    ldc 112979981 (java.lang.Integer)
    imul
    ifeq L10
    iload 1
    ldc -716754474 (java.lang.Integer)
    if_icmpne L9
    new java/lang/IllegalStateException
    dup
    invokespecial java/lang/IllegalStateException <init>:()V
    athrow
L13
    iload 4
    newarray 8
    astore 5
    goto L15
L11
    new java/lang/RuntimeException
    dup
    invokespecial java/lang/RuntimeException <init>:()V
    athrow
L5
    iload 4
    iflt L3
    iload 1
    ldc -716754474 (java.lang.Integer)
    if_icmpne L14
    new java/lang/IllegalStateException
    dup
    invokespecial java/lang/IllegalStateException <init>:()V
    athrow
L20
    iconst_1
    iload 3
    if_icmpne L21
    iload 1
    ldc -716754474 (java.lang.Integer)
    if_icmpne L16
    new java/lang/IllegalStateException
    dup
    invokespecial java/lang/IllegalStateException <init>:()V
    athrow
L10
    iload 5
    newarray 8
    astore 6
    goto L20
L21
    getstatic fv s:Ldp;
    aload 2
    aload 6
    ldc 1097337150 (java.lang.Integer)
    invokevirtual dp e:(Ldh;[BI)V
L17
    aload 6
    areturn
L22
    new java/lang/StringBuilder
    dup
    invokespecial java/lang/StringBuilder <init>:()V
    ldc "di.v(" (java.lang.String)
    invokevirtual java/lang/StringBuilder append:(Ljava/lang/String;)Ljava/lang/StringBuilder;
    ldc 41 (java.lang.Integer)
    invokevirtual java/lang/StringBuilder append:(C)Ljava/lang/StringBuilder;
    invokevirtual java/lang/StringBuilder toString:()Ljava/lang/String;
    invokestatic k a:(Ljava/lang/Throwable;Ljava/lang/String;)Lee;
    athrow
