dj e (IB)Lad;L1
    getstatic ad r:Lgr;
    iload 0
    i2l
    invokevirtual gr e:(J)Lgd;
    checkcast ad
    astore 2
    goto L2
L3
    aload 2
    areturn
L4
    aload 2
    bipush -115
    invokevirtual ad a:(B)V
    goto L5
L6
    getstatic ad c:Lfv;
    bipush 10
    iload 0
    ldc -1070597842 (java.lang.Integer)
    invokevirtual fv l:(III)[B
    astore 3
L7
    new ad
    dup
    invokespecial ad <init>:()V
    astore 2
L8
    aload 2
    ldc -924670761 (java.lang.Integer)
    iload 0
    imul
    putfield ad h:I
    goto L9
L10
    aload 2
    aconst_null
    putfield ad ap:[Ljava/lang/String;
    goto L11
L12
    aload 2
    new dh
    dup
    aload 3
    invokespecial dh <init>:([B)V
    ldc 1909748659 (java.lang.Integer)
    invokevirtual ad l:(Ldh;I)V
    goto L4
L13
    aload 2
    aload 2
    getfield ad bk:I
    ldc -1952217047 (java.lang.Integer)
    imul
    bipush -80
    invokestatic dj e:(IB)Lad;
    aload 2
    getfield ad bl:I
    ldc -1489812315 (java.lang.Integer)
    imul
    bipush -8
    invokestatic dj e:(IB)Lad;
    ldc -330792047 (java.lang.Integer)
    invokevirtual ad w:(Lad;Lad;I)V
    goto L14
L9
    aload 3
    ifnull L4
    goto L12
L15
    aload 2
    aload 2
    getfield ad aq:I
    ldc -1486695127 (java.lang.Integer)
    imul
    bipush -57
    invokestatic dj e:(IB)Lad;
    ldc -2093824353 (java.lang.Integer)
    aload 2
    getfield ad ar:I
    imul
    bipush -52
    invokestatic dj e:(IB)Lad;
    ldc 1705390256 (java.lang.Integer)
    invokevirtual ad u:(Lad;Lad;I)V
L16
    iconst_m1
    ldc -1952217047 (java.lang.Integer)
    aload 2
    getfield ad bk:I
    imul
    if_icmpeq L14
    iload 1
    iconst_3
    if_icmpne L13
    new java/lang/IllegalStateException
    dup
    invokespecial java/lang/IllegalStateException <init>:()V
    athrow
L2
    aload 2
    ifnull L6
    goto L3
L14
    getstatic dx w:Z
    ifne L17
    iload 1
    iconst_3
    if_icmpne L18
    new java/lang/IllegalStateException
    dup
    invokespecial java/lang/IllegalStateException <init>:()V
    athrow
L18
    aload 2
    getfield ad ax:Z
    ifeq L17
    iload 1
    iconst_3
    if_icmpne L19
    new java/lang/IllegalStateException
    dup
    invokespecial java/lang/IllegalStateException <init>:()V
    athrow
L19
    aload 2
    getstatic et e:Ljava/lang/String;
    putfield ad j:Ljava/lang/String;
L20
    aload 2
    iconst_0
    putfield ad aa:Z
    goto L10
L11
    aload 2
    aconst_null
    putfield ad ao:[Ljava/lang/String;
    goto L21
L5
    aload 2
    getfield ad aq:I
    ldc -1486695127 (java.lang.Integer)
    imul
    iconst_m1
    if_icmpeq L16
    goto L15
L21
    aload 2
    iconst_0
    putfield ad as:I
L17
    getstatic ad r:Lgr;
    aload 2
    iload 0
    i2l
    invokevirtual gr l:(Lgd;J)V
L22
    aload 2
    areturn
L23
    new java/lang/StringBuilder
    dup
    invokespecial java/lang/StringBuilder <init>:()V
    ldc "dj.e(" (java.lang.String)
    invokevirtual java/lang/StringBuilder append:(Ljava/lang/String;)Ljava/lang/StringBuilder;
    ldc 41 (java.lang.Integer)
    invokevirtual java/lang/StringBuilder append:(C)Ljava/lang/StringBuilder;
    invokevirtual java/lang/StringBuilder toString:()Ljava/lang/String;
    invokestatic k a:(Ljava/lang/Throwable;Ljava/lang/String;)Lee;
    athrow
