dk bk (IIIIIIIIIB)VL1
    aconst_null
    astore 10
    goto L2
L3
    getstatic client hl:Lgh;
    aload 10
    invokevirtual gh a:(Lgm;)V
    goto L4
L5
    aload 11
    ifnull L6
    goto L7
L8
    ldc -1506352819 (java.lang.Integer)
    aload 11
    getfield t l:I
    imul
    iload 1
    if_icmpne L9
    iload 9
    bipush 8
    if_icmpeq L10
    new java/lang/IllegalStateException
    dup
    invokespecial java/lang/IllegalStateException <init>:()V
    athrow
L11
    aload 10
    iload 3
    ldc 1764201691 (java.lang.Integer)
    imul
    putfield t a:I
    goto L12
L10
    iload 2
    ldc -1485218469 (java.lang.Integer)
    aload 11
    getfield t c:I
    imul
    if_icmpne L9
    iload 9
    bipush 8
    if_icmpeq L13
    return
L13
    aload 11
    getfield t a:I
    ldc -834255021 (java.lang.Integer)
    imul
    iload 3
    if_icmpne L9
L14
    aload 11
    astore 10
L15
    goto L6
L16
    aload 10
    ldc 939494099 (java.lang.Integer)
    iload 2
    imul
    putfield t c:I
    goto L17
L6
    aload 10
    ifnonnull L4
L18
    new t
    dup
    invokespecial t <init>:()V
    astore 10
L19
    aload 10
    ldc 27823615 (java.lang.Integer)
    iload 0
    imul
    putfield t e:I
    goto L11
L17
    aload 10
    iconst_1
    invokestatic t bw:(Lt;B)V
    goto L3
L2
    getstatic client hl:Lgh;
    invokevirtual gh i:()Lgm;
    checkcast t
    astore 11
    goto L5
L7
    ldc -1751944705 (java.lang.Integer)
    aload 11
    getfield t e:I
    imul
    iload 0
    if_icmpne L9
    iload 9
    bipush 8
    if_icmpeq L8
    new java/lang/IllegalStateException
    dup
    invokespecial java/lang/IllegalStateException <init>:()V
    athrow
L20
    aload 10
    iload 5
    ldc -1561762019 (java.lang.Integer)
    imul
    putfield t g:I
    goto L21
L22
    aload 10
    ldc 261186501 (java.lang.Integer)
    iload 8
    imul
    putfield t h:I
    goto L23
L4
    aload 10
    ldc -416359209 (java.lang.Integer)
    iload 4
    imul
    putfield t r:I
    goto L20
L9
    getstatic client hl:Lgh;
    invokevirtual gh f:()Lgm;
    checkcast t
    astore 11
    goto L5
L21
    aload 10
    ldc 331436709 (java.lang.Integer)
    iload 6
    imul
    putfield t f:I
L24
    aload 10
    iload 7
    ldc -651742731 (java.lang.Integer)
    imul
    putfield t o:I
    goto L22
L12
    aload 10
    iload 1
    ldc 1857503109 (java.lang.Integer)
    imul
    putfield t l:I
    goto L16
L23
    return
L25
    new java/lang/StringBuilder
    dup
    invokespecial java/lang/StringBuilder <init>:()V
    ldc "dk.bk(" (java.lang.String)
    invokevirtual java/lang/StringBuilder append:(Ljava/lang/String;)Ljava/lang/StringBuilder;
    ldc 41 (java.lang.Integer)
    invokevirtual java/lang/StringBuilder append:(C)Ljava/lang/StringBuilder;
    invokevirtual java/lang/StringBuilder toString:()Ljava/lang/String;
    invokestatic k a:(Ljava/lang/Throwable;Ljava/lang/String;)Lee;
    athrow
