dl df (IIIILbh;I)VL1
    iload 2
    iload 2
    imul
    iload 3
    iload 3
    imul
    iadd
    istore 6
    goto L2
L3
    getstatic cp am:[I
    iload 7
    iaload
    istore 9
    goto L4
L5
    iload 6
    ldc 90000 (java.lang.Integer)
    if_icmpge L6
    iload 5
    ldc -331391087 (java.lang.Integer)
    if_icmpne L7
    return
L8
    getstatic ch ex:Lbh;
    bipush 94
    iload 0
    iadd
    iload 14
    iadd
    iconst_4
    iadd
    bipush 10
    isub
    iload 1
    bipush 83
    iadd
    iload 15
    isub
    bipush 20
    isub
    bipush 20
    bipush 20
    bipush 15
    bipush 15
    dload 12
    sipush 256
    invokevirtual bh n:(IIIIIIDI)V
    goto L9
L10
    dload 12
    invokestatic java/lang/Math cos:(D)D
    ldc 57.0 (java.lang.Double)
    dmul
    d2i
    istore 15
    goto L8
L2
    iload 6
    sipush 4225
    if_icmple L6
    iload 5
    ldc -331391087 (java.lang.Integer)
    if_icmpne L5
    new java/lang/IllegalStateException
    dup
    invokespecial java/lang/IllegalStateException <init>:()V
    athrow
L4
    sipush 256
    iload 8
    imul
    ldc -981441773 (java.lang.Integer)
    getstatic client ec:I
    imul
    sipush 256
    iadd
    idiv
    istore 8
L11
    iload 9
    sipush 256
    imul
    sipush 256
    ldc -981441773 (java.lang.Integer)
    getstatic client ec:I
    imul
    iadd
    idiv
    istore 9
    goto L12
L13
    getstatic cp aw:[I
    iload 7
    iaload
    istore 8
    goto L3
L7
    ldc 1158077643 (java.lang.Integer)
    getstatic client el:I
    imul
    ldc 154136385 (java.lang.Integer)
    getstatic client fy:I
    imul
    iadd
    sipush 2047
    iand
    istore 7
    goto L13
L14
    iload 10
    i2d
    iload 11
    i2d
    invokestatic java/lang/Math atan2:(DD)D
    dstore 12
    goto L15
L9
    goto L16
L15
    dload 12
    invokestatic java/lang/Math sin:(D)D
    ldc 63.0 (java.lang.Double)
    dmul
    d2i
    istore 14
    goto L10
L12
    iload 2
    iload 9
    imul
    iload 8
    iload 3
    imul
    iadd
    bipush 16
    ishr
    istore 10
L17
    iload 3
    iload 9
    imul
    iload 2
    iload 8
    imul
    isub
    bipush 16
    ishr
    istore 11
    goto L14
L6
    iload 0
    iload 1
    iload 2
    iload 3
    aload 4
    ldc 1204133672 (java.lang.Integer)
    invokestatic fj dp:(IIIILbh;I)V
L16
    return
L18
    new java/lang/StringBuilder
    dup
    invokespecial java/lang/StringBuilder <init>:()V
    ldc "dl.df(" (java.lang.String)
    invokevirtual java/lang/StringBuilder append:(Ljava/lang/String;)Ljava/lang/StringBuilder;
    ldc 41 (java.lang.Integer)
    invokevirtual java/lang/StringBuilder append:(C)Ljava/lang/StringBuilder;
    invokevirtual java/lang/StringBuilder toString:()Ljava/lang/String;
    invokestatic k a:(Ljava/lang/Throwable;Ljava/lang/String;)Lee;
    athrow
