dm av (Ljava/lang/String;ZI)VL1
    iconst_4
    istore 3
L2
    bipush 6
    iload 3
    iadd
    istore 4
L3
    iload 3
    bipush 6
    iadd
    istore 5
L4
    getstatic gy co:Lhh;
    aload 0
    sipush 250
    invokevirtual hh w:(Ljava/lang/String;I)I
    istore 6
L5
    getstatic gy co:Lhh;
    aload 0
    sipush 250
    invokevirtual hh i:(Ljava/lang/String;I)I
    bipush 13
    imul
    istore 7
L6
    iload 4
    iload 3
    isub
    iload 5
    iload 3
    isub
    iload 3
    iload 3
    iload 6
    iadd
    iadd
    iload 7
    iload 3
    iadd
    iload 3
    iadd
    iconst_0
    invokestatic bt cs:(IIIII)V
L7
    iload 4
    iload 3
    isub
    iload 5
    iload 3
    isub
    iload 3
    iload 6
    iload 3
    iadd
    iadd
    iload 3
    iload 7
    iadd
    iload 3
    iadd
    ldc 16777215 (java.lang.Integer)
    invokestatic bt ca:(IIIII)V
L8
    getstatic gy co:Lhh;
    aload 0
    iload 4
    iload 5
    iload 6
    iload 7
    ldc 16777215 (java.lang.Integer)
    iconst_m1
    iconst_1
    iconst_1
    iconst_0
    invokevirtual hh h:(Ljava/lang/String;IIIIIIIII)I
    pop
L9
    iload 4
    iload 3
    isub
    iload 5
    iload 3
    isub
    iload 3
    iload 6
    iadd
    iload 3
    iadd
    iload 7
    iload 3
    iadd
    iload 3
    iadd
    ldc 1517496563 (java.lang.Integer)
    invokestatic client bd:(IIIII)V
L10
    iload 1
    ifeq L11
    iload 2
    ldc -714308640 (java.lang.Integer)
    if_icmpeq L12
    new java/lang/IllegalStateException
    dup
    invokespecial java/lang/IllegalStateException <init>:()V
    athrow
L12
    getstatic eb pd:Ljava/awt/Canvas;
    invokevirtual java/awt/Canvas getGraphics:()Ljava/awt/Graphics;
    astore 8
L13
    getstatic v py:Lbz;
    aload 8
    iconst_0
    iconst_0
    bipush -47
    invokevirtual bz a:(Ljava/awt/Graphics;IIB)V
L14
    goto L15
L16
    astore 8
L17
    getstatic eb pd:Ljava/awt/Canvas;
    invokevirtual java/awt/Canvas repaint:()V
L18
    goto L15
L11
    iload 4
    iload 5
    iload 6
    iload 7
    ldc -1687466395 (java.lang.Integer)
    invokestatic cm bb:(IIIII)V
L15
    return
L19
    new java/lang/StringBuilder
    dup
    invokespecial java/lang/StringBuilder <init>:()V
    ldc "dm.av(" (java.lang.String)
    invokevirtual java/lang/StringBuilder append:(Ljava/lang/String;)Ljava/lang/StringBuilder;
    ldc 41 (java.lang.Integer)
    invokevirtual java/lang/StringBuilder append:(C)Ljava/lang/StringBuilder;
    invokevirtual java/lang/StringBuilder toString:()Ljava/lang/String;
    invokestatic k a:(Ljava/lang/Throwable;Ljava/lang/String;)Lee;
    athrow
