dn p (Ldz;Ljava/awt/Component;III)Laa;L1
    ldc -279793531 (java.lang.Integer)
    getstatic aa l:I
    imul
    ifne L2
    iload 4
    ldc -1692490357 (java.lang.Integer)
    if_icmplt L3
    new java/lang/IllegalStateException
    dup
    invokespecial java/lang/IllegalStateException <init>:()V
    athrow
L3
    new java/lang/IllegalStateException
    dup
    invokespecial java/lang/IllegalStateException <init>:()V
    athrow
L2
    iload 2
    iflt L4
    iload 4
    ldc -1692490357 (java.lang.Integer)
    if_icmplt L5
    new java/lang/IllegalStateException
    dup
    invokespecial java/lang/IllegalStateException <init>:()V
    athrow
L5
    iload 2
    iconst_2
    if_icmplt L6
    iload 4
    ldc -1692490357 (java.lang.Integer)
    if_icmplt L4
    new java/lang/IllegalStateException
    dup
    invokespecial java/lang/IllegalStateException <init>:()V
    athrow
L4
    new java/lang/IllegalArgumentException
    dup
    invokespecial java/lang/IllegalArgumentException <init>:()V
    athrow
L6
    iload 3
    sipush 256
    if_icmpge L7
    iload 4
    ldc -1692490357 (java.lang.Integer)
    if_icmplt L8
    new java/lang/IllegalStateException
    dup
    invokespecial java/lang/IllegalStateException <init>:()V
    athrow
L8
    sipush 256
    istore 3
L7
    new bx
    dup
    invokespecial bx <init>:()V
    astore 5
L9
    aload 5
    getstatic aa c:Z
    ifeq L10
    iload 4
    ldc -1692490357 (java.lang.Integer)
    if_icmplt L11
    new java/lang/IllegalStateException
    dup
    invokespecial java/lang/IllegalStateException <init>:()V
    athrow
L11
    iconst_2
    goto L12
L10
    iconst_1
L12
    sipush 256
    imul
    newarray 10
    putfield aa f:[I
L13
    aload 5
    iload 3
    ldc -513505379 (java.lang.Integer)
    imul
    putfield aa j:I
L14
    aload 5
    aload 1
    invokevirtual aa e:(Ljava/awt/Component;)V
L15
    aload 5
    sipush 1024
    iload 3
    sipush -1024
    iand
    iadd
    ldc -629040163 (java.lang.Integer)
    imul
    putfield aa s:I
L16
    aload 5
    getfield aa s:I
    ldc 818451573 (java.lang.Integer)
    imul
    sipush 16384
    if_icmple L17
    aload 5
    ldc 1727479808 (java.lang.Integer)
    putfield aa s:I
L17
    aload 5
    ldc 818451573 (java.lang.Integer)
    aload 5
    getfield aa s:I
    imul
    invokevirtual aa a:(I)V
L18
    ldc -679105819 (java.lang.Integer)
    getstatic dl u:I
    imul
    ifle L19
    iload 4
    ldc -1692490357 (java.lang.Integer)
    if_icmplt L20
    new java/lang/IllegalStateException
    dup
    invokespecial java/lang/IllegalStateException <init>:()V
    athrow
L20
    getstatic aa w:Lbj;
    ifnonnull L19
    iload 4
    ldc -1692490357 (java.lang.Integer)
    if_icmplt L21
    new java/lang/IllegalStateException
    dup
    invokespecial java/lang/IllegalStateException <init>:()V
    athrow
L21
    new bj
    dup
    invokespecial bj <init>:()V
    putstatic aa w:Lbj;
L22
    getstatic aa w:Lbj;
    aload 0
    putfield bj e:Ldz;
L23
    aload 0
    getstatic aa w:Lbj;
    getstatic dl u:I
    ldc -679105819 (java.lang.Integer)
    imul
    bipush 8
    invokevirtual dz i:(Ljava/lang/Runnable;IB)Lex;
    pop
L19
    aconst_null
    getstatic aa w:Lbj;
    if_acmpeq L24
    iload 4
    ldc -1692490357 (java.lang.Integer)
    if_icmplt L25
    new java/lang/IllegalStateException
    dup
    invokespecial java/lang/IllegalStateException <init>:()V
    athrow
L25
    aconst_null
    getstatic aa w:Lbj;
    getfield bj a:[Laa;
    iload 2
    aaload
    if_acmpeq L26
    iload 4
    ldc -1692490357 (java.lang.Integer)
    if_icmplt L27
    new java/lang/IllegalStateException
    dup
    invokespecial java/lang/IllegalStateException <init>:()V
    athrow
L27
    new java/lang/IllegalArgumentException
    dup
    invokespecial java/lang/IllegalArgumentException <init>:()V
    athrow
L26
    getstatic aa w:Lbj;
    getfield bj a:[Laa;
    iload 2
    aload 5
    aastore
L24
    aload 5
L28
    areturn
L29
    astore 5
L30
    new af
    dup
    aload 0
    iload 2
    invokespecial af <init>:(Ldz;I)V
    astore 5
L31
    aload 5
    sipush 256
    getstatic aa c:Z
    ifeq L32
    iconst_2
    goto L33
L32
    iconst_1
L33
    imul
    newarray 10
    putfield aa f:[I
L34
    aload 5
    ldc -513505379 (java.lang.Integer)
    iload 3
    imul
    putfield aa j:I
L35
    aload 5
    aload 1
    invokevirtual aa e:(Ljava/awt/Component;)V
L36
    aload 5
    ldc 1727479808 (java.lang.Integer)
    putfield aa s:I
L37
    aload 5
    aload 5
    getfield aa s:I
    ldc 818451573 (java.lang.Integer)
    imul
    invokevirtual aa a:(I)V
L38
    getstatic dl u:I
    ldc -679105819 (java.lang.Integer)
    imul
    ifle L39
    iload 4
    ldc -1692490357 (java.lang.Integer)
    if_icmplt L40
    new java/lang/IllegalStateException
    dup
    invokespecial java/lang/IllegalStateException <init>:()V
    athrow
L40
    getstatic aa w:Lbj;
    ifnonnull L39
    iload 4
    ldc -1692490357 (java.lang.Integer)
    if_icmplt L41
    new java/lang/IllegalStateException
    dup
    invokespecial java/lang/IllegalStateException <init>:()V
    athrow
L41
    new bj
    dup
    invokespecial bj <init>:()V
    putstatic aa w:Lbj;
L42
    getstatic aa w:Lbj;
    aload 0
    putfield bj e:Ldz;
L43
    aload 0
    getstatic aa w:Lbj;
    getstatic dl u:I
    ldc -679105819 (java.lang.Integer)
    imul
    bipush 8
    invokevirtual dz i:(Ljava/lang/Runnable;IB)Lex;
    pop
L39
    aconst_null
    getstatic aa w:Lbj;
    if_acmpeq L44
L45
    aconst_null
    getstatic aa w:Lbj;
    getfield bj a:[Laa;
    iload 2
    aaload
    if_acmpeq L46
    new java/lang/IllegalArgumentException
    dup
    invokespecial java/lang/IllegalArgumentException <init>:()V
    athrow
L46
    getstatic aa w:Lbj;
    getfield bj a:[Laa;
    iload 2
    aload 5
    aastore
L44
    aload 5
L47
    areturn
L48
    astore 5
L49
    new aa
    dup
    invokespecial aa <init>:()V
    areturn
L50
    new java/lang/StringBuilder
    dup
    invokespecial java/lang/StringBuilder <init>:()V
    ldc "dn.p(" (java.lang.String)
    invokevirtual java/lang/StringBuilder append:(Ljava/lang/String;)Ljava/lang/StringBuilder;
    ldc 41 (java.lang.Integer)
    invokevirtual java/lang/StringBuilder append:(C)Ljava/lang/StringBuilder;
    invokevirtual java/lang/StringBuilder toString:()Ljava/lang/String;
    invokestatic k a:(Ljava/lang/Throwable;Ljava/lang/String;)Lee;
    athrow
