dp e (Ldh;[BI)VL1
    aload 1
    getfield dh e:[B
    ldc 910905453 (java.lang.Integer)
    aload 1
    getfield dh a:I
    imul
    baload
    bipush 31
    if_icmpne L2
    iload 3
    ldc -654168107 (java.lang.Integer)
    if_icmpgt L3
    new java/lang/IllegalStateException
    dup
    invokespecial java/lang/IllegalStateException <init>:()V
    athrow
L3
    bipush -117
    aload 1
    getfield dh e:[B
    iconst_1
    ldc 910905453 (java.lang.Integer)
    aload 1
    getfield dh a:I
    imul
    iadd
    baload
    if_icmpeq L4
L2
    new java/lang/RuntimeException
    dup
    ldc "" (java.lang.String)
    invokespecial java/lang/RuntimeException <init>:(Ljava/lang/String;)V
    athrow
L4
    aload 0
    getfield dp e:Ljava/util/zip/Inflater;
    ifnonnull L5
    iload 3
    ldc -654168107 (java.lang.Integer)
    if_icmpgt L6
    new java/lang/IllegalStateException
    dup
    invokespecial java/lang/IllegalStateException <init>:()V
    athrow
L6
    aload 0
    new java/util/zip/Inflater
    dup
    iconst_1
    invokespecial java/util/zip/Inflater <init>:(Z)V
    putfield dp e:Ljava/util/zip/Inflater;
L5
    aload 0
    getfield dp e:Ljava/util/zip/Inflater;
    aload 1
    getfield dh e:[B
    bipush 10
    ldc 910905453 (java.lang.Integer)
    aload 1
    getfield dh a:I
    imul
    iadd
    aload 1
    getfield dh e:[B
    arraylength
    bipush 8
    bipush 10
    ldc 910905453 (java.lang.Integer)
    aload 1
    getfield dh a:I
    imul
    iadd
    iadd
    isub
    invokevirtual java/util/zip/Inflater setInput:([BII)V
L7
    aload 0
    getfield dp e:Ljava/util/zip/Inflater;
    aload 2
    invokevirtual java/util/zip/Inflater inflate:([B)I
    pop
L8
    goto L9
L10
    astore 4
L11
    aload 0
    getfield dp e:Ljava/util/zip/Inflater;
    invokevirtual java/util/zip/Inflater reset:()V
L12
    new java/lang/RuntimeException
    dup
    ldc "" (java.lang.String)
    invokespecial java/lang/RuntimeException <init>:(Ljava/lang/String;)V
    athrow
L9
    aload 0
    getfield dp e:Ljava/util/zip/Inflater;
    invokevirtual java/util/zip/Inflater reset:()V
L13
    return
L14
    new java/lang/StringBuilder
    dup
    invokespecial java/lang/StringBuilder <init>:()V
    ldc "dp.e(" (java.lang.String)
    invokevirtual java/lang/StringBuilder append:(Ljava/lang/String;)Ljava/lang/StringBuilder;
    ldc 41 (java.lang.Integer)
    invokevirtual java/lang/StringBuilder append:(C)Ljava/lang/StringBuilder;
    invokevirtual java/lang/StringBuilder toString:()Ljava/lang/String;
    invokestatic k a:(Ljava/lang/Throwable;Ljava/lang/String;)Lee;
    athrow
