dx g (IIIIIZI)Lbh;L1
    iload 1
    iconst_m1
    if_icmpne L2
    iload 6
    ldc -830638404 (java.lang.Integer)
    if_icmpgt L3
    new java/lang/IllegalStateException
    dup
    invokespecial java/lang/IllegalStateException <init>:()V
    athrow
L4
    invokestatic cp e:()V
    goto L5
L2
    iload 4
    iconst_2
    if_icmpne L6
    iload 6
    ldc -830638404 (java.lang.Integer)
    if_icmpgt L7
    new java/lang/IllegalStateException
    dup
    invokespecial java/lang/IllegalStateException <init>:()V
    athrow
L7
    iconst_1
    iload 1
    if_icmpeq L6
    iload 6
    ldc -830638404 (java.lang.Integer)
    if_icmpgt L8
    new java/lang/IllegalStateException
    dup
    invokespecial java/lang/IllegalStateException <init>:()V
    athrow
L8
    iconst_1
    istore 4
    goto L6
L9
    aload 10
    iconst_1
    bipush 62
    invokevirtual ad r:(IB)Lcy;
    astore 11
    goto L10
L11
    ldc 1.5 (java.lang.Double)
    iload 17
    i2d
    dmul
    d2i
    istore 17
    goto L12
L13
    getstatic ad g:Lgr;
    lload 7
    invokevirtual gr e:(J)Lgd;
    checkcast bh
    astore 9
L14
    aload 9
    ifnull L15
    iload 6
    ldc -830638404 (java.lang.Integer)
    if_icmpgt L16
    new java/lang/IllegalStateException
    dup
    invokespecial java/lang/IllegalStateException <init>:()V
    athrow
L16
    aload 9
    areturn
L15
    iload 0
    bipush -84
    invokestatic dj e:(IB)Lad;
    astore 10
L17
    iload 1
    iconst_1
    if_icmple L9
    iload 6
    ldc -830638404 (java.lang.Integer)
    if_icmpgt L18
    new java/lang/IllegalStateException
    dup
    invokespecial java/lang/IllegalStateException <init>:()V
    athrow
L18
    aload 10
    getfield ad al:[I
    ifnull L9
    iload 6
    ldc -830638404 (java.lang.Integer)
    if_icmpgt L19
    new java/lang/IllegalStateException
    dup
    invokespecial java/lang/IllegalStateException <init>:()V
    athrow
L20
    ldc -1486695127 (java.lang.Integer)
    aload 10
    getfield ad aq:I
    imul
    iconst_m1
    if_icmpeq L21
    iload 6
    ldc -830638404 (java.lang.Integer)
    if_icmpgt L22
    new java/lang/IllegalStateException
    dup
    invokespecial java/lang/IllegalStateException <init>:()V
    athrow
L23
    iconst_0
    istore 12
L24
    iload 12
    bipush 10
    if_icmpge L25
    iload 6
    ldc -830638404 (java.lang.Integer)
    if_icmpgt L26
    new java/lang/IllegalStateException
    dup
    invokespecial java/lang/IllegalStateException <init>:()V
    athrow
L27
    aload 16
    invokestatic bt co:([I)V
    goto L28
L29
    iconst_0
    aload 10
    getfield ad ak:[I
    iload 12
    iaload
    if_icmpeq L30
    iload 6
    ldc -830638404 (java.lang.Integer)
    if_icmpgt L31
    new java/lang/IllegalStateException
    dup
    invokespecial java/lang/IllegalStateException <init>:()V
    athrow
L31
    aload 10
    getfield ad al:[I
    iload 12
    iaload
    istore 11
    goto L30
L6
    iload 0
    i2l
    iload 1
    i2l
    bipush 16
    lshl
    ladd
    iload 2
    i2l
    bipush 38
    lshl
    ladd
    iload 4
    i2l
    bipush 40
    lshl
    ladd
    iload 3
    i2l
    bipush 42
    lshl
    ladd
    lstore 7
    goto L32
L25
    iconst_m1
    iload 11
    if_icmpeq L9
    iload 6
    ldc -830638404 (java.lang.Integer)
    if_icmpgt L33
    new java/lang/IllegalStateException
    dup
    invokespecial java/lang/IllegalStateException <init>:()V
    athrow
L33
    iload 11
    bipush 27
    invokestatic dj e:(IB)Lad;
    astore 10
    goto L9
L34
    iconst_0
    putstatic cp c:Z
    goto L35
L36
    getstatic bt j:I
    istore 14
    goto L37
L38
    aconst_null
    areturn
L39
    iconst_0
    iload 3
    if_icmpeq L40
    goto L41
L22
    aload 10
    getfield ad ar:I
    ldc -2093824353 (java.lang.Integer)
    imul
    bipush 10
    iconst_1
    iconst_0
    iconst_0
    iconst_1
    ldc 454839372 (java.lang.Integer)
    invokestatic dx g:(IIIIIZI)Lbh;
    astore 12
    goto L42
L43
    aconst_null
    areturn
L42
    aconst_null
    aload 12
    if_acmpne L44
    iload 6
    ldc -830638404 (java.lang.Integer)
    if_icmpgt L43
    new java/lang/IllegalStateException
    dup
    invokespecial java/lang/IllegalStateException <init>:()V
    athrow
L45
    getstatic ad g:Lgr;
    aload 9
    lload 7
    invokevirtual gr l:(Lgd;J)V
    goto L46
L12
    iload 17
    getstatic cp aw:[I
    ldc 1852368649 (java.lang.Integer)
    aload 10
    getfield ad d:I
    imul
    iaload
    imul
    bipush 16
    ishr
    istore 18
    goto L47
L48
    iload 2
    iconst_1
    if_icmplt L49
    iload 6
    ldc -830638404 (java.lang.Integer)
    if_icmpgt L50
    new java/lang/IllegalStateException
    dup
    invokespecial java/lang/IllegalStateException <init>:()V
    athrow
L51
    aconst_null
    aload 12
    if_acmpne L44
    goto L52
L53
    new java/lang/StringBuilder
    dup
    invokespecial java/lang/StringBuilder <init>:()V
    ldc "<col=00ff80>" (java.lang.String)
    invokevirtual java/lang/StringBuilder append:(Ljava/lang/String;)Ljava/lang/StringBuilder;
    iload 1
    ldc 1000000 (java.lang.Integer)
    idiv
    invokevirtual java/lang/StringBuilder append:(I)Ljava/lang/StringBuilder;
    getstatic et fb:Ljava/lang/String;
    invokevirtual java/lang/StringBuilder append:(Ljava/lang/String;)Ljava/lang/StringBuilder;
    ldc "</col>" (java.lang.String)
    invokevirtual java/lang/StringBuilder append:(Ljava/lang/String;)Ljava/lang/StringBuilder;
    invokevirtual java/lang/StringBuilder toString:()Ljava/lang/String;
    astore 21
    goto L54
L55
    aconst_null
    astore 12
    goto L20
L44
    getstatic bt s:[I
    astore 13
    goto L36
L37
    getstatic bt m:I
    istore 15
L56
    iconst_4
    newarray 10
    astore 16
    goto L27
L35
    ldc -1550579387 (java.lang.Integer)
    aload 10
    getfield ad q:I
    imul
    istore 17
    goto L57
L28
    new bh
    dup
    bipush 36
    bipush 32
    invokespecial bh <init>:(II)V
    astore 9
    goto L58
L10
    aload 11
    ifnonnull L55
    iload 6
    ldc -830638404 (java.lang.Integer)
    if_icmpgt L38
    new java/lang/IllegalStateException
    dup
    invokespecial java/lang/IllegalStateException <init>:()V
    athrow
L59
    bipush 16
    bipush 16
    invokestatic cp c:(II)V
    goto L34
L60
    invokestatic cp e:()V
    goto L59
L58
    aload 9
    getfield bh e:[I
    bipush 36
    bipush 32
    invokestatic bt ck:([III)V
    goto L61
L19
    iconst_m1
    istore 11
    goto L23
L3
    iconst_0
    istore 4
    goto L6
L57
    iload 5
    ifeq L62
    iload 6
    ldc -830638404 (java.lang.Integer)
    if_icmpgt L11
    new java/lang/IllegalStateException
    dup
    invokespecial java/lang/IllegalStateException <init>:()V
    athrow
L62
    iload 2
    iconst_2
    if_icmpne L12
    goto L63
L64
    aload 11
    invokevirtual cy w:()V
    goto L65
L63
    iload 17
    i2d
    ldc 1.04 (java.lang.Double)
    dmul
    d2i
    istore 17
    goto L12
L66
    ldc -1489812315 (java.lang.Integer)
    aload 10
    getfield ad bl:I
    imul
    iload 1
    iload 2
    iload 3
    iconst_0
    iconst_0
    ldc -826298178 (java.lang.Integer)
    invokestatic dx g:(IIIIIZI)Lbh;
    astore 12
    goto L51
L47
    iload 17
    getstatic cp am:[I
    aload 10
    getfield ad d:I
    ldc 1852368649 (java.lang.Integer)
    imul
    iaload
    imul
    bipush 16
    ishr
    istore 19
    goto L64
L67
    aload 12
    iconst_0
    iconst_0
    invokevirtual bh h:(II)V
    goto L48
L65
    aload 11
    iconst_0
    ldc 1391227057 (java.lang.Integer)
    aload 10
    getfield ad b:I
    imul
    aload 10
    getfield ad x:I
    ldc -1181558825 (java.lang.Integer)
    imul
    ldc 1852368649 (java.lang.Integer)
    aload 10
    getfield ad d:I
    imul
    aload 10
    getfield ad n:I
    ldc -510409079 (java.lang.Integer)
    imul
    ldc -718238777 (java.lang.Integer)
    aload 11
    getfield cy cb:I
    imul
    iconst_2
    idiv
    iload 18
    iadd
    aload 10
    getfield ad v:I
    ldc -1145037447 (java.lang.Integer)
    imul
    iadd
    ldc -1145037447 (java.lang.Integer)
    aload 10
    getfield ad v:I
    imul
    iload 19
    iadd
    invokevirtual cy b:(IIIIIII)V
L68
    iconst_m1
    ldc -1952217047 (java.lang.Integer)
    aload 10
    getfield ad bk:I
    imul
    if_icmpeq L48
    iload 6
    ldc -830638404 (java.lang.Integer)
    if_icmpgt L67
    new java/lang/IllegalStateException
    dup
    invokespecial java/lang/IllegalStateException <init>:()V
    athrow
L61
    invokestatic bt cy:()V
    goto L60
L26
    iload 1
    aload 10
    getfield ad ak:[I
    iload 12
    iaload
    if_icmplt L30
    iload 6
    ldc -830638404 (java.lang.Integer)
    if_icmpgt L29
    new java/lang/IllegalStateException
    dup
    invokespecial java/lang/IllegalStateException <init>:()V
    athrow
L50
    aload 9
    iconst_1
    invokevirtual bh r:(I)V
L49
    iload 2
    iconst_2
    if_icmplt L39
    iload 6
    ldc -830638404 (java.lang.Integer)
    if_icmpgt L69
    new java/lang/IllegalStateException
    dup
    invokespecial java/lang/IllegalStateException <init>:()V
    athrow
L69
    aload 9
    ldc 16777215 (java.lang.Integer)
    invokevirtual bh r:(I)V
    goto L39
L70
    new java/lang/StringBuilder
    dup
    invokespecial java/lang/StringBuilder <init>:()V
    ldc "<col=ffffff>" (java.lang.String)
    invokevirtual java/lang/StringBuilder append:(Ljava/lang/String;)Ljava/lang/StringBuilder;
    iload 1
    sipush 1000
    idiv
    invokevirtual java/lang/StringBuilder append:(I)Ljava/lang/StringBuilder;
    getstatic et fl:Ljava/lang/String;
    invokevirtual java/lang/StringBuilder append:(Ljava/lang/String;)Ljava/lang/StringBuilder;
    ldc "</col>" (java.lang.String)
    invokevirtual java/lang/StringBuilder append:(Ljava/lang/String;)Ljava/lang/StringBuilder;
    invokevirtual java/lang/StringBuilder toString:()Ljava/lang/String;
    astore 21
    goto L71
L30
    iinc 12 1
    goto L24
L40
    aload 9
    getfield bh e:[I
    bipush 36
    bipush 32
    invokestatic bt ck:([III)V
L72
    iconst_m1
    aload 10
    getfield ad aq:I
    ldc -1486695127 (java.lang.Integer)
    imul
    if_icmpeq L73
    iload 6
    ldc -830638404 (java.lang.Integer)
    if_icmpgt L74
    new java/lang/IllegalStateException
    dup
    invokespecial java/lang/IllegalStateException <init>:()V
    athrow
L74
    aload 12
    iconst_0
    iconst_0
    invokevirtual bh h:(II)V
L73
    iconst_1
    iload 4
    if_icmpeq L75
    iload 6
    ldc -830638404 (java.lang.Integer)
    if_icmpgt L76
    new java/lang/IllegalStateException
    dup
    invokespecial java/lang/IllegalStateException <init>:()V
    athrow
L21
    iconst_m1
    ldc -1952217047 (java.lang.Integer)
    aload 10
    getfield ad bk:I
    imul
    if_icmpeq L44
    iload 6
    ldc -830638404 (java.lang.Integer)
    if_icmpgt L66
    new java/lang/IllegalStateException
    dup
    invokespecial java/lang/IllegalStateException <init>:()V
    athrow
L77
    aload 10
    getfield ad p:I
    ldc -94557995 (java.lang.Integer)
    imul
    iconst_1
    if_icmpne L78
    iload 6
    ldc -830638404 (java.lang.Integer)
    if_icmpgt L75
    new java/lang/IllegalStateException
    dup
    invokespecial java/lang/IllegalStateException <init>:()V
    athrow
L75
    getstatic hg o:Lhh;
    astore 20
L79
    iload 1
    ldc 100000 (java.lang.Integer)
    if_icmpge L80
L81
    new java/lang/StringBuilder
    dup
    invokespecial java/lang/StringBuilder <init>:()V
    ldc "<col=ffff00>" (java.lang.String)
    invokevirtual java/lang/StringBuilder append:(Ljava/lang/String;)Ljava/lang/StringBuilder;
    iload 1
    invokevirtual java/lang/StringBuilder append:(I)Ljava/lang/StringBuilder;
    ldc "</col>" (java.lang.String)
    invokevirtual java/lang/StringBuilder append:(Ljava/lang/String;)Ljava/lang/StringBuilder;
    invokevirtual java/lang/StringBuilder toString:()Ljava/lang/String;
    astore 21
L82
    goto L54
L80
    iload 1
    ldc 10000000 (java.lang.Integer)
    if_icmpge L53
    iload 6
    ldc -830638404 (java.lang.Integer)
    if_icmpgt L70
    new java/lang/IllegalStateException
    dup
    invokespecial java/lang/IllegalStateException <init>:()V
    athrow
L41
    aload 9
    iload 3
    invokevirtual bh f:(I)V
    goto L40
L71
    goto L54
L32
    iload 5
    ifne L15
    iload 6
    ldc -830638404 (java.lang.Integer)
    if_icmpgt L13
    new java/lang/IllegalStateException
    dup
    invokespecial java/lang/IllegalStateException <init>:()V
    athrow
L54
    aload 20
    aload 21
    iconst_0
    bipush 9
    ldc 16776960 (java.lang.Integer)
    iconst_1
    invokevirtual hh f:(Ljava/lang/String;IIII)V
L78
    iload 5
    ifne L46
    goto L45
L52
    aconst_null
    areturn
L46
    aload 13
    iload 14
    iload 15
    invokestatic bt ck:([III)V
L83
    aload 16
    invokestatic bt cn:([I)V
    goto L4
L76
    iconst_2
    iload 4
    if_icmpne L78
    iload 6
    ldc -830638404 (java.lang.Integer)
    if_icmpgt L77
    new java/lang/IllegalStateException
    dup
    invokespecial java/lang/IllegalStateException <init>:()V
    athrow
L5
    iconst_1
    putstatic cp c:Z
L84
    aload 9
    areturn
L85
    new java/lang/StringBuilder
    dup
    invokespecial java/lang/StringBuilder <init>:()V
    ldc "dx.g(" (java.lang.String)
    invokevirtual java/lang/StringBuilder append:(Ljava/lang/String;)Ljava/lang/StringBuilder;
    ldc 41 (java.lang.Integer)
    invokevirtual java/lang/StringBuilder append:(C)Ljava/lang/StringBuilder;
    invokevirtual java/lang/StringBuilder toString:()Ljava/lang/String;
    invokestatic k a:(Ljava/lang/Throwable;Ljava/lang/String;)Lee;
    athrow
