e l (IIIII)VL1
    getstatic m e:Lgf;
    iload 0
    i2l
    invokevirtual gf e:(J)Lgm;
    checkcast m
    astore 5
    goto L2
L3
    aload 6
    iload 8
    iconst_m1
    iastore
L4
    aload 7
    iload 8
    iconst_0
    iastore
    goto L5
L6
    getstatic m e:Lgf;
    aload 5
    iload 0
    i2l
    invokevirtual gf a:(Lgm;J)V
L7
    aload 5
    getfield m a:[I
    arraylength
    iload 1
    if_icmpgt L8
    iload 4
    ldc 166255335 (java.lang.Integer)
    if_icmpeq L9
    new java/lang/IllegalStateException
    dup
    invokespecial java/lang/IllegalStateException <init>:()V
    athrow
L10
    aload 7
    iload 8
    aload 5
    getfield m l:[I
    iload 8
    iaload
    iastore
    goto L11
L12
    iload 1
    iconst_1
    iadd
    newarray 10
    astore 7
    goto L13
L5
    iinc 8 1
    goto L14
L15
    iload 8
    aload 5
    getfield m a:[I
    arraylength
    if_icmpge L16
    iload 4
    ldc 166255335 (java.lang.Integer)
    if_icmpeq L17
    new java/lang/IllegalStateException
    dup
    invokespecial java/lang/IllegalStateException <init>:()V
    athrow
L17
    aload 6
    iload 8
    aload 5
    getfield m a:[I
    iload 8
    iaload
    iastore
    goto L10
L14
    iload 8
    iload 1
    if_icmpge L18
    iload 4
    ldc 166255335 (java.lang.Integer)
    if_icmpeq L3
    new java/lang/IllegalStateException
    dup
    invokespecial java/lang/IllegalStateException <init>:()V
    athrow
L11
    iinc 8 1
    goto L15
L16
    aload 5
    getfield m a:[I
    arraylength
    istore 8
    goto L14
L13
    iconst_0
    istore 8
    goto L15
L19
    aload 5
    getfield m l:[I
    iload 1
    iload 3
    iastore
    goto L20
L21
    new m
    dup
    invokespecial m <init>:()V
    astore 5
    goto L6
L9
    iload 1
    iconst_1
    iadd
    newarray 10
    astore 6
    goto L12
L18
    aload 5
    aload 6
    putfield m a:[I
L22
    aload 5
    aload 7
    putfield m l:[I
    goto L8
L2
    aload 5
    ifnonnull L7
    iload 4
    ldc 166255335 (java.lang.Integer)
    if_icmpeq L21
    return
L8
    aload 5
    getfield m a:[I
    iload 1
    iload 2
    iastore
    goto L19
L20
    return
L23
    new java/lang/StringBuilder
    dup
    invokespecial java/lang/StringBuilder <init>:()V
    ldc "e.l(" (java.lang.String)
    invokevirtual java/lang/StringBuilder append:(Ljava/lang/String;)Ljava/lang/StringBuilder;
    ldc 41 (java.lang.Integer)
    invokevirtual java/lang/StringBuilder append:(C)Ljava/lang/StringBuilder;
    invokevirtual java/lang/StringBuilder toString:()Ljava/lang/String;
    invokestatic k a:(Ljava/lang/Throwable;Ljava/lang/String;)Lee;
    athrow
