ed l (III)Lfb;L1
    iload 0
    ldc -2068421293 (java.lang.Integer)
    invokestatic f a:(II)Lfb;
    astore 3
    goto L2
L3
    aload 3
    areturn
L4
    iload 1
    aload 3
    getfield fb do:[Lfb;
    arraylength
    if_icmplt L5
    iload 2
    ldc 1791868066 (java.lang.Integer)
    if_icmplt L6
    new java/lang/IllegalStateException
    dup
    invokespecial java/lang/IllegalStateException <init>:()V
    athrow
L7
    aload 3
    ifnull L6
    iload 2
    ldc 1791868066 (java.lang.Integer)
    if_icmplt L8
    new java/lang/IllegalStateException
    dup
    invokespecial java/lang/IllegalStateException <init>:()V
    athrow
L5
    aload 3
    getfield fb do:[Lfb;
    iload 1
    aaload
    areturn
L2
    iconst_m1
    iload 1
    if_icmpne L7
    iload 2
    ldc 1791868066 (java.lang.Integer)
    if_icmplt L3
    new java/lang/IllegalStateException
    dup
    invokespecial java/lang/IllegalStateException <init>:()V
    athrow
L6
    aconst_null
    areturn
L8
    aload 3
    getfield fb do:[Lfb;
    ifnull L6
    iload 2
    ldc 1791868066 (java.lang.Integer)
    if_icmplt L4
    new java/lang/IllegalStateException
    dup
    invokespecial java/lang/IllegalStateException <init>:()V
    athrow
L9
    new java/lang/StringBuilder
    dup
    invokespecial java/lang/StringBuilder <init>:()V
    ldc "ed.l(" (java.lang.String)
    invokevirtual java/lang/StringBuilder append:(Ljava/lang/String;)Ljava/lang/StringBuilder;
    ldc 41 (java.lang.Integer)
    invokevirtual java/lang/StringBuilder append:(C)Ljava/lang/StringBuilder;
    invokevirtual java/lang/StringBuilder toString:()Ljava/lang/String;
    invokestatic k a:(Ljava/lang/Throwable;Ljava/lang/String;)Lee;
    athrow
