eg cg ([Lfb;IIIIIIIII)VL1
    iload 2
    iload 3
    iload 4
    iload 5
    invokestatic bt cw:(IIII)V
    goto L2
L3
    aload 28
    iload 25
    iload 23
    iadd
    iload 24
    iload 26
    iadd
    sipush 128
    invokevirtual bh y:(III)V
    goto L4
L5
    iconst_0
    istore 10
L6
    iload 10
    aload 0
    arraylength
    if_icmpge L7
    iload 9
    ldc 963070818 (java.lang.Integer)
    if_icmpgt L8
    new java/lang/IllegalStateException
    dup
    invokespecial java/lang/IllegalStateException <init>:()V
    athrow
L8
    aload 0
    iload 10
    aaload
    astore 11
    goto L9
L10
    iload 17
    iload 19
    if_icmplt L11
    goto L12
L13
    aload 20
    iload 13
    iload 21
    iload 25
    imul
    iadd
    iload 22
    iload 26
    imul
    iload 14
    iadd
    invokevirtual bh h:(II)V
    goto L14
L15
    iload 1
    aload 11
    getfield fb n:I
    ldc 737715635 (java.lang.Integer)
    imul
    if_icmpeq L16
    iload 9
    ldc 963070818 (java.lang.Integer)
    if_icmpgt L17
    return
L17
    ldc -1412584499 (java.lang.Integer)
    iload 1
    if_icmpne L18
    aload 11
    getstatic client jc:Lfb;
    if_acmpeq L16
    iload 9
    ldc 963070818 (java.lang.Integer)
    if_icmpgt L19
    new java/lang/IllegalStateException
    dup
    invokespecial java/lang/IllegalStateException <init>:()V
    athrow
L19
    goto L18
L16
    iload 8
    iconst_m1
    if_icmpne L20
L21
    getstatic client lv:[I
    getstatic client lp:I
    ldc 1502806549 (java.lang.Integer)
    imul
    aload 11
    getfield fb z:I
    ldc -1286163637 (java.lang.Integer)
    imul
    iload 6
    iadd
    iastore
    goto L22
L23
    getstatic ep r:I
    ldc -1616406211 (java.lang.Integer)
    imul
    ldc 1714086451 (java.lang.Integer)
    getstatic client ge:I
    imul
    isub
    istore 26
    goto L24
L25
    getstatic client ll:[I
    getstatic client lp:I
    ldc 1502806549 (java.lang.Integer)
    imul
    ldc -606292603 (java.lang.Integer)
    aload 11
    getfield fb b:I
    imul
    iastore
    goto L26
L27
    iconst_0
    istore 20
    goto L28
L29
    iload 20
    ifeq L30
    iload 9
    ldc 963070818 (java.lang.Integer)
    if_icmpgt L31
    new java/lang/IllegalStateException
    dup
    invokespecial java/lang/IllegalStateException <init>:()V
    athrow
L18
    iinc 10 1
    goto L6
L32
    aload 11
    iload 12
    ldc -105270637 (java.lang.Integer)
    imul
    putfield fb dq:I
    goto L33
L34
    aload 23
    invokevirtual java/lang/String length:()I
    ifle L35
    iload 9
    ldc 963070818 (java.lang.Integer)
    if_icmpgt L36
    new java/lang/IllegalStateException
    dup
    invokespecial java/lang/IllegalStateException <init>:()V
    athrow
L37
    aload 11
    getfield fb o:Z
    ifeq L38
    iload 9
    ldc 963070818 (java.lang.Integer)
    if_icmpgt L39
    new java/lang/IllegalStateException
    dup
    invokespecial java/lang/IllegalStateException <init>:()V
    athrow
L39
    aload 11
    ldc -1586922294 (java.lang.Integer)
    invokestatic ar dt:(Lfb;I)Z
    ifeq L38
    iload 9
    ldc 963070818 (java.lang.Integer)
    if_icmpgt L40
    new java/lang/IllegalStateException
    dup
    invokespecial java/lang/IllegalStateException <init>:()V
    athrow
L41
    aload 11
    iload 20
    ldc -2093032845 (java.lang.Integer)
    invokevirtual fb h:(II)Lbh;
    astore 25
    goto L42
L43
    aload 11
    ldc 440722930 (java.lang.Integer)
    putfield fb aa:I
    goto L44
L45
    aload 11
    getfield fb t:I
    ldc 937329469 (java.lang.Integer)
    imul
    istore 13
    goto L46
L47
    iinc 21 7
    goto L48
L49
    iconst_m1
    getstatic client ow:I
    ldc 1332636255 (java.lang.Integer)
    imul
    if_icmpne L50
    iload 9
    ldc 963070818 (java.lang.Integer)
    if_icmpgt L51
    new java/lang/IllegalStateException
    dup
    invokespecial java/lang/IllegalStateException <init>:()V
    athrow
L52
    goto L53
L54
    aload 11
    getfield fb ay:I
    ldc -450830685 (java.lang.Integer)
    imul
    putstatic client ov:I
    goto L50
L55
    getstatic hg hv:Ll;
    ldc 314116324 (java.lang.Integer)
    invokevirtual l a:(I)Lcy;
    astore 22
    goto L56
L57
    aload 11
    ldc -495505331 (java.lang.Integer)
    getstatic client ow:I
    imul
    putfield fb av:I
    goto L53
L58
    aload 11
    ldc 560269009 (java.lang.Integer)
    getstatic client ov:I
    imul
    putfield fb av:I
L59
    goto L53
L60
    sipush 325
    iload 13
    if_icmpne L61
L62
    ldc 1332636255 (java.lang.Integer)
    getstatic client ow:I
    imul
    iconst_m1
    if_icmpne L63
    iload 9
    ldc 963070818 (java.lang.Integer)
    if_icmpgt L64
    new java/lang/IllegalStateException
    dup
    invokespecial java/lang/IllegalStateException <init>:()V
    athrow
L64
    aload 11
    getfield fb av:I
    ldc 764905605 (java.lang.Integer)
    imul
    putstatic client ow:I
L65
    ldc -450830685 (java.lang.Integer)
    aload 11
    getfield fb ay:I
    imul
    putstatic client ov:I
    goto L63
L66
    ldc 891461123 (java.lang.Integer)
    aload 11
    getfield fb x:I
    imul
    ineg
    goto L67
L68
    aload 11
    ldc 560269009 (java.lang.Integer)
    getstatic client ov:I
    imul
    putfield fb av:I
    goto L53
L69
    aload 11
    getstatic client ow:I
    ldc -495505331 (java.lang.Integer)
    imul
    putfield fb av:I
    goto L70
L71
    iconst_m1
    goto L72
L61
    iload 13
    sipush 327
    if_icmpne L73
    iload 9
    ldc 963070818 (java.lang.Integer)
    if_icmpgt L43
    new java/lang/IllegalStateException
    dup
    invokespecial java/lang/IllegalStateException <init>:()V
    athrow
L74
    iload 22
    goto L75
L44
    aload 11
    ldc -117546507 (java.lang.Integer)
    getstatic client b:I
    imul
    i2d
    ldc 40.0 (java.lang.Double)
    ddiv
    invokestatic java/lang/Math sin:(D)D
    ldc 256.0 (java.lang.Double)
    dmul
    d2i
    sipush 2047
    iand
    ldc 1003527573 (java.lang.Integer)
    imul
    putfield fb bl:I
    goto L76
L77
    aload 20
    getfield bh i:I
    istore 22
    goto L78
L79
    aload 11
    iconst_0
    putfield fb aq:I
    goto L52
L80
    aload 11
    iconst_0
    putfield fb k:I
    goto L81
L82
    aload 11
    getfield fb k:I
    ldc -884306721 (java.lang.Integer)
    imul
    aload 11
    getfield fb ap:I
    ldc -820348081 (java.lang.Integer)
    imul
    ldc 891461123 (java.lang.Integer)
    aload 11
    getfield fb x:I
    imul
    isub
    if_icmple L83
    iload 9
    ldc 963070818 (java.lang.Integer)
    if_icmpgt L84
    new java/lang/IllegalStateException
    dup
    invokespecial java/lang/IllegalStateException <init>:()V
    athrow
L85
    iload 28
    iconst_m1
    if_icmpeq L86
    iload 9
    ldc 963070818 (java.lang.Integer)
    if_icmpgt L87
    new java/lang/IllegalStateException
    dup
    invokespecial java/lang/IllegalStateException <init>:()V
    athrow
L88
    aload 11
    ldc -117546507 (java.lang.Integer)
    getstatic client b:I
    imul
    i2d
    ldc 40.0 (java.lang.Double)
    ddiv
    invokestatic java/lang/Math sin:(D)D
    ldc 256.0 (java.lang.Double)
    dmul
    d2i
    sipush 2047
    iand
    ldc 1003527573 (java.lang.Integer)
    imul
    putfield fb bl:I
    goto L89
L90
    ldc 943913619 (java.lang.Integer)
    getstatic client if:I
    imul
    ldc -112317673 (java.lang.Integer)
    getstatic client io:I
    imul
    if_icmpne L35
    iload 9
    ldc 963070818 (java.lang.Integer)
    if_icmpgt L91
    new java/lang/IllegalStateException
    dup
    invokespecial java/lang/IllegalStateException <init>:()V
    athrow
L92
    aload 11
    ldc -1071127361 (java.lang.Integer)
    putfield fb aq:I
L53
    ldc -1286163637 (java.lang.Integer)
    aload 11
    getfield fb z:I
    imul
    iload 6
    iadd
    istore 13
L93
    iload 7
    ldc 1649028313 (java.lang.Integer)
    aload 11
    getfield fb q:I
    imul
    iadd
    istore 14
L94
    aload 11
    getfield fb ae:I
    ldc -1240641721 (java.lang.Integer)
    imul
    istore 15
L95
    getstatic client jc:Lfb;
    aload 11
    if_acmpne L96
    iload 9
    ldc 963070818 (java.lang.Integer)
    if_icmpgt L97
    return
L91
    iconst_0
    istore 20
    goto L98
L97
    iload 1
    ldc -1412584499 (java.lang.Integer)
    if_icmpeq L99
    iload 9
    ldc 963070818 (java.lang.Integer)
    if_icmpgt L100
    new java/lang/IllegalStateException
    dup
    invokespecial java/lang/IllegalStateException <init>:()V
    athrow
L101
    bipush 32
    iload 24
    iadd
    iload 3
    if_icmple L102
    iload 9
    ldc 963070818 (java.lang.Integer)
    if_icmpgt L103
    new java/lang/IllegalStateException
    dup
    invokespecial java/lang/IllegalStateException <init>:()V
    athrow
L104
    iload 6
    ldc 1529008151 (java.lang.Integer)
    imul
    putstatic ae kq:I
L105
    iload 7
    ldc -1169696881 (java.lang.Integer)
    imul
    putstatic dz kx:I
    goto L106
L107
    iload 23
    iload 21
    if_icmpge L108
    goto L109
L99
    getstatic client kg:Z
    ifeq L110
    iload 9
    ldc 963070818 (java.lang.Integer)
    if_icmpgt L111
    new java/lang/IllegalStateException
    dup
    invokespecial java/lang/IllegalStateException <init>:()V
    athrow
L111
    getstatic client jl:Z
    ifeq L110
L112
    getstatic ep i:I
    ldc -1976433391 (java.lang.Integer)
    imul
    istore 16
    goto L113
L114
    iload 3
    goto L115
L116
    iload 16
    getstatic client jx:I
    ldc 1113726955 (java.lang.Integer)
    imul
    isub
    istore 16
L117
    iload 17
    getstatic client jb:I
    ldc -227164249 (java.lang.Integer)
    imul
    isub
    istore 17
    goto L118
L119
    aload 11
    ldc 183036705 (java.lang.Integer)
    invokevirtual fb o:(I)Lhh;
    astore 20
    goto L120
L121
    ldc 1439179611 (java.lang.Integer)
    getstatic client jr:I
    imul
    istore 16
L122
    iload 16
    ldc -606292603 (java.lang.Integer)
    aload 11
    getfield fb b:I
    imul
    iadd
    ldc -606292603 (java.lang.Integer)
    getstatic client jm:Lfb;
    getfield fb b:I
    imul
    getstatic client jr:I
    ldc 1439179611 (java.lang.Integer)
    imul
    iadd
    if_icmple L123
    iload 9
    ldc 963070818 (java.lang.Integer)
    if_icmpgt L124
    new java/lang/IllegalStateException
    dup
    invokespecial java/lang/IllegalStateException <init>:()V
    athrow
L125
    aload 20
    iload 21
    iconst_2
    idiv
    iload 21
    iload 25
    imul
    iload 13
    iadd
    iadd
    iload 14
    iload 22
    iload 26
    imul
    iadd
    iload 22
    iconst_2
    idiv
    iadd
    aload 11
    getfield fb ag:I
    ldc -2062124619 (java.lang.Integer)
    imul
    sipush 4096
    invokevirtual bh v:(IIII)V
    goto L14
L123
    iload 17
    ldc -646172201 (java.lang.Integer)
    getstatic client jq:I
    imul
    if_icmpge L126
    iload 9
    ldc 963070818 (java.lang.Integer)
    if_icmpgt L127
    return
L127
    ldc -646172201 (java.lang.Integer)
    getstatic client jq:I
    imul
    istore 17
    goto L126
L128
    goto L18
L40
    goto L18
L129
    getstatic fb g:Z
    ifeq L18
    iload 9
    ldc 963070818 (java.lang.Integer)
    if_icmpgt L130
    new java/lang/IllegalStateException
    dup
    invokespecial java/lang/IllegalStateException <init>:()V
    athrow
L131
    aload 11
    getfield fb b:I
    ldc -606292603 (java.lang.Integer)
    imul
    iload 13
    iadd
    iload 14
    aload 11
    getfield fb k:I
    ldc -884306721 (java.lang.Integer)
    imul
    ldc 891461123 (java.lang.Integer)
    aload 11
    getfield fb x:I
    imul
    ldc -820348081 (java.lang.Integer)
    aload 11
    getfield fb ap:I
    imul
    ldc -621588407 (java.lang.Integer)
    invokestatic e ce:(IIIIII)V
    goto L132
L110
    aload 11
    getfield fb bg:Z
    ifne L96
    iload 9
    ldc 963070818 (java.lang.Integer)
    if_icmpgt L133
    new java/lang/IllegalStateException
    dup
    invokespecial java/lang/IllegalStateException <init>:()V
    athrow
L133
    sipush 128
    istore 15
L96
    aload 11
    getfield fb j:I
    ldc -1547422441 (java.lang.Integer)
    imul
    iconst_2
    if_icmpne L134
    iload 9
    ldc 963070818 (java.lang.Integer)
    if_icmpgt L135
    new java/lang/IllegalStateException
    dup
    invokespecial java/lang/IllegalStateException <init>:()V
    athrow
L135
    iload 2
    istore 16
L136
    iload 3
    istore 17
L137
    iload 4
    istore 18
L138
    iload 5
    istore 19
    goto L139
L134
    bipush 9
    aload 11
    getfield fb j:I
    ldc -1547422441 (java.lang.Integer)
    imul
    if_icmpne L140
    iload 9
    ldc 963070818 (java.lang.Integer)
    if_icmpgt L141
    new java/lang/IllegalStateException
    dup
    invokespecial java/lang/IllegalStateException <init>:()V
    athrow
L141
    iload 13
    istore 20
    goto L142
L143
    iload 13
    iload 14
    iload 12
    ldc -798668306 (java.lang.Integer)
    invokestatic f dk:(IIII)V
    goto L144
L145
    ldc 799883374 (java.lang.Integer)
    getstatic client ew:I
    imul
    istore 30
    goto L146
L147
    iload 14
    aload 11
    getfield fb x:I
    ldc 891461123 (java.lang.Integer)
    imul
    iadd
    istore 23
L148
    iload 22
    iload 20
    if_icmpge L107
    iload 9
    ldc 963070818 (java.lang.Integer)
    if_icmpgt L149
    new java/lang/IllegalStateException
    dup
    invokespecial java/lang/IllegalStateException <init>:()V
    athrow
L149
    iload 20
    istore 24
L150
    iload 22
    istore 20
L151
    iload 24
    istore 22
    goto L107
L70
    goto L53
L109
    iload 21
    istore 24
    goto L152
L153
    iconst_0
    ldc -1547422441 (java.lang.Integer)
    aload 11
    getfield fb j:I
    imul
    if_icmpne L154
    goto L155
L156
    iload 24
    istore 23
L108
    iinc 22 1
    goto L157
L158
    goto L159
L160
    iload 20
    iload 2
    if_icmple L161
    iload 9
    ldc 963070818 (java.lang.Integer)
    if_icmpgt L162
    new java/lang/IllegalStateException
    dup
    invokespecial java/lang/IllegalStateException <init>:()V
    athrow
L84
    aload 11
    aload 11
    getfield fb ap:I
    ldc -155947119 (java.lang.Integer)
    imul
    ldc -1570787491 (java.lang.Integer)
    aload 11
    getfield fb x:I
    imul
    isub
    putfield fb k:I
    goto L83
L163
    getstatic fb g:Z
    ifeq L18
    iload 9
    ldc 963070818 (java.lang.Integer)
    if_icmpgt L164
    new java/lang/IllegalStateException
    dup
    invokespecial java/lang/IllegalStateException <init>:()V
    athrow
L165
    iload 13
    iload 14
    aload 11
    getfield fb b:I
    ldc -606292603 (java.lang.Integer)
    imul
    aload 11
    getfield fb x:I
    ldc 891461123 (java.lang.Integer)
    imul
    iload 20
    invokestatic bt cs:(IIIII)V
    goto L18
L166
    iload 21
    iload 3
    if_icmple L114
    iload 9
    ldc 963070818 (java.lang.Integer)
    if_icmpgt L167
    new java/lang/IllegalStateException
    dup
    invokespecial java/lang/IllegalStateException <init>:()V
    athrow
L168
    ldc 891461123 (java.lang.Integer)
    aload 11
    getfield fb x:I
    imul
    iload 14
    iadd
    iload 28
    isub
    istore 35
    goto L169
L167
    iload 21
L115
    istore 17
L170
    iload 22
    iload 4
    if_icmpge L171
    iload 9
    ldc 963070818 (java.lang.Integer)
    if_icmpgt L74
    new java/lang/IllegalStateException
    dup
    invokespecial java/lang/IllegalStateException <init>:()V
    athrow
L63
    getstatic client oy:Lfq;
    getfield fq l:Z
    ifeq L69
    iload 9
    ldc 963070818 (java.lang.Integer)
    if_icmpgt L68
    return
L172
    aload 11
    ldc -1023277750 (java.lang.Integer)
    invokestatic dh cr:(Lfb;I)V
    goto L173
L174
    aload 23
    astore 24
    goto L175
L176
    iload 23
    iload 5
    if_icmpge L177
    iload 9
    ldc 963070818 (java.lang.Integer)
    if_icmpgt L178
    new java/lang/IllegalStateException
    dup
    invokespecial java/lang/IllegalStateException <init>:()V
    athrow
L179
    goto L180
L177
    iload 5
L181
    istore 19
    goto L182
L12
    goto L18
L183
    aload 11
    getfield fb b:I
    ldc -606292603 (java.lang.Integer)
    imul
    bipush 16
    ishl
    iload 22
    idiv
    istore 23
    goto L184
L185
    iload 14
    ldc 891461123 (java.lang.Integer)
    aload 11
    getfield fb x:I
    imul
    iadd
    istore 21
L186
    iload 13
    iload 2
    if_icmple L187
    iload 9
    ldc 963070818 (java.lang.Integer)
    if_icmpgt L188
    new java/lang/IllegalStateException
    dup
    invokespecial java/lang/IllegalStateException <init>:()V
    athrow
L188
    iload 13
    goto L189
L190
    aload 23
    getfield ad j:Ljava/lang/String;
    astore 22
    goto L191
L192
    goto L18
L193
    iload 14
    iload 3
    if_icmple L194
    iload 9
    ldc 963070818 (java.lang.Integer)
    if_icmpgt L195
    new java/lang/IllegalStateException
    dup
    invokespecial java/lang/IllegalStateException <init>:()V
    athrow
L196
    iload 25
    iload 23
    if_icmpge L197
    iload 9
    ldc 963070818 (java.lang.Integer)
    if_icmpgt L198
    new java/lang/IllegalStateException
    dup
    invokespecial java/lang/IllegalStateException <init>:()V
    athrow
L194
    iload 3
L199
    istore 17
L200
    iload 20
    iload 4
    if_icmpge L201
    iload 9
    ldc 963070818 (java.lang.Integer)
    if_icmpgt L202
    new java/lang/IllegalStateException
    dup
    invokespecial java/lang/IllegalStateException <init>:()V
    athrow
L202
    iload 20
    goto L203
L20
    iload 8
    istore 12
    goto L32
L203
    istore 18
    goto L204
L205
    aload 22
    aload 24
    invokevirtual hh c:(Ljava/lang/String;)I
    istore 26
    goto L206
L207
    iconst_0
    istore 25
    goto L208
L209
    aload 11
    getfield fb dv:[I
    iload 21
    iaload
    iconst_1
    isub
    bipush 19
    invokestatic dj e:(IB)Lad;
    astore 24
    goto L210
L211
    istore 19
L139
    aload 11
    getfield fb o:Z
    ifeq L11
    iload 9
    ldc 963070818 (java.lang.Integer)
    if_icmpgt L212
    new java/lang/IllegalStateException
    dup
    invokespecial java/lang/IllegalStateException <init>:()V
    athrow
L212
    iload 16
    iload 18
    if_icmpge L18
    goto L10
L213
    aload 11
    getfield fb b:I
    ldc -606292603 (java.lang.Integer)
    imul
    iflt L214
    iload 9
    ldc 963070818 (java.lang.Integer)
    if_icmpgt L215
    return
L113
    ldc -1616406211 (java.lang.Integer)
    getstatic ep r:I
    imul
    istore 17
    goto L116
L11
    iconst_0
    ldc 937329469 (java.lang.Integer)
    aload 11
    getfield fb t:I
    imul
    if_icmpeq L153
L216
    sipush 1337
    ldc 937329469 (java.lang.Integer)
    aload 11
    getfield fb t:I
    imul
    if_icmpne L217
    iload 9
    ldc 963070818 (java.lang.Integer)
    if_icmpgt L218
    new java/lang/IllegalStateException
    dup
    invokespecial java/lang/IllegalStateException <init>:()V
    athrow
L218
    ldc 1603012051 (java.lang.Integer)
    iload 13
    imul
    putstatic client im:I
L219
    iload 14
    ldc 1831812883 (java.lang.Integer)
    imul
    putstatic client ir:I
L220
    iload 13
    iload 14
    aload 11
    getfield fb b:I
    ldc -606292603 (java.lang.Integer)
    imul
    aload 11
    getfield fb x:I
    ldc 891461123 (java.lang.Integer)
    imul
    ldc -844363041 (java.lang.Integer)
    invokestatic y ay:(IIIII)V
L221
    iload 2
    iload 3
    iload 4
    iload 5
    invokestatic bt cw:(IIII)V
L222
    goto L18
L217
    sipush 1338
    aload 11
    getfield fb t:I
    ldc 937329469 (java.lang.Integer)
    imul
    if_icmpne L153
    goto L143
L48
    iload 13
    ldc -606292603 (java.lang.Integer)
    aload 11
    getfield fb b:I
    imul
    iadd
    iconst_5
    isub
    iload 20
    isub
    istore 25
    goto L223
L144
    iload 2
    iload 3
    iload 4
    iload 5
    invokestatic bt cw:(IIII)V
    goto L192
L224
    iload 23
    iload 4
    if_icmpge L102
    iload 9
    ldc 963070818 (java.lang.Integer)
    if_icmpgt L101
    return
L225
    iload 5
    iload 21
    isub
    istore 26
    goto L226
L155
    aload 11
    getfield fb o:Z
    ifne L227
    iload 9
    ldc 963070818 (java.lang.Integer)
    if_icmpgt L228
    new java/lang/IllegalStateException
    dup
    invokespecial java/lang/IllegalStateException <init>:()V
    athrow
L178
    iload 23
    goto L181
L33
    aload 11
    ldc -545667797 (java.lang.Integer)
    getstatic client b:I
    imul
    putfield fb el:I
    goto L37
L229
    goto L18
L227
    aload 11
    getfield fb o:Z
    ifne L81
    iload 9
    ldc 963070818 (java.lang.Integer)
    if_icmpgt L82
    return
L230
    iload 13
    aload 11
    getfield fb b:I
    ldc -606292603 (java.lang.Integer)
    imul
    iadd
    istore 22
    goto L147
L175
    ldc "" (java.lang.String)
    astore 23
    goto L205
L83
    ldc -884306721 (java.lang.Integer)
    aload 11
    getfield fb k:I
    imul
    ifge L81
    iload 9
    ldc 963070818 (java.lang.Integer)
    if_icmpgt L80
    return
L231
    iload 15
    ifeq L13
    iload 9
    ldc 963070818 (java.lang.Integer)
    if_icmpgt L232
    new java/lang/IllegalStateException
    dup
    invokespecial java/lang/IllegalStateException <init>:()V
    athrow
L233
    iconst_2
    aload 11
    getfield fb j:I
    ldc -1547422441 (java.lang.Integer)
    imul
    if_icmpne L234
    iload 9
    ldc 963070818 (java.lang.Integer)
    if_icmpgt L27
    return
L235
    iinc 20 6
    goto L47
L210
    iconst_1
    ldc -94557995 (java.lang.Integer)
    aload 24
    getfield ad p:I
    imul
    if_icmpeq L236
    iload 9
    ldc 963070818 (java.lang.Integer)
    if_icmpgt L237
    new java/lang/IllegalStateException
    dup
    invokespecial java/lang/IllegalStateException <init>:()V
    athrow
L238
    goto L18
L239
    aconst_null
    aload 20
    if_acmpeq L240
    iload 9
    ldc 963070818 (java.lang.Integer)
    if_icmpgt L241
    new java/lang/IllegalStateException
    dup
    invokespecial java/lang/IllegalStateException <init>:()V
    athrow
L242
    aload 24
    aload 11
    getfield fb de:I
    ldc 1702477405 (java.lang.Integer)
    imul
    ldc -100126598 (java.lang.Integer)
    invokevirtual ad f:(II)Lad;
    astore 24
    goto L243
L240
    iload 2
    iload 3
    iload 4
    iload 5
    invokestatic bt cw:(IIII)V
    goto L244
L245
    iload 17
    istore 14
    goto L110
L154
    getstatic client la:[Z
    iload 12
    baload
    ifne L246
    ldc 1688548609 (java.lang.Integer)
    getstatic client le:I
    imul
    iconst_1
    if_icmpgt L246
    iload 9
    ldc 963070818 (java.lang.Integer)
    if_icmpgt L247
    new java/lang/IllegalStateException
    dup
    invokespecial java/lang/IllegalStateException <init>:()V
    athrow
L247
    goto L18
L118
    iload 16
    ldc 1439179611 (java.lang.Integer)
    getstatic client jr:I
    imul
    if_icmpge L122
    iload 9
    ldc 963070818 (java.lang.Integer)
    if_icmpgt L121
    new java/lang/IllegalStateException
    dup
    invokespecial java/lang/IllegalStateException <init>:()V
    athrow
L241
    aload 20
    getfield c e:I
    ldc -193401837 (java.lang.Integer)
    imul
    iload 16
    iload 17
    iload 18
    iload 19
    iload 13
    iload 14
    iload 12
    ldc 1944229129 (java.lang.Integer)
    invokestatic ew ci:(IIIIIIIII)V
    goto L240
L248
    ldc -820348081 (java.lang.Integer)
    aload 11
    getfield fb ap:I
    imul
    aload 11
    getfield fb x:I
    ldc 891461123 (java.lang.Integer)
    imul
    if_icmple L132
    iload 9
    ldc 963070818 (java.lang.Integer)
    if_icmpgt L131
    new java/lang/IllegalStateException
    dup
    invokespecial java/lang/IllegalStateException <init>:()V
    athrow
L162
    iload 20
    goto L249
L250
    getstatic fq ib:Lfb;
    aload 11
    if_acmpne L251
    goto L252
L26
    getstatic client ln:[I
    ldc 1502806549 (java.lang.Integer)
    getstatic client lp:I
    imul
    ldc 891461123 (java.lang.Integer)
    aload 11
    getfield fb x:I
    imul
    iastore
    goto L253
L228
    aload 11
    ldc -1057723271 (java.lang.Integer)
    invokestatic ar dt:(Lfb;I)Z
    ifeq L227
    iload 9
    ldc 963070818 (java.lang.Integer)
    if_icmpgt L254
    new java/lang/IllegalStateException
    dup
    invokespecial java/lang/IllegalStateException <init>:()V
    athrow
L254
    getstatic fq ib:Lfb;
    aload 11
    if_acmpeq L227
    iload 9
    ldc 963070818 (java.lang.Integer)
    if_icmpgt L229
    new java/lang/IllegalStateException
    dup
    invokespecial java/lang/IllegalStateException <init>:()V
    athrow
L28
    iconst_0
    istore 21
L255
    iload 21
    aload 11
    getfield fb x:I
    ldc 891461123 (java.lang.Integer)
    imul
    if_icmpge L256
    iload 9
    ldc 963070818 (java.lang.Integer)
    if_icmpgt L257
    new java/lang/IllegalStateException
    dup
    invokespecial java/lang/IllegalStateException <init>:()V
    athrow
L67
    istore 21
    goto L258
L259
    iload 22
    ldc -606292603 (java.lang.Integer)
    aload 11
    getfield fb b:I
    imul
    if_icmpge L260
    iload 9
    ldc 963070818 (java.lang.Integer)
    if_icmpgt L261
    new java/lang/IllegalStateException
    dup
    invokespecial java/lang/IllegalStateException <init>:()V
    athrow
L261
    bipush 32
    aload 11
    getfield fb bd:I
    ldc 1440440859 (java.lang.Integer)
    imul
    iadd
    iload 22
    imul
    iload 13
    iadd
    istore 23
L262
    bipush 32
    aload 11
    getfield fb bb:I
    ldc 1346964537 (java.lang.Integer)
    imul
    iadd
    iload 21
    imul
    iload 14
    iadd
    istore 24
    goto L263
L264
    goto L18
L265
    iload 5
    goto L211
L266
    iload 24
    aload 11
    getfield fb bq:[I
    iload 20
    iaload
    iadd
    istore 24
L267
    aload 11
    getfield fb dv:[I
    iload 20
    iaload
    ifle L268
    iload 9
    ldc 963070818 (java.lang.Integer)
    if_icmpgt L207
    new java/lang/IllegalStateException
    dup
    invokespecial java/lang/IllegalStateException <init>:()V
    athrow
L269
    iload 25
    iconst_5
    iload 13
    iadd
    if_icmpge L270
    iload 9
    ldc 963070818 (java.lang.Integer)
    if_icmpgt L271
    new java/lang/IllegalStateException
    dup
    invokespecial java/lang/IllegalStateException <init>:()V
    athrow
L208
    iconst_0
    istore 26
    goto L272
L273
    iconst_m1
    goto L274
L275
    getstatic client jm:Lfb;
    getfield fb x:I
    ldc 891461123 (java.lang.Integer)
    imul
    ldc -646172201 (java.lang.Integer)
    getstatic client jq:I
    imul
    iadd
    ldc 891461123 (java.lang.Integer)
    aload 11
    getfield fb x:I
    imul
    isub
    istore 17
    goto L276
L2
    invokestatic cp e:()V
    goto L5
L277
    iload 26
    iload 24
    if_icmpge L278
    iload 9
    ldc 963070818 (java.lang.Integer)
    if_icmpgt L279
    new java/lang/IllegalStateException
    dup
    invokespecial java/lang/IllegalStateException <init>:()V
    athrow
L280
    aload 11
    aload 11
    ldc 1302390545 (java.lang.Integer)
    invokestatic by cm:(Lfb;I)Z
    bipush 80
    invokevirtual fb g:(ZB)Lbh;
    astore 20
    goto L281
L102
    aload 11
    getstatic c gm:Lfb;
    if_acmpne L282
    iload 20
    getstatic client gu:I
    ldc 596979433 (java.lang.Integer)
    imul
    if_icmpne L282
    iload 9
    ldc 963070818 (java.lang.Integer)
    if_icmpgt L283
    return
L283
    iconst_1
    ldc 1293091945 (java.lang.Integer)
    getstatic client in:I
    imul
    if_icmpne L284
    iload 9
    ldc 963070818 (java.lang.Integer)
    if_icmpgt L285
    return
L285
    iload 20
    getstatic fp iq:I
    ldc -7450759 (java.lang.Integer)
    imul
    if_icmpne L284
    goto L286
L287
    aload 11
    getfield fb o:Z
    ifne L132
    iload 9
    ldc 963070818 (java.lang.Integer)
    if_icmpgt L248
    new java/lang/IllegalStateException
    dup
    invokespecial java/lang/IllegalStateException <init>:()V
    athrow
L288
    iload 27
    aload 11
    getfield fb ds:[I
    iload 20
    iaload
    iconst_2
    iconst_0
    iconst_2
    iconst_0
    ldc -524707279 (java.lang.Integer)
    invokestatic dx g:(IIIIIZI)Lbh;
    astore 28
    goto L289
L284
    iload 27
    aload 11
    getfield fb ds:[I
    iload 20
    iaload
    iconst_1
    ldc 3153952 (java.lang.Integer)
    iconst_2
    iconst_0
    ldc 1847283563 (java.lang.Integer)
    invokestatic dx g:(IIIIIZI)Lbh;
    astore 28
L289
    aload 28
    ifnull L290
    iload 9
    ldc 963070818 (java.lang.Integer)
    if_icmpgt L291
    new java/lang/IllegalStateException
    dup
    invokespecial java/lang/IllegalStateException <init>:()V
    athrow
L291
    getstatic c gm:Lfb;
    aload 11
    if_acmpne L292
    ldc 596979433 (java.lang.Integer)
    getstatic client gu:I
    imul
    iload 20
    if_icmpne L292
    iload 9
    ldc 963070818 (java.lang.Integer)
    if_icmpgt L293
    new java/lang/IllegalStateException
    dup
    invokespecial java/lang/IllegalStateException <init>:()V
    athrow
L294
    aload 11
    getfield fb j:I
    ldc -1547422441 (java.lang.Integer)
    imul
    bipush 8
    if_icmpne L35
    goto L295
L257
    iconst_0
    istore 22
    goto L259
L24
    iload 25
    iconst_5
    if_icmpge L296
    iload 9
    ldc 963070818 (java.lang.Integer)
    if_icmpgt L297
    new java/lang/IllegalStateException
    dup
    invokespecial java/lang/IllegalStateException <init>:()V
    athrow
L297
    iload 25
    bipush -5
    if_icmple L296
    iload 9
    ldc 963070818 (java.lang.Integer)
    if_icmpgt L298
    new java/lang/IllegalStateException
    dup
    invokespecial java/lang/IllegalStateException <init>:()V
    athrow
L298
    iconst_0
    istore 25
L296
    iload 26
    iconst_5
    if_icmpge L299
    iload 9
    ldc 963070818 (java.lang.Integer)
    if_icmpgt L300
    new java/lang/IllegalStateException
    dup
    invokespecial java/lang/IllegalStateException <init>:()V
    athrow
L300
    iload 26
    bipush -5
    if_icmple L299
    iload 9
    ldc 963070818 (java.lang.Integer)
    if_icmpgt L301
    new java/lang/IllegalStateException
    dup
    invokespecial java/lang/IllegalStateException <init>:()V
    athrow
L301
    iconst_0
    istore 26
    goto L299
L191
    aload 22
    ifnonnull L302
    iload 9
    ldc 963070818 (java.lang.Integer)
    if_icmpgt L303
    return
L304
    aload 23
    iconst_4
    iload 28
    iadd
    invokevirtual java/lang/String substring:(I)Ljava/lang/String;
    astore 23
    goto L305
L306
    iconst_0
    istore 26
    goto L3
L307
    iload 21
    goto L211
L4
    iconst_m1
    iload 1
    if_icmpeq L282
    iload 9
    ldc 963070818 (java.lang.Integer)
    if_icmpgt L308
    return
L308
    aload 0
    iload 1
    ldc 65535 (java.lang.Integer)
    iand
    aaload
    astore 29
L309
    iload 26
    iload 24
    iadd
    getstatic bt t:I
    if_icmpge L310
    iload 9
    ldc 963070818 (java.lang.Integer)
    if_icmpgt L311
    new java/lang/IllegalStateException
    dup
    invokespecial java/lang/IllegalStateException <init>:()V
    athrow
L311
    aload 29
    getfield fb k:I
    ldc -884306721 (java.lang.Integer)
    imul
    ifle L310
    iload 9
    ldc 963070818 (java.lang.Integer)
    if_icmpgt L312
    return
L253
    getstatic client lp:I
    ldc 1886633277 (java.lang.Integer)
    iadd
    dup
    putstatic client lp:I
    ldc 1502806549 (java.lang.Integer)
    imul
    iconst_1
    isub
    istore 12
    goto L32
L313
    iload 30
    ldc 799883374 (java.lang.Integer)
    getstatic client ew:I
    imul
    if_icmple L314
    iload 9
    ldc 963070818 (java.lang.Integer)
    if_icmpgt L315
    return
L315
    getstatic client ew:I
    ldc 799883374 (java.lang.Integer)
    imul
    istore 30
    goto L314
L316
    aload 22
    invokevirtual cy w:()V
    goto L317
L81
    aload 0
    aload 11
    getfield fb h:I
    ldc 952871887 (java.lang.Integer)
    imul
    iload 16
    iload 17
    iload 18
    iload 19
    iload 13
    aload 11
    getfield fb p:I
    ldc 1503817007 (java.lang.Integer)
    imul
    isub
    iload 14
    aload 11
    getfield fb k:I
    ldc -884306721 (java.lang.Integer)
    imul
    isub
    iload 12
    ldc 1598525482 (java.lang.Integer)
    invokestatic eg cg:([Lfb;IIIIIIIII)V
    goto L318
L319
    aload 29
    dup
    getfield fb k:I
    ldc -1251725537 (java.lang.Integer)
    iload 30
    imul
    isub
    putfield fb k:I
L320
    getstatic client ge:I
    ldc 322103547 (java.lang.Integer)
    iload 30
    imul
    iadd
    putstatic client ge:I
    goto L321
L318
    aload 11
    getfield fb do:[Lfb;
    ifnull L322
    goto L323
L310
    iload 26
    iload 24
    iadd
    bipush 32
    iadd
    getstatic bt z:I
    if_icmple L324
    iload 9
    ldc 963070818 (java.lang.Integer)
    if_icmpgt L325
    new java/lang/IllegalStateException
    dup
    invokespecial java/lang/IllegalStateException <init>:()V
    athrow
L326
    aconst_null
    astore 22
    goto L327
L328
    iload 29
    iload 30
    iload 31
    invokestatic cp f:(III)V
    goto L329
L249
    istore 16
    goto L166
L330
    aload 11
    getfield fb ao:I
    ldc -1758654591 (java.lang.Integer)
    imul
    istore 20
    goto L250
L146
    iload 30
    ldc -820348081 (java.lang.Integer)
    aload 29
    getfield fb ap:I
    imul
    ldc 891461123 (java.lang.Integer)
    aload 29
    getfield fb x:I
    imul
    isub
    ldc -884306721 (java.lang.Integer)
    aload 29
    getfield fb k:I
    imul
    isub
    if_icmple L331
    iload 9
    ldc 963070818 (java.lang.Integer)
    if_icmpgt L332
    return
L189
    istore 16
    goto L193
L331
    aload 29
    dup
    getfield fb k:I
    ldc -1251725537 (java.lang.Integer)
    iload 30
    imul
    iadd
    putfield fb k:I
L333
    getstatic client ge:I
    ldc 322103547 (java.lang.Integer)
    iload 30
    imul
    isub
    putstatic client ge:I
L334
    aload 29
    ldc -1023277750 (java.lang.Integer)
    invokestatic dh cr:(Lfb;I)V
L324
    goto L282
L292
    getstatic dp gl:Lfb;
    aload 11
    if_acmpne L335
    iload 9
    ldc 963070818 (java.lang.Integer)
    if_icmpgt L336
    new java/lang/IllegalStateException
    dup
    invokespecial java/lang/IllegalStateException <init>:()V
    athrow
L336
    iload 20
    ldc 1726157493 (java.lang.Integer)
    getstatic client gw:I
    imul
    if_icmpne L335
    iload 9
    ldc 963070818 (java.lang.Integer)
    if_icmpgt L337
    new java/lang/IllegalStateException
    dup
    invokespecial java/lang/IllegalStateException <init>:()V
    athrow
L337
    aload 28
    iload 23
    iload 24
    sipush 128
    invokevirtual bh y:(III)V
    goto L282
L335
    aload 28
    iload 23
    iload 24
    invokevirtual bh h:(II)V
    goto L282
L182
    goto L139
L100
    aload 11
    getfield fb bg:Z
    ifne L99
    goto L338
L268
    aload 11
    getfield fb bn:[I
    ifnull L173
    iload 9
    ldc 963070818 (java.lang.Integer)
    if_icmpgt L339
    new java/lang/IllegalStateException
    dup
    invokespecial java/lang/IllegalStateException <init>:()V
    athrow
L339
    iload 20
    bipush 20
    if_icmpge L173
    iload 9
    ldc 963070818 (java.lang.Integer)
    if_icmpgt L41
    new java/lang/IllegalStateException
    dup
    invokespecial java/lang/IllegalStateException <init>:()V
    athrow
L340
    aload 11
    getfield fb au:Z
    ifeq L341
    iload 9
    ldc 963070818 (java.lang.Integer)
    if_icmpgt L342
    new java/lang/IllegalStateException
    dup
    invokespecial java/lang/IllegalStateException <init>:()V
    athrow
L42
    aconst_null
    aload 25
    if_acmpeq L343
    aload 25
    iload 23
    iload 24
    invokevirtual bh h:(II)V
    goto L173
L343
    getstatic fb g:Z
    ifeq L173
    iload 9
    ldc 963070818 (java.lang.Integer)
    if_icmpgt L172
    return
L344
    iload 23
    bipush 32
    iadd
    iload 2
    if_icmple L102
    iload 9
    ldc 963070818 (java.lang.Integer)
    if_icmpgt L224
    new java/lang/IllegalStateException
    dup
    invokespecial java/lang/IllegalStateException <init>:()V
    athrow
L173
    iinc 20 1
    goto L345
L321
    aload 29
    ldc -1023277750 (java.lang.Integer)
    invokestatic dh cr:(Lfb;I)V
    goto L310
L73
    sipush 328
    iload 13
    if_icmpne L53
    iload 9
    ldc 963070818 (java.lang.Integer)
    if_icmpgt L346
    new java/lang/IllegalStateException
    dup
    invokespecial java/lang/IllegalStateException <init>:()V
    athrow
L347
    iload 30
    ldc 799883374 (java.lang.Integer)
    getstatic client ew:I
    imul
    if_icmple L146
    iload 9
    ldc 963070818 (java.lang.Integer)
    if_icmpgt L145
    return
L234
    iconst_3
    ldc -1547422441 (java.lang.Integer)
    aload 11
    getfield fb j:I
    imul
    if_icmpne L348
    goto L349
L350
    iload 21
    aload 22
    getfield hh i:I
    iconst_1
    iadd
    iadd
    istore 21
    goto L179
L351
    aload 11
    getfield fb ai:I
    ldc 765676771 (java.lang.Integer)
    imul
    istore 20
    goto L352
L140
    iload 13
    aload 11
    getfield fb b:I
    ldc -606292603 (java.lang.Integer)
    imul
    iadd
    istore 20
    goto L185
L353
    iconst_0
    aload 11
    getfield fb am:I
    ldc -1729377613 (java.lang.Integer)
    imul
    if_icmpeq L251
    iload 9
    ldc 963070818 (java.lang.Integer)
    if_icmpgt L354
    new java/lang/IllegalStateException
    dup
    invokespecial java/lang/IllegalStateException <init>:()V
    athrow
L354
    aload 11
    getfield fb am:I
    ldc -1729377613 (java.lang.Integer)
    imul
    istore 20
    goto L251
L75
    istore 18
    goto L176
L332
    aload 29
    getfield fb ap:I
    ldc -820348081 (java.lang.Integer)
    imul
    aload 29
    getfield fb x:I
    ldc 891461123 (java.lang.Integer)
    imul
    isub
    aload 29
    getfield fb k:I
    ldc -884306721 (java.lang.Integer)
    imul
    isub
    istore 30
    goto L331
L252
    iconst_0
    aload 11
    getfield fb aw:I
    ldc 870233861 (java.lang.Integer)
    imul
    if_icmpeq L251
    iload 9
    ldc 963070818 (java.lang.Integer)
    if_icmpgt L355
    return
L355
    aload 11
    getfield fb aw:I
    ldc 870233861 (java.lang.Integer)
    imul
    istore 20
L251
    iload 15
    ifne L340
    iload 9
    ldc 963070818 (java.lang.Integer)
    if_icmpgt L356
    new java/lang/IllegalStateException
    dup
    invokespecial java/lang/IllegalStateException <init>:()V
    athrow
L22
    getstatic client lu:[I
    ldc 1502806549 (java.lang.Integer)
    getstatic client lp:I
    imul
    ldc 1649028313 (java.lang.Integer)
    aload 11
    getfield fb q:I
    imul
    iload 7
    iadd
    iastore
    goto L25
L130
    aload 11
    ldc -1023277750 (java.lang.Integer)
    invokestatic dh cr:(Lfb;I)V
    goto L18
L357
    iload 13
    iload 14
    aload 11
    getfield fb b:I
    ldc -606292603 (java.lang.Integer)
    imul
    ldc 891461123 (java.lang.Integer)
    aload 11
    getfield fb x:I
    imul
    iload 20
    invokestatic bt ca:(IIIII)V
    goto L18
L358
    iload 26
    iload 24
    iadd
    bipush 32
    iadd
    getstatic bt z:I
    isub
    ldc 509485067 (java.lang.Integer)
    getstatic client ew:I
    imul
    imul
    iconst_3
    idiv
    istore 30
    goto L347
L342
    iload 13
    iload 14
    aload 11
    getfield fb b:I
    ldc -606292603 (java.lang.Integer)
    imul
    aload 11
    getfield fb x:I
    ldc 891461123 (java.lang.Integer)
    imul
    iload 20
    sipush 256
    iload 15
    sipush 255
    iand
    isub
    invokestatic bt cc:(IIIIII)V
    goto L18
L341
    iload 13
    iload 14
    aload 11
    getfield fb b:I
    ldc -606292603 (java.lang.Integer)
    imul
    ldc 891461123 (java.lang.Integer)
    aload 11
    getfield fb x:I
    imul
    iload 20
    sipush 256
    iload 15
    sipush 255
    iand
    isub
    invokestatic bt dd:(IIIIII)V
L359
    goto L18
L348
    aload 11
    getfield fb j:I
    ldc -1547422441 (java.lang.Integer)
    imul
    iconst_4
    if_icmpne L360
L361
    aload 11
    ldc -1284781438 (java.lang.Integer)
    invokevirtual fb o:(I)Lhh;
    astore 20
L362
    aload 20
    ifnonnull L363
    iload 9
    ldc 963070818 (java.lang.Integer)
    if_icmpgt L163
    new java/lang/IllegalStateException
    dup
    invokespecial java/lang/IllegalStateException <init>:()V
    athrow
L364
    iconst_m1
    goto L365
L164
    aload 11
    ldc -1023277750 (java.lang.Integer)
    invokestatic dh cr:(Lfb;I)V
    goto L18
L363
    aload 11
    getfield fb bc:Ljava/lang/String;
    astore 22
L366
    aload 11
    ldc 1215626450 (java.lang.Integer)
    invokestatic by cm:(Lfb;I)Z
    ifeq L367
    iload 9
    ldc 963070818 (java.lang.Integer)
    if_icmpgt L368
    new java/lang/IllegalStateException
    dup
    invokespecial java/lang/IllegalStateException <init>:()V
    athrow
L368
    ldc 765676771 (java.lang.Integer)
    aload 11
    getfield fb ai:I
    imul
    istore 21
L369
    aload 11
    getstatic fq ib:Lfb;
    if_acmpne L370
    iload 9
    ldc 963070818 (java.lang.Integer)
    if_icmpgt L371
    new java/lang/IllegalStateException
    dup
    invokespecial java/lang/IllegalStateException <init>:()V
    athrow
L371
    aload 11
    getfield fb am:I
    ldc -1729377613 (java.lang.Integer)
    imul
    ifeq L370
    ldc -1729377613 (java.lang.Integer)
    aload 11
    getfield fb am:I
    imul
    istore 21
    goto L370
L372
    iload 26
    istore 20
    goto L350
L373
    aload 11
    getfield fb br:Ljava/lang/String;
    astore 22
    goto L374
L375
    ldc 891461123 (java.lang.Integer)
    aload 11
    getfield fb x:I
    imul
    iload 22
    iconst_1
    isub
    iadd
    iload 22
    idiv
    istore 24
    goto L376
L377
    aload 11
    getstatic fq ib:Lfb;
    if_acmpne L374
    iload 9
    ldc 963070818 (java.lang.Integer)
    if_icmpgt L378
    new java/lang/IllegalStateException
    dup
    invokespecial java/lang/IllegalStateException <init>:()V
    athrow
L378
    aload 11
    getfield fb aw:I
    ldc 870233861 (java.lang.Integer)
    imul
    ifeq L374
    iload 9
    ldc 963070818 (java.lang.Integer)
    if_icmpgt L379
    new java/lang/IllegalStateException
    dup
    invokespecial java/lang/IllegalStateException <init>:()V
    athrow
L379
    ldc 870233861 (java.lang.Integer)
    aload 11
    getfield fb aw:I
    imul
    istore 21
    goto L374
L86
    aload 23
    astore 24
    goto L380
L381
    iconst_m1
    ldc 689007975 (java.lang.Integer)
    aload 11
    getfield fb db:I
    imul
    if_icmpeq L382
    iload 9
    ldc 963070818 (java.lang.Integer)
    if_icmpgt L383
    new java/lang/IllegalStateException
    dup
    invokespecial java/lang/IllegalStateException <init>:()V
    athrow
L384
    iload 33
    iload 35
    iload 36
    iload 29
    iload 31
    iload 32
    aload 11
    getfield fb ao:I
    ldc -1758654591 (java.lang.Integer)
    imul
    invokestatic cp h:(IIIIIII)V
    goto L385
L260
    iinc 21 1
    goto L255
L386
    new java/lang/StringBuilder
    dup
    invokespecial java/lang/StringBuilder <init>:()V
    ldc 16748608 (java.lang.Integer)
    bipush -92
    invokestatic p e:(IB)Ljava/lang/String;
    invokevirtual java/lang/StringBuilder append:(Ljava/lang/String;)Ljava/lang/StringBuilder;
    aload 22
    invokevirtual java/lang/StringBuilder append:(Ljava/lang/String;)Ljava/lang/StringBuilder;
    getstatic a r:Ljava/lang/String;
    invokevirtual java/lang/StringBuilder append:(Ljava/lang/String;)Ljava/lang/StringBuilder;
    ldc " " (java.lang.String)
    invokevirtual java/lang/StringBuilder append:(Ljava/lang/String;)Ljava/lang/StringBuilder;
    bipush 120
    invokevirtual java/lang/StringBuilder append:(C)Ljava/lang/StringBuilder;
    ldc 1702477405 (java.lang.Integer)
    aload 11
    getfield fb de:I
    imul
    iconst_0
    invokestatic do cp:(IB)Ljava/lang/String;
    invokevirtual java/lang/StringBuilder append:(Ljava/lang/String;)Ljava/lang/StringBuilder;
    invokevirtual java/lang/StringBuilder toString:()Ljava/lang/String;
    astore 22
    goto L382
L385
    goto L18
L325
    aload 29
    getfield fb k:I
    ldc -884306721 (java.lang.Integer)
    imul
    ldc -820348081 (java.lang.Integer)
    aload 29
    getfield fb ap:I
    imul
    aload 29
    getfield fb x:I
    ldc 891461123 (java.lang.Integer)
    imul
    isub
    if_icmpge L324
    iload 9
    ldc 963070818 (java.lang.Integer)
    if_icmpgt L358
    new java/lang/IllegalStateException
    dup
    invokespecial java/lang/IllegalStateException <init>:()V
    athrow
L387
    iconst_1
    ldc 1702477405 (java.lang.Integer)
    aload 11
    getfield fb de:I
    imul
    if_icmpeq L382
    iload 9
    ldc 963070818 (java.lang.Integer)
    if_icmpgt L388
    new java/lang/IllegalStateException
    dup
    invokespecial java/lang/IllegalStateException <init>:()V
    athrow
L388
    aload 11
    getfield fb de:I
    ldc 1702477405 (java.lang.Integer)
    imul
    iconst_m1
    if_icmpeq L382
    iload 9
    ldc 963070818 (java.lang.Integer)
    if_icmpgt L386
    return
L35
    aload 11
    getfield fb j:I
    ldc -1547422441 (java.lang.Integer)
    imul
    bipush 9
    if_icmpne L18
    goto L389
L382
    aload 11
    getstatic client jz:Lfb;
    if_acmpne L390
    iload 9
    ldc 963070818 (java.lang.Integer)
    if_icmpgt L391
    return
L391
    aconst_null
    checkcast et
    pop
    getstatic et fu:Ljava/lang/String;
    astore 22
L392
    ldc -1758654591 (java.lang.Integer)
    aload 11
    getfield fb ao:I
    imul
    istore 21
L390
    aload 11
    getfield fb o:Z
    ifne L393
    iload 9
    ldc 963070818 (java.lang.Integer)
    if_icmpgt L394
    return
L394
    aload 22
    aload 11
    bipush 83
    invokestatic cm cd:(Ljava/lang/String;Lfb;B)Ljava/lang/String;
    astore 22
    goto L393
L30
    aload 11
    getfield fb an:I
    ldc -1170991307 (java.lang.Integer)
    imul
    istore 21
    goto L326
L395
    iconst_0
    goto L274
L276
    iload 16
    istore 13
    goto L245
L274
    aload 11
    getfield fb ba:I
    ldc 936296421 (java.lang.Integer)
    imul
    aload 11
    getfield fb bf:I
    ldc 671520387 (java.lang.Integer)
    imul
    ldc 66524405 (java.lang.Integer)
    aload 11
    getfield fb bu:I
    imul
    invokevirtual hh h:(Ljava/lang/String;IIIIIIIII)I
    pop
    goto L238
L299
    getstatic client gp:I
    ldc 1618329025 (java.lang.Integer)
    imul
    iconst_5
    if_icmpge L3
    iload 9
    ldc 963070818 (java.lang.Integer)
    if_icmpgt L396
    new java/lang/IllegalStateException
    dup
    invokespecial java/lang/IllegalStateException <init>:()V
    athrow
L360
    ldc -1547422441 (java.lang.Integer)
    aload 11
    getfield fb j:I
    imul
    iconst_5
    if_icmpne L397
L398
    aload 11
    getfield fb o:Z
    ifne L399
    iload 9
    ldc 963070818 (java.lang.Integer)
    if_icmpgt L280
    return
L263
    iload 20
    bipush 20
    if_icmpge L267
    iload 9
    ldc 963070818 (java.lang.Integer)
    if_icmpgt L400
    new java/lang/IllegalStateException
    dup
    invokespecial java/lang/IllegalStateException <init>:()V
    athrow
L281
    aconst_null
    aload 20
    if_acmpeq L401
    iload 9
    ldc 963070818 (java.lang.Integer)
    if_icmpgt L402
    new java/lang/IllegalStateException
    dup
    invokespecial java/lang/IllegalStateException <init>:()V
    athrow
L402
    aload 20
    iload 13
    iload 14
    invokevirtual bh h:(II)V
    goto L403
L401
    getstatic fb g:Z
    ifeq L403
    iload 9
    ldc 963070818 (java.lang.Integer)
    if_icmpgt L404
    new java/lang/IllegalStateException
    dup
    invokespecial java/lang/IllegalStateException <init>:()V
    athrow
L404
    aload 11
    ldc -1023277750 (java.lang.Integer)
    invokestatic dh cr:(Lfb;I)V
L403
    goto L18
L323
    aload 11
    getfield fb do:[Lfb;
    aload 11
    getfield fb h:I
    ldc 952871887 (java.lang.Integer)
    imul
    iload 16
    iload 17
    iload 18
    iload 19
    iload 13
    ldc 1503817007 (java.lang.Integer)
    aload 11
    getfield fb p:I
    imul
    isub
    iload 14
    ldc -884306721 (java.lang.Integer)
    aload 11
    getfield fb k:I
    imul
    isub
    iload 12
    ldc 1964557913 (java.lang.Integer)
    invokestatic eg cg:([Lfb;IIIIIIIII)V
    goto L322
L405
    ldc 689007975 (java.lang.Integer)
    aload 11
    getfield fb db:I
    imul
    aload 11
    getfield fb de:I
    ldc 1702477405 (java.lang.Integer)
    imul
    aload 11
    getfield fb ah:I
    ldc -1314196849 (java.lang.Integer)
    imul
    aload 11
    getfield fb at:I
    ldc 1297002649 (java.lang.Integer)
    imul
    aload 11
    getfield fb be:I
    ldc 1892090087 (java.lang.Integer)
    imul
    iconst_0
    ldc -26664873 (java.lang.Integer)
    invokestatic dx g:(IIIIIZI)Lbh;
    astore 20
    goto L406
L407
    aload 11
    iconst_0
    bipush 6
    invokevirtual fb g:(ZB)Lbh;
    astore 20
    goto L406
L51
    aload 11
    getfield fb av:I
    ldc 764905605 (java.lang.Integer)
    imul
    putstatic client ow:I
    goto L54
L408
    aload 20
    getfield bh w:I
    istore 21
    goto L77
L409
    iload 23
    ldc -606292603 (java.lang.Integer)
    aload 11
    getfield fb b:I
    imul
    if_icmpge L410
    iload 9
    ldc 963070818 (java.lang.Integer)
    if_icmpgt L411
    new java/lang/IllegalStateException
    dup
    invokespecial java/lang/IllegalStateException <init>:()V
    athrow
L78
    aload 11
    getfield fb aj:Z
    ifeq L412
    iload 9
    ldc 963070818 (java.lang.Integer)
    if_icmpgt L413
    new java/lang/IllegalStateException
    dup
    invokespecial java/lang/IllegalStateException <init>:()V
    athrow
L413
    iload 13
    iload 14
    iload 13
    ldc -606292603 (java.lang.Integer)
    aload 11
    getfield fb b:I
    imul
    iadd
    iload 14
    ldc 891461123 (java.lang.Integer)
    aload 11
    getfield fb x:I
    imul
    iadd
    invokestatic bt cl:(IIII)V
    goto L414
L415
    iconst_1
    iload 23
    ldc -798533739 (java.lang.Integer)
    aload 11
    getfield fb ab:I
    imul
    imul
    iadd
    bipush 17
    ishr
    istore 28
    goto L416
L204
    iload 21
    iload 5
    if_icmpge L265
    iload 9
    ldc 963070818 (java.lang.Integer)
    if_icmpgt L307
    new java/lang/IllegalStateException
    dup
    invokespecial java/lang/IllegalStateException <init>:()V
    athrow
L376
    iconst_0
    istore 25
    goto L196
L417
    iload 22
    aload 11
    getfield fb x:I
    ldc 891461123 (java.lang.Integer)
    imul
    if_icmpge L294
    iload 9
    ldc 963070818 (java.lang.Integer)
    if_icmpgt L418
    return
L198
    iconst_0
    istore 26
    goto L277
L142
    iload 14
    istore 21
    goto L230
L279
    aload 11
    getfield fb ag:I
    ldc -2062124619 (java.lang.Integer)
    imul
    ifeq L231
    iload 9
    ldc 963070818 (java.lang.Integer)
    if_icmpgt L125
    new java/lang/IllegalStateException
    dup
    invokespecial java/lang/IllegalStateException <init>:()V
    athrow
L419
    aload 11
    getfield fb bc:Ljava/lang/String;
    astore 23
    goto L420
L312
    getstatic bt t:I
    iload 24
    isub
    iload 26
    isub
    getstatic client ew:I
    ldc 509485067 (java.lang.Integer)
    imul
    imul
    iconst_3
    idiv
    istore 30
    goto L313
L232
    aload 20
    iload 13
    iload 25
    iload 21
    imul
    iadd
    iload 14
    iload 22
    iload 26
    imul
    iadd
    sipush 256
    iload 15
    sipush 255
    iand
    isub
    invokevirtual bh y:(III)V
    goto L14
L396
    iconst_0
    istore 25
    goto L306
L14
    iinc 26 1
    goto L277
L278
    iinc 25 1
    goto L196
L197
    iload 2
    iload 3
    iload 4
    iload 5
    invokestatic bt cw:(IIII)V
    goto L158
L38
    ldc 937329469 (java.lang.Integer)
    aload 11
    getfield fb t:I
    imul
    ifle L53
    iload 9
    ldc 963070818 (java.lang.Integer)
    if_icmpgt L45
    new java/lang/IllegalStateException
    dup
    invokespecial java/lang/IllegalStateException <init>:()V
    athrow
L412
    ldc -883404800 (java.lang.Integer)
    aload 11
    getfield fb b:I
    imul
    iload 21
    idiv
    istore 23
L421
    ldc -2062124619 (java.lang.Integer)
    aload 11
    getfield fb ag:I
    imul
    ifeq L422
    aload 20
    aload 11
    getfield fb b:I
    ldc -606292603 (java.lang.Integer)
    imul
    iconst_2
    idiv
    iload 13
    iadd
    ldc 891461123 (java.lang.Integer)
    aload 11
    getfield fb x:I
    imul
    iconst_2
    idiv
    iload 14
    iadd
    aload 11
    getfield fb ag:I
    ldc -2062124619 (java.lang.Integer)
    imul
    iload 23
    invokevirtual bh v:(IIII)V
    goto L159
L422
    iconst_0
    iload 15
    if_icmpeq L423
    aload 20
    iload 13
    iload 14
    ldc -606292603 (java.lang.Integer)
    aload 11
    getfield fb b:I
    imul
    ldc 891461123 (java.lang.Integer)
    aload 11
    getfield fb x:I
    imul
    sipush 256
    iload 15
    sipush 255
    iand
    isub
    invokevirtual bh d:(IIIII)V
    goto L159
L423
    aload 11
    getfield fb b:I
    ldc -606292603 (java.lang.Integer)
    imul
    iload 21
    if_icmpne L424
    iload 9
    ldc 963070818 (java.lang.Integer)
    if_icmpgt L425
    return
L425
    ldc 891461123 (java.lang.Integer)
    aload 11
    getfield fb x:I
    imul
    iload 22
    if_icmpeq L426
    iload 9
    ldc 963070818 (java.lang.Integer)
    if_icmpgt L424
    new java/lang/IllegalStateException
    dup
    invokespecial java/lang/IllegalStateException <init>:()V
    athrow
L424
    aload 20
    iload 13
    iload 14
    ldc -606292603 (java.lang.Integer)
    aload 11
    getfield fb b:I
    imul
    aload 11
    getfield fb x:I
    ldc 891461123 (java.lang.Integer)
    imul
    invokevirtual bh j:(IIII)V
    goto L159
L426
    aload 20
    iload 13
    iload 14
    invokevirtual bh h:(II)V
L159
    goto L427
L428
    getstatic fb g:Z
    ifeq L427
    iload 9
    ldc 963070818 (java.lang.Integer)
    if_icmpgt L429
    return
L293
    ldc -1976433391 (java.lang.Integer)
    getstatic ep i:I
    imul
    ldc 902430141 (java.lang.Integer)
    getstatic client ga:I
    imul
    isub
    istore 25
    goto L23
L427
    goto L18
L397
    bipush 6
    aload 11
    getfield fb j:I
    ldc -1547422441 (java.lang.Integer)
    imul
    if_icmpne L430
    iload 9
    ldc 963070818 (java.lang.Integer)
    if_icmpgt L431
    new java/lang/IllegalStateException
    dup
    invokespecial java/lang/IllegalStateException <init>:()V
    athrow
L432
    aload 20
    aload 25
    iload 26
    aload 11
    getfield fb b:I
    ldc -606292603 (java.lang.Integer)
    imul
    iadd
    iconst_1
    isub
    iload 27
    aload 11
    getfield fb ao:I
    ldc -1758654591 (java.lang.Integer)
    imul
    aload 11
    getfield fb bx:Z
    ifeq L71
    iload 9
    ldc 963070818 (java.lang.Integer)
    if_icmpgt L433
    return
L434
    iconst_0
    istore 21
    goto L435
L31
    aload 11
    getfield fb az:I
    ldc -850817991 (java.lang.Integer)
    imul
    istore 21
    goto L326
L124
    ldc -606292603 (java.lang.Integer)
    getstatic client jm:Lfb;
    getfield fb b:I
    imul
    ldc 1439179611 (java.lang.Integer)
    getstatic client jr:I
    imul
    iadd
    aload 11
    getfield fb b:I
    ldc -606292603 (java.lang.Integer)
    imul
    isub
    istore 16
    goto L123
L126
    iload 17
    aload 11
    getfield fb x:I
    ldc 891461123 (java.lang.Integer)
    imul
    iadd
    getstatic client jq:I
    ldc -646172201 (java.lang.Integer)
    imul
    ldc 891461123 (java.lang.Integer)
    getstatic client jm:Lfb;
    getfield fb x:I
    imul
    iadd
    if_icmple L276
    goto L275
L327
    iconst_0
    istore 23
L436
    iconst_m1
    aload 11
    getfield fb db:I
    ldc 689007975 (java.lang.Integer)
    imul
    if_icmpeq L437
    iload 9
    ldc 963070818 (java.lang.Integer)
    if_icmpgt L438
    new java/lang/IllegalStateException
    dup
    invokespecial java/lang/IllegalStateException <init>:()V
    athrow
L438
    aload 11
    getfield fb db:I
    ldc 689007975 (java.lang.Integer)
    imul
    bipush 74
    invokestatic dj e:(IB)Lad;
    astore 24
L439
    aload 24
    ifnull L440
    iload 9
    ldc 963070818 (java.lang.Integer)
    if_icmpgt L242
    new java/lang/IllegalStateException
    dup
    invokespecial java/lang/IllegalStateException <init>:()V
    athrow
L441
    iload 24
    aload 11
    getfield fb ab:I
    ldc -798533739 (java.lang.Integer)
    imul
    imul
    iconst_1
    iadd
    bipush 17
    ishr
    istore 26
    goto L442
L243
    aload 24
    iconst_1
    bipush 99
    invokevirtual ad r:(IB)Lcy;
    astore 22
L443
    aload 22
    ifnull L444
    iload 9
    ldc 963070818 (java.lang.Integer)
    if_icmpgt L316
    return
L237
    iconst_1
    aload 11
    getfield fb ds:[I
    iload 21
    iaload
    if_icmpeq L445
    iload 9
    ldc 963070818 (java.lang.Integer)
    if_icmpgt L236
    new java/lang/IllegalStateException
    dup
    invokespecial java/lang/IllegalStateException <init>:()V
    athrow
L272
    aload 11
    getfield fb dv:[I
    iload 20
    iaload
    iconst_1
    isub
    istore 27
    goto L344
L444
    aload 11
    ldc -1023277750 (java.lang.Integer)
    invokestatic dh cr:(Lfb;I)V
L440
    goto L56
L437
    ldc 799580057 (java.lang.Integer)
    aload 11
    getfield fb ar:I
    imul
    iconst_5
    if_icmpne L446
    iload 9
    ldc 963070818 (java.lang.Integer)
    if_icmpgt L447
    return
L399
    aload 11
    getfield fb db:I
    ldc 689007975 (java.lang.Integer)
    imul
    iconst_m1
    if_icmpeq L407
    iload 9
    ldc 963070818 (java.lang.Integer)
    if_icmpgt L405
    new java/lang/IllegalStateException
    dup
    invokespecial java/lang/IllegalStateException <init>:()V
    athrow
L448
    getstatic client oy:Lfq;
    aconst_null
    iconst_m1
    aconst_null
    iconst_m1
    ldc 1294511246 (java.lang.Integer)
    invokevirtual fq i:(Lah;ILah;II)Lcy;
    astore 22
    goto L56
L152
    iload 23
    istore 21
    goto L156
L446
    iload 21
    iconst_m1
    if_icmpne L449
    iload 9
    ldc 963070818 (java.lang.Integer)
    if_icmpgt L450
    new java/lang/IllegalStateException
    dup
    invokespecial java/lang/IllegalStateException <init>:()V
    athrow
L450
    aload 11
    aconst_null
    iconst_m1
    iload 20
    getstatic hg hv:Ll;
    getfield l a:Lfq;
    ldc -1883395359 (java.lang.Integer)
    invokevirtual fb s:(Lah;IZLfq;I)Lcy;
    astore 22
L451
    aload 22
    ifnonnull L56
    iload 9
    ldc 963070818 (java.lang.Integer)
    if_icmpgt L452
    new java/lang/IllegalStateException
    dup
    invokespecial java/lang/IllegalStateException <init>:()V
    athrow
L103
    iload 24
    iload 5
    if_icmplt L283
    iload 9
    ldc 963070818 (java.lang.Integer)
    if_icmpgt L102
    return
L453
    aload 11
    ldc -1023277750 (java.lang.Integer)
    invokestatic dh cr:(Lfb;I)V
    goto L56
L449
    iload 21
    ldc 152969838 (java.lang.Integer)
    invokestatic cd e:(II)Lah;
    astore 24
L454
    aload 11
    aload 24
    aload 11
    getfield fb dn:I
    ldc 1190026755 (java.lang.Integer)
    imul
    iload 20
    getstatic hg hv:Ll;
    getfield l a:Lfq;
    ldc -2139355530 (java.lang.Integer)
    invokevirtual fb s:(Lah;IZLfq;I)Lcy;
    astore 22
L455
    aconst_null
    aload 22
    if_acmpne L56
    iload 9
    ldc 963070818 (java.lang.Integer)
    if_icmpgt L456
    return
L456
    getstatic fb g:Z
    ifeq L56
    iload 9
    ldc 963070818 (java.lang.Integer)
    if_icmpgt L457
    return
L457
    aload 11
    ldc -1023277750 (java.lang.Integer)
    invokestatic dh cr:(Lfb;I)V
L56
    aload 11
    getfield fb b:I
    ldc -606292603 (java.lang.Integer)
    imul
    iconst_2
    idiv
    iload 13
    iadd
    aload 11
    getfield fb x:I
    ldc 891461123 (java.lang.Integer)
    imul
    iconst_2
    idiv
    iload 14
    iadd
    invokestatic cp c:(II)V
L458
    getstatic cp aw:[I
    aload 11
    getfield fb aa:I
    ldc -1210951069 (java.lang.Integer)
    imul
    iaload
    ldc 901237999 (java.lang.Integer)
    aload 11
    getfield fb bm:I
    imul
    imul
    bipush 16
    ishr
    istore 24
L459
    aload 11
    getfield fb bm:I
    ldc 901237999 (java.lang.Integer)
    imul
    getstatic cp am:[I
    aload 11
    getfield fb aa:I
    ldc -1210951069 (java.lang.Integer)
    imul
    iaload
    imul
    bipush 16
    ishr
    istore 25
L460
    aload 22
    ifnull L461
    iload 9
    ldc 963070818 (java.lang.Integer)
    if_icmpgt L462
    return
L462
    aload 11
    getfield fb o:Z
    ifne L463
    iload 9
    ldc 963070818 (java.lang.Integer)
    if_icmpgt L464
    new java/lang/IllegalStateException
    dup
    invokespecial java/lang/IllegalStateException <init>:()V
    athrow
L464
    aload 22
    iconst_0
    ldc -120011331 (java.lang.Integer)
    aload 11
    getfield fb bl:I
    imul
    iconst_0
    aload 11
    getfield fb aa:I
    ldc -1210951069 (java.lang.Integer)
    imul
    iconst_0
    iload 24
    iload 25
    invokevirtual cy b:(IIIIIII)V
    goto L461
L463
    aload 22
    invokevirtual cy w:()V
L465
    aload 11
    getfield fb bp:Z
    ifeq L466
    iload 9
    ldc 963070818 (java.lang.Integer)
    if_icmpgt L467
    new java/lang/IllegalStateException
    dup
    invokespecial java/lang/IllegalStateException <init>:()V
    athrow
L467
    aload 22
    iconst_0
    aload 11
    getfield fb bl:I
    ldc -120011331 (java.lang.Integer)
    imul
    aload 11
    getfield fb bk:I
    ldc -1689465665 (java.lang.Integer)
    imul
    aload 11
    getfield fb aa:I
    ldc -1210951069 (java.lang.Integer)
    imul
    aload 11
    getfield fb af:I
    ldc -2027432433 (java.lang.Integer)
    imul
    iload 23
    iload 24
    iadd
    aload 11
    getfield fb as:I
    ldc -831063669 (java.lang.Integer)
    imul
    iadd
    iload 25
    aload 11
    getfield fb as:I
    ldc -831063669 (java.lang.Integer)
    imul
    iadd
    aload 11
    getfield fb bm:I
    ldc 901237999 (java.lang.Integer)
    imul
    invokevirtual cy x:(IIIIIIII)V
    goto L461
L46
    sipush 324
    iload 13
    if_icmpne L60
    iload 9
    ldc 963070818 (java.lang.Integer)
    if_icmpgt L49
    new java/lang/IllegalStateException
    dup
    invokespecial java/lang/IllegalStateException <init>:()V
    athrow
L461
    invokestatic cp l:()V
L468
    goto L18
L430
    aload 11
    getfield fb j:I
    ldc -1547422441 (java.lang.Integer)
    imul
    bipush 7
    if_icmpne L294
    iload 9
    ldc 963070818 (java.lang.Integer)
    if_icmpgt L119
    new java/lang/IllegalStateException
    dup
    invokespecial java/lang/IllegalStateException <init>:()V
    athrow
L317
    aload 22
    getfield cy cb:I
    ldc -718238777 (java.lang.Integer)
    imul
    iconst_2
    idiv
    istore 23
    goto L440
L120
    aload 20
    ifnonnull L434
    iload 9
    ldc 963070818 (java.lang.Integer)
    if_icmpgt L129
    new java/lang/IllegalStateException
    dup
    invokespecial java/lang/IllegalStateException <init>:()V
    athrow
L349
    aload 11
    ldc 1525414048 (java.lang.Integer)
    invokestatic by cm:(Lfb;I)Z
    ifeq L330
    iload 9
    ldc 963070818 (java.lang.Integer)
    if_icmpgt L351
    new java/lang/IllegalStateException
    dup
    invokespecial java/lang/IllegalStateException <init>:()V
    athrow
L469
    aload 23
    aload 11
    bipush 47
    invokestatic cm cd:(Ljava/lang/String;Lfb;B)Ljava/lang/String;
    astore 23
    goto L34
L206
    iload 26
    iload 20
    if_icmple L350
    iload 9
    ldc 963070818 (java.lang.Integer)
    if_icmpgt L372
    new java/lang/IllegalStateException
    dup
    invokespecial java/lang/IllegalStateException <init>:()V
    athrow
L435
    iconst_0
    istore 22
    goto L417
L352
    aload 11
    getstatic fq ib:Lfb;
    if_acmpne L251
    iload 9
    ldc 963070818 (java.lang.Integer)
    if_icmpgt L353
    new java/lang/IllegalStateException
    dup
    invokespecial java/lang/IllegalStateException <init>:()V
    athrow
L418
    iconst_0
    istore 23
    goto L409
L201
    iload 4
    goto L203
L411
    aload 11
    getfield fb dv:[I
    iload 21
    iaload
    ifle L470
    goto L209
L244
    invokestatic cp e:()V
    goto L154
L256
    goto L18
L89
    aload 11
    ldc -1354541235 (java.lang.Integer)
    putfield fb ar:I
    goto L92
L236
    new java/lang/StringBuilder
    dup
    invokespecial java/lang/StringBuilder <init>:()V
    ldc 16748608 (java.lang.Integer)
    bipush -16
    invokestatic p e:(IB)Ljava/lang/String;
    invokevirtual java/lang/StringBuilder append:(Ljava/lang/String;)Ljava/lang/StringBuilder;
    aload 24
    getfield ad j:Ljava/lang/String;
    invokevirtual java/lang/StringBuilder append:(Ljava/lang/String;)Ljava/lang/StringBuilder;
    getstatic a r:Ljava/lang/String;
    invokevirtual java/lang/StringBuilder append:(Ljava/lang/String;)Ljava/lang/StringBuilder;
    ldc " " (java.lang.String)
    invokevirtual java/lang/StringBuilder append:(Ljava/lang/String;)Ljava/lang/StringBuilder;
    bipush 120
    invokevirtual java/lang/StringBuilder append:(C)Ljava/lang/StringBuilder;
    aload 11
    getfield fb ds:[I
    iload 21
    iaload
    iconst_0
    invokestatic do cp:(IB)Ljava/lang/String;
    invokevirtual java/lang/StringBuilder append:(Ljava/lang/String;)Ljava/lang/StringBuilder;
    invokevirtual java/lang/StringBuilder toString:()Ljava/lang/String;
    astore 25
    goto L471
L445
    new java/lang/StringBuilder
    dup
    invokespecial java/lang/StringBuilder <init>:()V
    ldc 16748608 (java.lang.Integer)
    bipush -95
    invokestatic p e:(IB)Ljava/lang/String;
    invokevirtual java/lang/StringBuilder append:(Ljava/lang/String;)Ljava/lang/StringBuilder;
    aload 24
    getfield ad j:Ljava/lang/String;
    invokevirtual java/lang/StringBuilder append:(Ljava/lang/String;)Ljava/lang/StringBuilder;
    getstatic a r:Ljava/lang/String;
    invokevirtual java/lang/StringBuilder append:(Ljava/lang/String;)Ljava/lang/StringBuilder;
    invokevirtual java/lang/StringBuilder toString:()Ljava/lang/String;
    astore 25
L471
    aload 11
    getfield fb bd:I
    ldc 1440440859 (java.lang.Integer)
    imul
    bipush 115
    iadd
    iload 23
    imul
    iload 13
    iadd
    istore 26
L472
    iload 22
    bipush 12
    aload 11
    getfield fb bb:I
    ldc 1346964537 (java.lang.Integer)
    imul
    iadd
    imul
    iload 14
    iadd
    istore 27
L473
    ldc 936296421 (java.lang.Integer)
    aload 11
    getfield fb ba:I
    imul
    ifne L474
    aload 20
    aload 25
    iload 26
    iload 27
    aload 11
    getfield fb ao:I
    ldc -1758654591 (java.lang.Integer)
    imul
    aload 11
    getfield fb bx:Z
    ifeq L475
    iload 9
    ldc 963070818 (java.lang.Integer)
    if_icmpgt L476
    new java/lang/IllegalStateException
    dup
    invokespecial java/lang/IllegalStateException <init>:()V
    athrow
L476
    iconst_0
    goto L477
L475
    iconst_m1
L477
    invokevirtual hh f:(Ljava/lang/String;IIII)V
    goto L470
L474
    aload 11
    getfield fb ba:I
    ldc 936296421 (java.lang.Integer)
    imul
    iconst_1
    if_icmpne L432
    iload 9
    ldc 963070818 (java.lang.Integer)
    if_icmpgt L478
    new java/lang/IllegalStateException
    dup
    invokespecial java/lang/IllegalStateException <init>:()V
    athrow
L416
    iload 25
    iload 13
    iadd
    istore 29
    goto L479
L480
    iconst_0
    goto L365
L481
    ldc 891461123 (java.lang.Integer)
    aload 11
    getfield fb x:I
    imul
    goto L67
L365
    invokevirtual hh o:(Ljava/lang/String;IIII)V
    goto L470
L482
    iload 24
    ineg
    istore 24
    goto L483
L433
    iconst_0
    goto L72
L356
    aload 11
    getfield fb au:Z
    ifeq L357
    iload 9
    ldc 963070818 (java.lang.Integer)
    if_icmpgt L165
    return
L72
    invokevirtual hh g:(Ljava/lang/String;IIII)V
L470
    iinc 21 1
L484
    iinc 23 1
    goto L409
L410
    iinc 22 1
    goto L417
L171
    iload 4
    goto L75
L295
    getstatic at iv:Lfb;
    aload 11
    if_acmpne L35
    iload 9
    ldc 963070818 (java.lang.Integer)
    if_icmpgt L90
    new java/lang/IllegalStateException
    dup
    invokespecial java/lang/IllegalStateException <init>:()V
    athrow
L447
    ldc 2059766591 (java.lang.Integer)
    aload 11
    getfield fb aq:I
    imul
    ifne L55
    iload 9
    ldc 963070818 (java.lang.Integer)
    if_icmpgt L448
    new java/lang/IllegalStateException
    dup
    invokespecial java/lang/IllegalStateException <init>:()V
    athrow
L282
    goto L173
L98
    iconst_0
    istore 21
L485
    getstatic gy co:Lhh;
    astore 22
L486
    aload 11
    getfield fb bc:Ljava/lang/String;
    astore 23
L487
    aload 23
    aload 11
    bipush 21
    invokestatic cm cd:(Ljava/lang/String;Lfb;B)Ljava/lang/String;
    astore 23
L180
    aload 23
    invokevirtual java/lang/String length:()I
    ifle L235
    iload 9
    ldc 963070818 (java.lang.Integer)
    if_icmpgt L488
    return
L488
    aload 23
    getstatic a i:Ljava/lang/String;
    invokevirtual java/lang/String indexOf:(Ljava/lang/String;)I
    istore 25
L489
    iload 25
    iconst_m1
    if_icmpeq L174
L490
    aload 23
    iconst_0
    iload 25
    invokevirtual java/lang/String substring:(II)Ljava/lang/String;
    astore 24
L491
    aload 23
    iconst_4
    iload 25
    iadd
    invokevirtual java/lang/String substring:(I)Ljava/lang/String;
    astore 23
    goto L205
L303
    ldc "null" (java.lang.String)
    astore 22
    goto L302
L286
    aload 11
    getfield fb h:I
    ldc 952871887 (java.lang.Integer)
    imul
    ldc 1565981493 (java.lang.Integer)
    getstatic aj ix:I
    imul
    if_icmpne L284
    iload 9
    ldc 963070818 (java.lang.Integer)
    if_icmpgt L288
    new java/lang/IllegalStateException
    dup
    invokespecial java/lang/IllegalStateException <init>:()V
    athrow
L406
    aload 20
    ifnull L428
    iload 9
    ldc 963070818 (java.lang.Integer)
    if_icmpgt L408
    new java/lang/IllegalStateException
    dup
    invokespecial java/lang/IllegalStateException <init>:()V
    athrow
L452
    getstatic fb g:Z
    ifeq L56
    iload 9
    ldc 963070818 (java.lang.Integer)
    if_icmpgt L453
    new java/lang/IllegalStateException
    dup
    invokespecial java/lang/IllegalStateException <init>:()V
    athrow
L431
    aload 11
    ldc 1769155520 (java.lang.Integer)
    invokestatic by cm:(Lfb;I)Z
    istore 20
    goto L29
L302
    iconst_1
    ldc -94557995 (java.lang.Integer)
    aload 23
    getfield ad p:I
    imul
    if_icmpeq L388
    iload 9
    ldc 963070818 (java.lang.Integer)
    if_icmpgt L387
    new java/lang/IllegalStateException
    dup
    invokespecial java/lang/IllegalStateException <init>:()V
    athrow
L246
    iconst_0
    ldc -1547422441 (java.lang.Integer)
    aload 11
    getfield fb j:I
    imul
    if_icmpne L132
    goto L287
L383
    ldc 689007975 (java.lang.Integer)
    aload 11
    getfield fb db:I
    imul
    bipush 31
    invokestatic dj e:(IB)Lad;
    astore 23
    goto L190
L132
    ldc -1547422441 (java.lang.Integer)
    aload 11
    getfield fb j:I
    imul
    iconst_1
    if_icmpne L233
    iload 9
    ldc 963070818 (java.lang.Integer)
    if_icmpgt L128
    new java/lang/IllegalStateException
    dup
    invokespecial java/lang/IllegalStateException <init>:()V
    athrow
L322
    getstatic client jv:Lgf;
    ldc 952871887 (java.lang.Integer)
    aload 11
    getfield fb h:I
    imul
    i2l
    invokevirtual gf e:(J)Lgm;
    checkcast c
    astore 20
    goto L239
L370
    aload 11
    getfield fb br:Ljava/lang/String;
    invokevirtual java/lang/String length:()I
    ifle L374
    goto L373
L9
    aconst_null
    aload 11
    if_acmpne L15
    goto L264
L271
    iload 13
    iconst_5
    iadd
    istore 25
L270
    iload 25
    iload 20
    iadd
    iload 4
    if_icmple L492
    iload 9
    ldc 963070818 (java.lang.Integer)
    if_icmpgt L493
    new java/lang/IllegalStateException
    dup
    invokespecial java/lang/IllegalStateException <init>:()V
    athrow
L157
    iinc 23 1
    goto L160
L492
    iload 26
    iload 21
    iadd
    iload 5
    if_icmple L226
    iload 9
    ldc 963070818 (java.lang.Integer)
    if_icmpgt L225
    new java/lang/IllegalStateException
    dup
    invokespecial java/lang/IllegalStateException <init>:()V
    athrow
L345
    iinc 22 1
    goto L259
L226
    iload 25
    iload 26
    iload 20
    iload 21
    ldc 16777120 (java.lang.Integer)
    invokestatic bt cs:(IIIII)V
L494
    iload 25
    iload 26
    iload 20
    iload 21
    iconst_0
    invokestatic bt ca:(IIIII)V
    goto L419
L338
    aload 0
    putstatic fb ks:[Lfb;
    goto L104
L420
    aload 22
    getfield hh i:I
    iload 26
    iadd
    iconst_2
    iadd
    istore 27
    goto L469
L414
    iload 21
    iconst_1
    isub
    aload 11
    getfield fb b:I
    ldc -606292603 (java.lang.Integer)
    imul
    iadd
    iload 21
    idiv
    istore 23
    goto L375
L493
    iload 4
    iload 20
    isub
    istore 25
    goto L492
L36
    aload 23
    getstatic a i:Ljava/lang/String;
    invokevirtual java/lang/String indexOf:(Ljava/lang/String;)I
    istore 28
    goto L85
L195
    iload 14
    goto L199
L87
    aload 23
    iconst_0
    iload 28
    invokevirtual java/lang/String substring:(II)Ljava/lang/String;
    astore 24
    goto L304
L495
    aload 29
    getfield fb k:I
    ldc -884306721 (java.lang.Integer)
    imul
    istore 30
    goto L319
L314
    iload 30
    aload 29
    getfield fb k:I
    ldc -884306721 (java.lang.Integer)
    imul
    if_icmple L319
    iload 9
    ldc 963070818 (java.lang.Integer)
    if_icmpgt L495
    return
L380
    ldc "" (java.lang.String)
    astore 23
    goto L305
L400
    iload 23
    aload 11
    getfield fb bj:[I
    iload 20
    iaload
    iadd
    istore 23
    goto L266
L496
    iload 27
    iconst_1
    aload 22
    getfield hh i:I
    iadd
    iadd
    istore 27
L497
    goto L34
L466
    aload 22
    iconst_0
    ldc -120011331 (java.lang.Integer)
    aload 11
    getfield fb bl:I
    imul
    aload 11
    getfield fb bk:I
    ldc -1689465665 (java.lang.Integer)
    imul
    aload 11
    getfield fb aa:I
    ldc -1210951069 (java.lang.Integer)
    imul
    aload 11
    getfield fb af:I
    ldc -2027432433 (java.lang.Integer)
    imul
    iload 23
    iload 24
    iadd
    aload 11
    getfield fb as:I
    ldc -831063669 (java.lang.Integer)
    imul
    iadd
    ldc -831063669 (java.lang.Integer)
    aload 11
    getfield fb as:I
    imul
    iload 25
    iadd
    invokevirtual cy b:(IIIIIII)V
    goto L461
L389
    ldc -798533739 (java.lang.Integer)
    aload 11
    getfield fb ab:I
    imul
    iconst_1
    if_icmpne L213
    iload 13
    iload 14
    aload 11
    getfield fb b:I
    ldc -606292603 (java.lang.Integer)
    imul
    iload 13
    iadd
    iload 14
    ldc 891461123 (java.lang.Integer)
    aload 11
    getfield fb x:I
    imul
    iadd
    aload 11
    getfield fb ao:I
    ldc -1758654591 (java.lang.Integer)
    imul
    invokestatic bt dw:(IIIII)V
    goto L18
L305
    aload 22
    aload 24
    iconst_3
    iload 25
    iadd
    iload 27
    iconst_0
    iconst_m1
    invokevirtual hh f:(Ljava/lang/String;IIII)V
    goto L496
L215
    ldc -606292603 (java.lang.Integer)
    aload 11
    getfield fb b:I
    imul
    goto L498
L214
    ldc -606292603 (java.lang.Integer)
    aload 11
    getfield fb b:I
    imul
    ineg
L498
    istore 20
L499
    ldc 891461123 (java.lang.Integer)
    aload 11
    getfield fb x:I
    imul
    iflt L66
    iload 9
    ldc 963070818 (java.lang.Integer)
    if_icmpgt L481
    new java/lang/IllegalStateException
    dup
    invokespecial java/lang/IllegalStateException <init>:()V
    athrow
L367
    ldc -1758654591 (java.lang.Integer)
    aload 11
    getfield fb ao:I
    imul
    istore 21
    goto L377
L290
    aload 11
    ldc -1023277750 (java.lang.Integer)
    invokestatic dh cr:(Lfb;I)V
    goto L282
L106
    goto L18
L258
    iload 20
    istore 22
L500
    iload 22
    iload 21
    if_icmpge L501
    iload 9
    ldc 963070818 (java.lang.Integer)
    if_icmpgt L502
    new java/lang/IllegalStateException
    dup
    invokespecial java/lang/IllegalStateException <init>:()V
    athrow
L502
    iload 21
    istore 22
L501
    iconst_0
    iload 22
    if_icmpne L183
    iload 9
    ldc 963070818 (java.lang.Integer)
    if_icmpgt L503
    new java/lang/IllegalStateException
    dup
    invokespecial java/lang/IllegalStateException <init>:()V
    athrow
L503
    goto L18
L429
    aload 11
    ldc -1023277750 (java.lang.Integer)
    invokestatic dh cr:(Lfb;I)V
    goto L427
L184
    aload 11
    getfield fb x:I
    ldc 891461123 (java.lang.Integer)
    imul
    bipush 16
    ishl
    iload 22
    idiv
    istore 24
L504
    iload 24
    iload 23
    if_icmpgt L482
    iload 9
    ldc 963070818 (java.lang.Integer)
    if_icmpgt L505
    new java/lang/IllegalStateException
    dup
    invokespecial java/lang/IllegalStateException <init>:()V
    athrow
L478
    aload 20
    aload 25
    iload 26
    ldc -606292603 (java.lang.Integer)
    aload 11
    getfield fb b:I
    imul
    iconst_2
    idiv
    iadd
    iload 27
    ldc -1758654591 (java.lang.Integer)
    aload 11
    getfield fb ao:I
    imul
    aload 11
    getfield fb bx:Z
    ifeq L364
    iload 9
    ldc 963070818 (java.lang.Integer)
    if_icmpgt L480
    new java/lang/IllegalStateException
    dup
    invokespecial java/lang/IllegalStateException <init>:()V
    athrow
L50
    getstatic client oy:Lfq;
    getfield fq l:Z
    ifeq L58
    iload 9
    ldc 963070818 (java.lang.Integer)
    if_icmpgt L57
    new java/lang/IllegalStateException
    dup
    invokespecial java/lang/IllegalStateException <init>:()V
    athrow
L483
    iload 24
    ldc -798533739 (java.lang.Integer)
    aload 11
    getfield fb ab:I
    imul
    imul
    bipush 17
    ishr
    istore 25
    goto L441
L223
    iconst_5
    ldc 891461123 (java.lang.Integer)
    aload 11
    getfield fb x:I
    imul
    iload 14
    iadd
    iadd
    istore 26
    goto L269
L442
    ldc -798533739 (java.lang.Integer)
    aload 11
    getfield fb ab:I
    imul
    iload 23
    imul
    bipush 17
    ishr
    istore 27
    goto L415
L161
    iload 2
    goto L249
L187
    iload 2
    goto L189
L479
    iload 13
    iload 26
    isub
    istore 30
L506
    aload 11
    getfield fb b:I
    ldc -606292603 (java.lang.Integer)
    imul
    iload 13
    iadd
    iload 26
    isub
    istore 31
L507
    iload 25
    aload 11
    getfield fb b:I
    ldc -606292603 (java.lang.Integer)
    imul
    iload 13
    iadd
    iadd
    istore 32
L508
    iload 14
    iload 27
    iadd
    istore 33
L509
    iload 14
    iload 28
    isub
    istore 34
    goto L168
L346
    aload 11
    ldc 440722930 (java.lang.Integer)
    putfield fb aa:I
    goto L88
L169
    iload 14
    ldc 891461123 (java.lang.Integer)
    aload 11
    getfield fb x:I
    imul
    iadd
    iload 27
    iadd
    istore 36
    goto L328
L374
    aload 11
    getfield fb o:Z
    ifeq L382
    iload 9
    ldc 963070818 (java.lang.Integer)
    if_icmpgt L381
    new java/lang/IllegalStateException
    dup
    invokespecial java/lang/IllegalStateException <init>:()V
    athrow
L329
    iload 33
    iload 34
    iload 35
    iload 29
    iload 30
    iload 31
    aload 11
    getfield fb ao:I
    ldc -1758654591 (java.lang.Integer)
    imul
    invokestatic cp h:(IIIIIII)V
L510
    iload 29
    iload 31
    iload 32
    invokestatic cp f:(III)V
    goto L384
L76
    aload 11
    ldc -1354541235 (java.lang.Integer)
    putfield fb ar:I
    goto L79
L393
    aload 20
    aload 22
    iload 13
    iload 14
    ldc -606292603 (java.lang.Integer)
    aload 11
    getfield fb b:I
    imul
    ldc 891461123 (java.lang.Integer)
    aload 11
    getfield fb x:I
    imul
    iload 21
    aload 11
    getfield fb bx:Z
    ifeq L273
    iload 9
    ldc 963070818 (java.lang.Integer)
    if_icmpgt L395
    return
L505
    iload 23
    ineg
    istore 23
    goto L483
L7
    return
L511
    new java/lang/StringBuilder
    dup
    invokespecial java/lang/StringBuilder <init>:()V
    ldc "eg.cg(" (java.lang.String)
    invokevirtual java/lang/StringBuilder append:(Ljava/lang/String;)Ljava/lang/StringBuilder;
    ldc 41 (java.lang.Integer)
    invokevirtual java/lang/StringBuilder append:(C)Ljava/lang/StringBuilder;
    invokevirtual java/lang/StringBuilder toString:()Ljava/lang/String;
    invokestatic k a:(Ljava/lang/Throwable;Ljava/lang/String;)Lee;
    athrow
