eo r ([BIII)VL1
    aload 0
    getfield eo c:Z
    ifeq L2
    iload 4
    ldc -642682455 (java.lang.Integer)
    if_icmpne L3
    new java/lang/IllegalStateException
    dup
    invokespecial java/lang/IllegalStateException <init>:()V
    athrow
L3
    return
L2
    aload 0
    getfield eo g:Z
    ifeq L4
    iload 4
    ldc -642682455 (java.lang.Integer)
    if_icmpne L5
    return
L5
    aload 0
    iconst_0
    putfield eo g:Z
L6
    new java/io/IOException
    dup
    invokespecial java/io/IOException <init>:()V
    athrow
L4
    aconst_null
    aload 0
    getfield eo i:[B
    if_acmpne L7
    iload 4
    ldc -642682455 (java.lang.Integer)
    if_icmpne L8
    new java/lang/IllegalStateException
    dup
    invokespecial java/lang/IllegalStateException <init>:()V
    athrow
L8
    aload 0
    sipush 5000
    newarray 8
    putfield eo i:[B
L7
    aload 0
    dup
    astore 5
    monitorenter
L9
    iconst_0
    istore 6
L10
    iload 6
    iload 3
    if_icmpge L11
    iload 4
    ldc -642682455 (java.lang.Integer)
    if_icmpne L12
    return
L12
    aload 0
    getfield eo i:[B
    ldc -2020947283 (java.lang.Integer)
    aload 0
    getfield eo f:I
    imul
    aload 1
    iload 2
    iload 6
    iadd
    baload
    bastore
L13
    aload 0
    aload 0
    getfield eo f:I
    ldc -2020947283 (java.lang.Integer)
    imul
    iconst_1
    iadd
    sipush 5000
    irem
    ldc 1791437093 (java.lang.Integer)
    imul
    putfield eo f:I
L14
    sipush 4900
    aload 0
    getfield eo r:I
    ldc 961801183 (java.lang.Integer)
    imul
    iadd
    sipush 5000
    irem
    ldc -2020947283 (java.lang.Integer)
    aload 0
    getfield eo f:I
    imul
    if_icmpne L15
    iload 4
    ldc -642682455 (java.lang.Integer)
    if_icmpne L16
    new java/lang/IllegalStateException
    dup
    invokespecial java/lang/IllegalStateException <init>:()V
    athrow
L16
    new java/io/IOException
    dup
    invokespecial java/io/IOException <init>:()V
    athrow
L15
    iinc 6 1
    goto L10
L11
    aload 0
    getfield eo w:Lex;
    ifnonnull L17
    iload 4
    ldc -642682455 (java.lang.Integer)
    if_icmpne L18
    new java/lang/IllegalStateException
    dup
    invokespecial java/lang/IllegalStateException <init>:()V
    athrow
L18
    aload 0
    aload 0
    getfield eo u:Ldz;
    aload 0
    iconst_3
    bipush 8
    invokevirtual dz i:(Ljava/lang/Runnable;IB)Lex;
    putfield eo w:Lex;
L17
    aload 0
    invokevirtual java/lang/Object notifyAll:()V
L19
    aload 5
    monitorexit
L20
    goto L21
L22
    astore 7
    aload 5
    monitorexit
L23
    aload 7
    athrow
L21
    return
L24
    new java/lang/StringBuilder
    dup
    invokespecial java/lang/StringBuilder <init>:()V
    ldc "eo.r(" (java.lang.String)
    invokevirtual java/lang/StringBuilder append:(Ljava/lang/String;)Ljava/lang/StringBuilder;
    ldc 41 (java.lang.Integer)
    invokevirtual java/lang/StringBuilder append:(C)Ljava/lang/StringBuilder;
    invokevirtual java/lang/StringBuilder toString:()Ljava/lang/String;
    invokestatic k a:(Ljava/lang/Throwable;Ljava/lang/String;)Lee;
    athrow
