ep ag (Law;S)VL1
    getstatic client mm:I
    ldc 168290855 (java.lang.Integer)
    imul
    ldc 1164900853 (java.lang.Integer)
    getstatic hg hv:Ll;
    getfield l b:I
    imul
    bipush 7
    ishr
    if_icmpne L2
    goto L3
L4
    getstatic aw a:Law;
    aload 0
    if_acmpne L5
    iload 1
    sipush 256
    if_icmpeq L6
    new java/lang/IllegalStateException
    dup
    invokespecial java/lang/IllegalStateException <init>:()V
    athrow
L7
    iconst_0
    putstatic client mm:I
    goto L2
L8
    aload 4
    getfield l b:I
    ldc 1164900853 (java.lang.Integer)
    imul
    bipush 7
    ishr
    istore 6
    goto L9
L10
    aload 0
    getstatic aw e:Law;
    if_acmpeq L11
    iload 1
    sipush 256
    if_icmpeq L12
    new java/lang/IllegalStateException
    dup
    invokespecial java/lang/IllegalStateException <init>:()V
    athrow
L13
    iload 7
    iflt L14
    iload 1
    sipush 256
    if_icmpeq L15
    new java/lang/IllegalStateException
    dup
    invokespecial java/lang/IllegalStateException <init>:()V
    athrow
L11
    iconst_1
    istore 2
    goto L16
L17
    getstatic hg hv:Ll;
    astore 4
    goto L18
L19
    ldc 7317091 (java.lang.Integer)
    getstatic client hd:I
    imul
    bipush 14
    ishl
    istore 5
    goto L20
L21
    getstatic aw e:Law;
    aload 0
    if_acmpne L4
    iload 1
    sipush 256
    if_icmpeq L17
    new java/lang/IllegalStateException
    dup
    invokespecial java/lang/IllegalStateException <init>:()V
    athrow
L3
    getstatic client mz:I
    ldc -482742593 (java.lang.Integer)
    imul
    ldc 109190397 (java.lang.Integer)
    getstatic hg hv:Ll;
    getfield l x:I
    imul
    bipush 7
    ishr
    if_icmpne L2
    iload 1
    sipush 256
    if_icmpeq L7
    new java/lang/IllegalStateException
    dup
    invokespecial java/lang/IllegalStateException <init>:()V
    athrow
L22
    aload 0
    getstatic aw c:Law;
    if_acmpne L20
    iload 1
    sipush 256
    if_icmpeq L23
    new java/lang/IllegalStateException
    dup
    invokespecial java/lang/IllegalStateException <init>:()V
    athrow
L18
    ldc 33538048 (java.lang.Integer)
    istore 5
    goto L20
L6
    getstatic client hg:[Ll;
    getstatic client hd:I
    ldc 7317091 (java.lang.Integer)
    imul
    aaload
    astore 4
    goto L19
L24
    aload 4
    ldc 2056569747 (java.lang.Integer)
    invokevirtual l l:(I)Z
    ifeq L14
    iload 1
    sipush 256
    if_icmpeq L25
    new java/lang/IllegalStateException
    dup
    invokespecial java/lang/IllegalStateException <init>:()V
    athrow
L26
    aconst_null
    aload 4
    getfield l s:Lcy;
    if_acmpeq L27
    iload 1
    sipush 256
    if_icmpeq L28
    new java/lang/IllegalStateException
    dup
    invokespecial java/lang/IllegalStateException <init>:()V
    athrow
L25
    aload 4
    getfield l d:Z
    ifne L14
    iload 1
    sipush 256
    if_icmpeq L29
    new java/lang/IllegalStateException
    dup
    invokespecial java/lang/IllegalStateException <init>:()V
    athrow
L5
    getstatic client hg:[Ll;
    getstatic client hw:[I
    iload 3
    iaload
    aaload
    astore 4
    goto L30
L23
    ldc 7317091 (java.lang.Integer)
    getstatic client hd:I
    imul
    getstatic client hw:[I
    iload 3
    iaload
    if_icmpne L20
    iload 1
    sipush 256
    if_icmpeq L31
    new java/lang/IllegalStateException
    dup
    invokespecial java/lang/IllegalStateException <init>:()V
    athrow
L14
    iinc 3 1
    goto L32
L20
    aconst_null
    aload 4
    if_acmpeq L14
    iload 1
    sipush 256
    if_icmpeq L24
    return
L33
    getstatic client b:I
    ldc -117546507 (java.lang.Integer)
    imul
    aload 4
    getfield l f:I
    ldc -141138323 (java.lang.Integer)
    imul
    if_icmpge L27
    goto L34
L16
    iconst_0
    istore 3
    goto L32
L29
    aload 4
    iconst_0
    putfield l y:Z
L35
    getstatic client h:Z
    ifeq L36
    iload 1
    sipush 256
    if_icmpeq L37
    return
L37
    getstatic client hr:I
    ldc 308668811 (java.lang.Integer)
    imul
    bipush 50
    if_icmpgt L38
    iload 1
    sipush 256
    if_icmpeq L36
    new java/lang/IllegalStateException
    dup
    invokespecial java/lang/IllegalStateException <init>:()V
    athrow
L36
    ldc 308668811 (java.lang.Integer)
    getstatic client hr:I
    imul
    sipush 200
    if_icmple L8
    iload 1
    sipush 256
    if_icmpeq L38
    new java/lang/IllegalStateException
    dup
    invokespecial java/lang/IllegalStateException <init>:()V
    athrow
L38
    aload 0
    getstatic aw e:Law;
    if_acmpeq L8
    iload 1
    sipush 256
    if_icmpeq L39
    new java/lang/IllegalStateException
    dup
    invokespecial java/lang/IllegalStateException <init>:()V
    athrow
L39
    ldc 140905021 (java.lang.Integer)
    aload 4
    getfield l k:I
    imul
    aload 4
    getfield l af:I
    ldc 1931040743 (java.lang.Integer)
    imul
    if_icmpne L8
    iload 1
    sipush 256
    if_icmpeq L40
    new java/lang/IllegalStateException
    dup
    invokespecial java/lang/IllegalStateException <init>:()V
    athrow
L12
    getstatic aw a:Law;
    aload 0
    if_acmpne L16
    iload 1
    sipush 256
    if_icmpeq L11
    return
L15
    iload 7
    bipush 104
    if_icmpge L14
    goto L26
L9
    ldc 109190397 (java.lang.Integer)
    aload 4
    getfield l x:I
    imul
    bipush 7
    ishr
    istore 7
L41
    iload 6
    iflt L14
    iload 6
    bipush 104
    if_icmpge L14
    iload 1
    sipush 256
    if_icmpeq L13
    return
L2
    ldc 308668811 (java.lang.Integer)
    getstatic client hr:I
    imul
    istore 2
    goto L10
L31
    goto L14
L30
    getstatic client hw:[I
    iload 3
    iaload
    bipush 14
    ishl
    istore 5
    goto L22
L28
    ldc -117546507 (java.lang.Integer)
    getstatic client b:I
    imul
    aload 4
    getfield l r:I
    ldc 443285693 (java.lang.Integer)
    imul
    if_icmplt L27
    iload 1
    sipush 256
    if_icmpeq L33
    new java/lang/IllegalStateException
    dup
    invokespecial java/lang/IllegalStateException <init>:()V
    athrow
L40
    aload 4
    iconst_1
    putfield l y:Z
    goto L8
L34
    aload 4
    iconst_0
    putfield l y:Z
L42
    aload 4
    aload 4
    getfield l b:I
    ldc 1164900853 (java.lang.Integer)
    imul
    ldc 109190397 (java.lang.Integer)
    aload 4
    getfield l x:I
    imul
    getstatic fd hz:I
    ldc -837647185 (java.lang.Integer)
    imul
    ldc 1958062732 (java.lang.Integer)
    invokestatic cl ar:(IIII)I
    ldc -560429671 (java.lang.Integer)
    imul
    putfield l i:I
L43
    getstatic n ds:Lcb;
    getstatic fd hz:I
    ldc -837647185 (java.lang.Integer)
    imul
    aload 4
    getfield l b:I
    ldc 1164900853 (java.lang.Integer)
    imul
    ldc 109190397 (java.lang.Integer)
    aload 4
    getfield l x:I
    imul
    aload 4
    getfield l i:I
    ldc 1947401897 (java.lang.Integer)
    imul
    bipush 60
    aload 4
    aload 4
    getfield l n:I
    ldc 1741660775 (java.lang.Integer)
    imul
    iload 5
    aload 4
    getfield l j:I
    ldc 12306763 (java.lang.Integer)
    imul
    ldc -324895949 (java.lang.Integer)
    aload 4
    getfield l m:I
    imul
    ldc -1675451685 (java.lang.Integer)
    aload 4
    getfield l t:I
    imul
    ldc 266241953 (java.lang.Integer)
    aload 4
    getfield l z:I
    imul
    invokevirtual cb s:(IIIIILch;IIIIII)Z
    pop
    goto L14
L27
    bipush 64
    aload 4
    getfield l b:I
    ldc 1164900853 (java.lang.Integer)
    imul
    bipush 127
    iand
    if_icmpne L44
    iload 1
    sipush 256
    if_icmpeq L45
    new java/lang/IllegalStateException
    dup
    invokespecial java/lang/IllegalStateException <init>:()V
    athrow
L45
    bipush 64
    ldc 109190397 (java.lang.Integer)
    aload 4
    getfield l x:I
    imul
    bipush 127
    iand
    if_icmpne L44
    iload 1
    sipush 256
    if_icmpeq L46
    new java/lang/IllegalStateException
    dup
    invokespecial java/lang/IllegalStateException <init>:()V
    athrow
L46
    ldc 1549434003 (java.lang.Integer)
    getstatic client gn:I
    imul
    getstatic client go:[[I
    iload 6
    aaload
    iload 7
    iaload
    if_icmpne L47
    iload 1
    sipush 256
    if_icmpeq L48
    new java/lang/IllegalStateException
    dup
    invokespecial java/lang/IllegalStateException <init>:()V
    athrow
L48
    goto L14
L47
    getstatic client go:[[I
    iload 6
    aaload
    iload 7
    getstatic client gn:I
    ldc 1549434003 (java.lang.Integer)
    imul
    iastore
L44
    aload 4
    aload 4
    getfield l b:I
    ldc 1164900853 (java.lang.Integer)
    imul
    ldc 109190397 (java.lang.Integer)
    aload 4
    getfield l x:I
    imul
    getstatic fd hz:I
    ldc -837647185 (java.lang.Integer)
    imul
    ldc 1958062732 (java.lang.Integer)
    invokestatic cl ar:(IIII)I
    ldc -560429671 (java.lang.Integer)
    imul
    putfield l i:I
L49
    getstatic n ds:Lcb;
    ldc -837647185 (java.lang.Integer)
    getstatic fd hz:I
    imul
    aload 4
    getfield l b:I
    ldc 1164900853 (java.lang.Integer)
    imul
    aload 4
    getfield l x:I
    ldc 109190397 (java.lang.Integer)
    imul
    aload 4
    getfield l i:I
    ldc 1947401897 (java.lang.Integer)
    imul
    bipush 60
    aload 4
    aload 4
    getfield l n:I
    ldc 1741660775 (java.lang.Integer)
    imul
    iload 5
    aload 4
    getfield l v:Z
    invokevirtual cb h:(IIIIILch;IIZ)Z
    pop
    goto L14
L32
    iload 3
    iload 2
    if_icmpge L50
    iload 1
    sipush 256
    if_icmpeq L21
    return
L50
    return
L51
    new java/lang/StringBuilder
    dup
    invokespecial java/lang/StringBuilder <init>:()V
    ldc "ep.ag(" (java.lang.String)
    invokevirtual java/lang/StringBuilder append:(Ljava/lang/String;)Ljava/lang/StringBuilder;
    ldc 41 (java.lang.Integer)
    invokevirtual java/lang/StringBuilder append:(C)Ljava/lang/StringBuilder;
    invokevirtual java/lang/StringBuilder toString:()Ljava/lang/String;
    invokestatic k a:(Ljava/lang/Throwable;Ljava/lang/String;)Lee;
    athrow
