er a (Ldh;B)VL1
    aload 1
    bipush 6
    bipush -103
    invokevirtual dh e:(IB)V
    goto L2
L3
    aload 1
    aload 0
    getfield er bl:I
    ldc 530558957 (java.lang.Integer)
    imul
    ldc 2127624183 (java.lang.Integer)
    invokevirtual dh c:(II)V
    goto L4
L5
    aload 1
    ldc -1023959087 (java.lang.Integer)
    aload 0
    getfield er ag:I
    imul
    bipush 106
    invokevirtual dh e:(IB)V
    goto L6
L7
    aload 1
    aload 0
    getfield er az:I
    ldc -600658801 (java.lang.Integer)
    imul
    bipush 75
    invokevirtual dh e:(IB)V
    goto L8
L9
    aload 1
    aload 0
    getfield er al:Ljava/lang/String;
    ldc 546499967 (java.lang.Integer)
    invokevirtual dh f:(Ljava/lang/String;I)V
    goto L10
L11
    bipush -11
    invokevirtual dh e:(IB)V
L12
    aload 1
    ldc -712239995 (java.lang.Integer)
    aload 0
    getfield er p:I
    imul
    iconst_2
    invokevirtual dh e:(IB)V
L13
    aload 1
    aload 0
    getfield er aw:I
    ldc 148647573 (java.lang.Integer)
    imul
    bipush -18
    invokevirtual dh e:(IB)V
L14
    aload 1
    aload 0
    getfield er am:I
    ldc 2066481605 (java.lang.Integer)
    imul
    bipush 33
    invokevirtual dh e:(IB)V
    goto L15
L16
    aload 1
    aload 0
    getfield er ac:I
    ldc -953069457 (java.lang.Integer)
    imul
    bipush 71
    invokevirtual dh a:(IB)V
    goto L17
L18
    iconst_0
    goto L19
L20
    aload 1
    aload 0
    getfield er ab:Z
    ifeq L18
    iload 2
    bipush 16
    if_icmpgt L21
    new java/lang/IllegalStateException
    dup
    invokespecial java/lang/IllegalStateException <init>:()V
    athrow
L21
    iconst_1
    goto L19
L22
    aload 1
    aload 0
    getfield er i:Z
    ifeq L23
    iload 2
    bipush 16
    if_icmpgt L24
    new java/lang/IllegalStateException
    dup
    invokespecial java/lang/IllegalStateException <init>:()V
    athrow
L19
    bipush -31
    invokevirtual dh e:(IB)V
L25
    aload 1
    ldc -1927546491 (java.lang.Integer)
    aload 0
    getfield er av:I
    imul
    bipush -45
    invokevirtual dh a:(IB)V
    goto L5
L26
    aload 1
    aload 0
    getfield er ae:I
    ldc 58875385 (java.lang.Integer)
    imul
    bipush -13
    invokevirtual dh e:(IB)V
    goto L20
L6
    aload 1
    ldc -354574075 (java.lang.Integer)
    aload 0
    getfield er ah:I
    imul
    bipush 66
    invokevirtual dh l:(IB)V
L27
    aload 1
    aload 0
    getfield er at:I
    ldc 1571281021 (java.lang.Integer)
    imul
    bipush -28
    invokevirtual dh a:(IB)V
    goto L9
L15
    aload 1
    ldc 2013251665 (java.lang.Integer)
    aload 0
    getfield er au:I
    imul
    bipush 6
    invokevirtual dh e:(IB)V
    goto L26
L10
    aload 1
    aload 0
    getfield er ak:Ljava/lang/String;
    ldc 546499967 (java.lang.Integer)
    invokevirtual dh f:(Ljava/lang/String;I)V
L28
    aload 1
    aload 0
    getfield er ar:Ljava/lang/String;
    ldc 546499967 (java.lang.Integer)
    invokevirtual dh f:(Ljava/lang/String;I)V
L29
    aload 1
    aload 0
    getfield er aq:Ljava/lang/String;
    ldc 546499967 (java.lang.Integer)
    invokevirtual dh f:(Ljava/lang/String;I)V
L30
    aload 1
    aload 0
    getfield er ad:I
    ldc -1667491077 (java.lang.Integer)
    imul
    bipush 52
    invokevirtual dh e:(IB)V
    goto L16
L24
    iconst_1
    goto L11
L17
    aload 1
    aload 0
    getfield er af:Ljava/lang/String;
    ldc 546499967 (java.lang.Integer)
    invokevirtual dh f:(Ljava/lang/String;I)V
    goto L31
L23
    iconst_0
    goto L11
L32
    aload 1
    aload 0
    getfield er an:I
    ldc 1857119129 (java.lang.Integer)
    imul
    bipush 71
    invokevirtual dh e:(IB)V
    goto L7
L2
    aload 1
    ldc -1067602671 (java.lang.Integer)
    aload 0
    getfield er w:I
    imul
    bipush -41
    invokevirtual dh e:(IB)V
    goto L22
L8
    iconst_0
    istore 3
L33
    iload 3
    aload 0
    getfield er aa:[I
    arraylength
    if_icmpge L3
    iload 2
    bipush 16
    if_icmpgt L34
    new java/lang/IllegalStateException
    dup
    invokespecial java/lang/IllegalStateException <init>:()V
    athrow
L34
    aload 1
    aload 0
    getfield er aa:[I
    iload 3
    iaload
    ldc 1023792483 (java.lang.Integer)
    invokevirtual dh c:(II)V
    iinc 3 1
    goto L33
L31
    aload 1
    aload 0
    getfield er as:Ljava/lang/String;
    ldc 546499967 (java.lang.Integer)
    invokevirtual dh f:(Ljava/lang/String;I)V
    goto L32
L4
    return
L35
    new java/lang/StringBuilder
    dup
    invokespecial java/lang/StringBuilder <init>:()V
    ldc "er.a(" (java.lang.String)
    invokevirtual java/lang/StringBuilder append:(Ljava/lang/String;)Ljava/lang/StringBuilder;
    ldc 41 (java.lang.Integer)
    invokevirtual java/lang/StringBuilder append:(C)Ljava/lang/StringBuilder;
    invokevirtual java/lang/StringBuilder toString:()Ljava/lang/String;
    invokestatic k a:(Ljava/lang/Throwable;Ljava/lang/String;)Lee;
    athrow
