eu f (III)IL1
    ldc 45365 (java.lang.Integer)
    iload 0
    iadd
    iload 1
    ldc 91923 (java.lang.Integer)
    iadd
    iconst_4
    bipush 67
    invokestatic l g:(IIIB)I
    sipush 128
    isub
    iload 0
    sipush 10294
    iadd
    iload 1
    ldc 37821 (java.lang.Integer)
    iadd
    iconst_2
    bipush -82
    invokestatic l g:(IIIB)I
    sipush 128
    isub
    iconst_1
    ishr
    iadd
    iload 0
    iload 1
    iconst_1
    bipush -3
    invokestatic l g:(IIIB)I
    sipush 128
    isub
    iconst_2
    ishr
    iadd
    istore 3
    goto L2
L3
    bipush 60
    istore 3
    goto L4
L5
    bipush 10
    istore 3
    goto L4
L6
    iload 3
    bipush 10
    if_icmpge L7
    iload 2
    ldc -1789935039 (java.lang.Integer)
    if_icmpeq L5
    new java/lang/IllegalStateException
    dup
    invokespecial java/lang/IllegalStateException <init>:()V
    athrow
L7
    iload 3
    bipush 60
    if_icmple L4
    iload 2
    ldc -1789935039 (java.lang.Integer)
    if_icmpeq L3
    new java/lang/IllegalStateException
    dup
    invokespecial java/lang/IllegalStateException <init>:()V
    athrow
L4
    iload 3
    ireturn
L2
    bipush 35
    ldc 0.3 (java.lang.Double)
    iload 3
    i2d
    dmul
    d2i
    iadd
    istore 3
    goto L6
L8
    new java/lang/StringBuilder
    dup
    invokespecial java/lang/StringBuilder <init>:()V
    ldc "eu.f(" (java.lang.String)
    invokevirtual java/lang/StringBuilder append:(Ljava/lang/String;)Ljava/lang/StringBuilder;
    ldc 41 (java.lang.Integer)
    invokevirtual java/lang/StringBuilder append:(C)Ljava/lang/StringBuilder;
    invokevirtual java/lang/StringBuilder toString:()Ljava/lang/String;
    invokestatic k a:(Ljava/lang/Throwable;Ljava/lang/String;)Lee;
    athrow
