ew op (IIII)VL1
    getstatic ew pq:Lew;
    ifnull L2
    iload 4
    ldc 1456490041 (java.lang.Integer)
    if_icmplt L3
    new java/lang/IllegalStateException
    dup
    invokespecial java/lang/IllegalStateException <init>:()V
    athrow
L3
    getstatic ew pw:I
    ldc 1336584277 (java.lang.Integer)
    iadd
    putstatic ew pw:I
L4
    getstatic ew pw:I
    ldc 929895677 (java.lang.Integer)
    imul
    iconst_3
    if_icmplt L5
    iload 4
    ldc 1456490041 (java.lang.Integer)
    if_icmplt L6
    return
L6
    aload 0
    ldc "alreadyloaded" (java.lang.String)
    ldc 1840508976 (java.lang.Integer)
    invokevirtual ew pf:(Ljava/lang/String;I)V
L7
    return
L5
    aload 0
    invokevirtual ew getAppletContext:()Ljava/applet/AppletContext;
    aload 0
    invokevirtual ew getDocumentBase:()Ljava/net/URL;
    ldc "_self" (java.lang.String)
    invokeinterface java/applet/AppletContext showDocument:(Ljava/net/URL;Ljava/lang/String;)V
L8
    return
L2
    aload 0
    putstatic ew pq:Lew;
L9
    iload 1
    ldc -2027302147 (java.lang.Integer)
    imul
    putstatic i pu:I
L10
    iload 2
    ldc 777195837 (java.lang.Integer)
    imul
    putstatic m pv:I
L11
    ldc 1060582365 (java.lang.Integer)
    iload 3
    imul
    putstatic ee l:I
L12
    aload 0
    putstatic ee e:Ljava/applet/Applet;
L13
    getstatic ag pb:Ldz;
    ifnonnull L14
    iload 4
    ldc 1456490041 (java.lang.Integer)
    if_icmplt L15
    new java/lang/IllegalStateException
    dup
    invokespecial java/lang/IllegalStateException <init>:()V
    athrow
L15
    new dz
    dup
    invokespecial dz <init>:()V
    putstatic ag pb:Ldz;
L14
    getstatic ag pb:Ldz;
    aload 0
    iconst_1
    bipush 8
    invokevirtual dz i:(Ljava/lang/Runnable;IB)Lex;
    pop
L16
    goto L17
L18
    astore 5
L19
    aconst_null
    aload 5
    ldc 65499401 (java.lang.Integer)
    invokestatic di e:(Ljava/lang/String;Ljava/lang/Throwable;I)V
L20
    aload 0
    ldc "crash" (java.lang.String)
    ldc 1115004599 (java.lang.Integer)
    invokevirtual ew pf:(Ljava/lang/String;I)V
L17
    return
L21
    new java/lang/StringBuilder
    dup
    invokespecial java/lang/StringBuilder <init>:()V
    ldc "ew.op(" (java.lang.String)
    invokevirtual java/lang/StringBuilder append:(Ljava/lang/String;)Ljava/lang/StringBuilder;
    ldc 41 (java.lang.Integer)
    invokevirtual java/lang/StringBuilder append:(C)Ljava/lang/StringBuilder;
    invokevirtual java/lang/StringBuilder toString:()Ljava/lang/String;
    invokestatic k a:(Ljava/lang/Throwable;Ljava/lang/String;)Lee;
    athrow
