ey l (III)IL1
    iload 2
    i2l
    ldc 1000000 (java.lang.Long)
    lmul
    lstore 4
    goto L2
L3
    iload 10
    ireturn
L4
    lload 6
    lload 4
    lcmp
    ifge L5
    iload 3
    ldc 1028546156 (java.lang.Integer)
    if_icmpgt L6
    new java/lang/IllegalStateException
    dup
    invokespecial java/lang/IllegalStateException <init>:()V
    athrow
L2
    aload 0
    getfield ey e:J
    ldc 2872021560689741841 (java.lang.Long)
    lmul
    invokestatic java/lang/System nanoTime:()J
    lsub
    lstore 6
    goto L4
L5
    lload 6
    ldc 1000000 (java.lang.Long)
    ldiv
    invokestatic ak e:(J)V
    goto L7
L8
    aload 0
    getfield ey e:J
    ldc 2872021560689741841 (java.lang.Long)
    lmul
    lload 8
    lcmp
    ifge L3
    iload 3
    ldc 1028546156 (java.lang.Integer)
    if_icmpgt L9
    new java/lang/IllegalStateException
    dup
    invokespecial java/lang/IllegalStateException <init>:()V
    athrow
L10
    iconst_0
    istore 10
    goto L11
L12
    iinc 10 1
    goto L13
L14
    iload 10
    iconst_1
    if_icmplt L12
    iload 3
    ldc 1028546156 (java.lang.Integer)
    if_icmpgt L15
    new java/lang/IllegalStateException
    dup
    invokespecial java/lang/IllegalStateException <init>:()V
    athrow
L15
    ldc 2872021560689741841 (java.lang.Long)
    aload 0
    getfield ey e:J
    lmul
    lload 8
    lcmp
    ifge L8
    iload 3
    ldc 1028546156 (java.lang.Integer)
    if_icmpgt L12
    new java/lang/IllegalStateException
    dup
    invokespecial java/lang/IllegalStateException <init>:()V
    athrow
L11
    iload 10
    bipush 10
    if_icmpge L8
    goto L14
L7
    invokestatic java/lang/System nanoTime:()J
    lstore 8
    goto L10
L13
    aload 0
    dup
    getfield ey e:J
    ldc -6237538773477532096 (java.lang.Long)
    iload 1
    i2l
    lmul
    ladd
    putfield ey e:J
    goto L11
L9
    aload 0
    lload 8
    ldc -20186975555411727 (java.lang.Long)
    lmul
    putfield ey e:J
    goto L3
L6
    lload 4
    lstore 6
    goto L5
L16
    new java/lang/StringBuilder
    dup
    invokespecial java/lang/StringBuilder <init>:()V
    ldc "ey.l(" (java.lang.String)
    invokevirtual java/lang/StringBuilder append:(Ljava/lang/String;)Ljava/lang/StringBuilder;
    ldc 41 (java.lang.Integer)
    invokevirtual java/lang/StringBuilder append:(C)Ljava/lang/StringBuilder;
    invokevirtual java/lang/StringBuilder toString:()Ljava/lang/String;
    invokestatic k a:(Ljava/lang/Throwable;Ljava/lang/String;)Lee;
    athrow
