f c (Lfv;III)Lbh;L1
    aload 0
    iload 1
    iload 2
    ldc -310979579 (java.lang.Integer)
    invokestatic ax h:(Lfv;III)Z
    ifne L2
    iload 3
    ldc 1603044905 (java.lang.Integer)
    if_icmpgt L3
    new java/lang/IllegalStateException
    dup
    invokespecial java/lang/IllegalStateException <init>:()V
    athrow
L3
    aconst_null
    areturn
L4
    iconst_0
    istore 8
    goto L5
L6
    aload 5
    getstatic hg c:[I
    iconst_0
    iaload
    putfield bh c:I
    goto L7
L2
    new bh
    dup
    invokespecial bh <init>:()V
    astore 5
    goto L8
L9
    aload 5
    iload 6
    newarray 10
    putfield bh e:[I
    goto L4
L7
    aload 5
    getstatic eb u:[I
    iconst_0
    iaload
    putfield bh u:I
L10
    aload 5
    getstatic by w:[I
    iconst_0
    iaload
    putfield bh a:I
L11
    aload 5
    getstatic by i:[I
    iconst_0
    iaload
    putfield bh l:I
    goto L12
L8
    aload 5
    getstatic by a:I
    ldc 2133846989 (java.lang.Integer)
    imul
    putfield bh w:I
    goto L13
L14
    getstatic ar f:[[B
    iconst_0
    aaload
    astore 7
    goto L9
L15
    aload 4
    areturn
L5
    iload 8
    iload 6
    if_icmpge L16
    iload 3
    ldc 1603044905 (java.lang.Integer)
    if_icmpgt L17
    new java/lang/IllegalStateException
    dup
    invokespecial java/lang/IllegalStateException <init>:()V
    athrow
L13
    aload 5
    getstatic by l:I
    ldc 494779715 (java.lang.Integer)
    imul
    putfield bh i:I
    goto L6
L17
    aload 5
    getfield bh e:[I
    iload 8
    getstatic cq r:[I
    aload 7
    iload 8
    baload
    sipush 255
    iand
    iaload
    iastore
    iinc 8 1
    goto L5
L16
    ldc 139753401 (java.lang.Integer)
    invokestatic au j:(I)V
L18
    aload 5
    astore 4
    goto L15
L12
    aload 5
    getfield bh l:I
    aload 5
    getfield bh a:I
    imul
    istore 6
    goto L14
L19
    new java/lang/StringBuilder
    dup
    invokespecial java/lang/StringBuilder <init>:()V
    ldc "f.c(" (java.lang.String)
    invokevirtual java/lang/StringBuilder append:(Ljava/lang/String;)Ljava/lang/StringBuilder;
    ldc 41 (java.lang.Integer)
    invokevirtual java/lang/StringBuilder append:(C)Ljava/lang/StringBuilder;
    invokevirtual java/lang/StringBuilder toString:()Ljava/lang/String;
    invokestatic k a:(Ljava/lang/Throwable;Ljava/lang/String;)Lee;
    athrow
