f dk (IIII)VL1
    ldc -1913414931 (java.lang.Integer)
    invokestatic cw n:(I)V
    goto L2
L3
    iconst_1
    istore 13
    goto L4
L2
    iload 0
    iload 1
    iload 0
    getstatic q ez:Lbs;
    getfield bs l:I
    iadd
    getstatic q ez:Lbs;
    getfield bs c:I
    iload 1
    iadd
    invokestatic bt cw:(IIII)V
    goto L5
L6
    iconst_5
    ldc 1217278719 (java.lang.Integer)
    getstatic client mx:I
    imul
    if_icmpeq L7
    iload 3
    ldc -1141317100 (java.lang.Integer)
    if_icmpne L8
    new java/lang/IllegalStateException
    dup
    invokespecial java/lang/IllegalStateException <init>:()V
    athrow
L8
    getstatic client el:I
    ldc 1158077643 (java.lang.Integer)
    imul
    ldc 154136385 (java.lang.Integer)
    getstatic client fy:I
    imul
    iadd
    sipush 2047
    iand
    istore 4
L9
    ldc 1164900853 (java.lang.Integer)
    getstatic hg hv:Ll;
    getfield l b:I
    imul
    bipush 32
    idiv
    bipush 48
    iadd
    istore 5
    goto L10
L11
    iload 7
    ldc 308668811 (java.lang.Integer)
    getstatic client hr:I
    imul
    if_icmpge L12
    iload 3
    ldc -1141317100 (java.lang.Integer)
    if_icmpne L13
    new java/lang/IllegalStateException
    dup
    invokespecial java/lang/IllegalStateException <init>:()V
    athrow
L14
    getstatic al my:Lbh;
    bipush 25
    iload 0
    iadd
    iconst_5
    iload 1
    iadd
    sipush 146
    sipush 151
    iload 5
    iload 6
    iload 4
    sipush 256
    ldc -981441773 (java.lang.Integer)
    getstatic client ec:I
    imul
    iadd
    getstatic j eb:[I
    getstatic cg eq:[I
    invokevirtual bh x:(IIIIIIII[I[I)V
L15
    iconst_0
    istore 7
    goto L16
L17
    getstatic client au:I
    ldc 72113091 (java.lang.Integer)
    imul
    getstatic client hg:[Ll;
    arraylength
    if_icmpge L18
    iload 3
    ldc -1141317100 (java.lang.Integer)
    if_icmpne L19
    return
L20
    iconst_2
    iconst_4
    getstatic client mb:[I
    iload 7
    iaload
    imul
    iadd
    getstatic hg hv:Ll;
    getfield l b:I
    ldc 1164900853 (java.lang.Integer)
    imul
    bipush 32
    idiv
    isub
    istore 8
L21
    iconst_2
    iconst_4
    getstatic client me:[I
    iload 7
    iaload
    imul
    iadd
    getstatic hg hv:Ll;
    getfield l x:I
    ldc 109190397 (java.lang.Integer)
    imul
    bipush 32
    idiv
    isub
    istore 9
    goto L22
L23
    getstatic client la:[Z
    iload 2
    baload
    ifeq L24
    iload 3
    ldc -1141317100 (java.lang.Integer)
    if_icmpne L25
    new java/lang/IllegalStateException
    dup
    invokespecial java/lang/IllegalStateException <init>:()V
    athrow
L26
    iinc 7 1
    goto L16
L27
    iconst_0
    istore 7
L28
    iload 7
    bipush 104
    if_icmpge L29
    iload 3
    ldc -1141317100 (java.lang.Integer)
    if_icmpne L30
    new java/lang/IllegalStateException
    dup
    invokespecial java/lang/IllegalStateException <init>:()V
    athrow
L31
    getstatic ds eh:Lbh;
    iload 0
    iload 1
    bipush 33
    bipush 33
    bipush 25
    bipush 25
    getstatic client fy:I
    ldc 154136385 (java.lang.Integer)
    imul
    sipush 256
    getstatic gp er:[I
    getstatic cs ev:[I
    invokevirtual bh x:(IIIIIIII[I[I)V
    goto L23
L32
    iload 8
    bipush 104
    if_icmpge L33
    iload 3
    ldc -1141317100 (java.lang.Integer)
    if_icmpne L34
    new java/lang/IllegalStateException
    dup
    invokespecial java/lang/IllegalStateException <init>:()V
    athrow
L35
    iinc 7 1
    goto L36
L13
    getstatic client hg:[Ll;
    getstatic client hw:[I
    iload 7
    iaload
    aaload
    astore 8
    goto L37
L38
    goto L39
L40
    iload 8
    iconst_4
    imul
    iconst_2
    iadd
    ldc 109190397 (java.lang.Integer)
    getstatic hg hv:Ll;
    getfield l x:I
    imul
    bipush 32
    idiv
    isub
    istore 11
L41
    iload 0
    iload 1
    iload 10
    iload 11
    getstatic o ed:[Lbh;
    iconst_0
    aaload
    ldc 1204133672 (java.lang.Integer)
    invokestatic fj dp:(IIIILbh;I)V
L42
    iinc 8 1
    goto L32
L37
    aload 8
    ifnull L43
    iload 3
    ldc -1141317100 (java.lang.Integer)
    if_icmpne L44
    new java/lang/IllegalStateException
    dup
    invokespecial java/lang/IllegalStateException <init>:()V
    athrow
L29
    iconst_0
    istore 7
L36
    iload 7
    getstatic client ch:I
    ldc -1048248787 (java.lang.Integer)
    imul
    if_icmpge L45
    iload 3
    ldc -1141317100 (java.lang.Integer)
    if_icmpne L46
    return
L22
    iload 0
    iload 1
    iload 8
    iload 9
    getstatic client mg:[Lbh;
    iload 7
    aaload
    ldc 1204133672 (java.lang.Integer)
    invokestatic fj dp:(IIIILbh;I)V
    goto L26
L47
    aload 8
    ifnull L35
    goto L48
L49
    return
L50
    aload 8
    getfield am e:Lay;
    astore 9
    goto L51
L5
    getstatic client mx:I
    ldc 1217278719 (java.lang.Integer)
    imul
    iconst_2
    if_icmpeq L7
    iload 3
    ldc -1141317100 (java.lang.Integer)
    if_icmpne L6
    new java/lang/IllegalStateException
    dup
    invokespecial java/lang/IllegalStateException <init>:()V
    athrow
L52
    aload 9
    getfield ay aw:[I
    ifnull L53
    iload 3
    ldc -1141317100 (java.lang.Integer)
    if_icmpne L54
    return
L55
    iconst_2
    iconst_4
    iload 7
    imul
    iadd
    ldc 1164900853 (java.lang.Integer)
    getstatic hg hv:Ll;
    getfield l b:I
    imul
    bipush 32
    idiv
    isub
    istore 10
    goto L40
L53
    aconst_null
    aload 9
    if_acmpeq L35
    iload 3
    ldc -1141317100 (java.lang.Integer)
    if_icmpne L56
    return
L56
    aload 9
    getfield ay x:Z
    ifeq L35
    goto L57
L58
    aload 8
    getfield am x:I
    ldc 109190397 (java.lang.Integer)
    imul
    bipush 32
    idiv
    ldc 109190397 (java.lang.Integer)
    getstatic hg hv:Ll;
    getfield l x:I
    imul
    bipush 32
    idiv
    isub
    istore 11
    goto L59
L60
    ldc 1164900853 (java.lang.Integer)
    aload 8
    getfield am b:I
    imul
    bipush 32
    idiv
    ldc 1164900853 (java.lang.Integer)
    getstatic hg hv:Ll;
    getfield l b:I
    imul
    bipush 32
    idiv
    isub
    istore 10
    goto L58
L61
    iload 0
    iload 1
    iload 9
    iload 10
    getstatic o ed:[Lbh;
    iconst_3
    aaload
    ldc 1204133672 (java.lang.Integer)
    invokestatic fj dp:(IIIILbh;I)V
    goto L43
L59
    iload 0
    iload 1
    iload 10
    iload 11
    getstatic o ed:[Lbh;
    iconst_1
    aaload
    ldc 1204133672 (java.lang.Integer)
    invokestatic fj dp:(IIIILbh;I)V
    goto L35
L10
    sipush 464
    ldc 109190397 (java.lang.Integer)
    getstatic hg hv:Ll;
    getfield l x:I
    imul
    bipush 32
    idiv
    isub
    istore 6
    goto L14
L45
    iconst_0
    istore 7
    goto L11
L62
    iload 12
    ifeq L63
    goto L64
L65
    iconst_1
    getstatic client aw:I
    ldc 577949343 (java.lang.Integer)
    imul
    if_icmpne L66
    goto L67
L18
    ldc 168290855 (java.lang.Integer)
    getstatic client mm:I
    imul
    ifeq L68
    iload 3
    ldc -1141317100 (java.lang.Integer)
    if_icmpne L69
    new java/lang/IllegalStateException
    dup
    invokespecial java/lang/IllegalStateException <init>:()V
    athrow
L44
    aload 8
    ldc 2142734435 (java.lang.Integer)
    invokevirtual l l:(I)Z
    ifeq L43
    iload 3
    ldc -1141317100 (java.lang.Integer)
    if_icmpne L70
    new java/lang/IllegalStateException
    dup
    invokespecial java/lang/IllegalStateException <init>:()V
    athrow
L70
    aload 8
    getfield l d:Z
    ifne L43
    iload 3
    ldc -1141317100 (java.lang.Integer)
    if_icmpne L71
    return
L71
    ldc 1164900853 (java.lang.Integer)
    aload 8
    getfield l b:I
    imul
    bipush 32
    idiv
    getstatic hg hv:Ll;
    getfield l b:I
    ldc 1164900853 (java.lang.Integer)
    imul
    bipush 32
    idiv
    isub
    istore 9
L72
    ldc 109190397 (java.lang.Integer)
    aload 8
    getfield l x:I
    imul
    bipush 32
    idiv
    ldc 109190397 (java.lang.Integer)
    getstatic hg hv:Ll;
    getfield l x:I
    imul
    bipush 32
    idiv
    isub
    istore 10
L73
    iconst_0
    istore 11
L74
    aload 8
    getfield l e:Ljava/lang/String;
    iconst_1
    ldc -1018513197 (java.lang.Integer)
    invokestatic w dc:(Ljava/lang/String;ZI)Z
    ifeq L75
    iconst_1
    istore 11
L75
    iconst_0
    istore 12
L76
    iconst_0
    istore 13
    goto L77
L78
    aload 7
    getfield l b:I
    ldc 1164900853 (java.lang.Integer)
    imul
    bipush 32
    idiv
    getstatic hg hv:Ll;
    getfield l b:I
    ldc 1164900853 (java.lang.Integer)
    imul
    bipush 32
    idiv
    isub
    istore 8
    goto L79
L33
    iinc 7 1
    goto L28
L80
    iconst_1
    istore 12
    goto L38
L48
    aload 8
    ldc 1793528260 (java.lang.Integer)
    invokevirtual am l:(I)Z
    ifeq L35
    iload 3
    ldc -1141317100 (java.lang.Integer)
    if_icmpne L50
    new java/lang/IllegalStateException
    dup
    invokespecial java/lang/IllegalStateException <init>:()V
    athrow
L81
    iinc 13 1
    goto L77
L82
    iconst_4
    iload 0
    bipush 93
    iadd
    iadd
    iload 1
    bipush 82
    iadd
    iconst_4
    isub
    iconst_3
    iconst_3
    ldc 16777215 (java.lang.Integer)
    invokestatic bt cs:(IIIII)V
    goto L83
L84
    iconst_0
    getstatic hg hv:Ll;
    getfield l q:I
    ldc 1593175097 (java.lang.Integer)
    imul
    if_icmpeq L4
    iload 3
    ldc -1141317100 (java.lang.Integer)
    if_icmpne L85
    new java/lang/IllegalStateException
    dup
    invokespecial java/lang/IllegalStateException <init>:()V
    athrow
L85
    aload 8
    getfield l q:I
    ldc 1593175097 (java.lang.Integer)
    imul
    ifeq L4
    goto L86
L54
    aload 9
    ldc -1465295093 (java.lang.Integer)
    invokevirtual ay i:(I)Lay;
    astore 9
    goto L53
L87
    iload 0
    iload 1
    iload 7
    iload 8
    getstatic ao ef:[Lbh;
    iconst_0
    aaload
    ldc 1204133672 (java.lang.Integer)
    invokestatic fj dp:(IIIILbh;I)V
    goto L68
L4
    iload 11
    ifeq L88
    iload 3
    ldc -1141317100 (java.lang.Integer)
    if_icmpne L61
    new java/lang/IllegalStateException
    dup
    invokespecial java/lang/IllegalStateException <init>:()V
    athrow
L34
    getstatic client hx:[[[Lgh;
    getstatic fd hz:I
    ldc -837647185 (java.lang.Integer)
    imul
    aaload
    iload 7
    aaload
    iload 8
    aaload
    astore 9
    goto L89
L88
    iload 13
    ifeq L62
    iload 3
    ldc -1141317100 (java.lang.Integer)
    if_icmpne L90
    new java/lang/IllegalStateException
    dup
    invokespecial java/lang/IllegalStateException <init>:()V
    athrow
L90
    iload 0
    iload 1
    iload 9
    iload 10
    getstatic o ed:[Lbh;
    iconst_4
    aaload
    ldc 1204133672 (java.lang.Integer)
    invokestatic fj dp:(IIIILbh;I)V
    goto L43
L30
    iconst_0
    istore 8
    goto L32
L64
    iload 0
    iload 1
    iload 9
    iload 10
    getstatic o ed:[Lbh;
    iconst_5
    aaload
    ldc 1204133672 (java.lang.Integer)
    invokestatic fj dp:(IIIILbh;I)V
    goto L43
L63
    iload 0
    iload 1
    iload 9
    iload 10
    getstatic o ed:[Lbh;
    iconst_2
    aaload
    ldc 1204133672 (java.lang.Integer)
    invokestatic fj dp:(IIIILbh;I)V
L43
    iinc 7 1
    goto L11
L12
    ldc 577949343 (java.lang.Integer)
    getstatic client aw:I
    imul
    ifeq L18
    iload 3
    ldc -1141317100 (java.lang.Integer)
    if_icmpne L91
    new java/lang/IllegalStateException
    dup
    invokespecial java/lang/IllegalStateException <init>:()V
    athrow
L91
    getstatic client b:I
    ldc -117546507 (java.lang.Integer)
    imul
    bipush 20
    irem
    bipush 10
    if_icmpge L18
    iload 3
    ldc -1141317100 (java.lang.Integer)
    if_icmpne L65
    new java/lang/IllegalStateException
    dup
    invokespecial java/lang/IllegalStateException <init>:()V
    athrow
L39
    iconst_0
    istore 13
    goto L84
L67
    getstatic client am:I
    ldc -1416594727 (java.lang.Integer)
    imul
    iflt L66
    iload 3
    ldc -1141317100 (java.lang.Integer)
    if_icmpne L92
    new java/lang/IllegalStateException
    dup
    invokespecial java/lang/IllegalStateException <init>:()V
    athrow
L92
    ldc -1416594727 (java.lang.Integer)
    getstatic client am:I
    imul
    getstatic client cf:[Lam;
    arraylength
    if_icmpge L66
    iload 3
    ldc -1141317100 (java.lang.Integer)
    if_icmpne L93
    new java/lang/IllegalStateException
    dup
    invokespecial java/lang/IllegalStateException <init>:()V
    athrow
L93
    getstatic client cf:[Lam;
    getstatic client am:I
    ldc -1416594727 (java.lang.Integer)
    imul
    aaload
    astore 7
L94
    aload 7
    ifnull L66
L95
    aload 7
    getfield am b:I
    ldc 1164900853 (java.lang.Integer)
    imul
    bipush 32
    idiv
    getstatic hg hv:Ll;
    getfield l b:I
    ldc 1164900853 (java.lang.Integer)
    imul
    bipush 32
    idiv
    isub
    istore 8
L96
    ldc 109190397 (java.lang.Integer)
    aload 7
    getfield am x:I
    imul
    bipush 32
    idiv
    ldc 109190397 (java.lang.Integer)
    getstatic hg hv:Ll;
    getfield l x:I
    imul
    bipush 32
    idiv
    isub
    istore 9
L97
    iload 0
    iload 1
    iload 8
    iload 9
    getstatic ao ef:[Lbh;
    iconst_1
    aaload
    ldc 1163068483 (java.lang.Integer)
    invokestatic dl df:(IIIILbh;I)V
    goto L66
L24
    getstatic client lt:[Z
    iload 2
    iconst_1
    bastore
    goto L49
L51
    aconst_null
    aload 9
    if_acmpeq L53
    iload 3
    ldc -1141317100 (java.lang.Integer)
    if_icmpne L52
    new java/lang/IllegalStateException
    dup
    invokespecial java/lang/IllegalStateException <init>:()V
    athrow
L98
    getstatic client ab:I
    ldc -1105739396 (java.lang.Integer)
    imul
    ldc 973940276 (java.lang.Integer)
    getstatic co cz:I
    imul
    isub
    iconst_2
    iadd
    getstatic hg hv:Ll;
    getfield l x:I
    ldc 109190397 (java.lang.Integer)
    imul
    bipush 32
    idiv
    isub
    istore 8
L99
    iload 0
    iload 1
    iload 7
    iload 8
    getstatic ao ef:[Lbh;
    iconst_1
    aaload
    ldc -571956918 (java.lang.Integer)
    invokestatic dl df:(IIIILbh;I)V
L100
    bipush 10
    getstatic client aw:I
    ldc 577949343 (java.lang.Integer)
    imul
    if_icmpne L18
    iload 3
    ldc -1141317100 (java.lang.Integer)
    if_icmpne L101
    new java/lang/IllegalStateException
    dup
    invokespecial java/lang/IllegalStateException <init>:()V
    athrow
L101
    getstatic client au:I
    ldc 72113091 (java.lang.Integer)
    imul
    iflt L18
    iload 3
    ldc -1141317100 (java.lang.Integer)
    if_icmpne L17
    new java/lang/IllegalStateException
    dup
    invokespecial java/lang/IllegalStateException <init>:()V
    athrow
L69
    getstatic client mm:I
    ldc 673163420 (java.lang.Integer)
    imul
    iconst_2
    iadd
    ldc 1164900853 (java.lang.Integer)
    getstatic hg hv:Ll;
    getfield l b:I
    imul
    bipush 32
    idiv
    isub
    istore 7
    goto L102
L19
    getstatic client hg:[Ll;
    getstatic client au:I
    ldc 72113091 (java.lang.Integer)
    imul
    aaload
    astore 7
L103
    aload 7
    ifnull L18
    iload 3
    ldc -1141317100 (java.lang.Integer)
    if_icmpne L78
    return
L57
    aload 9
    getfield ay ae:Z
    ifeq L35
    iload 3
    ldc -1141317100 (java.lang.Integer)
    if_icmpne L60
    new java/lang/IllegalStateException
    dup
    invokespecial java/lang/IllegalStateException <init>:()V
    athrow
L79
    ldc 109190397 (java.lang.Integer)
    aload 7
    getfield l x:I
    imul
    bipush 32
    idiv
    getstatic hg hv:Ll;
    getfield l x:I
    ldc 109190397 (java.lang.Integer)
    imul
    bipush 32
    idiv
    isub
    istore 9
L104
    iload 0
    iload 1
    iload 8
    iload 9
    getstatic ao ef:[Lbh;
    iconst_1
    aaload
    ldc -739018616 (java.lang.Integer)
    invokestatic dl df:(IIIILbh;I)V
    goto L18
L66
    getstatic client aw:I
    ldc 577949343 (java.lang.Integer)
    imul
    iconst_2
    if_icmpne L100
    iload 3
    ldc -1141317100 (java.lang.Integer)
    if_icmpne L105
    new java/lang/IllegalStateException
    dup
    invokespecial java/lang/IllegalStateException <init>:()V
    athrow
L102
    iconst_2
    getstatic client mz:I
    ldc -1930970372 (java.lang.Integer)
    imul
    iadd
    ldc 109190397 (java.lang.Integer)
    getstatic hg hv:Ll;
    getfield l x:I
    imul
    bipush 32
    idiv
    isub
    istore 8
    goto L87
L46
    getstatic client cf:[Lam;
    getstatic client cb:[I
    iload 7
    iaload
    aaload
    astore 8
    goto L47
L105
    iconst_2
    getstatic client ae:I
    ldc 1710972660 (java.lang.Integer)
    imul
    ldc -1827422796 (java.lang.Integer)
    getstatic x cs:I
    imul
    isub
    iadd
    getstatic hg hv:Ll;
    getfield l b:I
    ldc 1164900853 (java.lang.Integer)
    imul
    bipush 32
    idiv
    isub
    istore 7
    goto L98
L68
    getstatic hg hv:Ll;
    getfield l d:Z
    ifne L83
    iload 3
    ldc -1141317100 (java.lang.Integer)
    if_icmpne L82
    return
L77
    iload 13
    ldc 1151312169 (java.lang.Integer)
    getstatic cd mp:I
    imul
    if_icmpge L39
    goto L106
L83
    goto L107
L86
    ldc 1593175097 (java.lang.Integer)
    getstatic hg hv:Ll;
    getfield l q:I
    imul
    ldc 1593175097 (java.lang.Integer)
    aload 8
    getfield l q:I
    imul
    if_icmpne L4
    goto L3
L107
    ldc 1217278719 (java.lang.Integer)
    getstatic client mx:I
    imul
    iconst_3
    if_icmpge L108
    iload 3
    ldc -1141317100 (java.lang.Integer)
    if_icmpne L31
    new java/lang/IllegalStateException
    dup
    invokespecial java/lang/IllegalStateException <init>:()V
    athrow
L106
    aload 8
    getfield l e:Ljava/lang/String;
    getstatic r ma:[Ln;
    iload 13
    aaload
    getfield n e:Ljava/lang/String;
    invokevirtual java/lang/String equals:(Ljava/lang/Object;)Z
    ifeq L81
    goto L80
L108
    iload 0
    iload 1
    iconst_0
    getstatic gp er:[I
    getstatic cs ev:[I
    invokestatic bt dh:(III[I[I)V
    goto L23
L89
    aload 9
    ifnull L42
    goto L55
L25
    getstatic q ez:Lbs;
    iload 0
    iload 1
    invokevirtual bs l:(II)V
    goto L24
L7
    bipush 25
    iload 0
    iadd
    iconst_5
    iload 1
    iadd
    iconst_0
    getstatic j eb:[I
    getstatic cg eq:[I
    invokestatic bt dh:(III[I[I)V
    goto L107
L16
    iload 7
    ldc 531970677 (java.lang.Integer)
    getstatic client mw:I
    imul
    if_icmpge L27
    iload 3
    ldc -1141317100 (java.lang.Integer)
    if_icmpne L20
    new java/lang/IllegalStateException
    dup
    invokespecial java/lang/IllegalStateException <init>:()V
    athrow
L109
    new java/lang/StringBuilder
    dup
    invokespecial java/lang/StringBuilder <init>:()V
    ldc "f.dk(" (java.lang.String)
    invokevirtual java/lang/StringBuilder append:(Ljava/lang/String;)Ljava/lang/StringBuilder;
    ldc 41 (java.lang.Integer)
    invokevirtual java/lang/StringBuilder append:(C)Ljava/lang/StringBuilder;
    invokevirtual java/lang/StringBuilder toString:()Ljava/lang/String;
    invokestatic k a:(Ljava/lang/Throwable;Ljava/lang/String;)Lee;
    athrow
