fb s (Lah;IZLfq;I)Lcy;L1
    iconst_0
    putstatic fb g:Z
    goto L2
L3
    iload 6
    iconst_1
    if_icmpne L4
    iload 5
    ldc -781990728 (java.lang.Integer)
    if_icmplt L5
    new java/lang/IllegalStateException
    dup
    invokespecial java/lang/IllegalStateException <init>:()V
    athrow
L6
    ldc 1137929341 (java.lang.Integer)
    aload 0
    getfield fb ac:I
    imul
    istore 6
L7
    ldc -789220545 (java.lang.Integer)
    aload 0
    getfield fb ad:I
    imul
    istore 7
    goto L8
L9
    aconst_null
    areturn
L10
    ldc 2059766591 (java.lang.Integer)
    aload 0
    getfield fb aq:I
    imul
    istore 7
L8
    iconst_0
    iload 6
    if_icmpne L3
    iload 5
    ldc -781990728 (java.lang.Integer)
    if_icmplt L11
    new java/lang/IllegalStateException
    dup
    invokespecial java/lang/IllegalStateException <init>:()V
    athrow
L11
    aconst_null
    areturn
L12
    aload 8
    areturn
L5
    iconst_m1
    iload 7
    if_icmpne L4
    iload 5
    ldc -781990728 (java.lang.Integer)
    if_icmplt L13
    new java/lang/IllegalStateException
    dup
    invokespecial java/lang/IllegalStateException <init>:()V
    athrow
L14
    aload 8
    ifnonnull L15
    iload 5
    ldc -781990728 (java.lang.Integer)
    if_icmplt L16
    new java/lang/IllegalStateException
    dup
    invokespecial java/lang/IllegalStateException <init>:()V
    athrow
L4
    getstatic fb r:Lgr;
    iload 7
    iload 6
    bipush 16
    ishl
    iadd
    i2l
    invokevirtual gr e:(J)Lgd;
    checkcast cy
    astore 8
    goto L14
L17
    aconst_null
    aload 9
    if_acmpne L18
    iload 5
    ldc -781990728 (java.lang.Integer)
    if_icmplt L19
    new java/lang/IllegalStateException
    dup
    invokespecial java/lang/IllegalStateException <init>:()V
    athrow
L16
    iconst_1
    iload 6
    if_icmpne L20
L21
    getstatic fb c:Lfv;
    iload 7
    iconst_0
    invokestatic cr e:(Lfv;II)Lcr;
    astore 9
    goto L17
L15
    aload 1
    ifnull L12
    iload 5
    ldc -781990728 (java.lang.Integer)
    if_icmplt L22
    new java/lang/IllegalStateException
    dup
    invokespecial java/lang/IllegalStateException <init>:()V
    athrow
L19
    iconst_1
    putstatic fb g:Z
    goto L23
L24
    aload 9
    bipush 64
    sipush 768
    bipush -50
    bipush -10
    bipush -50
    invokevirtual cr p:(IIIII)Lcy;
    astore 8
    goto L25
L18
    aload 9
    bipush 64
    sipush 768
    bipush -50
    bipush -10
    bipush -50
    invokevirtual cr p:(IIIII)Lcy;
    astore 8
L20
    iload 6
    iconst_2
    if_icmpne L26
    iload 5
    ldc -781990728 (java.lang.Integer)
    if_icmplt L27
    new java/lang/IllegalStateException
    dup
    invokespecial java/lang/IllegalStateException <init>:()V
    athrow
L27
    iload 7
    bipush 54
    invokestatic ar e:(IB)Lay;
    bipush 69
    invokevirtual ay w:(B)Lcr;
    astore 9
    goto L28
L13
    aconst_null
    areturn
L29
    iconst_1
    putstatic fb g:Z
    goto L30
L31
    getstatic fb r:Lgr;
    aload 8
    iload 7
    iload 6
    bipush 16
    ishl
    iadd
    i2l
    invokevirtual gr l:(Lgd;J)V
    goto L15
L32
    aload 9
    bipush 64
    sipush 768
    bipush -50
    bipush -10
    bipush -50
    invokevirtual cr p:(IIIII)Lcy;
    astore 8
L26
    iconst_3
    iload 6
    if_icmpne L25
    iload 5
    ldc -781990728 (java.lang.Integer)
    if_icmplt L33
    new java/lang/IllegalStateException
    dup
    invokespecial java/lang/IllegalStateException <init>:()V
    athrow
L33
    aconst_null
    aload 4
    if_acmpne L34
    iload 5
    ldc -781990728 (java.lang.Integer)
    if_icmplt L9
    new java/lang/IllegalStateException
    dup
    invokespecial java/lang/IllegalStateException <init>:()V
    athrow
L23
    aconst_null
    areturn
L34
    aload 4
    bipush -81
    invokevirtual fq r:(B)Lcr;
    astore 9
    goto L35
L30
    aconst_null
    areturn
L36
    aload 0
    getfield fb ar:I
    ldc 799580057 (java.lang.Integer)
    imul
    istore 6
    goto L10
L37
    aconst_null
    areturn
L38
    aconst_null
    areturn
L25
    iconst_4
    iload 6
    if_icmpne L31
    iload 5
    ldc -781990728 (java.lang.Integer)
    if_icmplt L39
    new java/lang/IllegalStateException
    dup
    invokespecial java/lang/IllegalStateException <init>:()V
    athrow
L39
    iload 7
    bipush 13
    invokestatic dj e:(IB)Lad;
    astore 10
L40
    aload 10
    bipush 10
    ldc -1417743113 (java.lang.Integer)
    invokevirtual ad i:(II)Lcr;
    astore 9
L41
    aconst_null
    aload 9
    if_acmpne L42
    iload 5
    ldc -781990728 (java.lang.Integer)
    if_icmplt L43
    new java/lang/IllegalStateException
    dup
    invokespecial java/lang/IllegalStateException <init>:()V
    athrow
L43
    iconst_1
    putstatic fb g:Z
    goto L38
L35
    aconst_null
    aload 9
    if_acmpne L24
    iload 5
    ldc -781990728 (java.lang.Integer)
    if_icmplt L44
    new java/lang/IllegalStateException
    dup
    invokespecial java/lang/IllegalStateException <init>:()V
    athrow
L42
    aload 9
    ldc -1859198821 (java.lang.Integer)
    aload 10
    getfield ad az:I
    imul
    bipush 64
    iadd
    aload 10
    getfield ad af:I
    ldc 40571045 (java.lang.Integer)
    imul
    sipush 768
    iadd
    bipush -50
    bipush -10
    bipush -50
    invokevirtual cr p:(IIIII)Lcy;
    astore 8
    goto L31
L44
    iconst_1
    putstatic fb g:Z
    goto L37
L28
    aconst_null
    aload 9
    if_acmpne L32
    iload 5
    ldc -781990728 (java.lang.Integer)
    if_icmplt L29
    new java/lang/IllegalStateException
    dup
    invokespecial java/lang/IllegalStateException <init>:()V
    athrow
L22
    aload 1
    aload 8
    iload 2
    ldc -736776539 (java.lang.Integer)
    invokevirtual ah f:(Lcy;II)Lcy;
    astore 8
    goto L12
L2
    iload 3
    ifeq L36
    iload 5
    ldc -781990728 (java.lang.Integer)
    if_icmplt L6
    new java/lang/IllegalStateException
    dup
    invokespecial java/lang/IllegalStateException <init>:()V
    athrow
L45
    new java/lang/StringBuilder
    dup
    invokespecial java/lang/StringBuilder <init>:()V
    ldc "fb.s(" (java.lang.String)
    invokevirtual java/lang/StringBuilder append:(Ljava/lang/String;)Ljava/lang/StringBuilder;
    ldc 41 (java.lang.Integer)
    invokevirtual java/lang/StringBuilder append:(C)Ljava/lang/StringBuilder;
    invokevirtual java/lang/StringBuilder toString:()Ljava/lang/String;
    invokestatic k a:(Ljava/lang/Throwable;Ljava/lang/String;)Lee;
    athrow
