fb u (Ldh;I)VL1
    aload 0
    iconst_0
    putfield fb o:Z
    goto L2
L3
    aload 0
    ldc 499334371 (java.lang.Integer)
    putfield fb an:I
    goto L4
L5
    aload 0
    aload 1
    ldc 823737610 (java.lang.Integer)
    invokevirtual dh z:(I)I
    ldc -2055800161 (java.lang.Integer)
    imul
    putfield fb m:I
    goto L6
L7
    ldc -1547422441 (java.lang.Integer)
    aload 0
    getfield fb j:I
    imul
    bipush 7
    if_icmpne L8
    iload 2
    ldc -129974993 (java.lang.Integer)
    if_icmpeq L9
    return
L10
    aload 0
    aload 0
    aload 1
    ldc -1275845441 (java.lang.Integer)
    invokevirtual dh d:(I)I
    ldc -36323741 (java.lang.Integer)
    imul
    dup_x1
    putfield fb z:I
    ldc -1276132747 (java.lang.Integer)
    imul
    putfield fb y:I
L11
    aload 0
    aload 0
    aload 1
    ldc -463675582 (java.lang.Integer)
    invokevirtual dh d:(I)I
    ldc -292842647 (java.lang.Integer)
    imul
    dup_x1
    putfield fb q:I
    ldc -1448901703 (java.lang.Integer)
    imul
    putfield fb d:I
L12
    aload 0
    aload 1
    ldc -652773878 (java.lang.Integer)
    invokevirtual dh q:(I)I
    ldc 357890893 (java.lang.Integer)
    imul
    putfield fb b:I
    goto L13
L14
    aload 0
    aload 0
    getfield fb by:I
    ldc -440702821 (java.lang.Integer)
    imul
    iload 5
    bipush 11
    ishl
    ior
    ldc -121487981 (java.lang.Integer)
    imul
    putfield fb by:I
    goto L15
L16
    aload 0
    aload 1
    ldc 1654615725 (java.lang.Integer)
    invokevirtual dh z:(I)I
    ldc 1358801527 (java.lang.Integer)
    imul
    putfield fb ae:I
    goto L17
L18
    ldc 65535 (java.lang.Integer)
    aload 0
    getfield fb az:I
    ldc -850817991 (java.lang.Integer)
    imul
    if_icmpne L19
    iload 2
    ldc -129974993 (java.lang.Integer)
    if_icmpeq L20
    new java/lang/IllegalStateException
    dup
    invokespecial java/lang/IllegalStateException <init>:()V
    athrow
L21
    ldc 65535 (java.lang.Integer)
    aload 0
    getfield fb n:I
    ldc 737715635 (java.lang.Integer)
    imul
    if_icmpne L22
    iload 2
    ldc -129974993 (java.lang.Integer)
    if_icmpeq L23
    new java/lang/IllegalStateException
    dup
    invokespecial java/lang/IllegalStateException <init>:()V
    athrow
L24
    aload 0
    ldc -121487981 (java.lang.Integer)
    ldc -440702821 (java.lang.Integer)
    aload 0
    getfield fb by:I
    imul
    ldc -2147483648 (java.lang.Integer)
    ior
    imul
    putfield fb by:I
    goto L25
L22
    aload 0
    aload 0
    getfield fb n:I
    ldc 737715635 (java.lang.Integer)
    imul
    aload 0
    getfield fb h:I
    ldc 952871887 (java.lang.Integer)
    imul
    ldc -65536 (java.lang.Integer)
    iand
    iadd
    ldc 882545019 (java.lang.Integer)
    imul
    putfield fb n:I
L26
    aload 0
    aload 1
    ldc 2121873153 (java.lang.Integer)
    invokevirtual dh q:(I)I
    ldc -1756015691 (java.lang.Integer)
    imul
    putfield fb dj:I
L27
    aload 0
    getfield fb dj:I
    ldc 152781469 (java.lang.Integer)
    imul
    ldc 65535 (java.lang.Integer)
    if_icmpne L28
    aload 0
    ldc 1756015691 (java.lang.Integer)
    putfield fb dj:I
    goto L28
L29
    ldc 1810211167 (java.lang.Integer)
    aload 0
    getfield fb m:I
    imul
    iconst_5
    if_icmpne L30
    goto L31
L32
    iload 3
    ifle L33
    iload 2
    ldc -129974993 (java.lang.Integer)
    if_icmpeq L34
    new java/lang/IllegalStateException
    dup
    invokespecial java/lang/IllegalStateException <init>:()V
    athrow
L34
    aload 0
    iload 3
    newarray 10
    putfield fb du:[I
    goto L35
L36
    aload 0
    aload 1
    ldc -2062589178 (java.lang.Integer)
    invokevirtual dh x:(I)I
    ldc 37728577 (java.lang.Integer)
    imul
    putfield fb ay:I
    goto L37
L38
    iconst_0
    istore 4
    goto L39
L40
    aload 0
    aload 1
    ldc -422981876 (java.lang.Integer)
    invokevirtual dh q:(I)I
    ldc 1003527573 (java.lang.Integer)
    imul
    putfield fb bl:I
    goto L7
L41
    iconst_0
    istore 9
    goto L42
L43
    aload 0
    getfield fb dm:[I
    iload 4
    aload 1
    ldc -416961343 (java.lang.Integer)
    invokevirtual dh q:(I)I
    iastore
    goto L44
L45
    aload 0
    aload 1
    ldc -2086783619 (java.lang.Integer)
    invokevirtual dh x:(I)I
    ldc 517757131 (java.lang.Integer)
    imul
    putfield fb ai:I
    goto L46
L47
    aload 0
    aload 1
    ldc 666057493 (java.lang.Integer)
    invokevirtual dh q:(I)I
    ldc -2031066809 (java.lang.Integer)
    imul
    putfield fb bv:I
    goto L48
L49
    iload 4
    ifle L50
    iload 2
    ldc -129974993 (java.lang.Integer)
    if_icmpeq L51
    new java/lang/IllegalStateException
    dup
    invokespecial java/lang/IllegalStateException <init>:()V
    athrow
L51
    aload 0
    iload 4
    anewarray [I
    putfield fb dh:[[I
L52
    iconst_0
    istore 5
    goto L53
L54
    iconst_0
    istore 6
    goto L55
L56
    iinc 9 1
    goto L57
L58
    aload 0
    getfield fb dh:[[I
    iload 5
    iload 6
    newarray 10
    aastore
L59
    iconst_0
    istore 7
L60
    iload 7
    iload 6
    if_icmpge L61
L62
    aload 0
    getfield fb dh:[[I
    iload 5
    aaload
    iload 7
    aload 1
    ldc -2115636192 (java.lang.Integer)
    invokevirtual dh q:(I)I
    iastore
L63
    ldc 65535 (java.lang.Integer)
    aload 0
    getfield fb dh:[[I
    iload 5
    aaload
    iload 7
    iaload
    if_icmpne L64
    iload 2
    ldc -129974993 (java.lang.Integer)
    if_icmpeq L65
    new java/lang/IllegalStateException
    dup
    invokespecial java/lang/IllegalStateException <init>:()V
    athrow
L65
    aload 0
    getfield fb dh:[[I
    iload 5
    aaload
    iload 7
    iconst_m1
    iastore
L64
    iinc 7 1
    goto L60
L61
    iinc 5 1
    goto L53
L50
    ldc -1547422441 (java.lang.Integer)
    aload 0
    getfield fb j:I
    imul
    ifne L66
L67
    aload 0
    aload 1
    ldc -966187317 (java.lang.Integer)
    invokevirtual dh q:(I)I
    ldc 1564326831 (java.lang.Integer)
    imul
    putfield fb ap:I
L68
    aload 0
    aload 1
    ldc 1108251990 (java.lang.Integer)
    invokevirtual dh z:(I)I
    iconst_1
    if_icmpne L69
    iload 2
    ldc -129974993 (java.lang.Integer)
    if_icmpeq L70
    return
L46
    aload 0
    aload 1
    ldc -2022594754 (java.lang.Integer)
    invokevirtual dh x:(I)I
    ldc -398295603 (java.lang.Integer)
    imul
    putfield fb aw:I
    goto L71
L72
    aload 1
    ldc 1333243373 (java.lang.Integer)
    invokevirtual dh z:(I)I
    istore 7
    goto L73
L74
    aload 1
    ldc 1500735524 (java.lang.Integer)
    invokevirtual dh z:(I)I
    istore 5
    goto L75
L76
    ldc -1547422441 (java.lang.Integer)
    aload 0
    getfield fb j:I
    imul
    iconst_2
    if_icmpne L77
    iload 2
    ldc -129974993 (java.lang.Integer)
    if_icmpeq L78
    new java/lang/IllegalStateException
    dup
    invokespecial java/lang/IllegalStateException <init>:()V
    athrow
L79
    aload 0
    iconst_5
    anewarray java/lang/String
    putfield fb bi:[Ljava/lang/String;
    goto L80
L81
    aload 0
    ldc -440702821 (java.lang.Integer)
    aload 0
    getfield fb by:I
    imul
    ldc 1073741824 (java.lang.Integer)
    ior
    ldc -121487981 (java.lang.Integer)
    imul
    putfield fb by:I
    goto L82
L83
    putfield fb au:Z
    goto L84
L78
    aload 0
    aload 0
    getfield fb x:I
    ldc 891461123 (java.lang.Integer)
    imul
    ldc -606292603 (java.lang.Integer)
    aload 0
    getfield fb b:I
    imul
    imul
    newarray 10
    putfield fb dv:[I
    goto L85
L2
    aload 0
    aload 1
    ldc 1377280097 (java.lang.Integer)
    invokevirtual dh z:(I)I
    ldc 2113950375 (java.lang.Integer)
    imul
    putfield fb j:I
    goto L5
L86
    aload 1
    ldc 631495242 (java.lang.Integer)
    invokevirtual dh z:(I)I
    istore 5
    goto L87
L88
    aload 0
    aload 1
    ldc 755494784 (java.lang.Integer)
    invokevirtual dh z:(I)I
    iconst_1
    if_icmpne L89
    iload 2
    ldc -129974993 (java.lang.Integer)
    if_icmpeq L90
    new java/lang/IllegalStateException
    dup
    invokespecial java/lang/IllegalStateException <init>:()V
    athrow
L91
    aload 0
    ldc -440702821 (java.lang.Integer)
    aload 0
    getfield fb by:I
    imul
    ldc 268435456 (java.lang.Integer)
    ior
    ldc -121487981 (java.lang.Integer)
    imul
    putfield fb by:I
L92
    aload 1
    ldc 1648245862 (java.lang.Integer)
    invokevirtual dh z:(I)I
    istore 6
    goto L93
L94
    aload 0
    getfield fb j:I
    ldc -1547422441 (java.lang.Integer)
    imul
    iconst_2
    if_icmpne L15
    iload 2
    ldc -129974993 (java.lang.Integer)
    if_icmpeq L95
    return
L35
    aload 0
    iload 3
    newarray 10
    putfield fb dm:[I
    goto L38
L96
    putfield fb bx:Z
    goto L97
L70
    iconst_1
    goto L98
L99
    iconst_1
    aload 0
    getfield fb j:I
    ldc -1547422441 (java.lang.Integer)
    imul
    if_icmpeq L100
    iload 2
    ldc -129974993 (java.lang.Integer)
    if_icmpeq L101
    new java/lang/IllegalStateException
    dup
    invokespecial java/lang/IllegalStateException <init>:()V
    athrow
L25
    aload 1
    ldc 1794875840 (java.lang.Integer)
    invokevirtual dh z:(I)I
    istore 8
L102
    iconst_1
    iload 8
    if_icmpne L103
    iload 2
    ldc -129974993 (java.lang.Integer)
    if_icmpeq L104
    new java/lang/IllegalStateException
    dup
    invokespecial java/lang/IllegalStateException <init>:()V
    athrow
L53
    iload 5
    iload 4
    if_icmpge L50
    goto L105
L106
    aload 0
    getstatic et u:Ljava/lang/String;
    putfield fb dl:Ljava/lang/String;
    goto L107
L108
    aload 0
    aload 1
    ldc 1224676726 (java.lang.Integer)
    invokevirtual dh z:(I)I
    ldc -968416759 (java.lang.Integer)
    imul
    putfield fb bb:I
L109
    aload 0
    bipush 20
    newarray 10
    putfield fb bj:[I
L110
    aload 0
    bipush 20
    newarray 10
    putfield fb bq:[I
L111
    aload 0
    bipush 20
    newarray 10
    putfield fb bn:[I
    goto L41
L112
    aload 1
    ldc -375343314 (java.lang.Integer)
    invokevirtual dh q:(I)I
    pop
    goto L113
L42
    iload 9
    bipush 20
    if_icmpge L79
    iload 2
    ldc -129974993 (java.lang.Integer)
    if_icmpeq L114
    new java/lang/IllegalStateException
    dup
    invokespecial java/lang/IllegalStateException <init>:()V
    athrow
L114
    aload 1
    ldc 754011594 (java.lang.Integer)
    invokevirtual dh z:(I)I
    istore 10
L115
    iload 10
    iconst_1
    if_icmpne L116
    iload 2
    ldc -129974993 (java.lang.Integer)
    if_icmpeq L117
    new java/lang/IllegalStateException
    dup
    invokespecial java/lang/IllegalStateException <init>:()V
    athrow
L117
    aload 0
    getfield fb bj:[I
    iload 9
    aload 1
    ldc 1270535720 (java.lang.Integer)
    invokevirtual dh d:(I)I
    iastore
    goto L118
L73
    iload 7
    iconst_1
    if_icmpne L25
    iload 2
    ldc -129974993 (java.lang.Integer)
    if_icmpeq L24
    new java/lang/IllegalStateException
    dup
    invokespecial java/lang/IllegalStateException <init>:()V
    athrow
L39
    iload 4
    iload 3
    if_icmpge L33
    goto L119
L116
    aload 0
    getfield fb bn:[I
    iload 9
    iconst_m1
    iastore
L120
    iinc 9 1
    goto L42
L121
    aload 0
    ldc -121487981 (java.lang.Integer)
    aload 0
    getfield fb by:I
    ldc -440702821 (java.lang.Integer)
    imul
    iconst_1
    ior
    imul
    putfield fb by:I
L122
    return
L57
    iload 9
    iconst_5
    if_icmpge L77
    iload 2
    ldc -129974993 (java.lang.Integer)
    if_icmpeq L123
    new java/lang/IllegalStateException
    dup
    invokespecial java/lang/IllegalStateException <init>:()V
    athrow
L123
    aload 1
    ldc -45390468 (java.lang.Integer)
    invokevirtual dh p:(I)Ljava/lang/String;
    astore 10
L124
    aload 10
    invokevirtual java/lang/String length:()I
    ifle L56
    goto L125
L126
    iconst_4
    ldc -1547422441 (java.lang.Integer)
    aload 0
    getfield fb j:I
    imul
    if_icmpne L127
    iload 2
    ldc -129974993 (java.lang.Integer)
    if_icmpeq L100
    new java/lang/IllegalStateException
    dup
    invokespecial java/lang/IllegalStateException <init>:()V
    athrow
L128
    aload 0
    aload 0
    getfield fb by:I
    ldc -440702821 (java.lang.Integer)
    imul
    iconst_1
    bipush 23
    iload 9
    iadd
    ishl
    ior
    ldc -121487981 (java.lang.Integer)
    imul
    putfield fb by:I
    goto L56
L129
    aload 0
    aload 1
    ldc 1016496826 (java.lang.Integer)
    invokevirtual dh q:(I)I
    ldc -2031066809 (java.lang.Integer)
    imul
    putfield fb bv:I
    goto L130
L104
    aload 0
    ldc -121487981 (java.lang.Integer)
    aload 0
    getfield fb by:I
    ldc -440702821 (java.lang.Integer)
    imul
    ldc 536870912 (java.lang.Integer)
    ior
    imul
    putfield fb by:I
    goto L103
L131
    aload 0
    aload 1
    ldc 1161857956 (java.lang.Integer)
    invokevirtual dh z:(I)I
    ldc -400071187 (java.lang.Integer)
    imul
    putfield fb ba:I
    goto L129
L132
    iconst_1
    goto L83
L133
    iconst_0
    goto L83
L44
    iinc 4 1
    goto L39
L84
    iconst_4
    aload 0
    getfield fb j:I
    ldc -1547422441 (java.lang.Integer)
    imul
    if_icmpeq L134
    iload 2
    ldc -129974993 (java.lang.Integer)
    if_icmpeq L135
    new java/lang/IllegalStateException
    dup
    invokespecial java/lang/IllegalStateException <init>:()V
    athrow
L33
    aload 1
    ldc 2077255787 (java.lang.Integer)
    invokevirtual dh z:(I)I
    istore 4
    goto L49
L134
    aload 0
    aload 1
    ldc 1042357238 (java.lang.Integer)
    invokevirtual dh z:(I)I
    ldc -400071187 (java.lang.Integer)
    imul
    putfield fb ba:I
L136
    aload 0
    aload 1
    ldc 687136038 (java.lang.Integer)
    invokevirtual dh z:(I)I
    ldc 1596647467 (java.lang.Integer)
    imul
    putfield fb bf:I
    goto L137
L66
    ldc -1547422441 (java.lang.Integer)
    aload 0
    getfield fb j:I
    imul
    iconst_1
    if_icmpne L76
    iload 2
    ldc -129974993 (java.lang.Integer)
    if_icmpeq L112
    new java/lang/IllegalStateException
    dup
    invokespecial java/lang/IllegalStateException <init>:()V
    athrow
L138
    ldc -1547422441 (java.lang.Integer)
    aload 0
    getfield fb j:I
    imul
    iconst_4
    if_icmpne L139
    goto L45
L140
    aload 0
    aload 1
    ldc 693563648 (java.lang.Integer)
    invokevirtual dh p:(I)Ljava/lang/String;
    putfield fb br:Ljava/lang/String;
    goto L99
L141
    aload 0
    ldc 2031066809 (java.lang.Integer)
    putfield fb bv:I
L142
    aload 0
    aload 1
    ldc 643399337 (java.lang.Integer)
    invokevirtual dh z:(I)I
    iconst_1
    if_icmpne L143
    iconst_1
    goto L96
L144
    aload 0
    aload 1
    ldc -767592131 (java.lang.Integer)
    invokevirtual dh q:(I)I
    ldc 1649671359 (java.lang.Integer)
    imul
    putfield fb ad:I
    goto L145
L146
    aload 0
    aload 1
    ldc -2027786407 (java.lang.Integer)
    invokevirtual dh x:(I)I
    ldc -1595723647 (java.lang.Integer)
    imul
    putfield fb ao:I
    goto L147
L23
    aload 0
    ldc -882545019 (java.lang.Integer)
    putfield fb n:I
    goto L26
L148
    aload 0
    aload 1
    ldc 13657374 (java.lang.Integer)
    invokevirtual dh p:(I)Ljava/lang/String;
    putfield fb bc:Ljava/lang/String;
    goto L140
L93
    iconst_1
    iload 6
    if_icmpne L72
    iload 2
    ldc -129974993 (java.lang.Integer)
    if_icmpeq L149
    new java/lang/IllegalStateException
    dup
    invokespecial java/lang/IllegalStateException <init>:()V
    athrow
L135
    iconst_1
    ldc -1547422441 (java.lang.Integer)
    aload 0
    getfield fb j:I
    imul
    if_icmpne L97
    goto L134
L69
    iconst_0
    goto L98
L150
    aload 0
    ldc 891461123 (java.lang.Integer)
    aload 0
    getfield fb x:I
    imul
    aload 0
    getfield fb b:I
    ldc -606292603 (java.lang.Integer)
    imul
    imul
    newarray 10
    putfield fb ds:[I
    goto L131
L100
    aload 0
    aload 1
    ldc -2021338474 (java.lang.Integer)
    invokevirtual dh x:(I)I
    ldc -1595723647 (java.lang.Integer)
    imul
    putfield fb ao:I
L127
    iconst_3
    aload 0
    getfield fb j:I
    ldc -1547422441 (java.lang.Integer)
    imul
    if_icmpeq L45
    iload 2
    ldc -129974993 (java.lang.Integer)
    if_icmpeq L138
    new java/lang/IllegalStateException
    dup
    invokespecial java/lang/IllegalStateException <init>:()V
    athrow
L113
    aload 1
    ldc 782636202 (java.lang.Integer)
    invokevirtual dh z:(I)I
    pop
    goto L76
L143
    iconst_0
    goto L96
L151
    aload 0
    getstatic et i:Ljava/lang/String;
    putfield fb dl:Ljava/lang/String;
    goto L152
L71
    aload 0
    aload 1
    ldc -2120195381 (java.lang.Integer)
    invokevirtual dh x:(I)I
    ldc -1376652165 (java.lang.Integer)
    imul
    putfield fb am:I
L139
    iconst_5
    ldc -1547422441 (java.lang.Integer)
    aload 0
    getfield fb j:I
    imul
    if_icmpne L37
    iload 2
    ldc -129974993 (java.lang.Integer)
    if_icmpeq L153
    new java/lang/IllegalStateException
    dup
    invokespecial java/lang/IllegalStateException <init>:()V
    athrow
L97
    iconst_4
    ldc -1547422441 (java.lang.Integer)
    aload 0
    getfield fb j:I
    imul
    if_icmpne L99
    iload 2
    ldc -129974993 (java.lang.Integer)
    if_icmpeq L148
    new java/lang/IllegalStateException
    dup
    invokespecial java/lang/IllegalStateException <init>:()V
    athrow
L154
    aload 0
    getfield fb bn:[I
    iload 9
    aload 1
    ldc -1988018372 (java.lang.Integer)
    invokevirtual dh x:(I)I
    iastore
    goto L120
L37
    aload 0
    getfield fb j:I
    ldc -1547422441 (java.lang.Integer)
    imul
    bipush 6
    if_icmpne L7
    iload 2
    ldc -129974993 (java.lang.Integer)
    if_icmpeq L155
    new java/lang/IllegalStateException
    dup
    invokespecial java/lang/IllegalStateException <init>:()V
    athrow
L155
    aload 0
    ldc -270908247 (java.lang.Integer)
    putfield fb ar:I
L156
    aload 0
    aload 1
    ldc 1178199551 (java.lang.Integer)
    invokevirtual dh q:(I)I
    ldc -1071127361 (java.lang.Integer)
    imul
    putfield fb aq:I
L157
    ldc 65535 (java.lang.Integer)
    ldc 2059766591 (java.lang.Integer)
    aload 0
    getfield fb aq:I
    imul
    if_icmpne L158
    goto L159
L85
    aload 0
    ldc -606292603 (java.lang.Integer)
    aload 0
    getfield fb b:I
    imul
    aload 0
    getfield fb x:I
    ldc 891461123 (java.lang.Integer)
    imul
    imul
    newarray 10
    putfield fb ds:[I
    goto L86
L158
    aload 0
    ldc -415601451 (java.lang.Integer)
    putfield fb ac:I
    goto L144
L98
    putfield fb v:Z
    goto L66
L145
    ldc 65535 (java.lang.Integer)
    aload 0
    getfield fb ad:I
    ldc -789220545 (java.lang.Integer)
    imul
    if_icmpne L160
    iload 2
    ldc -129974993 (java.lang.Integer)
    if_icmpeq L161
    new java/lang/IllegalStateException
    dup
    invokespecial java/lang/IllegalStateException <init>:()V
    athrow
L161
    aload 0
    ldc -1649671359 (java.lang.Integer)
    putfield fb ad:I
    goto L160
L48
    ldc 65535 (java.lang.Integer)
    ldc 717944951 (java.lang.Integer)
    aload 0
    getfield fb bv:I
    imul
    if_icmpne L142
    goto L141
L160
    aload 0
    aload 1
    ldc -1549646651 (java.lang.Integer)
    invokevirtual dh q:(I)I
    ldc -499334371 (java.lang.Integer)
    imul
    putfield fb an:I
    goto L162
L163
    ldc 1810211167 (java.lang.Integer)
    aload 0
    getfield fb m:I
    imul
    iconst_4
    if_icmpeq L164
    iload 2
    ldc -129974993 (java.lang.Integer)
    if_icmpeq L165
    return
L4
    aload 0
    aload 1
    ldc 1111384892 (java.lang.Integer)
    invokevirtual dh q:(I)I
    ldc 1193189897 (java.lang.Integer)
    imul
    putfield fb az:I
    goto L18
L166
    aload 0
    aload 1
    ldc -2041086762 (java.lang.Integer)
    invokevirtual dh d:(I)I
    ldc -968416759 (java.lang.Integer)
    imul
    putfield fb bb:I
    goto L74
L20
    aload 0
    ldc -1193189897 (java.lang.Integer)
    putfield fb az:I
L19
    aload 0
    aload 1
    ldc -1039602456 (java.lang.Integer)
    invokevirtual dh q:(I)I
    ldc 2108744207 (java.lang.Integer)
    imul
    putfield fb bm:I
L167
    aload 0
    aload 1
    ldc -1222289882 (java.lang.Integer)
    invokevirtual dh q:(I)I
    ldc -1571883189 (java.lang.Integer)
    imul
    putfield fb aa:I
    goto L40
L118
    aload 0
    getfield fb bq:[I
    iload 9
    aload 1
    ldc 1256658304 (java.lang.Integer)
    invokevirtual dh d:(I)I
    iastore
    goto L154
L30
    bipush 6
    aload 0
    getfield fb m:I
    ldc 1810211167 (java.lang.Integer)
    imul
    if_icmpne L152
    iload 2
    ldc -129974993 (java.lang.Integer)
    if_icmpeq L151
    return
L9
    aload 0
    aload 0
    getfield fb b:I
    ldc -606292603 (java.lang.Integer)
    imul
    aload 0
    getfield fb x:I
    ldc 891461123 (java.lang.Integer)
    imul
    imul
    newarray 10
    putfield fb dv:[I
    goto L150
L13
    aload 0
    aload 1
    ldc 57163769 (java.lang.Integer)
    invokevirtual dh q:(I)I
    ldc -1659011925 (java.lang.Integer)
    imul
    putfield fb x:I
    goto L16
L153
    aload 0
    aload 1
    ldc -2074240738 (java.lang.Integer)
    invokevirtual dh x:(I)I
    ldc 507575507 (java.lang.Integer)
    imul
    putfield fb av:I
    goto L36
L162
    aload 0
    getfield fb an:I
    ldc -1170991307 (java.lang.Integer)
    imul
    ldc 65535 (java.lang.Integer)
    if_icmpne L4
    goto L3
L130
    aload 0
    getfield fb bv:I
    ldc 717944951 (java.lang.Integer)
    imul
    ldc 65535 (java.lang.Integer)
    if_icmpne L88
    iload 2
    ldc -129974993 (java.lang.Integer)
    if_icmpeq L168
    new java/lang/IllegalStateException
    dup
    invokespecial java/lang/IllegalStateException <init>:()V
    athrow
L168
    aload 0
    ldc 2031066809 (java.lang.Integer)
    putfield fb bv:I
    goto L88
L90
    iconst_1
    goto L169
L80
    iconst_0
    istore 9
    goto L57
L137
    aload 0
    aload 1
    ldc 1616279898 (java.lang.Integer)
    invokevirtual dh z:(I)I
    ldc 382859101 (java.lang.Integer)
    imul
    putfield fb bu:I
    goto L47
L169
    putfield fb bx:Z
    goto L146
L103
    aload 0
    aload 1
    ldc 758085090 (java.lang.Integer)
    invokevirtual dh z:(I)I
    ldc -295524333 (java.lang.Integer)
    imul
    putfield fb bd:I
    goto L108
L147
    aload 0
    aload 1
    ldc -856830523 (java.lang.Integer)
    invokevirtual dh d:(I)I
    ldc -295524333 (java.lang.Integer)
    imul
    putfield fb bd:I
    goto L166
L149
    aload 0
    ldc -440702821 (java.lang.Integer)
    aload 0
    getfield fb by:I
    imul
    ldc 1073741824 (java.lang.Integer)
    ior
    ldc -121487981 (java.lang.Integer)
    imul
    putfield fb by:I
    goto L72
L125
    aload 0
    getfield fb bi:[Ljava/lang/String;
    iload 9
    aload 10
    aastore
    goto L128
L75
    iconst_1
    iload 5
    if_icmpne L82
    iload 2
    ldc -129974993 (java.lang.Integer)
    if_icmpeq L81
    return
L17
    aload 0
    aload 1
    ldc 683029775 (java.lang.Integer)
    invokevirtual dh q:(I)I
    ldc 882545019 (java.lang.Integer)
    imul
    putfield fb n:I
    goto L21
L82
    aload 0
    iconst_5
    anewarray java/lang/String
    putfield fb bi:[Ljava/lang/String;
    goto L54
L170
    aload 0
    aload 1
    ldc 666659770 (java.lang.Integer)
    invokevirtual dh z:(I)I
    iconst_1
    if_icmpne L133
    iload 2
    ldc -129974993 (java.lang.Integer)
    if_icmpeq L132
    new java/lang/IllegalStateException
    dup
    invokespecial java/lang/IllegalStateException <init>:()V
    athrow
L55
    iload 6
    iconst_5
    if_icmpge L8
    iload 2
    ldc -129974993 (java.lang.Integer)
    if_icmpeq L171
    new java/lang/IllegalStateException
    dup
    invokespecial java/lang/IllegalStateException <init>:()V
    athrow
L171
    aload 1
    ldc -1415119390 (java.lang.Integer)
    invokevirtual dh p:(I)Ljava/lang/String;
    astore 7
L172
    aload 7
    invokevirtual java/lang/String length:()I
    ifle L173
    iload 2
    ldc -129974993 (java.lang.Integer)
    if_icmpeq L174
    new java/lang/IllegalStateException
    dup
    invokespecial java/lang/IllegalStateException <init>:()V
    athrow
L174
    aload 0
    getfield fb bi:[Ljava/lang/String;
    iload 6
    aload 7
    aastore
L175
    aload 0
    ldc -440702821 (java.lang.Integer)
    aload 0
    getfield fb by:I
    imul
    iconst_1
    bipush 23
    iload 6
    iadd
    ishl
    ior
    ldc -121487981 (java.lang.Integer)
    imul
    putfield fb by:I
L173
    iinc 6 1
    goto L55
L8
    bipush 8
    ldc -1547422441 (java.lang.Integer)
    aload 0
    getfield fb j:I
    imul
    if_icmpne L176
    iload 2
    ldc -129974993 (java.lang.Integer)
    if_icmpeq L177
    new java/lang/IllegalStateException
    dup
    invokespecial java/lang/IllegalStateException <init>:()V
    athrow
L177
    aload 0
    aload 1
    ldc 202820823 (java.lang.Integer)
    invokevirtual dh p:(I)Ljava/lang/String;
    putfield fb bc:Ljava/lang/String;
L176
    aload 0
    getfield fb m:I
    ldc 1810211167 (java.lang.Integer)
    imul
    iconst_2
    if_icmpeq L95
    iload 2
    ldc -129974993 (java.lang.Integer)
    if_icmpeq L94
    new java/lang/IllegalStateException
    dup
    invokespecial java/lang/IllegalStateException <init>:()V
    athrow
L87
    iconst_1
    iload 5
    if_icmpne L92
    iload 2
    ldc -129974993 (java.lang.Integer)
    if_icmpeq L91
    new java/lang/IllegalStateException
    dup
    invokespecial java/lang/IllegalStateException <init>:()V
    athrow
L95
    aload 0
    aload 1
    ldc -908442564 (java.lang.Integer)
    invokevirtual dh p:(I)Ljava/lang/String;
    putfield fb cf:Ljava/lang/String;
L178
    aload 0
    aload 1
    ldc -1283211541 (java.lang.Integer)
    invokevirtual dh p:(I)Ljava/lang/String;
    putfield fb dt:Ljava/lang/String;
L179
    aload 1
    ldc 155731495 (java.lang.Integer)
    invokevirtual dh q:(I)I
    bipush 63
    iand
    istore 5
    goto L14
L77
    iconst_3
    ldc -1547422441 (java.lang.Integer)
    aload 0
    getfield fb j:I
    imul
    if_icmpne L84
    iload 2
    ldc -129974993 (java.lang.Integer)
    if_icmpeq L170
    new java/lang/IllegalStateException
    dup
    invokespecial java/lang/IllegalStateException <init>:()V
    athrow
L15
    ldc 1810211167 (java.lang.Integer)
    aload 0
    getfield fb m:I
    imul
    iconst_1
    if_icmpeq L164
    iload 2
    ldc -129974993 (java.lang.Integer)
    if_icmpeq L163
    new java/lang/IllegalStateException
    dup
    invokespecial java/lang/IllegalStateException <init>:()V
    athrow
L28
    aload 1
    ldc 1639604981 (java.lang.Integer)
    invokevirtual dh z:(I)I
    istore 3
    goto L32
L165
    aload 0
    getfield fb m:I
    ldc 1810211167 (java.lang.Integer)
    imul
    iconst_5
    if_icmpeq L164
    iload 2
    ldc -129974993 (java.lang.Integer)
    if_icmpeq L180
    new java/lang/IllegalStateException
    dup
    invokespecial java/lang/IllegalStateException <init>:()V
    athrow
L180
    aload 0
    getfield fb m:I
    ldc 1810211167 (java.lang.Integer)
    imul
    bipush 6
    if_icmpne L152
    iload 2
    ldc -129974993 (java.lang.Integer)
    if_icmpeq L164
    new java/lang/IllegalStateException
    dup
    invokespecial java/lang/IllegalStateException <init>:()V
    athrow
L164
    aload 0
    aload 1
    ldc 1711787984 (java.lang.Integer)
    invokevirtual dh p:(I)Ljava/lang/String;
    putfield fb dl:Ljava/lang/String;
L181
    aload 0
    getfield fb dl:Ljava/lang/String;
    invokevirtual java/lang/String length:()I
    ifne L152
    iload 2
    ldc -129974993 (java.lang.Integer)
    if_icmpeq L182
    return
L182
    iconst_1
    ldc 1810211167 (java.lang.Integer)
    aload 0
    getfield fb m:I
    imul
    if_icmpne L107
    goto L106
L152
    iconst_1
    aload 0
    getfield fb m:I
    ldc 1810211167 (java.lang.Integer)
    imul
    if_icmpeq L183
    iload 2
    ldc -129974993 (java.lang.Integer)
    if_icmpeq L184
    new java/lang/IllegalStateException
    dup
    invokespecial java/lang/IllegalStateException <init>:()V
    athrow
L107
    ldc 1810211167 (java.lang.Integer)
    aload 0
    getfield fb m:I
    imul
    iconst_4
    if_icmpne L29
    iload 2
    ldc -129974993 (java.lang.Integer)
    if_icmpeq L185
    new java/lang/IllegalStateException
    dup
    invokespecial java/lang/IllegalStateException <init>:()V
    athrow
L185
    aload 0
    getstatic et w:Ljava/lang/String;
    putfield fb dl:Ljava/lang/String;
    goto L29
L105
    aload 1
    ldc -65206804 (java.lang.Integer)
    invokevirtual dh q:(I)I
    istore 6
    goto L58
L31
    aload 0
    getstatic et w:Ljava/lang/String;
    putfield fb dl:Ljava/lang/String;
    goto L30
L159
    aload 0
    ldc 1071127361 (java.lang.Integer)
    putfield fb aq:I
    goto L158
L119
    aload 0
    getfield fb du:[I
    iload 4
    aload 1
    ldc 1863663573 (java.lang.Integer)
    invokevirtual dh z:(I)I
    iastore
    goto L43
L6
    aload 0
    aload 1
    ldc -1589438050 (java.lang.Integer)
    invokevirtual dh q:(I)I
    ldc -788534251 (java.lang.Integer)
    imul
    putfield fb t:I
    goto L10
L184
    aload 0
    getfield fb m:I
    ldc 1810211167 (java.lang.Integer)
    imul
    iconst_4
    if_icmpeq L183
    iload 2
    ldc -129974993 (java.lang.Integer)
    if_icmpeq L186
    return
L89
    iconst_0
    goto L169
L183
    aload 0
    ldc -121487981 (java.lang.Integer)
    aload 0
    getfield fb by:I
    ldc -440702821 (java.lang.Integer)
    imul
    ldc 4194304 (java.lang.Integer)
    ior
    imul
    putfield fb by:I
L187
    bipush 6
    aload 0
    getfield fb m:I
    ldc 1810211167 (java.lang.Integer)
    imul
    if_icmpne L122
    iload 2
    ldc -129974993 (java.lang.Integer)
    if_icmpeq L121
    return
L101
    aload 0
    getfield fb j:I
    ldc -1547422441 (java.lang.Integer)
    imul
    iconst_3
    if_icmpeq L100
    iload 2
    ldc -129974993 (java.lang.Integer)
    if_icmpeq L126
    new java/lang/IllegalStateException
    dup
    invokespecial java/lang/IllegalStateException <init>:()V
    athrow
L186
    iconst_5
    aload 0
    getfield fb m:I
    ldc 1810211167 (java.lang.Integer)
    imul
    if_icmpne L187
    goto L183
L188
    new java/lang/StringBuilder
    dup
    invokespecial java/lang/StringBuilder <init>:()V
    ldc "fb.u(" (java.lang.String)
    invokevirtual java/lang/StringBuilder append:(Ljava/lang/String;)Ljava/lang/StringBuilder;
    ldc 41 (java.lang.Integer)
    invokevirtual java/lang/StringBuilder append:(C)Ljava/lang/StringBuilder;
    invokevirtual java/lang/StringBuilder toString:()Ljava/lang/String;
    invokestatic k a:(Ljava/lang/Throwable;Ljava/lang/String;)Lee;
    athrow
