fb w (Ldh;I)VL1
    aload 1
    ldc 1138652459 (java.lang.Integer)
    invokevirtual dh z:(I)I
    pop
    goto L2
L3
    aload 0
    aload 0
    aload 1
    ldc 1440067450 (java.lang.Integer)
    invokevirtual fb r:(Ldh;I)[I
    putfield fb cw:[I
    goto L4
L5
    aload 0
    aload 1
    ldc 1263921889 (java.lang.Integer)
    invokevirtual dh z:(I)I
    ldc 2113950375 (java.lang.Integer)
    imul
    putfield fb j:I
L6
    aload 0
    aload 1
    ldc -3809559 (java.lang.Integer)
    invokevirtual dh q:(I)I
    ldc -788534251 (java.lang.Integer)
    imul
    putfield fb t:I
    goto L7
L8
    aload 0
    aload 1
    ldc -1995846359 (java.lang.Integer)
    invokevirtual dh x:(I)I
    ldc 507575507 (java.lang.Integer)
    imul
    putfield fb av:I
    goto L9
L10
    aload 0
    aload 0
    aload 1
    ldc 1641498025 (java.lang.Integer)
    invokevirtual dh d:(I)I
    ldc -292842647 (java.lang.Integer)
    imul
    dup_x1
    putfield fb q:I
    ldc -1448901703 (java.lang.Integer)
    imul
    putfield fb d:I
L11
    aload 0
    aload 1
    ldc -1597650028 (java.lang.Integer)
    invokevirtual dh q:(I)I
    ldc 357890893 (java.lang.Integer)
    imul
    putfield fb b:I
    goto L12
L13
    aload 0
    aload 1
    ldc 630431386 (java.lang.Integer)
    invokevirtual dh z:(I)I
    ldc 382859101 (java.lang.Integer)
    imul
    putfield fb bu:I
    goto L14
L15
    aload 0
    aload 1
    ldc -1503864174 (java.lang.Integer)
    invokevirtual dh d:(I)I
    ldc -1659011925 (java.lang.Integer)
    imul
    putfield fb x:I
    goto L16
L17
    aload 0
    aload 1
    ldc -443441035 (java.lang.Integer)
    invokevirtual dh q:(I)I
    ldc -1659011925 (java.lang.Integer)
    imul
    putfield fb x:I
L16
    aload 0
    aload 1
    ldc 1597365275 (java.lang.Integer)
    invokevirtual dh q:(I)I
    ldc 882545019 (java.lang.Integer)
    imul
    putfield fb n:I
    goto L18
L19
    aload 0
    aload 1
    ldc -1975208060 (java.lang.Integer)
    invokevirtual dh x:(I)I
    ldc -151215191 (java.lang.Integer)
    imul
    putfield fb at:I
    goto L20
L21
    aload 0
    ldc -882545019 (java.lang.Integer)
    putfield fb n:I
    goto L22
L23
    aload 0
    ldc 882545019 (java.lang.Integer)
    ldc 952871887 (java.lang.Integer)
    aload 0
    getfield fb h:I
    imul
    ldc -65536 (java.lang.Integer)
    iand
    ldc 737715635 (java.lang.Integer)
    aload 0
    getfield fb n:I
    imul
    iadd
    imul
    putfield fb n:I
    goto L22
L24
    iconst_5
    ldc -1547422441 (java.lang.Integer)
    aload 0
    getfield fb j:I
    imul
    if_icmpne L25
    goto L8
L26
    iconst_1
    goto L27
L28
    iconst_0
L27
    putfield fb v:Z
L29
    iconst_0
    aload 0
    getfield fb j:I
    ldc -1547422441 (java.lang.Integer)
    imul
    if_icmpne L24
    iload 2
    ldc -1478722687 (java.lang.Integer)
    if_icmpgt L30
    return
L30
    aload 0
    aload 1
    ldc -1738682251 (java.lang.Integer)
    invokevirtual dh q:(I)I
    ldc 596586315 (java.lang.Integer)
    imul
    putfield fb ax:I
L31
    aload 0
    aload 1
    ldc 168893957 (java.lang.Integer)
    invokevirtual dh q:(I)I
    ldc 1564326831 (java.lang.Integer)
    imul
    putfield fb ap:I
    goto L24
L32
    aload 0
    aload 1
    ldc -2130766292 (java.lang.Integer)
    invokevirtual dh x:(I)I
    ldc -1595723647 (java.lang.Integer)
    imul
    putfield fb ao:I
    goto L33
L34
    aload 0
    ldc -270908247 (java.lang.Integer)
    putfield fb ar:I
    goto L35
L36
    aload 0
    aload 1
    ldc 1549624649 (java.lang.Integer)
    invokevirtual dh q:(I)I
    ldc -1571883189 (java.lang.Integer)
    imul
    putfield fb aa:I
    goto L37
L38
    aload 0
    aload 1
    ldc 1921015997 (java.lang.Integer)
    invokevirtual dh z:(I)I
    iconst_1
    if_icmpne L39
    iload 2
    ldc -1478722687 (java.lang.Integer)
    if_icmpgt L40
    new java/lang/IllegalStateException
    dup
    invokespecial java/lang/IllegalStateException <init>:()V
    athrow
L41
    iconst_1
    goto L42
L39
    iconst_0
L43
    putfield fb aj:Z
    goto L44
L18
    ldc 65535 (java.lang.Integer)
    ldc 737715635 (java.lang.Integer)
    aload 0
    getfield fb n:I
    imul
    if_icmpne L23
    iload 2
    ldc -1478722687 (java.lang.Integer)
    if_icmpgt L21
    new java/lang/IllegalStateException
    dup
    invokespecial java/lang/IllegalStateException <init>:()V
    athrow
L45
    aload 0
    aload 1
    ldc 822462568 (java.lang.Integer)
    invokevirtual dh z:(I)I
    ldc -353637265 (java.lang.Integer)
    imul
    putfield fb ah:I
    goto L19
L46
    iconst_0
    goto L47
L20
    aload 0
    aload 1
    ldc 1569904659 (java.lang.Integer)
    invokevirtual dh z:(I)I
    iconst_1
    if_icmpne L48
    iload 2
    ldc -1478722687 (java.lang.Integer)
    if_icmpgt L41
    new java/lang/IllegalStateException
    dup
    invokespecial java/lang/IllegalStateException <init>:()V
    athrow
L12
    bipush 9
    aload 0
    getfield fb j:I
    ldc -1547422441 (java.lang.Integer)
    imul
    if_icmpne L17
    iload 2
    ldc -1478722687 (java.lang.Integer)
    if_icmpgt L15
    new java/lang/IllegalStateException
    dup
    invokespecial java/lang/IllegalStateException <init>:()V
    athrow
L49
    aload 0
    aload 1
    ldc -1037841636 (java.lang.Integer)
    invokevirtual dh q:(I)I
    ldc 1095017279 (java.lang.Integer)
    imul
    putfield fb bk:I
    goto L50
L42
    putfield fb al:Z
L51
    aload 0
    aload 1
    ldc 869013474 (java.lang.Integer)
    invokevirtual dh z:(I)I
    iconst_1
    if_icmpne L52
    iload 2
    ldc -1478722687 (java.lang.Integer)
    if_icmpgt L53
    new java/lang/IllegalStateException
    dup
    invokespecial java/lang/IllegalStateException <init>:()V
    athrow
L54
    aload 0
    aload 0
    aload 1
    ldc -1913109915 (java.lang.Integer)
    invokevirtual fb i:(Ldh;I)[Ljava/lang/Object;
    putfield fb cy:[Ljava/lang/Object;
    goto L55
L52
    iconst_0
L56
    putfield fb ak:Z
L25
    bipush 6
    aload 0
    getfield fb j:I
    ldc -1547422441 (java.lang.Integer)
    imul
    if_icmpne L57
    iload 2
    ldc -1478722687 (java.lang.Integer)
    if_icmpgt L34
    new java/lang/IllegalStateException
    dup
    invokespecial java/lang/IllegalStateException <init>:()V
    athrow
L58
    aload 0
    aload 0
    aload 1
    ldc 647379566 (java.lang.Integer)
    invokevirtual fb i:(Ldh;I)[Ljava/lang/Object;
    putfield fb cd:[Ljava/lang/Object;
    goto L59
L35
    aload 0
    aload 1
    ldc 909826095 (java.lang.Integer)
    invokevirtual dh q:(I)I
    ldc -1071127361 (java.lang.Integer)
    imul
    putfield fb aq:I
    goto L60
L61
    aload 0
    aload 1
    ldc 893397164 (java.lang.Integer)
    invokevirtual dh z:(I)I
    iconst_1
    if_icmpne L62
    iload 2
    ldc -1478722687 (java.lang.Integer)
    if_icmpgt L63
    new java/lang/IllegalStateException
    dup
    invokespecial java/lang/IllegalStateException <init>:()V
    athrow
L64
    aload 0
    ldc 1071127361 (java.lang.Integer)
    putfield fb aq:I
L65
    aload 0
    aload 1
    ldc 387139249 (java.lang.Integer)
    invokevirtual dh d:(I)I
    ldc 103176431 (java.lang.Integer)
    imul
    putfield fb af:I
L66
    aload 0
    aload 1
    ldc 2081750516 (java.lang.Integer)
    invokevirtual dh d:(I)I
    ldc -340007389 (java.lang.Integer)
    imul
    putfield fb as:I
    goto L36
L67
    ldc -1547422441 (java.lang.Integer)
    aload 0
    getfield fb j:I
    imul
    bipush 9
    if_icmpne L68
    iload 2
    ldc -1478722687 (java.lang.Integer)
    if_icmpgt L69
    new java/lang/IllegalStateException
    dup
    invokespecial java/lang/IllegalStateException <init>:()V
    athrow
L70
    putfield fb au:Z
    goto L71
L53
    iconst_1
    goto L56
L50
    aload 0
    aload 1
    ldc -20024097 (java.lang.Integer)
    invokevirtual dh q:(I)I
    ldc 2108744207 (java.lang.Integer)
    imul
    putfield fb bm:I
L72
    aload 0
    aload 1
    ldc -1918601351 (java.lang.Integer)
    invokevirtual dh q:(I)I
    ldc -499334371 (java.lang.Integer)
    imul
    putfield fb an:I
L73
    aload 0
    getfield fb an:I
    ldc -1170991307 (java.lang.Integer)
    imul
    ldc 65535 (java.lang.Integer)
    if_icmpne L74
    iload 2
    ldc -1478722687 (java.lang.Integer)
    if_icmpgt L75
    new java/lang/IllegalStateException
    dup
    invokespecial java/lang/IllegalStateException <init>:()V
    athrow
L75
    aload 0
    ldc 499334371 (java.lang.Integer)
    putfield fb an:I
    goto L74
L47
    putfield fb bx:Z
    goto L76
L40
    iconst_1
    goto L43
L77
    iconst_0
L78
    putfield fb bp:Z
    goto L57
L79
    iconst_1
    goto L47
L80
    aload 0
    aload 1
    ldc 379446657 (java.lang.Integer)
    invokevirtual dh q:(I)I
    ldc -2031066809 (java.lang.Integer)
    imul
    putfield fb bv:I
L81
    ldc 65535 (java.lang.Integer)
    ldc 717944951 (java.lang.Integer)
    aload 0
    getfield fb bv:I
    imul
    if_icmpne L82
    iload 2
    ldc -1478722687 (java.lang.Integer)
    if_icmpgt L83
    new java/lang/IllegalStateException
    dup
    invokespecial java/lang/IllegalStateException <init>:()V
    athrow
L83
    aload 0
    ldc 2031066809 (java.lang.Integer)
    putfield fb bv:I
    goto L82
L84
    aload 0
    aload 0
    aload 1
    ldc -673367660 (java.lang.Integer)
    invokevirtual fb r:(Ldh;I)[I
    putfield fb ck:[I
    goto L3
L85
    aload 0
    aload 1
    ldc 1604318940 (java.lang.Integer)
    invokevirtual dh z:(I)I
    ldc 1596647467 (java.lang.Integer)
    imul
    putfield fb bf:I
    goto L86
L63
    iconst_1
    goto L87
L62
    iconst_0
    goto L87
L14
    aload 0
    aload 1
    ldc 1816663461 (java.lang.Integer)
    invokevirtual dh z:(I)I
    ldc -400071187 (java.lang.Integer)
    imul
    putfield fb ba:I
    goto L85
L71
    aload 0
    aload 1
    ldc 987436872 (java.lang.Integer)
    invokevirtual dh z:(I)I
    ldc 1358801527 (java.lang.Integer)
    imul
    putfield fb ae:I
    goto L67
L48
    iconst_0
    goto L42
L88
    aload 0
    aload 0
    aload 1
    ldc 371808414 (java.lang.Integer)
    invokevirtual fb i:(Ldh;I)[Ljava/lang/Object;
    putfield fb cg:[Ljava/lang/Object;
    goto L58
L76
    aload 0
    aload 1
    ldc -2060144851 (java.lang.Integer)
    invokevirtual dh x:(I)I
    ldc -1595723647 (java.lang.Integer)
    imul
    putfield fb ao:I
L89
    ldc -1547422441 (java.lang.Integer)
    aload 0
    getfield fb j:I
    imul
    iconst_3
    if_icmpne L67
    goto L32
L9
    aload 0
    aload 1
    ldc 1009485801 (java.lang.Integer)
    invokevirtual dh q:(I)I
    ldc 230911133 (java.lang.Integer)
    imul
    putfield fb ag:I
    goto L38
L33
    aload 0
    aload 1
    ldc 1799503087 (java.lang.Integer)
    invokevirtual dh z:(I)I
    iconst_1
    if_icmpne L90
    iload 2
    ldc -1478722687 (java.lang.Integer)
    if_icmpgt L91
    new java/lang/IllegalStateException
    dup
    invokespecial java/lang/IllegalStateException <init>:()V
    athrow
L82
    aload 0
    aload 1
    ldc -1264148028 (java.lang.Integer)
    invokevirtual dh p:(I)Ljava/lang/String;
    putfield fb bc:Ljava/lang/String;
    goto L13
L90
    iconst_0
    goto L70
L69
    aload 0
    aload 1
    ldc 751407287 (java.lang.Integer)
    invokevirtual dh z:(I)I
    ldc -1825489987 (java.lang.Integer)
    imul
    putfield fb ab:I
    goto L92
L4
    aload 0
    aload 0
    aload 1
    ldc -1508605093 (java.lang.Integer)
    invokevirtual fb r:(Ldh;I)[I
    putfield fb co:[I
    goto L93
L44
    aload 0
    aload 1
    ldc 1969131528 (java.lang.Integer)
    invokevirtual dh z:(I)I
    ldc 1358801527 (java.lang.Integer)
    imul
    putfield fb ae:I
    goto L45
L86
    aload 0
    aload 1
    ldc 1960080191 (java.lang.Integer)
    invokevirtual dh z:(I)I
    iconst_1
    if_icmpne L46
    goto L79
L7
    aload 0
    aload 0
    aload 1
    ldc -1565248918 (java.lang.Integer)
    invokevirtual dh d:(I)I
    ldc -36323741 (java.lang.Integer)
    imul
    dup_x1
    putfield fb z:I
    ldc -1276132747 (java.lang.Integer)
    imul
    putfield fb y:I
    goto L10
L68
    aload 0
    aload 1
    ldc -1750707672 (java.lang.Integer)
    invokevirtual dh b:(I)I
    ldc -121487981 (java.lang.Integer)
    imul
    putfield fb by:I
L94
    aload 0
    aload 1
    ldc -2113101995 (java.lang.Integer)
    invokevirtual dh p:(I)Ljava/lang/String;
    putfield fb bz:Ljava/lang/String;
L95
    aload 1
    ldc 1060387684 (java.lang.Integer)
    invokevirtual dh z:(I)I
    istore 3
L96
    iload 3
    ifle L97
    iload 2
    ldc -1478722687 (java.lang.Integer)
    if_icmpgt L98
    new java/lang/IllegalStateException
    dup
    invokespecial java/lang/IllegalStateException <init>:()V
    athrow
L98
    aload 0
    iload 3
    anewarray java/lang/String
    putfield fb bh:[Ljava/lang/String;
L99
    iconst_0
    istore 4
    goto L100
L2
    aload 0
    iconst_1
    putfield fb o:Z
    goto L5
L101
    aload 0
    getfield fb bh:[Ljava/lang/String;
    iload 4
    aload 1
    ldc -76773277 (java.lang.Integer)
    invokevirtual dh p:(I)Ljava/lang/String;
    aastore
    iinc 4 1
    goto L100
L97
    aload 0
    aload 1
    ldc 1887021437 (java.lang.Integer)
    invokevirtual dh z:(I)I
    ldc 352560981 (java.lang.Integer)
    imul
    putfield fb bs:I
L102
    aload 0
    aload 1
    ldc 833333391 (java.lang.Integer)
    invokevirtual dh z:(I)I
    ldc -1623623505 (java.lang.Integer)
    imul
    putfield fb bo:I
    goto L61
L22
    aload 0
    aload 1
    ldc 1746203193 (java.lang.Integer)
    invokevirtual dh z:(I)I
    iconst_1
    if_icmpne L28
    iload 2
    ldc -1478722687 (java.lang.Integer)
    if_icmpgt L26
    new java/lang/IllegalStateException
    dup
    invokespecial java/lang/IllegalStateException <init>:()V
    athrow
L100
    iload 4
    iload 3
    if_icmpge L97
    iload 2
    ldc -1478722687 (java.lang.Integer)
    if_icmpgt L101
    new java/lang/IllegalStateException
    dup
    invokespecial java/lang/IllegalStateException <init>:()V
    athrow
L57
    aload 0
    getfield fb j:I
    ldc -1547422441 (java.lang.Integer)
    imul
    iconst_4
    if_icmpne L89
    iload 2
    ldc -1478722687 (java.lang.Integer)
    if_icmpgt L80
    new java/lang/IllegalStateException
    dup
    invokespecial java/lang/IllegalStateException <init>:()V
    athrow
L87
    putfield fb bg:Z
L103
    aload 0
    aload 1
    ldc 76790678 (java.lang.Integer)
    invokevirtual dh p:(I)Ljava/lang/String;
    putfield fb cf:Ljava/lang/String;
L104
    aload 0
    aload 0
    aload 1
    ldc -1003407075 (java.lang.Integer)
    invokevirtual fb i:(Ldh;I)[Ljava/lang/Object;
    putfield fb cb:[Ljava/lang/Object;
L105
    aload 0
    aload 0
    aload 1
    ldc -1143520774 (java.lang.Integer)
    invokevirtual fb i:(Ldh;I)[Ljava/lang/Object;
    putfield fb cp:[Ljava/lang/Object;
L106
    aload 0
    aload 0
    aload 1
    ldc -1400311586 (java.lang.Integer)
    invokevirtual fb i:(Ldh;I)[Ljava/lang/Object;
    putfield fb cm:[Ljava/lang/Object;
L107
    aload 0
    aload 0
    aload 1
    ldc -868298664 (java.lang.Integer)
    invokevirtual fb i:(Ldh;I)[Ljava/lang/Object;
    putfield fb cx:[Ljava/lang/Object;
L108
    aload 0
    aload 0
    aload 1
    ldc -142449410 (java.lang.Integer)
    invokevirtual fb i:(Ldh;I)[Ljava/lang/Object;
    putfield fb ct:[Ljava/lang/Object;
L109
    aload 0
    aload 0
    aload 1
    ldc -1034145275 (java.lang.Integer)
    invokevirtual fb i:(Ldh;I)[Ljava/lang/Object;
    putfield fb cu:[Ljava/lang/Object;
L110
    aload 0
    aload 0
    aload 1
    ldc -1447135731 (java.lang.Integer)
    invokevirtual fb i:(Ldh;I)[Ljava/lang/Object;
    putfield fb cr:[Ljava/lang/Object;
L111
    aload 0
    aload 0
    aload 1
    ldc 942023482 (java.lang.Integer)
    invokevirtual fb i:(Ldh;I)[Ljava/lang/Object;
    putfield fb cl:[Ljava/lang/Object;
L112
    aload 0
    aload 0
    aload 1
    ldc 1439611608 (java.lang.Integer)
    invokevirtual fb i:(Ldh;I)[Ljava/lang/Object;
    putfield fb cn:[Ljava/lang/Object;
    goto L54
L37
    aload 0
    aload 1
    ldc -802371053 (java.lang.Integer)
    invokevirtual dh q:(I)I
    ldc 1003527573 (java.lang.Integer)
    imul
    putfield fb bl:I
    goto L49
L55
    aload 0
    aload 0
    aload 1
    ldc -1744498644 (java.lang.Integer)
    invokevirtual fb i:(Ldh;I)[Ljava/lang/Object;
    putfield fb ce:[Ljava/lang/Object;
L113
    aload 0
    aload 0
    aload 1
    ldc -1747525474 (java.lang.Integer)
    invokevirtual fb i:(Ldh;I)[Ljava/lang/Object;
    putfield fb cv:[Ljava/lang/Object;
L114
    aload 0
    aload 0
    aload 1
    ldc -2040236090 (java.lang.Integer)
    invokevirtual fb i:(Ldh;I)[Ljava/lang/Object;
    putfield fb ci:[Ljava/lang/Object;
    goto L88
L115
    iconst_1
    goto L78
L74
    aload 0
    aload 1
    ldc 1437098576 (java.lang.Integer)
    invokevirtual dh z:(I)I
    iconst_1
    if_icmpne L77
    iload 2
    ldc -1478722687 (java.lang.Integer)
    if_icmpgt L115
    new java/lang/IllegalStateException
    dup
    invokespecial java/lang/IllegalStateException <init>:()V
    athrow
L59
    aload 0
    aload 0
    aload 1
    ldc -1956071719 (java.lang.Integer)
    invokevirtual fb i:(Ldh;I)[Ljava/lang/Object;
    putfield fb cj:[Ljava/lang/Object;
L116
    aload 0
    aload 0
    aload 1
    ldc 1462848847 (java.lang.Integer)
    invokevirtual fb i:(Ldh;I)[Ljava/lang/Object;
    putfield fb cq:[Ljava/lang/Object;
L117
    aload 0
    aload 0
    aload 1
    ldc -1377271676 (java.lang.Integer)
    invokevirtual fb i:(Ldh;I)[Ljava/lang/Object;
    putfield fb cc:[Ljava/lang/Object;
    goto L84
L91
    iconst_1
    goto L70
L92
    aload 0
    aload 1
    ldc -2012737419 (java.lang.Integer)
    invokevirtual dh x:(I)I
    ldc -1595723647 (java.lang.Integer)
    imul
    putfield fb ao:I
    goto L68
L60
    ldc 65535 (java.lang.Integer)
    aload 0
    getfield fb aq:I
    ldc 2059766591 (java.lang.Integer)
    imul
    if_icmpne L65
    iload 2
    ldc -1478722687 (java.lang.Integer)
    if_icmpgt L64
    new java/lang/IllegalStateException
    dup
    invokespecial java/lang/IllegalStateException <init>:()V
    athrow
L93
    return
L118
    new java/lang/StringBuilder
    dup
    invokespecial java/lang/StringBuilder <init>:()V
    ldc "fb.w(" (java.lang.String)
    invokevirtual java/lang/StringBuilder append:(Ljava/lang/String;)Ljava/lang/StringBuilder;
    ldc 41 (java.lang.Integer)
    invokevirtual java/lang/StringBuilder append:(C)Ljava/lang/StringBuilder;
    invokevirtual java/lang/StringBuilder toString:()Ljava/lang/String;
    invokestatic k a:(Ljava/lang/Throwable;Ljava/lang/String;)Lee;
    athrow
