fc a (Ljava/lang/String;I)Ljava/io/File;L1
    getstatic di e:Z
    ifne L2
    iload 1
    ldc 1244342742 (java.lang.Integer)
    if_icmpeq L3
    new java/lang/IllegalStateException
    dup
    invokespecial java/lang/IllegalStateException <init>:()V
    athrow
L3
    new java/lang/RuntimeException
    dup
    ldc "" (java.lang.String)
    invokespecial java/lang/RuntimeException <init>:(Ljava/lang/String;)V
    athrow
L2
    getstatic di l:Ljava/util/Hashtable;
    aload 0
    invokevirtual java/util/Hashtable get:(Ljava/lang/Object;)Ljava/lang/Object;
    checkcast java/io/File
    astore 2
L4
    aload 2
    ifnull L5
    iload 1
    ldc 1244342742 (java.lang.Integer)
    if_icmpeq L6
    new java/lang/IllegalStateException
    dup
    invokespecial java/lang/IllegalStateException <init>:()V
    athrow
L6
    aload 2
    areturn
L5
    new java/io/File
    dup
    getstatic di a:Ljava/io/File;
    aload 0
    invokespecial java/io/File <init>:(Ljava/io/File;Ljava/lang/String;)V
    astore 3
L7
    aconst_null
    astore 4
L8
    new java/io/File
    dup
    aload 3
    invokevirtual java/io/File getParent:()Ljava/lang/String;
    invokespecial java/io/File <init>:(Ljava/lang/String;)V
    astore 5
L9
    aload 5
    invokevirtual java/io/File exists:()Z
    ifne L10
    iload 1
    ldc 1244342742 (java.lang.Integer)
    if_icmpeq L11
    new java/lang/IllegalStateException
    dup
    invokespecial java/lang/IllegalStateException <init>:()V
    athrow
L11
    new java/lang/RuntimeException
    dup
    ldc "" (java.lang.String)
    invokespecial java/lang/RuntimeException <init>:(Ljava/lang/String;)V
    athrow
L10
    new java/io/RandomAccessFile
    dup
    aload 3
    ldc "rw" (java.lang.String)
    invokespecial java/io/RandomAccessFile <init>:(Ljava/io/File;Ljava/lang/String;)V
    astore 4
L12
    aload 4
    invokevirtual java/io/RandomAccessFile read:()I
    istore 6
L13
    aload 4
    lconst_0
    invokevirtual java/io/RandomAccessFile seek:(J)V
L14
    aload 4
    iload 6
    invokevirtual java/io/RandomAccessFile write:(I)V
L15
    aload 4
    lconst_0
    invokevirtual java/io/RandomAccessFile seek:(J)V
L16
    aload 4
    invokevirtual java/io/RandomAccessFile close:()V
L17
    getstatic di l:Ljava/util/Hashtable;
    aload 0
    aload 3
    invokevirtual java/util/Hashtable put:(Ljava/lang/Object;Ljava/lang/Object;)Ljava/lang/Object;
    pop
L18
    aload 3
L19
    areturn
L20
    astore 5
L21
    aload 4
    ifnull L22
    iload 1
    ldc 1244342742 (java.lang.Integer)
    if_icmpeq L23
    new java/lang/IllegalStateException
    dup
    invokespecial java/lang/IllegalStateException <init>:()V
    athrow
L23
    aload 4
    invokevirtual java/io/RandomAccessFile close:()V
L24
    aconst_null
    astore 4
L22
    goto L25
L26
    astore 6
L25
    new java/lang/RuntimeException
    dup
    invokespecial java/lang/RuntimeException <init>:()V
    athrow
L27
    new java/lang/StringBuilder
    dup
    invokespecial java/lang/StringBuilder <init>:()V
    ldc "fc.a(" (java.lang.String)
    invokevirtual java/lang/StringBuilder append:(Ljava/lang/String;)Ljava/lang/StringBuilder;
    ldc 41 (java.lang.Integer)
    invokevirtual java/lang/StringBuilder append:(C)Ljava/lang/StringBuilder;
    invokevirtual java/lang/StringBuilder toString:()Ljava/lang/String;
    invokestatic k a:(Ljava/lang/Throwable;Ljava/lang/String;)Lee;
    athrow
