fd dm (Ljava/lang/String;I)VL1
    aload 0
    ldc "" (java.lang.String)
    invokevirtual java/lang/String equals:(Ljava/lang/Object;)Z
    ifeq L2
    iload 1
    ldc 369385702 (java.lang.Integer)
    if_icmpgt L3
    new java/lang/IllegalStateException
    dup
    invokespecial java/lang/IllegalStateException <init>:()V
    athrow
L4
    getstatic client cd:Ldj;
    astore 2
    goto L5
L2
    getstatic client cd:Ldj;
    sipush 168
    ldc 173777121 (java.lang.Integer)
    invokevirtual dj hl:(II)V
    goto L4
L6
    getstatic client cd:Ldj;
    aload 0
    sipush 502
    invokevirtual dj i:(Ljava/lang/String;S)V
    goto L7
L5
    aload 0
    invokevirtual java/lang/String length:()I
    iconst_1
    iadd
    istore 3
L8
    aload 2
    iload 3
    bipush 109
    invokevirtual dj e:(IB)V
    goto L6
L3
    return
L7
    return
L9
    new java/lang/StringBuilder
    dup
    invokespecial java/lang/StringBuilder <init>:()V
    ldc "fd.dm(" (java.lang.String)
    invokevirtual java/lang/StringBuilder append:(Ljava/lang/String;)Ljava/lang/StringBuilder;
    ldc 41 (java.lang.Integer)
    invokevirtual java/lang/StringBuilder append:(C)Ljava/lang/StringBuilder;
    invokevirtual java/lang/StringBuilder toString:()Ljava/lang/String;
    invokestatic k a:(Ljava/lang/Throwable;Ljava/lang/String;)Lee;
    athrow
