ff at (Lfm;B)IL1
    ldc -97158933 (java.lang.Integer)
    aload 1
    getfield fm f:I
    imul
    ldc 1382214807 (java.lang.Integer)
    aload 1
    getfield fm o:I
    imul
    ldc -1472820627 (java.lang.Integer)
    aload 1
    getfield fm g:I
    imul
    imul
    bipush 12
    ishr
    iadd
    istore 3
    goto L2
L3
    iload 5
    iconst_1
    if_icmpge L4
    iload 2
    bipush 16
    if_icmpeq L5
    new java/lang/IllegalStateException
    dup
    invokespecial java/lang/IllegalStateException <init>:()V
    athrow
L6
    aload 1
    getfield fm c:Lfd;
    astore 4
L7
    ldc 746263661 (java.lang.Integer)
    aload 4
    getfield fd r:I
    imul
    ifle L8
    aload 4
    getfield fd i:I
    ldc 912853581 (java.lang.Integer)
    imul
    ifgt L9
    iload 2
    bipush 16
    if_icmpeq L10
    new java/lang/IllegalStateException
    dup
    invokespecial java/lang/IllegalStateException <init>:()V
    athrow
L9
    ldc 912853581 (java.lang.Integer)
    aload 4
    getfield fd i:I
    imul
    iconst_2
    ishl
    istore 5
    goto L11
L8
    aload 1
    getfield fm l:Lbe;
    getfield be e:I
    sipush 256
    imul
    i2d
    ldc 2.0 (java.lang.Double)
    iload 3
    i2d
    ldc 3.255208333333333E-4 (java.lang.Double)
    dmul
    invokestatic java/lang/Math pow:(DD)D
    dmul
    getstatic aa l:I
    ldc -279793531 (java.lang.Integer)
    imul
    i2d
    ddiv
    ldc 0.5 (java.lang.Double)
    dadd
    d2i
    istore 5
    goto L3
L11
    ldc 1776705329 (java.lang.Integer)
    aload 4
    getfield fd f:I
    imul
    iconst_1
    ishl
    istore 6
L12
    ldc 1265315807 (java.lang.Integer)
    aload 1
    getfield fm z:I
    imul
    iload 6
    if_icmpge L13
    iload 2
    bipush 16
    if_icmpeq L14
    new java/lang/IllegalStateException
    dup
    invokespecial java/lang/IllegalStateException <init>:()V
    athrow
L10
    aload 0
    getfield ff h:[I
    ldc -980254659 (java.lang.Integer)
    aload 1
    getfield fm e:I
    imul
    iaload
    ifle L8
    iload 2
    bipush 16
    if_icmpeq L9
    new java/lang/IllegalStateException
    dup
    invokespecial java/lang/IllegalStateException <init>:()V
    athrow
L13
    iload 5
    aload 0
    getfield ff h:[I
    aload 1
    getfield fm e:I
    ldc -980254659 (java.lang.Integer)
    imul
    iaload
    bipush 7
    ishr
    iadd
    istore 5
L15
    ldc 0.01227184630308513 (java.lang.Double)
    aload 1
    getfield fm y:I
    ldc -904051777 (java.lang.Integer)
    imul
    sipush 511
    iand
    i2d
    dmul
    invokestatic java/lang/Math sin:(D)D
    dstore 7
L16
    iload 3
    iload 5
    i2d
    dload 7
    dmul
    d2i
    iadd
    istore 3
    goto L8
L14
    ldc 1265315807 (java.lang.Integer)
    aload 1
    getfield fm z:I
    imul
    iload 5
    imul
    iload 6
    idiv
    istore 5
    goto L13
L2
    iload 3
    aload 0
    getfield ff o:[I
    aload 1
    getfield fm e:I
    ldc -980254659 (java.lang.Integer)
    imul
    iaload
    sipush 8192
    isub
    aload 0
    getfield ff x:[I
    ldc -980254659 (java.lang.Integer)
    aload 1
    getfield fm e:I
    imul
    iaload
    imul
    bipush 12
    ishr
    iadd
    istore 3
    goto L6
L5
    iconst_1
    goto L17
L4
    iload 5
L17
    ireturn
L18
    new java/lang/StringBuilder
    dup
    invokespecial java/lang/StringBuilder <init>:()V
    ldc "ff.at(" (java.lang.String)
    invokevirtual java/lang/StringBuilder append:(Ljava/lang/String;)Ljava/lang/StringBuilder;
    ldc 41 (java.lang.Integer)
    invokevirtual java/lang/StringBuilder append:(C)Ljava/lang/StringBuilder;
    invokevirtual java/lang/StringBuilder toString:()Ljava/lang/String;
    invokestatic k a:(Ljava/lang/Throwable;Ljava/lang/String;)Lee;
    athrow
