ff aw (II)VL1
    iload 1
    ifge L2
    iload 2
    ldc -645116522 (java.lang.Integer)
    if_icmpgt L3
    return
L4
    aload 0
    iload 1
    ldc -1410994146 (java.lang.Integer)
    invokevirtual ff ae:(II)V
    goto L5
L6
    aload 0
    getfield ff s:[I
    iload 1
    sipush 8192
    iastore
    goto L4
L3
    iconst_0
    istore 1
    goto L7
L8
    return
L2
    aload 0
    getfield ff c:[I
    iload 1
    sipush 12800
    iastore
L9
    aload 0
    getfield ff u:[I
    iload 1
    sipush 8192
    iastore
L10
    aload 0
    getfield ff i:[I
    iload 1
    sipush 16383
    iastore
L11
    aload 0
    getfield ff o:[I
    iload 1
    sipush 8192
    iastore
L12
    aload 0
    getfield ff h:[I
    iload 1
    iconst_0
    iastore
    goto L6
L13
    aload 0
    iload 1
    sipush 8192
    ldc -1670604361 (java.lang.Integer)
    invokevirtual ff ah:(III)V
L14
    return
L15
    aload 0
    iload 1
    ldc 460359425 (java.lang.Integer)
    invokevirtual ff aw:(II)V
    iinc 1 1
    goto L7
L5
    aload 0
    iload 1
    bipush 7
    invokevirtual ff ag:(IB)V
    goto L16
L17
    aload 0
    getfield ff b:[I
    iload 1
    sipush 32767
    iastore
L18
    aload 0
    getfield ff x:[I
    iload 1
    sipush 256
    iastore
L19
    aload 0
    getfield ff n:[I
    iload 1
    iconst_0
    iastore
    goto L13
L7
    iload 1
    bipush 16
    if_icmpge L8
    iload 2
    ldc -645116522 (java.lang.Integer)
    if_icmpgt L15
    new java/lang/IllegalStateException
    dup
    invokespecial java/lang/IllegalStateException <init>:()V
    athrow
L16
    aload 0
    getfield ff d:[I
    iload 1
    iconst_0
    iastore
    goto L17
L20
    new java/lang/StringBuilder
    dup
    invokespecial java/lang/StringBuilder <init>:()V
    ldc "ff.aw(" (java.lang.String)
    invokevirtual java/lang/StringBuilder append:(Ljava/lang/String;)Ljava/lang/StringBuilder;
    ldc 41 (java.lang.Integer)
    invokevirtual java/lang/StringBuilder append:(C)Ljava/lang/StringBuilder;
    invokevirtual java/lang/StringBuilder toString:()Ljava/lang/String;
    invokestatic k a:(Ljava/lang/Throwable;Ljava/lang/String;)Lee;
    athrow
