ff ac (Lfm;[IIIB)ZL1
    aload 1
    ldc 234438059 (java.lang.Integer)
    getstatic aa l:I
    ldc -279793531 (java.lang.Integer)
    imul
    bipush 100
    idiv
    imul
    putfield fm d:I
L2
    aload 1
    getfield fm m:I
    ldc 1106072977 (java.lang.Integer)
    imul
    iflt L3
    goto L4
L5
    ldc -1933199925 (java.lang.Integer)
    aload 7
    getfield fd w:I
    imul
    ifle L6
    iload 5
    iconst_2
    if_icmplt L7
    new java/lang/IllegalStateException
    dup
    invokespecial java/lang/IllegalStateException <init>:()V
    athrow
L8
    aload 1
    getfield fm q:Lbc;
    invokevirtual bc am:()Z
    ifeq L3
    iload 5
    iconst_2
    if_icmplt L9
    new java/lang/IllegalStateException
    dup
    invokespecial java/lang/IllegalStateException <init>:()V
    athrow
L10
    aload 1
    dup
    getfield fm z:I
    ldc -502182881 (java.lang.Integer)
    iadd
    putfield fm z:I
    goto L11
L12
    aload 1
    invokevirtual fm if:()V
L13
    aload 1
    getfield fm u:I
    ldc 2076852313 (java.lang.Integer)
    imul
    ifle L14
    iload 5
    iconst_2
    if_icmplt L15
    new java/lang/IllegalStateException
    dup
    invokespecial java/lang/IllegalStateException <init>:()V
    athrow
L15
    aload 1
    aload 0
    getfield ff ax:[[Lfm;
    aload 1
    getfield fm e:I
    ldc -980254659 (java.lang.Integer)
    imul
    aaload
    ldc 2076852313 (java.lang.Integer)
    aload 1
    getfield fm u:I
    imul
    aaload
    if_acmpne L14
    iload 5
    iconst_2
    if_icmplt L16
    new java/lang/IllegalStateException
    dup
    invokespecial java/lang/IllegalStateException <init>:()V
    athrow
L17
    iconst_1
    ireturn
L9
    aload 1
    ldc -330792047 (java.lang.Integer)
    invokevirtual fm e:(I)V
    goto L12
L3
    aload 1
    getfield fm o:I
    ldc 1382214807 (java.lang.Integer)
    imul
    istore 6
L18
    iload 6
    ifle L19
    iload 5
    iconst_2
    if_icmplt L20
    new java/lang/IllegalStateException
    dup
    invokespecial java/lang/IllegalStateException <init>:()V
    athrow
L20
    iload 6
    ldc 16.0 (java.lang.Double)
    ldc 2.0 (java.lang.Double)
    aload 0
    getfield ff s:[I
    ldc -980254659 (java.lang.Integer)
    aload 1
    getfield fm e:I
    imul
    iaload
    i2d
    ldc 4.921259842519685E-4 (java.lang.Double)
    dmul
    invokestatic java/lang/Math pow:(DD)D
    dmul
    ldc 0.5 (java.lang.Double)
    dadd
    d2i
    isub
    istore 6
L21
    iload 6
    ifge L22
    iload 5
    iconst_2
    if_icmplt L23
    new java/lang/IllegalStateException
    dup
    invokespecial java/lang/IllegalStateException <init>:()V
    athrow
L23
    iconst_0
    istore 6
L22
    aload 1
    iload 6
    ldc 598692647 (java.lang.Integer)
    imul
    putfield fm o:I
    goto L19
L4
    aconst_null
    aload 1
    getfield fm q:Lbc;
    if_acmpeq L9
    goto L8
L24
    aload 7
    getfield fd e:[B
    ifnull L25
    iload 5
    iconst_2
    if_icmplt L26
    new java/lang/IllegalStateException
    dup
    invokespecial java/lang/IllegalStateException <init>:()V
    athrow
L11
    aload 1
    dup
    getfield fm y:I
    ldc -1973730605 (java.lang.Integer)
    aload 7
    getfield fd r:I
    imul
    iadd
    putfield fm y:I
    goto L27
L16
    aload 0
    getfield ff ax:[[Lfm;
    ldc -980254659 (java.lang.Integer)
    aload 1
    getfield fm e:I
    imul
    aaload
    aload 1
    getfield fm u:I
    ldc 2076852313 (java.lang.Integer)
    imul
    aconst_null
    aastore
    goto L14
L28
    aload 1
    getfield fm m:I
    ldc 1106072977 (java.lang.Integer)
    imul
    aload 7
    getfield fd a:[B
    ldc -381223443 (java.lang.Integer)
    aload 1
    getfield fm t:I
    imul
    iconst_2
    iadd
    baload
    sipush 255
    iand
    bipush 8
    ishl
    if_icmple L29
    goto L30
L27
    ldc 5.086263020833333E-6 (java.lang.Double)
    aload 1
    getfield fm w:I
    ldc 1336712917 (java.lang.Integer)
    imul
    bipush 60
    isub
    bipush 8
    ishl
    ldc 1382214807 (java.lang.Integer)
    aload 1
    getfield fm o:I
    imul
    ldc -1472820627 (java.lang.Integer)
    aload 1
    getfield fm g:I
    imul
    imul
    bipush 12
    ishr
    iadd
    i2d
    dmul
    dstore 9
L31
    aload 7
    getfield fd l:I
    ldc 666362741 (java.lang.Integer)
    imul
    ifle L24
    iload 5
    iconst_2
    if_icmplt L5
    new java/lang/IllegalStateException
    dup
    invokespecial java/lang/IllegalStateException <init>:()V
    athrow
L14
    iconst_1
    ireturn
L7
    aload 1
    dup
    getfield fm h:I
    ldc 128.0 (java.lang.Double)
    ldc 2.0 (java.lang.Double)
    dload 9
    ldc -1933199925 (java.lang.Integer)
    aload 7
    getfield fd w:I
    imul
    i2d
    dmul
    invokestatic java/lang/Math pow:(DD)D
    dmul
    ldc 0.5 (java.lang.Double)
    dadd
    d2i
    ldc 228038385 (java.lang.Integer)
    imul
    iadd
    putfield fm h:I
    goto L24
L6
    aload 1
    dup
    getfield fm h:I
    ldc -875857792 (java.lang.Integer)
    iadd
    putfield fm h:I
    goto L24
L19
    aload 1
    getfield fm q:Lbc;
    aload 0
    aload 1
    bipush 16
    invokevirtual ff at:(Lfm;B)I
    invokevirtual bc n:(I)V
    goto L32
L29
    aload 1
    getfield fm t:I
    ldc -381223443 (java.lang.Integer)
    imul
    aload 7
    getfield fd a:[B
    arraylength
    iconst_2
    isub
    if_icmpne L33
    iload 5
    iconst_2
    if_icmplt L34
    new java/lang/IllegalStateException
    dup
    invokespecial java/lang/IllegalStateException <init>:()V
    athrow
L35
    aload 1
    dup
    getfield fm s:I
    ldc 128.0 (java.lang.Double)
    ldc 2.0 (java.lang.Double)
    aload 7
    getfield fd c:I
    ldc 1519255705 (java.lang.Integer)
    imul
    i2d
    dload 9
    dmul
    invokestatic java/lang/Math pow:(DD)D
    dmul
    ldc 0.5 (java.lang.Double)
    dadd
    d2i
    ldc 804980981 (java.lang.Integer)
    imul
    iadd
    putfield fm s:I
    goto L36
L37
    ldc -381223443 (java.lang.Integer)
    aload 1
    getfield fm t:I
    imul
    aload 7
    getfield fd a:[B
    arraylength
    iconst_2
    isub
    if_icmpge L29
    iload 5
    iconst_2
    if_icmplt L28
    new java/lang/IllegalStateException
    dup
    invokespecial java/lang/IllegalStateException <init>:()V
    athrow
L36
    aload 1
    getfield fm j:I
    ldc -1347701651 (java.lang.Integer)
    imul
    aload 7
    getfield fd e:[B
    arraylength
    iconst_2
    isub
    if_icmpge L38
    ldc 765158237 (java.lang.Integer)
    aload 1
    getfield fm s:I
    imul
    aload 7
    getfield fd e:[B
    ldc -1347701651 (java.lang.Integer)
    aload 1
    getfield fm j:I
    imul
    iconst_2
    iadd
    baload
    sipush 255
    iand
    bipush 8
    ishl
    if_icmple L38
    iload 5
    iconst_2
    if_icmplt L39
    new java/lang/IllegalStateException
    dup
    invokespecial java/lang/IllegalStateException <init>:()V
    athrow
L39
    aload 1
    dup
    getfield fm j:I
    ldc 2130242250 (java.lang.Integer)
    iadd
    putfield fm j:I
    goto L36
L40
    aload 1
    dup
    getfield fm m:I
    ldc 1208334464 (java.lang.Integer)
    iadd
    putfield fm m:I
    goto L37
L38
    ldc -1347701651 (java.lang.Integer)
    aload 1
    getfield fm j:I
    imul
    aload 7
    getfield fd e:[B
    arraylength
    iconst_2
    isub
    if_icmpne L25
    iload 5
    iconst_2
    if_icmplt L41
    new java/lang/IllegalStateException
    dup
    invokespecial java/lang/IllegalStateException <init>:()V
    athrow
L42
    iconst_1
    istore 8
L25
    aload 1
    getfield fm m:I
    ldc 1106072977 (java.lang.Integer)
    imul
    iflt L33
    aconst_null
    aload 7
    getfield fd a:[B
    if_acmpeq L33
    iload 5
    iconst_2
    if_icmplt L43
    new java/lang/IllegalStateException
    dup
    invokespecial java/lang/IllegalStateException <init>:()V
    athrow
L43
    aload 0
    getfield ff d:[I
    aload 1
    getfield fm e:I
    ldc -980254659 (java.lang.Integer)
    imul
    iaload
    iconst_1
    iand
    ifne L33
    iload 5
    iconst_2
    if_icmplt L44
    new java/lang/IllegalStateException
    dup
    invokespecial java/lang/IllegalStateException <init>:()V
    athrow
L44
    ldc 2076852313 (java.lang.Integer)
    aload 1
    getfield fm u:I
    imul
    iflt L45
    iload 5
    iconst_2
    if_icmplt L46
    new java/lang/IllegalStateException
    dup
    invokespecial java/lang/IllegalStateException <init>:()V
    athrow
L47
    aload 1
    getfield fm q:Lbc;
    aload 2
    iload 3
    iload 4
    invokevirtual bc f:([III)V
    goto L48
L45
    aload 7
    getfield fd u:I
    ldc -1865527775 (java.lang.Integer)
    imul
    ifle L40
    iload 5
    iconst_2
    if_icmplt L49
    new java/lang/IllegalStateException
    dup
    invokespecial java/lang/IllegalStateException <init>:()V
    athrow
L49
    aload 1
    dup
    getfield fm m:I
    ldc 128.0 (java.lang.Double)
    ldc 2.0 (java.lang.Double)
    ldc -1865527775 (java.lang.Integer)
    aload 7
    getfield fd u:I
    imul
    i2d
    dload 9
    dmul
    invokestatic java/lang/Math pow:(DD)D
    dmul
    ldc 0.5 (java.lang.Double)
    dadd
    d2i
    ldc 1922042737 (java.lang.Integer)
    imul
    iadd
    putfield fm m:I
    goto L37
L32
    aload 1
    getfield fm c:Lfd;
    astore 7
L50
    iconst_0
    istore 8
    goto L10
L51
    aload 1
    dup
    getfield fm s:I
    ldc -41649536 (java.lang.Integer)
    iadd
    putfield fm s:I
    goto L36
L30
    aload 1
    dup
    getfield fm t:I
    ldc -198324278 (java.lang.Integer)
    iadd
    putfield fm t:I
    goto L37
L46
    aload 0
    getfield ff ax:[[Lfm;
    aload 1
    getfield fm e:I
    ldc -980254659 (java.lang.Integer)
    imul
    aaload
    ldc 2076852313 (java.lang.Integer)
    aload 1
    getfield fm u:I
    imul
    aaload
    aload 1
    if_acmpeq L33
    goto L45
L34
    iconst_1
    istore 8
L33
    iload 8
    ifeq L52
    iload 5
    iconst_2
    if_icmplt L53
    new java/lang/IllegalStateException
    dup
    invokespecial java/lang/IllegalStateException <init>:()V
    athrow
L54
    aload 1
    getfield fm m:I
    ldc 1106072977 (java.lang.Integer)
    imul
    iflt L17
    iload 5
    iconst_2
    if_icmplt L55
    new java/lang/IllegalStateException
    dup
    invokespecial java/lang/IllegalStateException <init>:()V
    athrow
L56
    aload 2
    ifnull L57
    goto L47
L53
    aload 1
    getfield fm q:Lbc;
    ldc 1246745859 (java.lang.Integer)
    aload 1
    getfield fm d:I
    imul
    invokevirtual bc x:(I)V
    goto L56
L57
    aload 1
    getfield fm q:Lbc;
    iload 4
    invokevirtual bc o:(I)V
L48
    aload 1
    getfield fm q:Lbc;
    invokevirtual bc au:()Z
    ifeq L58
    iload 5
    iconst_2
    if_icmplt L59
    new java/lang/IllegalStateException
    dup
    invokespecial java/lang/IllegalStateException <init>:()V
    athrow
L59
    aload 0
    getfield ff ae:Lfr;
    getfield fr l:Las;
    aload 1
    getfield fm q:Lbc;
    invokevirtual as e:(Lbu;)V
L58
    aload 1
    ldc -330792047 (java.lang.Integer)
    invokevirtual fm e:(I)V
    goto L54
L41
    aload 7
    getfield fd e:[B
    aload 1
    getfield fm j:I
    ldc -1347701651 (java.lang.Integer)
    imul
    iconst_1
    iadd
    baload
    ifne L25
    iload 5
    iconst_2
    if_icmplt L42
    new java/lang/IllegalStateException
    dup
    invokespecial java/lang/IllegalStateException <init>:()V
    athrow
L55
    aload 1
    invokevirtual fm if:()V
L60
    ldc 2076852313 (java.lang.Integer)
    aload 1
    getfield fm u:I
    imul
    ifle L17
    iload 5
    iconst_2
    if_icmplt L61
    new java/lang/IllegalStateException
    dup
    invokespecial java/lang/IllegalStateException <init>:()V
    athrow
L61
    aload 1
    aload 0
    getfield ff ax:[[Lfm;
    ldc -980254659 (java.lang.Integer)
    aload 1
    getfield fm e:I
    imul
    aaload
    aload 1
    getfield fm u:I
    ldc 2076852313 (java.lang.Integer)
    imul
    aaload
    if_acmpne L17
    iload 5
    iconst_2
    if_icmplt L62
    new java/lang/IllegalStateException
    dup
    invokespecial java/lang/IllegalStateException <init>:()V
    athrow
L62
    aload 0
    getfield ff ax:[[Lfm;
    aload 1
    getfield fm e:I
    ldc -980254659 (java.lang.Integer)
    imul
    aaload
    aload 1
    getfield fm u:I
    ldc 2076852313 (java.lang.Integer)
    imul
    aconst_null
    aastore
    goto L17
L26
    aload 7
    getfield fd c:I
    ldc 1519255705 (java.lang.Integer)
    imul
    ifle L51
    iload 5
    iconst_2
    if_icmplt L35
    new java/lang/IllegalStateException
    dup
    invokespecial java/lang/IllegalStateException <init>:()V
    athrow
L52
    aload 1
    getfield fm q:Lbc;
    ldc 1246745859 (java.lang.Integer)
    aload 1
    getfield fm d:I
    imul
    aload 0
    aload 1
    ldc -1267605373 (java.lang.Integer)
    invokevirtual ff al:(Lfm;I)I
    aload 0
    aload 1
    ldc 1347155097 (java.lang.Integer)
    invokevirtual ff ak:(Lfm;I)I
    invokevirtual bc b:(III)V
L63
    iconst_0
    ireturn
L64
    new java/lang/StringBuilder
    dup
    invokespecial java/lang/StringBuilder <init>:()V
    ldc "ff.ac(" (java.lang.String)
    invokevirtual java/lang/StringBuilder append:(Ljava/lang/String;)Ljava/lang/StringBuilder;
    ldc 41 (java.lang.Integer)
    invokevirtual java/lang/StringBuilder append:(C)Ljava/lang/StringBuilder;
    invokevirtual java/lang/StringBuilder toString:()Ljava/lang/String;
    invokestatic k a:(Ljava/lang/Throwable;Ljava/lang/String;)Lee;
    athrow
