ff l (Lfw;Lfv;Lbm;II)ZL1
    aload 1
    invokevirtual fw a:()V
    goto L2
L3
    aconst_null
    aload 10
    if_acmpne L4
    iload 5
    ldc -66708875 (java.lang.Integer)
    if_icmpne L5
    new java/lang/IllegalStateException
    dup
    invokespecial java/lang/IllegalStateException <init>:()V
    athrow
L6
    aconst_null
    astore 7
    goto L7
L8
    aload 0
    getfield ff e:Lgf;
    iload 9
    i2l
    invokevirtual gf e:(J)Lgm;
    checkcast fh
    astore 10
    goto L3
L9
    iconst_1
    newarray 10
    dup
    iconst_0
    iload 4
    iastore
    astore 7
    goto L10
L11
    aload 10
    ifnonnull L12
    iload 5
    ldc -66708875 (java.lang.Integer)
    if_icmpne L13
    new java/lang/IllegalStateException
    dup
    invokespecial java/lang/IllegalStateException <init>:()V
    athrow
L14
    aload 8
    ifnull L15
    iload 5
    ldc -66708875 (java.lang.Integer)
    if_icmpne L16
    new java/lang/IllegalStateException
    dup
    invokespecial java/lang/IllegalStateException <init>:()V
    athrow
L2
    iconst_1
    istore 6
    goto L6
L16
    aload 8
    getfield go ec:J
    l2i
    istore 9
    goto L8
L10
    aload 1
    getfield fw e:Lgf;
    invokevirtual gf c:()Lgm;
    checkcast go
    astore 8
    goto L14
L5
    aload 2
    iload 9
    ldc 1156140973 (java.lang.Integer)
    invokestatic df e:(Lfv;II)Lfh;
    astore 10
    goto L11
L7
    iload 4
    ifle L10
    iload 5
    ldc -66708875 (java.lang.Integer)
    if_icmpne L9
    new java/lang/IllegalStateException
    dup
    invokespecial java/lang/IllegalStateException <init>:()V
    athrow
L13
    iconst_0
    istore 6
L17
    goto L18
L12
    aload 0
    getfield ff e:Lgf;
    aload 10
    iload 9
    i2l
    invokevirtual gf a:(Lgm;J)V
L4
    aload 10
    aload 3
    aload 8
    getfield go e:[B
    aload 7
    bipush 9
    invokevirtual fh a:(Lbm;[B[IB)Z
    ifne L18
    iload 5
    ldc -66708875 (java.lang.Integer)
    if_icmpne L19
    new java/lang/IllegalStateException
    dup
    invokespecial java/lang/IllegalStateException <init>:()V
    athrow
L20
    iload 6
    ireturn
L18
    aload 1
    getfield fw e:Lgf;
    invokevirtual gf u:()Lgm;
    checkcast go
    astore 8
    goto L14
L19
    iconst_0
    istore 6
    goto L18
L21
    aload 1
    invokevirtual fw l:()V
    goto L20
L15
    iload 6
    ifeq L20
    iload 5
    ldc -66708875 (java.lang.Integer)
    if_icmpne L21
    new java/lang/IllegalStateException
    dup
    invokespecial java/lang/IllegalStateException <init>:()V
    athrow
L22
    new java/lang/StringBuilder
    dup
    invokespecial java/lang/StringBuilder <init>:()V
    ldc "ff.l(" (java.lang.String)
    invokevirtual java/lang/StringBuilder append:(Ljava/lang/String;)Ljava/lang/StringBuilder;
    ldc 41 (java.lang.Integer)
    invokevirtual java/lang/StringBuilder append:(C)Ljava/lang/StringBuilder;
    invokevirtual java/lang/StringBuilder toString:()Ljava/lang/String;
    invokestatic k a:(Ljava/lang/Throwable;Ljava/lang/String;)Lee;
    athrow
