ff n (II)VL1
    aload 0
    getfield ff ae:Lfr;
    getfield fr a:Lgh;
    invokevirtual gh i:()Lgm;
    checkcast fm
    astore 3
    goto L2
L3
    aload 3
    getfield fm q:Lbc;
    getstatic aa l:I
    ldc -279793531 (java.lang.Integer)
    imul
    bipush 100
    idiv
    invokevirtual bc x:(I)V
    goto L4
L5
    iload 1
    iflt L6
    iload 2
    ldc -494234791 (java.lang.Integer)
    if_icmpne L7
    new java/lang/IllegalStateException
    dup
    invokespecial java/lang/IllegalStateException <init>:()V
    athrow
L6
    aload 3
    getfield fm q:Lbc;
    ifnull L8
    iload 2
    ldc -494234791 (java.lang.Integer)
    if_icmpne L3
    return
L9
    aload 3
    ldc -330792047 (java.lang.Integer)
    invokevirtual fm e:(I)V
    goto L8
L4
    aload 3
    getfield fm q:Lbc;
    invokevirtual bc au:()Z
    ifeq L9
    goto L10
L7
    aload 3
    getfield fm e:I
    ldc -980254659 (java.lang.Integer)
    imul
    iload 1
    if_icmpne L11
    iload 2
    ldc -494234791 (java.lang.Integer)
    if_icmpne L6
    return
L2
    aconst_null
    aload 3
    if_acmpeq L12
    iload 2
    ldc -494234791 (java.lang.Integer)
    if_icmpne L5
    return
L13
    aload 3
    invokevirtual fm if:()V
    goto L11
L8
    ldc 1106072977 (java.lang.Integer)
    aload 3
    getfield fm m:I
    imul
    ifge L13
    iload 2
    ldc -494234791 (java.lang.Integer)
    if_icmpne L14
    new java/lang/IllegalStateException
    dup
    invokespecial java/lang/IllegalStateException <init>:()V
    athrow
L14
    aload 0
    getfield ff k:[[Lfm;
    ldc -980254659 (java.lang.Integer)
    aload 3
    getfield fm e:I
    imul
    aaload
    aload 3
    getfield fm w:I
    ldc 1336712917 (java.lang.Integer)
    imul
    aconst_null
    aastore
    goto L13
L10
    aload 0
    getfield ff ae:Lfr;
    getfield fr l:Las;
    aload 3
    getfield fm q:Lbc;
    invokevirtual as e:(Lbu;)V
    goto L9
L11
    aload 0
    getfield ff ae:Lfr;
    getfield fr a:Lgh;
    invokevirtual gh f:()Lgm;
    checkcast fm
    astore 3
    goto L2
L12
    return
L15
    new java/lang/StringBuilder
    dup
    invokespecial java/lang/StringBuilder <init>:()V
    ldc "ff.n(" (java.lang.String)
    invokevirtual java/lang/StringBuilder append:(Ljava/lang/String;)Ljava/lang/StringBuilder;
    ldc 41 (java.lang.Integer)
    invokevirtual java/lang/StringBuilder append:(C)Ljava/lang/StringBuilder;
    invokevirtual java/lang/StringBuilder toString:()Ljava/lang/String;
    invokestatic k a:(Ljava/lang/Throwable;Ljava/lang/String;)Lee;
    athrow
