ff q (IIII)VL1
    aload 0
    getfield ff k:[[Lfm;
    iload 1
    aaload
    iload 2
    aaload
    astore 5
    goto L2
L3
    goto L4
L5
    aload 0
    getfield ff k:[[Lfm;
    iload 1
    aaload
    iload 2
    aconst_null
    aastore
    goto L6
L4
    return
L6
    iconst_0
    aload 0
    getfield ff d:[I
    iload 1
    iaload
    iconst_2
    iand
    if_icmpeq L7
    iload 4
    ldc 1945812580 (java.lang.Integer)
    if_icmpne L8
    return
L8
    aload 0
    getfield ff ae:Lfr;
    getfield fr a:Lgh;
    invokevirtual gh i:()Lgm;
    checkcast fm
    astore 6
L9
    aload 6
    ifnull L3
    iload 4
    ldc 1945812580 (java.lang.Integer)
    if_icmpne L10
    new java/lang/IllegalStateException
    dup
    invokespecial java/lang/IllegalStateException <init>:()V
    athrow
L10
    aload 5
    getfield fm e:I
    ldc -980254659 (java.lang.Integer)
    imul
    aload 6
    getfield fm e:I
    ldc -980254659 (java.lang.Integer)
    imul
    if_icmpne L11
    ldc 1106072977 (java.lang.Integer)
    aload 6
    getfield fm m:I
    imul
    ifge L11
    iload 4
    ldc 1945812580 (java.lang.Integer)
    if_icmpne L12
    new java/lang/IllegalStateException
    dup
    invokespecial java/lang/IllegalStateException <init>:()V
    athrow
L12
    aload 6
    aload 5
    if_acmpeq L11
    iload 4
    ldc 1945812580 (java.lang.Integer)
    if_icmpne L13
    new java/lang/IllegalStateException
    dup
    invokespecial java/lang/IllegalStateException <init>:()V
    athrow
L13
    aload 5
    iconst_0
    putfield fm m:I
L14
    goto L3
L11
    aload 0
    getfield ff ae:Lfr;
    getfield fr a:Lgh;
    invokevirtual gh f:()Lgm;
    checkcast fm
    astore 6
    goto L9
L15
    return
L7
    aload 5
    iconst_0
    putfield fm m:I
    goto L4
L2
    aload 5
    ifnonnull L5
    iload 4
    ldc 1945812580 (java.lang.Integer)
    if_icmpne L15
    return
L16
    new java/lang/StringBuilder
    dup
    invokespecial java/lang/StringBuilder <init>:()V
    ldc "ff.q(" (java.lang.String)
    invokevirtual java/lang/StringBuilder append:(Ljava/lang/String;)Ljava/lang/StringBuilder;
    ldc 41 (java.lang.Integer)
    invokevirtual java/lang/StringBuilder append:(C)Ljava/lang/StringBuilder;
    invokevirtual java/lang/StringBuilder toString:()Ljava/lang/String;
    invokestatic k a:(Ljava/lang/Throwable;Ljava/lang/String;)Lee;
    athrow
