ff z (IIII)VL1
    aload 0
    iload 1
    iload 2
    bipush 64
    ldc 1069192949 (java.lang.Integer)
    invokevirtual ff q:(IIII)V
    goto L2
L3
    aload 7
    iconst_0
    putfield fm s:I
    goto L4
L5
    aload 0
    getfield ff ae:Lfr;
    getfield fr a:Lgh;
    invokevirtual gh r:()Lgm;
    checkcast fm
    astore 5
    goto L6
L7
    ldc 1106072977 (java.lang.Integer)
    aload 8
    getfield fm m:I
    imul
    ifge L8
    iload 4
    ldc -213146627 (java.lang.Integer)
    if_icmpeq L9
    return
L10
    iload 1
    aload 5
    getfield fm e:I
    ldc -980254659 (java.lang.Integer)
    imul
    if_icmpne L11
    iload 4
    ldc -213146627 (java.lang.Integer)
    if_icmpeq L12
    return
L13
    aload 7
    getfield fm u:I
    ldc 2076852313 (java.lang.Integer)
    imul
    iflt L14
    iload 4
    ldc -213146627 (java.lang.Integer)
    if_icmpeq L15
    return
L16
    aload 0
    getfield ff k:[[Lfm;
    iload 1
    aaload
    aload 5
    getfield fm w:I
    ldc 1336712917 (java.lang.Integer)
    imul
    aconst_null
    aastore
L17
    aload 0
    getfield ff k:[[Lfm;
    iload 1
    aaload
    iload 2
    aload 5
    aastore
L18
    aload 5
    getfield fm f:I
    ldc -97158933 (java.lang.Integer)
    imul
    aload 5
    getfield fm o:I
    ldc 1382214807 (java.lang.Integer)
    imul
    ldc -1472820627 (java.lang.Integer)
    aload 5
    getfield fm g:I
    imul
    imul
    bipush 12
    ishr
    iadd
    istore 6
L19
    aload 5
    dup
    getfield fm f:I
    ldc 1204121539 (java.lang.Integer)
    iload 2
    ldc 1336712917 (java.lang.Integer)
    aload 5
    getfield fm w:I
    imul
    isub
    bipush 8
    ishl
    imul
    iadd
    putfield fm f:I
    goto L20
L11
    aload 0
    getfield ff ae:Lfr;
    getfield fr a:Lgh;
    invokevirtual gh g:()Lgm;
    checkcast fm
    astore 5
    goto L6
L21
    aload 5
    ldc -181243904 (java.lang.Integer)
    putfield fm o:I
    goto L22
L23
    aload 7
    iload 1
    ldc -659679467 (java.lang.Integer)
    imul
    putfield fm e:I
    goto L24
L25
    return
L22
    aload 5
    iload 2
    ldc -1161188739 (java.lang.Integer)
    imul
    putfield fm w:I
    goto L25
L26
    aload 0
    getfield ff e:Lgf;
    aload 0
    getfield ff f:[I
    iload 1
    iaload
    i2l
    invokevirtual gf e:(J)Lgm;
    checkcast fh
    astore 5
    goto L27
L28
    aload 7
    ldc -1902916603 (java.lang.Integer)
    aload 5
    getfield fh u:[B
    iload 2
    baload
    sipush 255
    iand
    imul
    putfield fm r:I
    goto L29
L30
    return
L31
    aload 5
    getfield fh a:[Lbe;
    iload 2
    aaload
    astore 6
L32
    aconst_null
    aload 6
    if_acmpne L33
    iload 4
    ldc -213146627 (java.lang.Integer)
    if_icmpeq L34
    new java/lang/IllegalStateException
    dup
    invokespecial java/lang/IllegalStateException <init>:()V
    athrow
L34
    return
L33
    new fm
    dup
    invokespecial fm <init>:()V
    astore 7
    goto L23
L35
    aload 5
    getfield fh l:[S
    iload 2
    saload
    ifge L13
    goto L36
L24
    aload 7
    aload 5
    putfield fm a:Lfh;
L37
    aload 7
    aload 6
    putfield fm l:Lbe;
    goto L38
L39
    aload 7
    aload 6
    aload 0
    aload 7
    bipush 16
    invokevirtual ff at:(Lfm;B)I
    iconst_0
    aload 0
    aload 7
    ldc 1347155097 (java.lang.Integer)
    invokevirtual ff ak:(Lfm;I)I
    invokestatic bc c:(Lbe;III)Lbc;
    putfield fm q:Lbc;
    goto L40
L41
    aload 7
    aload 5
    getfield fh i:[B
    iload 2
    baload
    ldc -649000983 (java.lang.Integer)
    imul
    putfield fm u:I
    goto L42
L29
    aload 7
    ldc 1204121539 (java.lang.Integer)
    iload 2
    bipush 8
    ishl
    aload 5
    getfield fh l:[S
    iload 2
    saload
    sipush 32767
    iand
    isub
    imul
    putfield fm f:I
    goto L43
L44
    aload 7
    ldc -1463916505 (java.lang.Integer)
    sipush 1024
    aload 5
    getfield fh c:[B
    iload 2
    baload
    aload 5
    getfield fh e:I
    ldc 1092079633 (java.lang.Integer)
    imul
    iload 3
    iload 3
    imul
    imul
    imul
    iadd
    bipush 11
    ishr
    imul
    putfield fm i:I
    goto L28
L27
    aconst_null
    aload 5
    if_acmpne L31
    iload 4
    ldc -213146627 (java.lang.Integer)
    if_icmpeq L30
    new java/lang/IllegalStateException
    dup
    invokespecial java/lang/IllegalStateException <init>:()V
    athrow
L2
    iconst_0
    aload 0
    getfield ff d:[I
    iload 1
    iaload
    iconst_2
    iand
    if_icmpeq L26
    iload 4
    ldc -213146627 (java.lang.Integer)
    if_icmpeq L5
    return
L43
    aload 7
    iconst_0
    putfield fm h:I
    goto L3
L45
    aload 0
    getfield ff k:[[Lfm;
    iload 1
    aaload
    iload 2
    aload 7
    aastore
    goto L46
L4
    aload 7
    iconst_0
    putfield fm j:I
L47
    aload 7
    ldc -1922042737 (java.lang.Integer)
    putfield fm m:I
L48
    aload 7
    iconst_0
    putfield fm t:I
L49
    aload 0
    getfield ff n:[I
    iload 1
    iaload
    ifne L39
    goto L50
L51
    iconst_0
    goto L52
L53
    aload 8
    ifnull L8
    iload 4
    ldc -213146627 (java.lang.Integer)
    if_icmpeq L7
    return
L40
    aload 0
    aload 7
    aload 5
    getfield fh l:[S
    iload 2
    saload
    ifge L51
    iconst_1
L52
    bipush -87
    invokevirtual ff y:(Lfm;ZB)V
    goto L35
L38
    aload 7
    aload 5
    getfield fh w:[Lfd;
    iload 2
    aaload
    putfield fm c:Lfd;
    goto L41
L6
    aload 5
    ifnull L26
    iload 4
    ldc -213146627 (java.lang.Integer)
    if_icmpeq L10
    new java/lang/IllegalStateException
    dup
    invokespecial java/lang/IllegalStateException <init>:()V
    athrow
L36
    aload 7
    getfield fm q:Lbc;
    iconst_m1
    invokevirtual bc g:(I)V
    goto L13
L42
    aload 7
    ldc -1161188739 (java.lang.Integer)
    iload 2
    imul
    putfield fm w:I
    goto L44
L15
    aload 0
    getfield ff ax:[[Lfm;
    iload 1
    aaload
    ldc 2076852313 (java.lang.Integer)
    aload 7
    getfield fm u:I
    imul
    aaload
    astore 8
    goto L53
L20
    aload 5
    iload 6
    aload 5
    getfield fm f:I
    ldc -97158933 (java.lang.Integer)
    imul
    isub
    ldc -428142747 (java.lang.Integer)
    imul
    putfield fm g:I
    goto L21
L50
    aload 7
    aload 6
    aload 0
    aload 7
    bipush 16
    invokevirtual ff at:(Lfm;B)I
    aload 0
    aload 7
    ldc -2120760557 (java.lang.Integer)
    invokevirtual ff al:(Lfm;I)I
    aload 0
    aload 7
    ldc 1347155097 (java.lang.Integer)
    invokevirtual ff ak:(Lfm;I)I
    invokestatic bc c:(Lbe;III)Lbc;
    putfield fm q:Lbc;
    goto L35
L9
    aload 0
    getfield ff k:[[Lfm;
    iload 1
    aaload
    ldc 1336712917 (java.lang.Integer)
    aload 8
    getfield fm w:I
    imul
    aconst_null
    aastore
L54
    aload 8
    iconst_0
    putfield fm m:I
L8
    aload 0
    getfield ff ax:[[Lfm;
    iload 1
    aaload
    ldc 2076852313 (java.lang.Integer)
    aload 7
    getfield fm u:I
    imul
    aload 7
    aastore
L14
    aload 0
    getfield ff ae:Lfr;
    getfield fr a:Lgh;
    aload 7
    invokevirtual gh a:(Lgm;)V
    goto L45
L12
    aload 5
    getfield fm m:I
    ldc 1106072977 (java.lang.Integer)
    imul
    ifge L11
    iload 4
    ldc -213146627 (java.lang.Integer)
    if_icmpeq L16
    return
L46
    return
L55
    new java/lang/StringBuilder
    dup
    invokespecial java/lang/StringBuilder <init>:()V
    ldc "ff.z(" (java.lang.String)
    invokevirtual java/lang/StringBuilder append:(Ljava/lang/String;)Ljava/lang/StringBuilder;
    ldc 41 (java.lang.Integer)
    invokevirtual java/lang/StringBuilder append:(C)Ljava/lang/StringBuilder;
    invokevirtual java/lang/StringBuilder toString:()Ljava/lang/String;
    invokestatic k a:(Ljava/lang/Throwable;Ljava/lang/String;)Lee;
    athrow
