fo e (Ljava/lang/String;ZZI)VL1
    iload 1
    ifeq L2
    iload 3
    ldc 462828307 (java.lang.Integer)
    if_icmpeq L3
    new java/lang/IllegalStateException
    dup
    invokespecial java/lang/IllegalStateException <init>:()V
    athrow
L3
    iload 2
    ifne L4
    invokestatic java/awt/Desktop isDesktopSupported:()Z
    ifeq L4
    iload 3
    ldc 462828307 (java.lang.Integer)
    if_icmpeq L5
    return
L5
    invokestatic java/awt/Desktop getDesktop:()Ljava/awt/Desktop;
    getstatic java/awt/Desktop$Action BROWSE:Ljava/awt/Desktop$Action;
    invokevirtual java/awt/Desktop isSupported:(Ljava/awt/Desktop$Action;)Z
    ifeq L4
    iload 3
    ldc 462828307 (java.lang.Integer)
    if_icmpeq L6
    new java/lang/IllegalStateException
    dup
    invokespecial java/lang/IllegalStateException <init>:()V
    athrow
L6
    invokestatic java/awt/Desktop getDesktop:()Ljava/awt/Desktop;
    new java/net/URI
    dup
    aload 0
    invokespecial java/net/URI <init>:(Ljava/lang/String;)V
    invokevirtual java/awt/Desktop browse:(Ljava/net/URI;)V
L7
    goto L8
L9
    astore 4
L4
    getstatic dq a:Ljava/lang/String;
    ldc "win" (java.lang.String)
    invokevirtual java/lang/String startsWith:(Ljava/lang/String;)Z
    ifeq L10
    iload 3
    ldc 462828307 (java.lang.Integer)
    if_icmpeq L11
    new java/lang/IllegalStateException
    dup
    invokespecial java/lang/IllegalStateException <init>:()V
    athrow
L11
    iload 2
    ifne L10
    iload 3
    ldc 462828307 (java.lang.Integer)
    if_icmpeq L12
    new java/lang/IllegalStateException
    dup
    invokespecial java/lang/IllegalStateException <init>:()V
    athrow
L12
    aload 0
    iconst_0
    ldc "openjs" (java.lang.String)
    bipush -120
    invokestatic aj a:(Ljava/lang/String;ILjava/lang/String;B)Z
    pop
L13
    goto L8
L10
    getstatic dq a:Ljava/lang/String;
    ldc "mac" (java.lang.String)
    invokevirtual java/lang/String startsWith:(Ljava/lang/String;)Z
    ifeq L14
L15
    aload 0
    iconst_1
    ldc "openjs" (java.lang.String)
    bipush -9
    invokestatic aj a:(Ljava/lang/String;ILjava/lang/String;B)Z
    pop
L16
    goto L8
L14
    aload 0
    iconst_2
    ldc "openjs" (java.lang.String)
    bipush -50
    invokestatic aj a:(Ljava/lang/String;ILjava/lang/String;B)Z
    pop
    goto L8
L2
    aload 0
    iconst_3
    ldc "openjs" (java.lang.String)
    bipush -30
    invokestatic aj a:(Ljava/lang/String;ILjava/lang/String;B)Z
    pop
L8
    return
L17
    new java/lang/StringBuilder
    dup
    invokespecial java/lang/StringBuilder <init>:()V
    ldc "fo.e(" (java.lang.String)
    invokevirtual java/lang/StringBuilder append:(Ljava/lang/String;)Ljava/lang/StringBuilder;
    ldc 41 (java.lang.Integer)
    invokevirtual java/lang/StringBuilder append:(C)Ljava/lang/StringBuilder;
    invokevirtual java/lang/StringBuilder toString:()Ljava/lang/String;
    invokestatic k a:(Ljava/lang/Throwable;Ljava/lang/String;)Lee;
    athrow
