fq i (Lah;ILah;II)Lcy;L1
    iconst_m1
    aload 0
    getfield fq c:I
    ldc 144759051 (java.lang.Integer)
    imul
    if_icmpeq L2
    iload 5
    ldc 863844261 (java.lang.Integer)
    if_icmpgt L3
    new java/lang/IllegalStateException
    dup
    invokespecial java/lang/IllegalStateException <init>:()V
    athrow
L4
    aload 9
    ifnonnull L5
    goto L6
L2
    ldc -568719607362328879 (java.lang.Long)
    aload 0
    getfield fq u:J
    lmul
    lstore 6
    goto L7
L8
    iconst_1
    istore 10
    goto L9
L10
    aload 1
    ifnull L11
    goto L12
L9
    iinc 11 1
    goto L13
L14
    aload 1
    aload 9
    iload 2
    aload 3
    iload 4
    ldc -1346520529 (java.lang.Integer)
    invokevirtual ah r:(Lcy;ILah;II)Lcy;
    astore 10
    goto L15
L16
    bipush 12
    newarray 10
    astore 8
L17
    iconst_0
    istore 9
L18
    iload 9
    bipush 12
    if_icmpge L19
    goto L20
L21
    aload 1
    getfield ah m:I
    ldc 531822059 (java.lang.Integer)
    imul
    iflt L11
    iload 5
    ldc 863844261 (java.lang.Integer)
    if_icmpgt L22
    new java/lang/IllegalStateException
    dup
    invokespecial java/lang/IllegalStateException <init>:()V
    athrow
L5
    aload 9
    ifnonnull L23
    iload 5
    ldc 863844261 (java.lang.Integer)
    if_icmpgt L24
    new java/lang/IllegalStateException
    dup
    invokespecial java/lang/IllegalStateException <init>:()V
    athrow
L25
    lload 6
    aload 1
    getfield ah j:I
    ldc 1484644271 (java.lang.Integer)
    imul
    aload 0
    getfield fq e:[I
    iconst_5
    iaload
    isub
    bipush 40
    ishl
    i2l
    ladd
    lstore 6
L26
    aload 8
    iconst_5
    ldc 1484644271 (java.lang.Integer)
    aload 1
    getfield ah j:I
    imul
    iastore
    goto L21
L27
    iconst_0
    istore 14
    goto L28
L22
    lload 6
    aload 1
    getfield ah m:I
    ldc 531822059 (java.lang.Integer)
    imul
    aload 0
    getfield fq e:[I
    iconst_3
    iaload
    isub
    bipush 48
    ishl
    i2l
    ladd
    lstore 6
    goto L29
L19
    aload 1
    getfield ah j:I
    ldc 1484644271 (java.lang.Integer)
    imul
    iflt L21
    iload 5
    ldc 863844261 (java.lang.Integer)
    if_icmpgt L25
    new java/lang/IllegalStateException
    dup
    invokespecial java/lang/IllegalStateException <init>:()V
    athrow
L11
    getstatic fq h:Lgr;
    lload 6
    invokevirtual gr e:(J)Lgd;
    checkcast cy
    astore 9
L30
    aconst_null
    aload 9
    if_acmpne L23
    iload 5
    ldc 863844261 (java.lang.Integer)
    if_icmpgt L31
    new java/lang/IllegalStateException
    dup
    invokespecial java/lang/IllegalStateException <init>:()V
    athrow
L31
    iconst_0
    istore 10
L32
    iconst_0
    istore 11
L13
    iload 11
    bipush 12
    if_icmpge L33
    iload 5
    ldc 863844261 (java.lang.Integer)
    if_icmpgt L34
    new java/lang/IllegalStateException
    dup
    invokespecial java/lang/IllegalStateException <init>:()V
    athrow
L34
    aload 8
    iload 11
    iaload
    istore 12
L35
    iload 12
    sipush 256
    if_icmplt L36
    iload 5
    ldc 863844261 (java.lang.Integer)
    if_icmpgt L37
    new java/lang/IllegalStateException
    dup
    invokespecial java/lang/IllegalStateException <init>:()V
    athrow
L38
    aload 0
    getfield fq w:J
    ldc -3389093058227618093 (java.lang.Long)
    lmul
    ldc -1 (java.lang.Long)
    lcmp
    ifeq L4
    goto L39
L40
    iload 12
    sipush 256
    isub
    bipush 37
    invokestatic q a:(IB)Lal;
    sipush -22910
    invokevirtual al u:(S)Z
    ifne L36
    iload 5
    ldc 863844261 (java.lang.Integer)
    if_icmpgt L41
    new java/lang/IllegalStateException
    dup
    invokespecial java/lang/IllegalStateException <init>:()V
    athrow
L41
    iconst_1
    istore 10
L36
    iload 12
    sipush 512
    if_icmplt L9
    iload 5
    ldc 863844261 (java.lang.Integer)
    if_icmpgt L42
    new java/lang/IllegalStateException
    dup
    invokespecial java/lang/IllegalStateException <init>:()V
    athrow
L42
    iload 12
    sipush 512
    isub
    bipush 7
    invokestatic dj e:(IB)Lad;
    aload 0
    getfield fq l:Z
    ldc -1629166975 (java.lang.Integer)
    invokevirtual ad o:(ZI)Z
    ifne L9
    goto L8
L43
    aload 0
    getfield fq a:[I
    iload 14
    iaload
    getstatic bz r:[[S
    iload 14
    aaload
    arraylength
    if_icmpge L44
    iload 5
    ldc 863844261 (java.lang.Integer)
    if_icmpgt L45
    new java/lang/IllegalStateException
    dup
    invokespecial java/lang/IllegalStateException <init>:()V
    athrow
L46
    ldc 531822059 (java.lang.Integer)
    aload 1
    getfield ah m:I
    imul
    iflt L11
    iload 5
    ldc 863844261 (java.lang.Integer)
    if_icmpgt L16
    new java/lang/IllegalStateException
    dup
    invokespecial java/lang/IllegalStateException <init>:()V
    athrow
L33
    iload 10
    ifeq L5
    iload 5
    ldc 863844261 (java.lang.Integer)
    if_icmpgt L38
    new java/lang/IllegalStateException
    dup
    invokespecial java/lang/IllegalStateException <init>:()V
    athrow
L15
    aload 10
    areturn
L39
    getstatic fq h:Lgr;
    aload 0
    getfield fq w:J
    ldc -3389093058227618093 (java.lang.Long)
    lmul
    invokevirtual gr e:(J)Lgd;
    checkcast cy
    astore 9
    goto L4
L47
    iconst_0
    istore 13
    goto L48
L6
    aconst_null
    areturn
L49
    aload 1
    ifnull L50
    iload 5
    ldc 863844261 (java.lang.Integer)
    if_icmpgt L51
    new java/lang/IllegalStateException
    dup
    invokespecial java/lang/IllegalStateException <init>:()V
    athrow
L24
    bipush 12
    anewarray cr
    astore 11
L52
    iconst_0
    istore 12
    goto L47
L53
    aload 13
    getstatic a f:[S
    iload 14
    saload
    getstatic bn g:[[S
    iload 14
    aaload
    aload 0
    getfield fq a:[I
    iload 14
    iaload
    saload
    invokevirtual cr z:(SS)V
    goto L54
L48
    iload 13
    bipush 12
    if_icmpge L55
    iload 5
    ldc 863844261 (java.lang.Integer)
    if_icmpgt L56
    new java/lang/IllegalStateException
    dup
    invokespecial java/lang/IllegalStateException <init>:()V
    athrow
L56
    aload 8
    iload 13
    iaload
    istore 14
    goto L57
L20
    aload 8
    iload 9
    aload 0
    getfield fq e:[I
    iload 9
    iaload
    iastore
    iinc 9 1
    goto L18
L58
    iload 14
    sipush 512
    if_icmpge L59
    iload 5
    ldc 863844261 (java.lang.Integer)
    if_icmpgt L60
    new java/lang/IllegalStateException
    dup
    invokespecial java/lang/IllegalStateException <init>:()V
    athrow
L60
    iload 14
    sipush 256
    isub
    bipush 22
    invokestatic q a:(IB)Lal;
    sipush -6906
    invokevirtual al w:(S)Lcr;
    astore 15
L61
    aconst_null
    aload 15
    if_acmpeq L59
    iload 5
    ldc 863844261 (java.lang.Integer)
    if_icmpgt L62
    new java/lang/IllegalStateException
    dup
    invokespecial java/lang/IllegalStateException <init>:()V
    athrow
L62
    aload 11
    iload 12
    iinc 12 1
    aload 15
    aastore
    goto L59
L55
    new cr
    dup
    aload 11
    iload 12
    invokespecial cr <init>:([Lcr;I)V
    astore 13
    goto L27
L63
    iload 14
    sipush 512
    isub
    bipush -75
    invokestatic dj e:(IB)Lad;
    aload 0
    getfield fq l:Z
    ldc -2141459486 (java.lang.Integer)
    invokevirtual ad h:(ZI)Lcr;
    astore 15
L64
    aload 15
    ifnull L65
    aload 11
    iload 12
    iinc 12 1
    aload 15
    aastore
L65
    iinc 13 1
    goto L48
L66
    aconst_null
    aload 3
    if_acmpne L49
    iload 5
    ldc 863844261 (java.lang.Integer)
    if_icmpgt L67
    new java/lang/IllegalStateException
    dup
    invokespecial java/lang/IllegalStateException <init>:()V
    athrow
L59
    iload 14
    sipush 512
    if_icmplt L65
    iload 5
    ldc 863844261 (java.lang.Integer)
    if_icmpgt L63
    new java/lang/IllegalStateException
    dup
    invokespecial java/lang/IllegalStateException <init>:()V
    athrow
L28
    iload 14
    iconst_5
    if_icmpge L68
    iload 5
    ldc 863844261 (java.lang.Integer)
    if_icmpgt L43
    new java/lang/IllegalStateException
    dup
    invokespecial java/lang/IllegalStateException <init>:()V
    athrow
L54
    iinc 14 1
    goto L28
L45
    aload 13
    getstatic ds i:[S
    iload 14
    saload
    getstatic bz r:[[S
    iload 14
    aaload
    aload 0
    getfield fq a:[I
    iload 14
    iaload
    saload
    invokevirtual cr z:(SS)V
L44
    aload 0
    getfield fq a:[I
    iload 14
    iaload
    getstatic bn g:[[S
    iload 14
    aaload
    arraylength
    if_icmpge L54
    iload 5
    ldc 863844261 (java.lang.Integer)
    if_icmpgt L53
    new java/lang/IllegalStateException
    dup
    invokespecial java/lang/IllegalStateException <init>:()V
    athrow
L57
    iload 14
    sipush 256
    if_icmplt L59
    iload 5
    ldc 863844261 (java.lang.Integer)
    if_icmpgt L58
    new java/lang/IllegalStateException
    dup
    invokespecial java/lang/IllegalStateException <init>:()V
    athrow
L12
    aload 1
    getfield ah j:I
    ldc 1484644271 (java.lang.Integer)
    imul
    ifge L16
    iload 5
    ldc 863844261 (java.lang.Integer)
    if_icmpgt L46
    new java/lang/IllegalStateException
    dup
    invokespecial java/lang/IllegalStateException <init>:()V
    athrow
L68
    aload 13
    bipush 64
    sipush 850
    bipush -30
    bipush -50
    bipush -30
    invokevirtual cr p:(IIIII)Lcy;
    astore 9
L69
    getstatic fq h:Lgr;
    aload 9
    lload 6
    invokevirtual gr l:(Lgd;J)V
L70
    aload 0
    ldc -3832642427496871589 (java.lang.Long)
    lload 6
    lmul
    putfield fq w:J
    goto L23
L29
    aload 8
    iconst_3
    aload 1
    getfield ah m:I
    ldc 531822059 (java.lang.Integer)
    imul
    iastore
    goto L11
L7
    aload 0
    getfield fq e:[I
    astore 8
    goto L10
L67
    aload 9
    areturn
L23
    aload 1
    ifnonnull L49
    iload 5
    ldc 863844261 (java.lang.Integer)
    if_icmpgt L66
    new java/lang/IllegalStateException
    dup
    invokespecial java/lang/IllegalStateException <init>:()V
    athrow
L51
    aload 3
    ifnull L50
    iload 5
    ldc 863844261 (java.lang.Integer)
    if_icmpgt L14
    new java/lang/IllegalStateException
    dup
    invokespecial java/lang/IllegalStateException <init>:()V
    athrow
L3
    aload 0
    getfield fq c:I
    ldc 144759051 (java.lang.Integer)
    imul
    bipush 74
    invokestatic ar e:(IB)Lay;
    aload 1
    iload 2
    aload 3
    iload 4
    bipush -9
    invokevirtual ay u:(Lah;ILah;IB)Lcy;
    areturn
L50
    aconst_null
    aload 1
    if_acmpeq L71
    iload 5
    ldc 863844261 (java.lang.Integer)
    if_icmpgt L72
    new java/lang/IllegalStateException
    dup
    invokespecial java/lang/IllegalStateException <init>:()V
    athrow
L72
    aload 1
    aload 9
    iload 2
    ldc 873983008 (java.lang.Integer)
    invokevirtual ah u:(Lcy;II)Lcy;
    astore 10
    goto L15
L71
    aload 3
    aload 9
    iload 4
    ldc 1643524132 (java.lang.Integer)
    invokevirtual ah u:(Lcy;II)Lcy;
    astore 10
    goto L15
L37
    iload 12
    sipush 512
    if_icmpge L36
    iload 5
    ldc 863844261 (java.lang.Integer)
    if_icmpgt L40
    new java/lang/IllegalStateException
    dup
    invokespecial java/lang/IllegalStateException <init>:()V
    athrow
L73
    new java/lang/StringBuilder
    dup
    invokespecial java/lang/StringBuilder <init>:()V
    ldc "fq.i(" (java.lang.String)
    invokevirtual java/lang/StringBuilder append:(Ljava/lang/String;)Ljava/lang/StringBuilder;
    ldc 41 (java.lang.Integer)
    invokevirtual java/lang/StringBuilder append:(C)Ljava/lang/StringBuilder;
    invokevirtual java/lang/StringBuilder toString:()Ljava/lang/String;
    invokestatic k a:(Ljava/lang/Throwable;Ljava/lang/String;)Lee;
    athrow
