fq l (IZB)VL1
    aload 0
    getfield fq a:[I
    iload 1
    iaload
    istore 4
    goto L2
L3
    goto L4
L5
    iinc 4 -1
    goto L6
L2
    iload 2
    ifne L7
    iload 3
    bipush 8
    if_icmplt L5
    new java/lang/IllegalStateException
    dup
    invokespecial java/lang/IllegalStateException <init>:()V
    athrow
L8
    iconst_1
    istore 5
    goto L9
L10
    iload 1
    iconst_4
    if_icmpne L8
    iload 4
    bipush 8
    if_icmpne L8
    iload 3
    bipush 8
    if_icmplt L11
    new java/lang/IllegalStateException
    dup
    invokespecial java/lang/IllegalStateException <init>:()V
    athrow
L11
    iconst_0
    istore 5
L12
    goto L9
L13
    goto L4
L9
    iload 5
    ifeq L14
    iload 3
    bipush 8
    if_icmplt L13
    new java/lang/IllegalStateException
    dup
    invokespecial java/lang/IllegalStateException <init>:()V
    athrow
L14
    goto L5
L15
    iload 4
    getstatic bz r:[[S
    iload 1
    aaload
    arraylength
    if_icmplt L16
    iload 3
    bipush 8
    if_icmplt L17
    new java/lang/IllegalStateException
    dup
    invokespecial java/lang/IllegalStateException <init>:()V
    athrow
L7
    iinc 4 1
    goto L15
L18
    iconst_0
    istore 5
    goto L19
L20
    bipush 8
    iload 4
    if_icmpne L21
    iload 3
    bipush 8
    if_icmplt L18
    return
L16
    iconst_4
    iload 1
    if_icmpne L21
    iload 3
    bipush 8
    if_icmplt L20
    new java/lang/IllegalStateException
    dup
    invokespecial java/lang/IllegalStateException <init>:()V
    athrow
L22
    getstatic bz r:[[S
    iload 1
    aaload
    arraylength
    iconst_1
    isub
    istore 4
    goto L10
L17
    iconst_0
    istore 4
    goto L16
L19
    goto L23
L21
    iconst_1
    istore 5
L23
    iload 5
    ifeq L24
    iload 3
    bipush 8
    if_icmplt L3
    new java/lang/IllegalStateException
    dup
    invokespecial java/lang/IllegalStateException <init>:()V
    athrow
L6
    iload 4
    ifge L10
    iload 3
    bipush 8
    if_icmplt L22
    return
L24
    goto L7
L4
    aload 0
    getfield fq a:[I
    iload 1
    iload 4
    iastore
L25
    aload 0
    iconst_1
    invokevirtual fq w:(B)V
L26
    return
L27
    new java/lang/StringBuilder
    dup
    invokespecial java/lang/StringBuilder <init>:()V
    ldc "fq.l(" (java.lang.String)
    invokevirtual java/lang/StringBuilder append:(Ljava/lang/String;)Ljava/lang/StringBuilder;
    ldc 41 (java.lang.Integer)
    invokevirtual java/lang/StringBuilder append:(C)Ljava/lang/StringBuilder;
    invokevirtual java/lang/StringBuilder toString:()Ljava/lang/String;
    invokestatic k a:(Ljava/lang/Throwable;Ljava/lang/String;)Lee;
    athrow
