ft cx (Lfb;III)VL1
    aconst_null
    getstatic client jc:Lfb;
    if_acmpne L2
    iload 3
    ldc 171115759 (java.lang.Integer)
    if_icmplt L3
    new java/lang/IllegalStateException
    dup
    invokespecial java/lang/IllegalStateException <init>:()V
    athrow
L4
    aload 7
    astore 4
    goto L5
L2
    return
L6
    aload 0
    ifnull L7
    goto L8
L9
    iconst_0
    istore 8
    goto L10
L11
    aload 6
    bipush 25
    invokestatic t dj:(Lfb;B)I
    ldc -1538878527 (java.lang.Integer)
    invokestatic cj a:(II)I
    istore 7
L12
    iconst_0
    iload 7
    if_icmpne L13
    iload 3
    ldc 171115759 (java.lang.Integer)
    if_icmplt L14
    new java/lang/IllegalStateException
    dup
    invokespecial java/lang/IllegalStateException <init>:()V
    athrow
L14
    aconst_null
    astore 5
L15
    goto L16
L5
    aconst_null
    aload 4
    if_acmpeq L7
    iload 3
    ldc 171115759 (java.lang.Integer)
    if_icmplt L17
    return
L18
    aload 0
    putstatic client jc:Lfb;
    goto L19
L20
    goto L16
L21
    aconst_null
    aload 6
    if_acmpne L22
    iload 3
    ldc 171115759 (java.lang.Integer)
    if_icmplt L23
    new java/lang/IllegalStateException
    dup
    invokespecial java/lang/IllegalStateException <init>:()V
    athrow
L23
    aconst_null
    astore 5
    goto L20
L24
    aconst_null
    aload 7
    if_acmpne L4
    goto L25
L22
    iinc 8 1
    goto L26
L27
    aload 6
    astore 5
L16
    aload 5
    astore 7
    goto L24
L28
    aload 6
    getfield fb n:I
    ldc 737715635 (java.lang.Integer)
    imul
    ldc -2068421293 (java.lang.Integer)
    invokestatic f a:(II)Lfb;
    astore 6
    goto L21
L25
    aload 0
    getfield fb bt:Lfb;
    astore 7
    goto L4
L3
    getstatic client ih:Z
    ifeq L6
    goto L2
L29
    iconst_0
    putstatic e ky:I
    goto L30
L31
    ldc 1416558615 (java.lang.Integer)
    iload 2
    imul
    putstatic client jb:I
    goto L29
L7
    return
L17
    goto L18
L32
    aload 7
    ifnonnull L33
    iload 3
    ldc 171115759 (java.lang.Integer)
    if_icmplt L34
    new java/lang/IllegalStateException
    dup
    invokespecial java/lang/IllegalStateException <init>:()V
    athrow
L35
    aload 6
    bipush 113
    invokestatic t dj:(Lfb;B)I
    ldc -1491675720 (java.lang.Integer)
    invokestatic cj a:(II)I
    istore 7
L36
    iload 7
    ifne L9
    iload 3
    ldc 171115759 (java.lang.Integer)
    if_icmplt L37
    return
L37
    aconst_null
    astore 5
L38
    goto L39
L40
    aload 6
    getfield fb n:I
    ldc 737715635 (java.lang.Integer)
    imul
    ldc -2068421293 (java.lang.Integer)
    invokestatic f a:(II)Lfb;
    astore 6
    goto L41
L26
    iload 8
    iload 7
    if_icmpge L27
    iload 3
    ldc 171115759 (java.lang.Integer)
    if_icmplt L28
    new java/lang/IllegalStateException
    dup
    invokespecial java/lang/IllegalStateException <init>:()V
    athrow
L41
    aconst_null
    aload 6
    if_acmpne L42
    iload 3
    ldc 171115759 (java.lang.Integer)
    if_icmplt L43
    new java/lang/IllegalStateException
    dup
    invokespecial java/lang/IllegalStateException <init>:()V
    athrow
L8
    aload 0
    astore 6
    goto L11
L43
    aconst_null
    astore 5
L44
    goto L39
L45
    ldc 168366275 (java.lang.Integer)
    iload 1
    imul
    putstatic client jx:I
    goto L31
L46
    aload 6
    astore 5
L39
    aload 5
    astore 7
    goto L32
L13
    iconst_0
    istore 8
    goto L26
L34
    aload 0
    getfield fb bt:Lfb;
    astore 7
L33
    aload 7
    astore 4
L47
    aload 4
    putstatic client jm:Lfb;
    goto L45
L42
    iinc 8 1
L10
    iload 8
    iload 7
    if_icmpge L46
    iload 3
    ldc 171115759 (java.lang.Integer)
    if_icmplt L40
    new java/lang/IllegalStateException
    dup
    invokespecial java/lang/IllegalStateException <init>:()V
    athrow
L19
    aload 0
    astore 6
    goto L35
L30
    iconst_0
    putstatic client kg:Z
L48
    ldc 811532485 (java.lang.Integer)
    getstatic client ii:I
    imul
    ifle L49
    iload 3
    ldc 171115759 (java.lang.Integer)
    if_icmplt L50
    new java/lang/IllegalStateException
    dup
    invokespecial java/lang/IllegalStateException <init>:()V
    athrow
L50
    ldc 811532485 (java.lang.Integer)
    getstatic client ii:I
    imul
    iconst_1
    isub
    ldc 581476790 (java.lang.Integer)
    invokestatic dx ck:(II)V
L49
    return
L51
    new java/lang/StringBuilder
    dup
    invokespecial java/lang/StringBuilder <init>:()V
    ldc "ft.cx(" (java.lang.String)
    invokevirtual java/lang/StringBuilder append:(Ljava/lang/String;)Ljava/lang/StringBuilder;
    ldc 41 (java.lang.Integer)
    invokevirtual java/lang/StringBuilder append:(C)Ljava/lang/StringBuilder;
    invokevirtual java/lang/StringBuilder toString:()Ljava/lang/String;
    invokestatic k a:(Ljava/lang/Throwable;Ljava/lang/String;)Lee;
    athrow
