fv e ([BB)VL1
    aload 1
    arraylength
    istore 4
    goto L2
L3
    aload 0
    getfield fv h:[[Ljava/lang/Object;
    iload 11
    iconst_1
    iload 13
    iadd
    anewarray java/lang/Object
    aastore
    goto L4
L5
    iconst_0
    istore 7
L6
    iload 7
    iload 4
    if_icmpge L7
    iload 2
    bipush 12
    if_icmpne L8
    return
L8
    iload 6
    bipush 8
    iushr
    getstatic dh l:[I
    iload 6
    aload 1
    iload 7
    baload
    ixor
    sipush 255
    iand
    iaload
    ixor
    istore 6
L9
    iinc 7 1
    goto L6
L7
    iload 6
    iconst_m1
    ixor
    istore 6
L10
    iload 6
    istore 5
L11
    iload 5
    istore 3
L12
    aload 0
    iload 3
    ldc -1151331883 (java.lang.Integer)
    imul
    putfield fv j:I
    goto L13
L14
    return
L15
    iinc 10 1
    goto L16
L17
    iload 6
    iconst_5
    if_icmplt L18
    iload 2
    bipush 12
    if_icmpne L19
    new java/lang/IllegalStateException
    dup
    invokespecial java/lang/IllegalStateException <init>:()V
    athrow
L20
    iconst_0
    istore 10
    goto L21
L18
    new java/lang/RuntimeException
    dup
    ldc "" (java.lang.String)
    invokespecial java/lang/RuntimeException <init>:(Ljava/lang/String;)V
    athrow
L22
    iload 6
    bipush 6
    if_icmplt L23
    iload 2
    bipush 12
    if_icmpne L24
    new java/lang/IllegalStateException
    dup
    invokespecial java/lang/IllegalStateException <init>:()V
    athrow
L24
    aload 5
    ldc -1948254621 (java.lang.Integer)
    invokevirtual dh x:(I)I
    pop
    goto L23
L13
    new dh
    dup
    aload 1
    ldc -488552453 (java.lang.Integer)
    invokestatic di v:([BI)[B
    invokespecial dh <init>:([B)V
    astore 5
    goto L25
L26
    iload 6
    bipush 7
    if_icmplt L27
    iload 2
    bipush 12
    if_icmpne L28
    new java/lang/IllegalStateException
    dup
    invokespecial java/lang/IllegalStateException <init>:()V
    athrow
L28
    aload 0
    aload 5
    sipush 8876
    invokevirtual dh aw:(S)I
    ldc -1680569419 (java.lang.Integer)
    imul
    putfield fv e:I
    goto L29
L27
    aload 0
    aload 5
    ldc -1475249833 (java.lang.Integer)
    invokevirtual dh q:(I)I
    ldc -1680569419 (java.lang.Integer)
    imul
    putfield fv e:I
L29
    iconst_0
    istore 8
L30
    iconst_m1
    istore 9
L31
    aload 0
    ldc -1749792099 (java.lang.Integer)
    aload 0
    getfield fv e:I
    imul
    newarray 10
    putfield fv a:[I
L32
    iload 6
    bipush 7
    if_icmplt L20
    iload 2
    bipush 12
    if_icmpne L33
    return
L16
    iload 10
    aload 0
    getfield fv e:I
    ldc -1749792099 (java.lang.Integer)
    imul
    if_icmpge L34
    iload 2
    bipush 12
    if_icmpne L35
    new java/lang/IllegalStateException
    dup
    invokespecial java/lang/IllegalStateException <init>:()V
    athrow
L36
    aload 0
    getfield fv g:[Lfs;
    iload 11
    new fs
    dup
    aload 0
    getfield fv f:[[I
    iload 11
    aaload
    invokespecial fs <init>:([I)V
    aastore
    goto L37
L35
    aload 0
    getfield fv a:[I
    iload 10
    iload 8
    aload 5
    sipush 27559
    invokevirtual dh aw:(S)I
    iadd
    dup
    istore 8
    iastore
L38
    aload 0
    getfield fv a:[I
    iload 10
    iaload
    iload 9
    if_icmple L15
    iload 2
    bipush 12
    if_icmpne L39
    new java/lang/IllegalStateException
    dup
    invokespecial java/lang/IllegalStateException <init>:()V
    athrow
L2
    iconst_m1
    istore 6
    goto L5
L37
    iinc 10 1
    goto L40
L34
    goto L41
L42
    aload 0
    getfield fv a:[I
    iload 10
    iaload
    istore 11
    goto L43
L44
    aload 0
    getfield fv r:[[I
    iload 11
    iload 12
    newarray 10
    aastore
    goto L45
L19
    iload 6
    bipush 7
    if_icmple L22
    goto L18
L46
    aload 0
    getfield fv a:[I
    iload 10
    iaload
    iload 9
    if_icmple L47
    iload 2
    bipush 12
    if_icmpne L48
    new java/lang/IllegalStateException
    dup
    invokespecial java/lang/IllegalStateException <init>:()V
    athrow
L33
    iconst_0
    istore 10
    goto L16
L49
    iconst_0
    istore 10
    goto L50
L41
    aload 0
    iload 9
    iconst_1
    iadd
    newarray 10
    putfield fv u:[I
L51
    aload 0
    iload 9
    iconst_1
    iadd
    newarray 10
    putfield fv w:[I
L52
    aload 0
    iload 9
    iconst_1
    iadd
    newarray 10
    putfield fv i:[I
    goto L53
L54
    aload 0
    getfield fv h:[[Ljava/lang/Object;
    iload 11
    iconst_1
    iload 13
    iadd
    anewarray java/lang/Object
    aastore
    goto L55
L23
    aload 5
    ldc 1357752283 (java.lang.Integer)
    invokevirtual dh z:(I)I
    istore 7
    goto L26
L56
    aload 0
    iload 9
    iconst_1
    iadd
    anewarray [Ljava/lang/Object;
    putfield fv h:[[Ljava/lang/Object;
L57
    iload 7
    ifeq L49
L58
    aload 0
    iconst_1
    iload 9
    iadd
    newarray 10
    putfield fv l:[I
L59
    iconst_0
    istore 10
    goto L60
L61
    aload 0
    iconst_1
    iload 9
    iadd
    anewarray [I
    putfield fv f:[[I
    goto L62
L63
    aload 0
    getfield fv l:[I
    aload 0
    getfield fv a:[I
    iload 10
    iaload
    aload 5
    ldc -2036543563 (java.lang.Integer)
    invokevirtual dh x:(I)I
    iastore
    iinc 10 1
    goto L60
L64
    aload 0
    new fs
    dup
    aload 0
    getfield fv l:[I
    invokespecial fs <init>:([I)V
    putfield fv c:Lfs;
    goto L49
L25
    aload 5
    ldc 1527436287 (java.lang.Integer)
    invokevirtual dh z:(I)I
    istore 6
    goto L17
L50
    iload 10
    ldc -1749792099 (java.lang.Integer)
    aload 0
    getfield fv e:I
    imul
    if_icmpge L65
    aload 0
    getfield fv u:[I
    aload 0
    getfield fv a:[I
    iload 10
    iaload
    aload 5
    ldc -2136417127 (java.lang.Integer)
    invokevirtual dh x:(I)I
    iastore
    iinc 10 1
    goto L50
L65
    iconst_0
    istore 10
    goto L66
L60
    iload 10
    aload 0
    getfield fv e:I
    ldc -1749792099 (java.lang.Integer)
    imul
    if_icmpge L64
    iload 2
    bipush 12
    if_icmpne L63
    new java/lang/IllegalStateException
    dup
    invokespecial java/lang/IllegalStateException <init>:()V
    athrow
L43
    aload 0
    getfield fv i:[I
    iload 11
    iaload
    istore 12
    goto L67
L68
    aload 0
    getfield fv a:[I
    iload 10
    iload 8
    aload 5
    ldc 1576597750 (java.lang.Integer)
    invokevirtual dh q:(I)I
    iadd
    dup
    istore 8
    iastore
    goto L46
L69
    iload 10
    aload 0
    getfield fv e:I
    ldc -1749792099 (java.lang.Integer)
    imul
    if_icmpge L70
    goto L71
L45
    iconst_0
    istore 14
    goto L72
L70
    iload 6
    bipush 7
    if_icmplt L73
    iload 2
    bipush 12
    if_icmpne L74
    new java/lang/IllegalStateException
    dup
    invokespecial java/lang/IllegalStateException <init>:()V
    athrow
L74
    iconst_0
    istore 10
L75
    iload 10
    aload 0
    getfield fv e:I
    ldc -1749792099 (java.lang.Integer)
    imul
    if_icmpge L76
    iload 2
    bipush 12
    if_icmpne L77
    new java/lang/IllegalStateException
    dup
    invokespecial java/lang/IllegalStateException <init>:()V
    athrow
L77
    aload 0
    getfield fv a:[I
    iload 10
    iaload
    istore 11
    goto L78
L4
    iinc 10 1
    goto L75
L79
    iconst_0
    istore 8
L80
    iconst_m1
    istore 13
    goto L44
L81
    aload 0
    getfield fv i:[I
    iload 11
    iaload
    istore 12
    goto L82
L48
    aload 0
    getfield fv a:[I
    iload 10
    iaload
    istore 9
    goto L47
L72
    iload 14
    iload 12
    if_icmpge L3
    iload 2
    bipush 12
    if_icmpne L83
    new java/lang/IllegalStateException
    dup
    invokespecial java/lang/IllegalStateException <init>:()V
    athrow
L83
    aload 0
    getfield fv r:[[I
    iload 11
    aaload
    iload 14
    iload 8
    aload 5
    sipush 24797
    invokevirtual dh aw:(S)I
    iadd
    dup
    istore 8
    dup_x2
    iastore
    istore 15
    goto L84
L85
    iload 15
    istore 13
    goto L86
L87
    iload 15
    istore 13
L88
    iinc 14 1
    goto L72
L82
    aload 0
    getfield fv f:[[I
    iload 11
    aload 0
    getfield fv h:[[Ljava/lang/Object;
    iload 11
    aaload
    arraylength
    newarray 10
    aastore
    goto L89
L84
    iload 15
    iload 13
    if_icmple L88
    iload 2
    bipush 12
    if_icmpne L87
    new java/lang/IllegalStateException
    dup
    invokespecial java/lang/IllegalStateException <init>:()V
    athrow
L76
    goto L90
L73
    iconst_0
    istore 10
L91
    iload 10
    ldc -1749792099 (java.lang.Integer)
    aload 0
    getfield fv e:I
    imul
    if_icmpge L90
    goto L42
L78
    aload 0
    getfield fv i:[I
    iload 11
    iaload
    istore 12
    goto L79
L39
    aload 0
    getfield fv a:[I
    iload 10
    iaload
    istore 9
    goto L15
L92
    aload 0
    iconst_1
    iload 9
    iadd
    anewarray java/lang/Object
    putfield fv o:[Ljava/lang/Object;
    goto L56
L93
    iconst_m1
    istore 13
L94
    aload 0
    getfield fv r:[[I
    iload 11
    iload 12
    newarray 10
    aastore
L95
    iconst_0
    istore 14
    goto L96
L53
    aload 0
    iload 9
    iconst_1
    iadd
    anewarray [I
    putfield fv r:[[I
    goto L92
L97
    aload 0
    getfield fv r:[[I
    iload 11
    aaload
    iload 14
    iload 8
    aload 5
    ldc -1447432872 (java.lang.Integer)
    invokevirtual dh q:(I)I
    iadd
    dup
    istore 8
    dup_x2
    iastore
    istore 15
L98
    iload 15
    iload 13
    if_icmple L86
    iload 2
    bipush 12
    if_icmpne L85
    return
L47
    iinc 10 1
    goto L21
L86
    iinc 14 1
L96
    iload 14
    iload 12
    if_icmpge L54
    iload 2
    bipush 12
    if_icmpne L97
    return
L55
    iinc 10 1
    goto L91
L90
    iload 7
    ifeq L14
    goto L61
L99
    aload 0
    getfield fv w:[I
    aload 0
    getfield fv a:[I
    iload 10
    iaload
    aload 5
    ldc -2058938635 (java.lang.Integer)
    invokevirtual dh x:(I)I
    iastore
    iinc 10 1
    goto L66
L62
    aload 0
    iconst_1
    iload 9
    iadd
    anewarray fs
    putfield fv g:[Lfs;
L100
    iconst_0
    istore 10
L40
    iload 10
    ldc -1749792099 (java.lang.Integer)
    aload 0
    getfield fv e:I
    imul
    if_icmpge L14
    iload 2
    bipush 12
    if_icmpne L101
    new java/lang/IllegalStateException
    dup
    invokespecial java/lang/IllegalStateException <init>:()V
    athrow
L101
    aload 0
    getfield fv a:[I
    iload 10
    iaload
    istore 11
    goto L81
L102
    iconst_0
    istore 10
    goto L69
L21
    iload 10
    ldc -1749792099 (java.lang.Integer)
    aload 0
    getfield fv e:I
    imul
    if_icmpge L41
    iload 2
    bipush 12
    if_icmpne L68
    new java/lang/IllegalStateException
    dup
    invokespecial java/lang/IllegalStateException <init>:()V
    athrow
L89
    iconst_0
    istore 13
L103
    iload 13
    iload 12
    if_icmpge L36
    iload 2
    bipush 12
    if_icmpne L104
    new java/lang/IllegalStateException
    dup
    invokespecial java/lang/IllegalStateException <init>:()V
    athrow
L66
    iload 10
    aload 0
    getfield fv e:I
    ldc -1749792099 (java.lang.Integer)
    imul
    if_icmpge L102
    iload 2
    bipush 12
    if_icmpne L99
    new java/lang/IllegalStateException
    dup
    invokespecial java/lang/IllegalStateException <init>:()V
    athrow
L67
    iconst_0
    istore 8
    goto L93
L71
    aload 0
    getfield fv i:[I
    aload 0
    getfield fv a:[I
    iload 10
    iaload
    aload 5
    ldc 391069551 (java.lang.Integer)
    invokevirtual dh q:(I)I
    iastore
    iinc 10 1
    goto L69
L104
    aload 0
    getfield fv f:[[I
    iload 11
    aaload
    aload 0
    getfield fv r:[[I
    iload 11
    aaload
    iload 13
    iaload
    aload 5
    ldc -1978541479 (java.lang.Integer)
    invokevirtual dh x:(I)I
    iastore
    iinc 13 1
    goto L103
L105
    new java/lang/StringBuilder
    dup
    invokespecial java/lang/StringBuilder <init>:()V
    ldc "fv.e(" (java.lang.String)
    invokevirtual java/lang/StringBuilder append:(Ljava/lang/String;)Ljava/lang/StringBuilder;
    ldc 41 (java.lang.Integer)
    invokevirtual java/lang/StringBuilder append:(C)Ljava/lang/StringBuilder;
    invokevirtual java/lang/StringBuilder toString:()Ljava/lang/String;
    invokestatic k a:(Ljava/lang/Throwable;Ljava/lang/String;)Lee;
    athrow
