fv f (IIB)[BL1
    iload 1
    iflt L2
    goto L3
L4
    iload 4
    ifne L5
    iload 3
    bipush 14
    if_icmpne L6
    new java/lang/IllegalStateException
    dup
    invokespecial java/lang/IllegalStateException <init>:()V
    athrow
L7
    aload 0
    getfield fv h:[[Ljava/lang/Object;
    iload 1
    aaload
    ifnull L2
    iload 3
    bipush 14
    if_icmpne L8
    new java/lang/IllegalStateException
    dup
    invokespecial java/lang/IllegalStateException <init>:()V
    athrow
L8
    iload 2
    iflt L2
    iload 3
    bipush 14
    if_icmpne L9
    new java/lang/IllegalStateException
    dup
    invokespecial java/lang/IllegalStateException <init>:()V
    athrow
L9
    iload 2
    aload 0
    getfield fv h:[[Ljava/lang/Object;
    iload 1
    aaload
    arraylength
    if_icmplt L10
    iload 3
    bipush 14
    if_icmpne L2
    new java/lang/IllegalStateException
    dup
    invokespecial java/lang/IllegalStateException <init>:()V
    athrow
L2
    aconst_null
    areturn
L10
    aload 0
    getfield fv h:[[Ljava/lang/Object;
    iload 1
    aaload
    iload 2
    aaload
    ifnonnull L5
    iload 3
    bipush 14
    if_icmpne L11
    new java/lang/IllegalStateException
    dup
    invokespecial java/lang/IllegalStateException <init>:()V
    athrow
L3
    iload 1
    aload 0
    getfield fv h:[[Ljava/lang/Object;
    arraylength
    if_icmpge L2
    iload 3
    bipush 14
    if_icmpne L7
    new java/lang/IllegalStateException
    dup
    invokespecial java/lang/IllegalStateException <init>:()V
    athrow
L12
    aload 0
    iload 1
    ldc 1988208330 (java.lang.Integer)
    invokevirtual fv o:(II)V
L13
    aload 0
    iload 1
    aconst_null
    ldc -1866589529 (java.lang.Integer)
    invokevirtual fv z:(I[II)Z
    istore 4
    goto L4
L14
    iload 4
    ifne L5
    iload 3
    bipush 14
    if_icmpne L12
    new java/lang/IllegalStateException
    dup
    invokespecial java/lang/IllegalStateException <init>:()V
    athrow
L11
    aload 0
    iload 1
    aconst_null
    ldc 2892507 (java.lang.Integer)
    invokevirtual fv z:(I[II)Z
    istore 4
    goto L14
L6
    aconst_null
    areturn
L5
    aload 0
    getfield fv h:[[Ljava/lang/Object;
    iload 1
    aaload
    iload 2
    aaload
    iconst_0
    ldc 1308344614 (java.lang.Integer)
    invokestatic b r:(Ljava/lang/Object;ZI)[B
    astore 4
L15
    aload 4
    areturn
L16
    new java/lang/StringBuilder
    dup
    invokespecial java/lang/StringBuilder <init>:()V
    ldc "fv.f(" (java.lang.String)
    invokevirtual java/lang/StringBuilder append:(Ljava/lang/String;)Ljava/lang/StringBuilder;
    ldc 41 (java.lang.Integer)
    invokevirtual java/lang/StringBuilder append:(C)Ljava/lang/StringBuilder;
    invokevirtual java/lang/StringBuilder toString:()Ljava/lang/String;
    invokestatic k a:(Ljava/lang/Throwable;Ljava/lang/String;)Lee;
    athrow
