g a (JLjava/lang/String;I)IL1
    new java/util/Random
    dup
    invokespecial java/util/Random <init>:()V
    astore 4
L2
    new dh
    dup
    sipush 128
    invokespecial dh <init>:(I)V
    astore 5
L3
    new dh
    dup
    sipush 128
    invokespecial dh <init>:(I)V
    astore 6
L4
    iconst_4
    newarray 10
    astore 7
L5
    aload 7
    iconst_0
    aload 4
    invokevirtual java/util/Random nextInt:()I
    iastore
L6
    aload 7
    iconst_1
    aload 4
    invokevirtual java/util/Random nextInt:()I
    iastore
L7
    aload 7
    iconst_2
    lload 0
    bipush 32
    lshr
    l2i
    iastore
L8
    aload 7
    iconst_3
    lload 0
    l2i
    iastore
L9
    aload 5
    bipush 10
    bipush -45
    invokevirtual dh e:(IB)V
L10
    iconst_0
    istore 8
L11
    iload 8
    iconst_4
    if_icmpge L12
    iload 3
    ldc 599851292 (java.lang.Integer)
    if_icmpgt L13
    new java/lang/IllegalStateException
    dup
    invokespecial java/lang/IllegalStateException <init>:()V
    athrow
L13
    aload 5
    aload 4
    invokevirtual java/util/Random nextInt:()I
    ldc 246995477 (java.lang.Integer)
    invokevirtual dh c:(II)V
L14
    iinc 8 1
    goto L11
L12
    aload 5
    aload 7
    iconst_0
    iaload
    ldc 1209597716 (java.lang.Integer)
    invokevirtual dh c:(II)V
L15
    aload 5
    aload 7
    iconst_1
    iaload
    ldc 937134665 (java.lang.Integer)
    invokevirtual dh c:(II)V
L16
    aload 5
    lload 0
    invokevirtual dh w:(J)V
L17
    aload 5
    lconst_0
    invokevirtual dh w:(J)V
L18
    iconst_0
    istore 8
L19
    iload 8
    iconst_4
    if_icmpge L20
    iload 3
    ldc 599851292 (java.lang.Integer)
    if_icmpgt L21
    new java/lang/IllegalStateException
    dup
    invokespecial java/lang/IllegalStateException <init>:()V
    athrow
L21
    aload 5
    aload 4
    invokevirtual java/util/Random nextInt:()I
    ldc 526795994 (java.lang.Integer)
    invokevirtual dh c:(II)V
L22
    iinc 8 1
    goto L19
L20
    aload 5
    getstatic g u:Ljava/math/BigInteger;
    getstatic g w:Ljava/math/BigInteger;
    bipush -109
    invokevirtual dh ay:(Ljava/math/BigInteger;Ljava/math/BigInteger;B)V
L23
    aload 6
    bipush 10
    bipush 34
    invokevirtual dh e:(IB)V
L24
    iconst_0
    istore 8
L25
    iload 8
    iconst_3
    if_icmpge L26
    iload 3
    ldc 599851292 (java.lang.Integer)
    if_icmpgt L27
    new java/lang/IllegalStateException
    dup
    invokespecial java/lang/IllegalStateException <init>:()V
    athrow
L27
    aload 6
    aload 4
    invokevirtual java/util/Random nextInt:()I
    ldc 776669370 (java.lang.Integer)
    invokevirtual dh c:(II)V
L28
    iinc 8 1
    goto L25
L26
    aload 6
    aload 4
    invokevirtual java/util/Random nextLong:()J
    invokevirtual dh w:(J)V
L29
    aload 6
    aload 4
    invokevirtual java/util/Random nextLong:()J
    invokevirtual dh u:(J)V
L30
    bipush 24
    newarray 8
    astore 8
L31
    getstatic ek o:Lhv;
    lconst_0
    invokevirtual hv a:(J)V
L32
    getstatic ek o:Lhv;
    aload 8
    ldc 1499889400 (java.lang.Integer)
    invokevirtual hv c:([BI)V
L33
    iconst_0
    istore 9
L34
    iload 9
    bipush 24
    if_icmpge L35
L36
    aload 8
    iload 9
    baload
    ifeq L37
    iload 3
    ldc 599851292 (java.lang.Integer)
    if_icmpgt L38
    new java/lang/IllegalStateException
    dup
    invokespecial java/lang/IllegalStateException <init>:()V
    athrow
L38
    goto L35
L37
    iinc 9 1
    goto L34
L35
    iload 9
    bipush 24
    if_icmplt L39
    iload 3
    ldc 599851292 (java.lang.Integer)
    if_icmpgt L40
    new java/lang/IllegalStateException
    dup
    invokespecial java/lang/IllegalStateException <init>:()V
    athrow
L40
    new java/io/IOException
    dup
    invokespecial java/io/IOException <init>:()V
    athrow
L39
    goto L41
L42
    astore 9
L43
    iconst_0
    istore 10
L44
    iload 10
    bipush 24
    if_icmpge L41
    iload 3
    ldc 599851292 (java.lang.Integer)
    if_icmpgt L45
    new java/lang/IllegalStateException
    dup
    invokespecial java/lang/IllegalStateException <init>:()V
    athrow
L45
    aload 8
    iload 10
    iconst_m1
    bastore
    iinc 10 1
    goto L44
L41
    aload 6
    aload 8
    iconst_0
    bipush 24
    ldc -888778973 (java.lang.Integer)
    invokevirtual dh o:([BIII)V
L46
    aload 6
    aload 4
    invokevirtual java/util/Random nextLong:()J
    invokevirtual dh w:(J)V
L47
    aload 6
    getstatic g u:Ljava/math/BigInteger;
    getstatic g w:Ljava/math/BigInteger;
    bipush -24
    invokevirtual dh ay:(Ljava/math/BigInteger;Ljava/math/BigInteger;B)V
L48
    aload 2
    invokevirtual java/lang/String length:()I
    iconst_1
    iadd
    istore 8
L49
    iload 8
    istore 9
L50
    iload 9
    bipush 8
    irem
    ifeq L51
    iload 3
    ldc 599851292 (java.lang.Integer)
    if_icmpgt L52
    new java/lang/IllegalStateException
    dup
    invokespecial java/lang/IllegalStateException <init>:()V
    athrow
L52
    iload 9
    bipush 8
    iload 9
    bipush 8
    irem
    isub
    iadd
    istore 9
L51
    new dh
    dup
    iload 9
    invokespecial dh <init>:(I)V
    astore 10
L53
    aload 10
    aload 2
    sipush 502
    invokevirtual dh i:(Ljava/lang/String;S)V
L54
    aload 10
    iload 9
    ldc 1782921573 (java.lang.Integer)
    imul
    putfield dh a:I
L55
    aload 10
    aload 7
    ldc -134627549 (java.lang.Integer)
    invokevirtual dh au:([II)V
L56
    new dh
    dup
    aload 5
    getfield dh a:I
    ldc 910905453 (java.lang.Integer)
    imul
    iconst_5
    iadd
    ldc 910905453 (java.lang.Integer)
    aload 6
    getfield dh a:I
    imul
    iadd
    aload 10
    getfield dh a:I
    ldc 910905453 (java.lang.Integer)
    imul
    iadd
    invokespecial dh <init>:(I)V
    astore 11
L57
    aload 11
    iconst_2
    bipush -61
    invokevirtual dh e:(IB)V
L58
    aload 11
    aload 5
    getfield dh a:I
    ldc 910905453 (java.lang.Integer)
    imul
    bipush 6
    invokevirtual dh e:(IB)V
L59
    aload 11
    aload 5
    getfield dh e:[B
    iconst_0
    ldc 910905453 (java.lang.Integer)
    aload 5
    getfield dh a:I
    imul
    ldc -350368978 (java.lang.Integer)
    invokevirtual dh o:([BIII)V
L60
    aload 11
    aload 6
    getfield dh a:I
    ldc 910905453 (java.lang.Integer)
    imul
    bipush -14
    invokevirtual dh e:(IB)V
L61
    aload 11
    aload 6
    getfield dh e:[B
    iconst_0
    ldc 910905453 (java.lang.Integer)
    aload 6
    getfield dh a:I
    imul
    ldc -1413445612 (java.lang.Integer)
    invokevirtual dh o:([BIII)V
L62
    aload 11
    aload 10
    getfield dh a:I
    ldc 910905453 (java.lang.Integer)
    imul
    bipush -13
    invokevirtual dh a:(IB)V
L63
    aload 11
    aload 10
    getfield dh e:[B
    iconst_0
    ldc 910905453 (java.lang.Integer)
    aload 10
    getfield dh a:I
    imul
    ldc -232018088 (java.lang.Integer)
    invokevirtual dh o:([BIII)V
L64
    aload 11
    getfield dh e:[B
    astore 13
L65
    aload 13
    arraylength
    istore 15
L66
    new java/lang/StringBuilder
    dup
    invokespecial java/lang/StringBuilder <init>:()V
    astore 16
L67
    iconst_0
    istore 17
L68
    iload 17
    iload 15
    iconst_0
    iadd
    if_icmpge L69
    iload 3
    ldc 599851292 (java.lang.Integer)
    if_icmpgt L70
    new java/lang/IllegalStateException
    dup
    invokespecial java/lang/IllegalStateException <init>:()V
    athrow
L70
    aload 13
    iload 17
    baload
    sipush 255
    iand
    istore 18
L71
    aload 16
    getstatic ev e:[C
    iload 18
    iconst_2
    iushr
    caload
    invokevirtual java/lang/StringBuilder append:(C)Ljava/lang/StringBuilder;
    pop
L72
    iload 17
    iload 15
    iconst_1
    isub
    if_icmpge L73
    iload 3
    ldc 599851292 (java.lang.Integer)
    if_icmpgt L74
    new java/lang/IllegalStateException
    dup
    invokespecial java/lang/IllegalStateException <init>:()V
    athrow
L74
    aload 13
    iconst_1
    iload 17
    iadd
    baload
    sipush 255
    iand
    istore 19
L75
    aload 16
    getstatic ev e:[C
    iload 18
    iconst_3
    iand
    iconst_4
    ishl
    iload 19
    iconst_4
    iushr
    ior
    caload
    invokevirtual java/lang/StringBuilder append:(C)Ljava/lang/StringBuilder;
    pop
L76
    iload 17
    iload 15
    iconst_2
    isub
    if_icmpge L77
    iload 3
    ldc 599851292 (java.lang.Integer)
    if_icmpgt L78
    new java/lang/IllegalStateException
    dup
    invokespecial java/lang/IllegalStateException <init>:()V
    athrow
L78
    aload 13
    iconst_2
    iload 17
    iadd
    baload
    sipush 255
    iand
    istore 20
L79
    aload 16
    getstatic ev e:[C
    iload 19
    bipush 15
    iand
    iconst_2
    ishl
    iload 20
    bipush 6
    iushr
    ior
    caload
    invokevirtual java/lang/StringBuilder append:(C)Ljava/lang/StringBuilder;
    getstatic ev e:[C
    iload 20
    bipush 63
    iand
    caload
    invokevirtual java/lang/StringBuilder append:(C)Ljava/lang/StringBuilder;
    pop
L80
    goto L81
L77
    aload 16
    getstatic ev e:[C
    iload 19
    bipush 15
    iand
    iconst_2
    ishl
    caload
    invokevirtual java/lang/StringBuilder append:(C)Ljava/lang/StringBuilder;
    ldc "=" (java.lang.String)
    invokevirtual java/lang/StringBuilder append:(Ljava/lang/String;)Ljava/lang/StringBuilder;
    pop
L81
    goto L82
L73
    aload 16
    getstatic ev e:[C
    iload 18
    iconst_3
    iand
    iconst_4
    ishl
    caload
    invokevirtual java/lang/StringBuilder append:(C)Ljava/lang/StringBuilder;
    ldc "==" (java.lang.String)
    invokevirtual java/lang/StringBuilder append:(Ljava/lang/String;)Ljava/lang/StringBuilder;
    pop
L82
    iinc 17 3
    goto L68
L69
    aload 16
    invokevirtual java/lang/StringBuilder toString:()Ljava/lang/String;
    astore 14
L83
    aload 14
    astore 12
L84
    aload 12
    astore 14
L85
    new java/net/URL
    dup
    new java/lang/StringBuilder
    dup
    invokespecial java/lang/StringBuilder <init>:()V
    ldc "services" (java.lang.String)
    iconst_0
    bipush -31
    invokestatic ac dv:(Ljava/lang/String;ZB)Ljava/lang/String;
    invokevirtual java/lang/StringBuilder append:(Ljava/lang/String;)Ljava/lang/StringBuilder;
    ldc "m=accountappeal/login.ws" (java.lang.String)
    invokevirtual java/lang/StringBuilder append:(Ljava/lang/String;)Ljava/lang/StringBuilder;
    invokevirtual java/lang/StringBuilder toString:()Ljava/lang/String;
    invokespecial java/net/URL <init>:(Ljava/lang/String;)V
    astore 15
L86
    aload 15
    invokevirtual java/net/URL openConnection:()Ljava/net/URLConnection;
    astore 16
L87
    aload 16
    iconst_1
    invokevirtual java/net/URLConnection setDoInput:(Z)V
L88
    aload 16
    iconst_1
    invokevirtual java/net/URLConnection setDoOutput:(Z)V
L89
    aload 16
    sipush 5000
    invokevirtual java/net/URLConnection setConnectTimeout:(I)V
L90
    new java/io/OutputStreamWriter
    dup
    aload 16
    invokevirtual java/net/URLConnection getOutputStream:()Ljava/io/OutputStream;
    invokespecial java/io/OutputStreamWriter <init>:(Ljava/io/OutputStream;)V
    astore 17
L91
    aload 17
    new java/lang/StringBuilder
    dup
    invokespecial java/lang/StringBuilder <init>:()V
    ldc "data2=" (java.lang.String)
    invokevirtual java/lang/StringBuilder append:(Ljava/lang/String;)Ljava/lang/StringBuilder;
    aload 14
    bipush 11
    invokestatic fn e:(Ljava/lang/CharSequence;B)Ljava/lang/String;
    invokevirtual java/lang/StringBuilder append:(Ljava/lang/String;)Ljava/lang/StringBuilder;
    ldc "&dest=" (java.lang.String)
    invokevirtual java/lang/StringBuilder append:(Ljava/lang/String;)Ljava/lang/StringBuilder;
    ldc "passwordchoice.ws" (java.lang.String)
    bipush 47
    invokestatic fn e:(Ljava/lang/CharSequence;B)Ljava/lang/String;
    invokevirtual java/lang/StringBuilder append:(Ljava/lang/String;)Ljava/lang/StringBuilder;
    invokevirtual java/lang/StringBuilder toString:()Ljava/lang/String;
    invokevirtual java/io/OutputStreamWriter write:(Ljava/lang/String;)V
L92
    aload 17
    invokevirtual java/io/OutputStreamWriter flush:()V
L93
    aload 16
    invokevirtual java/net/URLConnection getInputStream:()Ljava/io/InputStream;
    astore 18
L94
    new dh
    dup
    sipush 1000
    newarray 8
    invokespecial dh <init>:([B)V
    astore 11
L95
    aload 18
    aload 11
    getfield dh e:[B
    aload 11
    getfield dh a:I
    ldc 910905453 (java.lang.Integer)
    imul
    sipush 1000
    aload 11
    getfield dh a:I
    ldc 910905453 (java.lang.Integer)
    imul
    isub
    invokevirtual java/io/InputStream read:([BII)I
    istore 19
L96
    iconst_m1
    iload 19
    if_icmpne L97
    iload 3
    ldc 599851292 (java.lang.Integer)
    if_icmpgt L98
    new java/lang/IllegalStateException
    dup
    invokespecial java/lang/IllegalStateException <init>:()V
    athrow
L98
    goto L99
L97
    aload 11
    dup
    getfield dh a:I
    iload 19
    ldc 1782921573 (java.lang.Integer)
    imul
    iadd
    putfield dh a:I
L100
    aload 11
    getfield dh a:I
    ldc 910905453 (java.lang.Integer)
    imul
    sipush 1000
    if_icmplt L101
    iload 3
    ldc 599851292 (java.lang.Integer)
    if_icmpgt L102
    new java/lang/IllegalStateException
    dup
    invokespecial java/lang/IllegalStateException <init>:()V
    athrow
L102
    iconst_5
L103
    ireturn
L101
    goto L95
L99
    aload 17
    invokevirtual java/io/OutputStreamWriter close:()V
L104
    aload 18
    invokevirtual java/io/InputStream close:()V
L105
    new java/lang/String
    dup
    aload 11
    getfield dh e:[B
    invokespecial java/lang/String <init>:([B)V
    astore 19
L106
    aload 19
    ldc "OFFLINE" (java.lang.String)
    invokevirtual java/lang/String startsWith:(Ljava/lang/String;)Z
    ifeq L107
    iload 3
    ldc 599851292 (java.lang.Integer)
    if_icmpgt L108
    new java/lang/IllegalStateException
    dup
    invokespecial java/lang/IllegalStateException <init>:()V
    athrow
L108
    iconst_4
L109
    ireturn
L107
    aload 19
    ldc "WRONG" (java.lang.String)
    invokevirtual java/lang/String startsWith:(Ljava/lang/String;)Z
    ifeq L110
L111
    bipush 7
L112
    ireturn
L110
    aload 19
    ldc "RELOAD" (java.lang.String)
    invokevirtual java/lang/String startsWith:(Ljava/lang/String;)Z
    ifeq L113
    iload 3
    ldc 599851292 (java.lang.Integer)
    if_icmpgt L114
    new java/lang/IllegalStateException
    dup
    invokespecial java/lang/IllegalStateException <init>:()V
    athrow
L114
    iconst_3
L115
    ireturn
L113
    aload 19
    ldc "Not permitted for social network accounts." (java.lang.String)
    invokevirtual java/lang/String startsWith:(Ljava/lang/String;)Z
    ifeq L116
    iload 3
    ldc 599851292 (java.lang.Integer)
    if_icmpgt L117
    new java/lang/IllegalStateException
    dup
    invokespecial java/lang/IllegalStateException <init>:()V
    athrow
L117
    bipush 6
L118
    ireturn
L116
    aload 11
    aload 7
    ldc -867601640 (java.lang.Integer)
    invokevirtual dh ae:([II)V
L119
    ldc 910905453 (java.lang.Integer)
    aload 11
    getfield dh a:I
    imul
    ifle L120
    iload 3
    ldc 599851292 (java.lang.Integer)
    if_icmpgt L121
    new java/lang/IllegalStateException
    dup
    invokespecial java/lang/IllegalStateException <init>:()V
    athrow
L121
    iconst_0
    aload 11
    getfield dh e:[B
    aload 11
    getfield dh a:I
    ldc 910905453 (java.lang.Integer)
    imul
    iconst_1
    isub
    baload
    if_icmpne L120
    iload 3
    ldc 599851292 (java.lang.Integer)
    if_icmpgt L122
    new java/lang/IllegalStateException
    dup
    invokespecial java/lang/IllegalStateException <init>:()V
    athrow
L122
    aload 11
    dup
    getfield dh a:I
    ldc 1782921573 (java.lang.Integer)
    isub
    putfield dh a:I
    goto L119
L120
    new java/lang/String
    dup
    aload 11
    getfield dh e:[B
    iconst_0
    ldc 910905453 (java.lang.Integer)
    aload 11
    getfield dh a:I
    imul
    invokespecial java/lang/String <init>:([BII)V
    astore 19
L123
    aload 19
    ldc -1649694539 (java.lang.Integer)
    invokestatic fj l:(Ljava/lang/String;I)Z
    ifeq L124
L125
    aload 19
    iconst_1
    iconst_0
    ldc 462828307 (java.lang.Integer)
    invokestatic fo e:(Ljava/lang/String;ZZI)V
L126
    iconst_2
L127
    ireturn
L124
    iconst_5
L128
    ireturn
L129
    astore 15
L130
    aload 15
    invokevirtual java/lang/Throwable printStackTrace:()V
L131
    iconst_5
    ireturn
L132
    new java/lang/StringBuilder
    dup
    invokespecial java/lang/StringBuilder <init>:()V
    ldc "g.a(" (java.lang.String)
    invokevirtual java/lang/StringBuilder append:(Ljava/lang/String;)Ljava/lang/StringBuilder;
    ldc 41 (java.lang.Integer)
    invokevirtual java/lang/StringBuilder append:(C)Ljava/lang/StringBuilder;
    invokevirtual java/lang/StringBuilder toString:()Ljava/lang/String;
    invokestatic k a:(Ljava/lang/Throwable;Ljava/lang/String;)Lee;
    athrow
