g q (IB)VL1
    iload 0
    bipush -3
    if_icmpne L2
    goto L3
L4
    return
L2
    iload 0
    bipush -2
    if_icmpne L5
    iload 1
    iconst_1
    if_icmpne L6
    new java/lang/IllegalStateException
    dup
    invokespecial java/lang/IllegalStateException <init>:()V
    athrow
L7
    getstatic et cc:Ljava/lang/String;
    getstatic et cs:Ljava/lang/String;
    getstatic et cz:Ljava/lang/String;
    sipush 5268
    invokestatic dd w:(Ljava/lang/String;Ljava/lang/String;Ljava/lang/String;S)V
    goto L8
L5
    iconst_m1
    iload 0
    if_icmpne L9
    iload 1
    iconst_1
    if_icmpne L10
    new java/lang/IllegalStateException
    dup
    invokespecial java/lang/IllegalStateException <init>:()V
    athrow
L8
    bipush 10
    bipush 82
    invokestatic dh g:(IB)V
    goto L11
L9
    iconst_3
    iload 0
    if_icmpne L12
    iload 1
    iconst_1
    if_icmpne L13
    new java/lang/IllegalStateException
    dup
    invokespecial java/lang/IllegalStateException <init>:()V
    athrow
L13
    getstatic et af:Ljava/lang/String;
    getstatic et as:Ljava/lang/String;
    getstatic et aa:Ljava/lang/String;
    sipush 30344
    invokestatic dd w:(Ljava/lang/String;Ljava/lang/String;Ljava/lang/String;S)V
    goto L8
L14
    bipush 56
    iload 0
    if_icmpne L15
    iload 1
    iconst_1
    if_icmpne L16
    new java/lang/IllegalStateException
    dup
    invokespecial java/lang/IllegalStateException <init>:()V
    athrow
L17
    getstatic et bl:Ljava/lang/String;
    getstatic et bk:Ljava/lang/String;
    getstatic et bm:Ljava/lang/String;
    sipush 26849
    invokestatic dd w:(Ljava/lang/String;Ljava/lang/String;Ljava/lang/String;S)V
    goto L8
L18
    iconst_5
    iload 0
    if_icmpne L19
    iload 1
    iconst_1
    if_icmpne L20
    new java/lang/IllegalStateException
    dup
    invokespecial java/lang/IllegalStateException <init>:()V
    athrow
L21
    getstatic et el:Ljava/lang/String;
    getstatic et ep:Ljava/lang/String;
    getstatic et ec:Ljava/lang/String;
    sipush 12556
    invokestatic dd w:(Ljava/lang/String;Ljava/lang/String;Ljava/lang/String;S)V
    goto L8
L22
    iload 0
    bipush 22
    if_icmpne L23
    iload 1
    iconst_1
    if_icmpne L7
    new java/lang/IllegalStateException
    dup
    invokespecial java/lang/IllegalStateException <init>:()V
    athrow
L24
    getstatic et bv:Ljava/lang/String;
    getstatic et bc:Ljava/lang/String;
    getstatic et br:Ljava/lang/String;
    sipush 27052
    invokestatic dd w:(Ljava/lang/String;Ljava/lang/String;Ljava/lang/String;S)V
    goto L8
L25
    iload 0
    bipush 7
    if_icmpne L26
    iload 1
    iconst_1
    if_icmpne L27
    new java/lang/IllegalStateException
    dup
    invokespecial java/lang/IllegalStateException <init>:()V
    athrow
L11
    return
L26
    iload 0
    bipush 8
    if_icmpne L28
    iload 1
    iconst_1
    if_icmpne L29
    new java/lang/IllegalStateException
    dup
    invokespecial java/lang/IllegalStateException <init>:()V
    athrow
L29
    getstatic et bx:Ljava/lang/String;
    getstatic et bd:Ljava/lang/String;
    getstatic et bb:Ljava/lang/String;
    sipush 17682
    invokestatic dd w:(Ljava/lang/String;Ljava/lang/String;Ljava/lang/String;S)V
    goto L8
L28
    iload 0
    bipush 9
    if_icmpne L30
    iload 1
    iconst_1
    if_icmpne L31
    new java/lang/IllegalStateException
    dup
    invokespecial java/lang/IllegalStateException <init>:()V
    athrow
L32
    getstatic et ei:Ljava/lang/String;
    getstatic et ed:Ljava/lang/String;
    getstatic et et:Ljava/lang/String;
    sipush 31917
    invokestatic dd w:(Ljava/lang/String;Ljava/lang/String;Ljava/lang/String;S)V
    goto L8
L33
    bipush 11
    bipush 76
    invokestatic dh g:(IB)V
    goto L4
L34
    getstatic et bi:Ljava/lang/String;
    getstatic et by:Ljava/lang/String;
    getstatic et bz:Ljava/lang/String;
    sipush 31578
    invokestatic dd w:(Ljava/lang/String;Ljava/lang/String;Ljava/lang/String;S)V
    goto L8
L35
    bipush 11
    iload 0
    if_icmpne L36
    iload 1
    iconst_1
    if_icmpne L37
    new java/lang/IllegalStateException
    dup
    invokespecial java/lang/IllegalStateException <init>:()V
    athrow
L37
    getstatic et bh:Ljava/lang/String;
    getstatic et bt:Ljava/lang/String;
    getstatic et bs:Ljava/lang/String;
    sipush 8371
    invokestatic dd w:(Ljava/lang/String;Ljava/lang/String;Ljava/lang/String;S)V
    goto L8
L36
    iload 0
    bipush 12
    if_icmpne L38
    iload 1
    iconst_1
    if_icmpne L39
    new java/lang/IllegalStateException
    dup
    invokespecial java/lang/IllegalStateException <init>:()V
    athrow
L40
    getstatic et dw:Ljava/lang/String;
    getstatic et dh:Ljava/lang/String;
    getstatic et du:Ljava/lang/String;
    sipush 28974
    invokestatic dd w:(Ljava/lang/String;Ljava/lang/String;Ljava/lang/String;S)V
    goto L8
L41
    getstatic et ea:Ljava/lang/String;
    getstatic et es:Ljava/lang/String;
    getstatic et ef:Ljava/lang/String;
    sipush 29242
    invokestatic dd w:(Ljava/lang/String;Ljava/lang/String;Ljava/lang/String;S)V
    goto L33
L42
    bipush 24
    iload 0
    if_icmpne L43
    iload 1
    iconst_1
    if_icmpne L44
    new java/lang/IllegalStateException
    dup
    invokespecial java/lang/IllegalStateException <init>:()V
    athrow
L45
    bipush 14
    iload 0
    if_icmpne L46
    iload 1
    iconst_1
    if_icmpne L47
    return
L47
    getstatic et ci:Ljava/lang/String;
    getstatic et cg:Ljava/lang/String;
    getstatic et cd:Ljava/lang/String;
    sipush 10252
    invokestatic dd w:(Ljava/lang/String;Ljava/lang/String;Ljava/lang/String;S)V
    goto L8
L48
    return
L46
    bipush 16
    iload 0
    if_icmpne L49
    iload 1
    iconst_1
    if_icmpne L50
    return
L51
    getstatic et da:Ljava/lang/String;
    getstatic et dg:Ljava/lang/String;
    getstatic et di:Ljava/lang/String;
    sipush 29171
    invokestatic dd w:(Ljava/lang/String;Ljava/lang/String;Ljava/lang/String;S)V
    goto L8
L52
    getstatic et cj:Ljava/lang/String;
    getstatic et cq:Ljava/lang/String;
    getstatic et ct:Ljava/lang/String;
    sipush 26962
    invokestatic dd w:(Ljava/lang/String;Ljava/lang/String;Ljava/lang/String;S)V
    goto L8
L53
    bipush 18
    iload 0
    if_icmpne L54
    getstatic et cx:Ljava/lang/String;
    getstatic et cu:Ljava/lang/String;
    getstatic et ck:Ljava/lang/String;
    sipush 3750
    invokestatic dd w:(Ljava/lang/String;Ljava/lang/String;Ljava/lang/String;S)V
    goto L8
L54
    iload 0
    bipush 19
    if_icmpne L55
    goto L56
L20
    getstatic et bw:Ljava/lang/String;
    getstatic et bp:Ljava/lang/String;
    getstatic et be:Ljava/lang/String;
    sipush 20243
    invokestatic dd w:(Ljava/lang/String;Ljava/lang/String;Ljava/lang/String;S)V
    goto L8
L55
    bipush 20
    iload 0
    if_icmpne L22
    iload 1
    iconst_1
    if_icmpne L57
    new java/lang/IllegalStateException
    dup
    invokespecial java/lang/IllegalStateException <init>:()V
    athrow
L23
    bipush 23
    iload 0
    if_icmpne L42
    iload 1
    iconst_1
    if_icmpne L58
    new java/lang/IllegalStateException
    dup
    invokespecial java/lang/IllegalStateException <init>:()V
    athrow
L12
    iload 0
    iconst_4
    if_icmpne L18
    iload 1
    iconst_1
    if_icmpne L17
    new java/lang/IllegalStateException
    dup
    invokespecial java/lang/IllegalStateException <init>:()V
    athrow
L27
    getstatic et bu:Ljava/lang/String;
    getstatic et ba:Ljava/lang/String;
    getstatic et bf:Ljava/lang/String;
    sipush 26789
    invokestatic dd w:(Ljava/lang/String;Ljava/lang/String;Ljava/lang/String;S)V
    goto L8
L19
    bipush 6
    iload 0
    if_icmpne L25
    iload 1
    iconst_1
    if_icmpne L24
    new java/lang/IllegalStateException
    dup
    invokespecial java/lang/IllegalStateException <init>:()V
    athrow
L58
    getstatic et ca:Ljava/lang/String;
    getstatic et dd:Ljava/lang/String;
    getstatic et dk:Ljava/lang/String;
    sipush 28414
    invokestatic dd w:(Ljava/lang/String;Ljava/lang/String;Ljava/lang/String;S)V
    goto L8
L30
    bipush 10
    iload 0
    if_icmpne L35
    iload 1
    iconst_1
    if_icmpne L34
    return
L44
    getstatic et df:Ljava/lang/String;
    getstatic et dp:Ljava/lang/String;
    getstatic et dc:Ljava/lang/String;
    sipush 5098
    invokestatic dd w:(Ljava/lang/String;Ljava/lang/String;Ljava/lang/String;S)V
    goto L8
L43
    iload 0
    bipush 25
    if_icmpne L59
    goto L40
L3
    getstatic et at:Ljava/lang/String;
    getstatic et al:Ljava/lang/String;
    getstatic et ak:Ljava/lang/String;
    sipush 1870
    invokestatic dd w:(Ljava/lang/String;Ljava/lang/String;Ljava/lang/String;S)V
    goto L8
L59
    bipush 26
    iload 0
    if_icmpne L60
    getstatic et dm:Ljava/lang/String;
    getstatic et dj:Ljava/lang/String;
    getstatic et dt:Ljava/lang/String;
    sipush 32604
    invokestatic dd w:(Ljava/lang/String;Ljava/lang/String;Ljava/lang/String;S)V
    goto L8
L60
    bipush 27
    iload 0
    if_icmpne L61
    getstatic et dl:Ljava/lang/String;
    getstatic et dv:Ljava/lang/String;
    getstatic et ds:Ljava/lang/String;
    sipush 18499
    invokestatic dd w:(Ljava/lang/String;Ljava/lang/String;Ljava/lang/String;S)V
    goto L8
L61
    iload 0
    bipush 31
    if_icmpne L62
    iload 1
    iconst_1
    if_icmpne L51
    new java/lang/IllegalStateException
    dup
    invokespecial java/lang/IllegalStateException <init>:()V
    athrow
L57
    getstatic et co:Ljava/lang/String;
    getstatic et cn:Ljava/lang/String;
    getstatic et cy:Ljava/lang/String;
    sipush 31406
    invokestatic dd w:(Ljava/lang/String;Ljava/lang/String;Ljava/lang/String;S)V
    goto L8
L62
    iload 0
    bipush 32
    if_icmpne L63
    iload 1
    iconst_1
    if_icmpne L64
    new java/lang/IllegalStateException
    dup
    invokespecial java/lang/IllegalStateException <init>:()V
    athrow
L38
    bipush 13
    iload 0
    if_icmpne L45
    iload 1
    iconst_1
    if_icmpne L65
    new java/lang/IllegalStateException
    dup
    invokespecial java/lang/IllegalStateException <init>:()V
    athrow
L63
    bipush 37
    iload 0
    if_icmpne L66
    iload 1
    iconst_1
    if_icmpne L21
    return
L6
    getstatic et ar:Ljava/lang/String;
    getstatic et aq:Ljava/lang/String;
    getstatic et ac:Ljava/lang/String;
    sipush 31690
    invokestatic dd w:(Ljava/lang/String;Ljava/lang/String;Ljava/lang/String;S)V
    goto L8
L66
    iload 0
    bipush 38
    if_icmpne L67
    iload 1
    iconst_1
    if_icmpne L68
    new java/lang/IllegalStateException
    dup
    invokespecial java/lang/IllegalStateException <init>:()V
    athrow
L68
    getstatic et ej:Ljava/lang/String;
    getstatic et eo:Ljava/lang/String;
    getstatic et ew:Ljava/lang/String;
    sipush 27055
    invokestatic dd w:(Ljava/lang/String;Ljava/lang/String;Ljava/lang/String;S)V
    goto L8
L67
    bipush 55
    iload 0
    if_icmpne L14
    iload 1
    iconst_1
    if_icmpne L69
    new java/lang/IllegalStateException
    dup
    invokespecial java/lang/IllegalStateException <init>:()V
    athrow
L69
    getstatic et eh:Ljava/lang/String;
    getstatic et ex:Ljava/lang/String;
    getstatic et ey:Ljava/lang/String;
    sipush 21018
    invokestatic dd w:(Ljava/lang/String;Ljava/lang/String;Ljava/lang/String;S)V
    goto L8
L10
    getstatic et ad:Ljava/lang/String;
    getstatic et an:Ljava/lang/String;
    getstatic et az:Ljava/lang/String;
    sipush 24211
    invokestatic dd w:(Ljava/lang/String;Ljava/lang/String;Ljava/lang/String;S)V
    goto L8
L16
    getstatic et ee:Ljava/lang/String;
    getstatic et ek:Ljava/lang/String;
    getstatic et em:Ljava/lang/String;
    sipush 12910
    invokestatic dd w:(Ljava/lang/String;Ljava/lang/String;Ljava/lang/String;S)V
L70
    bipush 11
    bipush 126
    invokestatic dh g:(IB)V
    goto L48
L49
    iload 0
    bipush 17
    if_icmpne L53
    iload 1
    iconst_1
    if_icmpne L52
    return
L15
    iload 0
    bipush 57
    if_icmpne L32
    iload 1
    iconst_1
    if_icmpne L41
    return
L56
    getstatic et cr:Ljava/lang/String;
    getstatic et cw:Ljava/lang/String;
    getstatic et cl:Ljava/lang/String;
    sipush 13544
    invokestatic dd w:(Ljava/lang/String;Ljava/lang/String;Ljava/lang/String;S)V
    goto L8
L65
    getstatic et ch:Ljava/lang/String;
    getstatic et cb:Ljava/lang/String;
    getstatic et cv:Ljava/lang/String;
    sipush 25012
    invokestatic dd w:(Ljava/lang/String;Ljava/lang/String;Ljava/lang/String;S)V
    goto L8
L50
    getstatic et cp:Ljava/lang/String;
    getstatic et ce:Ljava/lang/String;
    getstatic et cm:Ljava/lang/String;
    sipush 28931
    invokestatic dd w:(Ljava/lang/String;Ljava/lang/String;Ljava/lang/String;S)V
    goto L8
L39
    getstatic et bo:Ljava/lang/String;
    getstatic et bg:Ljava/lang/String;
    getstatic et cf:Ljava/lang/String;
    sipush 14215
    invokestatic dd w:(Ljava/lang/String;Ljava/lang/String;Ljava/lang/String;S)V
    goto L8
L31
    getstatic et bj:Ljava/lang/String;
    getstatic et bq:Ljava/lang/String;
    getstatic et bn:Ljava/lang/String;
    sipush 2225
    invokestatic dd w:(Ljava/lang/String;Ljava/lang/String;Ljava/lang/String;S)V
    goto L8
L64
    getstatic et dz:Ljava/lang/String;
    getstatic et dr:Ljava/lang/String;
    getstatic et dq:Ljava/lang/String;
    sipush 20830
    invokestatic dd w:(Ljava/lang/String;Ljava/lang/String;Ljava/lang/String;S)V
    goto L8
L71
    new java/lang/StringBuilder
    dup
    invokespecial java/lang/StringBuilder <init>:()V
    ldc "g.q(" (java.lang.String)
    invokevirtual java/lang/StringBuilder append:(Ljava/lang/String;)Ljava/lang/StringBuilder;
    ldc 41 (java.lang.Integer)
    invokevirtual java/lang/StringBuilder append:(C)Ljava/lang/StringBuilder;
    invokevirtual java/lang/StringBuilder toString:()Ljava/lang/String;
    invokestatic k a:(Ljava/lang/Throwable;Ljava/lang/String;)Lee;
    athrow
