g s ([BI)VL1
    new dh
    dup
    aload 0
    invokespecial dh <init>:([B)V
    astore 2
    goto L2
L3
    iconst_0
    istore 4
    goto L4
L5
    aload 2
    ldc 1909863834 (java.lang.Integer)
    invokevirtual dh q:(I)I
    ldc 636218001 (java.lang.Integer)
    imul
    putstatic by e:I
L6
    getstatic by e:I
    ldc 434443889 (java.lang.Integer)
    imul
    newarray 10
    putstatic hg c:[I
L7
    ldc 434443889 (java.lang.Integer)
    getstatic by e:I
    imul
    newarray 10
    putstatic eb u:[I
L8
    ldc 434443889 (java.lang.Integer)
    getstatic by e:I
    imul
    newarray 10
    putstatic by w:[I
L9
    ldc 434443889 (java.lang.Integer)
    getstatic by e:I
    imul
    newarray 10
    putstatic by i:[I
    goto L10
L11
    iconst_0
    istore 4
    goto L12
L13
    aload 2
    ldc 1782921573 (java.lang.Integer)
    aload 0
    arraylength
    bipush 7
    isub
    ldc -819416184 (java.lang.Integer)
    getstatic by e:I
    imul
    isub
    imul
    putfield dh a:I
L14
    aload 2
    ldc -1722722844 (java.lang.Integer)
    invokevirtual dh q:(I)I
    ldc -1936787195 (java.lang.Integer)
    imul
    putstatic by a:I
    goto L15
L16
    getstatic by i:[I
    iload 4
    iaload
    istore 6
    goto L17
L18
    aload 8
    iload 10
    aload 2
    bipush 105
    invokevirtual dh y:(B)B
    bastore
    iinc 10 1
    goto L19
L20
    iconst_0
    istore 4
L21
    iload 4
    ldc 434443889 (java.lang.Integer)
    getstatic by e:I
    imul
    if_icmpge L3
    iload 1
    ldc 1580525879 (java.lang.Integer)
    if_icmpeq L22
    new java/lang/IllegalStateException
    dup
    invokespecial java/lang/IllegalStateException <init>:()V
    athrow
L22
    getstatic hg c:[I
    iload 4
    aload 2
    ldc -407474373 (java.lang.Integer)
    invokevirtual dh q:(I)I
    iastore
    iinc 4 1
    goto L21
L23
    iload 10
    iload 5
    if_icmpge L24
    iload 1
    ldc 1580525879 (java.lang.Integer)
    if_icmpeq L25
    new java/lang/IllegalStateException
    dup
    invokespecial java/lang/IllegalStateException <init>:()V
    athrow
L4
    iload 4
    getstatic by e:I
    ldc 434443889 (java.lang.Integer)
    imul
    if_icmpge L11
    iload 1
    ldc 1580525879 (java.lang.Integer)
    if_icmpeq L26
    new java/lang/IllegalStateException
    dup
    invokespecial java/lang/IllegalStateException <init>:()V
    athrow
L15
    aload 2
    ldc 1493965014 (java.lang.Integer)
    invokevirtual dh q:(I)I
    ldc 1598928747 (java.lang.Integer)
    imul
    putstatic by l:I
    goto L27
L28
    iinc 4 1
    goto L29
L30
    iload 11
    iload 6
    if_icmpge L31
    iload 1
    ldc 1580525879 (java.lang.Integer)
    if_icmpeq L32
    new java/lang/IllegalStateException
    dup
    invokespecial java/lang/IllegalStateException <init>:()V
    athrow
L33
    getstatic by w:[I
    iload 4
    aload 2
    ldc -1158367268 (java.lang.Integer)
    invokevirtual dh q:(I)I
    iastore
    iinc 4 1
    goto L12
L34
    iconst_0
    istore 4
L35
    iload 4
    getstatic by e:I
    ldc 434443889 (java.lang.Integer)
    imul
    if_icmpge L36
    iload 1
    ldc 1580525879 (java.lang.Integer)
    if_icmpeq L37
    new java/lang/IllegalStateException
    dup
    invokespecial java/lang/IllegalStateException <init>:()V
    athrow
L37
    getstatic by i:[I
    iload 4
    aload 2
    ldc 852902487 (java.lang.Integer)
    invokevirtual dh q:(I)I
    iastore
    iinc 4 1
    goto L35
L36
    aload 2
    aload 0
    arraylength
    bipush 7
    isub
    getstatic by e:I
    ldc -819416184 (java.lang.Integer)
    imul
    isub
    iconst_3
    iload 3
    iconst_1
    isub
    imul
    isub
    ldc 1782921573 (java.lang.Integer)
    imul
    putfield dh a:I
L38
    iload 3
    newarray 10
    putstatic cq r:[I
    goto L39
L27
    aload 2
    ldc 2065857570 (java.lang.Integer)
    invokevirtual dh z:(I)I
    sipush 255
    iand
    iconst_1
    iadd
    istore 3
    goto L20
L29
    iload 4
    iload 3
    if_icmpge L40
    iload 1
    ldc 1580525879 (java.lang.Integer)
    if_icmpeq L41
    new java/lang/IllegalStateException
    dup
    invokespecial java/lang/IllegalStateException <init>:()V
    athrow
L42
    iconst_0
    istore 4
    goto L43
L44
    iconst_0
    getstatic cq r:[I
    iload 4
    iaload
    if_icmpne L28
    iload 1
    ldc 1580525879 (java.lang.Integer)
    if_icmpeq L45
    return
L45
    getstatic cq r:[I
    iload 4
    iconst_1
    iastore
    goto L28
L39
    iconst_1
    istore 4
    goto L29
L40
    aload 2
    iconst_0
    putfield dh a:I
    goto L42
L10
    ldc 434443889 (java.lang.Integer)
    getstatic by e:I
    imul
    anewarray [B
    putstatic ar f:[[B
    goto L13
L46
    getstatic by w:[I
    iload 4
    iaload
    istore 5
    goto L16
L47
    iload 9
    iconst_1
    if_icmpne L24
    iload 1
    ldc 1580525879 (java.lang.Integer)
    if_icmpeq L48
    return
L49
    goto L24
L17
    iload 6
    iload 5
    imul
    istore 7
    goto L50
L51
    iinc 11 1
    goto L30
L52
    getstatic ar f:[[B
    iload 4
    aload 8
    aastore
L53
    aload 2
    ldc 1128434968 (java.lang.Integer)
    invokevirtual dh z:(I)I
    istore 9
L54
    iload 9
    ifne L47
    iload 1
    ldc 1580525879 (java.lang.Integer)
    if_icmpeq L55
    new java/lang/IllegalStateException
    dup
    invokespecial java/lang/IllegalStateException <init>:()V
    athrow
L55
    iconst_0
    istore 10
L19
    iload 10
    iload 7
    if_icmpge L49
    iload 1
    ldc 1580525879 (java.lang.Integer)
    if_icmpeq L18
    new java/lang/IllegalStateException
    dup
    invokespecial java/lang/IllegalStateException <init>:()V
    athrow
L43
    iload 4
    ldc 434443889 (java.lang.Integer)
    getstatic by e:I
    imul
    if_icmpge L56
    iload 1
    ldc 1580525879 (java.lang.Integer)
    if_icmpeq L46
    return
L2
    aload 2
    ldc 1782921573 (java.lang.Integer)
    aload 0
    arraylength
    iconst_2
    isub
    imul
    putfield dh a:I
    goto L5
L12
    iload 4
    getstatic by e:I
    ldc 434443889 (java.lang.Integer)
    imul
    if_icmpge L34
    goto L33
L41
    getstatic cq r:[I
    iload 4
    aload 2
    ldc -1964682484 (java.lang.Integer)
    invokevirtual dh b:(I)I
    iastore
    goto L44
L26
    getstatic eb u:[I
    iload 4
    aload 2
    ldc -1771186905 (java.lang.Integer)
    invokevirtual dh q:(I)I
    iastore
    iinc 4 1
    goto L4
L25
    iconst_0
    istore 11
    goto L30
L50
    iload 7
    newarray 8
    astore 8
    goto L52
L32
    aload 8
    iload 10
    iload 5
    iload 11
    imul
    iadd
    aload 2
    bipush 66
    invokevirtual dh y:(B)B
    bastore
    goto L51
L48
    iconst_0
    istore 10
    goto L23
L31
    iinc 10 1
    goto L23
L24
    iinc 4 1
    goto L43
L56
    return
L57
    new java/lang/StringBuilder
    dup
    invokespecial java/lang/StringBuilder <init>:()V
    ldc "g.s(" (java.lang.String)
    invokevirtual java/lang/StringBuilder append:(Ljava/lang/String;)Ljava/lang/StringBuilder;
    ldc 41 (java.lang.Integer)
    invokevirtual java/lang/StringBuilder append:(C)Ljava/lang/StringBuilder;
    invokevirtual java/lang/StringBuilder toString:()Ljava/lang/String;
    invokestatic k a:(Ljava/lang/Throwable;Ljava/lang/String;)Lee;
    athrow
