h bz (IIIII)VL1
    iload 0
    iload 1
    ldc 455014601 (java.lang.Integer)
    invokestatic ed l:(III)Lfb;
    astore 5
    goto L2
L3
    aload 6
    aload 5
    putfield e l:Lfb;
    goto L4
L5
    aload 5
    getfield fb ct:[Ljava/lang/Object;
    ifnull L6
    iload 4
    ldc -1976433391 (java.lang.Integer)
    if_icmpgt L7
    return
L7
    new e
    dup
    invokespecial e <init>:()V
    astore 6
    goto L3
L8
    ldc -1464344827 (java.lang.Integer)
    iload 2
    imul
    putstatic da jj:I
    goto L9
L4
    aload 6
    aload 5
    getfield fb ct:[Ljava/lang/Object;
    putfield e e:[Ljava/lang/Object;
L10
    aload 6
    ldc -2119225707 (java.lang.Integer)
    invokestatic k e:(Le;I)V
    goto L6
L11
    iconst_1
    putstatic client is:Z
    goto L12
L13
    iload 1
    ldc 2120542787 (java.lang.Integer)
    imul
    putstatic client ja:I
    goto L8
L12
    ldc -1410757337 (java.lang.Integer)
    iload 0
    imul
    putstatic f jg:I
    goto L13
L2
    aload 5
    ifnull L6
    iload 4
    ldc -1976433391 (java.lang.Integer)
    if_icmpgt L5
    new java/lang/IllegalStateException
    dup
    invokespecial java/lang/IllegalStateException <init>:()V
    athrow
L14
    return
L9
    aload 5
    ldc -1023277750 (java.lang.Integer)
    invokestatic dh cr:(Lfb;I)V
    goto L14
L6
    iload 3
    ldc -1285544701 (java.lang.Integer)
    imul
    putstatic client jw:I
    goto L11
L15
    new java/lang/StringBuilder
    dup
    invokespecial java/lang/StringBuilder <init>:()V
    ldc "h.bz(" (java.lang.String)
    invokevirtual java/lang/StringBuilder append:(Ljava/lang/String;)Ljava/lang/StringBuilder;
    ldc 41 (java.lang.Integer)
    invokevirtual java/lang/StringBuilder append:(C)Ljava/lang/StringBuilder;
    invokevirtual java/lang/StringBuilder toString:()Ljava/lang/String;
    invokestatic k a:(Ljava/lang/Throwable;Ljava/lang/String;)Lee;
    athrow
