hk l (IIIIZB)VL1
    sipush 256
    istore 7
    goto L2
L3
    iload 9
    aload 0
    getfield hk ao:I
    ldc 2033114921 (java.lang.Integer)
    imul
    if_icmpge L4
    iload 6
    iconst_1
    if_icmplt L5
    new java/lang/IllegalStateException
    dup
    invokespecial java/lang/IllegalStateException <init>:()V
    athrow
L6
    iload 7
    ldc 131072 (java.lang.Integer)
    iadd
    istore 7
    goto L7
L8
    iload 9
    iflt L4
    iload 6
    iconst_1
    if_icmplt L3
    new java/lang/IllegalStateException
    dup
    invokespecial java/lang/IllegalStateException <init>:()V
    athrow
L9
    iload 2
    aload 0
    getfield hk ax:I
    ldc -1615258397 (java.lang.Integer)
    imul
    isub
    istore 2
L10
    iload 1
    istore 8
L11
    iload 8
    iload 1
    iload 3
    iadd
    if_icmpge L12
    goto L13
L2
    iload 5
    ifeq L7
    goto L6
L14
    iload 8
    aload 0
    getfield hk ap:I
    ldc -2109306413 (java.lang.Integer)
    imul
    if_icmpge L15
    iload 6
    iconst_1
    if_icmplt L16
    new java/lang/IllegalStateException
    dup
    invokespecial java/lang/IllegalStateException <init>:()V
    athrow
L16
    iload 2
    istore 9
L17
    iload 9
    iload 2
    iload 4
    iadd
    if_icmpge L15
    iload 6
    iconst_1
    if_icmplt L8
    new java/lang/IllegalStateException
    dup
    invokespecial java/lang/IllegalStateException <init>:()V
    athrow
L15
    iinc 8 1
    goto L11
L7
    iload 1
    ldc -762260917 (java.lang.Integer)
    aload 0
    getfield hk k:I
    imul
    isub
    istore 1
    goto L9
L5
    aload 0
    iload 8
    iload 9
    iload 7
    ldc 2138150898 (java.lang.Integer)
    invokevirtual hk w:(IIII)V
L4
    iinc 9 1
    goto L17
L13
    iload 8
    iflt L15
    iload 6
    iconst_1
    if_icmplt L14
    new java/lang/IllegalStateException
    dup
    invokespecial java/lang/IllegalStateException <init>:()V
    athrow
L12
    return
L18
    new java/lang/StringBuilder
    dup
    invokespecial java/lang/StringBuilder <init>:()V
    ldc "hk.l(" (java.lang.String)
    invokevirtual java/lang/StringBuilder append:(Ljava/lang/String;)Ljava/lang/StringBuilder;
    ldc 41 (java.lang.Integer)
    invokevirtual java/lang/StringBuilder append:(C)Ljava/lang/StringBuilder;
    invokevirtual java/lang/StringBuilder toString:()Ljava/lang/String;
    invokestatic k a:(Ljava/lang/Throwable;Ljava/lang/String;)Lee;
    athrow
