i u (Lhh;Lhh;Lhh;I)VL1
    getstatic ai ad:Z
    ifeq L2
L3
    getstatic fg az:[Lbh;
    ifnonnull L4
    iload 3
    ldc 1296574530 (java.lang.Integer)
    if_icmpne L5
    new java/lang/IllegalStateException
    dup
    invokespecial java/lang/IllegalStateException <init>:()V
    athrow
L5
    getstatic t be:Lfo;
    ldc "sl_back" (java.lang.String)
    ldc "" (java.lang.String)
    ldc 1004155434 (java.lang.Integer)
    invokestatic bm i:(Lfv;Ljava/lang/String;Ljava/lang/String;I)[Lbh;
    putstatic fg az:[Lbh;
L4
    getstatic ax af:[Lbs;
    ifnonnull L6
    iload 3
    ldc 1296574530 (java.lang.Integer)
    if_icmpne L7
    new java/lang/IllegalStateException
    dup
    invokespecial java/lang/IllegalStateException <init>:()V
    athrow
L7
    getstatic t be:Lfo;
    ldc "sl_flags" (java.lang.String)
    ldc "" (java.lang.String)
    bipush -11
    invokestatic j u:(Lfv;Ljava/lang/String;Ljava/lang/String;B)[Lbs;
    putstatic ax af:[Lbs;
L6
    getstatic av as:[Lbs;
    ifnonnull L8
    iload 3
    ldc 1296574530 (java.lang.Integer)
    if_icmpne L9
    new java/lang/IllegalStateException
    dup
    invokespecial java/lang/IllegalStateException <init>:()V
    athrow
L9
    getstatic t be:Lfo;
    ldc "sl_arrows" (java.lang.String)
    ldc "" (java.lang.String)
    bipush -97
    invokestatic j u:(Lfv;Ljava/lang/String;Ljava/lang/String;B)[Lbs;
    putstatic av as:[Lbs;
L8
    aconst_null
    getstatic ai aa:[Lbs;
    if_acmpne L10
    iload 3
    ldc 1296574530 (java.lang.Integer)
    if_icmpne L11
    return
L11
    getstatic t be:Lfo;
    ldc "sl_stars" (java.lang.String)
    ldc "" (java.lang.String)
    bipush 26
    invokestatic j u:(Lfv;Ljava/lang/String;Ljava/lang/String;B)[Lbs;
    putstatic ai aa:[Lbs;
L10
    iconst_0
    bipush 23
    sipush 765
    sipush 480
    iconst_0
    invokestatic bt cs:(IIIII)V
L12
    iconst_0
    iconst_0
    bipush 125
    bipush 23
    ldc 12425273 (java.lang.Integer)
    ldc 9135624 (java.lang.Integer)
    invokestatic bt cz:(IIIIII)V
L13
    bipush 125
    iconst_0
    sipush 640
    bipush 23
    ldc 5197647 (java.lang.Integer)
    ldc 2697513 (java.lang.Integer)
    invokestatic bt cz:(IIIIII)V
L14
    aload 0
    getstatic et jf:Ljava/lang/String;
    bipush 62
    bipush 15
    iconst_0
    iconst_m1
    invokevirtual hh o:(Ljava/lang/String;IIII)V
L15
    aconst_null
    getstatic ai aa:[Lbs;
    if_acmpeq L16
L17
    getstatic ai aa:[Lbs;
    iconst_1
    aaload
    sipush 140
    iconst_1
    invokevirtual bs l:(II)V
L18
    aload 1
    getstatic et jk:Ljava/lang/String;
    sipush 152
    bipush 10
    ldc 16777215 (java.lang.Integer)
    iconst_m1
    invokevirtual hh f:(Ljava/lang/String;IIII)V
L19
    getstatic ai aa:[Lbs;
    iconst_0
    aaload
    sipush 140
    bipush 12
    invokevirtual bs l:(II)V
L20
    aload 1
    getstatic et jn:Ljava/lang/String;
    sipush 152
    bipush 21
    ldc 16777215 (java.lang.Integer)
    iconst_m1
    invokevirtual hh f:(Ljava/lang/String;IIII)V
L16
    aconst_null
    getstatic av as:[Lbs;
    if_acmpeq L21
L22
    sipush 280
    istore 4
L23
    iconst_0
    getstatic ai bc:[I
    iconst_0
    iaload
    if_icmpne L24
    iload 3
    ldc 1296574530 (java.lang.Integer)
    if_icmpne L25
    new java/lang/IllegalStateException
    dup
    invokespecial java/lang/IllegalStateException <init>:()V
    athrow
L25
    getstatic ai br:[I
    iconst_0
    iaload
    ifne L24
    iload 3
    ldc 1296574530 (java.lang.Integer)
    if_icmpne L26
    return
L26
    getstatic av as:[Lbs;
    iconst_2
    aaload
    iload 4
    iconst_4
    invokevirtual bs l:(II)V
    goto L27
L24
    getstatic av as:[Lbs;
    iconst_0
    aaload
    iload 4
    iconst_4
    invokevirtual bs l:(II)V
L27
    getstatic ai bc:[I
    iconst_0
    iaload
    ifne L28
    iload 3
    ldc 1296574530 (java.lang.Integer)
    if_icmpne L29
    return
L29
    iconst_1
    getstatic ai br:[I
    iconst_0
    iaload
    if_icmpne L28
    iload 3
    ldc 1296574530 (java.lang.Integer)
    if_icmpne L30
    new java/lang/IllegalStateException
    dup
    invokespecial java/lang/IllegalStateException <init>:()V
    athrow
L30
    getstatic av as:[Lbs;
    iconst_3
    aaload
    iload 4
    bipush 15
    iadd
    iconst_4
    invokevirtual bs l:(II)V
    goto L31
L28
    getstatic av as:[Lbs;
    iconst_1
    aaload
    iload 4
    bipush 15
    iadd
    iconst_4
    invokevirtual bs l:(II)V
L31
    aload 0
    getstatic et jv:Ljava/lang/String;
    iload 4
    bipush 32
    iadd
    bipush 17
    ldc 16777215 (java.lang.Integer)
    iconst_m1
    invokevirtual hh f:(Ljava/lang/String;IIII)V
L32
    sipush 390
    istore 5
L33
    getstatic ai bc:[I
    iconst_0
    iaload
    iconst_1
    if_icmpne L34
    getstatic ai br:[I
    iconst_0
    iaload
    ifne L34
    getstatic av as:[Lbs;
    iconst_2
    aaload
    iload 5
    iconst_4
    invokevirtual bs l:(II)V
    goto L35
L34
    getstatic av as:[Lbs;
    iconst_0
    aaload
    iload 5
    iconst_4
    invokevirtual bs l:(II)V
L35
    iconst_1
    getstatic ai bc:[I
    iconst_0
    iaload
    if_icmpne L36
    iconst_1
    getstatic ai br:[I
    iconst_0
    iaload
    if_icmpne L36
    getstatic av as:[Lbs;
    iconst_3
    aaload
    bipush 15
    iload 5
    iadd
    iconst_4
    invokevirtual bs l:(II)V
    goto L37
L36
    getstatic av as:[Lbs;
    iconst_1
    aaload
    bipush 15
    iload 5
    iadd
    iconst_4
    invokevirtual bs l:(II)V
L37
    aload 0
    getstatic et jt:Ljava/lang/String;
    bipush 32
    iload 5
    iadd
    bipush 17
    ldc 16777215 (java.lang.Integer)
    iconst_m1
    invokevirtual hh f:(Ljava/lang/String;IIII)V
L38
    sipush 500
    istore 6
L39
    getstatic ai bc:[I
    iconst_0
    iaload
    iconst_2
    if_icmpne L40
    iload 3
    ldc 1296574530 (java.lang.Integer)
    if_icmpne L41
    return
L41
    getstatic ai br:[I
    iconst_0
    iaload
    ifne L40
    iload 3
    ldc 1296574530 (java.lang.Integer)
    if_icmpne L42
    new java/lang/IllegalStateException
    dup
    invokespecial java/lang/IllegalStateException <init>:()V
    athrow
L42
    getstatic av as:[Lbs;
    iconst_2
    aaload
    iload 6
    iconst_4
    invokevirtual bs l:(II)V
    goto L43
L40
    getstatic av as:[Lbs;
    iconst_0
    aaload
    iload 6
    iconst_4
    invokevirtual bs l:(II)V
L43
    iconst_2
    getstatic ai bc:[I
    iconst_0
    iaload
    if_icmpne L44
    iconst_1
    getstatic ai br:[I
    iconst_0
    iaload
    if_icmpne L44
    iload 3
    ldc 1296574530 (java.lang.Integer)
    if_icmpne L45
    new java/lang/IllegalStateException
    dup
    invokespecial java/lang/IllegalStateException <init>:()V
    athrow
L45
    getstatic av as:[Lbs;
    iconst_3
    aaload
    bipush 15
    iload 6
    iadd
    iconst_4
    invokevirtual bs l:(II)V
    goto L46
L44
    getstatic av as:[Lbs;
    iconst_1
    aaload
    bipush 15
    iload 6
    iadd
    iconst_4
    invokevirtual bs l:(II)V
L46
    aload 0
    getstatic et jd:Ljava/lang/String;
    iload 6
    bipush 32
    iadd
    bipush 17
    ldc 16777215 (java.lang.Integer)
    iconst_m1
    invokevirtual hh f:(Ljava/lang/String;IIII)V
L47
    sipush 610
    istore 7
L48
    iconst_3
    getstatic ai bc:[I
    iconst_0
    iaload
    if_icmpne L49
    iload 3
    ldc 1296574530 (java.lang.Integer)
    if_icmpne L50
    new java/lang/IllegalStateException
    dup
    invokespecial java/lang/IllegalStateException <init>:()V
    athrow
L50
    getstatic ai br:[I
    iconst_0
    iaload
    ifne L49
    getstatic av as:[Lbs;
    iconst_2
    aaload
    iload 7
    iconst_4
    invokevirtual bs l:(II)V
    goto L51
L49
    getstatic av as:[Lbs;
    iconst_0
    aaload
    iload 7
    iconst_4
    invokevirtual bs l:(II)V
L51
    iconst_3
    getstatic ai bc:[I
    iconst_0
    iaload
    if_icmpne L52
    iload 3
    ldc 1296574530 (java.lang.Integer)
    if_icmpne L53
    return
L53
    iconst_1
    getstatic ai br:[I
    iconst_0
    iaload
    if_icmpne L52
    iload 3
    ldc 1296574530 (java.lang.Integer)
    if_icmpne L54
    new java/lang/IllegalStateException
    dup
    invokespecial java/lang/IllegalStateException <init>:()V
    athrow
L54
    getstatic av as:[Lbs;
    iconst_3
    aaload
    iload 7
    bipush 15
    iadd
    iconst_4
    invokevirtual bs l:(II)V
    goto L55
L52
    getstatic av as:[Lbs;
    iconst_1
    aaload
    bipush 15
    iload 7
    iadd
    iconst_4
    invokevirtual bs l:(II)V
L55
    aload 0
    getstatic et jz:Ljava/lang/String;
    iload 7
    bipush 32
    iadd
    bipush 17
    ldc 16777215 (java.lang.Integer)
    iconst_m1
    invokevirtual hh f:(Ljava/lang/String;IIII)V
L21
    sipush 708
    iconst_4
    bipush 50
    bipush 16
    iconst_0
    invokestatic bt cs:(IIIII)V
L56
    aload 1
    getstatic et ic:Ljava/lang/String;
    sipush 733
    bipush 16
    ldc 16777215 (java.lang.Integer)
    iconst_m1
    invokevirtual hh o:(Ljava/lang/String;IIII)V
L57
    ldc 1331496373 (java.lang.Integer)
    putstatic ai bu:I
L58
    getstatic fg az:[Lbh;
    ifnull L59
    iload 3
    ldc 1296574530 (java.lang.Integer)
    if_icmpne L60
    new java/lang/IllegalStateException
    dup
    invokespecial java/lang/IllegalStateException <init>:()V
    athrow
L60
    bipush 88
    istore 4
L61
    bipush 19
    istore 5
L62
    sipush 765
    iconst_1
    iload 4
    iadd
    idiv
    istore 6
L63
    sipush 480
    iload 5
    iconst_1
    iadd
    idiv
    istore 7
L64
    iload 7
    istore 8
L65
    iload 6
    istore 9
L66
    iload 7
    iload 6
    iconst_1
    isub
    imul
    getstatic ai bk:I
    ldc 1361100369 (java.lang.Integer)
    imul
    if_icmplt L67
    iload 3
    ldc 1296574530 (java.lang.Integer)
    if_icmpne L68
    return
L68
    iinc 6 -1
L67
    iload 6
    iload 7
    iconst_1
    isub
    imul
    ldc 1361100369 (java.lang.Integer)
    getstatic ai bk:I
    imul
    if_icmplt L69
    iinc 7 -1
L69
    iload 7
    iconst_1
    isub
    iload 6
    imul
    getstatic ai bk:I
    ldc 1361100369 (java.lang.Integer)
    imul
    if_icmplt L70
    iload 3
    ldc 1296574530 (java.lang.Integer)
    if_icmpne L71
    new java/lang/IllegalStateException
    dup
    invokespecial java/lang/IllegalStateException <init>:()V
    athrow
L71
    iinc 7 -1
L70
    iload 7
    iload 8
    if_icmpne L72
    iload 6
    iload 9
    if_icmpne L72
    iload 3
    ldc 1296574530 (java.lang.Integer)
    if_icmpne L73
    return
L73
    goto L74
L72
    goto L64
L74
    sipush 765
    iload 6
    iload 4
    imul
    isub
    iconst_1
    iload 6
    iadd
    idiv
    istore 8
L75
    iload 8
    iconst_5
    if_icmple L76
    iconst_5
    istore 8
L76
    sipush 480
    iload 7
    iload 5
    imul
    isub
    iload 7
    iconst_1
    iadd
    idiv
    istore 9
L77
    iload 9
    iconst_5
    if_icmple L78
    iconst_5
    istore 9
L78
    sipush 765
    iload 6
    iload 4
    imul
    isub
    iload 8
    iload 6
    iconst_1
    isub
    imul
    isub
    iconst_2
    idiv
    istore 10
L79
    sipush 480
    iload 7
    iload 5
    imul
    isub
    iload 7
    iconst_1
    isub
    iload 9
    imul
    isub
    iconst_2
    idiv
    istore 11
L80
    bipush 23
    iload 11
    iadd
    istore 12
L81
    iload 10
    istore 13
L82
    iconst_0
    istore 14
L83
    iconst_0
    istore 15
L84
    iconst_0
    istore 16
L85
    iload 16
    ldc 1361100369 (java.lang.Integer)
    getstatic ai bk:I
    imul
    if_icmpge L86
L87
    getstatic b bm:[Lv;
    iload 16
    aaload
    astore 17
L88
    iconst_1
    istore 18
L89
    ldc 729509107 (java.lang.Integer)
    aload 17
    getfield v l:I
    imul
    invokestatic java/lang/Integer toString:(I)Ljava/lang/String;
    astore 19
L90
    iconst_m1
    aload 17
    getfield v l:I
    ldc 729509107 (java.lang.Integer)
    imul
    if_icmpne L91
    iload 3
    ldc 1296574530 (java.lang.Integer)
    if_icmpne L92
    new java/lang/IllegalStateException
    dup
    invokespecial java/lang/IllegalStateException <init>:()V
    athrow
L92
    getstatic et ji:Ljava/lang/String;
    astore 19
L93
    iconst_0
    istore 18
    goto L94
L91
    ldc 729509107 (java.lang.Integer)
    aload 17
    getfield v l:I
    imul
    sipush 1980
    if_icmple L94
    iload 3
    ldc 1296574530 (java.lang.Integer)
    if_icmpne L95
    new java/lang/IllegalStateException
    dup
    invokespecial java/lang/IllegalStateException <init>:()V
    athrow
L95
    getstatic et je:Ljava/lang/String;
    astore 19
L96
    iconst_0
    istore 18
L94
    aload 17
    ldc 276695614 (java.lang.Integer)
    invokevirtual v a:(I)Z
    ifeq L97
L98
    aload 17
    ldc 2027762506 (java.lang.Integer)
    invokevirtual v e:(I)Z
    ifeq L99
    iconst_3
    istore 20
    goto L100
L99
    iconst_2
    istore 20
    goto L100
L97
    aload 17
    ldc 1765297897 (java.lang.Integer)
    invokevirtual v e:(I)Z
    ifeq L101
    iload 3
    ldc 1296574530 (java.lang.Integer)
    if_icmpne L102
    new java/lang/IllegalStateException
    dup
    invokespecial java/lang/IllegalStateException <init>:()V
    athrow
L102
    iconst_1
    istore 20
    goto L100
L101
    iconst_0
    istore 20
L100
    getstatic ep i:I
    ldc -1976433391 (java.lang.Integer)
    imul
    iload 13
    if_icmplt L103
    iload 3
    ldc 1296574530 (java.lang.Integer)
    if_icmpne L104
    new java/lang/IllegalStateException
    dup
    invokespecial java/lang/IllegalStateException <init>:()V
    athrow
L104
    ldc -1616406211 (java.lang.Integer)
    getstatic ep r:I
    imul
    iload 12
    if_icmplt L103
    getstatic ep i:I
    ldc -1976433391 (java.lang.Integer)
    imul
    iload 4
    iload 13
    iadd
    if_icmpge L103
    iload 3
    ldc 1296574530 (java.lang.Integer)
    if_icmpne L105
    new java/lang/IllegalStateException
    dup
    invokespecial java/lang/IllegalStateException <init>:()V
    athrow
L105
    ldc -1616406211 (java.lang.Integer)
    getstatic ep r:I
    imul
    iload 12
    iload 5
    iadd
    if_icmpge L103
    iload 3
    ldc 1296574530 (java.lang.Integer)
    if_icmpne L106
    return
L106
    iload 18
    ifeq L103
    iload 3
    ldc 1296574530 (java.lang.Integer)
    if_icmpne L107
    return
L107
    ldc -1331496373 (java.lang.Integer)
    iload 16
    imul
    putstatic ai bu:I
L108
    getstatic fg az:[Lbh;
    iload 20
    aaload
    iload 13
    iload 12
    sipush 128
    ldc 16777215 (java.lang.Integer)
    invokevirtual bh t:(IIII)V
L109
    iconst_1
    istore 15
    goto L110
L103
    getstatic fg az:[Lbh;
    iload 20
    aaload
    iload 13
    iload 12
    invokevirtual bh g:(II)V
L110
    getstatic ax af:[Lbs;
    ifnull L111
    getstatic ax af:[Lbs;
    aload 17
    ldc 1672674814 (java.lang.Integer)
    invokevirtual v e:(I)Z
    ifeq L112
    bipush 8
    goto L113
L112
    iconst_0
L113
    aload 17
    getfield v w:I
    ldc -1762790165 (java.lang.Integer)
    imul
    iadd
    aaload
    iload 13
    bipush 29
    iadd
    iload 12
    invokevirtual bs l:(II)V
L111
    aload 0
    ldc 1985134815 (java.lang.Integer)
    aload 17
    getfield v e:I
    imul
    invokestatic java/lang/Integer toString:(I)Ljava/lang/String;
    iload 13
    bipush 15
    iadd
    iload 5
    iconst_2
    idiv
    iload 12
    iadd
    iconst_5
    iadd
    iconst_0
    iconst_m1
    invokevirtual hh o:(Ljava/lang/String;IIII)V
L114
    aload 1
    aload 19
    bipush 60
    iload 13
    iadd
    iload 12
    iload 5
    iconst_2
    idiv
    iadd
    iconst_5
    iadd
    ldc 268435455 (java.lang.Integer)
    iconst_m1
    invokevirtual hh o:(Ljava/lang/String;IIII)V
L115
    iload 12
    iload 9
    iload 5
    iadd
    iadd
    istore 12
L116
    iinc 14 1
    iload 14
    iload 7
    if_icmplt L117
    iload 3
    ldc 1296574530 (java.lang.Integer)
    if_icmpne L118
    new java/lang/IllegalStateException
    dup
    invokespecial java/lang/IllegalStateException <init>:()V
    athrow
L118
    iload 11
    bipush 23
    iadd
    istore 12
L119
    iload 13
    iload 8
    iload 4
    iadd
    iadd
    istore 13
L120
    iconst_0
    istore 14
L117
    iinc 16 1
    goto L85
L86
    iload 15
    ifeq L59
    iload 3
    ldc 1296574530 (java.lang.Integer)
    if_icmpne L121
    new java/lang/IllegalStateException
    dup
    invokespecial java/lang/IllegalStateException <init>:()V
    athrow
L121
    aload 1
    getstatic b bm:[Lv;
    ldc 1135247203 (java.lang.Integer)
    getstatic ai bu:I
    imul
    aaload
    getfield v u:Ljava/lang/String;
    invokevirtual hh c:(Ljava/lang/String;)I
    bipush 6
    iadd
    istore 16
L122
    bipush 8
    aload 1
    getfield hh i:I
    iadd
    istore 17
L123
    ldc -1976433391 (java.lang.Integer)
    getstatic ep i:I
    imul
    iload 16
    iconst_2
    idiv
    isub
    getstatic ep r:I
    ldc -1616406211 (java.lang.Integer)
    imul
    bipush 20
    iadd
    iconst_5
    iadd
    iload 16
    iload 17
    ldc 16777120 (java.lang.Integer)
    invokestatic bt cs:(IIIII)V
L124
    getstatic ep i:I
    ldc -1976433391 (java.lang.Integer)
    imul
    iload 16
    iconst_2
    idiv
    isub
    bipush 20
    getstatic ep r:I
    ldc -1616406211 (java.lang.Integer)
    imul
    iadd
    iconst_5
    iadd
    iload 16
    iload 17
    iconst_0
    invokestatic bt ca:(IIIII)V
L125
    aload 1
    getstatic b bm:[Lv;
    getstatic ai bu:I
    ldc 1135247203 (java.lang.Integer)
    imul
    aaload
    getfield v u:Ljava/lang/String;
    ldc -1976433391 (java.lang.Integer)
    getstatic ep i:I
    imul
    getstatic ep r:I
    ldc -1616406211 (java.lang.Integer)
    imul
    bipush 20
    iadd
    iconst_5
    iadd
    aload 1
    getfield hh i:I
    iadd
    iconst_4
    iadd
    iconst_0
    iconst_m1
    invokevirtual hh o:(Ljava/lang/String;IIII)V
L59
    getstatic eb pd:Ljava/awt/Canvas;
    invokevirtual java/awt/Canvas getGraphics:()Ljava/awt/Graphics;
    astore 4
L126
    getstatic v py:Lbz;
    aload 4
    iconst_0
    iconst_0
    bipush -66
    invokevirtual bz a:(Ljava/awt/Graphics;IIB)V
L127
    goto L128
L129
    astore 4
L130
    getstatic eb pd:Ljava/awt/Canvas;
    invokevirtual java/awt/Canvas repaint:()V
L128
    return
L2
    ldc 1532705327 (java.lang.Integer)
    getstatic client q:I
    imul
    ifeq L131
    iload 3
    ldc 1296574530 (java.lang.Integer)
    if_icmpne L132
    new java/lang/IllegalStateException
    dup
    invokespecial java/lang/IllegalStateException <init>:()V
    athrow
L132
    ldc 1532705327 (java.lang.Integer)
    getstatic client q:I
    imul
    iconst_5
    if_icmpne L133
    iload 3
    ldc 1296574530 (java.lang.Integer)
    if_icmpne L131
    new java/lang/IllegalStateException
    dup
    invokespecial java/lang/IllegalStateException <init>:()V
    athrow
L131
    bipush 20
    istore 4
L134
    aload 0
    getstatic et hf:Ljava/lang/String;
    sipush 382
    sipush 245
    iload 4
    isub
    ldc 16777215 (java.lang.Integer)
    iconst_m1
    invokevirtual hh o:(Ljava/lang/String;IIII)V
L135
    sipush 253
    iload 4
    isub
    istore 5
L136
    sipush 230
    iload 5
    sipush 304
    bipush 34
    ldc 9179409 (java.lang.Integer)
    invokestatic bt ca:(IIIII)V
L137
    sipush 231
    iload 5
    iconst_1
    iadd
    sipush 302
    bipush 32
    iconst_0
    invokestatic bt ca:(IIIII)V
L138
    sipush 232
    iconst_2
    iload 5
    iadd
    getstatic ai aw:I
    ldc 1615652001 (java.lang.Integer)
    imul
    bipush 30
    ldc 9179409 (java.lang.Integer)
    invokestatic bt cs:(IIIII)V
L139
    getstatic ai aw:I
    ldc 1615652001 (java.lang.Integer)
    imul
    sipush 232
    iadd
    iload 5
    iconst_2
    iadd
    sipush 300
    ldc 1615652001 (java.lang.Integer)
    getstatic ai aw:I
    imul
    isub
    bipush 30
    iconst_0
    invokestatic bt cs:(IIIII)V
L140
    aload 0
    getstatic ai am:Ljava/lang/String;
    sipush 382
    sipush 276
    iload 4
    isub
    ldc 16777215 (java.lang.Integer)
    iconst_m1
    invokevirtual hh o:(Ljava/lang/String;IIII)V
L133
    getstatic client q:I
    ldc 1532705327 (java.lang.Integer)
    imul
    bipush 20
    if_icmpne L141
    iload 3
    ldc 1296574530 (java.lang.Integer)
    if_icmpne L142
    new java/lang/IllegalStateException
    dup
    invokespecial java/lang/IllegalStateException <init>:()V
    athrow
L142
    getstatic ai a:Lbs;
    sipush 382
    getstatic ai a:Lbs;
    getfield bs l:I
    iconst_2
    idiv
    isub
    sipush 271
    getstatic ai a:Lbs;
    getfield bs c:I
    iconst_2
    idiv
    isub
    invokevirtual bs l:(II)V
L143
    sipush 211
    istore 4
L144
    aload 0
    getstatic ai ae:Ljava/lang/String;
    sipush 382
    iload 4
    ldc 16776960 (java.lang.Integer)
    iconst_0
    invokevirtual hh o:(Ljava/lang/String;IIII)V
L145
    iinc 4 15
L146
    aload 0
    getstatic ai ab:Ljava/lang/String;
    sipush 382
    iload 4
    ldc 16776960 (java.lang.Integer)
    iconst_0
    invokevirtual hh o:(Ljava/lang/String;IIII)V
L147
    iinc 4 15
L148
    aload 0
    getstatic ai av:Ljava/lang/String;
    sipush 382
    iload 4
    ldc 16776960 (java.lang.Integer)
    iconst_0
    invokevirtual hh o:(Ljava/lang/String;IIII)V
L149
    iinc 4 15
L150
    iinc 4 10
L151
    getstatic ai au:I
    ldc -47454393 (java.lang.Integer)
    imul
    iconst_4
    if_icmpeq L141
    iload 3
    ldc 1296574530 (java.lang.Integer)
    if_icmpne L152
    new java/lang/IllegalStateException
    dup
    invokespecial java/lang/IllegalStateException <init>:()V
    athrow
L152
    aload 0
    getstatic et hs:Ljava/lang/String;
    sipush 272
    iload 4
    ldc 16777215 (java.lang.Integer)
    iconst_0
    invokevirtual hh f:(Ljava/lang/String;IIII)V
L153
    sipush 200
    istore 5
L154
    getstatic ai ay:Ljava/lang/String;
    astore 6
L155
    aload 0
    aload 6
    invokevirtual hh c:(Ljava/lang/String;)I
    iload 5
    if_icmple L156
    iload 3
    ldc 1296574530 (java.lang.Integer)
    if_icmpne L157
    new java/lang/IllegalStateException
    dup
    invokespecial java/lang/IllegalStateException <init>:()V
    athrow
L157
    aload 6
    iconst_0
    aload 6
    invokevirtual java/lang/String length:()I
    iconst_1
    isub
    invokevirtual java/lang/String substring:(II)Ljava/lang/String;
    astore 6
    goto L155
L156
    aload 0
    aload 6
    invokestatic ha r:(Ljava/lang/String;)Ljava/lang/String;
    sipush 312
    iload 4
    ldc 16777215 (java.lang.Integer)
    iconst_0
    invokevirtual hh f:(Ljava/lang/String;IIII)V
L158
    iinc 4 15
L159
    aload 0
    astore 7
L160
    getstatic et hu:Ljava/lang/String;
    astore 8
L161
    getstatic ai ag:Ljava/lang/String;
    astore 10
L162
    aload 10
    invokeinterface java/lang/CharSequence length:()I
    istore 12
L163
    iload 12
    newarray 5
    astore 13
L164
    iconst_0
    istore 14
L165
    iload 14
    iload 12
    if_icmpge L166
    iload 3
    ldc 1296574530 (java.lang.Integer)
    if_icmpne L167
    new java/lang/IllegalStateException
    dup
    invokespecial java/lang/IllegalStateException <init>:()V
    athrow
L167
    aload 13
    iload 14
    bipush 42
    castore
    iinc 14 1
    goto L165
L166
    new java/lang/String
    dup
    aload 13
    invokespecial java/lang/String <init>:([C)V
    astore 11
L168
    aload 11
    astore 9
L169
    aload 7
    new java/lang/StringBuilder
    dup
    invokespecial java/lang/StringBuilder <init>:()V
    aload 8
    invokevirtual java/lang/StringBuilder append:(Ljava/lang/String;)Ljava/lang/StringBuilder;
    aload 9
    invokevirtual java/lang/StringBuilder append:(Ljava/lang/String;)Ljava/lang/StringBuilder;
    invokevirtual java/lang/StringBuilder toString:()Ljava/lang/String;
    sipush 274
    iload 4
    ldc 16777215 (java.lang.Integer)
    iconst_0
    invokevirtual hh f:(Ljava/lang/String;IIII)V
L170
    iinc 4 15
L141
    bipush 10
    ldc 1532705327 (java.lang.Integer)
    getstatic client q:I
    imul
    if_icmpeq L171
    iload 3
    ldc 1296574530 (java.lang.Integer)
    if_icmpne L172
    new java/lang/IllegalStateException
    dup
    invokespecial java/lang/IllegalStateException <init>:()V
    athrow
L172
    bipush 11
    getstatic client q:I
    ldc 1532705327 (java.lang.Integer)
    imul
    if_icmpne L173
    iload 3
    ldc 1296574530 (java.lang.Integer)
    if_icmpne L171
    new java/lang/IllegalStateException
    dup
    invokespecial java/lang/IllegalStateException <init>:()V
    athrow
L171
    getstatic ai a:Lbs;
    sipush 202
    sipush 171
    invokevirtual bs l:(II)V
L174
    getstatic ai au:I
    ldc -47454393 (java.lang.Integer)
    imul
    ifne L175
    iload 3
    ldc 1296574530 (java.lang.Integer)
    if_icmpne L176
    new java/lang/IllegalStateException
    dup
    invokespecial java/lang/IllegalStateException <init>:()V
    athrow
L176
    sipush 251
    istore 4
L177
    aload 0
    getstatic et hp:Ljava/lang/String;
    sipush 382
    iload 4
    ldc 16776960 (java.lang.Integer)
    iconst_0
    invokevirtual hh o:(Ljava/lang/String;IIII)V
L178
    iinc 4 30
L179
    sipush 302
    istore 5
L180
    sipush 291
    istore 6
L181
    getstatic ai l:Lbs;
    iload 5
    bipush 73
    isub
    iload 6
    bipush 20
    isub
    invokevirtual bs l:(II)V
L182
    aload 0
    getstatic et ih:Ljava/lang/String;
    iload 5
    bipush 73
    isub
    iload 6
    bipush 20
    isub
    sipush 144
    bipush 40
    ldc 16777215 (java.lang.Integer)
    iconst_0
    iconst_1
    iconst_1
    iconst_0
    invokevirtual hh h:(Ljava/lang/String;IIIIIIIII)I
    pop
L183
    sipush 462
    istore 5
L184
    getstatic ai l:Lbs;
    iload 5
    bipush 73
    isub
    iload 6
    bipush 20
    isub
    invokevirtual bs l:(II)V
L185
    aload 0
    getstatic et it:Ljava/lang/String;
    iload 5
    bipush 73
    isub
    iload 6
    bipush 20
    isub
    sipush 144
    bipush 40
    ldc 16777215 (java.lang.Integer)
    iconst_0
    iconst_1
    iconst_1
    iconst_0
    invokevirtual hh h:(Ljava/lang/String;IIIIIIIII)I
    pop
L186
    goto L173
L175
    getstatic ai au:I
    ldc -47454393 (java.lang.Integer)
    imul
    iconst_1
    if_icmpne L187
    iload 3
    ldc 1296574530 (java.lang.Integer)
    if_icmpne L188
    return
L188
    aload 0
    getstatic et ht:Ljava/lang/String;
    sipush 382
    sipush 211
    ldc 16776960 (java.lang.Integer)
    iconst_0
    invokevirtual hh o:(Ljava/lang/String;IIII)V
L189
    sipush 236
    istore 4
L190
    aload 0
    getstatic ai ae:Ljava/lang/String;
    sipush 382
    iload 4
    ldc 16777215 (java.lang.Integer)
    iconst_0
    invokevirtual hh o:(Ljava/lang/String;IIII)V
L191
    iinc 4 15
L192
    aload 0
    getstatic ai ab:Ljava/lang/String;
    sipush 382
    iload 4
    ldc 16777215 (java.lang.Integer)
    iconst_0
    invokevirtual hh o:(Ljava/lang/String;IIII)V
L193
    iinc 4 15
L194
    aload 0
    getstatic ai av:Ljava/lang/String;
    sipush 382
    iload 4
    ldc 16777215 (java.lang.Integer)
    iconst_0
    invokevirtual hh o:(Ljava/lang/String;IIII)V
L195
    iinc 4 15
L196
    sipush 302
    istore 5
L197
    sipush 321
    istore 6
L198
    getstatic ai l:Lbs;
    iload 5
    bipush 73
    isub
    iload 6
    bipush 20
    isub
    invokevirtual bs l:(II)V
L199
    aload 0
    getstatic et i:Ljava/lang/String;
    iload 5
    iload 6
    iconst_5
    iadd
    ldc 16777215 (java.lang.Integer)
    iconst_0
    invokevirtual hh o:(Ljava/lang/String;IIII)V
L200
    sipush 462
    istore 5
L201
    getstatic ai l:Lbs;
    iload 5
    bipush 73
    isub
    iload 6
    bipush 20
    isub
    invokevirtual bs l:(II)V
L202
    aload 0
    getstatic et ic:Ljava/lang/String;
    iload 5
    iconst_5
    iload 6
    iadd
    ldc 16777215 (java.lang.Integer)
    iconst_0
    invokevirtual hh o:(Ljava/lang/String;IIII)V
L203
    goto L173
L187
    iconst_2
    ldc -47454393 (java.lang.Integer)
    getstatic ai au:I
    imul
    if_icmpne L204
    iload 3
    ldc 1296574530 (java.lang.Integer)
    if_icmpne L205
    new java/lang/IllegalStateException
    dup
    invokespecial java/lang/IllegalStateException <init>:()V
    athrow
L205
    sipush 211
    istore 4
L206
    aload 0
    getstatic ai ae:Ljava/lang/String;
    sipush 382
    iload 4
    ldc 16776960 (java.lang.Integer)
    iconst_0
    invokevirtual hh o:(Ljava/lang/String;IIII)V
L207
    iinc 4 15
L208
    aload 0
    getstatic ai ab:Ljava/lang/String;
    sipush 382
    iload 4
    ldc 16776960 (java.lang.Integer)
    iconst_0
    invokevirtual hh o:(Ljava/lang/String;IIII)V
L209
    iinc 4 15
L210
    aload 0
    getstatic ai av:Ljava/lang/String;
    sipush 382
    iload 4
    ldc 16776960 (java.lang.Integer)
    iconst_0
    invokevirtual hh o:(Ljava/lang/String;IIII)V
L211
    iinc 4 15
L212
    iinc 4 10
L213
    aload 0
    getstatic et hs:Ljava/lang/String;
    sipush 272
    iload 4
    ldc 16777215 (java.lang.Integer)
    iconst_0
    invokevirtual hh f:(Ljava/lang/String;IIII)V
L214
    sipush 200
    istore 5
L215
    getstatic ai ay:Ljava/lang/String;
    astore 6
L216
    aload 0
    aload 6
    invokevirtual hh c:(Ljava/lang/String;)I
    iload 5
    if_icmple L217
    iload 3
    ldc 1296574530 (java.lang.Integer)
    if_icmpne L218
    return
L218
    aload 6
    iconst_1
    invokevirtual java/lang/String substring:(I)Ljava/lang/String;
    astore 6
    goto L216
L217
    aload 0
    new java/lang/StringBuilder
    dup
    invokespecial java/lang/StringBuilder <init>:()V
    aload 6
    invokestatic ha r:(Ljava/lang/String;)Ljava/lang/String;
    invokevirtual java/lang/StringBuilder append:(Ljava/lang/String;)Ljava/lang/StringBuilder;
    iconst_0
    ldc 423886265 (java.lang.Integer)
    getstatic ai ak:I
    imul
    if_icmpne L219
    iload 3
    ldc 1296574530 (java.lang.Integer)
    if_icmpne L220
    new java/lang/IllegalStateException
    dup
    invokespecial java/lang/IllegalStateException <init>:()V
    athrow
L220
    iconst_1
    goto L221
L219
    iconst_0
L221
    getstatic client b:I
    ldc -117546507 (java.lang.Integer)
    imul
    bipush 40
    irem
    bipush 20
    if_icmpge L222
    iload 3
    ldc 1296574530 (java.lang.Integer)
    if_icmpne L223
    return
L223
    iconst_1
    goto L224
L222
    iconst_0
L224
    iand
    ifeq L225
    iload 3
    ldc 1296574530 (java.lang.Integer)
    if_icmpne L226
    new java/lang/IllegalStateException
    dup
    invokespecial java/lang/IllegalStateException <init>:()V
    athrow
L226
    new java/lang/StringBuilder
    dup
    invokespecial java/lang/StringBuilder <init>:()V
    ldc 16776960 (java.lang.Integer)
    bipush -37
    invokestatic p e:(IB)Ljava/lang/String;
    invokevirtual java/lang/StringBuilder append:(Ljava/lang/String;)Ljava/lang/StringBuilder;
    getstatic a l:Ljava/lang/String;
    invokevirtual java/lang/StringBuilder append:(Ljava/lang/String;)Ljava/lang/StringBuilder;
    invokevirtual java/lang/StringBuilder toString:()Ljava/lang/String;
    goto L227
L225
    ldc "" (java.lang.String)
L227
    invokevirtual java/lang/StringBuilder append:(Ljava/lang/String;)Ljava/lang/StringBuilder;
    invokevirtual java/lang/StringBuilder toString:()Ljava/lang/String;
    sipush 312
    iload 4
    ldc 16777215 (java.lang.Integer)
    iconst_0
    invokevirtual hh f:(Ljava/lang/String;IIII)V
L228
    iinc 4 15
L229
    aload 0
    astore 7
L230
    getstatic et hu:Ljava/lang/String;
    astore 8
L231
    getstatic ai ag:Ljava/lang/String;
    astore 10
L232
    aload 10
    invokeinterface java/lang/CharSequence length:()I
    istore 12
L233
    iload 12
    newarray 5
    astore 13
L234
    iconst_0
    istore 14
L235
    iload 14
    iload 12
    if_icmpge L236
    iload 3
    ldc 1296574530 (java.lang.Integer)
    if_icmpne L237
    return
L237
    aload 13
    iload 14
    bipush 42
    castore
    iinc 14 1
    goto L235
L236
    new java/lang/String
    dup
    aload 13
    invokespecial java/lang/String <init>:([C)V
    astore 11
L238
    aload 11
    astore 9
L239
    aload 7
    new java/lang/StringBuilder
    dup
    invokespecial java/lang/StringBuilder <init>:()V
    aload 8
    invokevirtual java/lang/StringBuilder append:(Ljava/lang/String;)Ljava/lang/StringBuilder;
    aload 9
    invokevirtual java/lang/StringBuilder append:(Ljava/lang/String;)Ljava/lang/StringBuilder;
    ldc 423886265 (java.lang.Integer)
    getstatic ai ak:I
    imul
    iconst_1
    if_icmpne L240
    iconst_1
    goto L241
L240
    iconst_0
L241
    ldc -117546507 (java.lang.Integer)
    getstatic client b:I
    imul
    bipush 40
    irem
    bipush 20
    if_icmpge L242
    iload 3
    ldc 1296574530 (java.lang.Integer)
    if_icmpne L243
    return
L243
    iconst_1
    goto L244
L242
    iconst_0
L244
    iand
    ifeq L245
    iload 3
    ldc 1296574530 (java.lang.Integer)
    if_icmpne L246
    new java/lang/IllegalStateException
    dup
    invokespecial java/lang/IllegalStateException <init>:()V
    athrow
L246
    new java/lang/StringBuilder
    dup
    invokespecial java/lang/StringBuilder <init>:()V
    ldc 16776960 (java.lang.Integer)
    bipush -40
    invokestatic p e:(IB)Ljava/lang/String;
    invokevirtual java/lang/StringBuilder append:(Ljava/lang/String;)Ljava/lang/StringBuilder;
    getstatic a l:Ljava/lang/String;
    invokevirtual java/lang/StringBuilder append:(Ljava/lang/String;)Ljava/lang/StringBuilder;
    invokevirtual java/lang/StringBuilder toString:()Ljava/lang/String;
    goto L247
L245
    ldc "" (java.lang.String)
L247
    invokevirtual java/lang/StringBuilder append:(Ljava/lang/String;)Ljava/lang/StringBuilder;
    invokevirtual java/lang/StringBuilder toString:()Ljava/lang/String;
    sipush 274
    iload 4
    ldc 16777215 (java.lang.Integer)
    iconst_0
    invokevirtual hh f:(Ljava/lang/String;IIII)V
L248
    iinc 4 15
L249
    sipush 302
    istore 11
L250
    sipush 321
    istore 12
L251
    getstatic ai l:Lbs;
    iload 11
    bipush 73
    isub
    iload 12
    bipush 20
    isub
    invokevirtual bs l:(II)V
L252
    aload 0
    getstatic et ie:Ljava/lang/String;
    iload 11
    iconst_5
    iload 12
    iadd
    ldc 16777215 (java.lang.Integer)
    iconst_0
    invokevirtual hh o:(Ljava/lang/String;IIII)V
L253
    sipush 462
    istore 11
L254
    getstatic ai l:Lbs;
    iload 11
    bipush 73
    isub
    iload 12
    bipush 20
    isub
    invokevirtual bs l:(II)V
L255
    aload 0
    getstatic et ic:Ljava/lang/String;
    iload 11
    iload 12
    iconst_5
    iadd
    ldc 16777215 (java.lang.Integer)
    iconst_0
    invokevirtual hh o:(Ljava/lang/String;IIII)V
L256
    sipush 357
    istore 4
L257
    aload 1
    getstatic et ij:Ljava/lang/String;
    sipush 382
    iload 4
    ldc 16776960 (java.lang.Integer)
    iconst_0
    invokevirtual hh o:(Ljava/lang/String;IIII)V
L258
    goto L173
L204
    iconst_4
    getstatic ai au:I
    ldc -47454393 (java.lang.Integer)
    imul
    if_icmpne L259
    iload 3
    ldc 1296574530 (java.lang.Integer)
    if_icmpne L260
    new java/lang/IllegalStateException
    dup
    invokespecial java/lang/IllegalStateException <init>:()V
    athrow
L260
    aload 0
    getstatic et hd:Ljava/lang/String;
    sipush 382
    sipush 211
    ldc 16776960 (java.lang.Integer)
    iconst_0
    invokevirtual hh o:(Ljava/lang/String;IIII)V
L261
    sipush 236
    istore 4
L262
    aload 0
    getstatic ai ae:Ljava/lang/String;
    sipush 382
    iload 4
    ldc 16777215 (java.lang.Integer)
    iconst_0
    invokevirtual hh o:(Ljava/lang/String;IIII)V
L263
    iinc 4 15
L264
    aload 0
    getstatic ai ab:Ljava/lang/String;
    sipush 382
    iload 4
    ldc 16777215 (java.lang.Integer)
    iconst_0
    invokevirtual hh o:(Ljava/lang/String;IIII)V
L265
    iinc 4 15
L266
    aload 0
    getstatic ai av:Ljava/lang/String;
    sipush 382
    iload 4
    ldc 16777215 (java.lang.Integer)
    iconst_0
    invokevirtual hh o:(Ljava/lang/String;IIII)V
L267
    iinc 4 15
L268
    aload 0
    new java/lang/StringBuilder
    dup
    invokespecial java/lang/StringBuilder <init>:()V
    getstatic et hj:Ljava/lang/String;
    invokevirtual java/lang/StringBuilder append:(Ljava/lang/String;)Ljava/lang/StringBuilder;
    getstatic dn at:Ljava/lang/String;
    ldc -1283222392 (java.lang.Integer)
    invokestatic et g:(Ljava/lang/CharSequence;I)Ljava/lang/String;
    invokevirtual java/lang/StringBuilder append:(Ljava/lang/String;)Ljava/lang/StringBuilder;
    getstatic client b:I
    ldc -117546507 (java.lang.Integer)
    imul
    bipush 40
    irem
    bipush 20
    if_icmpge L269
    iload 3
    ldc 1296574530 (java.lang.Integer)
    if_icmpne L270
    new java/lang/IllegalStateException
    dup
    invokespecial java/lang/IllegalStateException <init>:()V
    athrow
L270
    new java/lang/StringBuilder
    dup
    invokespecial java/lang/StringBuilder <init>:()V
    ldc 16776960 (java.lang.Integer)
    bipush -114
    invokestatic p e:(IB)Ljava/lang/String;
    invokevirtual java/lang/StringBuilder append:(Ljava/lang/String;)Ljava/lang/StringBuilder;
    getstatic a l:Ljava/lang/String;
    invokevirtual java/lang/StringBuilder append:(Ljava/lang/String;)Ljava/lang/StringBuilder;
    invokevirtual java/lang/StringBuilder toString:()Ljava/lang/String;
    goto L271
L269
    ldc "" (java.lang.String)
L271
    invokevirtual java/lang/StringBuilder append:(Ljava/lang/String;)Ljava/lang/StringBuilder;
    invokevirtual java/lang/StringBuilder toString:()Ljava/lang/String;
    sipush 274
    iload 4
    ldc 16777215 (java.lang.Integer)
    iconst_0
    invokevirtual hh f:(Ljava/lang/String;IIII)V
L272
    iinc 4 -8
L273
    aload 0
    getstatic et f:Ljava/lang/String;
    sipush 373
    iload 4
    ldc 16776960 (java.lang.Integer)
    iconst_0
    invokevirtual hh f:(Ljava/lang/String;IIII)V
L274
    iinc 4 15
L275
    aload 0
    getstatic et g:Ljava/lang/String;
    sipush 373
    iload 4
    ldc 16776960 (java.lang.Integer)
    iconst_0
    invokevirtual hh f:(Ljava/lang/String;IIII)V
L276
    sipush 373
    aload 0
    getstatic et g:Ljava/lang/String;
    invokevirtual hh c:(Ljava/lang/String;)I
    iadd
    bipush 15
    iadd
    istore 5
L277
    iload 4
    aload 0
    getfield hh i:I
    isub
    istore 6
L278
    getstatic ai al:Z
    ifeq L279
    iload 3
    ldc 1296574530 (java.lang.Integer)
    if_icmpne L280
    new java/lang/IllegalStateException
    dup
    invokespecial java/lang/IllegalStateException <init>:()V
    athrow
L280
    getstatic client g:Lbs;
    astore 7
    goto L281
L279
    getstatic y f:Lbs;
    astore 7
L281
    aload 7
    iload 5
    iload 6
    invokevirtual bs l:(II)V
L282
    iinc 4 15
L283
    sipush 302
    istore 8
L284
    sipush 321
    istore 9
L285
    getstatic ai l:Lbs;
    iload 8
    bipush 73
    isub
    iload 9
    bipush 20
    isub
    invokevirtual bs l:(II)V
L286
    aload 0
    getstatic et i:Ljava/lang/String;
    iload 8
    iload 9
    iconst_5
    iadd
    ldc 16777215 (java.lang.Integer)
    iconst_0
    invokevirtual hh o:(Ljava/lang/String;IIII)V
L287
    sipush 462
    istore 8
L288
    getstatic ai l:Lbs;
    iload 8
    bipush 73
    isub
    iload 9
    bipush 20
    isub
    invokevirtual bs l:(II)V
L289
    aload 0
    getstatic et ic:Ljava/lang/String;
    iload 8
    iload 9
    iconst_5
    iadd
    ldc 16777215 (java.lang.Integer)
    iconst_0
    invokevirtual hh o:(Ljava/lang/String;IIII)V
L290
    aload 1
    getstatic et hx:Ljava/lang/String;
    sipush 382
    iload 9
    bipush 36
    iadd
    sipush 255
    iconst_0
    invokevirtual hh o:(Ljava/lang/String;IIII)V
L291
    goto L173
L259
    getstatic ai au:I
    ldc -47454393 (java.lang.Integer)
    imul
    iconst_5
    if_icmpne L292
    iload 3
    ldc 1296574530 (java.lang.Integer)
    if_icmpne L293
    return
L293
    aload 0
    getstatic et il:Ljava/lang/String;
    sipush 382
    sipush 201
    ldc 16776960 (java.lang.Integer)
    iconst_0
    invokevirtual hh o:(Ljava/lang/String;IIII)V
L294
    sipush 221
    istore 4
L295
    aload 2
    getstatic ai ae:Ljava/lang/String;
    sipush 382
    iload 4
    ldc 16776960 (java.lang.Integer)
    iconst_0
    invokevirtual hh o:(Ljava/lang/String;IIII)V
L296
    iinc 4 15
L297
    aload 2
    getstatic ai ab:Ljava/lang/String;
    sipush 382
    iload 4
    ldc 16776960 (java.lang.Integer)
    iconst_0
    invokevirtual hh o:(Ljava/lang/String;IIII)V
L298
    iinc 4 15
L299
    aload 2
    getstatic ai av:Ljava/lang/String;
    sipush 382
    iload 4
    ldc 16776960 (java.lang.Integer)
    iconst_0
    invokevirtual hh o:(Ljava/lang/String;IIII)V
L300
    iinc 4 15
L301
    iinc 4 14
L302
    aload 0
    getstatic et ix:Ljava/lang/String;
    sipush 237
    iload 4
    ldc 16777215 (java.lang.Integer)
    iconst_0
    invokevirtual hh f:(Ljava/lang/String;IIII)V
L303
    sipush 174
    istore 5
L304
    getstatic ai ay:Ljava/lang/String;
    astore 6
L305
    aload 0
    aload 6
    invokevirtual hh c:(Ljava/lang/String;)I
    iload 5
    if_icmple L306
    iload 3
    ldc 1296574530 (java.lang.Integer)
    if_icmpne L307
    new java/lang/IllegalStateException
    dup
    invokespecial java/lang/IllegalStateException <init>:()V
    athrow
L307
    aload 6
    iconst_1
    invokevirtual java/lang/String substring:(I)Ljava/lang/String;
    astore 6
    goto L305
L306
    aload 0
    new java/lang/StringBuilder
    dup
    invokespecial java/lang/StringBuilder <init>:()V
    aload 6
    invokestatic ha r:(Ljava/lang/String;)Ljava/lang/String;
    invokevirtual java/lang/StringBuilder append:(Ljava/lang/String;)Ljava/lang/StringBuilder;
    ldc -117546507 (java.lang.Integer)
    getstatic client b:I
    imul
    bipush 40
    irem
    bipush 20
    if_icmpge L308
    iload 3
    ldc 1296574530 (java.lang.Integer)
    if_icmpne L309
    new java/lang/IllegalStateException
    dup
    invokespecial java/lang/IllegalStateException <init>:()V
    athrow
L309
    new java/lang/StringBuilder
    dup
    invokespecial java/lang/StringBuilder <init>:()V
    ldc 16776960 (java.lang.Integer)
    bipush -95
    invokestatic p e:(IB)Ljava/lang/String;
    invokevirtual java/lang/StringBuilder append:(Ljava/lang/String;)Ljava/lang/StringBuilder;
    getstatic a l:Ljava/lang/String;
    invokevirtual java/lang/StringBuilder append:(Ljava/lang/String;)Ljava/lang/StringBuilder;
    invokevirtual java/lang/StringBuilder toString:()Ljava/lang/String;
    goto L310
L308
    ldc "" (java.lang.String)
L310
    invokevirtual java/lang/StringBuilder append:(Ljava/lang/String;)Ljava/lang/StringBuilder;
    invokevirtual java/lang/StringBuilder toString:()Ljava/lang/String;
    sipush 348
    iload 4
    ldc 16777215 (java.lang.Integer)
    iconst_0
    invokevirtual hh f:(Ljava/lang/String;IIII)V
L311
    iinc 4 15
L312
    sipush 302
    istore 7
L313
    sipush 321
    istore 8
L314
    getstatic ai l:Lbs;
    iload 7
    bipush 73
    isub
    iload 8
    bipush 20
    isub
    invokevirtual bs l:(II)V
L315
    aload 0
    getstatic et iw:Ljava/lang/String;
    iload 7
    iload 8
    iconst_5
    iadd
    ldc 16777215 (java.lang.Integer)
    iconst_0
    invokevirtual hh o:(Ljava/lang/String;IIII)V
L316
    sipush 462
    istore 7
L317
    getstatic ai l:Lbs;
    iload 7
    bipush 73
    isub
    iload 8
    bipush 20
    isub
    invokevirtual bs l:(II)V
L318
    aload 0
    getstatic et ii:Ljava/lang/String;
    iload 7
    iload 8
    iconst_5
    iadd
    ldc 16777215 (java.lang.Integer)
    iconst_0
    invokevirtual hh o:(Ljava/lang/String;IIII)V
L319
    goto L173
L292
    ldc -47454393 (java.lang.Integer)
    getstatic ai au:I
    imul
    bipush 6
    if_icmpne L173
L320
    sipush 211
    istore 4
L321
    aload 0
    getstatic ai ae:Ljava/lang/String;
    sipush 382
    iload 4
    ldc 16776960 (java.lang.Integer)
    iconst_0
    invokevirtual hh o:(Ljava/lang/String;IIII)V
L322
    iinc 4 15
L323
    aload 0
    getstatic ai ab:Ljava/lang/String;
    sipush 382
    iload 4
    ldc 16776960 (java.lang.Integer)
    iconst_0
    invokevirtual hh o:(Ljava/lang/String;IIII)V
L324
    iinc 4 15
L325
    aload 0
    getstatic ai av:Ljava/lang/String;
    sipush 382
    iload 4
    ldc 16776960 (java.lang.Integer)
    iconst_0
    invokevirtual hh o:(Ljava/lang/String;IIII)V
L326
    iinc 4 15
L327
    sipush 382
    istore 5
L328
    sipush 321
    istore 6
L329
    getstatic ai l:Lbs;
    iload 5
    bipush 73
    isub
    iload 6
    bipush 20
    isub
    invokevirtual bs l:(II)V
L330
    aload 0
    getstatic et ii:Ljava/lang/String;
    iload 5
    iconst_5
    iload 6
    iadd
    ldc 16777215 (java.lang.Integer)
    iconst_0
    invokevirtual hh o:(Ljava/lang/String;IIII)V
L173
    ldc 1771145803 (java.lang.Integer)
    getstatic ai ao:I
    imul
    ifle L331
    iload 3
    ldc 1296574530 (java.lang.Integer)
    if_icmpne L332
    return
L332
    getstatic ai ao:I
    ldc 1771145803 (java.lang.Integer)
    imul
    istore 4
L333
    sipush 256
    istore 5
L334
    getstatic ai ax:I
    iload 4
    ldc 799587712 (java.lang.Integer)
    imul
    iadd
    putstatic ai ax:I
L335
    ldc 87418291 (java.lang.Integer)
    getstatic ai ax:I
    imul
    getstatic dq n:[I
    arraylength
    if_icmple L336
    iload 3
    ldc 1296574530 (java.lang.Integer)
    if_icmpne L337
    new java/lang/IllegalStateException
    dup
    invokespecial java/lang/IllegalStateException <init>:()V
    athrow
L337
    getstatic ai ax:I
    ldc -60862085 (java.lang.Integer)
    getstatic dq n:[I
    arraylength
    imul
    isub
    putstatic ai ax:I
L338
    invokestatic java/lang/Math random:()D
    ldc 12.0 (java.lang.Double)
    dmul
    d2i
    istore 6
L339
    getstatic ai c:[Lbs;
    iload 6
    aaload
    bipush -114
    invokestatic z i:(Lbs;B)V
L336
    iconst_0
    istore 6
L340
    sipush 128
    iload 4
    imul
    istore 7
L341
    iload 5
    iload 4
    isub
    sipush 128
    imul
    istore 8
L342
    iconst_0
    istore 9
L343
    iload 9
    iload 8
    if_icmpge L344
    iload 3
    ldc 1296574530 (java.lang.Integer)
    if_icmpne L345
    new java/lang/IllegalStateException
    dup
    invokespecial java/lang/IllegalStateException <init>:()V
    athrow
L345
    getstatic bi p:[I
    iload 6
    iload 7
    iadd
    iaload
    getstatic dq n:[I
    iload 6
    getstatic ai ax:I
    ldc 87418291 (java.lang.Integer)
    imul
    iadd
    getstatic dq n:[I
    arraylength
    iconst_1
    isub
    iand
    iaload
    iload 4
    imul
    bipush 6
    idiv
    isub
    istore 10
L346
    iload 10
    ifge L347
    iconst_0
    istore 10
L347
    getstatic bi p:[I
    iload 6
    iinc 6 1
    iload 10
    iastore
L348
    iinc 9 1
    goto L343
L344
    iload 5
    iload 4
    isub
    istore 9
L349
    iload 9
    iload 5
    if_icmpge L350
    iload 3
    ldc 1296574530 (java.lang.Integer)
    if_icmpne L351
    return
L351
    iload 9
    sipush 128
    imul
    istore 10
L352
    iconst_0
    istore 11
L353
    iload 11
    sipush 128
    if_icmpge L354
    iload 3
    ldc 1296574530 (java.lang.Integer)
    if_icmpne L355
    new java/lang/IllegalStateException
    dup
    invokespecial java/lang/IllegalStateException <init>:()V
    athrow
L355
    invokestatic java/lang/Math random:()D
    ldc 100.0 (java.lang.Double)
    dmul
    d2i
    istore 12
L356
    iload 12
    bipush 50
    if_icmpge L357
    iload 3
    ldc 1296574530 (java.lang.Integer)
    if_icmpne L358
    new java/lang/IllegalStateException
    dup
    invokespecial java/lang/IllegalStateException <init>:()V
    athrow
L358
    iload 11
    bipush 10
    if_icmple L357
    iload 3
    ldc 1296574530 (java.lang.Integer)
    if_icmpne L359
    new java/lang/IllegalStateException
    dup
    invokespecial java/lang/IllegalStateException <init>:()V
    athrow
L359
    iload 11
    bipush 118
    if_icmpge L357
    iload 3
    ldc 1296574530 (java.lang.Integer)
    if_icmpne L360
    new java/lang/IllegalStateException
    dup
    invokespecial java/lang/IllegalStateException <init>:()V
    athrow
L360
    getstatic bi p:[I
    iload 10
    iload 11
    iadd
    sipush 255
    iastore
    goto L361
L357
    getstatic bi p:[I
    iload 11
    iload 10
    iadd
    iconst_0
    iastore
L361
    iinc 11 1
    goto L353
L354
    iinc 9 1
    goto L349
L350
    getstatic ai b:I
    ldc 126146209 (java.lang.Integer)
    imul
    ifle L362
    iload 3
    ldc 1296574530 (java.lang.Integer)
    if_icmpne L363
    new java/lang/IllegalStateException
    dup
    invokespecial java/lang/IllegalStateException <init>:()V
    athrow
L363
    getstatic ai b:I
    iload 4
    ldc 802305412 (java.lang.Integer)
    imul
    isub
    putstatic ai b:I
L362
    ldc 730828835 (java.lang.Integer)
    getstatic ai x:I
    imul
    ifle L364
    iload 3
    ldc 1296574530 (java.lang.Integer)
    if_icmpne L365
    new java/lang/IllegalStateException
    dup
    invokespecial java/lang/IllegalStateException <init>:()V
    athrow
L365
    getstatic ai x:I
    iload 4
    ldc 1899396652 (java.lang.Integer)
    imul
    isub
    putstatic ai x:I
L364
    iconst_0
    ldc 126146209 (java.lang.Integer)
    getstatic ai b:I
    imul
    if_icmpne L366
    iload 3
    ldc 1296574530 (java.lang.Integer)
    if_icmpne L367
    new java/lang/IllegalStateException
    dup
    invokespecial java/lang/IllegalStateException <init>:()V
    athrow
L367
    iconst_0
    ldc 730828835 (java.lang.Integer)
    getstatic ai x:I
    imul
    if_icmpne L366
L368
    invokestatic java/lang/Math random:()D
    sipush 2000
    iload 4
    idiv
    i2d
    dmul
    d2i
    istore 9
L369
    iconst_0
    iload 9
    if_icmpne L370
    iload 3
    ldc 1296574530 (java.lang.Integer)
    if_icmpne L371
    new java/lang/IllegalStateException
    dup
    invokespecial java/lang/IllegalStateException <init>:()V
    athrow
L371
    ldc -768244736 (java.lang.Integer)
    putstatic ai b:I
L370
    iload 9
    iconst_1
    if_icmpne L366
    ldc 914238464 (java.lang.Integer)
    putstatic ai x:I
L366
    iconst_0
    istore 9
L372
    iload 9
    iload 5
    iload 4
    isub
    if_icmpge L373
    getstatic ai t:[I
    iload 9
    getstatic ai t:[I
    iload 4
    iload 9
    iadd
    iaload
    iastore
    iinc 9 1
    goto L372
L373
    iload 5
    iload 4
    isub
    istore 9
L374
    iload 9
    iload 5
    if_icmpge L375
L376
    getstatic ai t:[I
    iload 9
    ldc 1668207911 (java.lang.Integer)
    getstatic ai ai:I
    imul
    i2d
    ldc 14.0 (java.lang.Double)
    ddiv
    invokestatic java/lang/Math sin:(D)D
    ldc 16.0 (java.lang.Double)
    dmul
    ldc 1668207911 (java.lang.Integer)
    getstatic ai ai:I
    imul
    i2d
    ldc 15.0 (java.lang.Double)
    ddiv
    invokestatic java/lang/Math sin:(D)D
    ldc 14.0 (java.lang.Double)
    dmul
    dadd
    getstatic ai ai:I
    ldc 1668207911 (java.lang.Integer)
    imul
    i2d
    ldc 16.0 (java.lang.Double)
    ddiv
    invokestatic java/lang/Math sin:(D)D
    ldc 12.0 (java.lang.Double)
    dmul
    dadd
    d2i
    iastore
L377
    getstatic ai ai:I
    ldc 264587927 (java.lang.Integer)
    iadd
    putstatic ai ai:I
L378
    iinc 9 1
    goto L374
L375
    getstatic ai ap:I
    iload 4
    ldc -956820343 (java.lang.Integer)
    imul
    iadd
    putstatic ai ap:I
L379
    getstatic client b:I
    ldc -117546507 (java.lang.Integer)
    imul
    iconst_1
    iand
    iload 4
    iadd
    iconst_2
    idiv
    istore 9
L380
    iload 9
    ifle L381
    iload 3
    ldc 1296574530 (java.lang.Integer)
    if_icmpne L382
    new java/lang/IllegalStateException
    dup
    invokespecial java/lang/IllegalStateException <init>:()V
    athrow
L382
    iconst_0
    istore 10
L383
    iload 10
    getstatic ai ap:I
    ldc -818205628 (java.lang.Integer)
    imul
    if_icmpge L384
    iload 3
    ldc 1296574530 (java.lang.Integer)
    if_icmpne L385
    new java/lang/IllegalStateException
    dup
    invokespecial java/lang/IllegalStateException <init>:()V
    athrow
L385
    invokestatic java/lang/Math random:()D
    ldc 124.0 (java.lang.Double)
    dmul
    d2i
    iconst_2
    iadd
    istore 11
L386
    invokestatic java/lang/Math random:()D
    ldc 128.0 (java.lang.Double)
    dmul
    d2i
    sipush 128
    iadd
    istore 12
L387
    getstatic bi p:[I
    iload 11
    iload 12
    bipush 7
    ishl
    iadd
    sipush 192
    iastore
L388
    iinc 10 1
    goto L383
L384
    iconst_0
    putstatic ai ap:I
L389
    iconst_0
    istore 10
L390
    iload 10
    iload 5
    if_icmpge L391
    iload 3
    ldc 1296574530 (java.lang.Integer)
    if_icmpne L392
    new java/lang/IllegalStateException
    dup
    invokespecial java/lang/IllegalStateException <init>:()V
    athrow
L392
    iconst_0
    istore 11
L393
    iload 10
    sipush 128
    imul
    istore 12
L394
    iload 9
    ineg
    istore 13
L395
    iload 13
    sipush 128
    if_icmpge L396
    iload 3
    ldc 1296574530 (java.lang.Integer)
    if_icmpne L397
    return
L397
    iload 13
    iload 9
    iadd
    sipush 128
    if_icmpge L398
    iload 3
    ldc 1296574530 (java.lang.Integer)
    if_icmpne L399
    return
L399
    iload 11
    getstatic bi p:[I
    iload 9
    iload 13
    iload 12
    iadd
    iadd
    iaload
    iadd
    istore 11
L398
    iload 13
    iload 9
    iconst_1
    iadd
    isub
    iflt L400
    iload 3
    ldc 1296574530 (java.lang.Integer)
    if_icmpne L401
    new java/lang/IllegalStateException
    dup
    invokespecial java/lang/IllegalStateException <init>:()V
    athrow
L401
    iload 11
    getstatic bi p:[I
    iload 12
    iload 13
    iadd
    iconst_1
    iload 9
    iadd
    isub
    iaload
    isub
    istore 11
L400
    iload 13
    iflt L402
    getstatic em k:[I
    iload 12
    iload 13
    iadd
    iload 11
    iconst_1
    iload 9
    iconst_2
    imul
    iadd
    idiv
    iastore
L402
    iinc 13 1
    goto L395
L396
    iinc 10 1
    goto L390
L391
    iconst_0
    istore 10
L403
    iload 10
    sipush 128
    if_icmpge L381
    iload 3
    ldc 1296574530 (java.lang.Integer)
    if_icmpne L404
    return
L404
    iconst_0
    istore 11
L405
    iload 9
    ineg
    istore 12
L406
    iload 12
    iload 5
    if_icmpge L407
    iload 3
    ldc 1296574530 (java.lang.Integer)
    if_icmpne L408
    new java/lang/IllegalStateException
    dup
    invokespecial java/lang/IllegalStateException <init>:()V
    athrow
L408
    sipush 128
    iload 12
    imul
    istore 13
L409
    iload 12
    iload 9
    iadd
    iload 5
    if_icmpge L410
    iload 3
    ldc 1296574530 (java.lang.Integer)
    if_icmpne L411
    return
L411
    iload 11
    getstatic em k:[I
    iload 10
    iload 13
    iadd
    sipush 128
    iload 9
    imul
    iadd
    iaload
    iadd
    istore 11
L410
    iload 12
    iload 9
    iconst_1
    iadd
    isub
    iflt L412
    iload 11
    getstatic em k:[I
    iload 13
    iload 10
    iadd
    iconst_1
    iload 9
    iadd
    sipush 128
    imul
    isub
    iaload
    isub
    istore 11
L412
    iload 12
    iflt L413
    iload 3
    ldc 1296574530 (java.lang.Integer)
    if_icmpne L414
    new java/lang/IllegalStateException
    dup
    invokespecial java/lang/IllegalStateException <init>:()V
    athrow
L414
    getstatic bi p:[I
    iload 13
    iload 10
    iadd
    iload 11
    iconst_1
    iconst_2
    iload 9
    imul
    iadd
    idiv
    iastore
L413
    iinc 12 1
    goto L406
L407
    iinc 10 1
    goto L403
L381
    iconst_0
    putstatic ai ao:I
L331
    bipush -55
    invokestatic eo f:(B)V
L415
    getstatic eb r:[Lbs;
    getstatic dk ol:Lf;
    getfield f c:Z
    ifeq L416
    iload 3
    ldc 1296574530 (java.lang.Integer)
    if_icmpne L417
    new java/lang/IllegalStateException
    dup
    invokespecial java/lang/IllegalStateException <init>:()V
    athrow
L417
    iconst_1
    goto L418
L416
    iconst_0
L418
    aaload
    sipush 725
    sipush 463
    invokevirtual bs l:(II)V
L419
    getstatic client q:I
    ldc 1532705327 (java.lang.Integer)
    imul
    iconst_5
    if_icmple L420
    iload 3
    ldc 1296574530 (java.lang.Integer)
    if_icmpne L421
    new java/lang/IllegalStateException
    dup
    invokespecial java/lang/IllegalStateException <init>:()V
    athrow
L421
    iconst_0
    getstatic client s:I
    ldc 1136922049 (java.lang.Integer)
    imul
    if_icmpne L420
L422
    getstatic o bl:Lbs;
    ifnull L423
    iload 3
    ldc 1296574530 (java.lang.Integer)
    if_icmpne L424
    return
L424
    iconst_5
    istore 4
L425
    sipush 463
    istore 5
L426
    bipush 100
    istore 6
L427
    bipush 35
    istore 7
L428
    getstatic o bl:Lbs;
    iload 4
    iload 5
    invokevirtual bs l:(II)V
L429
    aload 0
    new java/lang/StringBuilder
    dup
    invokespecial java/lang/StringBuilder <init>:()V
    getstatic et fy:Ljava/lang/String;
    invokevirtual java/lang/StringBuilder append:(Ljava/lang/String;)Ljava/lang/StringBuilder;
    ldc " " (java.lang.String)
    invokevirtual java/lang/StringBuilder append:(Ljava/lang/String;)Ljava/lang/StringBuilder;
    ldc 2109224683 (java.lang.Integer)
    getstatic client c:I
    imul
    invokevirtual java/lang/StringBuilder append:(I)Ljava/lang/StringBuilder;
    invokevirtual java/lang/StringBuilder toString:()Ljava/lang/String;
    iload 6
    iconst_2
    idiv
    iload 4
    iadd
    iload 5
    iload 7
    iconst_2
    idiv
    iadd
    iconst_2
    isub
    ldc 16777215 (java.lang.Integer)
    iconst_0
    invokevirtual hh o:(Ljava/lang/String;IIII)V
L430
    aconst_null
    getstatic da an:Ly;
    if_acmpeq L431
    iload 3
    ldc 1296574530 (java.lang.Integer)
    if_icmpne L432
    return
L432
    aload 1
    getstatic et jp:Ljava/lang/String;
    iload 4
    iload 6
    iconst_2
    idiv
    iadd
    bipush 12
    iload 5
    iload 7
    iconst_2
    idiv
    iadd
    iadd
    ldc 16777215 (java.lang.Integer)
    iconst_0
    invokevirtual hh o:(Ljava/lang/String;IIII)V
    goto L433
L431
    aload 1
    getstatic et jo:Ljava/lang/String;
    iload 6
    iconst_2
    idiv
    iload 4
    iadd
    bipush 12
    iload 7
    iconst_2
    idiv
    iload 5
    iadd
    iadd
    ldc 16777215 (java.lang.Integer)
    iconst_0
    invokevirtual hh o:(Ljava/lang/String;IIII)V
L433
    goto L420
L423
    getstatic t be:Lfo;
    ldc "sl_button" (java.lang.String)
    ldc "" (java.lang.String)
    ldc 178245890 (java.lang.Integer)
    invokestatic an w:(Lfv;Ljava/lang/String;Ljava/lang/String;I)Lbs;
    putstatic o bl:Lbs;
L420
    getstatic eb pd:Ljava/awt/Canvas;
    invokevirtual java/awt/Canvas getGraphics:()Ljava/awt/Graphics;
    astore 4
L434
    getstatic v py:Lbz;
    aload 4
    iconst_0
    iconst_0
    bipush -5
    invokevirtual bz a:(Ljava/awt/Graphics;IIB)V
L435
    goto L436
L437
    astore 4
L438
    getstatic eb pd:Ljava/awt/Canvas;
    invokevirtual java/awt/Canvas repaint:()V
L436
    return
L439
    new java/lang/StringBuilder
    dup
    invokespecial java/lang/StringBuilder <init>:()V
    ldc "i.u(" (java.lang.String)
    invokevirtual java/lang/StringBuilder append:(Ljava/lang/String;)Ljava/lang/StringBuilder;
    ldc 41 (java.lang.Integer)
    invokevirtual java/lang/StringBuilder append:(C)Ljava/lang/StringBuilder;
    invokevirtual java/lang/StringBuilder toString:()Ljava/lang/String;
    invokestatic k a:(Ljava/lang/Throwable;Ljava/lang/String;)Lee;
    athrow
