j bx (III)VL1
    ldc 811532485 (java.lang.Integer)
    getstatic client ii:I
    imul
    iconst_2
    if_icmpge L2
    iload 2
    ldc 744023977 (java.lang.Integer)
    if_icmpne L3
    return
L4
    ldc 811532485 (java.lang.Integer)
    getstatic client ii:I
    imul
    iconst_2
    if_icmpge L5
    iload 2
    ldc 744023977 (java.lang.Integer)
    if_icmpne L6
    return
L7
    getstatic client iy:[Ljava/lang/String;
    iload 5
    aaload
    astore 4
    goto L8
L9
    getstatic client iu:[Ljava/lang/String;
    iload 5
    aaload
    invokevirtual java/lang/String length:()I
    ifle L7
    iload 2
    ldc 744023977 (java.lang.Integer)
    if_icmpne L10
    return
L2
    iconst_1
    getstatic client in:I
    ldc 1293091945 (java.lang.Integer)
    imul
    if_icmpne L5
    iload 2
    ldc 744023977 (java.lang.Integer)
    if_icmpne L4
    return
L11
    new java/lang/StringBuilder
    dup
    invokespecial java/lang/StringBuilder <init>:()V
    getstatic client jf:Ljava/lang/String;
    invokevirtual java/lang/StringBuilder append:(Ljava/lang/String;)Ljava/lang/StringBuilder;
    getstatic et fz:Ljava/lang/String;
    invokevirtual java/lang/StringBuilder append:(Ljava/lang/String;)Ljava/lang/StringBuilder;
    getstatic client jk:Ljava/lang/String;
    invokevirtual java/lang/StringBuilder append:(Ljava/lang/String;)Ljava/lang/StringBuilder;
    ldc " " (java.lang.String)
    invokevirtual java/lang/StringBuilder append:(Ljava/lang/String;)Ljava/lang/StringBuilder;
    getstatic a w:Ljava/lang/String;
    invokevirtual java/lang/StringBuilder append:(Ljava/lang/String;)Ljava/lang/StringBuilder;
    invokevirtual java/lang/StringBuilder toString:()Ljava/lang/String;
    astore 3
    goto L12
L6
    new java/lang/StringBuilder
    dup
    invokespecial java/lang/StringBuilder <init>:()V
    getstatic et ev:Ljava/lang/String;
    invokevirtual java/lang/StringBuilder append:(Ljava/lang/String;)Ljava/lang/StringBuilder;
    getstatic et fz:Ljava/lang/String;
    invokevirtual java/lang/StringBuilder append:(Ljava/lang/String;)Ljava/lang/StringBuilder;
    getstatic client it:Ljava/lang/String;
    invokevirtual java/lang/StringBuilder append:(Ljava/lang/String;)Ljava/lang/StringBuilder;
    ldc " " (java.lang.String)
    invokevirtual java/lang/StringBuilder append:(Ljava/lang/String;)Ljava/lang/StringBuilder;
    getstatic a w:Ljava/lang/String;
    invokevirtual java/lang/StringBuilder append:(Ljava/lang/String;)Ljava/lang/StringBuilder;
    invokevirtual java/lang/StringBuilder toString:()Ljava/lang/String;
    astore 3
    goto L12
L5
    getstatic client is:Z
    ifeq L13
    iload 2
    ldc 744023977 (java.lang.Integer)
    if_icmpne L14
    new java/lang/IllegalStateException
    dup
    invokespecial java/lang/IllegalStateException <init>:()V
    athrow
L14
    ldc 811532485 (java.lang.Integer)
    getstatic client ii:I
    imul
    iconst_2
    if_icmpge L13
    iload 2
    ldc 744023977 (java.lang.Integer)
    if_icmpne L11
    return
L8
    aload 4
    astore 3
    goto L12
L13
    ldc 811532485 (java.lang.Integer)
    getstatic client ii:I
    imul
    iconst_1
    isub
    istore 5
    goto L9
L15
    getstatic hg cn:Lhh;
    aload 3
    iconst_4
    iload 0
    iadd
    iload 1
    bipush 15
    iadd
    ldc 16777215 (java.lang.Integer)
    iconst_0
    ldc -117546507 (java.lang.Integer)
    getstatic client b:I
    imul
    sipush 1000
    idiv
    invokevirtual hh t:(Ljava/lang/String;IIIII)V
    goto L16
L10
    new java/lang/StringBuilder
    dup
    invokespecial java/lang/StringBuilder <init>:()V
    getstatic client iy:[Ljava/lang/String;
    iload 5
    aaload
    invokevirtual java/lang/StringBuilder append:(Ljava/lang/String;)Ljava/lang/StringBuilder;
    getstatic et fz:Ljava/lang/String;
    invokevirtual java/lang/StringBuilder append:(Ljava/lang/String;)Ljava/lang/StringBuilder;
    getstatic client iu:[Ljava/lang/String;
    iload 5
    aaload
    invokevirtual java/lang/StringBuilder append:(Ljava/lang/String;)Ljava/lang/StringBuilder;
    invokevirtual java/lang/StringBuilder toString:()Ljava/lang/String;
    astore 4
    goto L8
L17
    getstatic client is:Z
    ifne L2
    return
L12
    ldc 811532485 (java.lang.Integer)
    getstatic client ii:I
    imul
    iconst_2
    if_icmple L15
    iload 2
    ldc 744023977 (java.lang.Integer)
    if_icmpne L18
    new java/lang/IllegalStateException
    dup
    invokespecial java/lang/IllegalStateException <init>:()V
    athrow
L18
    new java/lang/StringBuilder
    dup
    invokespecial java/lang/StringBuilder <init>:()V
    aload 3
    invokevirtual java/lang/StringBuilder append:(Ljava/lang/String;)Ljava/lang/StringBuilder;
    ldc 16777215 (java.lang.Integer)
    bipush -55
    invokestatic p e:(IB)Ljava/lang/String;
    invokevirtual java/lang/StringBuilder append:(Ljava/lang/String;)Ljava/lang/StringBuilder;
    ldc " " (java.lang.String)
    invokevirtual java/lang/StringBuilder append:(Ljava/lang/String;)Ljava/lang/StringBuilder;
    bipush 47
    invokevirtual java/lang/StringBuilder append:(C)Ljava/lang/StringBuilder;
    ldc " " (java.lang.String)
    invokevirtual java/lang/StringBuilder append:(Ljava/lang/String;)Ljava/lang/StringBuilder;
    ldc 811532485 (java.lang.Integer)
    getstatic client ii:I
    imul
    iconst_2
    isub
    invokevirtual java/lang/StringBuilder append:(I)Ljava/lang/StringBuilder;
    getstatic et en:Ljava/lang/String;
    invokevirtual java/lang/StringBuilder append:(Ljava/lang/String;)Ljava/lang/StringBuilder;
    invokevirtual java/lang/StringBuilder toString:()Ljava/lang/String;
    astore 3
    goto L15
L3
    getstatic client in:I
    ldc 1293091945 (java.lang.Integer)
    imul
    ifne L2
    iload 2
    ldc 744023977 (java.lang.Integer)
    if_icmpne L17
    return
L16
    return
L19
    new java/lang/StringBuilder
    dup
    invokespecial java/lang/StringBuilder <init>:()V
    ldc "j.bx(" (java.lang.String)
    invokevirtual java/lang/StringBuilder append:(Ljava/lang/String;)Ljava/lang/StringBuilder;
    ldc 41 (java.lang.Integer)
    invokevirtual java/lang/StringBuilder append:(C)Ljava/lang/StringBuilder;
    invokevirtual java/lang/StringBuilder toString:()Ljava/lang/String;
    invokestatic k a:(Ljava/lang/Throwable;Ljava/lang/String;)Lee;
    athrow
