j cz (IIIB)Lc;L1
    new c
    dup
    invokespecial c <init>:()V
    astore 4
    goto L2
L3
    iload 6
    ldc 1928687330 (java.lang.Integer)
    invokestatic df c:(II)Z
    ifne L4
    iload 3
    bipush 17
    if_icmpeq L5
    new java/lang/IllegalStateException
    dup
    invokespecial java/lang/IllegalStateException <init>:()V
    athrow
L6
    aload 4
    iload 2
    ldc 279327029 (java.lang.Integer)
    imul
    putfield c a:I
L7
    getstatic client jv:Lgf;
    aload 4
    iload 0
    i2l
    invokevirtual gf a:(Lgm;J)V
L8
    iload 1
    sipush -31021
    invokestatic av co:(IS)V
    goto L9
L10
    getstatic client jz:Lfb;
    ldc -1023277750 (java.lang.Integer)
    invokestatic dh cr:(Lfb;I)V
    goto L11
L12
    iload 0
    ldc -2068421293 (java.lang.Integer)
    invokestatic f a:(II)Lfb;
    astore 5
    goto L13
L5
    goto L14
L15
    aload 5
    ldc -1023277750 (java.lang.Integer)
    invokestatic dh cr:(Lfb;I)V
    goto L16
L13
    aconst_null
    aload 5
    if_acmpeq L16
    iload 3
    bipush 17
    if_icmpeq L15
    new java/lang/IllegalStateException
    dup
    invokespecial java/lang/IllegalStateException <init>:()V
    athrow
L16
    aconst_null
    getstatic client jz:Lfb;
    if_acmpeq L17
    goto L10
L11
    aconst_null
    putstatic client jz:Lfb;
L17
    ldc 359132303 (java.lang.Integer)
    invokestatic j bg:(I)V
L18
    ldc -1189404095 (java.lang.Integer)
    getstatic client jn:I
    imul
    iconst_m1
    if_icmpeq L14
    iload 3
    bipush 17
    if_icmpeq L19
    new java/lang/IllegalStateException
    dup
    invokespecial java/lang/IllegalStateException <init>:()V
    athrow
L19
    getstatic client jn:I
    ldc -1189404095 (java.lang.Integer)
    imul
    istore 6
    goto L3
L2
    aload 4
    iload 1
    ldc 1458814491 (java.lang.Integer)
    imul
    putfield c e:I
    goto L6
L9
    iload 1
    ldc -1251557586 (java.lang.Integer)
    invokestatic ax l:(II)V
    goto L12
L4
    getstatic fb e:[[Lfb;
    iload 6
    aaload
    iconst_1
    ldc -92685187 (java.lang.Integer)
    invokestatic ap ct:([Lfb;II)V
L14
    aload 4
    areturn
L20
    new java/lang/StringBuilder
    dup
    invokespecial java/lang/StringBuilder <init>:()V
    ldc "j.cz(" (java.lang.String)
    invokevirtual java/lang/StringBuilder append:(Ljava/lang/String;)Ljava/lang/StringBuilder;
    ldc 41 (java.lang.Integer)
    invokevirtual java/lang/StringBuilder append:(C)Ljava/lang/StringBuilder;
    invokevirtual java/lang/StringBuilder toString:()Ljava/lang/String;
    invokestatic k a:(Ljava/lang/Throwable;Ljava/lang/String;)Lee;
    athrow
