l e (Ldh;I)VL1
    aload 1
    iconst_0
    putfield dh a:I
    goto L2
L3
    iload 6
    bipush 12
    if_icmpge L4
    iload 2
    ldc 541244721 (java.lang.Integer)
    if_icmpeq L5
    return
L6
    aload 0
    aload 1
    bipush 9
    invokevirtual dh y:(B)B
    ldc 1831680313 (java.lang.Integer)
    imul
    putfield l l:I
L7
    aload 0
    aload 1
    bipush 122
    invokevirtual dh y:(B)B
    ldc 1340456745 (java.lang.Integer)
    imul
    putfield l c:I
L8
    iconst_m1
    istore 4
L9
    aload 0
    iconst_0
    putfield l q:I
    goto L10
L11
    iload 8
    iflt L12
    iload 2
    ldc 541244721 (java.lang.Integer)
    if_icmpeq L13
    new java/lang/IllegalStateException
    dup
    invokespecial java/lang/IllegalStateException <init>:()V
    athrow
L14
    iconst_0
    istore 6
    goto L3
L15
    ldc -708614931 (java.lang.Integer)
    getstatic client r:I
    imul
    ifne L16
    iload 2
    ldc 541244721 (java.lang.Integer)
    if_icmpeq L17
    new java/lang/IllegalStateException
    dup
    invokespecial java/lang/IllegalStateException <init>:()V
    athrow
L18
    return
L19
    iload 7
    ifne L20
    iload 2
    ldc 541244721 (java.lang.Integer)
    if_icmpeq L21
    new java/lang/IllegalStateException
    dup
    invokespecial java/lang/IllegalStateException <init>:()V
    athrow
L21
    aload 5
    iload 6
    iconst_0
    iastore
L22
    goto L23
L20
    aload 1
    ldc 651503594 (java.lang.Integer)
    invokevirtual dh z:(I)I
    istore 8
L24
    aload 5
    iload 6
    iload 8
    iload 7
    bipush 8
    ishl
    iadd
    iastore
L25
    iconst_0
    iload 6
    if_icmpne L26
    iload 2
    ldc 541244721 (java.lang.Integer)
    if_icmpeq L27
    new java/lang/IllegalStateException
    dup
    invokespecial java/lang/IllegalStateException <init>:()V
    athrow
L28
    iinc 7 1
    goto L29
L30
    aload 1
    ldc 735648899 (java.lang.Integer)
    invokevirtual dh q:(I)I
    istore 4
L31
    goto L4
L32
    aload 0
    ldc 1189257963 (java.lang.Integer)
    putfield l k:I
    goto L33
L27
    aload 5
    iconst_0
    iaload
    ldc 65535 (java.lang.Integer)
    if_icmpne L26
    goto L30
L34
    aload 0
    aload 1
    ldc 1068598799 (java.lang.Integer)
    invokevirtual dh q:(I)I
    ldc 556026125 (java.lang.Integer)
    imul
    putfield l am:I
    goto L35
L36
    aload 0
    iload 9
    ldc 1041515017 (java.lang.Integer)
    imul
    putfield l q:I
L23
    iinc 6 1
    goto L3
L4
    iconst_5
    newarray 10
    astore 6
L37
    iconst_0
    istore 7
L29
    iload 7
    iconst_5
    if_icmpge L38
    iload 2
    ldc 541244721 (java.lang.Integer)
    if_icmpeq L39
    new java/lang/IllegalStateException
    dup
    invokespecial java/lang/IllegalStateException <init>:()V
    athrow
L40
    aload 0
    ldc -482982463 (java.lang.Integer)
    putfield l ai:I
    goto L41
L16
    aload 0
    getfield l a:Lfq;
    ifnonnull L42
    iload 2
    ldc 541244721 (java.lang.Integer)
    if_icmpeq L43
    return
L44
    aload 0
    getfield l au:I
    ldc -715260025 (java.lang.Integer)
    imul
    ldc 65535 (java.lang.Integer)
    if_icmpne L45
    iload 2
    ldc 541244721 (java.lang.Integer)
    if_icmpeq L46
    new java/lang/IllegalStateException
    dup
    invokespecial java/lang/IllegalStateException <init>:()V
    athrow
L39
    aload 1
    ldc 1260402765 (java.lang.Integer)
    invokevirtual dh z:(I)I
    istore 8
    goto L11
L47
    aload 6
    iload 7
    iload 8
    iastore
    goto L28
L48
    ldc 65535 (java.lang.Integer)
    ldc -484883235 (java.lang.Integer)
    aload 0
    getfield l ao:I
    imul
    if_icmpne L49
    iload 2
    ldc 541244721 (java.lang.Integer)
    if_icmpeq L50
    new java/lang/IllegalStateException
    dup
    invokespecial java/lang/IllegalStateException <init>:()V
    athrow
L51
    aload 5
    iload 6
    iaload
    sipush 512
    isub
    bipush -10
    invokestatic dj e:(IB)Lad;
    getfield ad as:I
    ldc 842043747 (java.lang.Integer)
    imul
    istore 9
    goto L52
L53
    ldc 65535 (java.lang.Integer)
    ldc 140905021 (java.lang.Integer)
    aload 0
    getfield l k:I
    imul
    if_icmpne L33
    iload 2
    ldc 541244721 (java.lang.Integer)
    if_icmpeq L32
    new java/lang/IllegalStateException
    dup
    invokespecial java/lang/IllegalStateException <init>:()V
    athrow
L54
    aload 0
    getstatic hg hv:Ll;
    if_acmpne L55
    iload 2
    ldc 541244721 (java.lang.Integer)
    if_icmpeq L56
    new java/lang/IllegalStateException
    dup
    invokespecial java/lang/IllegalStateException <init>:()V
    athrow
L33
    aload 0
    aload 1
    ldc -2146448712 (java.lang.Integer)
    invokevirtual dh q:(I)I
    ldc -1073420625 (java.lang.Integer)
    imul
    putfield l ax:I
L57
    aload 0
    getfield l ax:I
    ldc 1870934095 (java.lang.Integer)
    imul
    ldc 65535 (java.lang.Integer)
    if_icmpne L58
    iload 2
    ldc 541244721 (java.lang.Integer)
    if_icmpeq L59
    new java/lang/IllegalStateException
    dup
    invokespecial java/lang/IllegalStateException <init>:()V
    athrow
L59
    aload 0
    ldc 1073420625 (java.lang.Integer)
    putfield l ax:I
L58
    aload 0
    aload 0
    getfield l ax:I
    ldc -717852443 (java.lang.Integer)
    imul
    putfield l ap:I
L60
    aload 0
    aload 1
    ldc 165645110 (java.lang.Integer)
    invokevirtual dh q:(I)I
    ldc 204583797 (java.lang.Integer)
    imul
    putfield l ao:I
    goto L48
L52
    iload 9
    ifeq L23
    iload 2
    ldc 541244721 (java.lang.Integer)
    if_icmpeq L36
    new java/lang/IllegalStateException
    dup
    invokespecial java/lang/IllegalStateException <init>:()V
    athrow
L41
    aload 0
    aload 1
    ldc 1369766869 (java.lang.Integer)
    invokevirtual dh q:(I)I
    ldc -570019589 (java.lang.Integer)
    imul
    putfield l aw:I
    goto L61
L49
    aload 0
    aload 1
    ldc -1327958020 (java.lang.Integer)
    invokevirtual dh q:(I)I
    ldc 482982463 (java.lang.Integer)
    imul
    putfield l ai:I
L62
    ldc 65535 (java.lang.Integer)
    ldc 743519679 (java.lang.Integer)
    aload 0
    getfield l ai:I
    imul
    if_icmpne L41
    iload 2
    ldc 541244721 (java.lang.Integer)
    if_icmpeq L40
    new java/lang/IllegalStateException
    dup
    invokespecial java/lang/IllegalStateException <init>:()V
    athrow
L50
    aload 0
    ldc -204583797 (java.lang.Integer)
    putfield l ao:I
    goto L49
L63
    aload 0
    ldc -556026125 (java.lang.Integer)
    putfield l am:I
    goto L64
L2
    aload 1
    ldc 1635800587 (java.lang.Integer)
    invokevirtual dh z:(I)I
    istore 3
    goto L6
L65
    aload 0
    ldc 570019589 (java.lang.Integer)
    putfield l aw:I
    goto L34
L46
    aload 0
    ldc 712796617 (java.lang.Integer)
    putfield l au:I
    goto L45
L35
    ldc 65535 (java.lang.Integer)
    ldc 655273413 (java.lang.Integer)
    aload 0
    getfield l am:I
    imul
    if_icmpne L64
    goto L63
L61
    ldc 1759795763 (java.lang.Integer)
    aload 0
    getfield l aw:I
    imul
    ldc 65535 (java.lang.Integer)
    if_icmpne L34
    iload 2
    ldc 541244721 (java.lang.Integer)
    if_icmpeq L65
    new java/lang/IllegalStateException
    dup
    invokespecial java/lang/IllegalStateException <init>:()V
    athrow
L64
    aload 0
    aload 1
    ldc 509513207 (java.lang.Integer)
    invokevirtual dh q:(I)I
    ldc -712796617 (java.lang.Integer)
    imul
    putfield l au:I
    goto L44
L43
    aload 0
    new fq
    dup
    invokespecial fq <init>:()V
    putfield l a:Lfq;
    goto L42
L12
    iconst_0
    istore 8
    goto L47
L26
    aload 5
    iload 6
    iaload
    sipush 512
    if_icmplt L23
    iload 2
    ldc 541244721 (java.lang.Integer)
    if_icmpeq L51
    new java/lang/IllegalStateException
    dup
    invokespecial java/lang/IllegalStateException <init>:()V
    athrow
L66
    aload 0
    aload 1
    ldc 646400279 (java.lang.Integer)
    invokevirtual dh q:(I)I
    ldc -1793975997 (java.lang.Integer)
    imul
    putfield l w:I
    goto L67
L56
    aload 0
    getfield l e:Ljava/lang/String;
    putstatic ee a:Ljava/lang/String;
L55
    aload 0
    aload 1
    ldc 752699100 (java.lang.Integer)
    invokevirtual dh z:(I)I
    ldc 1972414871 (java.lang.Integer)
    imul
    putfield l u:I
    goto L66
L13
    iload 8
    getstatic bz r:[[S
    iload 7
    aaload
    arraylength
    if_icmplt L47
    iload 2
    ldc 541244721 (java.lang.Integer)
    if_icmpeq L12
    return
L67
    aload 0
    aload 1
    ldc 994700744 (java.lang.Integer)
    invokevirtual dh z:(I)I
    iconst_1
    if_icmpne L68
    iload 2
    ldc 541244721 (java.lang.Integer)
    if_icmpeq L69
    new java/lang/IllegalStateException
    dup
    invokespecial java/lang/IllegalStateException <init>:()V
    athrow
L69
    iconst_1
    goto L70
L68
    iconst_0
L70
    putfield l d:Z
    goto L15
L38
    aload 0
    aload 1
    ldc -252827417 (java.lang.Integer)
    invokevirtual dh q:(I)I
    ldc -1189257963 (java.lang.Integer)
    imul
    putfield l k:I
    goto L53
L17
    getstatic client jp:I
    ldc 339448555 (java.lang.Integer)
    imul
    iconst_2
    if_icmplt L16
    iload 2
    ldc 541244721 (java.lang.Integer)
    if_icmpeq L71
    new java/lang/IllegalStateException
    dup
    invokespecial java/lang/IllegalStateException <init>:()V
    athrow
L71
    aload 0
    iconst_0
    putfield l d:Z
    goto L16
L5
    aload 1
    ldc 677992085 (java.lang.Integer)
    invokevirtual dh z:(I)I
    istore 7
    goto L19
L45
    aload 0
    aload 1
    ldc 406727896 (java.lang.Integer)
    invokevirtual dh p:(I)Ljava/lang/String;
    putfield l e:Ljava/lang/String;
    goto L54
L42
    aload 0
    getfield l a:Lfq;
    aload 5
    aload 6
    iload 3
    iconst_1
    if_icmpne L72
    iload 2
    ldc 541244721 (java.lang.Integer)
    if_icmpeq L73
    new java/lang/IllegalStateException
    dup
    invokespecial java/lang/IllegalStateException <init>:()V
    athrow
L73
    iconst_1
    goto L74
L72
    iconst_0
L74
    iload 4
    ldc 1663840826 (java.lang.Integer)
    invokevirtual fq e:([I[IZII)V
    goto L18
L10
    bipush 12
    newarray 10
    astore 5
    goto L14
L75
    new java/lang/StringBuilder
    dup
    invokespecial java/lang/StringBuilder <init>:()V
    ldc "l.e(" (java.lang.String)
    invokevirtual java/lang/StringBuilder append:(Ljava/lang/String;)Ljava/lang/StringBuilder;
    ldc 41 (java.lang.Integer)
    invokevirtual java/lang/StringBuilder append:(C)Ljava/lang/StringBuilder;
    invokevirtual java/lang/StringBuilder toString:()Ljava/lang/String;
    invokestatic k a:(Ljava/lang/Throwable;Ljava/lang/String;)Lee;
    athrow
