l l (IIILag;II)VL1
    new x
    dup
    invokespecial x <init>:()V
    astore 6
    goto L2
L3
    return
L4
    aload 6
    ldc -655133965 (java.lang.Integer)
    aload 6
    getfield x o:I
    imul
    invokestatic java/lang/Math random:()D
    ldc 1101907701 (java.lang.Integer)
    aload 6
    getfield x h:I
    imul
    aload 6
    getfield x o:I
    ldc -655133965 (java.lang.Integer)
    imul
    isub
    i2d
    dmul
    d2i
    iadd
    ldc 675723943 (java.lang.Integer)
    imul
    putfield x j:I
    goto L3
L5
    aload 6
    iload 1
    ldc 1230068608 (java.lang.Integer)
    imul
    putfield x l:I
    goto L6
L7
    aload 3
    getfield ag z:I
    ldc 1527764841 (java.lang.Integer)
    imul
    istore 7
L8
    aload 3
    getfield ag y:I
    ldc -1050702509 (java.lang.Integer)
    imul
    istore 8
L9
    iconst_1
    iload 4
    if_icmpeq L10
    goto L11
L12
    aload 6
    ldc 277957248 (java.lang.Integer)
    aload 3
    getfield ag ad:I
    imul
    putfield x i:I
    goto L13
L10
    ldc -1050702509 (java.lang.Integer)
    aload 3
    getfield ag y:I
    imul
    istore 7
L14
    aload 3
    getfield ag z:I
    ldc 1527764841 (java.lang.Integer)
    imul
    istore 8
L15
    aload 6
    ldc 1417350272 (java.lang.Integer)
    iload 1
    iload 7
    iadd
    imul
    putfield x u:I
L16
    aload 6
    iload 2
    iload 8
    iadd
    ldc 40074880 (java.lang.Integer)
    imul
    putfield x w:I
L17
    aload 6
    aload 3
    getfield ag ac:I
    ldc 1175319703 (java.lang.Integer)
    imul
    putfield x f:I
    goto L12
L18
    aload 6
    getfield x s:[I
    ifnull L3
    goto L4
L2
    aload 6
    iload 0
    ldc -370119867 (java.lang.Integer)
    imul
    putfield x a:I
    goto L5
L19
    aload 6
    ldc 1518180293 (java.lang.Integer)
    aload 3
    getfield ag az:I
    imul
    putfield x h:I
L20
    aload 6
    aload 3
    getfield ag af:[I
    putfield x s:[I
L21
    aload 3
    getfield ag ak:[I
    ifnull L22
    iload 5
    ldc -156399299 (java.lang.Integer)
    if_icmpne L23
    new java/lang/IllegalStateException
    dup
    invokespecial java/lang/IllegalStateException <init>:()V
    athrow
L13
    aload 6
    aload 3
    getfield ag an:I
    ldc 1466258211 (java.lang.Integer)
    imul
    putfield x o:I
    goto L19
L24
    aload 6
    bipush 22
    invokevirtual x a:(B)V
L22
    getstatic x e:Lgh;
    aload 6
    invokevirtual gh a:(Lgm;)V
    goto L18
L6
    aload 6
    iload 2
    ldc 438109824 (java.lang.Integer)
    imul
    putfield x c:I
    goto L7
L11
    iconst_3
    iload 4
    if_icmpne L15
    goto L10
L23
    aload 6
    aload 3
    putfield x r:Lag;
    goto L24
L25
    new java/lang/StringBuilder
    dup
    invokespecial java/lang/StringBuilder <init>:()V
    ldc "l.l(" (java.lang.String)
    invokevirtual java/lang/StringBuilder append:(Ljava/lang/String;)Ljava/lang/StringBuilder;
    ldc 41 (java.lang.Integer)
    invokevirtual java/lang/StringBuilder append:(C)Ljava/lang/StringBuilder;
    invokevirtual java/lang/StringBuilder toString:()Ljava/lang/String;
    invokestatic k a:(Ljava/lang/Throwable;Ljava/lang/String;)Lee;
    athrow
