m e (IB)Lag;L1
    getstatic ag c:Lgr;
    iload 0
    i2l
    invokevirtual gr e:(J)Lgd;
    checkcast ag
    astore 2
    goto L2
L3
    aload 2
    areturn
L4
    aload 2
    areturn
L5
    getstatic ag a:Lfv;
    bipush 6
    iload 0
    ldc -1852121536 (java.lang.Integer)
    invokevirtual fv l:(III)[B
    astore 3
L6
    new ag
    dup
    invokespecial ag <init>:()V
    astore 2
    goto L7
L2
    aload 2
    ifnull L5
    iload 1
    bipush 88
    if_icmplt L4
    new java/lang/IllegalStateException
    dup
    invokespecial java/lang/IllegalStateException <init>:()V
    athrow
L8
    aconst_null
    aload 3
    if_acmpeq L9
    iload 1
    bipush 88
    if_icmplt L10
    new java/lang/IllegalStateException
    dup
    invokespecial java/lang/IllegalStateException <init>:()V
    athrow
L7
    aload 2
    ldc 427501887 (java.lang.Integer)
    iload 0
    imul
    putfield ag f:I
    goto L8
L11
    aload 2
    getfield ag at:Z
    ifeq L12
    iload 1
    bipush 88
    if_icmplt L13
    new java/lang/IllegalStateException
    dup
    invokespecial java/lang/IllegalStateException <init>:()V
    athrow
L9
    aload 2
    bipush -34
    invokevirtual ag a:(B)V
    goto L11
L13
    aload 2
    iconst_0
    putfield ag q:I
    goto L14
L10
    aload 2
    new dh
    dup
    aload 3
    invokespecial dh <init>:([B)V
    ldc 1725099630 (java.lang.Integer)
    invokevirtual ag l:(Ldh;I)V
    goto L9
L12
    getstatic ag c:Lgr;
    aload 2
    iload 0
    i2l
    invokevirtual gr l:(Lgd;J)V
    goto L3
L14
    aload 2
    iconst_0
    putfield ag d:Z
    goto L12
L15
    new java/lang/StringBuilder
    dup
    invokespecial java/lang/StringBuilder <init>:()V
    ldc "m.e(" (java.lang.String)
    invokevirtual java/lang/StringBuilder append:(Ljava/lang/String;)Ljava/lang/StringBuilder;
    ldc 41 (java.lang.Integer)
    invokevirtual java/lang/StringBuilder append:(C)Ljava/lang/StringBuilder;
    invokevirtual java/lang/StringBuilder toString:()Ljava/lang/String;
    invokestatic k a:(Ljava/lang/Throwable;Ljava/lang/String;)Lee;
    athrow
