n cq ([Lfb;IIIIIIIB)VL1
    iconst_0
    istore 9
    goto L2
L3
    aload 10
    getfield fb o:Z
    ifeq L4
    iload 8
    iconst_0
    if_icmpgt L5
    return
L6
    aload 0
    iload 9
    aaload
    astore 10
    goto L7
L8
    getstatic client ls:Lgh;
    aload 22
    invokevirtual gh a:(Lgm;)V
    goto L9
L10
    goto L11
L12
    goto L13
L14
    aload 10
    ldc -210186597 (java.lang.Integer)
    invokestatic d dl:(Lfb;I)Ljava/lang/String;
    astore 21
    goto L15
L16
    aload 10
    getfield fb ch:Z
    ifne L17
    aload 10
    bipush 60
    invokestatic t dj:(Lfb;B)I
    ifne L17
    iload 8
    iconst_0
    if_icmpgt L18
    new java/lang/IllegalStateException
    dup
    invokespecial java/lang/IllegalStateException <init>:()V
    athrow
L19
    iload 28
    ifeq L20
    goto L21
L22
    goto L11
L17
    iload 1
    ldc 737715635 (java.lang.Integer)
    aload 10
    getfield fb n:I
    imul
    if_icmpeq L23
    iload 8
    iconst_0
    if_icmpgt L24
    new java/lang/IllegalStateException
    dup
    invokespecial java/lang/IllegalStateException <init>:()V
    athrow
L25
    ldc -1286163637 (java.lang.Integer)
    aload 10
    getfield fb z:I
    imul
    iload 6
    iadd
    istore 11
    goto L26
L27
    bipush 36
    istore 29
    goto L28
L29
    aconst_null
    aload 10
    getfield fb bh:[Ljava/lang/String;
    if_acmpeq L30
    goto L31
L32
    goto L11
L33
    aconst_null
    aload 10
    getfield fb cg:[Ljava/lang/Object;
    if_acmpeq L34
    iload 8
    iconst_0
    if_icmpgt L35
    return
L26
    aload 10
    getfield fb q:I
    ldc 1649028313 (java.lang.Integer)
    imul
    iload 7
    iadd
    istore 12
    goto L36
L37
    aload 22
    aload 10
    putfield e l:Lfb;
    goto L38
L39
    iload 2
    istore 13
    goto L40
L41
    aload 22
    iconst_1
    putfield e a:Z
    goto L42
L43
    new e
    dup
    invokespecial e <init>:()V
    astore 22
    goto L44
L45
    aload 22
    ldc -133900669 (java.lang.Integer)
    ldc 1563808941 (java.lang.Integer)
    getstatic ep m:I
    imul
    iload 12
    isub
    imul
    putfield e u:I
    goto L46
L47
    bipush 9
    aload 10
    getfield fb j:I
    ldc -1547422441 (java.lang.Integer)
    imul
    if_icmpne L48
    iload 8
    iconst_0
    if_icmpgt L49
    return
L49
    iload 11
    istore 17
L50
    iload 12
    istore 18
L51
    iload 11
    ldc -606292603 (java.lang.Integer)
    aload 10
    getfield fb b:I
    imul
    iadd
    istore 19
L52
    iload 12
    ldc 891461123 (java.lang.Integer)
    aload 10
    getfield fb x:I
    imul
    iadd
    istore 20
L53
    iload 19
    iload 17
    if_icmpge L54
    iload 8
    iconst_0
    if_icmpgt L55
    return
L55
    iload 17
    istore 21
L56
    iload 19
    istore 17
L57
    iload 21
    istore 19
L54
    iload 20
    iload 18
    if_icmpge L58
L59
    iload 18
    istore 21
    goto L60
L61
    bipush 22
    istore 32
    goto L62
L63
    iload 21
    istore 20
    goto L58
L64
    iload 30
    iconst_4
    if_icmpne L65
    goto L66
L67
    iinc 20 1
    goto L68
L69
    iload 12
    aload 10
    getfield fb x:I
    ldc 891461123 (java.lang.Integer)
    imul
    iadd
    istore 18
    goto L70
L71
    iload 17
    goto L72
L73
    iload 2
L72
    istore 13
L74
    iload 18
    iload 3
    if_icmple L75
    iload 8
    iconst_0
    if_icmpgt L76
    new java/lang/IllegalStateException
    dup
    invokespecial java/lang/IllegalStateException <init>:()V
    athrow
L77
    goto L11
L75
    iload 3
    goto L78
L79
    goto L80
L81
    iconst_0
    istore 21
    goto L82
L83
    iload 19
    goto L84
L85
    iload 4
L84
    istore 15
    goto L86
L87
    goto L88
L89
    iload 20
    goto L90
L91
    aload 22
    aload 10
    putfield e l:Lfb;
    goto L92
L90
    istore 16
    goto L79
L93
    getstatic et eb:Ljava/lang/String;
    new java/lang/StringBuilder
    dup
    invokespecial java/lang/StringBuilder <init>:()V
    ldc 16748608 (java.lang.Integer)
    bipush -124
    invokestatic p e:(IB)Ljava/lang/String;
    invokevirtual java/lang/StringBuilder append:(Ljava/lang/String;)Ljava/lang/StringBuilder;
    aload 29
    getfield ad j:Ljava/lang/String;
    invokevirtual java/lang/StringBuilder append:(Ljava/lang/String;)Ljava/lang/StringBuilder;
    invokevirtual java/lang/StringBuilder toString:()Ljava/lang/String;
    sipush 1004
    aload 28
    getfield ax e:I
    ldc 1019941107 (java.lang.Integer)
    imul
    iload 23
    iload 24
    ldc -1495285549 (java.lang.Integer)
    invokestatic fk bo:(Ljava/lang/String;Ljava/lang/String;IIIII)V
    goto L94
L95
    aload 25
    aload 10
    putfield e l:Lfb;
    goto L96
L97
    aload 19
    getfield e a:Z
    ifeq L98
    iload 8
    iconst_0
    if_icmpgt L99
    return
L70
    iload 11
    iload 2
    if_icmple L100
    iload 8
    iconst_0
    if_icmpgt L101
    new java/lang/IllegalStateException
    dup
    invokespecial java/lang/IllegalStateException <init>:()V
    athrow
L101
    iload 11
    goto L102
L103
    new e
    dup
    invokespecial e <init>:()V
    astore 25
    goto L95
L104
    getstatic ep i:I
    ldc -1976433391 (java.lang.Integer)
    imul
    iload 15
    if_icmpge L105
    iload 8
    iconst_0
    if_icmpgt L106
    return
L107
    iload 12
    iload 3
    if_icmple L108
    iload 8
    iconst_0
    if_icmpgt L109
    new java/lang/IllegalStateException
    dup
    invokespecial java/lang/IllegalStateException <init>:()V
    athrow
L109
    iload 12
    goto L110
L108
    iload 3
    goto L110
L111
    iconst_1
    istore 19
    goto L112
L113
    iload 17
    iload 4
    if_icmpge L114
    iload 8
    iconst_0
    if_icmpgt L115
    return
L115
    iload 17
    goto L116
L114
    iload 4
L116
    istore 15
L117
    iload 18
    iload 5
    if_icmpge L118
    iload 8
    iconst_0
    if_icmpgt L119
    new java/lang/IllegalStateException
    dup
    invokespecial java/lang/IllegalStateException <init>:()V
    athrow
L119
    iload 18
    goto L120
L121
    getstatic client is:Z
    ifeq L122
    iload 8
    iconst_0
    if_icmpgt L123
    new java/lang/IllegalStateException
    dup
    invokespecial java/lang/IllegalStateException <init>:()V
    athrow
L124
    iconst_1
    istore 21
    goto L125
L80
    getstatic client jc:Lfb;
    aload 10
    if_acmpne L3
L126
    iconst_1
    putstatic client kf:Z
    goto L127
L128
    ldc 1164900853 (java.lang.Integer)
    aload 29
    getfield l b:I
    imul
    ldc 1164900853 (java.lang.Integer)
    aload 27
    getfield l b:I
    imul
    if_icmpne L129
    iload 8
    iconst_0
    if_icmpgt L130
    new java/lang/IllegalStateException
    dup
    invokespecial java/lang/IllegalStateException <init>:()V
    athrow
L131
    ldc 1023882891 (java.lang.Integer)
    iload 12
    imul
    putstatic client kw:I
    goto L3
L132
    iinc 30 -1
    goto L133
L5
    iload 13
    iload 15
    if_icmpge L11
    iload 14
    iload 16
    if_icmplt L4
    iload 8
    iconst_0
    if_icmpgt L134
    new java/lang/IllegalStateException
    dup
    invokespecial java/lang/IllegalStateException <init>:()V
    athrow
L134
    goto L11
L4
    ldc -1976433391 (java.lang.Integer)
    getstatic ep i:I
    imul
    istore 17
    goto L135
L136
    getstatic client hg:[Ll;
    getstatic client hw:[I
    iload 28
    iaload
    aaload
    astore 29
    goto L137
L138
    iconst_0
    ldc -1750678861 (java.lang.Integer)
    getstatic ep s:I
    imul
    if_icmpeq L139
    iload 8
    iconst_0
    if_icmpgt L140
    return
L140
    ldc -642165313 (java.lang.Integer)
    getstatic ep j:I
    imul
    istore 17
L141
    getstatic ep m:I
    ldc 1563808941 (java.lang.Integer)
    imul
    istore 18
L139
    sipush 1337
    aload 10
    getfield fb t:I
    ldc 937329469 (java.lang.Integer)
    imul
    if_icmpne L142
    iload 8
    iconst_0
    if_icmpgt L143
    new java/lang/IllegalStateException
    dup
    invokespecial java/lang/IllegalStateException <init>:()V
    athrow
L143
    aload 10
    ldc -1023277750 (java.lang.Integer)
    invokestatic dh cr:(Lfb;I)V
    goto L144
L145
    aload 10
    bipush 36
    invokestatic t dj:(Lfb;B)I
    istore 25
    goto L146
L147
    getstatic client ih:Z
    ifne L11
    iload 8
    iconst_0
    if_icmpgt L148
    new java/lang/IllegalStateException
    dup
    invokespecial java/lang/IllegalStateException <init>:()V
    athrow
L148
    iload 17
    iload 13
    if_icmplt L11
    iload 8
    iconst_0
    if_icmpgt L149
    new java/lang/IllegalStateException
    dup
    invokespecial java/lang/IllegalStateException <init>:()V
    athrow
L150
    getstatic client ls:Lgh;
    aload 22
    invokevirtual gh a:(Lgm;)V
    goto L151
L152
    aload 22
    iconst_1
    putfield e a:Z
    goto L153
L154
    getstatic client ls:Lgh;
    aload 22
    invokevirtual gh a:(Lgm;)V
    goto L155
L156
    ldc -191152561 (java.lang.Integer)
    getstatic client kr:I
    imul
    ldc -307148225 (java.lang.Integer)
    aload 10
    getfield fb dg:I
    imul
    if_icmple L157
    iload 8
    iconst_0
    if_icmpgt L158
    new java/lang/IllegalStateException
    dup
    invokespecial java/lang/IllegalStateException <init>:()V
    athrow
L159
    getstatic client is:Z
    ifne L160
    iload 8
    iconst_0
    if_icmpgt L161
    new java/lang/IllegalStateException
    dup
    invokespecial java/lang/IllegalStateException <init>:()V
    athrow
L161
    getstatic et fp:Ljava/lang/String;
    ldc "" (java.lang.String)
    bipush 23
    iconst_0
    iload 17
    iload 13
    isub
    iload 18
    iload 14
    isub
    ldc -1626607987 (java.lang.Integer)
    invokestatic fk bo:(Ljava/lang/String;Ljava/lang/String;IIIII)V
L160
    iconst_m1
    istore 19
L162
    iconst_m1
    istore 20
    goto L163
L164
    aload 10
    getfield fb dl:Ljava/lang/String;
    ldc "" (java.lang.String)
    bipush 28
    iconst_0
    iconst_0
    ldc 952871887 (java.lang.Integer)
    aload 10
    getfield fb h:I
    imul
    ldc -1796381072 (java.lang.Integer)
    invokestatic fk bo:(Ljava/lang/String;Ljava/lang/String;IIIII)V
    goto L165
L166
    iconst_0
    istore 19
    goto L112
L167
    aload 22
    aload 10
    getfield fb cu:[Ljava/lang/Object;
    putfield e e:[Ljava/lang/Object;
    goto L168
L169
    iload 22
    bipush 127
    iand
    istore 23
L170
    iload 22
    bipush 7
    ishr
    bipush 127
    iand
    istore 24
    goto L171
L21
    getstatic et ev:Ljava/lang/String;
    new java/lang/StringBuilder
    dup
    invokespecial java/lang/StringBuilder <init>:()V
    ldc 16748608 (java.lang.Integer)
    bipush -32
    invokestatic p e:(IB)Ljava/lang/String;
    invokevirtual java/lang/StringBuilder append:(Ljava/lang/String;)Ljava/lang/StringBuilder;
    aload 26
    getfield ad j:Ljava/lang/String;
    invokevirtual java/lang/StringBuilder append:(Ljava/lang/String;)Ljava/lang/StringBuilder;
    invokevirtual java/lang/StringBuilder toString:()Ljava/lang/String;
    bipush 38
    ldc 1822592743 (java.lang.Integer)
    aload 26
    getfield ad h:I
    imul
    iload 21
    aload 10
    getfield fb h:I
    ldc 952871887 (java.lang.Integer)
    imul
    ldc -1510278918 (java.lang.Integer)
    invokestatic fk bo:(Ljava/lang/String;Ljava/lang/String;IIIII)V
    goto L20
L172
    iload 22
    bipush 14
    ishr
    sipush 32767
    iand
    istore 26
L173
    iload 20
    iload 22
    if_icmpne L174
    iload 8
    iconst_0
    if_icmpgt L175
    new java/lang/IllegalStateException
    dup
    invokespecial java/lang/IllegalStateException <init>:()V
    athrow
L176
    iload 30
    iconst_2
    if_icmpne L177
    iload 8
    iconst_0
    if_icmpgt L178
    new java/lang/IllegalStateException
    dup
    invokespecial java/lang/IllegalStateException <init>:()V
    athrow
L179
    iload 18
    iload 12
    isub
    istore 20
    goto L180
L181
    getstatic ep m:I
    ldc 1563808941 (java.lang.Integer)
    imul
    iload 14
    if_icmplt L125
    iload 8
    iconst_0
    if_icmpgt L182
    new java/lang/IllegalStateException
    dup
    invokespecial java/lang/IllegalStateException <init>:()V
    athrow
L183
    iload 22
    aload 10
    getfield fb x:I
    ldc 891461123 (java.lang.Integer)
    imul
    if_icmpge L184
    goto L185
L186
    iload 26
    bipush -72
    invokestatic m e:(IB)Lag;
    astore 27
    goto L187
L188
    aload 10
    iconst_0
    putfield fb da:Z
    goto L33
L189
    iload 5
    istore 16
    goto L80
L190
    aconst_null
    aload 27
    if_acmpne L191
    iload 8
    iconst_0
    if_icmpgt L192
    new java/lang/IllegalStateException
    dup
    invokespecial java/lang/IllegalStateException <init>:()V
    athrow
L192
    goto L193
L191
    getstatic client in:I
    ldc 1293091945 (java.lang.Integer)
    imul
    iconst_1
    if_icmpne L194
L195
    getstatic et ev:Ljava/lang/String;
    new java/lang/StringBuilder
    dup
    invokespecial java/lang/StringBuilder <init>:()V
    getstatic client it:Ljava/lang/String;
    invokevirtual java/lang/StringBuilder append:(Ljava/lang/String;)Ljava/lang/StringBuilder;
    ldc " " (java.lang.String)
    invokevirtual java/lang/StringBuilder append:(Ljava/lang/String;)Ljava/lang/StringBuilder;
    getstatic a w:Ljava/lang/String;
    invokevirtual java/lang/StringBuilder append:(Ljava/lang/String;)Ljava/lang/StringBuilder;
    ldc " " (java.lang.String)
    invokevirtual java/lang/StringBuilder append:(Ljava/lang/String;)Ljava/lang/StringBuilder;
    ldc 65535 (java.lang.Integer)
    bipush -49
    invokestatic p e:(IB)Ljava/lang/String;
    invokevirtual java/lang/StringBuilder append:(Ljava/lang/String;)Ljava/lang/StringBuilder;
    aload 27
    getfield ag h:Ljava/lang/String;
    invokevirtual java/lang/StringBuilder append:(Ljava/lang/String;)Ljava/lang/StringBuilder;
    invokevirtual java/lang/StringBuilder toString:()Ljava/lang/String;
    iconst_1
    iload 22
    iload 23
    iload 24
    ldc -2028971365 (java.lang.Integer)
    invokestatic fk bo:(Ljava/lang/String;Ljava/lang/String;IIIII)V
    goto L196
L197
    aload 27
    invokevirtual gh r:()Lgm;
    checkcast ax
    astore 28
    goto L198
L199
    getstatic da jj:I
    ldc -448064051 (java.lang.Integer)
    imul
    iconst_4
    iand
    iconst_4
    if_icmpne L196
    iload 8
    iconst_0
    if_icmpgt L200
    new java/lang/IllegalStateException
    dup
    invokespecial java/lang/IllegalStateException <init>:()V
    athrow
L200
    getstatic client jf:Ljava/lang/String;
    new java/lang/StringBuilder
    dup
    invokespecial java/lang/StringBuilder <init>:()V
    getstatic client jk:Ljava/lang/String;
    invokevirtual java/lang/StringBuilder append:(Ljava/lang/String;)Ljava/lang/StringBuilder;
    ldc " " (java.lang.String)
    invokevirtual java/lang/StringBuilder append:(Ljava/lang/String;)Ljava/lang/StringBuilder;
    getstatic a w:Ljava/lang/String;
    invokevirtual java/lang/StringBuilder append:(Ljava/lang/String;)Ljava/lang/StringBuilder;
    ldc " " (java.lang.String)
    invokevirtual java/lang/StringBuilder append:(Ljava/lang/String;)Ljava/lang/StringBuilder;
    ldc 65535 (java.lang.Integer)
    bipush -73
    invokestatic p e:(IB)Ljava/lang/String;
    invokevirtual java/lang/StringBuilder append:(Ljava/lang/String;)Ljava/lang/StringBuilder;
    aload 27
    getfield ag h:Ljava/lang/String;
    invokevirtual java/lang/StringBuilder append:(Ljava/lang/String;)Ljava/lang/StringBuilder;
    invokevirtual java/lang/StringBuilder toString:()Ljava/lang/String;
    iconst_2
    iload 22
    iload 23
    iload 24
    ldc -2068787379 (java.lang.Integer)
    invokestatic fk bo:(Ljava/lang/String;Ljava/lang/String;IIIII)V
    goto L196
L201
    iload 22
    iload 19
    iload 24
    isub
    if_icmplt L11
    iload 8
    iconst_0
    if_icmpgt L202
    new java/lang/IllegalStateException
    dup
    invokespecial java/lang/IllegalStateException <init>:()V
    athrow
L203
    getstatic client ju:Z
    ifeq L204
    iload 8
    iconst_0
    if_icmpgt L205
    new java/lang/IllegalStateException
    dup
    invokespecial java/lang/IllegalStateException <init>:()V
    athrow
L184
    aload 10
    getfield fb o:Z
    ifeq L206
    iload 8
    iconst_0
    if_icmpgt L207
    new java/lang/IllegalStateException
    dup
    invokespecial java/lang/IllegalStateException <init>:()V
    athrow
L208
    getstatic ep r:I
    ldc -1616406211 (java.lang.Integer)
    imul
    iload 14
    if_icmplt L209
    iload 8
    iconst_0
    if_icmpgt L210
    new java/lang/IllegalStateException
    dup
    invokespecial java/lang/IllegalStateException <init>:()V
    athrow
L211
    iconst_4
    istore 29
    goto L212
L213
    iconst_1
    iload 29
    if_icmpne L214
    iload 8
    iconst_0
    if_icmpgt L215
    new java/lang/IllegalStateException
    dup
    invokespecial java/lang/IllegalStateException <init>:()V
    athrow
L216
    aload 28
    iload 29
    aaload
    ifnull L217
    iload 8
    iconst_0
    if_icmpgt L218
    new java/lang/IllegalStateException
    dup
    invokespecial java/lang/IllegalStateException <init>:()V
    athrow
L219
    aload 10
    getfield fb bi:[Ljava/lang/String;
    astore 27
    goto L220
L221
    iload 18
    iload 14
    if_icmplt L206
    goto L222
L223
    iconst_3
    istore 30
    goto L213
L224
    iinc 22 1
    goto L183
L215
    iconst_4
    istore 30
L214
    iload 29
    iconst_2
    if_icmpne L225
    iload 8
    iconst_0
    if_icmpgt L226
    new java/lang/IllegalStateException
    dup
    invokespecial java/lang/IllegalStateException <init>:()V
    athrow
L226
    iconst_5
    istore 30
L225
    iload 29
    iconst_3
    if_icmpne L227
    goto L228
L229
    iload 22
    ldc 1947199569 (java.lang.Integer)
    getstatic client kh:I
    imul
    if_icmpge L230
    iload 8
    iconst_0
    if_icmpgt L231
    new java/lang/IllegalStateException
    dup
    invokespecial java/lang/IllegalStateException <init>:()V
    athrow
L227
    iload 29
    iconst_4
    if_icmpne L232
    goto L233
L234
    goto L235
L232
    aload 28
    iload 29
    aaload
    new java/lang/StringBuilder
    dup
    invokespecial java/lang/StringBuilder <init>:()V
    ldc 65535 (java.lang.Integer)
    bipush -88
    invokestatic p e:(IB)Ljava/lang/String;
    invokevirtual java/lang/StringBuilder append:(Ljava/lang/String;)Ljava/lang/StringBuilder;
    aload 27
    getfield ag h:Ljava/lang/String;
    invokevirtual java/lang/StringBuilder append:(Ljava/lang/String;)Ljava/lang/StringBuilder;
    invokevirtual java/lang/StringBuilder toString:()Ljava/lang/String;
    iload 30
    iload 22
    iload 23
    iload 24
    ldc -1291351416 (java.lang.Integer)
    invokestatic fk bo:(Ljava/lang/String;Ljava/lang/String;IIIII)V
    goto L217
L236
    iconst_1
    getstatic ep w:I
    ldc 945615415 (java.lang.Integer)
    imul
    if_icmpeq L237
    iload 8
    iconst_0
    if_icmpgt L238
    new java/lang/IllegalStateException
    dup
    invokespecial java/lang/IllegalStateException <init>:()V
    athrow
L239
    getstatic et eb:Ljava/lang/String;
    new java/lang/StringBuilder
    dup
    invokespecial java/lang/StringBuilder <init>:()V
    ldc 65535 (java.lang.Integer)
    bipush -72
    invokestatic p e:(IB)Ljava/lang/String;
    invokevirtual java/lang/StringBuilder append:(Ljava/lang/String;)Ljava/lang/StringBuilder;
    aload 27
    getfield ag h:Ljava/lang/String;
    invokevirtual java/lang/StringBuilder append:(Ljava/lang/String;)Ljava/lang/StringBuilder;
    invokevirtual java/lang/StringBuilder toString:()Ljava/lang/String;
    sipush 1002
    aload 27
    getfield ag f:I
    ldc -840218945 (java.lang.Integer)
    imul
    bipush 14
    ishl
    iload 23
    iload 24
    ldc -1299079212 (java.lang.Integer)
    invokestatic fk bo:(Ljava/lang/String;Ljava/lang/String;IIIII)V
L196
    iconst_1
    iload 25
    if_icmpne L240
    iload 8
    iconst_0
    if_icmpgt L241
    new java/lang/IllegalStateException
    dup
    invokespecial java/lang/IllegalStateException <init>:()V
    athrow
L241
    getstatic client cf:[Lam;
    iload 26
    aaload
    astore 27
L242
    aconst_null
    aload 27
    if_acmpne L243
    iload 8
    iconst_0
    if_icmpgt L244
    return
L244
    goto L193
L243
    ldc 1705445099 (java.lang.Integer)
    aload 27
    getfield am e:Lay;
    getfield ay i:I
    imul
    iconst_1
    if_icmpne L245
    iload 8
    iconst_0
    if_icmpgt L246
    return
L246
    aload 27
    getfield am b:I
    ldc 1164900853 (java.lang.Integer)
    imul
    bipush 127
    iand
    bipush 64
    if_icmpne L245
    iload 8
    iconst_0
    if_icmpgt L247
    new java/lang/IllegalStateException
    dup
    invokespecial java/lang/IllegalStateException <init>:()V
    athrow
L247
    bipush 64
    ldc 109190397 (java.lang.Integer)
    aload 27
    getfield am x:I
    imul
    bipush 127
    iand
    if_icmpne L245
    iload 8
    iconst_0
    if_icmpgt L248
    new java/lang/IllegalStateException
    dup
    invokespecial java/lang/IllegalStateException <init>:()V
    athrow
L249
    aload 27
    getfield am x:I
    ldc 109190397 (java.lang.Integer)
    imul
    aload 29
    getfield l x:I
    ldc 109190397 (java.lang.Integer)
    imul
    if_icmpne L250
    goto L251
L252
    iload 28
    getstatic client ch:I
    ldc -1048248787 (java.lang.Integer)
    imul
    if_icmpge L253
    iload 8
    iconst_0
    if_icmpgt L254
    return
L254
    getstatic client cf:[Lam;
    getstatic client cb:[I
    iload 28
    iaload
    aaload
    astore 29
    goto L255
L256
    aload 10
    getfield fb bh:[Ljava/lang/String;
    arraylength
    iload 22
    if_icmple L257
    iload 8
    iconst_0
    if_icmpgt L258
    new java/lang/IllegalStateException
    dup
    invokespecial java/lang/IllegalStateException <init>:()V
    athrow
L259
    getstatic n ds:Lcb;
    getstatic fd hz:I
    ldc -837647185 (java.lang.Integer)
    imul
    iload 23
    iload 24
    iload 22
    invokevirtual cb aw:(IIII)I
    iflt L196
    iload 8
    iconst_0
    if_icmpgt L186
    new java/lang/IllegalStateException
    dup
    invokespecial java/lang/IllegalStateException <init>:()V
    athrow
L260
    iinc 24 1
    goto L261
L262
    iload 20
    iload 25
    if_icmplt L263
    goto L264
L265
    aload 29
    getfield am x:I
    ldc 109190397 (java.lang.Integer)
    imul
    ldc 109190397 (java.lang.Integer)
    aload 27
    getfield am x:I
    imul
    if_icmpne L266
    iload 8
    iconst_0
    if_icmpgt L267
    new java/lang/IllegalStateException
    dup
    invokespecial java/lang/IllegalStateException <init>:()V
    athrow
L267
    aload 29
    getfield am e:Lay;
    getstatic client cb:[I
    iload 28
    iaload
    iload 23
    iload 24
    ldc 504071109 (java.lang.Integer)
    invokestatic x ch:(Lay;IIII)V
L266
    iinc 28 1
    goto L252
L268
    new e
    dup
    invokespecial e <init>:()V
    astore 22
    goto L269
L270
    iload 28
    ldc 308668811 (java.lang.Integer)
    getstatic client hr:I
    imul
    if_icmpge L245
    iload 8
    iconst_0
    if_icmpgt L271
    new java/lang/IllegalStateException
    dup
    invokespecial java/lang/IllegalStateException <init>:()V
    athrow
L271
    getstatic client hg:[Ll;
    getstatic client hw:[I
    iload 28
    iaload
    aaload
    astore 29
    goto L272
L273
    aload 27
    ldc -1919657677 (java.lang.Integer)
    invokestatic dj cl:([Ljava/lang/String;I)[Ljava/lang/String;
    astore 27
    goto L274
L275
    aload 27
    getfield am b:I
    ldc 1164900853 (java.lang.Integer)
    imul
    aload 29
    getfield l b:I
    ldc 1164900853 (java.lang.Integer)
    imul
    if_icmpne L250
    iload 8
    iconst_0
    if_icmpgt L249
    new java/lang/IllegalStateException
    dup
    invokespecial java/lang/IllegalStateException <init>:()V
    athrow
L18
    getstatic client jm:Lfb;
    aload 10
    if_acmpeq L17
    iload 8
    iconst_0
    if_icmpgt L22
    new java/lang/IllegalStateException
    dup
    invokespecial java/lang/IllegalStateException <init>:()V
    athrow
L251
    aload 29
    getstatic client hw:[I
    iload 28
    iaload
    iload 23
    iload 24
    ldc 1001507113 (java.lang.Integer)
    invokestatic di cb:(Ll;IIII)V
L250
    iinc 28 1
    goto L270
L276
    getstatic client ju:Z
    ifeq L277
    iload 8
    iconst_0
    if_icmpgt L278
    new java/lang/IllegalStateException
    dup
    invokespecial java/lang/IllegalStateException <init>:()V
    athrow
L240
    iconst_0
    iload 25
    if_icmpne L279
    iload 8
    iconst_0
    if_icmpgt L280
    new java/lang/IllegalStateException
    dup
    invokespecial java/lang/IllegalStateException <init>:()V
    athrow
L280
    getstatic client hg:[Ll;
    iload 26
    aaload
    astore 27
    goto L281
L282
    iload 19
    iload 4
    if_icmpge L85
    iload 8
    iconst_0
    if_icmpgt L83
    new java/lang/IllegalStateException
    dup
    invokespecial java/lang/IllegalStateException <init>:()V
    athrow
L283
    aload 22
    aload 10
    putfield e l:Lfb;
    goto L284
L285
    aload 27
    getfield l b:I
    ldc 1164900853 (java.lang.Integer)
    imul
    bipush 127
    iand
    bipush 64
    if_icmpne L286
    bipush 64
    ldc 109190397 (java.lang.Integer)
    aload 27
    getfield l x:I
    imul
    bipush 127
    iand
    if_icmpne L286
    goto L287
L288
    iload 23
    ifne L29
    goto L289
L290
    aconst_null
    aload 10
    getfield fb dk:[Ljava/lang/Object;
    if_acmpeq L155
    iload 8
    iconst_0
    if_icmpgt L291
    new java/lang/IllegalStateException
    dup
    invokespecial java/lang/IllegalStateException <init>:()V
    athrow
L292
    getstatic client kt:I
    ldc 631780777 (java.lang.Integer)
    imul
    aload 10
    getfield fb dg:I
    ldc -307148225 (java.lang.Integer)
    imul
    if_icmple L156
    iload 8
    iconst_0
    if_icmpgt L293
    return
L294
    aload 29
    ifnull L295
    iload 8
    iconst_0
    if_icmpgt L296
    new java/lang/IllegalStateException
    dup
    invokespecial java/lang/IllegalStateException <init>:()V
    athrow
L297
    iload 20
    bipush 32
    isub
    iload 20
    imul
    iload 21
    idiv
    istore 24
    goto L298
L158
    aconst_null
    aload 10
    getfield fb dd:[Ljava/lang/Object;
    if_acmpeq L157
    iload 8
    iconst_0
    if_icmpgt L299
    new java/lang/IllegalStateException
    dup
    invokespecial java/lang/IllegalStateException <init>:()V
    athrow
L300
    ldc 109190397 (java.lang.Integer)
    aload 27
    getfield l x:I
    imul
    aload 29
    getfield am x:I
    ldc 109190397 (java.lang.Integer)
    imul
    if_icmpne L295
    iload 8
    iconst_0
    if_icmpgt L301
    return
L301
    aload 29
    getfield am e:Lay;
    getstatic client cb:[I
    iload 28
    iaload
    iload 23
    iload 24
    ldc 1087897305 (java.lang.Integer)
    invokestatic x ch:(Lay;IIII)V
L295
    iinc 28 1
    goto L302
L303
    iconst_0
    istore 28
    goto L304
L305
    iload 22
    iload 19
    getstatic client fu:I
    ldc 1475049201 (java.lang.Integer)
    imul
    isub
    if_icmplt L306
    iload 8
    iconst_0
    if_icmpgt L307
    new java/lang/IllegalStateException
    dup
    invokespecial java/lang/IllegalStateException <init>:()V
    athrow
L308
    iload 28
    iconst_4
    if_icmpne L309
    iload 8
    iconst_0
    if_icmpgt L310
    new java/lang/IllegalStateException
    dup
    invokespecial java/lang/IllegalStateException <init>:()V
    athrow
L137
    aconst_null
    aload 29
    if_acmpeq L129
    iload 8
    iconst_0
    if_icmpgt L311
    return
L311
    aload 27
    aload 29
    if_acmpeq L129
    iload 8
    iconst_0
    if_icmpgt L128
    new java/lang/IllegalStateException
    dup
    invokespecial java/lang/IllegalStateException <init>:()V
    athrow
L312
    ldc 1164900853 (java.lang.Integer)
    aload 27
    getfield l b:I
    imul
    aload 29
    getfield am b:I
    ldc 1164900853 (java.lang.Integer)
    imul
    if_icmpne L295
    goto L300
L313
    aload 10
    bipush 37
    invokestatic t dj:(Lfb;B)I
    bipush 35
    invokestatic cu w:(IB)Z
    ifeq L314
    iload 8
    iconst_0
    if_icmpgt L315
    new java/lang/IllegalStateException
    dup
    invokespecial java/lang/IllegalStateException <init>:()V
    athrow
L316
    iload 30
    iflt L317
    iload 8
    iconst_0
    if_icmpgt L318
    new java/lang/IllegalStateException
    dup
    invokespecial java/lang/IllegalStateException <init>:()V
    athrow
L129
    iinc 28 1
    goto L304
L286
    iload 26
    ldc 7317091 (java.lang.Integer)
    getstatic client hd:I
    imul
    if_icmpeq L319
    iload 8
    iconst_0
    if_icmpgt L320
    new java/lang/IllegalStateException
    dup
    invokespecial java/lang/IllegalStateException <init>:()V
    athrow
L320
    aload 27
    iload 26
    iload 23
    iload 24
    ldc 1404125809 (java.lang.Integer)
    invokestatic di cb:(Ll;IIII)V
    goto L279
L321
    aload 10
    ldc -1330569311 (java.lang.Integer)
    invokestatic ar dt:(Lfb;I)Z
    ifeq L322
    iload 8
    iconst_0
    if_icmpgt L323
    new java/lang/IllegalStateException
    dup
    invokespecial java/lang/IllegalStateException <init>:()V
    athrow
L279
    iload 25
    iconst_3
    if_icmpne L193
    iload 8
    iconst_0
    if_icmpgt L324
    new java/lang/IllegalStateException
    dup
    invokespecial java/lang/IllegalStateException <init>:()V
    athrow
L324
    getstatic client hx:[[[Lgh;
    getstatic fd hz:I
    ldc -837647185 (java.lang.Integer)
    imul
    aaload
    iload 23
    aaload
    iload 24
    aaload
    astore 27
L325
    aload 27
    ifnull L193
    goto L197
L326
    aload 10
    getfield fb dw:[Ljava/lang/Object;
    ifnull L327
    iload 8
    iconst_0
    if_icmpgt L328
    new java/lang/IllegalStateException
    dup
    invokespecial java/lang/IllegalStateException <init>:()V
    athrow
L198
    aload 28
    ifnull L193
    iload 8
    iconst_0
    if_icmpgt L329
    return
L330
    aload 10
    getfield fb ck:[I
    ifnull L331
    iload 8
    iconst_0
    if_icmpgt L332
    new java/lang/IllegalStateException
    dup
    invokespecial java/lang/IllegalStateException <init>:()V
    athrow
L333
    iconst_1
    ldc 1293091945 (java.lang.Integer)
    getstatic client in:I
    imul
    if_icmpne L121
    iload 8
    iconst_0
    if_icmpgt L334
    new java/lang/IllegalStateException
    dup
    invokespecial java/lang/IllegalStateException <init>:()V
    athrow
L28
    aload 27
    iload 28
    aaload
    new java/lang/StringBuilder
    dup
    invokespecial java/lang/StringBuilder <init>:()V
    ldc 16748608 (java.lang.Integer)
    bipush -108
    invokestatic p e:(IB)Ljava/lang/String;
    invokevirtual java/lang/StringBuilder append:(Ljava/lang/String;)Ljava/lang/StringBuilder;
    aload 26
    getfield ad j:Ljava/lang/String;
    invokevirtual java/lang/StringBuilder append:(Ljava/lang/String;)Ljava/lang/StringBuilder;
    invokevirtual java/lang/StringBuilder toString:()Ljava/lang/String;
    iload 29
    aload 26
    getfield ad h:I
    ldc 1822592743 (java.lang.Integer)
    imul
    iload 21
    ldc 952871887 (java.lang.Integer)
    aload 10
    getfield fb h:I
    imul
    ldc -1701117687 (java.lang.Integer)
    invokestatic fk bo:(Ljava/lang/String;Ljava/lang/String;IIIII)V
    goto L335
L336
    iconst_3
    iload 31
    if_icmpne L337
    iload 8
    iconst_0
    if_icmpgt L338
    new java/lang/IllegalStateException
    dup
    invokespecial java/lang/IllegalStateException <init>:()V
    athrow
L123
    ldc -448064051 (java.lang.Integer)
    getstatic da jj:I
    imul
    iconst_1
    iand
    iconst_1
    if_icmpne L94
    iload 8
    iconst_0
    if_icmpgt L339
    new java/lang/IllegalStateException
    dup
    invokespecial java/lang/IllegalStateException <init>:()V
    athrow
L339
    getstatic client jf:Ljava/lang/String;
    new java/lang/StringBuilder
    dup
    invokespecial java/lang/StringBuilder <init>:()V
    getstatic client jk:Ljava/lang/String;
    invokevirtual java/lang/StringBuilder append:(Ljava/lang/String;)Ljava/lang/StringBuilder;
    ldc " " (java.lang.String)
    invokevirtual java/lang/StringBuilder append:(Ljava/lang/String;)Ljava/lang/StringBuilder;
    getstatic a w:Ljava/lang/String;
    invokevirtual java/lang/StringBuilder append:(Ljava/lang/String;)Ljava/lang/StringBuilder;
    ldc " " (java.lang.String)
    invokevirtual java/lang/StringBuilder append:(Ljava/lang/String;)Ljava/lang/StringBuilder;
    ldc 16748608 (java.lang.Integer)
    bipush -28
    invokestatic p e:(IB)Ljava/lang/String;
    invokevirtual java/lang/StringBuilder append:(Ljava/lang/String;)Ljava/lang/StringBuilder;
    aload 29
    getfield ad j:Ljava/lang/String;
    invokevirtual java/lang/StringBuilder append:(Ljava/lang/String;)Ljava/lang/StringBuilder;
    invokevirtual java/lang/StringBuilder toString:()Ljava/lang/String;
    bipush 17
    ldc 1019941107 (java.lang.Integer)
    aload 28
    getfield ax e:I
    imul
    iload 23
    iload 24
    ldc -1853747666 (java.lang.Integer)
    invokestatic fk bo:(Ljava/lang/String;Ljava/lang/String;IIIII)V
    goto L94
L340
    getstatic da jj:I
    ldc -448064051 (java.lang.Integer)
    imul
    bipush 16
    iand
    bipush 16
    if_icmpne L263
    iload 8
    iconst_0
    if_icmpgt L341
    return
L342
    iload 5
    goto L90
L278
    aload 30
    ldc -1478580660 (java.lang.Integer)
    invokestatic dj cl:([Ljava/lang/String;I)[Ljava/lang/String;
    astore 30
    goto L277
L30
    aconst_null
    astore 22
    goto L343
L344
    iload 31
    iflt L93
L345
    aconst_null
    aload 30
    if_acmpeq L346
    iload 8
    iconst_0
    if_icmpgt L347
    new java/lang/IllegalStateException
    dup
    invokespecial java/lang/IllegalStateException <init>:()V
    athrow
L347
    aload 30
    iload 31
    aaload
    ifnull L346
    iload 8
    iconst_0
    if_icmpgt L348
    new java/lang/IllegalStateException
    dup
    invokespecial java/lang/IllegalStateException <init>:()V
    athrow
L348
    iconst_0
    istore 32
    goto L349
L350
    getstatic client hg:[Ll;
    getstatic client hd:I
    ldc 7317091 (java.lang.Integer)
    imul
    aaload
    astore 23
    goto L351
L352
    bipush 18
    istore 32
L353
    iload 31
    iconst_1
    if_icmpne L354
    goto L355
L356
    getstatic ep r:I
    ldc -1616406211 (java.lang.Integer)
    imul
    iload 14
    if_icmplt L105
    iload 8
    iconst_0
    if_icmpgt L104
    new java/lang/IllegalStateException
    dup
    invokespecial java/lang/IllegalStateException <init>:()V
    athrow
L354
    iload 31
    iconst_2
    if_icmpne L336
    iload 8
    iconst_0
    if_icmpgt L357
    return
L357
    bipush 20
    istore 32
    goto L336
L287
    iconst_0
    istore 28
    goto L302
L358
    bipush 40
    istore 31
    goto L176
L359
    ldc 1164900853 (java.lang.Integer)
    aload 27
    getfield am b:I
    imul
    aload 29
    getfield am b:I
    ldc 1164900853 (java.lang.Integer)
    imul
    if_icmpne L266
    iload 8
    iconst_0
    if_icmpgt L265
    new java/lang/IllegalStateException
    dup
    invokespecial java/lang/IllegalStateException <init>:()V
    athrow
L360
    iconst_0
    goto L361
L62
    aload 30
    iload 31
    aaload
    new java/lang/StringBuilder
    dup
    invokespecial java/lang/StringBuilder <init>:()V
    ldc 16748608 (java.lang.Integer)
    bipush -5
    invokestatic p e:(IB)Ljava/lang/String;
    invokevirtual java/lang/StringBuilder append:(Ljava/lang/String;)Ljava/lang/StringBuilder;
    aload 29
    getfield ad j:Ljava/lang/String;
    invokevirtual java/lang/StringBuilder append:(Ljava/lang/String;)Ljava/lang/StringBuilder;
    invokevirtual java/lang/StringBuilder toString:()Ljava/lang/String;
    iload 32
    aload 28
    getfield ax e:I
    ldc 1019941107 (java.lang.Integer)
    imul
    iload 23
    iload 24
    ldc -1540006728 (java.lang.Integer)
    invokestatic fk bo:(Ljava/lang/String;Ljava/lang/String;IIIII)V
L362
    goto L363
L174
    iload 22
    istore 20
    goto L364
L365
    getstatic et a:Ljava/lang/String;
    new java/lang/StringBuilder
    dup
    invokespecial java/lang/StringBuilder <init>:()V
    ldc 16748608 (java.lang.Integer)
    bipush -88
    invokestatic p e:(IB)Ljava/lang/String;
    invokevirtual java/lang/StringBuilder append:(Ljava/lang/String;)Ljava/lang/StringBuilder;
    aload 29
    getfield ad j:Ljava/lang/String;
    invokevirtual java/lang/StringBuilder append:(Ljava/lang/String;)Ljava/lang/StringBuilder;
    invokevirtual java/lang/StringBuilder toString:()Ljava/lang/String;
    bipush 20
    aload 28
    getfield ax e:I
    ldc 1019941107 (java.lang.Integer)
    imul
    iload 23
    iload 24
    ldc -1916526525 (java.lang.Integer)
    invokestatic fk bo:(Ljava/lang/String;Ljava/lang/String;IIIII)V
    goto L363
L130
    aload 27
    getfield l x:I
    ldc 109190397 (java.lang.Integer)
    imul
    aload 29
    getfield l x:I
    ldc 109190397 (java.lang.Integer)
    imul
    if_icmpne L129
    iload 8
    iconst_0
    if_icmpgt L366
    return
L367
    iconst_0
    putstatic client fo:Z
    goto L368
L369
    goto L193
L370
    goto L198
L24
    goto L11
L371
    iload 19
    iconst_m1
    if_icmpeq L77
    iload 8
    iconst_0
    if_icmpgt L372
    new java/lang/IllegalStateException
    dup
    invokespecial java/lang/IllegalStateException <init>:()V
    athrow
L46
    aload 22
    aload 10
    getfield fb cv:[Ljava/lang/Object;
    putfield e e:[Ljava/lang/Object;
    goto L373
L374
    iload 19
    bipush 7
    ishr
    bipush 127
    iand
    istore 22
    goto L350
L375
    getstatic client ls:Lgh;
    aload 25
    invokevirtual gh a:(Lgm;)V
    goto L376
L351
    aload 23
    ldc 7317091 (java.lang.Integer)
    getstatic client hd:I
    imul
    iload 21
    iload 22
    ldc 1375525500 (java.lang.Integer)
    invokestatic di cb:(Ll;IIII)V
    goto L77
L377
    getstatic client cf:[Lam;
    getstatic client cb:[I
    iload 28
    iaload
    aaload
    astore 29
    goto L294
L142
    sipush 1338
    aload 10
    getfield fb t:I
    ldc 937329469 (java.lang.Integer)
    imul
    if_icmpne L378
    iload 8
    iconst_0
    if_icmpgt L379
    new java/lang/IllegalStateException
    dup
    invokespecial java/lang/IllegalStateException <init>:()V
    athrow
L380
    aload 10
    getfield fb dj:I
    ldc 152781469 (java.lang.Integer)
    imul
    iflt L381
    goto L382
L383
    goto L11
L378
    getstatic client ih:Z
    ifne L206
    iload 8
    iconst_0
    if_icmpgt L384
    new java/lang/IllegalStateException
    dup
    invokespecial java/lang/IllegalStateException <init>:()V
    athrow
L384
    iload 17
    iload 13
    if_icmplt L206
    iload 8
    iconst_0
    if_icmpgt L221
    new java/lang/IllegalStateException
    dup
    invokespecial java/lang/IllegalStateException <init>:()V
    athrow
L385
    aload 27
    ldc -348828741 (java.lang.Integer)
    invokevirtual ag o:(I)Lag;
    astore 27
    goto L190
L40
    iload 3
    istore 14
    goto L386
L387
    iload 18
    iload 16
    if_icmpge L206
    iload 8
    iconst_0
    if_icmpgt L388
    new java/lang/IllegalStateException
    dup
    invokespecial java/lang/IllegalStateException <init>:()V
    athrow
L388
    iload 17
    iload 11
    isub
    istore 19
    goto L179
L76
    iload 18
    goto L78
L180
    iconst_1
    aload 10
    getfield fb m:I
    ldc 1810211167 (java.lang.Integer)
    imul
    if_icmpne L389
    iload 8
    iconst_0
    if_icmpgt L390
    return
L390
    aload 10
    getfield fb dl:Ljava/lang/String;
    ldc "" (java.lang.String)
    bipush 24
    iconst_0
    iconst_0
    aload 10
    getfield fb h:I
    ldc 952871887 (java.lang.Integer)
    imul
    ldc -1891301838 (java.lang.Integer)
    invokestatic fk bo:(Ljava/lang/String;Ljava/lang/String;IIIII)V
L389
    ldc 1810211167 (java.lang.Integer)
    aload 10
    getfield fb m:I
    imul
    iconst_2
    if_icmpne L391
    iload 8
    iconst_0
    if_icmpgt L392
    new java/lang/IllegalStateException
    dup
    invokespecial java/lang/IllegalStateException <init>:()V
    athrow
L393
    aload 23
    aload 10
    getfield fb cz:[Ljava/lang/Object;
    putfield e e:[Ljava/lang/Object;
    goto L394
L187
    aconst_null
    aload 27
    getfield ag ak:[I
    if_acmpeq L190
    iload 8
    iconst_0
    if_icmpgt L385
    new java/lang/IllegalStateException
    dup
    invokespecial java/lang/IllegalStateException <init>:()V
    athrow
L15
    aload 21
    ifnull L391
    iload 8
    iconst_0
    if_icmpgt L395
    new java/lang/IllegalStateException
    dup
    invokespecial java/lang/IllegalStateException <init>:()V
    athrow
L396
    aload 22
    astore 23
    goto L397
L391
    aload 10
    getfield fb m:I
    ldc 1810211167 (java.lang.Integer)
    imul
    iconst_3
    if_icmpne L398
    iload 8
    iconst_0
    if_icmpgt L399
    new java/lang/IllegalStateException
    dup
    invokespecial java/lang/IllegalStateException <init>:()V
    athrow
L399
    getstatic et fj:Ljava/lang/String;
    ldc "" (java.lang.String)
    bipush 26
    iconst_0
    iconst_0
    aload 10
    getfield fb h:I
    ldc 952871887 (java.lang.Integer)
    imul
    ldc -1470453445 (java.lang.Integer)
    invokestatic fk bo:(Ljava/lang/String;Ljava/lang/String;IIIII)V
    goto L398
L228
    bipush 6
    istore 30
    goto L227
L400
    iload 20
    ldc 1928687330 (java.lang.Integer)
    invokestatic df c:(II)Z
    ifne L401
    iload 8
    iconst_0
    if_icmpgt L402
    new java/lang/IllegalStateException
    dup
    invokespecial java/lang/IllegalStateException <init>:()V
    athrow
L165
    iconst_5
    aload 10
    getfield fb m:I
    ldc 1810211167 (java.lang.Integer)
    imul
    if_icmpne L403
    iload 8
    iconst_0
    if_icmpgt L404
    new java/lang/IllegalStateException
    dup
    invokespecial java/lang/IllegalStateException <init>:()V
    athrow
L404
    aload 10
    getfield fb dl:Ljava/lang/String;
    ldc "" (java.lang.String)
    bipush 29
    iconst_0
    iconst_0
    aload 10
    getfield fb h:I
    ldc 952871887 (java.lang.Integer)
    imul
    ldc -1699995143 (java.lang.Integer)
    invokestatic fk bo:(Ljava/lang/String;Ljava/lang/String;IIIII)V
L403
    aload 10
    getfield fb m:I
    ldc 1810211167 (java.lang.Integer)
    imul
    bipush 6
    if_icmpne L405
    getstatic client jz:Lfb;
    ifnonnull L405
    iload 8
    iconst_0
    if_icmpgt L406
    new java/lang/IllegalStateException
    dup
    invokespecial java/lang/IllegalStateException <init>:()V
    athrow
L406
    aload 10
    getfield fb dl:Ljava/lang/String;
    ldc "" (java.lang.String)
    bipush 30
    iconst_0
    iconst_m1
    aload 10
    getfield fb h:I
    ldc 952871887 (java.lang.Integer)
    imul
    ldc -1335002860 (java.lang.Integer)
    invokestatic fk bo:(Ljava/lang/String;Ljava/lang/String;IIIII)V
L405
    aload 10
    getfield fb j:I
    ldc -1547422441 (java.lang.Integer)
    imul
    iconst_2
    if_icmpne L184
    iload 8
    iconst_0
    if_icmpgt L407
    new java/lang/IllegalStateException
    dup
    invokespecial java/lang/IllegalStateException <init>:()V
    athrow
L204
    aconst_null
    aload 28
    if_acmpeq L239
    iload 8
    iconst_0
    if_icmpgt L211
    new java/lang/IllegalStateException
    dup
    invokespecial java/lang/IllegalStateException <init>:()V
    athrow
L408
    iconst_0
    istore 22
    goto L183
L409
    iconst_1
    ldc 1705445099 (java.lang.Integer)
    aload 29
    getfield am e:Lay;
    getfield ay i:I
    imul
    if_icmpne L266
    iload 8
    iconst_0
    if_icmpgt L359
    return
L410
    iload 19
    iload 24
    if_icmplt L263
    iload 8
    iconst_0
    if_icmpgt L262
    new java/lang/IllegalStateException
    dup
    invokespecial java/lang/IllegalStateException <init>:()V
    athrow
L411
    iload 23
    aload 10
    getfield fb b:I
    ldc -606292603 (java.lang.Integer)
    imul
    if_icmpge L224
    iload 8
    iconst_0
    if_icmpgt L412
    new java/lang/IllegalStateException
    dup
    invokespecial java/lang/IllegalStateException <init>:()V
    athrow
L135
    ldc -1616406211 (java.lang.Integer)
    getstatic ep r:I
    imul
    istore 18
    goto L138
L413
    iload 22
    aload 10
    getfield fb bb:I
    ldc 1346964537 (java.lang.Integer)
    imul
    bipush 32
    iadd
    imul
    istore 25
    goto L414
L327
    ldc -1755448163 (java.lang.Integer)
    getstatic client ka:I
    imul
    aload 10
    getfield fb dg:I
    ldc -307148225 (java.lang.Integer)
    imul
    if_icmple L155
    iload 8
    iconst_0
    if_icmpgt L290
    return
L415
    iload 24
    aload 10
    getfield fb bj:[I
    iload 21
    iaload
    iadd
    istore 24
    goto L416
L395
    aload 21
    new java/lang/StringBuilder
    dup
    invokespecial java/lang/StringBuilder <init>:()V
    ldc 65280 (java.lang.Integer)
    bipush -81
    invokestatic p e:(IB)Ljava/lang/String;
    invokevirtual java/lang/StringBuilder append:(Ljava/lang/String;)Ljava/lang/StringBuilder;
    aload 10
    getfield fb dt:Ljava/lang/String;
    invokevirtual java/lang/StringBuilder append:(Ljava/lang/String;)Ljava/lang/StringBuilder;
    invokevirtual java/lang/StringBuilder toString:()Ljava/lang/String;
    bipush 25
    iconst_0
    iconst_m1
    ldc 952871887 (java.lang.Integer)
    aload 10
    getfield fb h:I
    imul
    ldc -1233737674 (java.lang.Integer)
    invokestatic fk bo:(Ljava/lang/String;Ljava/lang/String;IIIII)V
    goto L391
L417
    aconst_null
    aload 10
    getfield fb cc:[Ljava/lang/Object;
    if_acmpeq L418
    goto L419
L209
    getstatic ep i:I
    ldc -1976433391 (java.lang.Integer)
    imul
    iload 13
    if_icmplt L166
    iload 8
    iconst_0
    if_icmpgt L420
    new java/lang/IllegalStateException
    dup
    invokespecial java/lang/IllegalStateException <init>:()V
    athrow
L264
    iload 19
    iload 24
    bipush 32
    iadd
    if_icmpge L263
    iload 8
    iconst_0
    if_icmpgt L421
    new java/lang/IllegalStateException
    dup
    invokespecial java/lang/IllegalStateException <init>:()V
    athrow
L421
    iload 20
    bipush 32
    iload 25
    iadd
    if_icmpge L263
    iload 8
    iconst_0
    if_icmpgt L422
    new java/lang/IllegalStateException
    dup
    invokespecial java/lang/IllegalStateException <init>:()V
    athrow
L422
    iload 21
    ldc 1635233123 (java.lang.Integer)
    imul
    putstatic client gb:I
    goto L423
L424
    aload 22
    aload 10
    putfield e l:Lfb;
    goto L425
L426
    getstatic ep i:I
    ldc -1976433391 (java.lang.Integer)
    imul
    iload 13
    if_icmplt L105
    goto L356
L427
    aload 10
    getfield fb dv:[I
    iload 21
    iaload
    iconst_1
    isub
    bipush 66
    invokestatic dj e:(IB)Lad;
    astore 26
L428
    ldc 1293091945 (java.lang.Integer)
    getstatic client in:I
    imul
    iconst_1
    if_icmpne L314
    goto L313
L429
    iload 19
    ifeq L430
    iload 8
    iconst_0
    if_icmpgt L431
    new java/lang/IllegalStateException
    dup
    invokespecial java/lang/IllegalStateException <init>:()V
    athrow
L315
    ldc 952871887 (java.lang.Integer)
    aload 10
    getfield fb h:I
    imul
    getstatic aj ix:I
    ldc 1565981493 (java.lang.Integer)
    imul
    if_icmpne L432
    goto L433
L434
    iload 19
    ifeq L435
    iload 8
    iconst_0
    if_icmpgt L436
    new java/lang/IllegalStateException
    dup
    invokespecial java/lang/IllegalStateException <init>:()V
    athrow
L432
    getstatic et ev:Ljava/lang/String;
    new java/lang/StringBuilder
    dup
    invokespecial java/lang/StringBuilder <init>:()V
    getstatic client it:Ljava/lang/String;
    invokevirtual java/lang/StringBuilder append:(Ljava/lang/String;)Ljava/lang/StringBuilder;
    ldc " " (java.lang.String)
    invokevirtual java/lang/StringBuilder append:(Ljava/lang/String;)Ljava/lang/StringBuilder;
    getstatic a w:Ljava/lang/String;
    invokevirtual java/lang/StringBuilder append:(Ljava/lang/String;)Ljava/lang/StringBuilder;
    ldc " " (java.lang.String)
    invokevirtual java/lang/StringBuilder append:(Ljava/lang/String;)Ljava/lang/StringBuilder;
    ldc 16748608 (java.lang.Integer)
    bipush -69
    invokestatic p e:(IB)Ljava/lang/String;
    invokevirtual java/lang/StringBuilder append:(Ljava/lang/String;)Ljava/lang/StringBuilder;
    aload 26
    getfield ad j:Ljava/lang/String;
    invokevirtual java/lang/StringBuilder append:(Ljava/lang/String;)Ljava/lang/StringBuilder;
    invokevirtual java/lang/StringBuilder toString:()Ljava/lang/String;
    bipush 31
    ldc 1822592743 (java.lang.Integer)
    aload 26
    getfield ad h:I
    imul
    iload 21
    aload 10
    getfield fb h:I
    ldc 952871887 (java.lang.Integer)
    imul
    ldc -1976987128 (java.lang.Integer)
    invokestatic fk bo:(Ljava/lang/String;Ljava/lang/String;IIIII)V
    goto L263
L437
    aload 10
    ldc -210186597 (java.lang.Integer)
    invokestatic d dl:(Lfb;I)Ljava/lang/String;
    astore 21
    goto L438
L439
    aload 10
    bipush 35
    invokestatic t dj:(Lfb;B)I
    bipush -78
    invokestatic cu w:(IB)Z
    ifeq L440
    goto L340
L441
    iload 23
    aload 10
    getfield fb co:[I
    iload 24
    iaload
    if_icmpne L442
    iload 8
    iconst_0
    if_icmpgt L103
    new java/lang/IllegalStateException
    dup
    invokespecial java/lang/IllegalStateException <init>:()V
    athrow
L341
    getstatic client jf:Ljava/lang/String;
    new java/lang/StringBuilder
    dup
    invokespecial java/lang/StringBuilder <init>:()V
    getstatic client jk:Ljava/lang/String;
    invokevirtual java/lang/StringBuilder append:(Ljava/lang/String;)Ljava/lang/StringBuilder;
    ldc " " (java.lang.String)
    invokevirtual java/lang/StringBuilder append:(Ljava/lang/String;)Ljava/lang/StringBuilder;
    getstatic a w:Ljava/lang/String;
    invokevirtual java/lang/StringBuilder append:(Ljava/lang/String;)Ljava/lang/StringBuilder;
    ldc " " (java.lang.String)
    invokevirtual java/lang/StringBuilder append:(Ljava/lang/String;)Ljava/lang/StringBuilder;
    ldc 16748608 (java.lang.Integer)
    bipush -9
    invokestatic p e:(IB)Ljava/lang/String;
    invokevirtual java/lang/StringBuilder append:(Ljava/lang/String;)Ljava/lang/StringBuilder;
    aload 26
    getfield ad j:Ljava/lang/String;
    invokevirtual java/lang/StringBuilder append:(Ljava/lang/String;)Ljava/lang/StringBuilder;
    invokevirtual java/lang/StringBuilder toString:()Ljava/lang/String;
    bipush 32
    ldc 1822592743 (java.lang.Integer)
    aload 26
    getfield ad h:I
    imul
    iload 21
    aload 10
    getfield fb h:I
    ldc 952871887 (java.lang.Integer)
    imul
    ldc -1401187876 (java.lang.Integer)
    invokestatic fk bo:(Ljava/lang/String;Ljava/lang/String;IIIII)V
    goto L263
L440
    aload 26
    getfield ad ao:[Ljava/lang/String;
    astore 27
    goto L443
L86
    iload 20
    iload 5
    if_icmpge L342
    iload 8
    iconst_0
    if_icmpgt L89
    new java/lang/IllegalStateException
    dup
    invokespecial java/lang/IllegalStateException <init>:()V
    athrow
L110
    istore 14
    goto L113
L274
    aload 10
    bipush 67
    invokestatic t dj:(Lfb;B)I
    bipush -74
    invokestatic cu w:(IB)Z
    ifeq L444
    iload 8
    iconst_0
    if_icmpgt L445
    new java/lang/IllegalStateException
    dup
    invokespecial java/lang/IllegalStateException <init>:()V
    athrow
L445
    iconst_4
    istore 28
L446
    iload 28
    iconst_3
    if_icmplt L444
L447
    aload 27
    ifnull L308
    iload 8
    iconst_0
    if_icmpgt L448
    new java/lang/IllegalStateException
    dup
    invokespecial java/lang/IllegalStateException <init>:()V
    athrow
L448
    aconst_null
    aload 27
    iload 28
    aaload
    if_acmpeq L308
    iload 8
    iconst_0
    if_icmpgt L449
    new java/lang/IllegalStateException
    dup
    invokespecial java/lang/IllegalStateException <init>:()V
    athrow
L450
    ldc -193401837 (java.lang.Integer)
    aload 19
    getfield c e:I
    imul
    istore 20
    goto L400
L451
    aload 24
    aload 10
    getfield fb bz:Ljava/lang/String;
    bipush 57
    iload 22
    iconst_1
    iadd
    aload 10
    getfield fb s:I
    ldc 101374153 (java.lang.Integer)
    imul
    aload 10
    getfield fb h:I
    ldc 952871887 (java.lang.Integer)
    imul
    ldc -1849516930 (java.lang.Integer)
    invokestatic fk bo:(Ljava/lang/String;Ljava/lang/String;IIIII)V
    goto L452
L453
    bipush 37
    istore 29
    goto L28
L454
    getstatic client ls:Lgh;
    aload 22
    invokevirtual gh a:(Lgm;)V
    goto L455
L335
    goto L309
L456
    getstatic client lm:Lgh;
    aload 22
    invokevirtual gh a:(Lgm;)V
    goto L34
L310
    getstatic et l:Ljava/lang/String;
    new java/lang/StringBuilder
    dup
    invokespecial java/lang/StringBuilder <init>:()V
    ldc 16748608 (java.lang.Integer)
    bipush -9
    invokestatic p e:(IB)Ljava/lang/String;
    invokevirtual java/lang/StringBuilder append:(Ljava/lang/String;)Ljava/lang/StringBuilder;
    aload 26
    getfield ad j:Ljava/lang/String;
    invokevirtual java/lang/StringBuilder append:(Ljava/lang/String;)Ljava/lang/StringBuilder;
    invokevirtual java/lang/StringBuilder toString:()Ljava/lang/String;
    bipush 37
    ldc 1822592743 (java.lang.Integer)
    aload 26
    getfield ad h:I
    imul
    iload 21
    aload 10
    getfield fb h:I
    ldc 952871887 (java.lang.Integer)
    imul
    ldc -1590217851 (java.lang.Integer)
    invokestatic fk bo:(Ljava/lang/String;Ljava/lang/String;IIIII)V
L309
    iinc 28 -1
    goto L446
L457
    iinc 22 1
    goto L229
L458
    iload 29
    bipush 31
    ishr
    iconst_1
    iand
    ifeq L459
    iload 8
    iconst_0
    if_icmpgt L460
    new java/lang/IllegalStateException
    dup
    invokespecial java/lang/IllegalStateException <init>:()V
    athrow
L414
    iload 21
    bipush 20
    if_icmpge L410
    goto L415
L149
    iload 18
    iload 14
    if_icmplt L11
    iload 8
    iconst_0
    if_icmpgt L461
    new java/lang/IllegalStateException
    dup
    invokespecial java/lang/IllegalStateException <init>:()V
    athrow
L462
    istore 28
    goto L19
L463
    iconst_0
    iload 24
    iload 21
    iconst_1
    iadd
    ishr
    iconst_1
    iand
    if_icmpeq L360
    iload 8
    iconst_0
    if_icmpgt L464
    new java/lang/IllegalStateException
    dup
    invokespecial java/lang/IllegalStateException <init>:()V
    athrow
L423
    aload 10
    putstatic t gt:Lfb;
    goto L465
L212
    iload 29
    iflt L239
    iload 8
    iconst_0
    if_icmpgt L216
    return
L466
    aload 27
    ifnull L219
    iload 8
    iconst_0
    if_icmpgt L467
    new java/lang/IllegalStateException
    dup
    invokespecial java/lang/IllegalStateException <init>:()V
    athrow
L467
    iconst_2
    istore 30
L133
    iload 30
    iflt L219
    iload 8
    iconst_0
    if_icmpgt L468
    new java/lang/IllegalStateException
    dup
    invokespecial java/lang/IllegalStateException <init>:()V
    athrow
L468
    aload 27
    iload 30
    aaload
    ifnull L132
    iload 8
    iconst_0
    if_icmpgt L469
    new java/lang/IllegalStateException
    dup
    invokespecial java/lang/IllegalStateException <init>:()V
    athrow
L470
    aload 22
    ldc -1227089081 (java.lang.Integer)
    ldc -1976433391 (java.lang.Integer)
    getstatic ep i:I
    imul
    iload 11
    isub
    imul
    putfield e c:I
    goto L471
L472
    aconst_null
    astore 23
    goto L12
L473
    bipush 33
    istore 31
L474
    iconst_1
    iload 30
    if_icmpne L475
    iload 8
    iconst_0
    if_icmpgt L476
    new java/lang/IllegalStateException
    dup
    invokespecial java/lang/IllegalStateException <init>:()V
    athrow
L476
    bipush 34
    istore 31
    goto L475
L477
    ldc -1705214451 (java.lang.Integer)
    putstatic client ii:I
    goto L209
L478
    bipush 35
    istore 31
L479
    aload 27
    iload 30
    aaload
    new java/lang/StringBuilder
    dup
    invokespecial java/lang/StringBuilder <init>:()V
    ldc 16748608 (java.lang.Integer)
    bipush -47
    invokestatic p e:(IB)Ljava/lang/String;
    invokevirtual java/lang/StringBuilder append:(Ljava/lang/String;)Ljava/lang/StringBuilder;
    aload 26
    getfield ad j:Ljava/lang/String;
    invokevirtual java/lang/StringBuilder append:(Ljava/lang/String;)Ljava/lang/StringBuilder;
    invokevirtual java/lang/StringBuilder toString:()Ljava/lang/String;
    iload 31
    ldc 1822592743 (java.lang.Integer)
    aload 26
    getfield ad h:I
    imul
    iload 21
    ldc 952871887 (java.lang.Integer)
    aload 10
    getfield fb h:I
    imul
    ldc -1934692746 (java.lang.Integer)
    invokestatic fk bo:(Ljava/lang/String;Ljava/lang/String;IIIII)V
    goto L132
L233
    sipush 1001
    istore 30
    goto L232
L386
    iload 4
    istore 15
    goto L189
L220
    getstatic client ju:Z
    ifeq L480
    aload 27
    ldc -2101409365 (java.lang.Integer)
    invokestatic dj cl:([Ljava/lang/String;I)[Ljava/lang/String;
    astore 27
L480
    aconst_null
    aload 27
    if_acmpeq L317
L481
    iconst_4
    istore 30
    goto L316
L193
    iinc 21 1
    goto L482
L122
    aload 29
    getfield ad ap:[Ljava/lang/String;
    astore 30
    goto L276
L483
    iconst_0
    istore 31
L484
    iconst_0
    iload 30
    if_icmpne L485
    goto L486
L487
    aconst_null
    putstatic client jc:Lfb;
    goto L488
L489
    iconst_0
    getstatic client in:I
    ldc 1293091945 (java.lang.Integer)
    imul
    if_icmpne L160
    iload 8
    iconst_0
    if_icmpgt L159
    new java/lang/IllegalStateException
    dup
    invokespecial java/lang/IllegalStateException <init>:()V
    athrow
L490
    new e
    dup
    invokespecial e <init>:()V
    astore 22
    goto L152
L491
    aload 22
    aload 10
    putfield e l:Lfb;
    goto L492
L178
    bipush 41
    istore 31
L177
    iload 30
    iconst_3
    if_icmpne L64
    bipush 42
    istore 31
    goto L64
L118
    iload 5
    goto L120
L66
    bipush 43
    istore 31
L65
    aload 27
    iload 30
    aaload
    new java/lang/StringBuilder
    dup
    invokespecial java/lang/StringBuilder <init>:()V
    ldc 16748608 (java.lang.Integer)
    bipush -48
    invokestatic p e:(IB)Ljava/lang/String;
    invokevirtual java/lang/StringBuilder append:(Ljava/lang/String;)Ljava/lang/StringBuilder;
    aload 26
    getfield ad j:Ljava/lang/String;
    invokevirtual java/lang/StringBuilder append:(Ljava/lang/String;)Ljava/lang/StringBuilder;
    invokevirtual java/lang/StringBuilder toString:()Ljava/lang/String;
    iload 31
    ldc 1822592743 (java.lang.Integer)
    aload 26
    getfield ad h:I
    imul
    iload 21
    ldc 952871887 (java.lang.Integer)
    aload 10
    getfield fb h:I
    imul
    ldc -2024095966 (java.lang.Integer)
    invokestatic fk bo:(Ljava/lang/String;Ljava/lang/String;IIIII)V
L493
    iinc 30 -1
    goto L316
L317
    getstatic et eb:Ljava/lang/String;
    new java/lang/StringBuilder
    dup
    invokespecial java/lang/StringBuilder <init>:()V
    ldc 16748608 (java.lang.Integer)
    bipush -70
    invokestatic p e:(IB)Ljava/lang/String;
    invokevirtual java/lang/StringBuilder append:(Ljava/lang/String;)Ljava/lang/StringBuilder;
    aload 26
    getfield ad j:Ljava/lang/String;
    invokevirtual java/lang/StringBuilder append:(Ljava/lang/String;)Ljava/lang/StringBuilder;
    invokevirtual java/lang/StringBuilder toString:()Ljava/lang/String;
    sipush 1005
    aload 26
    getfield ad h:I
    ldc 1822592743 (java.lang.Integer)
    imul
    iload 21
    aload 10
    getfield fb h:I
    ldc 952871887 (java.lang.Integer)
    imul
    ldc -2128224049 (java.lang.Integer)
    invokestatic fk bo:(Ljava/lang/String;Ljava/lang/String;IIIII)V
    goto L263
L281
    aconst_null
    aload 27
    if_acmpne L285
    goto L369
L465
    aload 10
    getfield fb dv:[I
    iload 21
    iaload
    ifle L263
    iload 8
    iconst_0
    if_icmpgt L427
    return
L363
    iinc 31 -1
    goto L344
L494
    iconst_0
    aload 10
    getfield fb j:I
    ldc -1547422441 (java.lang.Integer)
    imul
    if_icmpeq L17
    iload 8
    iconst_0
    if_icmpgt L16
    new java/lang/IllegalStateException
    dup
    invokespecial java/lang/IllegalStateException <init>:()V
    athrow
L207
    getstatic client is:Z
    ifeq L495
    iload 8
    iconst_0
    if_icmpgt L496
    return
L210
    getstatic ep i:I
    ldc -1976433391 (java.lang.Integer)
    imul
    iload 15
    if_icmpge L209
    iload 8
    iconst_0
    if_icmpgt L497
    return
L498
    bipush 32
    ldc -448064051 (java.lang.Integer)
    getstatic da jj:I
    imul
    bipush 32
    iand
    if_icmpne L206
    iload 8
    iconst_0
    if_icmpgt L499
    new java/lang/IllegalStateException
    dup
    invokespecial java/lang/IllegalStateException <init>:()V
    athrow
L499
    getstatic client jf:Ljava/lang/String;
    new java/lang/StringBuilder
    dup
    invokespecial java/lang/StringBuilder <init>:()V
    getstatic client jk:Ljava/lang/String;
    invokevirtual java/lang/StringBuilder append:(Ljava/lang/String;)Ljava/lang/StringBuilder;
    ldc " " (java.lang.String)
    invokevirtual java/lang/StringBuilder append:(Ljava/lang/String;)Ljava/lang/StringBuilder;
    getstatic a w:Ljava/lang/String;
    invokevirtual java/lang/StringBuilder append:(Ljava/lang/String;)Ljava/lang/StringBuilder;
    ldc " " (java.lang.String)
    invokevirtual java/lang/StringBuilder append:(Ljava/lang/String;)Ljava/lang/StringBuilder;
    aload 10
    getfield fb bz:Ljava/lang/String;
    invokevirtual java/lang/StringBuilder append:(Ljava/lang/String;)Ljava/lang/StringBuilder;
    invokevirtual java/lang/StringBuilder toString:()Ljava/lang/String;
    bipush 58
    iconst_0
    ldc 101374153 (java.lang.Integer)
    aload 10
    getfield fb s:I
    imul
    ldc 952871887 (java.lang.Integer)
    aload 10
    getfield fb h:I
    imul
    ldc -1308686150 (java.lang.Integer)
    invokestatic fk bo:(Ljava/lang/String;Ljava/lang/String;IIIII)V
    goto L206
L495
    bipush 9
    istore 21
L500
    iload 21
    iconst_5
    if_icmplt L437
    iload 8
    iconst_0
    if_icmpgt L501
    new java/lang/IllegalStateException
    dup
    invokespecial java/lang/IllegalStateException <init>:()V
    athrow
L501
    aload 10
    bipush 27
    invokestatic t dj:(Lfb;B)I
    istore 24
    goto L463
L222
    iload 17
    iload 15
    if_icmpge L206
    iload 8
    iconst_0
    if_icmpgt L387
    new java/lang/IllegalStateException
    dup
    invokespecial java/lang/IllegalStateException <init>:()V
    athrow
L464
    iconst_1
    goto L361
L502
    getstatic client ls:Lgh;
    aload 22
    invokevirtual gh a:(Lgm;)V
    goto L503
L504
    iconst_1
    putstatic client jl:Z
    goto L505
L506
    iinc 21 -1
    goto L500
L289
    aload 10
    getfield fb cy:[Ljava/lang/Object;
    ifnonnull L29
    iload 8
    iconst_0
    if_icmpgt L507
    new java/lang/IllegalStateException
    dup
    invokespecial java/lang/IllegalStateException <init>:()V
    athrow
L507
    aconst_null
    astore 22
L508
    goto L396
L509
    aload 22
    ldc -1616406211 (java.lang.Integer)
    getstatic ep r:I
    imul
    iload 12
    isub
    ldc -133900669 (java.lang.Integer)
    imul
    putfield e u:I
    goto L510
L31
    aload 10
    getfield fb bh:[Ljava/lang/String;
    arraylength
    iload 21
    if_icmple L30
    iload 8
    iconst_0
    if_icmpgt L511
    new java/lang/IllegalStateException
    dup
    invokespecial java/lang/IllegalStateException <init>:()V
    athrow
L511
    aload 10
    getfield fb bh:[Ljava/lang/String;
    iload 21
    aaload
    ifnull L30
    iload 8
    iconst_0
    if_icmpgt L512
    return
L512
    aload 10
    getfield fb bh:[Ljava/lang/String;
    iload 21
    aaload
    invokevirtual java/lang/String trim:()Ljava/lang/String;
    invokevirtual java/lang/String length:()I
    ifne L513
    iload 8
    iconst_0
    if_icmpgt L30
    new java/lang/IllegalStateException
    dup
    invokespecial java/lang/IllegalStateException <init>:()V
    athrow
L514
    getstatic client ls:Lgh;
    aload 22
    invokevirtual gh a:(Lgm;)V
    goto L430
L343
    goto L396
L513
    aload 10
    getfield fb bh:[Ljava/lang/String;
    iload 21
    aaload
    astore 22
    goto L396
L503
    aload 10
    getfield fb dy:Z
    ifne L435
    iload 8
    iconst_0
    if_icmpgt L434
    new java/lang/IllegalStateException
    dup
    invokespecial java/lang/IllegalStateException <init>:()V
    athrow
L397
    aconst_null
    aload 23
    if_acmpeq L506
    iload 8
    iconst_0
    if_icmpgt L515
    new java/lang/IllegalStateException
    dup
    invokespecial java/lang/IllegalStateException <init>:()V
    athrow
L515
    aload 23
    aload 10
    getfield fb bz:Ljava/lang/String;
    sipush 1007
    iconst_1
    iload 21
    iadd
    aload 10
    getfield fb s:I
    ldc 101374153 (java.lang.Integer)
    imul
    aload 10
    getfield fb h:I
    ldc 952871887 (java.lang.Integer)
    imul
    ldc -1540345083 (java.lang.Integer)
    invokestatic fk bo:(Ljava/lang/String;Ljava/lang/String;IIIII)V
    goto L506
L412
    bipush 32
    ldc 1440440859 (java.lang.Integer)
    aload 10
    getfield fb bd:I
    imul
    iadd
    iload 23
    imul
    istore 24
    goto L413
L516
    iload 22
    iflt L517
    goto L145
L438
    aload 21
    ifnull L518
    iload 8
    iconst_0
    if_icmpgt L519
    new java/lang/IllegalStateException
    dup
    invokespecial java/lang/IllegalStateException <init>:()V
    athrow
L519
    aload 21
    aload 10
    getfield fb bz:Ljava/lang/String;
    bipush 25
    iconst_0
    aload 10
    getfield fb s:I
    ldc 101374153 (java.lang.Integer)
    imul
    aload 10
    getfield fb h:I
    ldc 952871887 (java.lang.Integer)
    imul
    ldc -2033338187 (java.lang.Integer)
    invokestatic fk bo:(Ljava/lang/String;Ljava/lang/String;IIIII)V
L518
    iconst_4
    istore 22
    goto L516
L520
    aload 10
    getfield fb bh:[Ljava/lang/String;
    iload 22
    aaload
    invokevirtual java/lang/String trim:()Ljava/lang/String;
    invokevirtual java/lang/String length:()I
    ifne L521
    iload 8
    iconst_0
    if_icmpgt L257
    new java/lang/IllegalStateException
    dup
    invokespecial java/lang/IllegalStateException <init>:()V
    athrow
L482
    iload 21
    getstatic cy bv:I
    if_icmpge L371
    goto L522
L146
    iload 25
    iconst_1
    iload 22
    iadd
    ishr
    iconst_1
    iand
    ifeq L523
    iload 8
    iconst_0
    if_icmpgt L524
    new java/lang/IllegalStateException
    dup
    invokespecial java/lang/IllegalStateException <init>:()V
    athrow
L94
    aload 27
    invokevirtual gh g:()Lgm;
    checkcast ax
    astore 28
    goto L370
L525
    iinc 23 1
    goto L411
L526
    istore 24
L527
    iload 24
    ifne L528
    iload 8
    iconst_0
    if_icmpgt L529
    new java/lang/IllegalStateException
    dup
    invokespecial java/lang/IllegalStateException <init>:()V
    athrow
L530
    ldc -1616406211 (java.lang.Integer)
    getstatic ep r:I
    imul
    istore 23
    goto L531
L475
    iload 30
    iconst_2
    if_icmpne L479
    goto L478
L302
    iload 28
    getstatic client ch:I
    ldc -1048248787 (java.lang.Integer)
    imul
    if_icmpge L303
    iload 8
    iconst_0
    if_icmpgt L377
    new java/lang/IllegalStateException
    dup
    invokespecial java/lang/IllegalStateException <init>:()V
    athrow
L334
    getstatic et ev:Ljava/lang/String;
    new java/lang/StringBuilder
    dup
    invokespecial java/lang/StringBuilder <init>:()V
    getstatic client it:Ljava/lang/String;
    invokevirtual java/lang/StringBuilder append:(Ljava/lang/String;)Ljava/lang/StringBuilder;
    ldc " " (java.lang.String)
    invokevirtual java/lang/StringBuilder append:(Ljava/lang/String;)Ljava/lang/StringBuilder;
    getstatic a w:Ljava/lang/String;
    invokevirtual java/lang/StringBuilder append:(Ljava/lang/String;)Ljava/lang/StringBuilder;
    ldc " " (java.lang.String)
    invokevirtual java/lang/StringBuilder append:(Ljava/lang/String;)Ljava/lang/StringBuilder;
    ldc 16748608 (java.lang.Integer)
    bipush -53
    invokestatic p e:(IB)Ljava/lang/String;
    invokevirtual java/lang/StringBuilder append:(Ljava/lang/String;)Ljava/lang/StringBuilder;
    aload 29
    getfield ad j:Ljava/lang/String;
    invokevirtual java/lang/StringBuilder append:(Ljava/lang/String;)Ljava/lang/StringBuilder;
    invokevirtual java/lang/StringBuilder toString:()Ljava/lang/String;
    bipush 16
    ldc 1019941107 (java.lang.Integer)
    aload 28
    getfield ax e:I
    imul
    iload 23
    iload 24
    ldc -1191059891 (java.lang.Integer)
    invokestatic fk bo:(Ljava/lang/String;Ljava/lang/String;IIIII)V
    goto L94
L153
    aload 22
    aload 10
    putfield e l:Lfb;
    goto L532
L258
    aconst_null
    aload 10
    getfield fb bh:[Ljava/lang/String;
    iload 22
    aaload
    if_acmpeq L257
    iload 8
    iconst_0
    if_icmpgt L520
    new java/lang/IllegalStateException
    dup
    invokespecial java/lang/IllegalStateException <init>:()V
    athrow
L392
    getstatic client is:Z
    ifne L391
    iload 8
    iconst_0
    if_icmpgt L14
    new java/lang/IllegalStateException
    dup
    invokespecial java/lang/IllegalStateException <init>:()V
    athrow
L182
    getstatic ep j:I
    ldc -642165313 (java.lang.Integer)
    imul
    iload 15
    if_icmpge L125
    iload 8
    iconst_0
    if_icmpgt L533
    new java/lang/IllegalStateException
    dup
    invokespecial java/lang/IllegalStateException <init>:()V
    athrow
L534
    goto L13
L521
    aload 10
    getfield fb bh:[Ljava/lang/String;
    iload 22
    aaload
    astore 23
L13
    aload 23
    astore 24
    goto L535
L171
    iload 22
    bipush 29
    ishr
    iconst_3
    iand
    istore 25
    goto L172
L528
    aconst_null
    aload 10
    getfield fb bh:[Ljava/lang/String;
    if_acmpeq L257
    iload 8
    iconst_0
    if_icmpgt L256
    new java/lang/IllegalStateException
    dup
    invokespecial java/lang/IllegalStateException <init>:()V
    athrow
L452
    iinc 22 -1
    goto L516
L536
    aconst_null
    aload 10
    getfield fb cv:[Ljava/lang/Object;
    if_acmpeq L537
    iload 8
    iconst_0
    if_icmpgt L538
    new java/lang/IllegalStateException
    dup
    invokespecial java/lang/IllegalStateException <init>:()V
    athrow
L539
    getstatic et i:Ljava/lang/String;
    ldc "" (java.lang.String)
    bipush 30
    iconst_0
    ldc 101374153 (java.lang.Integer)
    aload 10
    getfield fb s:I
    imul
    ldc 952871887 (java.lang.Integer)
    aload 10
    getfield fb h:I
    imul
    ldc -1878097805 (java.lang.Integer)
    invokestatic fk bo:(Ljava/lang/String;Ljava/lang/String;IIIII)V
L206
    ldc -1547422441 (java.lang.Integer)
    aload 10
    getfield fb j:I
    imul
    ifne L540
    iload 8
    iconst_0
    if_icmpgt L541
    new java/lang/IllegalStateException
    dup
    invokespecial java/lang/IllegalStateException <init>:()V
    athrow
L541
    aload 10
    getfield fb o:Z
    ifne L322
    iload 8
    iconst_0
    if_icmpgt L321
    new java/lang/IllegalStateException
    dup
    invokespecial java/lang/IllegalStateException <init>:()V
    athrow
L461
    iload 17
    iload 15
    if_icmpge L11
    goto L542
L323
    getstatic fq ib:Lfb;
    aload 10
    if_acmpeq L322
    iload 8
    iconst_0
    if_icmpgt L543
    new java/lang/IllegalStateException
    dup
    invokespecial java/lang/IllegalStateException <init>:()V
    athrow
L543
    goto L11
L322
    aload 0
    ldc 952871887 (java.lang.Integer)
    aload 10
    getfield fb h:I
    imul
    iload 13
    iload 14
    iload 15
    iload 16
    iload 11
    ldc 1503817007 (java.lang.Integer)
    aload 10
    getfield fb p:I
    imul
    isub
    iload 12
    aload 10
    getfield fb k:I
    ldc -884306721 (java.lang.Integer)
    imul
    isub
    bipush 10
    invokestatic n cq:([Lfb;IIIIIIIB)V
L544
    aconst_null
    aload 10
    getfield fb do:[Lfb;
    if_acmpeq L545
    iload 8
    iconst_0
    if_icmpgt L546
    new java/lang/IllegalStateException
    dup
    invokespecial java/lang/IllegalStateException <init>:()V
    athrow
L546
    aload 10
    getfield fb do:[Lfb;
    ldc 952871887 (java.lang.Integer)
    aload 10
    getfield fb h:I
    imul
    iload 13
    iload 14
    iload 15
    iload 16
    iload 11
    ldc 1503817007 (java.lang.Integer)
    aload 10
    getfield fb p:I
    imul
    isub
    iload 12
    aload 10
    getfield fb k:I
    ldc -884306721 (java.lang.Integer)
    imul
    isub
    bipush 26
    invokestatic n cq:([Lfb;IIIIIIIB)V
    goto L545
L304
    iload 28
    ldc 308668811 (java.lang.Integer)
    getstatic client hr:I
    imul
    if_icmpge L286
    iload 8
    iconst_0
    if_icmpgt L136
    new java/lang/IllegalStateException
    dup
    invokespecial java/lang/IllegalStateException <init>:()V
    athrow
L318
    aconst_null
    aload 27
    iload 30
    aaload
    if_acmpeq L493
    iload 8
    iconst_0
    if_icmpgt L483
    new java/lang/IllegalStateException
    dup
    invokespecial java/lang/IllegalStateException <init>:()V
    athrow
L547
    ldc -1460840163 (java.lang.Integer)
    aload 19
    getfield c a:I
    imul
    ifne L450
    getstatic ep i:I
    ldc -1976433391 (java.lang.Integer)
    imul
    iload 13
    if_icmplt L450
    iload 8
    iconst_0
    if_icmpgt L548
    new java/lang/IllegalStateException
    dup
    invokespecial java/lang/IllegalStateException <init>:()V
    athrow
L549
    getstatic client iy:[Ljava/lang/String;
    iconst_0
    getstatic et ic:Ljava/lang/String;
    aastore
    goto L550
L551
    ldc -1976433391 (java.lang.Integer)
    getstatic ep i:I
    imul
    iload 15
    if_icmpge L450
    iload 8
    iconst_0
    if_icmpgt L552
    return
L553
    aload 22
    iconst_1
    putfield e a:Z
    goto L554
L555
    getstatic client ih:Z
    ifne L450
    getstatic client jy:Z
    ifne L450
    iload 8
    iconst_0
    if_icmpgt L549
    new java/lang/IllegalStateException
    dup
    invokespecial java/lang/IllegalStateException <init>:()V
    athrow
L524
    iconst_1
    goto L526
L550
    getstatic client iu:[Ljava/lang/String;
    iconst_0
    ldc "" (java.lang.String)
    aastore
L556
    getstatic client ia:[I
    iconst_0
    sipush 1006
    iastore
L557
    ldc -1705214451 (java.lang.Integer)
    putstatic client ii:I
    goto L450
L372
    iload 19
    bipush 127
    iand
    istore 21
    goto L374
L558
    aload 27
    getfield ag ao:[Ljava/lang/String;
    astore 28
    goto L203
L402
    goto L540
L401
    getstatic fb e:[[Lfb;
    iload 20
    aaload
    iconst_m1
    iload 13
    iload 14
    iload 15
    iload 16
    iload 11
    iload 12
    bipush 46
    invokestatic n cq:([Lfb;IIIIIIIB)V
L540
    aload 10
    getfield fb o:Z
    ifeq L559
    iload 8
    iconst_0
    if_icmpgt L560
    new java/lang/IllegalStateException
    dup
    invokespecial java/lang/IllegalStateException <init>:()V
    athrow
L560
    aload 10
    getfield fb ep:Z
    ifeq L209
    iload 8
    iconst_0
    if_icmpgt L561
    new java/lang/IllegalStateException
    dup
    invokespecial java/lang/IllegalStateException <init>:()V
    athrow
L561
    getstatic ep i:I
    ldc -1976433391 (java.lang.Integer)
    imul
    iload 13
    if_icmplt L209
    iload 8
    iconst_0
    if_icmpgt L208
    new java/lang/IllegalStateException
    dup
    invokespecial java/lang/IllegalStateException <init>:()V
    athrow
L562
    aload 10
    ldc -1880614510 (java.lang.Integer)
    invokestatic ar dt:(Lfb;I)Z
    ifeq L25
    goto L32
L443
    getstatic client ju:Z
    ifeq L274
    iload 8
    iconst_0
    if_icmpgt L273
    new java/lang/IllegalStateException
    dup
    invokespecial java/lang/IllegalStateException <init>:()V
    athrow
L497
    getstatic ep r:I
    ldc -1616406211 (java.lang.Integer)
    imul
    iload 16
    if_icmpge L209
L563
    getstatic client ls:Lgh;
    invokevirtual gh i:()Lgm;
    checkcast e
    astore 19
L564
    aconst_null
    aload 19
    if_acmpeq L565
    iload 8
    iconst_0
    if_icmpgt L97
    new java/lang/IllegalStateException
    dup
    invokespecial java/lang/IllegalStateException <init>:()V
    athrow
L522
    getstatic cy bc:[I
    iload 21
    iaload
    istore 22
    goto L169
L99
    aload 19
    invokevirtual e if:()V
L566
    aload 19
    getfield e l:Lfb;
    iconst_0
    putfield fb dy:Z
    goto L98
L102
    istore 13
    goto L107
L565
    ldc 963286165 (java.lang.Integer)
    getstatic e ky:I
    imul
    ifne L567
    iload 8
    iconst_0
    if_icmpgt L487
    new java/lang/IllegalStateException
    dup
    invokespecial java/lang/IllegalStateException <init>:()V
    athrow
L120
    istore 16
    goto L80
L488
    aconst_null
    putstatic client jm:Lfb;
L567
    getstatic client ih:Z
    ifne L209
L568
    getstatic client iy:[Ljava/lang/String;
    iconst_0
    getstatic et ic:Ljava/lang/String;
    aastore
L569
    getstatic client iu:[Ljava/lang/String;
    iconst_0
    ldc "" (java.lang.String)
    aastore
L570
    getstatic client ia:[I
    iconst_0
    sipush 1006
    iastore
    goto L477
L535
    aconst_null
    aload 24
    if_acmpeq L452
    iload 8
    iconst_0
    if_icmpgt L451
    new java/lang/IllegalStateException
    dup
    invokespecial java/lang/IllegalStateException <init>:()V
    athrow
L60
    iload 20
    istore 18
    goto L63
L571
    getstatic client ih:Z
    ifeq L572
    goto L573
L574
    ldc -1976433391 (java.lang.Integer)
    getstatic ep i:I
    imul
    iload 15
    if_icmpge L166
    iload 8
    iconst_0
    if_icmpgt L575
    return
L545
    getstatic client jv:Lgf;
    ldc 952871887 (java.lang.Integer)
    aload 10
    getfield fb h:I
    imul
    i2l
    invokevirtual gf e:(J)Lgm;
    checkcast c
    astore 19
    goto L576
L11
    iinc 9 1
    goto L2
L577
    new e
    dup
    invokespecial e <init>:()V
    astore 22
    goto L283
L578
    aload 22
    ldc -1616406211 (java.lang.Integer)
    getstatic ep r:I
    imul
    iload 12
    isub
    ldc -133900669 (java.lang.Integer)
    imul
    putfield e u:I
    goto L579
L485
    iconst_1
    iload 30
    if_icmpne L176
    iload 8
    iconst_0
    if_icmpgt L358
    new java/lang/IllegalStateException
    dup
    invokespecial java/lang/IllegalStateException <init>:()V
    athrow
L238
    getstatic q at:Z
    ifne L81
    iload 8
    iconst_0
    if_icmpgt L580
    new java/lang/IllegalStateException
    dup
    invokespecial java/lang/IllegalStateException <init>:()V
    athrow
L23
    aload 10
    getfield fb o:Z
    ifeq L25
    iload 8
    iconst_0
    if_icmpgt L562
    new java/lang/IllegalStateException
    dup
    invokespecial java/lang/IllegalStateException <init>:()V
    athrow
L237
    iload 19
    ifeq L81
    iload 8
    iconst_0
    if_icmpgt L581
    return
L582
    aconst_null
    aload 10
    getfield fb cp:[Ljava/lang/Object;
    if_acmpeq L435
    iload 8
    iconst_0
    if_icmpgt L490
    new java/lang/IllegalStateException
    dup
    invokespecial java/lang/IllegalStateException <init>:()V
    athrow
L583
    getstatic client jc:Lfb;
    ifnonnull L11
    iload 8
    iconst_0
    if_icmpgt L584
    new java/lang/IllegalStateException
    dup
    invokespecial java/lang/IllegalStateException <init>:()V
    athrow
L580
    iconst_4
    ldc 945615415 (java.lang.Integer)
    getstatic ep w:I
    imul
    if_icmpne L81
    iload 8
    iconst_0
    if_icmpgt L237
    return
L585
    getstatic q at:Z
    ifne L125
    iconst_4
    ldc -1750678861 (java.lang.Integer)
    getstatic ep s:I
    imul
    if_icmpne L125
L586
    ldc -642165313 (java.lang.Integer)
    getstatic ep j:I
    imul
    iload 13
    if_icmplt L125
    iload 8
    iconst_0
    if_icmpgt L181
    return
L587
    ldc -606292603 (java.lang.Integer)
    aload 10
    getfield fb b:I
    imul
    istore 24
    goto L201
L205
    aload 28
    ldc -1893410634 (java.lang.Integer)
    invokestatic dj cl:([Ljava/lang/String;I)[Ljava/lang/String;
    astore 28
    goto L204
L533
    ldc 1563808941 (java.lang.Integer)
    getstatic ep m:I
    imul
    iload 16
    if_icmpge L125
    iload 8
    iconst_0
    if_icmpgt L124
    new java/lang/IllegalStateException
    dup
    invokespecial java/lang/IllegalStateException <init>:()V
    athrow
L548
    ldc -1616406211 (java.lang.Integer)
    getstatic ep r:I
    imul
    iload 14
    if_icmplt L450
    iload 8
    iconst_0
    if_icmpgt L551
    new java/lang/IllegalStateException
    dup
    invokespecial java/lang/IllegalStateException <init>:()V
    athrow
L125
    iload 21
    ifeq L588
    iload 8
    iconst_0
    if_icmpgt L589
    new java/lang/IllegalStateException
    dup
    invokespecial java/lang/IllegalStateException <init>:()V
    athrow
L589
    aload 10
    getstatic ep j:I
    ldc -642165313 (java.lang.Integer)
    imul
    iload 11
    isub
    ldc 1563808941 (java.lang.Integer)
    getstatic ep m:I
    imul
    iload 12
    isub
    ldc -954126053 (java.lang.Integer)
    invokestatic ft cx:(Lfb;III)V
L588
    getstatic client jc:Lfb;
    ifnull L590
    iload 8
    iconst_0
    if_icmpgt L591
    return
L420
    getstatic ep r:I
    ldc -1616406211 (java.lang.Integer)
    imul
    iload 14
    if_icmplt L166
    iload 8
    iconst_0
    if_icmpgt L574
    return
L592
    iload 19
    ifeq L590
    iload 8
    iconst_0
    if_icmpgt L593
    new java/lang/IllegalStateException
    dup
    invokespecial java/lang/IllegalStateException <init>:()V
    athrow
L593
    aload 10
    bipush 61
    invokestatic t dj:(Lfb;B)I
    ldc 1059672230 (java.lang.Integer)
    invokestatic ej l:(II)Z
    ifeq L590
    iload 8
    iconst_0
    if_icmpgt L594
    new java/lang/IllegalStateException
    dup
    invokespecial java/lang/IllegalStateException <init>:()V
    athrow
L594
    aload 10
    putstatic client jh:Lfb;
L590
    getstatic client jm:Lfb;
    aload 10
    if_acmpne L595
    iload 8
    iconst_0
    if_icmpgt L504
    return
L596
    new e
    dup
    invokespecial e <init>:()V
    astore 22
    goto L597
L505
    ldc 1361269971 (java.lang.Integer)
    iload 11
    imul
    putstatic client jr:I
L598
    ldc 48648679 (java.lang.Integer)
    iload 12
    imul
    putstatic client jq:I
L595
    aload 10
    getfield fb ch:Z
    ifeq L559
    iload 8
    iconst_0
    if_icmpgt L599
    return
L599
    iload 19
    ifeq L418
    iconst_0
    getstatic client ld:I
    ldc -548139547 (java.lang.Integer)
    imul
    if_icmpeq L418
    iload 8
    iconst_0
    if_icmpgt L417
    new java/lang/IllegalStateException
    dup
    invokespecial java/lang/IllegalStateException <init>:()V
    athrow
L575
    ldc -1616406211 (java.lang.Integer)
    getstatic ep r:I
    imul
    iload 16
    if_icmpge L166
    iload 8
    iconst_0
    if_icmpgt L111
    return
L419
    new e
    dup
    invokespecial e <init>:()V
    astore 22
L600
    aload 22
    iconst_1
    putfield e a:Z
    goto L601
L602
    iload 22
    iload 19
    bipush 16
    iadd
    if_icmpge L603
    goto L604
L605
    aload 22
    getstatic client ld:I
    ldc -1691055569 (java.lang.Integer)
    imul
    putfield e u:I
L606
    aload 22
    aload 10
    getfield fb cc:[Ljava/lang/Object;
    putfield e e:[Ljava/lang/Object;
L607
    getstatic client ls:Lgh;
    aload 22
    invokevirtual gh a:(Lgm;)V
L418
    getstatic client jc:Lfb;
    ifnonnull L608
    iload 8
    iconst_0
    if_icmpgt L609
    new java/lang/IllegalStateException
    dup
    invokespecial java/lang/IllegalStateException <init>:()V
    athrow
L609
    getstatic c gm:Lfb;
    ifnonnull L608
    iload 8
    iconst_0
    if_icmpgt L610
    new java/lang/IllegalStateException
    dup
    invokespecial java/lang/IllegalStateException <init>:()V
    athrow
L96
    aload 25
    aload 10
    getfield fb cl:[Ljava/lang/Object;
    putfield e e:[Ljava/lang/Object;
    goto L611
L608
    iconst_0
    istore 21
L612
    iconst_0
    istore 20
    goto L613
L194
    getstatic client is:Z
    ifeq L558
    goto L199
L614
    aload 10
    getfield fb da:Z
    ifne L537
    iload 8
    iconst_0
    if_icmpgt L615
    new java/lang/IllegalStateException
    dup
    invokespecial java/lang/IllegalStateException <init>:()V
    athrow
L601
    aload 22
    aload 10
    putfield e l:Lfb;
    goto L605
L616
    aload 10
    iconst_1
    putfield fb da:Z
    goto L536
L272
    aload 29
    ifnull L250
    iload 8
    iconst_0
    if_icmpgt L275
    new java/lang/IllegalStateException
    dup
    invokespecial java/lang/IllegalStateException <init>:()V
    athrow
L538
    new e
    dup
    invokespecial e <init>:()V
    astore 22
    goto L617
L581
    iconst_1
    istore 20
    goto L81
L618
    aload 22
    aload 10
    putfield e l:Lfb;
L619
    aload 22
    ldc -642165313 (java.lang.Integer)
    getstatic ep j:I
    imul
    iload 11
    isub
    ldc -1227089081 (java.lang.Integer)
    imul
    putfield e c:I
    goto L45
L433
    ldc -7450759 (java.lang.Integer)
    getstatic fp iq:I
    imul
    iload 21
    if_icmpeq L263
    iload 8
    iconst_0
    if_icmpgt L432
    new java/lang/IllegalStateException
    dup
    invokespecial java/lang/IllegalStateException <init>:()V
    athrow
L98
    getstatic client ls:Lgh;
    invokevirtual gh f:()Lgm;
    checkcast e
    astore 19
    goto L564
L373
    getstatic client ls:Lgh;
    aload 22
    invokevirtual gh a:(Lgm;)V
L537
    aload 10
    getfield fb da:Z
    ifeq L9
    iload 8
    iconst_0
    if_icmpgt L620
    new java/lang/IllegalStateException
    dup
    invokespecial java/lang/IllegalStateException <init>:()V
    athrow
L620
    iload 20
    ifeq L9
    iload 8
    iconst_0
    if_icmpgt L621
    new java/lang/IllegalStateException
    dup
    invokespecial java/lang/IllegalStateException <init>:()V
    athrow
L621
    aload 10
    getfield fb ci:[Ljava/lang/Object;
    ifnull L9
    iload 8
    iconst_0
    if_icmpgt L43
    new java/lang/IllegalStateException
    dup
    invokespecial java/lang/IllegalStateException <init>:()V
    athrow
L496
    aload 10
    bipush 22
    invokestatic t dj:(Lfb;B)I
    ldc 1099483050 (java.lang.Integer)
    invokestatic co c:(II)Z
    ifeq L206
    iload 8
    iconst_0
    if_icmpgt L498
    new java/lang/IllegalStateException
    dup
    invokespecial java/lang/IllegalStateException <init>:()V
    athrow
L622
    iload 23
    aload 10
    getfield fb cw:[I
    iload 24
    iaload
    if_icmpne L260
    iload 8
    iconst_0
    if_icmpgt L623
    new java/lang/IllegalStateException
    dup
    invokespecial java/lang/IllegalStateException <init>:()V
    athrow
L624
    aload 22
    aload 10
    putfield e l:Lfb;
    goto L470
L218
    iconst_0
    istore 30
    goto L625
L127
    iload 11
    ldc 588440073 (java.lang.Integer)
    imul
    putstatic client ke:I
    goto L131
L626
    aload 22
    aload 10
    getfield fb ci:[Ljava/lang/Object;
    putfield e e:[Ljava/lang/Object;
    goto L8
L106
    getstatic ep r:I
    ldc -1616406211 (java.lang.Integer)
    imul
    iload 16
    if_icmpge L105
    iload 8
    iconst_0
    if_icmpgt L380
    new java/lang/IllegalStateException
    dup
    invokespecial java/lang/IllegalStateException <init>:()V
    athrow
L627
    aload 10
    getfield fb cr:[Ljava/lang/Object;
    ifnull L628
    iload 8
    iconst_0
    if_icmpgt L629
    new java/lang/IllegalStateException
    dup
    invokespecial java/lang/IllegalStateException <init>:()V
    athrow
L630
    iload 20
    ifne L34
    iload 8
    iconst_0
    if_icmpgt L188
    new java/lang/IllegalStateException
    dup
    invokespecial java/lang/IllegalStateException <init>:()V
    athrow
L610
    getstatic client ih:Z
    ifeq L614
    iload 8
    iconst_0
    if_icmpgt L608
    new java/lang/IllegalStateException
    dup
    invokespecial java/lang/IllegalStateException <init>:()V
    athrow
L576
    aconst_null
    aload 19
    if_acmpeq L540
    iload 8
    iconst_0
    if_icmpgt L547
    new java/lang/IllegalStateException
    dup
    invokespecial java/lang/IllegalStateException <init>:()V
    athrow
L35
    new e
    dup
    invokespecial e <init>:()V
    astore 22
    goto L553
L631
    iload 23
    iload 12
    iload 20
    iadd
    bipush 16
    isub
    if_icmplt L305
    iload 8
    iconst_0
    if_icmpgt L632
    new java/lang/IllegalStateException
    dup
    invokespecial java/lang/IllegalStateException <init>:()V
    athrow
L554
    aload 22
    aload 10
    putfield e l:Lfb;
L633
    aload 22
    ldc -1227089081 (java.lang.Integer)
    ldc -1976433391 (java.lang.Integer)
    getstatic ep i:I
    imul
    iload 11
    isub
    imul
    putfield e c:I
    goto L578
L368
    ldc 945615415 (java.lang.Integer)
    getstatic ep w:I
    imul
    iconst_1
    if_icmpeq L634
    iload 8
    iconst_0
    if_icmpgt L635
    return
L379
    iload 11
    iload 12
    ldc 1709609665 (java.lang.Integer)
    invokestatic r ap:(III)V
    goto L383
L217
    iinc 29 -1
    goto L212
L34
    iload 20
    ifeq L503
    iload 8
    iconst_0
    if_icmpgt L636
    new java/lang/IllegalStateException
    dup
    invokespecial java/lang/IllegalStateException <init>:()V
    athrow
L636
    aload 10
    getfield fb cd:[Ljava/lang/Object;
    ifnull L503
L637
    new e
    dup
    invokespecial e <init>:()V
    astore 22
L638
    aload 22
    iconst_1
    putfield e a:Z
    goto L639
L407
    iconst_0
    istore 21
    goto L408
L640
    aload 22
    ldc -1976433391 (java.lang.Integer)
    getstatic ep i:I
    imul
    iload 11
    isub
    ldc -1227089081 (java.lang.Integer)
    imul
    putfield e c:I
    goto L509
L257
    aconst_null
    astore 23
    goto L534
L510
    aload 22
    aload 10
    getfield fb cd:[Ljava/lang/Object;
    putfield e e:[Ljava/lang/Object;
    goto L502
L641
    aload 10
    ldc -1023277750 (java.lang.Integer)
    invokestatic dh cr:(Lfb;I)V
    goto L642
L361
    istore 23
    goto L288
L643
    getstatic client kk:I
    ldc 1518980093 (java.lang.Integer)
    imul
    aload 10
    getfield fb dr:I
    ldc 629474053 (java.lang.Integer)
    imul
    if_icmple L644
    iload 8
    iconst_0
    if_icmpgt L645
    new java/lang/IllegalStateException
    dup
    invokespecial java/lang/IllegalStateException <init>:()V
    athrow
L436
    aload 10
    iconst_1
    putfield fb dy:Z
    goto L582
L112
    iconst_0
    istore 20
    goto L236
L314
    getstatic client is:Z
    ifeq L440
    goto L439
L646
    getstatic client kj:[I
    iload 22
    bipush 31
    iand
    iaload
    istore 23
    goto L647
L349
    iload 31
    ifne L353
    iload 8
    iconst_0
    if_icmpgt L352
    new java/lang/IllegalStateException
    dup
    invokespecial java/lang/IllegalStateException <init>:()V
    athrow
L532
    aload 22
    ldc -1227089081 (java.lang.Integer)
    getstatic ep i:I
    ldc -1976433391 (java.lang.Integer)
    imul
    iload 11
    isub
    imul
    putfield e c:I
L648
    aload 22
    ldc -133900669 (java.lang.Integer)
    getstatic ep r:I
    ldc -1616406211 (java.lang.Integer)
    imul
    iload 12
    isub
    imul
    putfield e u:I
L649
    aload 22
    aload 10
    getfield fb cp:[Ljava/lang/Object;
    putfield e e:[Ljava/lang/Object;
L650
    getstatic client ls:Lgh;
    aload 22
    invokevirtual gh a:(Lgm;)V
L435
    aload 10
    getfield fb dy:Z
    ifeq L430
    goto L429
L398
    ldc 1810211167 (java.lang.Integer)
    aload 10
    getfield fb m:I
    imul
    iconst_4
    if_icmpne L165
    iload 8
    iconst_0
    if_icmpgt L164
    new java/lang/IllegalStateException
    dup
    invokespecial java/lang/IllegalStateException <init>:()V
    athrow
L431
    aload 10
    getfield fb ce:[Ljava/lang/Object;
    ifnull L430
L651
    new e
    dup
    invokespecial e <init>:()V
    astore 22
L652
    aload 22
    iconst_1
    putfield e a:Z
    goto L91
L653
    new e
    dup
    invokespecial e <init>:()V
    astore 22
    goto L41
L92
    aload 22
    ldc -1227089081 (java.lang.Integer)
    getstatic ep i:I
    ldc -1976433391 (java.lang.Integer)
    imul
    iload 11
    isub
    imul
    putfield e c:I
L654
    aload 22
    getstatic ep r:I
    ldc -1616406211 (java.lang.Integer)
    imul
    iload 12
    isub
    ldc -133900669 (java.lang.Integer)
    imul
    putfield e u:I
L655
    aload 22
    aload 10
    getfield fb ce:[Ljava/lang/Object;
    putfield e e:[Ljava/lang/Object;
    goto L514
L337
    iconst_4
    iload 31
    if_icmpne L62
    iload 8
    iconst_0
    if_icmpgt L61
    new java/lang/IllegalStateException
    dup
    invokespecial java/lang/IllegalStateException <init>:()V
    athrow
L430
    aload 10
    getfield fb dy:Z
    ifeq L656
    iload 8
    iconst_0
    if_icmpgt L657
    return
L657
    iload 19
    ifne L656
L658
    aload 10
    iconst_0
    putfield fb dy:Z
L659
    aload 10
    getfield fb cm:[Ljava/lang/Object;
    ifnull L656
    iload 8
    iconst_0
    if_icmpgt L653
    return
L68
    iload 17
    iload 2
    if_icmple L73
    iload 8
    iconst_0
    if_icmpgt L71
    new java/lang/IllegalStateException
    dup
    invokespecial java/lang/IllegalStateException <init>:()V
    athrow
L144
    getstatic client d:Z
    ifne L11
    iload 8
    iconst_0
    if_icmpgt L147
    new java/lang/IllegalStateException
    dup
    invokespecial java/lang/IllegalStateException <init>:()V
    athrow
L42
    aload 22
    aload 10
    putfield e l:Lfb;
L660
    aload 22
    getstatic ep i:I
    ldc -1976433391 (java.lang.Integer)
    imul
    iload 11
    isub
    ldc -1227089081 (java.lang.Integer)
    imul
    putfield e c:I
L661
    aload 22
    ldc -133900669 (java.lang.Integer)
    getstatic ep r:I
    ldc -1616406211 (java.lang.Integer)
    imul
    iload 12
    isub
    imul
    putfield e u:I
L662
    aload 22
    aload 10
    getfield fb cm:[Ljava/lang/Object;
    putfield e e:[Ljava/lang/Object;
L663
    getstatic client lm:Lgh;
    aload 22
    invokevirtual gh a:(Lgm;)V
L656
    aload 10
    getfield fb cn:[Ljava/lang/Object;
    ifnull L664
    iload 8
    iconst_0
    if_icmpgt L665
    new java/lang/IllegalStateException
    dup
    invokespecial java/lang/IllegalStateException <init>:()V
    athrow
L665
    new e
    dup
    invokespecial e <init>:()V
    astore 22
    goto L37
L486
    bipush 39
    istore 31
    goto L485
L38
    aload 22
    aload 10
    getfield fb cn:[Ljava/lang/Object;
    putfield e e:[Ljava/lang/Object;
L666
    getstatic client li:Lgh;
    aload 22
    invokevirtual gh a:(Lgm;)V
L664
    aload 10
    getfield fb cu:[Ljava/lang/Object;
    ifnull L627
    iload 8
    iconst_0
    if_icmpgt L667
    return
L667
    getstatic client kn:I
    ldc 1477285925 (java.lang.Integer)
    imul
    ldc -965156547 (java.lang.Integer)
    aload 10
    getfield fb di:I
    imul
    if_icmple L627
    iload 8
    iconst_0
    if_icmpgt L330
    return
L175
    goto L193
L552
    getstatic ep r:I
    ldc -1616406211 (java.lang.Integer)
    imul
    iload 16
    if_icmpge L450
    iload 8
    iconst_0
    if_icmpgt L555
    new java/lang/IllegalStateException
    dup
    invokespecial java/lang/IllegalStateException <init>:()V
    athrow
L331
    new e
    dup
    invokespecial e <init>:()V
    astore 22
L668
    aload 22
    aload 10
    putfield e l:Lfb;
    goto L167
L277
    iconst_4
    istore 31
    goto L344
L449
    iload 28
    iconst_3
    if_icmpne L453
    iload 8
    iconst_0
    if_icmpgt L27
    new java/lang/IllegalStateException
    dup
    invokespecial java/lang/IllegalStateException <init>:()V
    athrow
L617
    aload 22
    iconst_1
    putfield e a:Z
    goto L618
L669
    aload 10
    getfield fb di:I
    ldc -965156547 (java.lang.Integer)
    imul
    istore 22
L670
    iload 22
    ldc 1477285925 (java.lang.Integer)
    getstatic client kn:I
    imul
    if_icmpge L235
    iload 8
    iconst_0
    if_icmpgt L671
    new java/lang/IllegalStateException
    dup
    invokespecial java/lang/IllegalStateException <init>:()V
    athrow
L671
    getstatic client kl:[I
    iload 22
    bipush 31
    iand
    iaload
    istore 23
L672
    iconst_0
    istore 24
L673
    iload 24
    aload 10
    getfield fb ck:[I
    arraylength
    if_icmpge L674
L675
    aload 10
    getfield fb ck:[I
    iload 24
    iaload
    iload 23
    if_icmpne L676
    iload 8
    iconst_0
    if_icmpgt L677
    new java/lang/IllegalStateException
    dup
    invokespecial java/lang/IllegalStateException <init>:()V
    athrow
L299
    new e
    dup
    invokespecial e <init>:()V
    astore 22
    goto L678
L679
    aload 25
    aload 10
    putfield e l:Lfb;
L680
    aload 25
    aload 10
    getfield fb cu:[Ljava/lang/Object;
    putfield e e:[Ljava/lang/Object;
L681
    getstatic client ls:Lgh;
    aload 25
    invokevirtual gh a:(Lgm;)V
L682
    goto L235
L529
    aconst_null
    aload 10
    getfield fb cy:[Ljava/lang/Object;
    if_acmpne L528
    iload 8
    iconst_0
    if_icmpgt L472
    new java/lang/IllegalStateException
    dup
    invokespecial java/lang/IllegalStateException <init>:()V
    athrow
L674
    iinc 22 1
    goto L670
L235
    aload 10
    ldc 1854222601 (java.lang.Integer)
    getstatic client kn:I
    imul
    putfield fb di:I
    goto L627
L579
    aload 22
    aload 10
    getfield fb cg:[Ljava/lang/Object;
    putfield e e:[Ljava/lang/Object;
    goto L456
L629
    ldc 1947199569 (java.lang.Integer)
    getstatic client kh:I
    imul
    aload 10
    getfield fb dz:I
    ldc -1125758625 (java.lang.Integer)
    imul
    if_icmple L628
    iload 8
    iconst_0
    if_icmpgt L683
    new java/lang/IllegalStateException
    dup
    invokespecial java/lang/IllegalStateException <init>:()V
    athrow
L48
    iload 11
    ldc -606292603 (java.lang.Integer)
    aload 10
    getfield fb b:I
    imul
    iadd
    istore 17
    goto L69
L684
    getstatic client kh:I
    ldc 1947199569 (java.lang.Integer)
    imul
    aload 10
    getfield fb dz:I
    ldc -1125758625 (java.lang.Integer)
    imul
    isub
    bipush 32
    if_icmple L685
    iload 8
    iconst_0
    if_icmpgt L577
    new java/lang/IllegalStateException
    dup
    invokespecial java/lang/IllegalStateException <init>:()V
    athrow
L163
    iconst_0
    istore 21
    goto L482
L9
    aload 10
    getfield fb da:Z
    ifeq L34
    goto L630
L284
    aload 22
    aload 10
    getfield fb cr:[Ljava/lang/Object;
    putfield e e:[Ljava/lang/Object;
    goto L150
L185
    iconst_0
    istore 23
    goto L411
L151
    goto L230
L685
    aload 10
    getfield fb dz:I
    ldc -1125758625 (java.lang.Integer)
    imul
    istore 22
    goto L229
L245
    aload 27
    getfield am e:Lay;
    iload 26
    iload 23
    iload 24
    ldc 1775278006 (java.lang.Integer)
    invokestatic x ch:(Lay;IIII)V
    goto L240
L231
    getstatic client ko:[I
    iload 22
    bipush 31
    iand
    iaload
    istore 23
L686
    iconst_0
    istore 24
L261
    iload 24
    aload 10
    getfield fb cw:[I
    arraylength
    if_icmpge L457
    goto L622
L2
    iload 9
    aload 0
    arraylength
    if_icmpge L687
    iload 8
    iconst_0
    if_icmpgt L6
    new java/lang/IllegalStateException
    dup
    invokespecial java/lang/IllegalStateException <init>:()V
    athrow
L623
    new e
    dup
    invokespecial e <init>:()V
    astore 25
L688
    aload 25
    aload 10
    putfield e l:Lfb;
L689
    aload 25
    aload 10
    getfield fb cr:[Ljava/lang/Object;
    putfield e e:[Ljava/lang/Object;
    goto L375
L255
    aload 29
    ifnull L266
    goto L690
L319
    iload 20
    istore 19
    goto L279
L615
    iload 21
    ifeq L537
    iload 8
    iconst_0
    if_icmpgt L616
    new java/lang/IllegalStateException
    dup
    invokespecial java/lang/IllegalStateException <init>:()V
    athrow
L78
    istore 14
    goto L282
L230
    aload 10
    ldc 1515404367 (java.lang.Integer)
    getstatic client kh:I
    imul
    putfield fb dz:I
L628
    aconst_null
    aload 10
    getfield fb cl:[Ljava/lang/Object;
    if_acmpeq L644
    iload 8
    iconst_0
    if_icmpgt L643
    new java/lang/IllegalStateException
    dup
    invokespecial java/lang/IllegalStateException <init>:()V
    athrow
L691
    aload 10
    ldc -1023277750 (java.lang.Integer)
    invokestatic dh cr:(Lfb;I)V
    goto L11
L559
    aload 10
    getfield fb o:Z
    ifne L11
    iload 8
    iconst_0
    if_icmpgt L583
    return
L692
    ldc 1518980093 (java.lang.Integer)
    getstatic client kk:I
    imul
    ldc 629474053 (java.lang.Integer)
    aload 10
    getfield fb dr:I
    imul
    isub
    bipush 32
    if_icmple L693
    iload 8
    iconst_0
    if_icmpgt L694
    return
L694
    new e
    dup
    invokespecial e <init>:()V
    astore 22
L695
    aload 22
    aload 10
    putfield e l:Lfb;
L696
    aload 22
    aload 10
    getfield fb cl:[Ljava/lang/Object;
    putfield e e:[Ljava/lang/Object;
    goto L454
L7
    aload 10
    ifnonnull L697
    goto L10
L455
    goto L88
L693
    ldc 629474053 (java.lang.Integer)
    aload 10
    getfield fb dr:I
    imul
    istore 22
L698
    iload 22
    getstatic client kk:I
    ldc 1518980093 (java.lang.Integer)
    imul
    if_icmpge L88
    iload 8
    iconst_0
    if_icmpgt L646
    return
L36
    ldc -1547422441 (java.lang.Integer)
    aload 10
    getfield fb j:I
    imul
    iconst_2
    if_icmpne L47
    goto L39
L647
    iconst_0
    istore 24
L699
    iload 24
    aload 10
    getfield fb co:[I
    arraylength
    if_icmpge L700
    iload 8
    iconst_0
    if_icmpgt L441
    new java/lang/IllegalStateException
    dup
    invokespecial java/lang/IllegalStateException <init>:()V
    athrow
L329
    aload 28
    getfield ax e:I
    ldc 1019941107 (java.lang.Integer)
    imul
    bipush -58
    invokestatic dj e:(IB)Lad;
    astore 29
    goto L333
L676
    iinc 24 1
    goto L673
L100
    iload 2
    goto L102
L58
    iinc 19 1
    goto L67
L611
    getstatic client ls:Lgh;
    aload 25
    invokevirtual gh a:(Lgm;)V
    goto L87
L364
    iload 25
    iconst_2
    if_icmpne L196
    iload 8
    iconst_0
    if_icmpgt L259
    new java/lang/IllegalStateException
    dup
    invokespecial java/lang/IllegalStateException <init>:()V
    athrow
L442
    iinc 24 1
    goto L699
L700
    iinc 22 1
    goto L698
L296
    ldc 1705445099 (java.lang.Integer)
    aload 29
    getfield am e:Lay;
    getfield ay i:I
    imul
    iconst_1
    if_icmpne L295
    iload 8
    iconst_0
    if_icmpgt L312
    new java/lang/IllegalStateException
    dup
    invokespecial java/lang/IllegalStateException <init>:()V
    athrow
L644
    getstatic client kc:I
    ldc 1422348277 (java.lang.Integer)
    imul
    aload 10
    getfield fb dg:I
    ldc -307148225 (java.lang.Integer)
    imul
    if_icmple L292
    aconst_null
    aload 10
    getfield fb cs:[Ljava/lang/Object;
    if_acmpeq L292
    goto L268
L517
    aload 10
    bipush 74
    invokestatic t dj:(Lfb;B)I
    bipush 88
    invokestatic ck e:(IB)Z
    ifeq L206
    iload 8
    iconst_0
    if_icmpgt L539
    return
L269
    aload 22
    aload 10
    putfield e l:Lfb;
L701
    aload 22
    aload 10
    getfield fb cs:[Ljava/lang/Object;
    putfield e e:[Ljava/lang/Object;
L702
    getstatic client ls:Lgh;
    aload 22
    invokevirtual gh a:(Lgm;)V
    goto L292
L253
    iconst_0
    istore 28
    goto L270
L293
    aload 10
    getfield fb ca:[Ljava/lang/Object;
    ifnull L156
    iload 8
    iconst_0
    if_icmpgt L703
    new java/lang/IllegalStateException
    dup
    invokespecial java/lang/IllegalStateException <init>:()V
    athrow
L703
    new e
    dup
    invokespecial e <init>:()V
    astore 22
    goto L424
L444
    aload 10
    bipush 55
    invokestatic t dj:(Lfb;B)I
    istore 29
    goto L458
L425
    aload 22
    aload 10
    getfield fb ca:[Ljava/lang/Object;
    putfield e e:[Ljava/lang/Object;
L704
    getstatic client ls:Lgh;
    aload 22
    invokevirtual gh a:(Lgm;)V
    goto L156
L460
    iconst_1
    goto L462
L332
    ldc 1477285925 (java.lang.Integer)
    getstatic client kn:I
    imul
    aload 10
    getfield fb di:I
    ldc -965156547 (java.lang.Integer)
    imul
    isub
    bipush 32
    if_icmple L669
    iload 8
    iconst_0
    if_icmpgt L331
    new java/lang/IllegalStateException
    dup
    invokespecial java/lang/IllegalStateException <init>:()V
    athrow
L639
    aload 22
    aload 10
    putfield e l:Lfb;
    goto L640
L678
    aload 22
    aload 10
    putfield e l:Lfb;
L705
    aload 22
    aload 10
    getfield fb dd:[Ljava/lang/Object;
    putfield e e:[Ljava/lang/Object;
L706
    getstatic client ls:Lgh;
    aload 22
    invokevirtual gh a:(Lgm;)V
L157
    getstatic client ku:I
    ldc 1329054113 (java.lang.Integer)
    imul
    ldc -307148225 (java.lang.Integer)
    aload 10
    getfield fb dg:I
    imul
    if_icmple L707
    iload 8
    iconst_0
    if_icmpgt L708
    new java/lang/IllegalStateException
    dup
    invokespecial java/lang/IllegalStateException <init>:()V
    athrow
L708
    aconst_null
    aload 10
    getfield fb dc:[Ljava/lang/Object;
    if_acmpeq L707
    goto L596
L20
    aconst_null
    checkcast fc
    pop
    aload 10
    bipush 31
    invokestatic t dj:(Lfb;B)I
    bipush -70
    invokestatic cu w:(IB)Z
    ifeq L219
    iload 8
    iconst_0
    if_icmpgt L466
    new java/lang/IllegalStateException
    dup
    invokespecial java/lang/IllegalStateException <init>:()V
    athrow
L597
    aload 22
    aload 10
    putfield e l:Lfb;
L709
    aload 22
    aload 10
    getfield fb dc:[Ljava/lang/Object;
    putfield e e:[Ljava/lang/Object;
L710
    getstatic client ls:Lgh;
    aload 22
    invokevirtual gh a:(Lgm;)V
L707
    ldc -418974459 (java.lang.Integer)
    getstatic client kv:I
    imul
    ldc -307148225 (java.lang.Integer)
    aload 10
    getfield fb dg:I
    imul
    if_icmple L327
    iload 8
    iconst_0
    if_icmpgt L326
    new java/lang/IllegalStateException
    dup
    invokespecial java/lang/IllegalStateException <init>:()V
    athrow
L697
    aload 10
    getfield fb o:Z
    ifeq L17
    iload 8
    iconst_0
    if_icmpgt L494
    new java/lang/IllegalStateException
    dup
    invokespecial java/lang/IllegalStateException <init>:()V
    athrow
L328
    new e
    dup
    invokespecial e <init>:()V
    astore 22
    goto L491
L44
    aload 22
    iconst_1
    putfield e a:Z
    goto L624
L492
    aload 22
    aload 10
    getfield fb dw:[Ljava/lang/Object;
    putfield e e:[Ljava/lang/Object;
L711
    getstatic client ls:Lgh;
    aload 22
    invokevirtual gh a:(Lgm;)V
    goto L327
L88
    aload 10
    ldc 1227581081 (java.lang.Integer)
    getstatic client kk:I
    imul
    putfield fb dr:I
    goto L644
L712
    iconst_0
    iload 30
    if_icmpne L474
    iload 8
    iconst_0
    if_icmpgt L473
    new java/lang/IllegalStateException
    dup
    invokespecial java/lang/IllegalStateException <init>:()V
    athrow
L291
    new e
    dup
    invokespecial e <init>:()V
    astore 22
L713
    aload 22
    aload 10
    putfield e l:Lfb;
L714
    aload 22
    aload 10
    getfield fb dk:[Ljava/lang/Object;
    putfield e e:[Ljava/lang/Object;
    goto L154
L416
    iload 25
    aload 10
    getfield fb bq:[I
    iload 21
    iaload
    iadd
    istore 25
    goto L410
L155
    aload 10
    getstatic client ki:I
    ldc 1293946573 (java.lang.Integer)
    imul
    putfield fb dg:I
L715
    aconst_null
    aload 10
    getfield fb cz:[Ljava/lang/Object;
    if_acmpeq L559
    iload 8
    iconst_0
    if_icmpgt L716
    new java/lang/IllegalStateException
    dup
    invokespecial java/lang/IllegalStateException <init>:()V
    athrow
L716
    iconst_0
    istore 22
L717
    iload 22
    getstatic client lk:I
    ldc -551903993 (java.lang.Integer)
    imul
    if_icmpge L559
    iload 8
    iconst_0
    if_icmpgt L718
    new java/lang/IllegalStateException
    dup
    invokespecial java/lang/IllegalStateException <init>:()V
    athrow
L718
    new e
    dup
    invokespecial e <init>:()V
    astore 23
L719
    aload 23
    aload 10
    putfield e l:Lfb;
L720
    aload 23
    ldc -1411627027 (java.lang.Integer)
    getstatic client ml:[I
    iload 22
    iaload
    imul
    putfield e r:I
L721
    aload 23
    getstatic client mr:[I
    iload 22
    iaload
    ldc 481009671 (java.lang.Integer)
    imul
    putfield e f:I
    goto L393
L683
    aconst_null
    aload 10
    getfield fb cw:[I
    if_acmpeq L577
    iload 8
    iconst_0
    if_icmpgt L684
    new java/lang/IllegalStateException
    dup
    invokespecial java/lang/IllegalStateException <init>:()V
    athrow
L394
    getstatic client ls:Lgh;
    aload 23
    invokevirtual gh a:(Lgm;)V
L722
    iinc 22 1
    goto L717
L542
    iload 18
    iload 16
    if_icmpge L11
    iload 8
    iconst_0
    if_icmpgt L489
    new java/lang/IllegalStateException
    dup
    invokespecial java/lang/IllegalStateException <init>:()V
    athrow
L338
    bipush 21
    istore 32
    goto L337
L584
    aconst_null
    getstatic c gm:Lfb;
    if_acmpne L11
    goto L571
L471
    aload 22
    ldc -133900669 (java.lang.Integer)
    getstatic ep r:I
    ldc -1616406211 (java.lang.Integer)
    imul
    iload 12
    isub
    imul
    putfield e u:I
    goto L626
L573
    goto L11
L572
    ldc 152781469 (java.lang.Integer)
    aload 10
    getfield fb dj:I
    imul
    ifge L426
    iload 8
    iconst_0
    if_icmpgt L723
    new java/lang/IllegalStateException
    dup
    invokespecial java/lang/IllegalStateException <init>:()V
    athrow
L723
    iconst_0
    aload 10
    getfield fb aw:I
    ldc 870233861 (java.lang.Integer)
    imul
    if_icmpeq L105
    goto L426
L459
    iconst_0
    goto L462
L591
    getstatic client jc:Lfb;
    aload 10
    if_acmpeq L590
    iload 8
    iconst_0
    if_icmpgt L592
    new java/lang/IllegalStateException
    dup
    invokespecial java/lang/IllegalStateException <init>:()V
    athrow
L168
    getstatic client ls:Lgh;
    aload 22
    invokevirtual gh a:(Lgm;)V
    goto L234
L366
    aload 29
    getstatic client hw:[I
    iload 28
    iaload
    iload 23
    iload 24
    ldc 902573772 (java.lang.Integer)
    invokestatic di cb:(Ll;IIII)V
    goto L129
L263
    iinc 21 1
    goto L525
L382
    aload 0
    ldc 152781469 (java.lang.Integer)
    aload 10
    getfield fb dj:I
    imul
    aaload
    putstatic fq ib:Lfb;
    goto L105
L381
    aload 10
    putstatic fq ib:Lfb;
L105
    bipush 8
    aload 10
    getfield fb j:I
    ldc -1547422441 (java.lang.Integer)
    imul
    if_icmpne L724
    iload 8
    iconst_0
    if_icmpgt L725
    return
L690
    aload 29
    aload 27
    if_acmpeq L266
    goto L409
L726
    ldc -1616406211 (java.lang.Integer)
    getstatic ep r:I
    imul
    iload 14
    if_icmplt L724
    iload 8
    iconst_0
    if_icmpgt L727
    new java/lang/IllegalStateException
    dup
    invokespecial java/lang/IllegalStateException <init>:()V
    athrow
L727
    ldc -1976433391 (java.lang.Integer)
    getstatic ep i:I
    imul
    iload 15
    if_icmpge L724
    iload 8
    iconst_0
    if_icmpgt L728
    new java/lang/IllegalStateException
    dup
    invokespecial java/lang/IllegalStateException <init>:()V
    athrow
L728
    getstatic ep r:I
    ldc -1616406211 (java.lang.Integer)
    imul
    iload 16
    if_icmpge L724
    iload 8
    iconst_0
    if_icmpgt L729
    new java/lang/IllegalStateException
    dup
    invokespecial java/lang/IllegalStateException <init>:()V
    athrow
L729
    aload 10
    putstatic at iv:Lfb;
L724
    ldc -820348081 (java.lang.Integer)
    aload 10
    getfield fb ap:I
    imul
    aload 10
    getfield fb x:I
    ldc 891461123 (java.lang.Integer)
    imul
    if_icmple L11
    iload 8
    iconst_0
    if_icmpgt L730
    new java/lang/IllegalStateException
    dup
    invokespecial java/lang/IllegalStateException <init>:()V
    athrow
L730
    iload 11
    aload 10
    getfield fb b:I
    ldc -606292603 (java.lang.Integer)
    imul
    iadd
    istore 19
L731
    ldc 891461123 (java.lang.Integer)
    aload 10
    getfield fb x:I
    imul
    istore 20
L732
    ldc -820348081 (java.lang.Integer)
    aload 10
    getfield fb ap:I
    imul
    istore 21
L733
    getstatic ep i:I
    ldc -1976433391 (java.lang.Integer)
    imul
    istore 22
    goto L530
L248
    iconst_0
    istore 28
    goto L252
L531
    getstatic client fo:Z
    ifeq L734
    iload 8
    iconst_0
    if_icmpgt L735
    new java/lang/IllegalStateException
    dup
    invokespecial java/lang/IllegalStateException <init>:()V
    athrow
L735
    ldc 39272992 (java.lang.Integer)
    putstatic client fu:I
    goto L367
L734
    iconst_0
    putstatic client fu:I
    goto L367
L82
    getstatic ep s:I
    ldc -1750678861 (java.lang.Integer)
    imul
    iconst_1
    if_icmpeq L586
    iload 8
    iconst_0
    if_icmpgt L585
    new java/lang/IllegalStateException
    dup
    invokespecial java/lang/IllegalStateException <init>:()V
    athrow
L725
    ldc -1976433391 (java.lang.Integer)
    getstatic ep i:I
    imul
    iload 13
    if_icmplt L724
    goto L726
L635
    getstatic q at:Z
    ifne L306
    ldc 945615415 (java.lang.Integer)
    getstatic ep w:I
    imul
    iconst_4
    if_icmpne L306
    iload 8
    iconst_0
    if_icmpgt L634
    new java/lang/IllegalStateException
    dup
    invokespecial java/lang/IllegalStateException <init>:()V
    athrow
L634
    iload 22
    iload 19
    if_icmplt L603
    goto L602
L346
    iload 31
    iconst_2
    if_icmpne L363
    iload 8
    iconst_0
    if_icmpgt L365
    new java/lang/IllegalStateException
    dup
    invokespecial java/lang/IllegalStateException <init>:()V
    athrow
L604
    iload 23
    iload 12
    if_icmplt L603
    iload 8
    iconst_0
    if_icmpgt L736
    new java/lang/IllegalStateException
    dup
    invokespecial java/lang/IllegalStateException <init>:()V
    athrow
L736
    iload 23
    iload 12
    bipush 16
    iadd
    if_icmpge L603
L737
    aload 10
    dup
    getfield fb k:I
    ldc -711934852 (java.lang.Integer)
    isub
    putfield fb k:I
L738
    aload 10
    ldc -1023277750 (java.lang.Integer)
    invokestatic dh cr:(Lfb;I)V
    goto L306
L603
    iload 22
    iload 19
    if_icmplt L305
    iload 8
    iconst_0
    if_icmpgt L739
    new java/lang/IllegalStateException
    dup
    invokespecial java/lang/IllegalStateException <init>:()V
    athrow
L739
    iload 22
    iload 19
    bipush 16
    iadd
    if_icmpge L305
    iload 8
    iconst_0
    if_icmpgt L631
    new java/lang/IllegalStateException
    dup
    invokespecial java/lang/IllegalStateException <init>:()V
    athrow
L677
    new e
    dup
    invokespecial e <init>:()V
    astore 25
    goto L679
L632
    iload 23
    iload 12
    iload 20
    iadd
    if_icmpge L305
L740
    aload 10
    dup
    getfield fb k:I
    ldc -711934852 (java.lang.Integer)
    iadd
    putfield fb k:I
L741
    aload 10
    ldc -1023277750 (java.lang.Integer)
    invokestatic dh cr:(Lfb;I)V
    goto L306
L625
    iconst_0
    iload 29
    if_icmpne L213
    iload 8
    iconst_0
    if_icmpgt L223
    new java/lang/IllegalStateException
    dup
    invokespecial java/lang/IllegalStateException <init>:()V
    athrow
L307
    iload 22
    bipush 16
    iload 19
    iadd
    getstatic client fu:I
    ldc 1475049201 (java.lang.Integer)
    imul
    iadd
    if_icmpge L306
    iload 8
    iconst_0
    if_icmpgt L742
    new java/lang/IllegalStateException
    dup
    invokespecial java/lang/IllegalStateException <init>:()V
    athrow
L742
    iload 23
    iload 12
    bipush 16
    iadd
    if_icmplt L306
    iload 8
    iconst_0
    if_icmpgt L743
    new java/lang/IllegalStateException
    dup
    invokespecial java/lang/IllegalStateException <init>:()V
    athrow
L743
    iload 23
    iload 20
    iload 12
    iadd
    bipush 16
    isub
    if_icmpge L306
    iload 8
    iconst_0
    if_icmpgt L297
    return
L376
    goto L230
L298
    iload 24
    bipush 8
    if_icmpge L744
    iload 8
    iconst_0
    if_icmpgt L745
    new java/lang/IllegalStateException
    dup
    invokespecial java/lang/IllegalStateException <init>:()V
    athrow
L745
    bipush 8
    istore 24
L744
    iload 23
    iload 12
    isub
    bipush 16
    isub
    iload 24
    iconst_2
    idiv
    isub
    istore 25
L746
    iload 20
    bipush 32
    isub
    iload 24
    isub
    istore 26
L747
    aload 10
    ldc -1251725537 (java.lang.Integer)
    iload 21
    iload 20
    isub
    iload 25
    imul
    iload 26
    idiv
    imul
    putfield fb k:I
    goto L641
L355
    bipush 19
    istore 32
    goto L354
L642
    iconst_1
    putstatic client fo:Z
L306
    ldc -548139547 (java.lang.Integer)
    getstatic client ld:I
    imul
    ifeq L11
    iload 8
    iconst_0
    if_icmpgt L587
    new java/lang/IllegalStateException
    dup
    invokespecial java/lang/IllegalStateException <init>:()V
    athrow
L645
    aload 10
    getfield fb co:[I
    ifnull L694
    iload 8
    iconst_0
    if_icmpgt L692
    return
L613
    iconst_0
    istore 19
    goto L614
L202
    iload 23
    iload 12
    if_icmplt L11
    iload 8
    iconst_0
    if_icmpgt L748
    return
L748
    iload 22
    iload 19
    bipush 16
    iadd
    if_icmpge L11
    iload 8
    iconst_0
    if_icmpgt L749
    new java/lang/IllegalStateException
    dup
    invokespecial java/lang/IllegalStateException <init>:()V
    athrow
L749
    iload 23
    iload 12
    iload 20
    iadd
    if_icmpgt L11
    iload 8
    iconst_0
    if_icmpgt L750
    new java/lang/IllegalStateException
    dup
    invokespecial java/lang/IllegalStateException <init>:()V
    athrow
L750
    aload 10
    dup
    getfield fb k:I
    getstatic client ld:I
    ldc -1741249057 (java.lang.Integer)
    imul
    iadd
    putfield fb k:I
    goto L691
L469
    iconst_0
    istore 31
    goto L712
L523
    iconst_0
    goto L526
L687
    return
L751
    new java/lang/StringBuilder
    dup
    invokespecial java/lang/StringBuilder <init>:()V
    ldc "n.cq(" (java.lang.String)
    invokevirtual java/lang/StringBuilder append:(Ljava/lang/String;)Ljava/lang/StringBuilder;
    ldc 41 (java.lang.Integer)
    invokevirtual java/lang/StringBuilder append:(C)Ljava/lang/StringBuilder;
    invokevirtual java/lang/StringBuilder toString:()Ljava/lang/String;
    invokestatic k a:(Ljava/lang/Throwable;Ljava/lang/String;)Lee;
    athrow
