p e (II)Laj;L1
    getstatic aj a:Lgr;
    iload 0
    i2l
    invokevirtual gr e:(J)Lgd;
    checkcast aj
    astore 2
L2
    aload 2
    ifnull L3
    iload 1
    ldc -1165677472 (java.lang.Integer)
    if_icmpeq L4
    new java/lang/IllegalStateException
    dup
    invokespecial java/lang/IllegalStateException <init>:()V
    athrow
L4
    aload 2
    areturn
L3
    getstatic aj e:Lfv;
    iconst_1
    iload 0
    ldc -1235376730 (java.lang.Integer)
    invokevirtual fv l:(III)[B
    astore 3
L5
    new aj
    dup
    invokespecial aj <init>:()V
    astore 2
L6
    aconst_null
    aload 3
    if_acmpeq L7
    iload 1
    ldc -1165677472 (java.lang.Integer)
    if_icmpeq L8
    new java/lang/IllegalStateException
    dup
    invokespecial java/lang/IllegalStateException <init>:()V
    athrow
L9
    aload 2
    areturn
L7
    aload 2
    ldc -1633024867 (java.lang.Integer)
    invokevirtual aj a:(I)V
L10
    getstatic aj a:Lgr;
    aload 2
    iload 0
    i2l
    invokevirtual gr l:(Lgd;J)V
    goto L9
L8
    aload 2
    new dh
    dup
    aload 3
    invokespecial dh <init>:([B)V
    iload 0
    bipush 9
    invokevirtual aj l:(Ldh;IB)V
    goto L7
L11
    new java/lang/StringBuilder
    dup
    invokespecial java/lang/StringBuilder <init>:()V
    ldc "p.e(" (java.lang.String)
    invokevirtual java/lang/StringBuilder append:(Ljava/lang/String;)Ljava/lang/StringBuilder;
    ldc 41 (java.lang.Integer)
    invokevirtual java/lang/StringBuilder append:(C)Ljava/lang/StringBuilder;
    invokevirtual java/lang/StringBuilder toString:()Ljava/lang/String;
    invokestatic k a:(Ljava/lang/Throwable;Ljava/lang/String;)Lee;
    athrow
