r a (II)Laq;L1
    getstatic aq a:Lgr;
    iload 0
    i2l
    invokevirtual gr e:(J)Lgd;
    checkcast aq
    astore 2
    goto L2
L3
    aload 2
    areturn
L4
    aload 2
    areturn
L5
    aload 2
    new dh
    dup
    aload 3
    invokespecial dh <init>:([B)V
    ldc -2047981609 (java.lang.Integer)
    invokevirtual aq l:(Ldh;I)V
    goto L6
L7
    aload 3
    ifnull L6
    iload 1
    ldc 2038417887 (java.lang.Integer)
    if_icmpne L5
    new java/lang/IllegalStateException
    dup
    invokespecial java/lang/IllegalStateException <init>:()V
    athrow
L8
    getstatic aq e:Lfv;
    bipush 8
    iload 0
    ldc -1948023966 (java.lang.Integer)
    invokevirtual fv l:(III)[B
    astore 3
    goto L9
L2
    aload 2
    ifnull L8
    iload 1
    ldc 2038417887 (java.lang.Integer)
    if_icmpne L4
    new java/lang/IllegalStateException
    dup
    invokespecial java/lang/IllegalStateException <init>:()V
    athrow
L6
    getstatic aq a:Lgr;
    aload 2
    iload 0
    i2l
    invokevirtual gr l:(Lgd;J)V
    goto L3
L9
    new aq
    dup
    invokespecial aq <init>:()V
    astore 2
    goto L7
L10
    new java/lang/StringBuilder
    dup
    invokespecial java/lang/StringBuilder <init>:()V
    ldc "r.a(" (java.lang.String)
    invokevirtual java/lang/StringBuilder append:(Ljava/lang/String;)Ljava/lang/StringBuilder;
    ldc 41 (java.lang.Integer)
    invokevirtual java/lang/StringBuilder append:(C)Ljava/lang/StringBuilder;
    invokevirtual java/lang/StringBuilder toString:()Ljava/lang/String;
    invokestatic k a:(Ljava/lang/Throwable;Ljava/lang/String;)Lee;
    athrow
