r ap (III)VL1
    iconst_0
    ldc 1217278719 (java.lang.Integer)
    getstatic client mx:I
    imul
    if_icmpeq L2
    iload 2
    ldc 1522878182 (java.lang.Integer)
    if_icmpgt L3
    return
L4
    getstatic client cd:Ldj;
    iload 4
    bipush -4
    invokevirtual dj e:(IB)V
    goto L5
L6
    iload 4
    iflt L7
    iload 2
    ldc 1522878182 (java.lang.Integer)
    if_icmpgt L8
    return
L2
    ldc -1750678861 (java.lang.Integer)
    getstatic ep s:I
    imul
    iconst_1
    if_icmpeq L9
    iload 2
    ldc 1522878182 (java.lang.Integer)
    if_icmpgt L10
    return
L10
    getstatic q at:Z
    ifne L7
    iload 2
    ldc 1522878182 (java.lang.Integer)
    if_icmpgt L11
    new java/lang/IllegalStateException
    dup
    invokespecial java/lang/IllegalStateException <init>:()V
    athrow
L11
    getstatic ep s:I
    ldc -1750678861 (java.lang.Integer)
    imul
    iconst_4
    if_icmpne L7
L9
    getstatic ep j:I
    ldc -642165313 (java.lang.Integer)
    imul
    bipush 25
    isub
    iload 0
    isub
    istore 3
    goto L12
L13
    iload 11
    ldc 1754300735 (java.lang.Integer)
    imul
    putstatic client mz:I
    goto L7
L14
    iload 3
    iflt L7
    iload 2
    ldc 1522878182 (java.lang.Integer)
    if_icmpgt L6
    return
L15
    iload 4
    sipush 142
    if_icmpgt L16
    iload 2
    ldc 1522878182 (java.lang.Integer)
    if_icmpgt L17
    new java/lang/IllegalStateException
    dup
    invokespecial java/lang/IllegalStateException <init>:()V
    athrow
L8
    iload 3
    sipush 146
    if_icmpge L7
    iload 2
    ldc 1522878182 (java.lang.Integer)
    if_icmpgt L18
    return
L18
    iload 4
    sipush 151
    if_icmpge L7
    iload 2
    ldc 1522878182 (java.lang.Integer)
    if_icmpgt L19
    new java/lang/IllegalStateException
    dup
    invokespecial java/lang/IllegalStateException <init>:()V
    athrow
L19
    iload 3
    iflt L16
    iload 2
    ldc 1522878182 (java.lang.Integer)
    if_icmpgt L20
    new java/lang/IllegalStateException
    dup
    invokespecial java/lang/IllegalStateException <init>:()V
    athrow
L21
    getstatic client cd:Ldj;
    getstatic dr ce:[Z
    bipush 82
    baload
    ifeq L22
    goto L23
L24
    iload 4
    bipush 117
    if_icmplt L16
    iload 2
    ldc 1522878182 (java.lang.Integer)
    if_icmpgt L15
    return
L25
    iload 7
    sipush 256
    ldc -981441773 (java.lang.Integer)
    getstatic client ec:I
    imul
    iadd
    imul
    bipush 8
    ishr
    istore 7
    goto L26
L17
    return
L16
    iinc 3 -73
    goto L27
L3
    iconst_3
    ldc 1217278719 (java.lang.Integer)
    getstatic client mx:I
    imul
    if_icmpeq L2
    iload 2
    ldc 1522878182 (java.lang.Integer)
    if_icmpgt L28
    new java/lang/IllegalStateException
    dup
    invokespecial java/lang/IllegalStateException <init>:()V
    athrow
L29
    getstatic client fy:I
    ldc 154136385 (java.lang.Integer)
    imul
    ldc 1158077643 (java.lang.Integer)
    getstatic client el:I
    imul
    iadd
    sipush 2047
    iand
    istore 5
    goto L30
L31
    iload 4
    iload 7
    imul
    iload 3
    iload 6
    imul
    isub
    bipush 11
    ishr
    istore 9
    goto L32
L33
    getstatic cp am:[I
    iload 5
    iaload
    istore 7
L34
    iload 6
    sipush 256
    ldc -981441773 (java.lang.Integer)
    getstatic client ec:I
    imul
    iadd
    imul
    bipush 8
    ishr
    istore 6
    goto L25
L35
    getstatic client cd:Ldj;
    bipush 119
    ldc -1526335214 (java.lang.Integer)
    invokevirtual dj hl:(II)V
    goto L36
L26
    iload 6
    iload 4
    imul
    iload 3
    iload 7
    imul
    iadd
    bipush 11
    ishr
    istore 8
    goto L31
L28
    return
L37
    getstatic client cd:Ldj;
    ldc 1158077643 (java.lang.Integer)
    getstatic client el:I
    imul
    bipush -30
    invokevirtual dj e:(IB)V
    goto L38
L39
    ldc 109190397 (java.lang.Integer)
    getstatic hg hv:Ll;
    getfield l x:I
    imul
    iload 9
    isub
    bipush 7
    ishr
    istore 11
    goto L35
L20
    iload 3
    bipush 23
    if_icmpgt L16
    iload 2
    ldc 1522878182 (java.lang.Integer)
    if_icmpgt L24
    new java/lang/IllegalStateException
    dup
    invokespecial java/lang/IllegalStateException <init>:()V
    athrow
L36
    getstatic client cd:Ldj;
    bipush 18
    bipush -16
    invokevirtual dj e:(IB)V
L40
    getstatic client cd:Ldj;
    getstatic co cz:I
    ldc 1317226893 (java.lang.Integer)
    imul
    iload 11
    iadd
    ldc 1995852139 (java.lang.Integer)
    invokevirtual dj af:(II)V
    goto L21
L27
    iinc 4 -75
    goto L29
L23
    getstatic dr ce:[Z
    bipush 81
    baload
    ifeq L41
    iload 2
    ldc 1522878182 (java.lang.Integer)
    if_icmpgt L42
    new java/lang/IllegalStateException
    dup
    invokespecial java/lang/IllegalStateException <init>:()V
    athrow
L42
    iconst_2
    goto L43
L44
    getstatic client cd:Ldj;
    bipush 57
    bipush -11
    invokevirtual dj e:(IB)V
    goto L37
L22
    iconst_0
    goto L43
L30
    getstatic cp aw:[I
    iload 5
    iaload
    istore 6
    goto L33
L45
    getstatic client cd:Ldj;
    iload 10
    ldc 616886125 (java.lang.Integer)
    getstatic x cs:I
    imul
    iadd
    bipush -72
    invokevirtual dj a:(IB)V
L46
    getstatic client cd:Ldj;
    iload 3
    bipush -25
    invokevirtual dj e:(IB)V
    goto L4
L12
    ldc 1563808941 (java.lang.Integer)
    getstatic ep m:I
    imul
    iconst_5
    isub
    iload 1
    isub
    istore 4
    goto L14
L5
    getstatic client cd:Ldj;
    ldc 154136385 (java.lang.Integer)
    getstatic client fy:I
    imul
    bipush 20
    invokevirtual dj a:(IB)V
    goto L44
L47
    getstatic client cd:Ldj;
    ldc 1164900853 (java.lang.Integer)
    getstatic hg hv:Ll;
    getfield l b:I
    imul
    bipush -64
    invokevirtual dj a:(IB)V
    goto L48
L41
    iconst_1
    goto L43
L38
    getstatic client cd:Ldj;
    getstatic client ec:I
    ldc -981441773 (java.lang.Integer)
    imul
    bipush -101
    invokevirtual dj e:(IB)V
    goto L49
L7
    return
L32
    getstatic hg hv:Ll;
    getfield l b:I
    ldc 1164900853 (java.lang.Integer)
    imul
    iload 8
    iadd
    bipush 7
    ishr
    istore 10
    goto L39
L48
    getstatic client cd:Ldj;
    getstatic hg hv:Ll;
    getfield l x:I
    ldc 109190397 (java.lang.Integer)
    imul
    bipush -29
    invokevirtual dj a:(IB)V
L50
    getstatic client cd:Ldj;
    bipush 63
    bipush -56
    invokevirtual dj e:(IB)V
L51
    iload 10
    ldc -467606121 (java.lang.Integer)
    imul
    putstatic client mm:I
    goto L13
L49
    getstatic client cd:Ldj;
    bipush 89
    bipush 41
    invokevirtual dj e:(IB)V
    goto L47
L43
    ldc 110292168 (java.lang.Integer)
    invokevirtual dj at:(II)V
    goto L45
L52
    new java/lang/StringBuilder
    dup
    invokespecial java/lang/StringBuilder <init>:()V
    ldc "r.ap(" (java.lang.String)
    invokevirtual java/lang/StringBuilder append:(Ljava/lang/String;)Ljava/lang/StringBuilder;
    ldc 41 (java.lang.Integer)
    invokevirtual java/lang/StringBuilder append:(C)Ljava/lang/StringBuilder;
    invokevirtual java/lang/StringBuilder toString:()Ljava/lang/String;
    invokestatic k a:(Ljava/lang/Throwable;Ljava/lang/String;)Lee;
    athrow
