r cj (Lfb;II)IL1
    aconst_null
    aload 0
    getfield fb dh:[[I
    if_acmpeq L2
    iload 1
    aload 0
    getfield fb dh:[[I
    arraylength
    if_icmplt L3
    iload 2
    ldc -1285737891 (java.lang.Integer)
    if_icmpeq L2
    new java/lang/IllegalStateException
    dup
    invokespecial java/lang/IllegalStateException <init>:()V
    athrow
L2
    bipush -2
    ireturn
L3
    aload 0
    getfield fb dh:[[I
    iload 1
    aaload
    astore 3
L4
    iconst_0
    istore 4
L5
    iconst_0
    istore 5
L6
    iconst_0
    istore 6
L7
    aload 3
    iload 5
    iinc 5 1
    iaload
    istore 7
L8
    iconst_0
    istore 8
L9
    iconst_0
    istore 9
L10
    iconst_0
    iload 7
    if_icmpne L11
    iload 4
L12
    ireturn
L11
    iload 7
    iconst_1
    if_icmpne L13
    iload 2
    ldc -1285737891 (java.lang.Integer)
    if_icmpeq L14
    new java/lang/IllegalStateException
    dup
    invokespecial java/lang/IllegalStateException <init>:()V
    athrow
L14
    getstatic client hs:[I
    aload 3
    iload 5
    iinc 5 1
    iaload
    iaload
    istore 8
L13
    iconst_2
    iload 7
    if_icmpne L15
    iload 2
    ldc -1285737891 (java.lang.Integer)
    if_icmpeq L16
    new java/lang/IllegalStateException
    dup
    invokespecial java/lang/IllegalStateException <init>:()V
    athrow
L16
    getstatic client hu:[I
    aload 3
    iload 5
    iinc 5 1
    iaload
    iaload
    istore 8
L15
    iconst_3
    iload 7
    if_icmpne L17
    iload 2
    ldc -1285737891 (java.lang.Integer)
    if_icmpeq L18
    new java/lang/IllegalStateException
    dup
    invokespecial java/lang/IllegalStateException <init>:()V
    athrow
L18
    getstatic client hj:[I
    aload 3
    iload 5
    iinc 5 1
    iaload
    iaload
    istore 8
L17
    iload 7
    iconst_4
    if_icmpne L19
    iload 2
    ldc -1285737891 (java.lang.Integer)
    if_icmpeq L20
    new java/lang/IllegalStateException
    dup
    invokespecial java/lang/IllegalStateException <init>:()V
    athrow
L20
    aload 3
    iload 5
    iinc 5 1
    iaload
    bipush 16
    ishl
    istore 10
L21
    iload 10
    aload 3
    iload 5
    iinc 5 1
    iaload
    iadd
    istore 10
L22
    iload 10
    ldc -2068421293 (java.lang.Integer)
    invokestatic f a:(II)Lfb;
    astore 11
L23
    aload 3
    iload 5
    iinc 5 1
    iaload
    istore 12
L24
    iconst_m1
    iload 12
    if_icmpeq L19
    iload 2
    ldc -1285737891 (java.lang.Integer)
    if_icmpeq L25
    new java/lang/IllegalStateException
    dup
    invokespecial java/lang/IllegalStateException <init>:()V
    athrow
L25
    iload 12
    bipush 33
    invokestatic dj e:(IB)Lad;
    getfield ad ax:Z
    ifeq L26
    iload 2
    ldc -1285737891 (java.lang.Integer)
    if_icmpeq L27
    new java/lang/IllegalStateException
    dup
    invokespecial java/lang/IllegalStateException <init>:()V
    athrow
L27
    getstatic client o:Z
    ifeq L19
    iload 2
    ldc -1285737891 (java.lang.Integer)
    if_icmpeq L26
    new java/lang/IllegalStateException
    dup
    invokespecial java/lang/IllegalStateException <init>:()V
    athrow
L26
    iconst_0
    istore 13
L28
    iload 13
    aload 11
    getfield fb dv:[I
    arraylength
    if_icmpge L19
L29
    iload 12
    iconst_1
    iadd
    aload 11
    getfield fb dv:[I
    iload 13
    iaload
    if_icmpne L30
    iload 8
    aload 11
    getfield fb ds:[I
    iload 13
    iaload
    iadd
    istore 8
L30
    iinc 13 1
    goto L28
L19
    iload 7
    iconst_5
    if_icmpne L31
    iload 2
    ldc -1285737891 (java.lang.Integer)
    if_icmpeq L32
    new java/lang/IllegalStateException
    dup
    invokespecial java/lang/IllegalStateException <init>:()V
    athrow
L32
    getstatic fl l:[I
    aload 3
    iload 5
    iinc 5 1
    iaload
    iaload
    istore 8
L31
    iload 7
    bipush 6
    if_icmpne L33
    getstatic ei l:[I
    getstatic client hu:[I
    aload 3
    iload 5
    iinc 5 1
    iaload
    iaload
    iconst_1
    isub
    iaload
    istore 8
L33
    bipush 7
    iload 7
    if_icmpne L34
    iload 2
    ldc -1285737891 (java.lang.Integer)
    if_icmpeq L35
    new java/lang/IllegalStateException
    dup
    invokespecial java/lang/IllegalStateException <init>:()V
    athrow
L35
    getstatic fl l:[I
    aload 3
    iload 5
    iinc 5 1
    iaload
    iaload
    bipush 100
    imul
    ldc 46875 (java.lang.Integer)
    idiv
    istore 8
L34
    bipush 8
    iload 7
    if_icmpne L36
    iload 2
    ldc -1285737891 (java.lang.Integer)
    if_icmpeq L37
    new java/lang/IllegalStateException
    dup
    invokespecial java/lang/IllegalStateException <init>:()V
    athrow
L37
    getstatic hg hv:Ll;
    getfield l u:I
    ldc 1815897639 (java.lang.Integer)
    imul
    istore 8
L36
    iload 7
    bipush 9
    if_icmpne L38
    iload 2
    ldc -1285737891 (java.lang.Integer)
    if_icmpeq L39
    new java/lang/IllegalStateException
    dup
    invokespecial java/lang/IllegalStateException <init>:()V
    athrow
L39
    iconst_0
    istore 10
L40
    iload 10
    bipush 25
    if_icmpge L38
    iload 2
    ldc -1285737891 (java.lang.Integer)
    if_icmpeq L41
    new java/lang/IllegalStateException
    dup
    invokespecial java/lang/IllegalStateException <init>:()V
    athrow
L41
    getstatic ei a:[Z
    iload 10
    baload
    ifeq L42
    iload 2
    ldc -1285737891 (java.lang.Integer)
    if_icmpeq L43
    new java/lang/IllegalStateException
    dup
    invokespecial java/lang/IllegalStateException <init>:()V
    athrow
L43
    iload 8
    getstatic client hu:[I
    iload 10
    iaload
    iadd
    istore 8
L42
    iinc 10 1
    goto L40
L38
    bipush 10
    iload 7
    if_icmpne L44
    iload 2
    ldc -1285737891 (java.lang.Integer)
    if_icmpeq L45
    new java/lang/IllegalStateException
    dup
    invokespecial java/lang/IllegalStateException <init>:()V
    athrow
L45
    aload 3
    iload 5
    iinc 5 1
    iaload
    bipush 16
    ishl
    istore 10
L46
    iload 10
    aload 3
    iload 5
    iinc 5 1
    iaload
    iadd
    istore 10
L47
    iload 10
    ldc -2068421293 (java.lang.Integer)
    invokestatic f a:(II)Lfb;
    astore 11
L48
    aload 3
    iload 5
    iinc 5 1
    iaload
    istore 12
L49
    iconst_m1
    iload 12
    if_icmpeq L44
    iload 2
    ldc -1285737891 (java.lang.Integer)
    if_icmpeq L50
    new java/lang/IllegalStateException
    dup
    invokespecial java/lang/IllegalStateException <init>:()V
    athrow
L50
    iload 12
    bipush 76
    invokestatic dj e:(IB)Lad;
    getfield ad ax:Z
    ifeq L51
    iload 2
    ldc -1285737891 (java.lang.Integer)
    if_icmpeq L52
    new java/lang/IllegalStateException
    dup
    invokespecial java/lang/IllegalStateException <init>:()V
    athrow
L52
    getstatic client o:Z
    ifeq L44
    iload 2
    ldc -1285737891 (java.lang.Integer)
    if_icmpeq L51
    new java/lang/IllegalStateException
    dup
    invokespecial java/lang/IllegalStateException <init>:()V
    athrow
L51
    iconst_0
    istore 13
L53
    iload 13
    aload 11
    getfield fb dv:[I
    arraylength
    if_icmpge L44
    iload 2
    ldc -1285737891 (java.lang.Integer)
    if_icmpeq L54
    new java/lang/IllegalStateException
    dup
    invokespecial java/lang/IllegalStateException <init>:()V
    athrow
L54
    iload 12
    iconst_1
    iadd
    aload 11
    getfield fb dv:[I
    iload 13
    iaload
    if_icmpne L55
L56
    ldc 999999999 (java.lang.Integer)
    istore 8
L57
    goto L44
L55
    iinc 13 1
    goto L53
L44
    iload 7
    bipush 11
    if_icmpne L58
    iload 2
    ldc -1285737891 (java.lang.Integer)
    if_icmpeq L59
    new java/lang/IllegalStateException
    dup
    invokespecial java/lang/IllegalStateException <init>:()V
    athrow
L59
    getstatic client ji:I
    ldc -90505793 (java.lang.Integer)
    imul
    istore 8
L58
    bipush 12
    iload 7
    if_icmpne L60
    iload 2
    ldc -1285737891 (java.lang.Integer)
    if_icmpeq L61
    new java/lang/IllegalStateException
    dup
    invokespecial java/lang/IllegalStateException <init>:()V
    athrow
L61
    ldc 1061692207 (java.lang.Integer)
    getstatic client je:I
    imul
    istore 8
L60
    bipush 13
    iload 7
    if_icmpne L62
    iload 2
    ldc -1285737891 (java.lang.Integer)
    if_icmpeq L63
    new java/lang/IllegalStateException
    dup
    invokespecial java/lang/IllegalStateException <init>:()V
    athrow
L63
    getstatic fl l:[I
    aload 3
    iload 5
    iinc 5 1
    iaload
    iaload
    istore 10
L64
    aload 3
    iload 5
    iinc 5 1
    iaload
    istore 11
L65
    iload 10
    iconst_1
    iload 11
    ishl
    iand
    ifeq L66
    iload 2
    ldc -1285737891 (java.lang.Integer)
    if_icmpeq L67
    new java/lang/IllegalStateException
    dup
    invokespecial java/lang/IllegalStateException <init>:()V
    athrow
L67
    iconst_1
    goto L68
L66
    iconst_0
L68
    istore 8
L62
    iload 7
    bipush 14
    if_icmpne L69
    iload 2
    ldc -1285737891 (java.lang.Integer)
    if_icmpeq L70
    new java/lang/IllegalStateException
    dup
    invokespecial java/lang/IllegalStateException <init>:()V
    athrow
L70
    aload 3
    iload 5
    iinc 5 1
    iaload
    istore 10
L71
    iload 10
    ldc -39317852 (java.lang.Integer)
    invokestatic c e:(II)I
    istore 8
L69
    bipush 15
    iload 7
    if_icmpne L72
    iload 2
    ldc -1285737891 (java.lang.Integer)
    if_icmpeq L73
    new java/lang/IllegalStateException
    dup
    invokespecial java/lang/IllegalStateException <init>:()V
    athrow
L73
    iconst_1
    istore 9
L72
    iload 7
    bipush 16
    if_icmpne L74
    iload 2
    ldc -1285737891 (java.lang.Integer)
    if_icmpeq L75
    new java/lang/IllegalStateException
    dup
    invokespecial java/lang/IllegalStateException <init>:()V
    athrow
L75
    iconst_2
    istore 9
L74
    iload 7
    bipush 17
    if_icmpne L76
    iload 2
    ldc -1285737891 (java.lang.Integer)
    if_icmpeq L77
    new java/lang/IllegalStateException
    dup
    invokespecial java/lang/IllegalStateException <init>:()V
    athrow
L77
    iconst_3
    istore 9
L76
    iload 7
    bipush 18
    if_icmpne L78
    iload 2
    ldc -1285737891 (java.lang.Integer)
    if_icmpeq L79
    new java/lang/IllegalStateException
    dup
    invokespecial java/lang/IllegalStateException <init>:()V
    athrow
L79
    ldc 1164900853 (java.lang.Integer)
    getstatic hg hv:Ll;
    getfield l b:I
    imul
    bipush 7
    ishr
    ldc 616886125 (java.lang.Integer)
    getstatic x cs:I
    imul
    iadd
    istore 8
L78
    bipush 19
    iload 7
    if_icmpne L80
    iload 2
    ldc -1285737891 (java.lang.Integer)
    if_icmpeq L81
    new java/lang/IllegalStateException
    dup
    invokespecial java/lang/IllegalStateException <init>:()V
    athrow
L81
    getstatic hg hv:Ll;
    getfield l x:I
    ldc 109190397 (java.lang.Integer)
    imul
    bipush 7
    ishr
    getstatic co cz:I
    ldc 1317226893 (java.lang.Integer)
    imul
    iadd
    istore 8
L80
    bipush 20
    iload 7
    if_icmpne L82
    aload 3
    iload 5
    iinc 5 1
    iaload
    istore 8
L82
    iconst_0
    iload 9
    if_icmpne L83
    iload 2
    ldc -1285737891 (java.lang.Integer)
    if_icmpeq L84
    new java/lang/IllegalStateException
    dup
    invokespecial java/lang/IllegalStateException <init>:()V
    athrow
L84
    iconst_0
    iload 6
    if_icmpne L85
    iload 2
    ldc -1285737891 (java.lang.Integer)
    if_icmpeq L86
    new java/lang/IllegalStateException
    dup
    invokespecial java/lang/IllegalStateException <init>:()V
    athrow
L86
    iload 4
    iload 8
    iadd
    istore 4
L85
    iload 6
    iconst_1
    if_icmpne L87
    iload 2
    ldc -1285737891 (java.lang.Integer)
    if_icmpeq L88
    new java/lang/IllegalStateException
    dup
    invokespecial java/lang/IllegalStateException <init>:()V
    athrow
L88
    iload 4
    iload 8
    isub
    istore 4
L87
    iconst_2
    iload 6
    if_icmpne L89
    iload 2
    ldc -1285737891 (java.lang.Integer)
    if_icmpeq L90
    new java/lang/IllegalStateException
    dup
    invokespecial java/lang/IllegalStateException <init>:()V
    athrow
L90
    iload 8
    ifeq L89
    iload 2
    ldc -1285737891 (java.lang.Integer)
    if_icmpeq L91
    new java/lang/IllegalStateException
    dup
    invokespecial java/lang/IllegalStateException <init>:()V
    athrow
L91
    iload 4
    iload 8
    idiv
    istore 4
L89
    iload 6
    iconst_3
    if_icmpne L92
    iload 2
    ldc -1285737891 (java.lang.Integer)
    if_icmpeq L93
    new java/lang/IllegalStateException
    dup
    invokespecial java/lang/IllegalStateException <init>:()V
    athrow
L93
    iload 4
    iload 8
    imul
    istore 4
L92
    iconst_0
    istore 6
    goto L94
L83
    iload 9
    istore 6
L94
    goto L7
L95
    astore 3
L96
    iconst_m1
    ireturn
L97
    new java/lang/StringBuilder
    dup
    invokespecial java/lang/StringBuilder <init>:()V
    ldc "r.cj(" (java.lang.String)
    invokevirtual java/lang/StringBuilder append:(Ljava/lang/String;)Ljava/lang/StringBuilder;
    ldc 41 (java.lang.Integer)
    invokevirtual java/lang/StringBuilder append:(C)Ljava/lang/StringBuilder;
    invokevirtual java/lang/StringBuilder toString:()Ljava/lang/String;
    invokestatic k a:(Ljava/lang/Throwable;Ljava/lang/String;)Lee;
    athrow
