r g (Lew;B)VL1
    getstatic ep s:I
    ldc -1750678861 (java.lang.Integer)
    imul
    iconst_1
    if_icmpeq L2
    iload 1
    iconst_1
    if_icmplt L3
    new java/lang/IllegalStateException
    dup
    invokespecial java/lang/IllegalStateException <init>:()V
    athrow
L4
    sipush 390
    istore 3
    goto L5
L6
    ldc -1750678861 (java.lang.Integer)
    getstatic ep s:I
    imul
    iconst_4
    if_icmpne L7
    iload 1
    iconst_1
    if_icmplt L2
    new java/lang/IllegalStateException
    dup
    invokespecial java/lang/IllegalStateException <init>:()V
    athrow
L8
    getstatic ep m:I
    ldc 1563808941 (java.lang.Integer)
    imul
    iconst_4
    if_icmplt L9
    iload 1
    iconst_1
    if_icmplt L10
    new java/lang/IllegalStateException
    dup
    invokespecial java/lang/IllegalStateException <init>:()V
    athrow
L11
    ldc -642165313 (java.lang.Integer)
    getstatic ep j:I
    imul
    iload 4
    bipush 14
    iadd
    if_icmpgt L12
    iload 1
    iconst_1
    if_icmplt L13
    new java/lang/IllegalStateException
    dup
    invokespecial java/lang/IllegalStateException <init>:()V
    athrow
L14
    getstatic ep j:I
    ldc -642165313 (java.lang.Integer)
    imul
    iload 2
    bipush 14
    iadd
    if_icmpgt L9
    goto L8
L15
    getstatic ai w:Lbh;
    sipush 382
    iconst_0
    invokevirtual bh g:(II)V
    goto L16
L17
    return
L18
    iconst_0
    iconst_0
    bipush 91
    invokestatic i s:(IIB)V
L19
    return
L9
    getstatic ep j:I
    ldc -642165313 (java.lang.Integer)
    imul
    bipush 15
    iload 2
    iadd
    if_icmplt L4
    goto L20
L21
    getstatic fk u:Lbh;
    iconst_0
    iconst_0
    invokevirtual bh g:(II)V
    goto L22
L23
    getstatic ep m:I
    ldc 1563808941 (java.lang.Integer)
    imul
    iconst_4
    if_icmplt L4
    iload 1
    iconst_1
    if_icmplt L24
    new java/lang/IllegalStateException
    dup
    invokespecial java/lang/IllegalStateException <init>:()V
    athrow
L25
    return
L26
    iconst_0
    iconst_1
    bipush 27
    invokestatic i s:(IIB)V
L27
    return
L28
    ldc 1563808941 (java.lang.Integer)
    getstatic ep m:I
    imul
    bipush 18
    if_icmpgt L29
    goto L30
L20
    ldc -642165313 (java.lang.Integer)
    getstatic ep j:I
    imul
    bipush 80
    iload 2
    iadd
    if_icmpgt L4
    iload 1
    iconst_1
    if_icmplt L23
    return
L31
    getstatic ep j:I
    ldc -642165313 (java.lang.Integer)
    imul
    bipush 14
    iload 3
    iadd
    if_icmpgt L32
    getstatic ep m:I
    ldc 1563808941 (java.lang.Integer)
    imul
    iconst_4
    if_icmplt L32
    iload 1
    iconst_1
    if_icmplt L33
    new java/lang/IllegalStateException
    dup
    invokespecial java/lang/IllegalStateException <init>:()V
    athrow
L33
    ldc 1563808941 (java.lang.Integer)
    getstatic ep m:I
    imul
    bipush 18
    if_icmpgt L32
    iload 1
    iconst_1
    if_icmplt L34
    new java/lang/IllegalStateException
    dup
    invokespecial java/lang/IllegalStateException <init>:()V
    athrow
L35
    iconst_2
    iconst_1
    bipush 127
    invokestatic i s:(IIB)V
    goto L17
L36
    return
L32
    ldc -642165313 (java.lang.Integer)
    getstatic ep j:I
    imul
    bipush 15
    iload 3
    iadd
    if_icmplt L37
    iload 1
    iconst_1
    if_icmplt L38
    new java/lang/IllegalStateException
    dup
    invokespecial java/lang/IllegalStateException <init>:()V
    athrow
L38
    getstatic ep j:I
    ldc -642165313 (java.lang.Integer)
    imul
    iload 3
    bipush 80
    iadd
    if_icmpgt L37
    getstatic ep m:I
    ldc 1563808941 (java.lang.Integer)
    imul
    iconst_4
    if_icmplt L37
    goto L39
L3
    getstatic q at:Z
    ifne L7
    iload 1
    iconst_1
    if_icmplt L6
    new java/lang/IllegalStateException
    dup
    invokespecial java/lang/IllegalStateException <init>:()V
    athrow
L40
    iconst_1
    iconst_1
    bipush 49
    invokestatic i s:(IIB)V
L41
    return
L37
    sipush 500
    istore 4
    goto L42
L10
    getstatic ep m:I
    ldc 1563808941 (java.lang.Integer)
    imul
    bipush 18
    if_icmpgt L9
    iload 1
    iconst_1
    if_icmplt L18
    new java/lang/IllegalStateException
    dup
    invokespecial java/lang/IllegalStateException <init>:()V
    athrow
L12
    ldc -642165313 (java.lang.Integer)
    getstatic ep j:I
    imul
    iload 4
    bipush 15
    iadd
    if_icmplt L43
    iload 1
    iconst_1
    if_icmplt L44
    new java/lang/IllegalStateException
    dup
    invokespecial java/lang/IllegalStateException <init>:()V
    athrow
L13
    ldc 1563808941 (java.lang.Integer)
    getstatic ep m:I
    imul
    iconst_4
    if_icmplt L12
    iload 1
    iconst_1
    if_icmplt L45
    new java/lang/IllegalStateException
    dup
    invokespecial java/lang/IllegalStateException <init>:()V
    athrow
L45
    getstatic ep m:I
    ldc 1563808941 (java.lang.Integer)
    imul
    bipush 18
    if_icmpgt L12
L46
    iconst_2
    iconst_0
    bipush 72
    invokestatic i s:(IIB)V
    goto L25
L29
    ldc -642165313 (java.lang.Integer)
    getstatic ep j:I
    imul
    sipush 708
    if_icmplt L47
    iload 1
    iconst_1
    if_icmplt L48
    new java/lang/IllegalStateException
    dup
    invokespecial java/lang/IllegalStateException <init>:()V
    athrow
L49
    getstatic ep j:I
    ldc -642165313 (java.lang.Integer)
    imul
    iload 2
    if_icmplt L9
    iload 1
    iconst_1
    if_icmplt L14
    new java/lang/IllegalStateException
    dup
    invokespecial java/lang/IllegalStateException <init>:()V
    athrow
L43
    sipush 610
    istore 5
    goto L50
L51
    ldc 1563808941 (java.lang.Integer)
    getstatic ep m:I
    imul
    iconst_4
    if_icmplt L43
    ldc 1563808941 (java.lang.Integer)
    getstatic ep m:I
    imul
    bipush 18
    if_icmpgt L43
    goto L35
L34
    iconst_1
    iconst_0
    bipush 62
    invokestatic i s:(IIB)V
    goto L36
L5
    getstatic ep j:I
    ldc -642165313 (java.lang.Integer)
    imul
    iload 3
    if_icmplt L32
    iload 1
    iconst_1
    if_icmplt L31
    new java/lang/IllegalStateException
    dup
    invokespecial java/lang/IllegalStateException <init>:()V
    athrow
L30
    iconst_3
    iconst_1
    bipush 53
    invokestatic i s:(IIB)V
    goto L52
L53
    return
L54
    ldc -642165313 (java.lang.Integer)
    getstatic ep j:I
    imul
    iload 5
    bipush 14
    iadd
    if_icmpgt L55
    iload 1
    iconst_1
    if_icmplt L56
    new java/lang/IllegalStateException
    dup
    invokespecial java/lang/IllegalStateException <init>:()V
    athrow
L56
    getstatic ep m:I
    ldc 1563808941 (java.lang.Integer)
    imul
    iconst_4
    if_icmplt L55
    iload 1
    iconst_1
    if_icmplt L57
    new java/lang/IllegalStateException
    dup
    invokespecial java/lang/IllegalStateException <init>:()V
    athrow
L57
    ldc 1563808941 (java.lang.Integer)
    getstatic ep m:I
    imul
    bipush 18
    if_icmpgt L55
    iload 1
    iconst_1
    if_icmplt L58
    new java/lang/IllegalStateException
    dup
    invokespecial java/lang/IllegalStateException <init>:()V
    athrow
L58
    iconst_3
    iconst_0
    bipush 119
    invokestatic i s:(IIB)V
L59
    return
L55
    ldc -642165313 (java.lang.Integer)
    getstatic ep j:I
    imul
    iload 5
    bipush 15
    iadd
    if_icmplt L29
    iload 1
    iconst_1
    if_icmplt L60
    new java/lang/IllegalStateException
    dup
    invokespecial java/lang/IllegalStateException <init>:()V
    athrow
L60
    ldc -642165313 (java.lang.Integer)
    getstatic ep j:I
    imul
    bipush 80
    iload 5
    iadd
    if_icmpgt L29
    iload 1
    iconst_1
    if_icmplt L61
    return
L2
    sipush 280
    istore 2
    goto L49
L24
    ldc 1563808941 (java.lang.Integer)
    getstatic ep m:I
    imul
    bipush 18
    if_icmpgt L4
    iload 1
    iconst_1
    if_icmplt L26
    new java/lang/IllegalStateException
    dup
    invokespecial java/lang/IllegalStateException <init>:()V
    athrow
L42
    getstatic ep j:I
    ldc -642165313 (java.lang.Integer)
    imul
    iload 4
    if_icmplt L12
    iload 1
    iconst_1
    if_icmplt L11
    new java/lang/IllegalStateException
    dup
    invokespecial java/lang/IllegalStateException <init>:()V
    athrow
L44
    getstatic ep j:I
    ldc -642165313 (java.lang.Integer)
    imul
    bipush 80
    iload 4
    iadd
    if_icmpgt L43
    iload 1
    iconst_1
    if_icmplt L51
    new java/lang/IllegalStateException
    dup
    invokespecial java/lang/IllegalStateException <init>:()V
    athrow
L62
    getstatic ev i:Lbs;
    sipush 382
    getstatic ev i:Lbs;
    getfield bs l:I
    iconst_2
    idiv
    isub
    bipush 18
    invokevirtual bs l:(II)V
    goto L63
L48
    getstatic ep m:I
    ldc 1563808941 (java.lang.Integer)
    imul
    iconst_4
    if_icmplt L47
    goto L64
L61
    getstatic ep m:I
    ldc 1563808941 (java.lang.Integer)
    imul
    iconst_4
    if_icmplt L29
    iload 1
    iconst_1
    if_icmplt L28
    new java/lang/IllegalStateException
    dup
    invokespecial java/lang/IllegalStateException <init>:()V
    athrow
L65
    getstatic ep m:I
    ldc 1563808941 (java.lang.Integer)
    imul
    bipush 20
    if_icmpgt L47
    iload 1
    iconst_1
    if_icmplt L66
    new java/lang/IllegalStateException
    dup
    invokespecial java/lang/IllegalStateException <init>:()V
    athrow
L66
    iconst_0
    putstatic ai ad:Z
    goto L21
L64
    ldc -642165313 (java.lang.Integer)
    getstatic ep j:I
    imul
    sipush 758
    if_icmpgt L47
    goto L65
L22
    getstatic ai w:Lbh;
    sipush 382
    iconst_0
    invokevirtual bh g:(II)V
    goto L62
L52
    return
L63
    return
L47
    ldc 1135247203 (java.lang.Integer)
    getstatic ai bu:I
    imul
    iconst_m1
    if_icmpeq L7
    iload 1
    iconst_1
    if_icmplt L67
    new java/lang/IllegalStateException
    dup
    invokespecial java/lang/IllegalStateException <init>:()V
    athrow
L67
    getstatic b bm:[Lv;
    ldc 1135247203 (java.lang.Integer)
    getstatic ai bu:I
    imul
    aaload
    astore 6
L68
    aload 6
    ldc -383629132 (java.lang.Integer)
    invokestatic ak o:(Lv;I)V
L69
    iconst_0
    putstatic ai ad:Z
L70
    getstatic fk u:Lbh;
    iconst_0
    iconst_0
    invokevirtual bh g:(II)V
    goto L15
L50
    getstatic ep j:I
    ldc -642165313 (java.lang.Integer)
    imul
    iload 5
    if_icmplt L55
    iload 1
    iconst_1
    if_icmplt L54
    return
L16
    getstatic ev i:Lbs;
    sipush 382
    getstatic ev i:Lbs;
    getfield bs l:I
    iconst_2
    idiv
    isub
    bipush 18
    invokevirtual bs l:(II)V
    goto L53
L39
    getstatic ep m:I
    ldc 1563808941 (java.lang.Integer)
    imul
    bipush 18
    if_icmpgt L37
    iload 1
    iconst_1
    if_icmplt L40
    new java/lang/IllegalStateException
    dup
    invokespecial java/lang/IllegalStateException <init>:()V
    athrow
L7
    return
L71
    new java/lang/StringBuilder
    dup
    invokespecial java/lang/StringBuilder <init>:()V
    ldc "r.g(" (java.lang.String)
    invokevirtual java/lang/StringBuilder append:(Ljava/lang/String;)Ljava/lang/StringBuilder;
    ldc 41 (java.lang.Integer)
    invokevirtual java/lang/StringBuilder append:(C)Ljava/lang/StringBuilder;
    invokevirtual java/lang/StringBuilder toString:()Ljava/lang/String;
    invokestatic k a:(Ljava/lang/Throwable;Ljava/lang/String;)Lee;
    athrow
