s r (Lfv;Lfv;Ljava/lang/String;Ljava/lang/String;I)Lhh;L1
    aload 0
    aload 2
    ldc 372779710 (java.lang.Integer)
    invokevirtual fv y:(Ljava/lang/String;I)I
    istore 5
    goto L2
L3
    aload 0
    iload 5
    iload 6
    ldc 660647799 (java.lang.Integer)
    invokestatic ax h:(Lfv;III)Z
    ifne L4
    iload 4
    ldc -197160885 (java.lang.Integer)
    if_icmplt L5
    new java/lang/IllegalStateException
    dup
    invokespecial java/lang/IllegalStateException <init>:()V
    athrow
L6
    goto L7
L5
    aconst_null
    astore 7
    goto L6
L4
    aload 1
    iload 5
    iload 6
    ldc -1601295013 (java.lang.Integer)
    invokevirtual fv l:(III)[B
    ldc 1690342691 (java.lang.Integer)
    invokestatic l o:([BI)Lhh;
    astore 7
    goto L7
L2
    aload 0
    iload 5
    aload 3
    sipush 20606
    invokevirtual fv q:(ILjava/lang/String;S)I
    istore 6
    goto L3
L7
    aload 7
    areturn
L8
    new java/lang/StringBuilder
    dup
    invokespecial java/lang/StringBuilder <init>:()V
    ldc "s.r(" (java.lang.String)
    invokevirtual java/lang/StringBuilder append:(Ljava/lang/String;)Ljava/lang/StringBuilder;
    ldc 41 (java.lang.Integer)
    invokevirtual java/lang/StringBuilder append:(C)Ljava/lang/StringBuilder;
    invokevirtual java/lang/StringBuilder toString:()Ljava/lang/String;
    invokestatic k a:(Ljava/lang/Throwable;Ljava/lang/String;)Lee;
    athrow
