t bw (Lt;B)VL1
    iconst_0
    istore 2
    goto L2
L3
    iconst_1
    aload 0
    getfield t a:I
    ldc -834255021 (java.lang.Integer)
    imul
    if_icmpne L4
    goto L5
L6
    iconst_0
    istore 4
L7
    iconst_0
    istore 5
    goto L8
L9
    aload 0
    getfield t a:I
    ldc -834255021 (java.lang.Integer)
    imul
    iconst_3
    if_icmpne L10
    iload 1
    iconst_1
    if_icmpeq L11
    return
L12
    getstatic n ds:Lcb;
    aload 0
    getfield t e:I
    ldc -1751944705 (java.lang.Integer)
    imul
    aload 0
    getfield t l:I
    ldc -1506352819 (java.lang.Integer)
    imul
    ldc -1485218469 (java.lang.Integer)
    aload 0
    getfield t c:I
    imul
    invokevirtual cb ax:(III)I
    istore 2
    goto L3
L13
    getstatic n ds:Lcb;
    aload 0
    getfield t e:I
    ldc -1751944705 (java.lang.Integer)
    imul
    aload 0
    getfield t l:I
    ldc -1506352819 (java.lang.Integer)
    imul
    ldc -1485218469 (java.lang.Integer)
    aload 0
    getfield t c:I
    imul
    iload 2
    invokevirtual cb aw:(IIII)I
    istore 6
    goto L14
L5
    getstatic n ds:Lcb;
    ldc -1751944705 (java.lang.Integer)
    aload 0
    getfield t e:I
    imul
    aload 0
    getfield t l:I
    ldc -1506352819 (java.lang.Integer)
    imul
    aload 0
    getfield t c:I
    ldc -1485218469 (java.lang.Integer)
    imul
    invokevirtual cb ap:(III)I
    istore 2
    goto L4
L15
    iload 6
    bipush 31
    iand
    istore 4
    goto L16
L2
    iconst_m1
    istore 3
    goto L6
L17
    getstatic n ds:Lcb;
    ldc -1751944705 (java.lang.Integer)
    aload 0
    getfield t e:I
    imul
    ldc -1506352819 (java.lang.Integer)
    aload 0
    getfield t l:I
    imul
    aload 0
    getfield t c:I
    ldc -1485218469 (java.lang.Integer)
    imul
    invokevirtual cb ao:(III)I
    istore 2
    goto L9
L4
    aload 0
    getfield t a:I
    ldc -834255021 (java.lang.Integer)
    imul
    iconst_2
    if_icmpne L9
    iload 1
    iconst_1
    if_icmpeq L17
    new java/lang/IllegalStateException
    dup
    invokespecial java/lang/IllegalStateException <init>:()V
    athrow
L18
    aload 0
    iload 4
    ldc 790232049 (java.lang.Integer)
    imul
    putfield t i:I
    goto L19
L11
    getstatic n ds:Lcb;
    ldc -1751944705 (java.lang.Integer)
    aload 0
    getfield t e:I
    imul
    ldc -1506352819 (java.lang.Integer)
    aload 0
    getfield t l:I
    imul
    ldc -1485218469 (java.lang.Integer)
    aload 0
    getfield t c:I
    imul
    invokevirtual cb ai:(III)I
    istore 2
    goto L10
L14
    iload 2
    bipush 14
    ishr
    sipush 32767
    iand
    istore 3
    goto L15
L16
    iload 6
    bipush 6
    ishr
    iconst_3
    iand
    istore 5
    goto L20
L8
    iconst_0
    aload 0
    getfield t a:I
    ldc -834255021 (java.lang.Integer)
    imul
    if_icmpne L3
    iload 1
    iconst_1
    if_icmpeq L12
    new java/lang/IllegalStateException
    dup
    invokespecial java/lang/IllegalStateException <init>:()V
    athrow
L20
    aload 0
    iload 3
    ldc 1954871241 (java.lang.Integer)
    imul
    putfield t u:I
    goto L18
L10
    iconst_0
    iload 2
    if_icmpeq L20
    iload 1
    iconst_1
    if_icmpeq L13
    new java/lang/IllegalStateException
    dup
    invokespecial java/lang/IllegalStateException <init>:()V
    athrow
L19
    aload 0
    ldc -138574865 (java.lang.Integer)
    iload 5
    imul
    putfield t w:I
L21
    return
L22
    new java/lang/StringBuilder
    dup
    invokespecial java/lang/StringBuilder <init>:()V
    ldc "t.bw(" (java.lang.String)
    invokevirtual java/lang/StringBuilder append:(Ljava/lang/String;)Ljava/lang/StringBuilder;
    ldc 41 (java.lang.Integer)
    invokevirtual java/lang/StringBuilder append:(C)Ljava/lang/StringBuilder;
    invokevirtual java/lang/StringBuilder toString:()Ljava/lang/String;
    invokestatic k a:(Ljava/lang/Throwable;Ljava/lang/String;)Lee;
    athrow
