u aj (ZI)VL1
    iconst_0
    istore 2
L2
    iload 2
    getstatic client ch:I
    ldc -1048248787 (java.lang.Integer)
    imul
    if_icmpge L3
    iload 1
    ldc 1259711054 (java.lang.Integer)
    if_icmpne L4
    new java/lang/IllegalStateException
    dup
    invokespecial java/lang/IllegalStateException <init>:()V
    athrow
L4
    getstatic client cf:[Lam;
    getstatic client cb:[I
    iload 2
    iaload
    aaload
    astore 3
    goto L5
L6
    aload 3
    ifnull L7
    goto L8
L7
    iinc 2 1
    goto L2
L9
    aload 3
    getfield am e:Lay;
    getfield ay k:Z
    iload 0
    if_icmpne L7
    goto L10
L11
    iconst_1
    ldc 1291018633 (java.lang.Integer)
    aload 3
    getfield am p:I
    imul
    if_icmpne L12
    iload 1
    ldc 1259711054 (java.lang.Integer)
    if_icmpne L13
    return
L10
    aload 3
    getfield am e:Lay;
    ldc -1473350869 (java.lang.Integer)
    invokevirtual ay r:(I)Z
    ifeq L7
    iload 1
    ldc 1259711054 (java.lang.Integer)
    if_icmpne L14
    new java/lang/IllegalStateException
    dup
    invokespecial java/lang/IllegalStateException <init>:()V
    athrow
L14
    ldc 1164900853 (java.lang.Integer)
    aload 3
    getfield am b:I
    imul
    bipush 7
    ishr
    istore 5
L15
    aload 3
    getfield am x:I
    ldc 109190397 (java.lang.Integer)
    imul
    bipush 7
    ishr
    istore 6
L16
    iload 5
    iflt L7
    iload 1
    ldc 1259711054 (java.lang.Integer)
    if_icmpne L17
    new java/lang/IllegalStateException
    dup
    invokespecial java/lang/IllegalStateException <init>:()V
    athrow
L17
    iload 5
    bipush 104
    if_icmpge L7
    iload 1
    ldc 1259711054 (java.lang.Integer)
    if_icmpne L18
    return
L18
    iload 6
    iflt L7
    iload 1
    ldc 1259711054 (java.lang.Integer)
    if_icmpne L19
    return
L5
    getstatic client cb:[I
    iload 2
    iaload
    bipush 14
    ishl
    ldc 536870912 (java.lang.Integer)
    iadd
    istore 4
    goto L6
L19
    iload 6
    bipush 104
    if_icmpge L7
    iload 1
    ldc 1259711054 (java.lang.Integer)
    if_icmpne L11
    return
L13
    bipush 64
    ldc 1164900853 (java.lang.Integer)
    aload 3
    getfield am b:I
    imul
    bipush 127
    iand
    if_icmpne L12
    iload 1
    ldc 1259711054 (java.lang.Integer)
    if_icmpne L20
    return
L20
    bipush 64
    aload 3
    getfield am x:I
    ldc 109190397 (java.lang.Integer)
    imul
    bipush 127
    iand
    if_icmpne L12
    iload 1
    ldc 1259711054 (java.lang.Integer)
    if_icmpne L21
    new java/lang/IllegalStateException
    dup
    invokespecial java/lang/IllegalStateException <init>:()V
    athrow
L21
    ldc 1549434003 (java.lang.Integer)
    getstatic client gn:I
    imul
    getstatic client go:[[I
    iload 5
    aaload
    iload 6
    iaload
    if_icmpne L22
    goto L7
L22
    getstatic client go:[[I
    iload 5
    aaload
    iload 6
    getstatic client gn:I
    ldc 1549434003 (java.lang.Integer)
    imul
    iastore
    goto L12
L8
    aload 3
    ldc 1627470340 (java.lang.Integer)
    invokevirtual am l:(I)Z
    ifeq L7
    iload 1
    ldc 1259711054 (java.lang.Integer)
    if_icmpne L9
    return
L23
    iload 4
    ldc -2147483648 (java.lang.Integer)
    isub
    istore 4
L24
    getstatic n ds:Lcb;
    getstatic fd hz:I
    ldc -837647185 (java.lang.Integer)
    imul
    aload 3
    getfield am b:I
    ldc 1164900853 (java.lang.Integer)
    imul
    aload 3
    getfield am x:I
    ldc 109190397 (java.lang.Integer)
    imul
    ldc 1020813888 (java.lang.Integer)
    aload 3
    getfield am p:I
    imul
    bipush 64
    isub
    ldc 1164900853 (java.lang.Integer)
    aload 3
    getfield am b:I
    imul
    iadd
    ldc 1020813888 (java.lang.Integer)
    aload 3
    getfield am p:I
    imul
    bipush 64
    isub
    aload 3
    getfield am x:I
    ldc 109190397 (java.lang.Integer)
    imul
    iadd
    getstatic fd hz:I
    ldc -837647185 (java.lang.Integer)
    imul
    ldc 1958062732 (java.lang.Integer)
    invokestatic cl ar:(IIII)I
    bipush 60
    ldc 1020813888 (java.lang.Integer)
    aload 3
    getfield am p:I
    imul
    bipush 64
    isub
    iadd
    aload 3
    aload 3
    getfield am n:I
    ldc 1741660775 (java.lang.Integer)
    imul
    iload 4
    aload 3
    getfield am v:Z
    invokevirtual cb h:(IIIIILch;IIZ)Z
    pop
    goto L7
L12
    aload 3
    getfield am e:Lay;
    getfield ay ae:Z
    ifne L24
    iload 1
    ldc 1259711054 (java.lang.Integer)
    if_icmpne L23
    new java/lang/IllegalStateException
    dup
    invokespecial java/lang/IllegalStateException <init>:()V
    athrow
L3
    return
L25
    new java/lang/StringBuilder
    dup
    invokespecial java/lang/StringBuilder <init>:()V
    ldc "u.aj(" (java.lang.String)
    invokevirtual java/lang/StringBuilder append:(Ljava/lang/String;)Ljava/lang/StringBuilder;
    ldc 41 (java.lang.Integer)
    invokevirtual java/lang/StringBuilder append:(C)Ljava/lang/StringBuilder;
    invokevirtual java/lang/StringBuilder toString:()Ljava/lang/String;
    invokestatic k a:(Ljava/lang/Throwable;Ljava/lang/String;)Lee;
    athrow
