v ae (Lab;I)VL1
    iconst_0
    ldc -913616539 (java.lang.Integer)
    aload 0
    getfield ab bh:I
    imul
    if_icmpne L2
    goto L3
L4
    iconst_0
    iload 4
    if_icmpeq L5
    iload 1
    ldc 195560510 (java.lang.Integer)
    if_icmpgt L6
    return
L2
    iconst_m1
    aload 0
    getfield ab ad:I
    ldc -522366309 (java.lang.Integer)
    imul
    if_icmpeq L5
    iload 1
    ldc 195560510 (java.lang.Integer)
    if_icmpgt L7
    new java/lang/IllegalStateException
    dup
    invokespecial java/lang/IllegalStateException <init>:()V
    athrow
L3
    return
L8
    getstatic client cf:[Lam;
    ldc -522366309 (java.lang.Integer)
    aload 0
    getfield ab ad:I
    imul
    aaload
    astore 2
    goto L9
L10
    aload 0
    iconst_0
    putfield ab az:I
    goto L11
L12
    aload 0
    ldc -1437200415 (java.lang.Integer)
    aload 0
    getfield ab by:I
    imul
    putfield ab n:I
    goto L13
L14
    aload 0
    iload 4
    i2d
    iload 5
    i2d
    invokestatic java/lang/Math atan2:(DD)D
    ldc 325.949 (java.lang.Double)
    dmul
    d2i
    sipush 2047
    iand
    ldc 441905207 (java.lang.Integer)
    imul
    putfield ab by:I
    goto L15
L16
    iconst_0
    iload 3
    if_icmpne L6
    iload 1
    ldc 195560510 (java.lang.Integer)
    if_icmpgt L4
    return
L17
    aload 0
    getfield ab ax:I
    ldc 1870934095 (java.lang.Integer)
    imul
    iconst_m1
    if_icmpeq L18
    iload 1
    ldc 195560510 (java.lang.Integer)
    if_icmpgt L19
    return
L6
    aload 0
    iload 3
    i2d
    iload 4
    i2d
    invokestatic java/lang/Math atan2:(DD)D
    ldc 325.949 (java.lang.Double)
    dmul
    d2i
    sipush 2047
    iand
    ldc 441905207 (java.lang.Integer)
    imul
    putfield ab by:I
L5
    ldc -522366309 (java.lang.Integer)
    aload 0
    getfield ab ad:I
    imul
    ldc 32768 (java.lang.Integer)
    if_icmplt L15
    iload 1
    ldc 195560510 (java.lang.Integer)
    if_icmpgt L20
    new java/lang/IllegalStateException
    dup
    invokespecial java/lang/IllegalStateException <init>:()V
    athrow
L20
    aload 0
    getfield ab ad:I
    ldc -522366309 (java.lang.Integer)
    imul
    ldc 32768 (java.lang.Integer)
    isub
    istore 2
    goto L21
L22
    ldc -445968203 (java.lang.Integer)
    aload 0
    getfield ab bz:I
    imul
    bipush 25
    if_icmpgt L23
    iload 1
    ldc 195560510 (java.lang.Integer)
    if_icmpgt L24
    return
L25
    return
L26
    getstatic client hg:[Ll;
    iload 2
    aaload
    astore 3
L27
    aload 3
    ifnull L15
L28
    aload 0
    getfield ab b:I
    ldc 1164900853 (java.lang.Integer)
    imul
    aload 3
    getfield l b:I
    ldc 1164900853 (java.lang.Integer)
    imul
    isub
    istore 4
L29
    ldc 109190397 (java.lang.Integer)
    aload 0
    getfield ab x:I
    imul
    aload 3
    getfield l x:I
    ldc 109190397 (java.lang.Integer)
    imul
    isub
    istore 5
L30
    iload 4
    ifne L14
    iload 1
    ldc 195560510 (java.lang.Integer)
    if_icmpgt L31
    new java/lang/IllegalStateException
    dup
    invokespecial java/lang/IllegalStateException <init>:()V
    athrow
L31
    iload 5
    ifeq L15
    iload 1
    ldc 195560510 (java.lang.Integer)
    if_icmpgt L14
    new java/lang/IllegalStateException
    dup
    invokespecial java/lang/IllegalStateException <init>:()V
    athrow
L32
    ldc -445968203 (java.lang.Integer)
    aload 0
    getfield ab bz:I
    imul
    bipush 25
    if_icmpgt L17
    iload 1
    ldc 195560510 (java.lang.Integer)
    if_icmpgt L33
    new java/lang/IllegalStateException
    dup
    invokespecial java/lang/IllegalStateException <init>:()V
    athrow
L34
    iload 2
    aload 0
    getfield ab bh:I
    ldc -913616539 (java.lang.Integer)
    imul
    if_icmplt L12
    iload 1
    ldc 195560510 (java.lang.Integer)
    if_icmpgt L35
    new java/lang/IllegalStateException
    dup
    invokespecial java/lang/IllegalStateException <init>:()V
    athrow
L36
    iconst_0
    ldc 1589467783 (java.lang.Integer)
    aload 0
    getfield ab az:I
    imul
    if_icmpeq L11
L37
    iconst_0
    ldc -426846849 (java.lang.Integer)
    aload 0
    getfield ab bt:I
    imul
    if_icmpeq L38
    ldc 1823185993 (java.lang.Integer)
    aload 0
    getfield ab cf:I
    imul
    ifle L11
    iload 1
    ldc 195560510 (java.lang.Integer)
    if_icmpgt L38
    new java/lang/IllegalStateException
    dup
    invokespecial java/lang/IllegalStateException <init>:()V
    athrow
L38
    aload 0
    getfield ab b:I
    ldc 1164900853 (java.lang.Integer)
    imul
    aload 0
    getfield ab an:I
    ldc 567809984 (java.lang.Integer)
    imul
    getstatic x cs:I
    ldc 826006336 (java.lang.Integer)
    imul
    isub
    ldc 826006336 (java.lang.Integer)
    getstatic x cs:I
    imul
    isub
    isub
    istore 2
L39
    aload 0
    getfield ab x:I
    ldc 109190397 (java.lang.Integer)
    imul
    aload 0
    getfield ab az:I
    ldc -1353276992 (java.lang.Integer)
    imul
    getstatic co cz:I
    ldc -1596824768 (java.lang.Integer)
    imul
    isub
    getstatic co cz:I
    ldc -1596824768 (java.lang.Integer)
    imul
    isub
    isub
    istore 3
L40
    iload 2
    ifne L41
    iconst_0
    iload 3
    if_icmpeq L42
    iload 1
    ldc 195560510 (java.lang.Integer)
    if_icmpgt L41
    return
L41
    aload 0
    iload 2
    i2d
    iload 3
    i2d
    invokestatic java/lang/Math atan2:(DD)D
    ldc 325.949 (java.lang.Double)
    dmul
    d2i
    sipush 2047
    iand
    ldc 441905207 (java.lang.Integer)
    imul
    putfield ab by:I
L42
    aload 0
    iconst_0
    putfield ab an:I
    goto L10
L43
    aload 0
    dup
    getfield ab n:I
    aload 0
    getfield ab bh:I
    ldc -1296906669 (java.lang.Integer)
    imul
    isub
    putfield ab n:I
    goto L44
L11
    ldc 1553712519 (java.lang.Integer)
    aload 0
    getfield ab by:I
    imul
    aload 0
    getfield ab n:I
    ldc 1741660775 (java.lang.Integer)
    imul
    isub
    sipush 2047
    iand
    istore 2
    goto L45
L7
    aload 0
    getfield ab ad:I
    ldc -522366309 (java.lang.Integer)
    imul
    ldc 32768 (java.lang.Integer)
    if_icmpge L5
    iload 1
    ldc 195560510 (java.lang.Integer)
    if_icmpgt L8
    return
L46
    aload 0
    dup
    getfield ab bz:I
    ldc 55664029 (java.lang.Integer)
    iadd
    putfield ab bz:I
    goto L47
L23
    aload 0
    getfield ab ap:I
    ldc -1087853277 (java.lang.Integer)
    imul
    iconst_m1
    if_icmpeq L48
    goto L49
L18
    aload 0
    ldc -257616741 (java.lang.Integer)
    aload 0
    getfield ab ao:I
    imul
    putfield ab af:I
    goto L50
L44
    iconst_1
    istore 3
    goto L34
L51
    iload 2
    sipush 2048
    ldc -913616539 (java.lang.Integer)
    aload 0
    getfield ab bh:I
    imul
    isub
    if_icmple L52
    goto L53
L35
    iload 2
    sipush 2048
    ldc -913616539 (java.lang.Integer)
    aload 0
    getfield ab bh:I
    imul
    isub
    if_icmple L54
    goto L12
L47
    iload 2
    sipush 1024
    if_icmple L55
    iload 1
    ldc 195560510 (java.lang.Integer)
    if_icmpgt L43
    new java/lang/IllegalStateException
    dup
    invokespecial java/lang/IllegalStateException <init>:()V
    athrow
L13
    iconst_0
    istore 3
    goto L54
L48
    aload 0
    aload 0
    getfield ab ao:I
    ldc -257616741 (java.lang.Integer)
    imul
    putfield ab af:I
    goto L56
L45
    iload 2
    ifeq L57
    iload 1
    ldc 195560510 (java.lang.Integer)
    if_icmpgt L46
    new java/lang/IllegalStateException
    dup
    invokespecial java/lang/IllegalStateException <init>:()V
    athrow
L33
    iload 3
    ifeq L50
    iload 1
    ldc 195560510 (java.lang.Integer)
    if_icmpgt L17
    new java/lang/IllegalStateException
    dup
    invokespecial java/lang/IllegalStateException <init>:()V
    athrow
L58
    goto L25
L19
    aload 0
    aload 0
    getfield ab ax:I
    ldc 1432237913 (java.lang.Integer)
    imul
    putfield ab af:I
    goto L50
L57
    aload 0
    iconst_0
    putfield ab bz:I
    goto L25
L50
    goto L56
L55
    aload 0
    dup
    getfield ab n:I
    aload 0
    getfield ab bh:I
    ldc -1296906669 (java.lang.Integer)
    imul
    iadd
    putfield ab n:I
L59
    iconst_1
    istore 3
L60
    iload 2
    aload 0
    getfield ab bh:I
    ldc -913616539 (java.lang.Integer)
    imul
    if_icmplt L53
    iload 1
    ldc 195560510 (java.lang.Integer)
    if_icmpgt L51
    new java/lang/IllegalStateException
    dup
    invokespecial java/lang/IllegalStateException <init>:()V
    athrow
L54
    aload 0
    getfield ab af:I
    ldc 1931040743 (java.lang.Integer)
    imul
    aload 0
    getfield ab k:I
    ldc 140905021 (java.lang.Integer)
    imul
    if_icmpne L50
    iload 1
    ldc 195560510 (java.lang.Integer)
    if_icmpgt L32
    new java/lang/IllegalStateException
    dup
    invokespecial java/lang/IllegalStateException <init>:()V
    athrow
L49
    aload 0
    aload 0
    getfield ab ap:I
    ldc 1503865189 (java.lang.Integer)
    imul
    putfield ab af:I
    goto L56
L61
    iconst_0
    istore 3
L52
    ldc 1931040743 (java.lang.Integer)
    aload 0
    getfield ab af:I
    imul
    ldc 140905021 (java.lang.Integer)
    aload 0
    getfield ab k:I
    imul
    if_icmpne L56
    iload 1
    ldc 195560510 (java.lang.Integer)
    if_icmpgt L22
    new java/lang/IllegalStateException
    dup
    invokespecial java/lang/IllegalStateException <init>:()V
    athrow
L62
    sipush 2047
    istore 2
    goto L26
L24
    iload 3
    ifeq L56
    iload 1
    ldc 195560510 (java.lang.Integer)
    if_icmpgt L23
    new java/lang/IllegalStateException
    dup
    invokespecial java/lang/IllegalStateException <init>:()V
    athrow
L21
    getstatic client ht:I
    ldc 1958675107 (java.lang.Integer)
    imul
    iload 2
    if_icmpne L26
    iload 1
    ldc 195560510 (java.lang.Integer)
    if_icmpgt L62
    new java/lang/IllegalStateException
    dup
    invokespecial java/lang/IllegalStateException <init>:()V
    athrow
L63
    aload 0
    getfield ab x:I
    ldc 109190397 (java.lang.Integer)
    imul
    ldc 109190397 (java.lang.Integer)
    aload 2
    getfield am x:I
    imul
    isub
    istore 4
    goto L16
L53
    aload 0
    ldc -1437200415 (java.lang.Integer)
    aload 0
    getfield ab by:I
    imul
    putfield ab n:I
    goto L61
L56
    aload 0
    dup
    astore 3
    ldc 1995856215 (java.lang.Integer)
    ldc 1741660775 (java.lang.Integer)
    aload 3
    getfield ab n:I
    imul
    sipush 2047
    iand
    imul
    putfield ab n:I
    goto L58
L15
    iconst_0
    aload 0
    getfield ab an:I
    ldc 881287263 (java.lang.Integer)
    imul
    if_icmpne L37
    iload 1
    ldc 195560510 (java.lang.Integer)
    if_icmpgt L36
    return
L64
    aload 0
    getfield ab b:I
    ldc 1164900853 (java.lang.Integer)
    imul
    aload 2
    getfield am b:I
    ldc 1164900853 (java.lang.Integer)
    imul
    isub
    istore 3
    goto L63
L9
    aconst_null
    aload 2
    if_acmpeq L5
    goto L64
L65
    new java/lang/StringBuilder
    dup
    invokespecial java/lang/StringBuilder <init>:()V
    ldc "v.ae(" (java.lang.String)
    invokevirtual java/lang/StringBuilder append:(Ljava/lang/String;)Ljava/lang/StringBuilder;
    ldc 41 (java.lang.Integer)
    invokevirtual java/lang/StringBuilder append:(C)Ljava/lang/StringBuilder;
    invokevirtual java/lang/StringBuilder toString:()Ljava/lang/String;
    invokestatic k a:(Ljava/lang/Throwable;Ljava/lang/String;)Lee;
    athrow
