v aw (Lab;IS)VL1
    ldc 1585316651 (java.lang.Integer)
    aload 0
    getfield ab bb:I
    imul
    getstatic client b:I
    ldc -117546507 (java.lang.Integer)
    imul
    if_icmple L2
    iload 2
    sipush 1600
    if_icmpne L3
    new java/lang/IllegalStateException
    dup
    invokespecial java/lang/IllegalStateException <init>:()V
    athrow
L4
    ldc -117546507 (java.lang.Integer)
    getstatic client b:I
    imul
    ldc 959944223 (java.lang.Integer)
    aload 0
    getfield ab br:I
    imul
    if_icmplt L5
    iload 2
    sipush 1600
    if_icmpne L6
    new java/lang/IllegalStateException
    dup
    invokespecial java/lang/IllegalStateException <init>:()V
    athrow
L7
    iconst_m1
    aload 0
    getfield ab bl:I
    ldc 1048158519 (java.lang.Integer)
    imul
    if_icmpeq L8
    iload 2
    sipush 1600
    if_icmpne L9
    new java/lang/IllegalStateException
    dup
    invokespecial java/lang/IllegalStateException <init>:()V
    athrow
L10
    aload 0
    bipush -9
    invokestatic cq au:(Lab;B)V
    goto L11
L12
    aload 0
    iconst_0
    putfield ab bj:I
    goto L13
L14
    ldc -426846849 (java.lang.Integer)
    aload 0
    getfield ab bt:I
    imul
    ifne L7
    iload 2
    sipush 1600
    if_icmpne L15
    new java/lang/IllegalStateException
    dup
    invokespecial java/lang/IllegalStateException <init>:()V
    athrow
L15
    aload 0
    iconst_0
    putfield ab cf:I
L16
    goto L11
L17
    iload 7
    sipush -256
    if_icmplt L18
    iload 2
    sipush 1600
    if_icmpne L19
    new java/lang/IllegalStateException
    dup
    invokespecial java/lang/IllegalStateException <init>:()V
    athrow
L9
    aload 0
    getfield ab bw:I
    ldc -1613918591 (java.lang.Integer)
    imul
    ifne L8
    iload 2
    sipush 1600
    if_icmpne L20
    new java/lang/IllegalStateException
    dup
    invokespecial java/lang/IllegalStateException <init>:()V
    athrow
L20
    aload 0
    getfield ab bl:I
    ldc 1048158519 (java.lang.Integer)
    imul
    ldc 152969838 (java.lang.Integer)
    invokestatic cd e:(II)Lah;
    astore 3
L21
    ldc 176322769 (java.lang.Integer)
    aload 0
    getfield ab ch:I
    imul
    ifle L22
    iload 2
    sipush 1600
    if_icmpne L23
    new java/lang/IllegalStateException
    dup
    invokespecial java/lang/IllegalStateException <init>:()V
    athrow
L24
    aload 0
    getfield ab x:I
    ldc 109190397 (java.lang.Integer)
    imul
    iload 6
    if_icmpge L25
    iload 2
    sipush 1600
    if_icmpne L26
    new java/lang/IllegalStateException
    dup
    invokespecial java/lang/IllegalStateException <init>:()V
    athrow
L23
    aload 3
    getfield ah z:I
    ldc -106389737 (java.lang.Integer)
    imul
    ifne L22
    iload 2
    sipush 1600
    if_icmpne L27
    new java/lang/IllegalStateException
    dup
    invokespecial java/lang/IllegalStateException <init>:()V
    athrow
L28
    goto L11
L22
    ldc 176322769 (java.lang.Integer)
    aload 0
    getfield ab ch:I
    imul
    ifgt L8
    iload 2
    sipush 1600
    if_icmpne L29
    new java/lang/IllegalStateException
    dup
    invokespecial java/lang/IllegalStateException <init>:()V
    athrow
L30
    aload 0
    ldc 161565184 (java.lang.Integer)
    putfield ab by:I
    goto L31
L32
    aload 0
    dup
    getfield ab cf:I
    ldc 824907257 (java.lang.Integer)
    iadd
    putfield ab cf:I
L33
    goto L11
L8
    aload 0
    getfield ab b:I
    ldc 1164900853 (java.lang.Integer)
    imul
    istore 3
L34
    ldc 109190397 (java.lang.Integer)
    aload 0
    getfield ab x:I
    imul
    istore 4
L35
    aload 0
    getfield ab bs:[I
    ldc -426846849 (java.lang.Integer)
    aload 0
    getfield ab bt:I
    imul
    iconst_1
    isub
    iaload
    sipush 128
    imul
    aload 0
    getfield ab p:I
    ldc 1020813888 (java.lang.Integer)
    imul
    iadd
    istore 5
L36
    ldc 1020813888 (java.lang.Integer)
    aload 0
    getfield ab p:I
    imul
    sipush 128
    aload 0
    getfield ab bo:[I
    ldc -426846849 (java.lang.Integer)
    aload 0
    getfield ab bt:I
    imul
    iconst_1
    isub
    iaload
    imul
    iadd
    istore 6
L37
    iload 5
    iload 3
    isub
    sipush 256
    if_icmpgt L38
    iload 5
    iload 3
    isub
    sipush -256
    if_icmplt L38
    iload 2
    sipush 1600
    if_icmpne L39
    return
L40
    aload 0
    ldc -2003952775 (java.lang.Integer)
    putfield ab bl:I
    goto L41
L42
    iload 6
    iload 4
    isub
    sipush -256
    if_icmpge L43
    iload 2
    sipush 1600
    if_icmpne L38
    new java/lang/IllegalStateException
    dup
    invokespecial java/lang/IllegalStateException <init>:()V
    athrow
L38
    aload 0
    iload 5
    ldc 1306077789 (java.lang.Integer)
    imul
    putfield ab b:I
L44
    aload 0
    ldc 1172037717 (java.lang.Integer)
    iload 6
    imul
    putfield ab x:I
L45
    goto L11
L43
    iload 3
    iload 5
    if_icmpge L46
    iload 2
    sipush 1600
    if_icmpne L47
    return
L47
    iload 4
    iload 6
    if_icmpge L48
    iload 2
    sipush 1600
    if_icmpne L49
    new java/lang/IllegalStateException
    dup
    invokespecial java/lang/IllegalStateException <init>:()V
    athrow
L50
    iload 10
    ifeq L51
    iload 2
    sipush 1600
    if_icmpne L52
    new java/lang/IllegalStateException
    dup
    invokespecial java/lang/IllegalStateException <init>:()V
    athrow
L53
    aload 0
    dup
    getfield ab bt:I
    ldc 453175935 (java.lang.Integer)
    isub
    putfield ab bt:I
    goto L54
L55
    aload 0
    ldc 1620148480 (java.lang.Integer)
    putfield ab by:I
    goto L31
L56
    aload 0
    getfield ab bw:I
    ldc -1613918591 (java.lang.Integer)
    imul
    iconst_1
    if_icmpgt L57
    iload 2
    sipush 1600
    if_icmpne L58
    new java/lang/IllegalStateException
    dup
    invokespecial java/lang/IllegalStateException <init>:()V
    athrow
L46
    iload 3
    iload 5
    if_icmple L59
    iload 2
    sipush 1600
    if_icmpne L60
    new java/lang/IllegalStateException
    dup
    invokespecial java/lang/IllegalStateException <init>:()V
    athrow
L60
    iload 4
    iload 6
    if_icmpge L61
    goto L62
L63
    aload 3
    aload 0
    getfield ab as:I
    ldc -17018627 (java.lang.Integer)
    imul
    ldc 1164900853 (java.lang.Integer)
    aload 0
    getfield ab b:I
    imul
    aload 0
    getfield ab x:I
    ldc 109190397 (java.lang.Integer)
    imul
    ldc 1797324181 (java.lang.Integer)
    invokestatic gt p:(Lah;IIII)V
    goto L64
L65
    aload 0
    ldc -276694981 (java.lang.Integer)
    aload 0
    getfield ab k:I
    imul
    putfield ab af:I
    goto L14
L66
    aload 0
    dup
    getfield ab b:I
    iload 9
    ldc 1306077789 (java.lang.Integer)
    imul
    iadd
    putfield ab b:I
    goto L67
L68
    aload 0
    ldc -1377800704 (java.lang.Integer)
    putfield ab by:I
    goto L31
L69
    aload 0
    ldc 1425265329 (java.lang.Integer)
    putfield ab be:I
    goto L70
L71
    bipush 8
    istore 9
    goto L72
L73
    iload 4
    iload 6
    if_icmple L31
    iload 2
    sipush 1600
    if_icmpne L74
    new java/lang/IllegalStateException
    dup
    invokespecial java/lang/IllegalStateException <init>:()V
    athrow
L74
    aload 0
    iconst_0
    putfield ab by:I
    goto L31
L18
    iload 7
    sipush 256
    if_icmplt L75
    iload 2
    sipush 1600
    if_icmpne L76
    new java/lang/IllegalStateException
    dup
    invokespecial java/lang/IllegalStateException <init>:()V
    athrow
L77
    iload 7
    sipush 1024
    if_icmple L78
    iload 2
    sipush 1600
    if_icmpne L79
    new java/lang/IllegalStateException
    dup
    invokespecial java/lang/IllegalStateException <init>:()V
    athrow
L58
    aload 0
    getfield ab bl:I
    ldc 1048158519 (java.lang.Integer)
    imul
    ldc 152969838 (java.lang.Integer)
    invokestatic cd e:(II)Lah;
    astore 3
    goto L80
L81
    aload 0
    getfield ab ao:I
    ldc -484883235 (java.lang.Integer)
    imul
    istore 8
    goto L82
L83
    ldc -426846849 (java.lang.Integer)
    aload 0
    getfield ab bt:I
    imul
    iconst_3
    if_icmple L84
    iload 2
    sipush 1600
    if_icmpne L85
    new java/lang/IllegalStateException
    dup
    invokespecial java/lang/IllegalStateException <init>:()V
    athrow
L86
    aload 3
    aload 0
    getfield ab bk:I
    ldc -166629429 (java.lang.Integer)
    imul
    ldc 1164900853 (java.lang.Integer)
    aload 0
    getfield ab b:I
    imul
    aload 0
    getfield ab x:I
    ldc 109190397 (java.lang.Integer)
    imul
    ldc 1797324181 (java.lang.Integer)
    invokestatic gt p:(Lah;IIII)V
    goto L41
L87
    aload 0
    getfield ab be:I
    ldc 147245487 (java.lang.Integer)
    imul
    iconst_m1
    if_icmpeq L5
    iload 2
    sipush 1600
    if_icmpne L4
    return
L88
    aload 0
    getfield ab au:I
    ldc -715260025 (java.lang.Integer)
    imul
    iconst_m1
    if_icmpeq L89
    iload 2
    sipush 1600
    if_icmpne L90
    new java/lang/IllegalStateException
    dup
    invokespecial java/lang/IllegalStateException <init>:()V
    athrow
L76
    iload 7
    sipush 768
    if_icmpge L75
    iload 2
    sipush 1600
    if_icmpne L91
    new java/lang/IllegalStateException
    dup
    invokespecial java/lang/IllegalStateException <init>:()V
    athrow
L91
    aload 0
    getfield ab am:I
    ldc 655273413 (java.lang.Integer)
    imul
    istore 8
    goto L92
L75
    iload 7
    sipush -768
    if_icmplt L92
    iload 2
    sipush 1600
    if_icmpne L93
    new java/lang/IllegalStateException
    dup
    invokespecial java/lang/IllegalStateException <init>:()V
    athrow
L93
    iload 7
    sipush -256
    if_icmpgt L92
    iload 2
    sipush 1600
    if_icmpne L94
    return
L94
    aload 0
    getfield ab aw:I
    ldc 1759795763 (java.lang.Integer)
    imul
    istore 8
    goto L92
L95
    aload 3
    ifnull L96
    iload 2
    sipush 1600
    if_icmpne L97
    new java/lang/IllegalStateException
    dup
    invokespecial java/lang/IllegalStateException <init>:()V
    athrow
L49
    aload 0
    ldc -1297018112 (java.lang.Integer)
    putfield ab by:I
    goto L31
L82
    aload 0
    ldc -1635398697 (java.lang.Integer)
    iload 8
    imul
    putfield ab af:I
L98
    iconst_4
    istore 9
L99
    iconst_1
    istore 10
L100
    aload 0
    instanceof am
    ifeq L50
    iload 2
    sipush 1600
    if_icmpne L101
    new java/lang/IllegalStateException
    dup
    invokespecial java/lang/IllegalStateException <init>:()V
    athrow
L101
    aload 0
    checkcast am
    getfield am e:Lay;
    getfield ay ab:Z
    istore 10
    goto L50
L27
    aload 0
    dup
    getfield ab cf:I
    ldc 824907257 (java.lang.Integer)
    iadd
    putfield ab cf:I
    goto L28
L48
    iload 4
    iload 6
    if_icmple L30
    iload 2
    sipush 1600
    if_icmpne L55
    new java/lang/IllegalStateException
    dup
    invokespecial java/lang/IllegalStateException <init>:()V
    athrow
L102
    aload 0
    getfield ab ad:I
    ldc -522366309 (java.lang.Integer)
    imul
    iconst_m1
    if_icmpne L103
    iload 2
    sipush 1600
    if_icmpne L104
    new java/lang/IllegalStateException
    dup
    invokespecial java/lang/IllegalStateException <init>:()V
    athrow
L29
    aload 3
    getfield ah y:I
    ldc 687350469 (java.lang.Integer)
    imul
    ifne L8
    goto L32
L105
    iconst_2
    istore 9
    goto L103
L106
    aload 0
    ldc -2003952775 (java.lang.Integer)
    putfield ab bl:I
    goto L69
L107
    bipush 6
    istore 9
    goto L83
L108
    aload 0
    ldc 1425265329 (java.lang.Integer)
    putfield ab be:I
    goto L109
L85
    bipush 8
    istore 9
L84
    aload 0
    getfield ab cf:I
    ldc 1823185993 (java.lang.Integer)
    imul
    ifle L110
    ldc -426846849 (java.lang.Integer)
    aload 0
    getfield ab bt:I
    imul
    iconst_1
    if_icmple L110
    iload 2
    sipush 1600
    if_icmpne L111
    return
L111
    bipush 8
    istore 9
L112
    aload 0
    dup
    getfield ab cf:I
    ldc 824907257 (java.lang.Integer)
    isub
    putfield ab cf:I
    goto L110
L113
    aload 4
    ldc -1055712757 (java.lang.Integer)
    aload 0
    getfield ab bv:I
    imul
    aload 0
    getfield ab b:I
    ldc 1164900853 (java.lang.Integer)
    imul
    ldc 109190397 (java.lang.Integer)
    aload 0
    getfield ab x:I
    imul
    ldc 1797324181 (java.lang.Integer)
    invokestatic gt p:(Lah;IIII)V
    goto L114
L115
    bipush 6
    istore 9
L116
    aload 0
    getfield ab bt:I
    ldc -426846849 (java.lang.Integer)
    imul
    iconst_2
    if_icmple L117
    iload 2
    sipush 1600
    if_icmpne L118
    new java/lang/IllegalStateException
    dup
    invokespecial java/lang/IllegalStateException <init>:()V
    athrow
L119
    aload 0
    dup
    getfield ab x:I
    ldc 1172037717 (java.lang.Integer)
    iload 9
    imul
    iadd
    putfield ab x:I
    goto L120
L117
    aload 0
    getfield ab cf:I
    ldc 1823185993 (java.lang.Integer)
    imul
    ifle L110
    iload 2
    sipush 1600
    if_icmpne L121
    return
L121
    ldc -426846849 (java.lang.Integer)
    aload 0
    getfield ab bt:I
    imul
    iconst_1
    if_icmple L110
    iload 2
    sipush 1600
    if_icmpne L71
    new java/lang/IllegalStateException
    dup
    invokespecial java/lang/IllegalStateException <init>:()V
    athrow
L52
    ldc 1741660775 (java.lang.Integer)
    aload 0
    getfield ab n:I
    imul
    ldc 1553712519 (java.lang.Integer)
    aload 0
    getfield ab by:I
    imul
    if_icmpeq L103
    goto L102
L72
    aload 0
    dup
    getfield ab cf:I
    ldc 824907257 (java.lang.Integer)
    isub
    putfield ab cf:I
    goto L110
L103
    ldc -426846849 (java.lang.Integer)
    aload 0
    getfield ab bt:I
    imul
    iconst_2
    if_icmple L83
    iload 2
    sipush 1600
    if_icmpne L107
    new java/lang/IllegalStateException
    dup
    invokespecial java/lang/IllegalStateException <init>:()V
    athrow
L122
    iload 9
    iconst_1
    ishl
    istore 9
L123
    iload 9
    bipush 8
    if_icmplt L89
    iload 2
    sipush 1600
    if_icmpne L124
    new java/lang/IllegalStateException
    dup
    invokespecial java/lang/IllegalStateException <init>:()V
    athrow
L124
    aload 0
    getfield ab af:I
    ldc 1931040743 (java.lang.Integer)
    imul
    ldc -484883235 (java.lang.Integer)
    aload 0
    getfield ab ao:I
    imul
    if_icmpne L89
    iload 2
    sipush 1600
    if_icmpne L88
    new java/lang/IllegalStateException
    dup
    invokespecial java/lang/IllegalStateException <init>:()V
    athrow
L26
    aload 0
    iload 6
    ldc 1172037717 (java.lang.Integer)
    imul
    putfield ab x:I
    goto L25
L90
    aload 0
    ldc -827021471 (java.lang.Integer)
    aload 0
    getfield ab au:I
    imul
    putfield ab af:I
L89
    iload 3
    iload 5
    if_icmpge L125
    iload 2
    sipush 1600
    if_icmpne L66
    new java/lang/IllegalStateException
    dup
    invokespecial java/lang/IllegalStateException <init>:()V
    athrow
L126
    ldc -166629429 (java.lang.Integer)
    aload 0
    getfield ab bk:I
    imul
    iflt L40
    iload 2
    sipush 1600
    if_icmpne L127
    new java/lang/IllegalStateException
    dup
    invokespecial java/lang/IllegalStateException <init>:()V
    athrow
L67
    ldc 1164900853 (java.lang.Integer)
    aload 0
    getfield ab b:I
    imul
    iload 5
    if_icmple L128
    iload 2
    sipush 1600
    if_icmpne L129
    return
L129
    aload 0
    ldc 1306077789 (java.lang.Integer)
    iload 5
    imul
    putfield ab b:I
    goto L128
L125
    iload 3
    iload 5
    if_icmple L128
    iload 2
    sipush 1600
    if_icmpne L130
    new java/lang/IllegalStateException
    dup
    invokespecial java/lang/IllegalStateException <init>:()V
    athrow
L130
    aload 0
    dup
    getfield ab b:I
    iload 9
    ldc 1306077789 (java.lang.Integer)
    imul
    isub
    putfield ab b:I
L131
    ldc 1164900853 (java.lang.Integer)
    aload 0
    getfield ab b:I
    imul
    iload 5
    if_icmpge L128
    aload 0
    iload 5
    ldc 1306077789 (java.lang.Integer)
    imul
    putfield ab b:I
L128
    iload 4
    iload 6
    if_icmpge L132
    goto L119
L70
    aload 0
    iconst_0
    putfield ab bb:I
    goto L133
L120
    aload 0
    getfield ab x:I
    ldc 109190397 (java.lang.Integer)
    imul
    iload 6
    if_icmple L25
    iload 2
    sipush 1600
    if_icmpne L134
    new java/lang/IllegalStateException
    dup
    invokespecial java/lang/IllegalStateException <init>:()V
    athrow
L97
    aconst_null
    aload 3
    getfield ah w:[I
    if_acmpeq L96
    iload 2
    sipush 1600
    if_icmpne L135
    return
L136
    aload 0
    getfield ab x:I
    ldc 109190397 (java.lang.Integer)
    imul
    sipush 13184
    if_icmplt L137
    iload 2
    sipush 1600
    if_icmpne L106
    new java/lang/IllegalStateException
    dup
    invokespecial java/lang/IllegalStateException <init>:()V
    athrow
L138
    aload 0
    dup
    getfield ab x:I
    ldc 1172037717 (java.lang.Integer)
    iload 9
    imul
    isub
    putfield ab x:I
    goto L24
L139
    aload 0
    getfield ab x:I
    ldc 109190397 (java.lang.Integer)
    imul
    sipush 128
    if_icmplt L106
    iload 2
    sipush 1600
    if_icmpne L140
    new java/lang/IllegalStateException
    dup
    invokespecial java/lang/IllegalStateException <init>:()V
    athrow
L59
    iload 4
    iload 6
    if_icmpge L73
    iload 2
    sipush 1600
    if_icmpne L141
    new java/lang/IllegalStateException
    dup
    invokespecial java/lang/IllegalStateException <init>:()V
    athrow
L51
    aload 0
    getfield ab bt:I
    ldc -426846849 (java.lang.Integer)
    imul
    iconst_1
    if_icmple L116
    iload 2
    sipush 1600
    if_icmpne L115
    return
L142
    aload 0
    ldc -576750765 (java.lang.Integer)
    putfield ab bc:I
    goto L143
L144
    aload 0
    getfield ab bv:I
    ldc -1055712757 (java.lang.Integer)
    imul
    aload 4
    getfield ah w:[I
    arraylength
    if_icmplt L109
    iload 2
    sipush 1600
    if_icmpne L108
    return
L104
    aload 0
    getfield ab bh:I
    ldc -913616539 (java.lang.Integer)
    imul
    ifeq L103
    iload 2
    sipush 1600
    if_icmpne L105
    new java/lang/IllegalStateException
    dup
    invokespecial java/lang/IllegalStateException <init>:()V
    athrow
L145
    aload 0
    getfield ab bv:I
    ldc -1055712757 (java.lang.Integer)
    imul
    iflt L108
    goto L144
L146
    aload 3
    ldc -17018627 (java.lang.Integer)
    aload 0
    getfield ab as:I
    imul
    ldc 1164900853 (java.lang.Integer)
    aload 0
    getfield ab b:I
    imul
    ldc 109190397 (java.lang.Integer)
    aload 0
    getfield ab x:I
    imul
    ldc 1797324181 (java.lang.Integer)
    invokestatic gt p:(Lah;IIII)V
    goto L87
L147
    aload 0
    getfield ab x:I
    ldc 109190397 (java.lang.Integer)
    imul
    sipush 11776
    if_icmplt L148
    iload 2
    sipush 1600
    if_icmpne L149
    new java/lang/IllegalStateException
    dup
    invokespecial java/lang/IllegalStateException <init>:()V
    athrow
L140
    aload 0
    getfield ab b:I
    ldc 1164900853 (java.lang.Integer)
    imul
    sipush 13184
    if_icmpge L106
    iload 2
    sipush 1600
    if_icmpne L136
    new java/lang/IllegalStateException
    dup
    invokespecial java/lang/IllegalStateException <init>:()V
    athrow
L13
    aload 0
    ldc 586821952 (java.lang.Integer)
    aload 0
    getfield ab p:I
    imul
    aload 0
    getfield ab bs:[I
    iconst_0
    iaload
    ldc -325767552 (java.lang.Integer)
    imul
    iadd
    putfield ab b:I
    goto L150
L39
    iload 6
    iload 4
    isub
    sipush 256
    if_icmpgt L38
    iload 2
    sipush 1600
    if_icmpne L42
    new java/lang/IllegalStateException
    dup
    invokespecial java/lang/IllegalStateException <init>:()V
    athrow
L19
    iload 7
    sipush 256
    if_icmpgt L18
    iload 2
    sipush 1600
    if_icmpne L151
    return
L25
    aload 0
    getfield ab b:I
    ldc 1164900853 (java.lang.Integer)
    imul
    iload 5
    if_icmpne L11
    iload 2
    sipush 1600
    if_icmpne L152
    new java/lang/IllegalStateException
    dup
    invokespecial java/lang/IllegalStateException <init>:()V
    athrow
L133
    aload 0
    iconst_0
    putfield ab bj:I
L153
    aload 0
    aload 0
    getfield ab p:I
    ldc 586821952 (java.lang.Integer)
    imul
    aload 0
    getfield ab bs:[I
    iconst_0
    iaload
    ldc -325767552 (java.lang.Integer)
    imul
    iadd
    putfield ab b:I
L154
    aload 0
    aload 0
    getfield ab p:I
    ldc -695165120 (java.lang.Integer)
    imul
    aload 0
    getfield ab bo:[I
    iconst_0
    iaload
    ldc -303027584 (java.lang.Integer)
    imul
    iadd
    putfield ab x:I
    goto L155
L54
    aload 0
    getfield ab ch:I
    ldc 176322769 (java.lang.Integer)
    imul
    ifle L11
    iload 2
    sipush 1600
    if_icmpne L156
    return
L137
    aload 0
    getstatic hg hv:Ll;
    if_acmpne L148
    iload 2
    sipush 1600
    if_icmpne L157
    new java/lang/IllegalStateException
    dup
    invokespecial java/lang/IllegalStateException <init>:()V
    athrow
L157
    ldc 1164900853 (java.lang.Integer)
    aload 0
    getfield ab b:I
    imul
    sipush 1536
    if_icmplt L149
    iload 2
    sipush 1600
    if_icmpne L158
    new java/lang/IllegalStateException
    dup
    invokespecial java/lang/IllegalStateException <init>:()V
    athrow
L159
    iconst_0
    aload 0
    getfield ab bw:I
    ldc -1613918591 (java.lang.Integer)
    imul
    if_icmpne L160
    iload 2
    sipush 1600
    if_icmpne L161
    new java/lang/IllegalStateException
    dup
    invokespecial java/lang/IllegalStateException <init>:()V
    athrow
L162
    aload 0
    ldc 1458583296 (java.lang.Integer)
    putfield ab by:I
    goto L31
L155
    aload 0
    ldc -2027115078 (java.lang.Integer)
    invokevirtual ab y:(I)V
    goto L137
L149
    aload 0
    ldc -2003952775 (java.lang.Integer)
    putfield ab bl:I
L163
    aload 0
    ldc 1425265329 (java.lang.Integer)
    putfield ab be:I
    goto L164
L78
    ldc 743519679 (java.lang.Integer)
    aload 0
    getfield ab ai:I
    imul
    istore 8
    goto L17
L165
    aload 0
    getfield ab bc:I
    ldc 880312539 (java.lang.Integer)
    imul
    aload 4
    getfield ah r:[I
    aload 0
    getfield ab bv:I
    ldc -1055712757 (java.lang.Integer)
    imul
    iaload
    if_icmple L114
    goto L142
L166
    aload 0
    dup
    getfield ab bp:I
    ldc -1059423029 (java.lang.Integer)
    iadd
    putfield ab bp:I
    goto L167
L150
    aload 0
    aload 0
    getfield ab p:I
    ldc -695165120 (java.lang.Integer)
    imul
    aload 0
    getfield ab bo:[I
    iconst_0
    iaload
    ldc -303027584 (java.lang.Integer)
    imul
    iadd
    putfield ab x:I
L168
    aload 0
    ldc -2027115078 (java.lang.Integer)
    invokevirtual ab y:(I)V
    goto L148
L152
    iload 6
    aload 0
    getfield ab x:I
    ldc 109190397 (java.lang.Integer)
    imul
    if_icmpne L11
    iload 2
    sipush 1600
    if_icmpne L53
    return
L169
    ldc 1585316651 (java.lang.Integer)
    aload 0
    getfield ab bb:I
    imul
    ldc -117546507 (java.lang.Integer)
    getstatic client b:I
    imul
    if_icmpgt L57
    iload 2
    sipush 1600
    if_icmpne L170
    new java/lang/IllegalStateException
    dup
    invokespecial java/lang/IllegalStateException <init>:()V
    athrow
L171
    iconst_m1
    aload 0
    getfield ab af:I
    ldc 1931040743 (java.lang.Integer)
    imul
    if_icmpeq L87
    iload 2
    sipush 1600
    if_icmpne L172
    new java/lang/IllegalStateException
    dup
    invokespecial java/lang/IllegalStateException <init>:()V
    athrow
L172
    aload 0
    getfield ab af:I
    ldc 1931040743 (java.lang.Integer)
    imul
    ldc 152969838 (java.lang.Integer)
    invokestatic cd e:(II)Lah;
    astore 3
    goto L95
L79
    iinc 7 -2048
    goto L78
L151
    aload 0
    getfield ab ao:I
    ldc -484883235 (java.lang.Integer)
    imul
    istore 8
    goto L92
L135
    aload 0
    dup
    getfield ab aa:I
    ldc 2046778665 (java.lang.Integer)
    iadd
    putfield ab aa:I
L173
    aload 0
    getfield ab as:I
    ldc -17018627 (java.lang.Integer)
    imul
    aload 3
    getfield ah w:[I
    arraylength
    if_icmpge L64
    ldc 1670811417 (java.lang.Integer)
    aload 0
    getfield ab aa:I
    imul
    aload 3
    getfield ah r:[I
    aload 0
    getfield ab as:I
    ldc -17018627 (java.lang.Integer)
    imul
    iaload
    if_icmple L64
    iload 2
    sipush 1600
    if_icmpne L174
    return
L174
    aload 0
    ldc 2046778665 (java.lang.Integer)
    putfield ab aa:I
L175
    aload 0
    dup
    getfield ab as:I
    ldc 1028017237 (java.lang.Integer)
    iadd
    putfield ab as:I
    goto L63
L141
    aload 0
    ldc 1539365888 (java.lang.Integer)
    putfield ab by:I
    goto L31
L176
    aload 0
    iconst_0
    putfield ab v:Z
    goto L171
L177
    aload 0
    iconst_0
    putfield ab aa:I
    goto L178
L31
    ldc 1553712519 (java.lang.Integer)
    aload 0
    getfield ab by:I
    imul
    aload 0
    getfield ab n:I
    ldc 1741660775 (java.lang.Integer)
    imul
    isub
    sipush 2047
    iand
    istore 7
    goto L77
L156
    aload 0
    dup
    getfield ab ch:I
    ldc 1917902897 (java.lang.Integer)
    isub
    putfield ab ch:I
    goto L11
L96
    aload 0
    ldc 1635398697 (java.lang.Integer)
    putfield ab af:I
    goto L87
L158
    aload 0
    getfield ab x:I
    ldc 109190397 (java.lang.Integer)
    imul
    sipush 1536
    if_icmplt L149
    iload 2
    sipush 1600
    if_icmpne L179
    return
L180
    aload 0
    ldc -2003952775 (java.lang.Integer)
    putfield ab bl:I
    goto L160
L6
    aload 0
    getfield ab bv:I
    ldc -1055712757 (java.lang.Integer)
    imul
    ifge L181
    iload 2
    sipush 1600
    if_icmpne L182
    return
L182
    aload 0
    iconst_0
    putfield ab bv:I
L181
    aload 0
    getfield ab be:I
    ldc 147245487 (java.lang.Integer)
    imul
    ldc -1840890086 (java.lang.Integer)
    invokestatic ez a:(II)Lat;
    getfield at i:I
    ldc -332207823 (java.lang.Integer)
    imul
    istore 3
L183
    iload 3
    iconst_m1
    if_icmpeq L184
    iload 2
    sipush 1600
    if_icmpne L185
    return
L185
    iload 3
    ldc 152969838 (java.lang.Integer)
    invokestatic cd e:(II)Lah;
    astore 4
L186
    aconst_null
    aload 4
    if_acmpeq L187
    iload 2
    sipush 1600
    if_icmpne L188
    new java/lang/IllegalStateException
    dup
    invokespecial java/lang/IllegalStateException <init>:()V
    athrow
L188
    aload 4
    getfield ah w:[I
    ifnull L187
    iload 2
    sipush 1600
    if_icmpne L189
    new java/lang/IllegalStateException
    dup
    invokespecial java/lang/IllegalStateException <init>:()V
    athrow
L189
    aload 0
    dup
    getfield ab bc:I
    ldc -576750765 (java.lang.Integer)
    iadd
    putfield ab bc:I
L190
    ldc -1055712757 (java.lang.Integer)
    aload 0
    getfield ab bv:I
    imul
    aload 4
    getfield ah w:[I
    arraylength
    if_icmpge L114
    goto L165
L148
    aload 0
    ldc 1889666253 (java.lang.Integer)
    invokestatic v ae:(Lab;I)V
    goto L176
L11
    aload 0
    getfield ab b:I
    ldc 1164900853 (java.lang.Integer)
    imul
    sipush 128
    if_icmplt L106
    iload 2
    sipush 1600
    if_icmpne L139
    new java/lang/IllegalStateException
    dup
    invokespecial java/lang/IllegalStateException <init>:()V
    athrow
L143
    aload 0
    dup
    getfield ab bv:I
    ldc 928063907 (java.lang.Integer)
    iadd
    putfield ab bv:I
    goto L113
L164
    aload 0
    iconst_0
    putfield ab bb:I
    goto L12
L114
    ldc -1055712757 (java.lang.Integer)
    aload 0
    getfield ab bv:I
    imul
    aload 4
    getfield ah w:[I
    arraylength
    if_icmplt L109
    iload 2
    sipush 1600
    if_icmpne L145
    return
L178
    aload 0
    iconst_0
    putfield ab as:I
    goto L146
L132
    iload 4
    iload 6
    if_icmple L25
    iload 2
    sipush 1600
    if_icmpne L138
    new java/lang/IllegalStateException
    dup
    invokespecial java/lang/IllegalStateException <init>:()V
    athrow
L92
    iconst_m1
    iload 8
    if_icmpne L82
    goto L81
L187
    aload 0
    ldc 1425265329 (java.lang.Integer)
    putfield ab be:I
L109
    goto L5
L179
    ldc 1164900853 (java.lang.Integer)
    aload 0
    getfield ab b:I
    imul
    sipush 11776
    if_icmpge L149
    iload 2
    sipush 1600
    if_icmpne L147
    new java/lang/IllegalStateException
    dup
    invokespecial java/lang/IllegalStateException <init>:()V
    athrow
L5
    iconst_m1
    ldc 1048158519 (java.lang.Integer)
    aload 0
    getfield ab bl:I
    imul
    if_icmpeq L57
    iload 2
    sipush 1600
    if_icmpne L56
    new java/lang/IllegalStateException
    dup
    invokespecial java/lang/IllegalStateException <init>:()V
    athrow
L62
    aload 0
    ldc 80782592 (java.lang.Integer)
    putfield ab by:I
    goto L31
L3
    aload 0
    bipush 59
    invokestatic df am:(Lab;B)V
    goto L11
L80
    iconst_1
    ldc -106389737 (java.lang.Integer)
    aload 3
    getfield ah z:I
    imul
    if_icmpne L57
    iload 2
    sipush 1600
    if_icmpne L191
    new java/lang/IllegalStateException
    dup
    invokespecial java/lang/IllegalStateException <init>:()V
    athrow
L191
    aload 0
    getfield ab ch:I
    ldc 176322769 (java.lang.Integer)
    imul
    ifle L57
    iload 2
    sipush 1600
    if_icmpne L169
    return
L64
    aload 0
    getfield ab as:I
    ldc -17018627 (java.lang.Integer)
    imul
    aload 3
    getfield ah w:[I
    arraylength
    if_icmplt L87
    iload 2
    sipush 1600
    if_icmpne L177
    new java/lang/IllegalStateException
    dup
    invokespecial java/lang/IllegalStateException <init>:()V
    athrow
L170
    aload 0
    getfield ab bj:I
    ldc 842014775 (java.lang.Integer)
    imul
    getstatic client b:I
    ldc -117546507 (java.lang.Integer)
    imul
    if_icmpge L57
L192
    aload 0
    ldc -270225023 (java.lang.Integer)
    putfield ab bw:I
L193
    goto L194
L57
    iconst_m1
    ldc 1048158519 (java.lang.Integer)
    aload 0
    getfield ab bl:I
    imul
    if_icmpeq L160
    iload 2
    sipush 1600
    if_icmpne L159
    new java/lang/IllegalStateException
    dup
    invokespecial java/lang/IllegalStateException <init>:()V
    athrow
L184
    aload 0
    ldc 1425265329 (java.lang.Integer)
    putfield ab be:I
    goto L5
L161
    aload 0
    getfield ab bl:I
    ldc 1048158519 (java.lang.Integer)
    imul
    ldc 152969838 (java.lang.Integer)
    invokestatic cd e:(II)Lah;
    astore 3
L195
    aconst_null
    aload 3
    if_acmpeq L180
    iload 2
    sipush 1600
    if_icmpne L196
    new java/lang/IllegalStateException
    dup
    invokespecial java/lang/IllegalStateException <init>:()V
    athrow
L196
    aload 3
    getfield ah w:[I
    ifnull L180
    iload 2
    sipush 1600
    if_icmpne L197
    new java/lang/IllegalStateException
    dup
    invokespecial java/lang/IllegalStateException <init>:()V
    athrow
L197
    aload 0
    dup
    getfield ab bm:I
    ldc -1158843175 (java.lang.Integer)
    iadd
    putfield ab bm:I
L198
    ldc -166629429 (java.lang.Integer)
    aload 0
    getfield ab bk:I
    imul
    aload 3
    getfield ah w:[I
    arraylength
    if_icmpge L199
    iload 2
    sipush 1600
    if_icmpne L200
    new java/lang/IllegalStateException
    dup
    invokespecial java/lang/IllegalStateException <init>:()V
    athrow
L200
    ldc 1554762601 (java.lang.Integer)
    aload 0
    getfield ab bm:I
    imul
    aload 3
    getfield ah r:[I
    ldc -166629429 (java.lang.Integer)
    aload 0
    getfield ab bk:I
    imul
    iaload
    if_icmple L199
    iload 2
    sipush 1600
    if_icmpne L201
    new java/lang/IllegalStateException
    dup
    invokespecial java/lang/IllegalStateException <init>:()V
    athrow
L201
    aload 0
    ldc -1158843175 (java.lang.Integer)
    putfield ab bm:I
L202
    aload 0
    dup
    getfield ab bk:I
    ldc -1427915293 (java.lang.Integer)
    iadd
    putfield ab bk:I
L203
    aload 3
    ldc -166629429 (java.lang.Integer)
    aload 0
    getfield ab bk:I
    imul
    aload 0
    getfield ab b:I
    ldc 1164900853 (java.lang.Integer)
    imul
    aload 0
    getfield ab x:I
    ldc 109190397 (java.lang.Integer)
    imul
    ldc 1797324181 (java.lang.Integer)
    invokestatic gt p:(Lah;IIII)V
L199
    ldc -166629429 (java.lang.Integer)
    aload 0
    getfield ab bk:I
    imul
    aload 3
    getfield ah w:[I
    arraylength
    if_icmplt L41
    iload 2
    sipush 1600
    if_icmpne L204
    new java/lang/IllegalStateException
    dup
    invokespecial java/lang/IllegalStateException <init>:()V
    athrow
L204
    aload 0
    dup
    getfield ab bk:I
    aload 3
    getfield ah g:I
    ldc -639453017 (java.lang.Integer)
    imul
    isub
    putfield ab bk:I
    goto L166
L134
    aload 0
    iload 6
    ldc 1172037717 (java.lang.Integer)
    imul
    putfield ab x:I
    goto L25
L167
    aload 0
    getfield ab bp:I
    ldc 2021066979 (java.lang.Integer)
    imul
    aload 3
    getfield ah t:I
    ldc -670156097 (java.lang.Integer)
    imul
    if_icmplt L126
    iload 2
    sipush 1600
    if_icmpne L205
    new java/lang/IllegalStateException
    dup
    invokespecial java/lang/IllegalStateException <init>:()V
    athrow
L205
    aload 0
    ldc -2003952775 (java.lang.Integer)
    putfield ab bl:I
    goto L41
L118
    bipush 8
    istore 9
    goto L117
L127
    ldc -166629429 (java.lang.Integer)
    aload 0
    getfield ab bk:I
    imul
    aload 3
    getfield ah w:[I
    arraylength
    if_icmplt L86
    iload 2
    sipush 1600
    if_icmpne L40
    new java/lang/IllegalStateException
    dup
    invokespecial java/lang/IllegalStateException <init>:()V
    athrow
L61
    iload 4
    iload 6
    if_icmple L68
    iload 2
    sipush 1600
    if_icmpne L162
    new java/lang/IllegalStateException
    dup
    invokespecial java/lang/IllegalStateException <init>:()V
    athrow
L2
    ldc 842014775 (java.lang.Integer)
    aload 0
    getfield ab bj:I
    imul
    ldc -117546507 (java.lang.Integer)
    getstatic client b:I
    imul
    if_icmplt L65
    iload 2
    sipush 1600
    if_icmpne L10
    return
L41
    aload 0
    aload 3
    getfield ah h:Z
    putfield ab v:Z
    goto L160
L206
    aload 0
    dup
    getfield ab bw:I
    ldc -270225023 (java.lang.Integer)
    isub
    putfield ab bw:I
    goto L194
L160
    ldc -1613918591 (java.lang.Integer)
    aload 0
    getfield ab bw:I
    imul
    ifle L194
    iload 2
    sipush 1600
    if_icmpne L206
    new java/lang/IllegalStateException
    dup
    invokespecial java/lang/IllegalStateException <init>:()V
    athrow
L110
    aload 0
    getfield ab bg:[Z
    ldc -426846849 (java.lang.Integer)
    aload 0
    getfield ab bt:I
    imul
    iconst_1
    isub
    baload
    ifeq L123
    iload 2
    sipush 1600
    if_icmpne L122
    new java/lang/IllegalStateException
    dup
    invokespecial java/lang/IllegalStateException <init>:()V
    athrow
L194
    return
L207
    new java/lang/StringBuilder
    dup
    invokespecial java/lang/StringBuilder <init>:()V
    ldc "v.aw(" (java.lang.String)
    invokevirtual java/lang/StringBuilder append:(Ljava/lang/String;)Ljava/lang/StringBuilder;
    ldc 41 (java.lang.Integer)
    invokevirtual java/lang/StringBuilder append:(C)Ljava/lang/StringBuilder;
    invokevirtual java/lang/StringBuilder toString:()Ljava/lang/String;
    invokestatic k a:(Ljava/lang/Throwable;Ljava/lang/String;)Lee;
    athrow
