v e (Ljava/lang/String;Ljava/lang/String;Ljava/lang/String;Ljava/lang/String;I)ZL1
    aconst_null
    aload 0
    if_acmpeq L2
    iload 4
    ldc 1213234965 (java.lang.Integer)
    if_icmpeq L3
    new java/lang/IllegalStateException
    dup
    invokespecial java/lang/IllegalStateException <init>:()V
    athrow
L4
    aload 1
    aload 3
    invokevirtual java/lang/String equals:(Ljava/lang/Object;)Z
    ireturn
L5
    aload 0
    ldc "#" (java.lang.String)
    invokevirtual java/lang/String startsWith:(Ljava/lang/String;)Z
    ifne L6
    iload 4
    ldc 1213234965 (java.lang.Integer)
    if_icmpeq L7
    new java/lang/IllegalStateException
    dup
    invokespecial java/lang/IllegalStateException <init>:()V
    athrow
L3
    aload 2
    ifnonnull L5
    iload 4
    ldc 1213234965 (java.lang.Integer)
    if_icmpeq L2
    new java/lang/IllegalStateException
    dup
    invokespecial java/lang/IllegalStateException <init>:()V
    athrow
L7
    aload 2
    ldc "#" (java.lang.String)
    invokevirtual java/lang/String startsWith:(Ljava/lang/String;)Z
    ifeq L4
    iload 4
    ldc 1213234965 (java.lang.Integer)
    if_icmpeq L6
    new java/lang/IllegalStateException
    dup
    invokespecial java/lang/IllegalStateException <init>:()V
    athrow
L6
    aload 0
    aload 2
    invokevirtual java/lang/String equals:(Ljava/lang/Object;)Z
    ireturn
L2
    iconst_0
    ireturn
L8
    new java/lang/StringBuilder
    dup
    invokespecial java/lang/StringBuilder <init>:()V
    ldc "v.e(" (java.lang.String)
    invokevirtual java/lang/StringBuilder append:(Ljava/lang/String;)Ljava/lang/StringBuilder;
    ldc 41 (java.lang.Integer)
    invokevirtual java/lang/StringBuilder append:(C)Ljava/lang/StringBuilder;
    invokevirtual java/lang/StringBuilder toString:()Ljava/lang/String;
    invokestatic k a:(Ljava/lang/Throwable;Ljava/lang/String;)Lee;
    athrow
