w dc (Ljava/lang/String;ZI)ZL1
    aconst_null
    aload 0
    if_acmpne L2
    iload 2
    ldc 1251565557 (java.lang.Integer)
    if_icmplt L3
    new java/lang/IllegalStateException
    dup
    invokespecial java/lang/IllegalStateException <init>:()V
    athrow
L4
    iinc 4 1
    goto L5
L6
    iconst_0
    ireturn
L7
    iconst_0
    istore 4
L5
    iload 4
    getstatic client oi:I
    ldc -78716921 (java.lang.Integer)
    imul
    if_icmpge L8
    iload 2
    ldc 1251565557 (java.lang.Integer)
    if_icmplt L9
    new java/lang/IllegalStateException
    dup
    invokespecial java/lang/IllegalStateException <init>:()V
    athrow
L3
    iconst_0
    ireturn
L10
    iload 1
    ifeq L11
    iload 2
    ldc 1251565557 (java.lang.Integer)
    if_icmplt L12
    new java/lang/IllegalStateException
    dup
    invokespecial java/lang/IllegalStateException <init>:()V
    athrow
L12
    iconst_0
    ldc -1241775569 (java.lang.Integer)
    getstatic client or:[Lz;
    iload 4
    aaload
    getfield z l:I
    imul
    if_icmpeq L4
    iload 2
    ldc 1251565557 (java.lang.Integer)
    if_icmplt L11
    new java/lang/IllegalStateException
    dup
    invokespecial java/lang/IllegalStateException <init>:()V
    athrow
L11
    iconst_1
    ireturn
L8
    aload 3
    getstatic hg hv:Ll;
    getfield l e:Ljava/lang/String;
    getstatic dj g:Lge;
    ldc -1094635158 (java.lang.Integer)
    invokestatic dp l:(Ljava/lang/CharSequence;Lge;I)Ljava/lang/String;
    invokevirtual java/lang/String equalsIgnoreCase:(Ljava/lang/String;)Z
    ifeq L6
    iload 2
    ldc 1251565557 (java.lang.Integer)
    if_icmplt L13
    new java/lang/IllegalStateException
    dup
    invokespecial java/lang/IllegalStateException <init>:()V
    athrow
L9
    aload 3
    getstatic client or:[Lz;
    iload 4
    aaload
    getfield z e:Ljava/lang/String;
    getstatic dj g:Lge;
    ldc -896778172 (java.lang.Integer)
    invokestatic dp l:(Ljava/lang/CharSequence;Lge;I)Ljava/lang/String;
    invokevirtual java/lang/String equalsIgnoreCase:(Ljava/lang/String;)Z
    ifeq L4
    iload 2
    ldc 1251565557 (java.lang.Integer)
    if_icmplt L10
    new java/lang/IllegalStateException
    dup
    invokespecial java/lang/IllegalStateException <init>:()V
    athrow
L13
    iconst_1
    ireturn
L2
    aload 0
    getstatic dj g:Lge;
    ldc -898653331 (java.lang.Integer)
    invokestatic dp l:(Ljava/lang/CharSequence;Lge;I)Ljava/lang/String;
    astore 3
    goto L7
L14
    new java/lang/StringBuilder
    dup
    invokespecial java/lang/StringBuilder <init>:()V
    ldc "w.dc(" (java.lang.String)
    invokevirtual java/lang/StringBuilder append:(Ljava/lang/String;)Ljava/lang/StringBuilder;
    ldc 41 (java.lang.Integer)
    invokevirtual java/lang/StringBuilder append:(C)Ljava/lang/StringBuilder;
    invokevirtual java/lang/StringBuilder toString:()Ljava/lang/String;
    invokestatic k a:(Ljava/lang/Throwable;Ljava/lang/String;)Lee;
    athrow
