w j ([Lv;II[I[IB)VL1
    iload 1
    iload 2
    if_icmpge L2
    iload 5
    iconst_3
    if_icmplt L3
    new java/lang/IllegalStateException
    dup
    invokespecial java/lang/IllegalStateException <init>:()V
    athrow
L4
    iconst_1
    iload 2
    iadd
    istore 7
    goto L5
L6
    iload 6
    iload 7
    if_icmpge L7
    goto L8
L5
    iload 1
    iload 2
    iadd
    iconst_2
    idiv
    istore 8
    goto L9
L10
    iconst_1
    aload 4
    iload 11
    iaload
    if_icmpne L11
    iload 5
    iconst_3
    if_icmplt L12
    new java/lang/IllegalStateException
    dup
    invokespecial java/lang/IllegalStateException <init>:()V
    athrow
L13
    aload 0
    iload 8
    aload 0
    iload 1
    aaload
    aastore
L14
    aload 0
    iload 1
    aload 9
    aastore
    goto L6
L15
    iconst_0
    istore 11
    goto L16
L8
    iconst_1
    istore 10
L17
    iinc 7 -1
L18
    iconst_0
    istore 11
L19
    iload 11
    iconst_4
    if_icmpge L20
    goto L21
L22
    aload 0
    iload 6
    aload 0
    iload 7
    aaload
    aastore
    goto L23
L24
    aload 0
    iload 7
    aaload
    getfield v i:I
    ldc -1386077703 (java.lang.Integer)
    imul
    istore 12
L25
    ldc -1386077703 (java.lang.Integer)
    aload 9
    getfield v i:I
    imul
    istore 13
    goto L11
L26
    aload 3
    iload 11
    iaload
    iconst_1
    if_icmpne L27
    iload 5
    iconst_3
    if_icmplt L28
    new java/lang/IllegalStateException
    dup
    invokespecial java/lang/IllegalStateException <init>:()V
    athrow
L28
    aload 0
    iload 7
    aaload
    getfield v l:I
    ldc 729509107 (java.lang.Integer)
    imul
    istore 12
    goto L29
L30
    iload 12
    iconst_m1
    if_icmpne L31
    iload 5
    iconst_3
    if_icmplt L32
    new java/lang/IllegalStateException
    dup
    invokespecial java/lang/IllegalStateException <init>:()V
    athrow
L33
    goto L20
L34
    iconst_1
    aload 4
    iload 11
    iaload
    if_icmpne L35
    iload 5
    iconst_3
    if_icmplt L36
    new java/lang/IllegalStateException
    dup
    invokespecial java/lang/IllegalStateException <init>:()V
    athrow
L36
    sipush 2001
    istore 12
L35
    iconst_m1
    iload 13
    if_icmpne L11
    iload 5
    iconst_3
    if_icmplt L10
    new java/lang/IllegalStateException
    dup
    invokespecial java/lang/IllegalStateException <init>:()V
    athrow
L37
    iconst_2
    aload 3
    iload 11
    iaload
    if_icmpne L38
    iload 5
    iconst_3
    if_icmplt L39
    return
L12
    sipush 2001
    istore 13
    goto L11
L40
    iconst_0
    goto L41
L42
    aload 0
    iload 7
    aaload
    ldc 1568248628 (java.lang.Integer)
    invokevirtual v e:(I)Z
    ifeq L40
    iload 5
    iconst_3
    if_icmplt L43
    return
L44
    goto L45
L46
    aload 4
    iload 11
    iaload
    iconst_1
    if_icmpne L47
    iload 5
    iconst_3
    if_icmplt L48
    new java/lang/IllegalStateException
    dup
    invokespecial java/lang/IllegalStateException <init>:()V
    athrow
L41
    istore 12
    goto L49
L3
    iload 1
    iconst_1
    isub
    istore 6
    goto L4
L50
    iconst_0
    istore 10
    goto L51
L52
    iconst_0
L53
    istore 13
    goto L11
L54
    aload 0
    iload 7
    aaload
    getfield v e:I
    ldc 1985134815 (java.lang.Integer)
    imul
    istore 12
    goto L55
L45
    iload 10
    ifne L56
    iload 5
    iconst_3
    if_icmplt L57
    new java/lang/IllegalStateException
    dup
    invokespecial java/lang/IllegalStateException <init>:()V
    athrow
L11
    iload 13
    iload 12
    if_icmpne L46
    iload 5
    iconst_3
    if_icmplt L58
    new java/lang/IllegalStateException
    dup
    invokespecial java/lang/IllegalStateException <init>:()V
    athrow
L58
    iload 11
    iconst_3
    if_icmpne L59
    iload 5
    iconst_3
    if_icmplt L60
    new java/lang/IllegalStateException
    dup
    invokespecial java/lang/IllegalStateException <init>:()V
    athrow
L32
    aload 4
    iload 11
    iaload
    iconst_1
    if_icmpne L31
    iload 5
    iconst_3
    if_icmplt L61
    new java/lang/IllegalStateException
    dup
    invokespecial java/lang/IllegalStateException <init>:()V
    athrow
L27
    iconst_3
    aload 3
    iload 11
    iaload
    if_icmpne L54
    iload 5
    iconst_3
    if_icmplt L42
    return
L48
    iload 12
    iload 13
    if_icmple L47
    iload 5
    iconst_3
    if_icmplt L62
    new java/lang/IllegalStateException
    dup
    invokespecial java/lang/IllegalStateException <init>:()V
    athrow
L62
    goto L20
L47
    iconst_0
    aload 4
    iload 11
    iaload
    if_icmpne L50
    goto L63
L51
    goto L20
L29
    ldc 729509107 (java.lang.Integer)
    aload 9
    getfield v l:I
    imul
    istore 13
    goto L64
L65
    iconst_1
    istore 10
    goto L56
L66
    iload 12
    iload 13
    if_icmple L67
    iload 5
    iconst_3
    if_icmplt L44
    return
L59
    iinc 11 1
    goto L19
L20
    iload 10
    ifne L17
    goto L65
L21
    aload 3
    iload 11
    iaload
    iconst_2
    if_icmpne L26
    iload 5
    iconst_3
    if_icmplt L24
    return
L56
    iinc 6 1
    goto L15
L68
    aload 9
    ldc 1805565426 (java.lang.Integer)
    invokevirtual v e:(I)Z
    ifeq L69
    iload 5
    iconst_3
    if_icmplt L70
    new java/lang/IllegalStateException
    dup
    invokespecial java/lang/IllegalStateException <init>:()V
    athrow
L16
    iload 11
    iconst_4
    if_icmpge L45
    iload 5
    iconst_3
    if_icmplt L37
    new java/lang/IllegalStateException
    dup
    invokespecial java/lang/IllegalStateException <init>:()V
    athrow
L55
    ldc 1985134815 (java.lang.Integer)
    aload 9
    getfield v e:I
    imul
    istore 13
    goto L11
L39
    ldc -1386077703 (java.lang.Integer)
    aload 0
    iload 6
    aaload
    getfield v i:I
    imul
    istore 12
L71
    ldc -1386077703 (java.lang.Integer)
    aload 9
    getfield v i:I
    imul
    istore 13
    goto L72
L60
    iconst_0
    istore 10
    goto L59
L73
    ldc 729509107 (java.lang.Integer)
    aload 0
    iload 6
    aaload
    getfield v l:I
    imul
    istore 12
L74
    ldc 729509107 (java.lang.Integer)
    aload 9
    getfield v l:I
    imul
    istore 13
    goto L30
L9
    aload 0
    iload 8
    aaload
    astore 9
    goto L13
L61
    sipush 2001
    istore 12
    goto L31
L75
    istore 13
    goto L72
L49
    aload 9
    ldc 2025849537 (java.lang.Integer)
    invokevirtual v e:(I)Z
    ifeq L52
    goto L76
L77
    aload 4
    iload 11
    iaload
    iconst_1
    if_icmpne L72
    iload 5
    iconst_3
    if_icmplt L78
    new java/lang/IllegalStateException
    dup
    invokespecial java/lang/IllegalStateException <init>:()V
    athrow
L79
    iconst_3
    iload 11
    if_icmpne L80
    iload 5
    iconst_3
    if_icmplt L81
    new java/lang/IllegalStateException
    dup
    invokespecial java/lang/IllegalStateException <init>:()V
    athrow
L82
    aload 3
    iload 11
    iaload
    iconst_3
    if_icmpne L83
    iload 5
    iconst_3
    if_icmplt L84
    return
L84
    aload 0
    iload 6
    aaload
    ldc 2032692977 (java.lang.Integer)
    invokevirtual v e:(I)Z
    ifeq L85
    iload 5
    iconst_3
    if_icmplt L86
    new java/lang/IllegalStateException
    dup
    invokespecial java/lang/IllegalStateException <init>:()V
    athrow
L86
    iconst_1
    goto L87
L85
    iconst_0
L87
    istore 12
    goto L68
L88
    aload 4
    iload 11
    iaload
    ifne L67
    iload 5
    iconst_3
    if_icmplt L66
    new java/lang/IllegalStateException
    dup
    invokespecial java/lang/IllegalStateException <init>:()V
    athrow
L70
    iconst_1
    goto L75
L69
    iconst_0
    goto L75
L64
    iload 12
    iconst_m1
    if_icmpne L35
    iload 5
    iconst_3
    if_icmplt L34
    new java/lang/IllegalStateException
    dup
    invokespecial java/lang/IllegalStateException <init>:()V
    athrow
L83
    aload 0
    iload 6
    aaload
    getfield v e:I
    ldc 1985134815 (java.lang.Integer)
    imul
    istore 12
L89
    ldc 1985134815 (java.lang.Integer)
    aload 9
    getfield v e:I
    imul
    istore 13
L72
    iload 13
    iload 12
    if_icmpne L90
    goto L79
L63
    iload 12
    iload 13
    if_icmpge L50
    iload 5
    iconst_3
    if_icmplt L33
    new java/lang/IllegalStateException
    dup
    invokespecial java/lang/IllegalStateException <init>:()V
    athrow
L81
    iconst_0
    istore 10
    goto L80
L90
    iconst_1
    aload 4
    iload 11
    iaload
    if_icmpne L88
    iload 12
    iload 13
    if_icmpge L88
    iload 5
    iconst_3
    if_icmplt L91
    new java/lang/IllegalStateException
    dup
    invokespecial java/lang/IllegalStateException <init>:()V
    athrow
L91
    goto L45
L31
    iconst_m1
    iload 13
    if_icmpne L72
    iload 5
    iconst_3
    if_icmplt L77
    new java/lang/IllegalStateException
    dup
    invokespecial java/lang/IllegalStateException <init>:()V
    athrow
L43
    iconst_1
    goto L41
L78
    sipush 2001
    istore 13
    goto L72
L67
    iconst_0
    istore 10
L92
    goto L45
L80
    iinc 11 1
    goto L16
L76
    iconst_1
    goto L53
L57
    iload 6
    iload 7
    if_icmpge L93
    iload 5
    iconst_3
    if_icmplt L94
    new java/lang/IllegalStateException
    dup
    invokespecial java/lang/IllegalStateException <init>:()V
    athrow
L94
    aload 0
    iload 6
    aaload
    astore 11
    goto L22
L95
    aload 0
    iload 7
    iconst_1
    iadd
    iload 2
    aload 3
    aload 4
    bipush -109
    invokestatic w j:([Lv;II[I[IB)V
    goto L2
L23
    aload 0
    iload 7
    aload 11
    aastore
L93
    goto L6
L7
    aload 0
    iload 1
    iload 7
    aload 3
    aload 4
    bipush -64
    invokestatic w j:([Lv;II[I[IB)V
    goto L95
L38
    iconst_1
    aload 3
    iload 11
    iaload
    if_icmpne L82
    iload 5
    iconst_3
    if_icmplt L73
    return
L2
    return
L96
    new java/lang/StringBuilder
    dup
    invokespecial java/lang/StringBuilder <init>:()V
    ldc "w.j(" (java.lang.String)
    invokevirtual java/lang/StringBuilder append:(Ljava/lang/String;)Ljava/lang/StringBuilder;
    ldc 41 (java.lang.Integer)
    invokevirtual java/lang/StringBuilder append:(C)Ljava/lang/StringBuilder;
    invokevirtual java/lang/StringBuilder toString:()Ljava/lang/String;
    invokestatic k a:(Ljava/lang/Throwable;Ljava/lang/String;)Lee;
    athrow
