x ch (Lay;IIII)VL1
    ldc 811532485 (java.lang.Integer)
    getstatic client ii:I
    imul
    sipush 400
    if_icmplt L2
    iload 4
    ldc -666149669 (java.lang.Integer)
    if_icmpne L3
    new java/lang/IllegalStateException
    dup
    invokespecial java/lang/IllegalStateException <init>:()V
    athrow
L4
    iconst_3
    iload 7
    if_icmpne L5
    iload 4
    ldc -666149669 (java.lang.Integer)
    if_icmpne L6
    new java/lang/IllegalStateException
    dup
    invokespecial java/lang/IllegalStateException <init>:()V
    athrow
L7
    iconst_0
    ldc 210860257 (java.lang.Integer)
    aload 0
    getfield ay n:I
    imul
    if_icmpeq L8
    iload 4
    ldc -666149669 (java.lang.Integer)
    if_icmpne L9
    new java/lang/IllegalStateException
    dup
    invokespecial java/lang/IllegalStateException <init>:()V
    athrow
L10
    aload 0
    ldc -206479707 (java.lang.Integer)
    invokevirtual ay i:(I)Lay;
    astore 0
L11
    aconst_null
    aload 0
    if_acmpne L12
    iload 4
    ldc -666149669 (java.lang.Integer)
    if_icmpne L13
    new java/lang/IllegalStateException
    dup
    invokespecial java/lang/IllegalStateException <init>:()V
    athrow
L13
    return
L12
    aload 0
    getfield ay ae:Z
    ifne L14
    iload 4
    ldc -666149669 (java.lang.Integer)
    if_icmpne L15
    new java/lang/IllegalStateException
    dup
    invokespecial java/lang/IllegalStateException <init>:()V
    athrow
L5
    iload 7
    iconst_4
    if_icmpne L16
    iload 4
    ldc -666149669 (java.lang.Integer)
    if_icmpne L17
    return
L14
    aload 0
    getfield ay av:Z
    ifeq L18
    iload 4
    ldc -666149669 (java.lang.Integer)
    if_icmpne L19
    new java/lang/IllegalStateException
    dup
    invokespecial java/lang/IllegalStateException <init>:()V
    athrow
L19
    getstatic client jo:I
    ldc 905918277 (java.lang.Integer)
    imul
    iload 1
    if_icmpeq L18
    iload 4
    ldc -666149669 (java.lang.Integer)
    if_icmpne L20
    new java/lang/IllegalStateException
    dup
    invokespecial java/lang/IllegalStateException <init>:()V
    athrow
L21
    iconst_2
    getstatic da jj:I
    ldc -448064051 (java.lang.Integer)
    imul
    iconst_2
    iand
    if_icmpne L22
    iload 4
    ldc -666149669 (java.lang.Integer)
    if_icmpne L23
    new java/lang/IllegalStateException
    dup
    invokespecial java/lang/IllegalStateException <init>:()V
    athrow
L18
    aload 0
    getfield ay w:Ljava/lang/String;
    astore 5
    goto L7
L24
    iconst_4
    istore 7
    goto L25
L9
    new java/lang/StringBuilder
    dup
    invokespecial java/lang/StringBuilder <init>:()V
    aload 5
    invokevirtual java/lang/StringBuilder append:(Ljava/lang/String;)Ljava/lang/StringBuilder;
    aload 0
    getfield ay n:I
    ldc 210860257 (java.lang.Integer)
    imul
    ldc 1815897639 (java.lang.Integer)
    getstatic hg hv:Ll;
    getfield l u:I
    imul
    ldc 846687583 (java.lang.Integer)
    invokestatic a cv:(III)Ljava/lang/String;
    invokevirtual java/lang/StringBuilder append:(Ljava/lang/String;)Ljava/lang/StringBuilder;
    ldc " " (java.lang.String)
    invokevirtual java/lang/StringBuilder append:(Ljava/lang/String;)Ljava/lang/StringBuilder;
    getstatic a c:Ljava/lang/String;
    invokevirtual java/lang/StringBuilder append:(Ljava/lang/String;)Ljava/lang/StringBuilder;
    getstatic et fv:Ljava/lang/String;
    invokevirtual java/lang/StringBuilder append:(Ljava/lang/String;)Ljava/lang/StringBuilder;
    aload 0
    getfield ay n:I
    ldc 210860257 (java.lang.Integer)
    imul
    invokevirtual java/lang/StringBuilder append:(I)Ljava/lang/StringBuilder;
    getstatic a u:Ljava/lang/String;
    invokevirtual java/lang/StringBuilder append:(Ljava/lang/String;)Ljava/lang/StringBuilder;
    invokevirtual java/lang/StringBuilder toString:()Ljava/lang/String;
    astore 5
L8
    iconst_1
    getstatic client in:I
    ldc 1293091945 (java.lang.Integer)
    imul
    if_icmpne L26
    iload 4
    ldc -666149669 (java.lang.Integer)
    if_icmpne L27
    new java/lang/IllegalStateException
    dup
    invokespecial java/lang/IllegalStateException <init>:()V
    athrow
L27
    getstatic et ev:Ljava/lang/String;
    new java/lang/StringBuilder
    dup
    invokespecial java/lang/StringBuilder <init>:()V
    getstatic client it:Ljava/lang/String;
    invokevirtual java/lang/StringBuilder append:(Ljava/lang/String;)Ljava/lang/StringBuilder;
    ldc " " (java.lang.String)
    invokevirtual java/lang/StringBuilder append:(Ljava/lang/String;)Ljava/lang/StringBuilder;
    getstatic a w:Ljava/lang/String;
    invokevirtual java/lang/StringBuilder append:(Ljava/lang/String;)Ljava/lang/StringBuilder;
    ldc " " (java.lang.String)
    invokevirtual java/lang/StringBuilder append:(Ljava/lang/String;)Ljava/lang/StringBuilder;
    ldc 16776960 (java.lang.Integer)
    bipush -54
    invokestatic p e:(IB)Ljava/lang/String;
    invokevirtual java/lang/StringBuilder append:(Ljava/lang/String;)Ljava/lang/StringBuilder;
    aload 5
    invokevirtual java/lang/StringBuilder append:(Ljava/lang/String;)Ljava/lang/StringBuilder;
    invokevirtual java/lang/StringBuilder toString:()Ljava/lang/String;
    bipush 7
    iload 1
    iload 2
    iload 3
    ldc -1936383105 (java.lang.Integer)
    invokestatic fk bo:(Ljava/lang/String;Ljava/lang/String;IIIII)V
    goto L22
L28
    aconst_null
    aload 6
    if_acmpeq L29
    iload 4
    ldc -666149669 (java.lang.Integer)
    if_icmpne L24
    new java/lang/IllegalStateException
    dup
    invokespecial java/lang/IllegalStateException <init>:()V
    athrow
L30
    aload 6
    ldc -1787010159 (java.lang.Integer)
    invokestatic dj cl:([Ljava/lang/String;I)[Ljava/lang/String;
    astore 6
    goto L28
L2
    aconst_null
    aload 0
    getfield ay aw:[I
    if_acmpeq L11
    iload 4
    ldc -666149669 (java.lang.Integer)
    if_icmpne L10
    new java/lang/IllegalStateException
    dup
    invokespecial java/lang/IllegalStateException <init>:()V
    athrow
L31
    aload 0
    getfield ay b:[Ljava/lang/String;
    astore 6
L32
    getstatic client ju:Z
    ifeq L28
    iload 4
    ldc -666149669 (java.lang.Integer)
    if_icmpne L30
    new java/lang/IllegalStateException
    dup
    invokespecial java/lang/IllegalStateException <init>:()V
    athrow
L33
    iload 7
    ifne L34
    iload 4
    ldc -666149669 (java.lang.Integer)
    if_icmpne L35
    return
L26
    getstatic client is:Z
    ifeq L31
    iload 4
    ldc -666149669 (java.lang.Integer)
    if_icmpne L21
    new java/lang/IllegalStateException
    dup
    invokespecial java/lang/IllegalStateException <init>:()V
    athrow
L3
    return
L36
    bipush 9
    istore 8
    goto L37
L38
    sipush 2000
    istore 8
    goto L39
L40
    aload 6
    iload 7
    aaload
    getstatic et eq:Ljava/lang/String;
    invokevirtual java/lang/String equalsIgnoreCase:(Ljava/lang/String;)Z
    ifne L41
    iload 4
    ldc -666149669 (java.lang.Integer)
    if_icmpne L42
    new java/lang/IllegalStateException
    dup
    invokespecial java/lang/IllegalStateException <init>:()V
    athrow
L43
    aconst_null
    aload 6
    iload 7
    aaload
    if_acmpeq L41
    iload 4
    ldc -666149669 (java.lang.Integer)
    if_icmpne L40
    return
L44
    iload 7
    ifne L37
    iload 4
    ldc -666149669 (java.lang.Integer)
    if_icmpne L36
    new java/lang/IllegalStateException
    dup
    invokespecial java/lang/IllegalStateException <init>:()V
    athrow
L45
    aload 6
    iload 7
    aaload
    getstatic et eq:Ljava/lang/String;
    invokevirtual java/lang/String equalsIgnoreCase:(Ljava/lang/String;)Z
    ifeq L46
    goto L47
L37
    iconst_1
    iload 7
    if_icmpne L48
    bipush 10
    istore 8
    goto L48
L25
    iload 7
    iflt L29
    iload 4
    ldc -666149669 (java.lang.Integer)
    if_icmpne L43
    new java/lang/IllegalStateException
    dup
    invokespecial java/lang/IllegalStateException <init>:()V
    athrow
L49
    bipush 11
    istore 8
    goto L4
L50
    getstatic et eb:Ljava/lang/String;
    new java/lang/StringBuilder
    dup
    invokespecial java/lang/StringBuilder <init>:()V
    ldc 16776960 (java.lang.Integer)
    bipush -42
    invokestatic p e:(IB)Ljava/lang/String;
    invokevirtual java/lang/StringBuilder append:(Ljava/lang/String;)Ljava/lang/StringBuilder;
    aload 5
    invokevirtual java/lang/StringBuilder append:(Ljava/lang/String;)Ljava/lang/StringBuilder;
    invokevirtual java/lang/StringBuilder toString:()Ljava/lang/String;
    sipush 1003
    iload 1
    iload 2
    iload 3
    ldc -1300680979 (java.lang.Integer)
    invokestatic fk bo:(Ljava/lang/String;Ljava/lang/String;IIIII)V
    goto L22
L6
    bipush 12
    istore 8
    goto L5
L48
    iconst_2
    iload 7
    if_icmpne L4
    goto L49
L17
    bipush 13
    istore 8
L16
    aload 6
    iload 7
    aaload
    new java/lang/StringBuilder
    dup
    invokespecial java/lang/StringBuilder <init>:()V
    ldc 16776960 (java.lang.Integer)
    bipush -87
    invokestatic p e:(IB)Ljava/lang/String;
    invokevirtual java/lang/StringBuilder append:(Ljava/lang/String;)Ljava/lang/StringBuilder;
    aload 5
    invokevirtual java/lang/StringBuilder append:(Ljava/lang/String;)Ljava/lang/StringBuilder;
    invokevirtual java/lang/StringBuilder toString:()Ljava/lang/String;
    iload 8
    iload 1
    iload 2
    iload 3
    ldc -1543712864 (java.lang.Integer)
    invokestatic fk bo:(Ljava/lang/String;Ljava/lang/String;IIIII)V
L41
    iinc 7 -1
    goto L25
L20
    return
L51
    iconst_4
    istore 7
L52
    iload 7
    iflt L50
    iload 4
    ldc -666149669 (java.lang.Integer)
    if_icmpne L53
    new java/lang/IllegalStateException
    dup
    invokespecial java/lang/IllegalStateException <init>:()V
    athrow
L54
    bipush 10
    iload 8
    iadd
    istore 9
    goto L55
L15
    return
L47
    iconst_0
    istore 8
L56
    getstatic client al:Lq;
    getstatic q a:Lq;
    if_acmpeq L38
    getstatic q e:Lq;
    getstatic client al:Lq;
    if_acmpne L39
    iload 4
    ldc -666149669 (java.lang.Integer)
    if_icmpne L57
    new java/lang/IllegalStateException
    dup
    invokespecial java/lang/IllegalStateException <init>:()V
    athrow
L57
    ldc 210860257 (java.lang.Integer)
    aload 0
    getfield ay n:I
    imul
    getstatic hg hv:Ll;
    getfield l u:I
    ldc 1815897639 (java.lang.Integer)
    imul
    if_icmple L39
    iload 4
    ldc -666149669 (java.lang.Integer)
    if_icmpne L38
    new java/lang/IllegalStateException
    dup
    invokespecial java/lang/IllegalStateException <init>:()V
    athrow
L23
    getstatic client jf:Ljava/lang/String;
    new java/lang/StringBuilder
    dup
    invokespecial java/lang/StringBuilder <init>:()V
    getstatic client jk:Ljava/lang/String;
    invokevirtual java/lang/StringBuilder append:(Ljava/lang/String;)Ljava/lang/StringBuilder;
    ldc " " (java.lang.String)
    invokevirtual java/lang/StringBuilder append:(Ljava/lang/String;)Ljava/lang/StringBuilder;
    getstatic a w:Ljava/lang/String;
    invokevirtual java/lang/StringBuilder append:(Ljava/lang/String;)Ljava/lang/StringBuilder;
    ldc " " (java.lang.String)
    invokevirtual java/lang/StringBuilder append:(Ljava/lang/String;)Ljava/lang/StringBuilder;
    ldc 16776960 (java.lang.Integer)
    bipush -110
    invokestatic p e:(IB)Ljava/lang/String;
    invokevirtual java/lang/StringBuilder append:(Ljava/lang/String;)Ljava/lang/StringBuilder;
    aload 5
    invokevirtual java/lang/StringBuilder append:(Ljava/lang/String;)Ljava/lang/StringBuilder;
    invokevirtual java/lang/StringBuilder toString:()Ljava/lang/String;
    bipush 8
    iload 1
    iload 2
    iload 3
    ldc -1978545842 (java.lang.Integer)
    invokestatic fk bo:(Ljava/lang/String;Ljava/lang/String;IIIII)V
    goto L22
L39
    iconst_0
    istore 9
    goto L33
L58
    bipush 13
    iload 8
    iadd
    istore 9
    goto L59
L35
    bipush 9
    iload 8
    iadd
    istore 9
L34
    iload 7
    iconst_1
    if_icmpne L55
    goto L54
L42
    iconst_0
    istore 8
    goto L44
L55
    iconst_2
    iload 7
    if_icmpne L60
    iload 4
    ldc -666149669 (java.lang.Integer)
    if_icmpne L61
    new java/lang/IllegalStateException
    dup
    invokespecial java/lang/IllegalStateException <init>:()V
    athrow
L29
    aconst_null
    aload 6
    if_acmpeq L50
    goto L51
L60
    iconst_3
    iload 7
    if_icmpne L62
    iload 4
    ldc -666149669 (java.lang.Integer)
    if_icmpne L63
    new java/lang/IllegalStateException
    dup
    invokespecial java/lang/IllegalStateException <init>:()V
    athrow
L63
    bipush 12
    iload 8
    iadd
    istore 9
L62
    iconst_4
    iload 7
    if_icmpne L59
    iload 4
    ldc -666149669 (java.lang.Integer)
    if_icmpne L58
    return
L46
    iinc 7 -1
    goto L52
L59
    aload 6
    iload 7
    aaload
    new java/lang/StringBuilder
    dup
    invokespecial java/lang/StringBuilder <init>:()V
    ldc 16776960 (java.lang.Integer)
    bipush -60
    invokestatic p e:(IB)Ljava/lang/String;
    invokevirtual java/lang/StringBuilder append:(Ljava/lang/String;)Ljava/lang/StringBuilder;
    aload 5
    invokevirtual java/lang/StringBuilder append:(Ljava/lang/String;)Ljava/lang/StringBuilder;
    invokevirtual java/lang/StringBuilder toString:()Ljava/lang/String;
    iload 9
    iload 1
    iload 2
    iload 3
    ldc -1623167393 (java.lang.Integer)
    invokestatic fk bo:(Ljava/lang/String;Ljava/lang/String;IIIII)V
    goto L46
L61
    iload 8
    bipush 11
    iadd
    istore 9
    goto L60
L53
    aconst_null
    aload 6
    iload 7
    aaload
    if_acmpeq L46
    iload 4
    ldc -666149669 (java.lang.Integer)
    if_icmpne L45
    new java/lang/IllegalStateException
    dup
    invokespecial java/lang/IllegalStateException <init>:()V
    athrow
L22
    return
L64
    new java/lang/StringBuilder
    dup
    invokespecial java/lang/StringBuilder <init>:()V
    ldc "x.ch(" (java.lang.String)
    invokevirtual java/lang/StringBuilder append:(Ljava/lang/String;)Ljava/lang/StringBuilder;
    ldc 41 (java.lang.Integer)
    invokevirtual java/lang/StringBuilder append:(C)Ljava/lang/StringBuilder;
    invokevirtual java/lang/StringBuilder toString:()Ljava/lang/String;
    invokestatic k a:(Ljava/lang/Throwable;Ljava/lang/String;)Lee;
    athrow
