y ac (ZB)VL1
    iload 0
    putstatic client db:Z
    goto L2
L3
    iload 6
    iconst_4
    if_icmpge L4
    iload 1
    iconst_0
    if_icmplt L5
    new java/lang/IllegalStateException
    dup
    invokespecial java/lang/IllegalStateException <init>:()V
    athrow
L6
    getstatic client ce:Ldj;
    bipush -8
    invokevirtual dj bl:(B)I
    istore 2
    goto L7
L8
    iload 4
    newarray 10
    putstatic cw dj:[I
    goto L9
L10
    ldc 2039932147 (java.lang.Integer)
    getstatic client cm:I
    imul
    ldc 910905453 (java.lang.Integer)
    getstatic client ce:Ldj;
    getfield dj a:I
    imul
    isub
    bipush 16
    idiv
    istore 4
L11
    iload 4
    iconst_4
UNKNOWN-NODE:     multianewarray org.objectweb.asm.tree.MultiANewArrayInsnNode@67acfde9
    putstatic e dt:[[I
    goto L12
L13
    getstatic cw dj:[I
    iload 4
    getstatic ee bm:Lfo;
    new java/lang/StringBuilder
    dup
    invokespecial java/lang/StringBuilder <init>:()V
    ldc "l" (java.lang.String)
    invokevirtual java/lang/StringBuilder append:(Ljava/lang/String;)Ljava/lang/StringBuilder;
    iload 9
    invokevirtual java/lang/StringBuilder append:(I)Ljava/lang/StringBuilder;
    ldc "_" (java.lang.String)
    invokevirtual java/lang/StringBuilder append:(Ljava/lang/String;)Ljava/lang/StringBuilder;
    iload 10
    invokevirtual java/lang/StringBuilder append:(I)Ljava/lang/StringBuilder;
    invokevirtual java/lang/StringBuilder toString:()Ljava/lang/String;
    ldc 1955428017 (java.lang.Integer)
    invokevirtual fo y:(Ljava/lang/String;I)I
    iastore
    goto L14
L15
    iload 5
    iload 4
    if_icmpge L16
    iload 1
    iconst_0
    if_icmplt L17
    new java/lang/IllegalStateException
    dup
    invokespecial java/lang/IllegalStateException <init>:()V
    athrow
L17
    iconst_0
    istore 6
    goto L3
L2
    getstatic client db:Z
    ifne L18
    iload 1
    iconst_0
    if_icmplt L6
    return
L5
    getstatic e dt:[[I
    iload 5
    aaload
    iload 6
    getstatic client ce:Ldj;
    ldc -1860613919 (java.lang.Integer)
    invokevirtual dj bu:(I)I
    iastore
L19
    iinc 6 1
    goto L3
L4
    iinc 5 1
    goto L15
L16
    getstatic client ce:Ldj;
    bipush 98
    invokevirtual dj as:(B)I
    istore 5
L20
    getstatic client ce:Ldj;
    bipush 100
    invokevirtual dj as:(B)I
    istore 6
L21
    getstatic client ce:Ldj;
    ldc -999217047 (java.lang.Integer)
    invokevirtual dj ar:(I)I
    istore 7
    goto L22
L23
    iload 11
    iconst_3
    ishr
    sipush 2047
    iand
    istore 13
    goto L24
L25
    iload 4
    newarray 10
    putstatic ao dm:[I
    goto L8
L26
    iload 3
    bipush 8
    idiv
    bipush 48
    if_icmpeq L27
    iload 1
    iconst_0
    if_icmplt L28
    new java/lang/IllegalStateException
    dup
    invokespecial java/lang/IllegalStateException <init>:()V
    athrow
L29
    iload 10
    sipush 147
    if_icmpeq L30
    iload 1
    iconst_0
    if_icmplt L31
    new java/lang/IllegalStateException
    dup
    invokespecial java/lang/IllegalStateException <init>:()V
    athrow
L32
    iload 4
    anewarray [B
    putstatic ab dv:[[B
L33
    iconst_0
    istore 8
    goto L26
L34
    iload 9
    bipush 13
    if_icmpge L35
    iload 1
    iconst_0
    if_icmplt L36
    return
L28
    iload 3
    bipush 8
    idiv
    bipush 49
    if_icmpne L37
    iload 1
    iconst_0
    if_icmplt L27
    return
L27
    iload 5
    bipush 8
    idiv
    bipush 48
    if_icmpne L37
    goto L38
L39
    iload 6
    iconst_1
    if_icmpne L40
    iload 1
    iconst_0
    if_icmplt L41
    new java/lang/IllegalStateException
    dup
    invokespecial java/lang/IllegalStateException <init>:()V
    athrow
L41
    getstatic client de:[[[I
    iload 3
    aaload
    iload 4
    aaload
    iload 5
    getstatic client ce:Ldj;
    bipush 26
    ldc -253074223 (java.lang.Integer)
    invokevirtual dj hs:(II)I
    iastore
    goto L42
L43
    sipush 148
    iload 5
    bipush 8
    idiv
    if_icmpne L44
    iload 1
    iconst_0
    if_icmplt L45
    return
L46
    iinc 4 1
    goto L47
L44
    iconst_0
    istore 4
L48
    iload 3
    bipush 6
    isub
    bipush 8
    idiv
    istore 9
    goto L49
L50
    iload 3
    iconst_4
UNKNOWN-NODE:     multianewarray org.objectweb.asm.tree.MultiANewArrayInsnNode@42c0a16e
    putstatic e dt:[[I
    goto L51
L52
    iload 5
    iconst_4
    if_icmpge L53
    iload 1
    iconst_0
    if_icmplt L54
    new java/lang/IllegalStateException
    dup
    invokespecial java/lang/IllegalStateException <init>:()V
    athrow
L36
    iconst_0
    istore 10
    goto L55
L56
    iload 10
    iload 9
    bipush 8
    ishl
    iadd
    istore 11
L57
    iload 8
    ifeq L58
    iload 1
    iconst_0
    if_icmplt L59
    new java/lang/IllegalStateException
    dup
    invokespecial java/lang/IllegalStateException <init>:()V
    athrow
L59
    iload 10
    bipush 49
    if_icmpeq L30
    iload 1
    iconst_0
    if_icmplt L60
    return
L61
    getstatic client ce:Ldj;
    iconst_1
    ldc 1654750871 (java.lang.Integer)
    invokevirtual dj hs:(II)I
    istore 6
    goto L39
L62
    iconst_0
    istore 9
    goto L34
L37
    iload 3
    bipush 8
    idiv
    bipush 48
    if_icmpne L44
    iload 1
    iconst_0
    if_icmplt L43
    new java/lang/IllegalStateException
    dup
    invokespecial java/lang/IllegalStateException <init>:()V
    athrow
L63
    bipush 49
    iload 9
    if_icmpne L58
    goto L64
L54
    getstatic e dt:[[I
    iload 4
    aaload
    iload 5
    getstatic client ce:Ldj;
    ldc -2079700845 (java.lang.Integer)
    invokevirtual dj x:(I)I
    iastore
    goto L65
L66
    iload 5
    bipush 6
    isub
    bipush 8
    idiv
    istore 10
    goto L67
L58
    getstatic ae du:[I
    iload 4
    iload 11
    iastore
L68
    getstatic ao dm:[I
    iload 4
    getstatic ee bm:Lfo;
    new java/lang/StringBuilder
    dup
    invokespecial java/lang/StringBuilder <init>:()V
    ldc "m" (java.lang.String)
    invokevirtual java/lang/StringBuilder append:(Ljava/lang/String;)Ljava/lang/StringBuilder;
    iload 9
    invokevirtual java/lang/StringBuilder append:(I)Ljava/lang/StringBuilder;
    ldc "_" (java.lang.String)
    invokevirtual java/lang/StringBuilder append:(Ljava/lang/String;)Ljava/lang/StringBuilder;
    iload 10
    invokevirtual java/lang/StringBuilder append:(I)Ljava/lang/StringBuilder;
    invokevirtual java/lang/StringBuilder toString:()Ljava/lang/String;
    ldc 159496975 (java.lang.Integer)
    invokevirtual fo y:(Ljava/lang/String;I)I
    iastore
    goto L13
L30
    iinc 10 1
    goto L67
L14
    iinc 4 1
    goto L30
L31
    bipush 50
    iload 9
    if_icmpeq L30
    goto L63
L69
    iinc 9 1
    goto L49
L70
    iload 3
    iload 5
    iload 7
    iload 2
    iload 6
    bipush -16
    invokestatic c ad:(IIIIIB)V
L71
    goto L72
L18
    getstatic client ce:Ldj;
    ldc -2101369861 (java.lang.Integer)
    invokevirtual dj aq:(I)I
    istore 2
L73
    getstatic client ce:Ldj;
    bipush -49
    invokevirtual dj hi:(B)V
L74
    iconst_0
    istore 3
L75
    iload 3
    iconst_4
    if_icmpge L76
    iload 1
    iconst_0
    if_icmplt L77
    new java/lang/IllegalStateException
    dup
    invokespecial java/lang/IllegalStateException <init>:()V
    athrow
L77
    iconst_0
    istore 4
L47
    iload 4
    bipush 13
    if_icmpge L78
    iload 1
    iconst_0
    if_icmplt L79
    new java/lang/IllegalStateException
    dup
    invokespecial java/lang/IllegalStateException <init>:()V
    athrow
L79
    iconst_0
    istore 5
L80
    iload 5
    bipush 13
    if_icmpge L46
    iload 1
    iconst_0
    if_icmplt L61
    return
L38
    iconst_1
    istore 8
    goto L37
L78
    iinc 3 1
    goto L75
L60
    sipush 149
    iload 10
    if_icmpeq L30
    iload 1
    iconst_0
    if_icmplt L29
    return
L64
    iload 10
    bipush 47
    if_icmpne L58
    iload 1
    iconst_0
    if_icmplt L81
    new java/lang/IllegalStateException
    dup
    invokespecial java/lang/IllegalStateException <init>:()V
    athrow
L42
    iinc 5 1
    goto L80
L82
    iinc 15 1
    goto L83
L7
    getstatic client ce:Ldj;
    bipush 99
    invokevirtual dj as:(B)I
    istore 3
    goto L10
L67
    iload 10
    bipush 6
    iload 5
    iadd
    bipush 8
    idiv
    if_icmpgt L69
    iload 1
    iconst_0
    if_icmplt L56
    new java/lang/IllegalStateException
    dup
    invokespecial java/lang/IllegalStateException <init>:()V
    athrow
L84
    getstatic client cm:I
    ldc 2039932147 (java.lang.Integer)
    imul
    getstatic client ce:Ldj;
    getfield dj a:I
    ldc 910905453 (java.lang.Integer)
    imul
    isub
    bipush 16
    idiv
    istore 3
    goto L50
L85
    iload 14
    bipush 8
    ishr
    sipush 255
    iand
    istore 15
    goto L86
L51
    iconst_0
    istore 4
L87
    iload 4
    iload 3
    if_icmpge L88
L89
    iconst_0
    istore 5
    goto L52
L12
    iconst_0
    istore 5
    goto L15
L9
    iload 4
    anewarray [B
    putstatic da dl:[[B
    goto L32
L65
    iinc 5 1
    goto L52
L76
    getstatic client ce:Ldj;
    iconst_3
    invokevirtual dj hu:(B)V
    goto L84
L88
    getstatic client ce:Ldj;
    bipush -41
    invokevirtual dj bl:(B)I
    istore 4
L90
    getstatic client ce:Ldj;
    bipush 75
    invokevirtual dj as:(B)I
    istore 5
L91
    getstatic client ce:Ldj;
    bipush 113
    invokevirtual dj as:(B)I
    istore 6
L92
    getstatic client ce:Ldj;
    ldc -1284776918 (java.lang.Integer)
    invokevirtual dj aa:(I)I
    istore 7
L93
    iload 3
    newarray 10
    putstatic ae du:[I
L94
    iload 3
    newarray 10
    putstatic ao dm:[I
L95
    iload 3
    newarray 10
    putstatic cw dj:[I
    goto L96
L22
    iload 4
    newarray 10
    putstatic ae du:[I
    goto L25
L97
    iload 3
    anewarray [B
    putstatic ab dv:[[B
    goto L98
L72
    return
L99
    iconst_0
    istore 8
L100
    iload 8
    iconst_4
    if_icmpge L101
    iload 1
    iconst_0
    if_icmplt L62
    new java/lang/IllegalStateException
    dup
    invokespecial java/lang/IllegalStateException <init>:()V
    athrow
L81
    goto L30
L98
    iconst_0
    istore 3
    goto L99
L40
    getstatic client de:[[[I
    iload 3
    aaload
    iload 4
    aaload
    iload 5
    iconst_m1
    iastore
    goto L42
L55
    iload 10
    bipush 13
    if_icmpge L102
    iload 1
    iconst_0
    if_icmplt L103
    new java/lang/IllegalStateException
    dup
    invokespecial java/lang/IllegalStateException <init>:()V
    athrow
L103
    getstatic client de:[[[I
    iload 8
    aaload
    iload 9
    aaload
    iload 10
    iaload
    istore 11
L104
    iload 11
    iconst_m1
    if_icmpeq L105
    iload 1
    iconst_0
    if_icmplt L106
    new java/lang/IllegalStateException
    dup
    invokespecial java/lang/IllegalStateException <init>:()V
    athrow
L106
    iload 11
    bipush 14
    ishr
    sipush 1023
    iand
    istore 12
    goto L23
L83
    iload 15
    iload 3
    if_icmpge L107
    iload 1
    iconst_0
    if_icmplt L108
    new java/lang/IllegalStateException
    dup
    invokespecial java/lang/IllegalStateException <init>:()V
    athrow
L24
    iload 13
    bipush 8
    idiv
    iload 12
    bipush 8
    idiv
    bipush 8
    ishl
    iadd
    istore 14
L109
    iconst_0
    istore 15
    goto L83
L110
    getstatic ae du:[I
    iload 3
    iload 14
    iastore
    goto L85
L108
    iload 14
    getstatic ae du:[I
    iload 15
    iaload
    if_icmpne L82
    iload 1
    iconst_0
    if_icmplt L111
    return
L111
    iconst_m1
    istore 14
    goto L112
L49
    iload 9
    bipush 6
    iload 3
    iadd
    bipush 8
    idiv
    if_icmpgt L70
    goto L66
L45
    iconst_1
    istore 8
    goto L44
L107
    iload 14
    iconst_m1
    if_icmpeq L105
    iload 1
    iconst_0
    if_icmplt L110
    new java/lang/IllegalStateException
    dup
    invokespecial java/lang/IllegalStateException <init>:()V
    athrow
L53
    iinc 4 1
    goto L87
L112
    goto L107
L86
    iload 14
    sipush 255
    iand
    istore 16
L113
    getstatic ao dm:[I
    iload 3
    getstatic ee bm:Lfo;
    new java/lang/StringBuilder
    dup
    invokespecial java/lang/StringBuilder <init>:()V
    ldc "m" (java.lang.String)
    invokevirtual java/lang/StringBuilder append:(Ljava/lang/String;)Ljava/lang/StringBuilder;
    iload 15
    invokevirtual java/lang/StringBuilder append:(I)Ljava/lang/StringBuilder;
    ldc "_" (java.lang.String)
    invokevirtual java/lang/StringBuilder append:(Ljava/lang/String;)Ljava/lang/StringBuilder;
    iload 16
    invokevirtual java/lang/StringBuilder append:(I)Ljava/lang/StringBuilder;
    invokevirtual java/lang/StringBuilder toString:()Ljava/lang/String;
    ldc 206029358 (java.lang.Integer)
    invokevirtual fo y:(Ljava/lang/String;I)I
    iastore
L114
    getstatic cw dj:[I
    iload 3
    getstatic ee bm:Lfo;
    new java/lang/StringBuilder
    dup
    invokespecial java/lang/StringBuilder <init>:()V
    ldc "l" (java.lang.String)
    invokevirtual java/lang/StringBuilder append:(Ljava/lang/String;)Ljava/lang/StringBuilder;
    iload 15
    invokevirtual java/lang/StringBuilder append:(I)Ljava/lang/StringBuilder;
    ldc "_" (java.lang.String)
    invokevirtual java/lang/StringBuilder append:(Ljava/lang/String;)Ljava/lang/StringBuilder;
    iload 16
    invokevirtual java/lang/StringBuilder append:(I)Ljava/lang/StringBuilder;
    invokevirtual java/lang/StringBuilder toString:()Ljava/lang/String;
    ldc -1835261304 (java.lang.Integer)
    invokevirtual fo y:(Ljava/lang/String;I)I
    iastore
L115
    iinc 3 1
L105
    iinc 10 1
    goto L55
L102
    iinc 9 1
    goto L34
L35
    iinc 8 1
    goto L100
L101
    iload 7
    iload 4
    iload 2
    iload 5
    iload 6
    bipush -28
    invokestatic c ad:(IIIIIB)V
    goto L72
L96
    iload 3
    anewarray [B
    putstatic da dl:[[B
    goto L97
L116
    new java/lang/StringBuilder
    dup
    invokespecial java/lang/StringBuilder <init>:()V
    ldc "y.ac(" (java.lang.String)
    invokevirtual java/lang/StringBuilder append:(Ljava/lang/String;)Ljava/lang/StringBuilder;
    ldc 41 (java.lang.Integer)
    invokevirtual java/lang/StringBuilder append:(C)Ljava/lang/StringBuilder;
    invokevirtual java/lang/StringBuilder toString:()Ljava/lang/String;
    invokestatic k a:(Ljava/lang/Throwable;Ljava/lang/String;)Lee;
    athrow
