y ay (IIIII)VL1
    iload 0
    iload 1
    iload 2
    iload 0
    iadd
    iload 3
    iload 1
    iadd
    invokestatic bt cw:(IIII)V
    goto L2
L3
    iconst_3
    istore 7
    goto L4
L5
    getstatic client gn:I
    ldc -929168997 (java.lang.Integer)
    iadd
    putstatic client gn:I
L6
    getstatic aw e:Law;
    sipush 256
    invokestatic ep ag:(Law;S)V
L7
    iconst_0
    istore 5
L8
    ldc 7317091 (java.lang.Integer)
    getstatic client hd:I
    imul
    iflt L9
    iload 4
    ldc -844363041 (java.lang.Integer)
    if_icmpeq L10
    return
L10
    iconst_0
    istore 6
L11
    iload 6
    ldc 308668811 (java.lang.Integer)
    getstatic client hr:I
    imul
    if_icmpge L9
    iload 4
    ldc -844363041 (java.lang.Integer)
    if_icmpeq L12
    new java/lang/IllegalStateException
    dup
    invokespecial java/lang/IllegalStateException <init>:()V
    athrow
L13
    getstatic ev fj:I
    ldc -514809633 (java.lang.Integer)
    imul
    ldc -494234791 (java.lang.Integer)
    getstatic e fe:I
    imul
    getstatic fd hz:I
    ldc -837647185 (java.lang.Integer)
    imul
    ldc 1958062732 (java.lang.Integer)
    invokestatic cl ar:(IIII)I
    istore 8
    goto L14
L15
    iconst_1
    istore 5
    goto L16
L17
    iconst_m1
    iload 16
    if_icmpne L18
    iload 4
    ldc -844363041 (java.lang.Integer)
    if_icmpeq L19
    new java/lang/IllegalStateException
    dup
    invokespecial java/lang/IllegalStateException <init>:()V
    athrow
L20
    iinc 6 1
    goto L11
L9
    iload 5
    ifeq L21
    iload 4
    ldc -844363041 (java.lang.Integer)
    if_icmpeq L22
    new java/lang/IllegalStateException
    dup
    invokespecial java/lang/IllegalStateException <init>:()V
    athrow
L22
    getstatic aw a:Law;
    sipush 256
    invokestatic ep ag:(Law;S)V
    goto L21
L2
    invokestatic cp e:()V
    goto L5
L23
    iload 5
    ifeq L24
    iload 4
    ldc -844363041 (java.lang.Integer)
    if_icmpeq L25
    return
L26
    iinc 16 1
    goto L27
L28
    getstatic gy co:Lhh;
    new java/lang/StringBuilder
    dup
    invokespecial java/lang/StringBuilder <init>:()V
    ldc "Mem:" (java.lang.String)
    invokevirtual java/lang/StringBuilder append:(Ljava/lang/String;)Ljava/lang/StringBuilder;
    iload 17
    invokevirtual java/lang/StringBuilder append:(I)Ljava/lang/StringBuilder;
    ldc "k" (java.lang.String)
    invokevirtual java/lang/StringBuilder append:(Ljava/lang/String;)Ljava/lang/StringBuilder;
    invokevirtual java/lang/StringBuilder toString:()Ljava/lang/String;
    iload 14
    iload 15
    iload 18
    iconst_m1
    invokevirtual hh g:(Ljava/lang/String;IIII)V
    goto L29
L30
    sipush 256
    invokestatic ep ag:(Law;S)V
    goto L31
L32
    goto L4
L33
    getstatic client ho:Lgh;
    invokevirtual gh i:()Lgm;
    checkcast i
    astore 6
L34
    aconst_null
    aload 6
    if_acmpeq L35
    iload 4
    ldc -844363041 (java.lang.Integer)
    if_icmpeq L36
    new java/lang/IllegalStateException
    dup
    invokespecial java/lang/IllegalStateException <init>:()V
    athrow
L37
    return
L38
    ldc -117546507 (java.lang.Integer)
    getstatic client b:I
    imul
    aload 6
    getfield i r:I
    ldc -695449035 (java.lang.Integer)
    imul
    if_icmple L39
    iload 4
    ldc -844363041 (java.lang.Integer)
    if_icmpeq L40
    new java/lang/IllegalStateException
    dup
    invokespecial java/lang/IllegalStateException <init>:()V
    athrow
L41
    getstatic client cf:[Lam;
    ldc -985603043 (java.lang.Integer)
    aload 6
    getfield i o:I
    imul
    iconst_1
    isub
    aaload
    astore 7
    goto L42
L39
    ldc -117546507 (java.lang.Integer)
    getstatic client b:I
    imul
    ldc -21978375 (java.lang.Integer)
    aload 6
    getfield i i:I
    imul
    if_icmplt L43
    iload 4
    ldc -844363041 (java.lang.Integer)
    if_icmpeq L44
    new java/lang/IllegalStateException
    dup
    invokespecial java/lang/IllegalStateException <init>:()V
    athrow
L45
    aload 6
    aload 7
    getfield l b:I
    ldc 1164900853 (java.lang.Integer)
    imul
    aload 7
    getfield l x:I
    ldc 109190397 (java.lang.Integer)
    imul
    aload 7
    getfield l b:I
    ldc 1164900853 (java.lang.Integer)
    imul
    ldc 109190397 (java.lang.Integer)
    aload 7
    getfield l x:I
    imul
    aload 6
    getfield i a:I
    ldc 1511118707 (java.lang.Integer)
    imul
    ldc 1958062732 (java.lang.Integer)
    invokestatic cl ar:(IIII)I
    ldc 537825681 (java.lang.Integer)
    aload 6
    getfield i w:I
    imul
    isub
    getstatic client b:I
    ldc -117546507 (java.lang.Integer)
    imul
    ldc -117853029 (java.lang.Integer)
    invokevirtual i e:(IIIII)V
    goto L46
L47
    iconst_0
    putstatic cy bv:I
    goto L48
L42
    aload 7
    ifnull L49
    goto L50
L51
    aload 7
    ifnull L46
    iload 4
    ldc -844363041 (java.lang.Integer)
    if_icmpeq L52
    return
L53
    iload 24
    sipush 150
    if_icmpge L54
    iload 4
    ldc -844363041 (java.lang.Integer)
    if_icmpeq L55
    return
L56
    iload 12
    iload 0
    iload 2
    iadd
    if_icmpge L57
    iload 4
    ldc -844363041 (java.lang.Integer)
    if_icmpeq L58
    new java/lang/IllegalStateException
    dup
    invokespecial java/lang/IllegalStateException <init>:()V
    athrow
L59
    aload 7
    getfield am x:I
    ldc 109190397 (java.lang.Integer)
    imul
    sipush 13312
    if_icmpge L49
    goto L60
L61
    getstatic client gn:I
    ldc 1549434003 (java.lang.Integer)
    imul
    bipush 20
    irem
    bipush 10
    if_icmpge L62
    goto L63
L49
    aload 6
    getfield i o:I
    ldc -985603043 (java.lang.Integer)
    imul
    ifge L46
    goto L64
L65
    iload 15
    sipush 3062
    if_icmpgt L66
    iload 4
    ldc -844363041 (java.lang.Integer)
    if_icmpeq L67
    new java/lang/IllegalStateException
    dup
    invokespecial java/lang/IllegalStateException <init>:()V
    athrow
L68
    getstatic ep j:I
    ldc -642165313 (java.lang.Integer)
    imul
    istore 12
    goto L69
L70
    getstatic hg hv:Ll;
    astore 7
    goto L51
L71
    getstatic client hg:[Ll;
    iload 8
    aaload
    astore 7
    goto L51
L72
    aload 6
    getstatic client ew:I
    ldc 509485067 (java.lang.Integer)
    imul
    ldc 872909031 (java.lang.Integer)
    invokevirtual ap e:(II)V
    goto L73
L52
    aload 7
    getfield l b:I
    ldc 1164900853 (java.lang.Integer)
    imul
    iflt L46
    iload 4
    ldc -844363041 (java.lang.Integer)
    if_icmpeq L74
    return
L75
    iload 24
    bipush 100
    isub
    iconst_5
    imul
    ldc 65280 (java.lang.Integer)
    iadd
    istore 23
    goto L76
L77
    getstatic client gf:[Ljava/lang/String;
    iload 16
    aaload
    astore 22
    goto L78
L79
    iload 16
    ldc 168556945 (java.lang.Integer)
    getstatic client fm:I
    imul
    if_icmpge L80
    iload 4
    ldc -844363041 (java.lang.Integer)
    if_icmpeq L81
    return
L82
    getstatic client fl:I
    ldc 1650051081 (java.lang.Integer)
    imul
    istore 6
    goto L83
L46
    aload 6
    ldc 509485067 (java.lang.Integer)
    getstatic client ew:I
    imul
    iconst_1
    invokevirtual i l:(IB)V
    goto L84
L64
    aload 6
    getfield i o:I
    ldc -985603043 (java.lang.Integer)
    imul
    ineg
    iconst_1
    isub
    istore 8
    goto L85
L43
    getstatic client ho:Lgh;
    invokevirtual gh f:()Lgm;
    checkcast i
    astore 6
    goto L34
L86
    iload 18
    iconst_2
    iadd
    getstatic client fa:[I
    iload 22
    iaload
    getstatic client fn:[I
    iload 22
    iaload
    isub
    if_icmple L87
    goto L88
L89
    ldc 109190397 (java.lang.Integer)
    aload 7
    getfield am x:I
    imul
    iflt L49
    iload 4
    ldc -844363041 (java.lang.Integer)
    if_icmpeq L59
    new java/lang/IllegalStateException
    dup
    invokespecial java/lang/IllegalStateException <init>:()V
    athrow
L90
    ldc -837647185 (java.lang.Integer)
    getstatic fd hz:I
    imul
    ldc 1665009545 (java.lang.Integer)
    aload 6
    getfield ap l:I
    imul
    if_icmpne L91
    iload 4
    ldc -844363041 (java.lang.Integer)
    if_icmpeq L92
    new java/lang/IllegalStateException
    dup
    invokespecial java/lang/IllegalStateException <init>:()V
    athrow
L92
    aload 6
    getfield ap g:Z
    ifeq L93
    iload 4
    ldc -844363041 (java.lang.Integer)
    if_icmpeq L91
    return
L94
    getstatic e fe:I
    ldc -494234791 (java.lang.Integer)
    imul
    istore 9
    goto L95
L93
    getstatic client b:I
    ldc -117546507 (java.lang.Integer)
    imul
    aload 6
    getfield ap a:I
    ldc -64640073 (java.lang.Integer)
    imul
    if_icmplt L96
    iload 4
    ldc -844363041 (java.lang.Integer)
    if_icmpeq L72
    new java/lang/IllegalStateException
    dup
    invokespecial java/lang/IllegalStateException <init>:()V
    athrow
L97
    iconst_1
    getstatic client gq:[I
    iload 16
    iaload
    if_icmpne L98
    iload 4
    ldc -844363041 (java.lang.Integer)
    if_icmpeq L99
    return
L73
    aload 6
    getfield ap g:Z
    ifeq L100
    iload 4
    ldc -844363041 (java.lang.Integer)
    if_icmpeq L101
    new java/lang/IllegalStateException
    dup
    invokespecial java/lang/IllegalStateException <init>:()V
    athrow
L102
    ldc -2018558187 (java.lang.Integer)
    getstatic client gd:I
    imul
    iconst_2
    if_icmpne L103
    goto L104
L100
    getstatic n ds:Lcb;
    ldc 1665009545 (java.lang.Integer)
    aload 6
    getfield ap l:I
    imul
    aload 6
    getfield ap c:I
    ldc -2024215077 (java.lang.Integer)
    imul
    ldc -129974993 (java.lang.Integer)
    aload 6
    getfield ap u:I
    imul
    aload 6
    getfield ap w:I
    ldc 569730493 (java.lang.Integer)
    imul
    bipush 60
    aload 6
    iconst_0
    iconst_m1
    iconst_0
    invokevirtual cb h:(IIIIILch;IIZ)Z
    pop
    goto L96
L105
    iload 12
    ifne L106
    goto L107
L108
    getstatic client nz:Z
    ifne L109
    iload 4
    ldc -844363041 (java.lang.Integer)
    if_icmpeq L82
    new java/lang/IllegalStateException
    dup
    invokespecial java/lang/IllegalStateException <init>:()V
    athrow
L110
    iload 0
    iload 1
    iload 2
    iload 3
    iconst_0
    invokestatic bt cs:(IIIII)V
    goto L111
L83
    getstatic client fr:I
    ldc 481733069 (java.lang.Integer)
    imul
    sipush 256
    idiv
    iload 6
    if_icmple L112
    iload 4
    ldc -844363041 (java.lang.Integer)
    if_icmpeq L113
    new java/lang/IllegalStateException
    dup
    invokespecial java/lang/IllegalStateException <init>:()V
    athrow
L113
    ldc 481733069 (java.lang.Integer)
    getstatic client fr:I
    imul
    sipush 256
    idiv
    istore 6
L112
    getstatic client om:[Z
    iconst_4
    baload
    ifeq L114
    goto L115
L116
    getstatic dk ol:Lf;
    getfield f l:Z
    ifeq L13
    iload 4
    ldc -844363041 (java.lang.Integer)
    if_icmpeq L117
    new java/lang/IllegalStateException
    dup
    invokespecial java/lang/IllegalStateException <init>:()V
    athrow
L84
    getstatic n ds:Lcb;
    ldc -837647185 (java.lang.Integer)
    getstatic fd hz:I
    imul
    aload 6
    getfield i s:D
    d2i
    aload 6
    getfield i j:D
    d2i
    aload 6
    getfield i m:D
    d2i
    bipush 60
    aload 6
    aload 6
    getfield i b:I
    ldc 1112625425 (java.lang.Integer)
    imul
    iconst_m1
    iconst_0
    invokevirtual cb h:(IIIIILch;IIZ)Z
    pop
    goto L43
L114
    getstatic client fy:I
    ldc 154136385 (java.lang.Integer)
    imul
    getstatic client dz:I
    ldc 694455695 (java.lang.Integer)
    imul
    iadd
    sipush 2047
    iand
    istore 7
L118
    getstatic dh fx:I
    ldc -1834691 (java.lang.Integer)
    imul
    getstatic hg hv:Ll;
    getfield l b:I
    ldc 1164900853 (java.lang.Integer)
    imul
    ldc 109190397 (java.lang.Integer)
    getstatic hg hv:Ll;
    getfield l x:I
    imul
    getstatic fd hz:I
    ldc -837647185 (java.lang.Integer)
    imul
    ldc 1958062732 (java.lang.Integer)
    invokestatic cl ar:(IIII)I
    bipush 50
    isub
    getstatic ap fg:I
    ldc -910012941 (java.lang.Integer)
    imul
    iload 6
    iload 7
    iconst_3
    iload 6
    imul
    sipush 600
    iadd
    bipush 115
    invokestatic cj aq:(IIIIIIB)V
L109
    getstatic client nz:Z
    ifne L116
    iload 4
    ldc -844363041 (java.lang.Integer)
    if_icmpeq L119
    new java/lang/IllegalStateException
    dup
    invokespecial java/lang/IllegalStateException <init>:()V
    athrow
L119
    iconst_5
    invokestatic r ah:(B)I
    istore 6
    goto L120
L121
    iload 21
    ifeq L122
    iload 4
    ldc -844363041 (java.lang.Integer)
    if_icmpeq L123
    new java/lang/IllegalStateException
    dup
    invokespecial java/lang/IllegalStateException <init>:()V
    athrow
L117
    ldc -837647185 (java.lang.Integer)
    getstatic fd hz:I
    imul
    istore 7
L124
    goto L4
L115
    getstatic client ok:[I
    iconst_4
    iaload
    sipush 128
    iadd
    iload 6
    if_icmple L114
    goto L125
L14
    iload 8
    getstatic ev fz:I
    ldc -866461883 (java.lang.Integer)
    imul
    isub
    sipush 800
    if_icmpge L3
    iload 4
    ldc -844363041 (java.lang.Integer)
    if_icmpeq L126
    new java/lang/IllegalStateException
    dup
    invokespecial java/lang/IllegalStateException <init>:()V
    athrow
L126
    iconst_0
    getstatic w a:[[[B
    getstatic fd hz:I
    ldc -837647185 (java.lang.Integer)
    imul
    aaload
    getstatic ev fj:I
    ldc -514809633 (java.lang.Integer)
    imul
    bipush 7
    ishr
    aaload
    ldc -494234791 (java.lang.Integer)
    getstatic e fe:I
    imul
    bipush 7
    ishr
    baload
    iconst_4
    iand
    if_icmpeq L3
    goto L127
L128
    ldc 1164900853 (java.lang.Integer)
    aload 7
    getfield am b:I
    imul
    sipush 13312
    if_icmpge L49
    iload 4
    ldc -844363041 (java.lang.Integer)
    if_icmpeq L89
    new java/lang/IllegalStateException
    dup
    invokespecial java/lang/IllegalStateException <init>:()V
    athrow
L129
    iconst_5
    getstatic client gq:[I
    iload 16
    iaload
    if_icmpne L130
    iload 4
    ldc -844363041 (java.lang.Integer)
    if_icmpeq L131
    new java/lang/IllegalStateException
    dup
    invokespecial java/lang/IllegalStateException <init>:()V
    athrow
L101
    aload 6
    invokevirtual ap if:()V
    goto L96
L29
    iinc 15 15
    goto L132
L120
    getstatic ev fj:I
    ldc -514809633 (java.lang.Integer)
    imul
    istore 7
L133
    ldc -866461883 (java.lang.Integer)
    getstatic ev fz:I
    imul
    istore 8
    goto L94
L134
    getstatic s fb:I
    ldc -827356221 (java.lang.Integer)
    imul
    sipush 383
    if_icmple L135
    iload 4
    ldc -844363041 (java.lang.Integer)
    if_icmpeq L136
    return
L74
    aload 7
    getfield l b:I
    ldc 1164900853 (java.lang.Integer)
    imul
    sipush 13312
    if_icmpge L46
    iload 4
    ldc -844363041 (java.lang.Integer)
    if_icmpeq L137
    new java/lang/IllegalStateException
    dup
    invokespecial java/lang/IllegalStateException <init>:()V
    athrow
L138
    getstatic ez fk:I
    ldc -472476531 (java.lang.Integer)
    imul
    istore 11
L139
    iconst_0
    istore 12
L140
    iload 12
    iconst_5
    if_icmpge L141
    iload 4
    ldc -844363041 (java.lang.Integer)
    if_icmpeq L142
    new java/lang/IllegalStateException
    dup
    invokespecial java/lang/IllegalStateException <init>:()V
    athrow
L142
    getstatic client om:[Z
    iload 12
    baload
    ifeq L135
    iload 4
    ldc -844363041 (java.lang.Integer)
    if_icmpeq L143
    new java/lang/IllegalStateException
    dup
    invokespecial java/lang/IllegalStateException <init>:()V
    athrow
L143
    invokestatic java/lang/Math random:()D
    iconst_1
    getstatic client of:[I
    iload 12
    iaload
    iconst_2
    imul
    iadd
    i2d
    dmul
    getstatic client of:[I
    iload 12
    iaload
    i2d
    dsub
    getstatic client od:[I
    iload 12
    iaload
    i2d
    getstatic client oz:[I
    iload 12
    iaload
    i2d
    ldc 100.0 (java.lang.Double)
    ddiv
    dmul
    invokestatic java/lang/Math sin:(D)D
    getstatic client ok:[I
    iload 12
    iaload
    i2d
    dmul
    dadd
    d2i
    istore 13
    goto L105
L144
    sipush 150
    getstatic client gg:[I
    iload 16
    iaload
    isub
    istore 24
    goto L145
L107
    getstatic ev fj:I
    iload 13
    ldc -648340705 (java.lang.Integer)
    imul
    iadd
    putstatic ev fj:I
L106
    iload 12
    iconst_1
    if_icmpne L146
    iload 4
    ldc -844363041 (java.lang.Integer)
    if_icmpeq L147
    return
L147
    getstatic ev fz:I
    iload 13
    ldc 1416962957 (java.lang.Integer)
    imul
    iadd
    putstatic ev fz:I
L146
    iconst_2
    iload 12
    if_icmpne L148
    iload 4
    ldc -844363041 (java.lang.Integer)
    if_icmpeq L149
    new java/lang/IllegalStateException
    dup
    invokespecial java/lang/IllegalStateException <init>:()V
    athrow
L150
    iload 24
    bipush 100
    if_icmpge L151
    iload 4
    ldc -844363041 (java.lang.Integer)
    if_icmpeq L152
    new java/lang/IllegalStateException
    dup
    invokespecial java/lang/IllegalStateException <init>:()V
    athrow
L148
    iload 12
    iconst_3
    if_icmpne L153
    iload 4
    ldc -844363041 (java.lang.Integer)
    if_icmpeq L154
    new java/lang/IllegalStateException
    dup
    invokespecial java/lang/IllegalStateException <init>:()V
    athrow
L154
    ldc -381465019 (java.lang.Integer)
    iload 13
    ldc -472476531 (java.lang.Integer)
    getstatic ez fk:I
    imul
    iadd
    sipush 2047
    iand
    imul
    putstatic ez fk:I
L153
    iconst_4
    iload 12
    if_icmpne L135
    iload 4
    ldc -844363041 (java.lang.Integer)
    if_icmpeq L155
    new java/lang/IllegalStateException
    dup
    invokespecial java/lang/IllegalStateException <init>:()V
    athrow
L155
    getstatic s fb:I
    ldc 1391672555 (java.lang.Integer)
    iload 13
    imul
    iadd
    putstatic s fb:I
L156
    ldc -827356221 (java.lang.Integer)
    getstatic s fb:I
    imul
    sipush 128
    if_icmpge L134
    iload 4
    ldc -844363041 (java.lang.Integer)
    if_icmpeq L157
    return
L157
    ldc 2040427904 (java.lang.Integer)
    putstatic s fb:I
    goto L134
L16
    goto L9
L136
    ldc 434643861 (java.lang.Integer)
    putstatic s fb:I
L135
    iinc 12 1
    goto L140
L158
    iload 14
    sipush 3118
    if_icmpgt L159
    iload 4
    ldc -844363041 (java.lang.Integer)
    if_icmpeq L160
    return
L161
    ldc -1616406211 (java.lang.Integer)
    getstatic ep r:I
    imul
    istore 13
L162
    iconst_0
    getstatic ep s:I
    ldc -1750678861 (java.lang.Integer)
    imul
    if_icmpeq L163
    goto L68
L164
    iconst_1
    istore 14
    goto L165
L166
    ldc 16776960 (java.lang.Integer)
    istore 23
    goto L167
L168
    iload 24
    bipush 125
    isub
    istore 25
    goto L169
L40
    aload 6
    invokevirtual i if:()V
    goto L43
L58
    iload 13
    iload 1
    if_icmplt L57
    iload 4
    ldc -844363041 (java.lang.Integer)
    if_icmpeq L170
    new java/lang/IllegalStateException
    dup
    invokespecial java/lang/IllegalStateException <init>:()V
    athrow
L66
    getstatic client ao:Z
    ifeq L132
    goto L171
L172
    iconst_1
    putstatic cy bw:Z
    goto L47
L173
    ldc 16711680 (java.lang.Integer)
    istore 18
    goto L174
L48
    iload 12
    iload 0
    isub
    putstatic cy bp:I
L175
    iload 13
    iload 1
    isub
    putstatic cy be:I
    goto L176
L24
    getstatic aw l:Law;
    goto L30
L177
    iconst_0
    putstatic cy bv:I
L176
    ldc -2021744604 (java.lang.Integer)
    invokestatic cw n:(I)V
    goto L110
L63
    ldc 16711680 (java.lang.Integer)
    goto L178
L111
    ldc -1985432894 (java.lang.Integer)
    invokestatic cw n:(I)V
L179
    getstatic n ds:Lcb;
    ldc -514809633 (java.lang.Integer)
    getstatic ev fj:I
    imul
    getstatic ev fz:I
    ldc -866461883 (java.lang.Integer)
    imul
    getstatic e fe:I
    ldc -494234791 (java.lang.Integer)
    imul
    getstatic s fb:I
    ldc -827356221 (java.lang.Integer)
    imul
    ldc -472476531 (java.lang.Integer)
    getstatic ez fk:I
    imul
    iload 6
    invokevirtual cb aj:(IIIIII)V
    goto L180
L181
    goto L121
L182
    getstatic n ds:Lcb;
    invokevirtual cb m:()V
    goto L183
L85
    iload 8
    ldc 1958675107 (java.lang.Integer)
    getstatic client ht:I
    imul
    if_icmpne L71
    iload 4
    ldc -844363041 (java.lang.Integer)
    if_icmpeq L70
    return
L184
    iconst_0
    istore 14
L185
    iconst_m1
    istore 15
L186
    iconst_m1
    istore 16
L27
    iload 16
    ldc -1048248787 (java.lang.Integer)
    getstatic client ch:I
    imul
    getstatic client hr:I
    ldc 308668811 (java.lang.Integer)
    imul
    iadd
    if_icmpge L187
    goto L17
L188
    sipush 150
    getstatic client gg:[I
    iload 16
    iaload
    isub
    istore 24
    goto L189
L19
    getstatic hg hv:Ll;
    astore 17
    goto L190
L18
    iload 16
    getstatic client hr:I
    ldc 308668811 (java.lang.Integer)
    imul
    if_icmpge L191
    iload 4
    ldc -844363041 (java.lang.Integer)
    if_icmpeq L192
    new java/lang/IllegalStateException
    dup
    invokespecial java/lang/IllegalStateException <init>:()V
    athrow
L192
    getstatic client hg:[Ll;
    getstatic client hw:[I
    iload 16
    iaload
    aaload
    astore 17
L193
    ldc 7317091 (java.lang.Integer)
    getstatic client hd:I
    imul
    getstatic client hw:[I
    iload 16
    iaload
    if_icmpne L190
    iload 4
    ldc -844363041 (java.lang.Integer)
    if_icmpeq L164
    new java/lang/IllegalStateException
    dup
    invokespecial java/lang/IllegalStateException <init>:()V
    athrow
L180
    ldc -1858566822 (java.lang.Integer)
    invokestatic cw n:(I)V
    goto L182
L44
    ldc -985603043 (java.lang.Integer)
    aload 6
    getfield i o:I
    imul
    ifle L49
    iload 4
    ldc -844363041 (java.lang.Integer)
    if_icmpeq L41
    new java/lang/IllegalStateException
    dup
    invokespecial java/lang/IllegalStateException <init>:()V
    athrow
L194
    goto L26
L195
    getstatic client fn:[I
    iload 16
    iaload
    istore 20
    goto L196
L95
    getstatic s fb:I
    ldc -827356221 (java.lang.Integer)
    imul
    istore 10
    goto L138
L197
    iload 17
    ldc 32768 (java.lang.Integer)
    if_icmple L174
    goto L198
L187
    iload 14
    ifeq L199
    goto L200
L163
    iload 12
    iload 0
    if_icmplt L57
    goto L56
L199
    iconst_0
    istore 16
    goto L79
L178
    istore 23
    goto L201
L81
    getstatic client ft:[I
    iload 16
    iaload
    istore 17
    goto L202
L203
    ldc 45056 (java.lang.Integer)
    goto L204
L205
    getstatic client fs:[I
    iload 16
    iaload
    istore 19
    goto L195
L206
    ldc 109190397 (java.lang.Integer)
    aload 7
    getfield l x:I
    imul
    sipush 13312
    if_icmpge L46
    goto L45
L196
    iconst_1
    istore 21
    goto L121
L25
    getstatic aw c:Law;
    goto L30
L123
    iconst_0
    istore 21
L207
    iconst_0
    istore 22
    goto L208
L141
    ldc -1976433391 (java.lang.Integer)
    getstatic ep i:I
    imul
    istore 12
    goto L161
L137
    aload 7
    getfield l x:I
    ldc 109190397 (java.lang.Integer)
    imul
    iflt L46
    iload 4
    ldc -844363041 (java.lang.Integer)
    if_icmpeq L206
    new java/lang/IllegalStateException
    dup
    invokespecial java/lang/IllegalStateException <init>:()V
    athrow
L88
    iload 18
    iload 20
    isub
    getstatic client fa:[I
    iload 22
    iaload
    iconst_2
    iadd
    if_icmpge L87
    iload 4
    ldc -844363041 (java.lang.Integer)
    if_icmpeq L209
    new java/lang/IllegalStateException
    dup
    invokespecial java/lang/IllegalStateException <init>:()V
    athrow
L209
    iload 17
    iload 19
    isub
    getstatic client fs:[I
    iload 22
    iaload
    getstatic client ft:[I
    iload 22
    iaload
    iadd
    if_icmpge L87
    iload 17
    iload 19
    iadd
    getstatic client ft:[I
    iload 22
    iaload
    getstatic client fs:[I
    iload 22
    iaload
    isub
    if_icmple L87
    iload 4
    ldc -844363041 (java.lang.Integer)
    if_icmpeq L210
    new java/lang/IllegalStateException
    dup
    invokespecial java/lang/IllegalStateException <init>:()V
    athrow
L211
    iload 0
    iload 1
    iload 2
    iload 0
    iadd
    iload 1
    iload 3
    iadd
    invokestatic bt cw:(IIII)V
    goto L130
L35
    getstatic client hi:Lgh;
    invokevirtual gh i:()Lgm;
    checkcast ap
    astore 6
    goto L212
L213
    iconst_1
    istore 21
L87
    iinc 22 1
    goto L208
L4
    iload 7
    istore 6
    goto L120
L122
    ldc 428275229 (java.lang.Integer)
    getstatic client ft:[I
    iload 16
    iaload
    imul
    putstatic client gh:I
L214
    getstatic client fa:[I
    iload 16
    iload 18
    dup_x2
    iastore
    ldc 2118733097 (java.lang.Integer)
    imul
    putstatic client gi:I
    goto L77
L21
    iconst_1
    ldc -328869459 (java.lang.Integer)
    invokestatic u aj:(ZI)V
    goto L23
L78
    getstatic client jt:I
    ldc -1707817889 (java.lang.Integer)
    imul
    ifne L215
    iload 4
    ldc -844363041 (java.lang.Integer)
    if_icmpeq L166
    new java/lang/IllegalStateException
    dup
    invokespecial java/lang/IllegalStateException <init>:()V
    athrow
L216
    getstatic et o:Ljava/lang/String;
    iconst_0
    ldc -714308640 (java.lang.Integer)
    invokestatic dm av:(Ljava/lang/String;ZI)V
    goto L37
L167
    getstatic client gr:[I
    iload 16
    iaload
    bipush 6
    if_icmpge L217
    iload 4
    ldc -844363041 (java.lang.Integer)
    if_icmpeq L218
    new java/lang/IllegalStateException
    dup
    invokespecial java/lang/IllegalStateException <init>:()V
    athrow
L218
    getstatic client lz:[I
    getstatic client gr:[I
    iload 16
    iaload
    iaload
    istore 23
L217
    getstatic client gr:[I
    iload 16
    iaload
    bipush 6
    if_icmpne L201
    iload 4
    ldc -844363041 (java.lang.Integer)
    if_icmpeq L61
    new java/lang/IllegalStateException
    dup
    invokespecial java/lang/IllegalStateException <init>:()V
    athrow
L219
    ldc 16711935 (java.lang.Integer)
    ldc 327680 (java.lang.Integer)
    iload 24
    bipush 50
    isub
    imul
    isub
    istore 23
    goto L54
L91
    aload 6
    invokevirtual ap if:()V
    goto L96
L62
    ldc 16776960 (java.lang.Integer)
    goto L178
L165
    iload 16
    istore 15
    goto L194
L201
    getstatic client gr:[I
    iload 16
    iaload
    bipush 7
    if_icmpne L220
    iload 4
    ldc -844363041 (java.lang.Integer)
    if_icmpeq L221
    return
L12
    getstatic client hw:[I
    iload 6
    iaload
    ldc 7317091 (java.lang.Integer)
    getstatic client hd:I
    imul
    if_icmpne L20
    iload 4
    ldc -844363041 (java.lang.Integer)
    if_icmpeq L15
    return
L222
    sipush 255
    goto L223
L224
    ldc 65535 (java.lang.Integer)
L223
    istore 23
    goto L220
L225
    iload 15
    sipush 3056
    if_icmplt L226
    iload 4
    ldc -844363041 (java.lang.Integer)
    if_icmpeq L227
    return
L228
    ldc 1549434003 (java.lang.Integer)
    getstatic client gn:I
    imul
    bipush 20
    irem
    bipush 10
    if_icmpge L229
    iload 4
    ldc -844363041 (java.lang.Integer)
    if_icmpeq L203
    new java/lang/IllegalStateException
    dup
    invokespecial java/lang/IllegalStateException <init>:()V
    athrow
L183
    iconst_0
    putstatic client fm:I
    goto L184
L229
    ldc 8454016 (java.lang.Integer)
L204
    istore 23
    goto L230
L125
    sipush 128
    getstatic client ok:[I
    iconst_4
    iaload
    iadd
    istore 6
    goto L114
L231
    iload 24
    bipush 125
    if_icmple L169
    iload 4
    ldc -844363041 (java.lang.Integer)
    if_icmpeq L168
    new java/lang/IllegalStateException
    dup
    invokespecial java/lang/IllegalStateException <init>:()V
    athrow
L145
    iload 24
    bipush 50
    if_icmpge L150
    sipush 1280
    iload 24
    imul
    ldc 16711680 (java.lang.Integer)
    iadd
    istore 23
    goto L76
L232
    getstatic client gh:I
    ldc 1273855029 (java.lang.Integer)
    imul
    iload 0
    iadd
    bipush 50
    isub
    iload 1
    iload 0
    getstatic client gh:I
    ldc 1273855029 (java.lang.Integer)
    imul
    iadd
    bipush 50
    iadd
    iload 1
    iload 3
    iadd
    invokestatic bt cl:(IIII)V
    goto L233
L152
    ldc 16776960 (java.lang.Integer)
    iload 24
    bipush 50
    isub
    ldc 327680 (java.lang.Integer)
    imul
    isub
    istore 23
    goto L76
L151
    iload 24
    sipush 150
    if_icmpge L76
    iload 4
    ldc -844363041 (java.lang.Integer)
    if_icmpeq L75
    new java/lang/IllegalStateException
    dup
    invokespecial java/lang/IllegalStateException <init>:()V
    athrow
L60
    aload 6
    ldc 1164900853 (java.lang.Integer)
    aload 7
    getfield am b:I
    imul
    ldc 109190397 (java.lang.Integer)
    aload 7
    getfield am x:I
    imul
    ldc 1164900853 (java.lang.Integer)
    aload 7
    getfield am b:I
    imul
    aload 7
    getfield am x:I
    ldc 109190397 (java.lang.Integer)
    imul
    aload 6
    getfield i a:I
    ldc 1511118707 (java.lang.Integer)
    imul
    ldc 1958062732 (java.lang.Integer)
    invokestatic cl ar:(IIII)I
    ldc 537825681 (java.lang.Integer)
    aload 6
    getfield i w:I
    imul
    isub
    getstatic client b:I
    ldc -117546507 (java.lang.Integer)
    imul
    ldc 2141623322 (java.lang.Integer)
    invokevirtual i e:(IIIII)V
    goto L49
L198
    getstatic client h:Z
    ifeq L174
    iload 4
    ldc -844363041 (java.lang.Integer)
    if_icmpeq L173
    new java/lang/IllegalStateException
    dup
    invokespecial java/lang/IllegalStateException <init>:()V
    athrow
L234
    sipush 150
    getstatic client gg:[I
    iload 16
    iaload
    isub
    istore 24
L235
    iload 24
    bipush 50
    if_icmpge L236
    iload 4
    ldc -844363041 (java.lang.Integer)
    if_icmpeq L237
    new java/lang/IllegalStateException
    dup
    invokespecial java/lang/IllegalStateException <init>:()V
    athrow
L237
    ldc 16711680 (java.lang.Integer)
    iconst_5
    iload 24
    imul
    iadd
    istore 23
    goto L54
L236
    iload 24
    bipush 100
    if_icmpge L53
    iload 4
    ldc -844363041 (java.lang.Integer)
    if_icmpeq L219
    return
L149
    getstatic e fe:I
    iload 13
    ldc 1012303081 (java.lang.Integer)
    imul
    iadd
    putstatic e fe:I
    goto L148
L31
    iconst_0
    ldc -2051799234 (java.lang.Integer)
    invokestatic u aj:(ZI)V
    goto L33
L55
    ldc 327680 (java.lang.Integer)
    iload 24
    bipush 100
    isub
    imul
    sipush 255
    iadd
    iconst_5
    iload 24
    bipush 100
    isub
    imul
    isub
    istore 23
L54
    getstatic client gr:[I
    iload 16
    iaload
    bipush 11
    if_icmpne L238
    iload 4
    ldc -844363041 (java.lang.Integer)
    if_icmpeq L188
    new java/lang/IllegalStateException
    dup
    invokespecial java/lang/IllegalStateException <init>:()V
    athrow
L170
    iload 13
    iload 3
    iload 1
    iadd
    if_icmpge L57
    iload 4
    ldc -844363041 (java.lang.Integer)
    if_icmpeq L172
    return
L189
    iload 24
    bipush 50
    if_icmpge L239
    iload 4
    ldc -844363041 (java.lang.Integer)
    if_icmpeq L240
    return
L240
    ldc 16777215 (java.lang.Integer)
    ldc 327685 (java.lang.Integer)
    iload 24
    imul
    isub
    istore 23
    goto L238
L239
    iload 24
    bipush 100
    if_icmpge L241
    iload 4
    ldc -844363041 (java.lang.Integer)
    if_icmpeq L242
    new java/lang/IllegalStateException
    dup
    invokespecial java/lang/IllegalStateException <init>:()V
    athrow
L242
    ldc 65280 (java.lang.Integer)
    iload 24
    bipush 50
    isub
    ldc 327685 (java.lang.Integer)
    imul
    iadd
    istore 23
    goto L238
L241
    iload 24
    sipush 150
    if_icmpge L238
    iload 4
    ldc -844363041 (java.lang.Integer)
    if_icmpeq L243
    new java/lang/IllegalStateException
    dup
    invokespecial java/lang/IllegalStateException <init>:()V
    athrow
L243
    ldc 16777215 (java.lang.Integer)
    ldc 327680 (java.lang.Integer)
    iload 24
    bipush 100
    isub
    imul
    isub
    istore 23
    goto L238
L96
    getstatic client hi:Lgh;
    invokevirtual gh f:()Lgm;
    checkcast ap
    astore 6
    goto L212
L244
    getstatic hg cn:Lhh;
    aload 22
    iload 0
    ldc 1273855029 (java.lang.Integer)
    getstatic client gh:I
    imul
    iadd
    iload 1
    getstatic client gi:I
    ldc 1995677465 (java.lang.Integer)
    imul
    iadd
    iload 23
    iconst_0
    invokevirtual hh o:(Ljava/lang/String;IIII)V
    goto L97
L36
    ldc 1511118707 (java.lang.Integer)
    aload 6
    getfield i a:I
    imul
    ldc -837647185 (java.lang.Integer)
    getstatic fd hz:I
    imul
    if_icmpne L40
    iload 4
    ldc -844363041 (java.lang.Integer)
    if_icmpeq L38
    new java/lang/IllegalStateException
    dup
    invokespecial java/lang/IllegalStateException <init>:()V
    athrow
L76
    bipush 10
    getstatic client gr:[I
    iload 16
    iaload
    if_icmpne L54
    goto L234
L98
    iconst_2
    getstatic client gq:[I
    iload 16
    iaload
    if_icmpne L245
    iload 4
    ldc -844363041 (java.lang.Integer)
    if_icmpeq L246
    new java/lang/IllegalStateException
    dup
    invokespecial java/lang/IllegalStateException <init>:()V
    athrow
L246
    getstatic hg cn:Lhh;
    aload 22
    iload 0
    getstatic client gh:I
    ldc 1273855029 (java.lang.Integer)
    imul
    iadd
    iload 1
    ldc 1995677465 (java.lang.Integer)
    getstatic client gi:I
    imul
    iadd
    iload 23
    iconst_0
    ldc 1549434003 (java.lang.Integer)
    getstatic client gn:I
    imul
    invokevirtual hh j:(Ljava/lang/String;IIIII)V
    goto L245
L159
    iconst_1
    getstatic client gc:I
    ldc -1171775011 (java.lang.Integer)
    imul
    if_icmpne L66
    iload 4
    ldc -844363041 (java.lang.Integer)
    if_icmpeq L247
    return
L248
    getstatic hg cn:Lhh;
    aload 22
    iload 0
    ldc 1273855029 (java.lang.Integer)
    getstatic client gh:I
    imul
    iadd
    getstatic client gi:I
    ldc 1995677465 (java.lang.Integer)
    imul
    iload 1
    iadd
    iload 23
    iconst_0
    getstatic client gn:I
    ldc 1549434003 (java.lang.Integer)
    imul
    sipush 150
    getstatic client gg:[I
    iload 16
    iaload
    isub
    invokevirtual hh m:(Ljava/lang/String;IIIIII)V
L249
    getstatic client gq:[I
    iload 16
    iaload
    iconst_4
    if_icmpne L129
L250
    sipush 150
    getstatic client gg:[I
    iload 16
    iaload
    isub
    getstatic hg cn:Lhh;
    aload 22
    invokevirtual hh c:(Ljava/lang/String;)I
    bipush 100
    iadd
    imul
    sipush 150
    idiv
    istore 24
    goto L232
L230
    bipush 9
    getstatic client gr:[I
    iload 16
    iaload
    if_icmpne L76
    goto L144
L233
    getstatic hg cn:Lhh;
    aload 22
    getstatic client gh:I
    ldc 1273855029 (java.lang.Integer)
    imul
    iload 0
    iadd
    bipush 50
    iadd
    iload 24
    isub
    getstatic client gi:I
    ldc 1995677465 (java.lang.Integer)
    imul
    iload 1
    iadd
    iload 23
    iconst_0
    invokevirtual hh f:(Ljava/lang/String;IIII)V
L251
    iload 0
    iload 1
    iload 2
    iload 0
    iadd
    iload 3
    iload 1
    iadd
    invokestatic bt cw:(IIII)V
    goto L129
L208
    iload 22
    iload 16
    if_icmpge L181
    iload 4
    ldc -844363041 (java.lang.Integer)
    if_icmpeq L86
    return
L212
    aconst_null
    aload 6
    if_acmpeq L108
    iload 4
    ldc -844363041 (java.lang.Integer)
    if_icmpeq L90
    new java/lang/IllegalStateException
    dup
    invokespecial java/lang/IllegalStateException <init>:()V
    athrow
L252
    iconst_0
    istore 25
L253
    iload 24
    bipush 25
    if_icmpge L231
    iload 4
    ldc -844363041 (java.lang.Integer)
    if_icmpeq L254
    new java/lang/IllegalStateException
    dup
    invokespecial java/lang/IllegalStateException <init>:()V
    athrow
L254
    iload 24
    bipush 25
    isub
    istore 25
    goto L169
L131
    sipush 150
    getstatic client gg:[I
    iload 16
    iaload
    isub
    istore 24
    goto L252
L255
    ldc 1501484989 (java.lang.Integer)
    getstatic client ae:I
    imul
    getstatic x cs:I
    ldc 616886125 (java.lang.Integer)
    imul
    isub
    bipush 7
    ishl
    ldc 915534347 (java.lang.Integer)
    getstatic client ay:I
    imul
    iadd
    ldc 149707579 (java.lang.Integer)
    getstatic client ag:I
    imul
    getstatic client ab:I
    ldc 797306975 (java.lang.Integer)
    imul
    getstatic co cz:I
    ldc 1317226893 (java.lang.Integer)
    imul
    isub
    bipush 7
    ishl
    iadd
    ldc 1204740086 (java.lang.Integer)
    getstatic client av:I
    imul
    iconst_0
    invokestatic cm ak:(IIIB)V
    goto L256
L169
    iload 0
    iload 1
    getstatic client gi:I
    ldc 1995677465 (java.lang.Integer)
    imul
    iadd
    getstatic hg cn:Lhh;
    getfield hh i:I
    isub
    iconst_1
    isub
    iload 2
    iload 0
    iadd
    ldc 1995677465 (java.lang.Integer)
    getstatic client gi:I
    imul
    iload 1
    iadd
    iconst_5
    iadd
    invokestatic bt cl:(IIII)V
L257
    getstatic hg cn:Lhh;
    aload 22
    iload 0
    ldc 1273855029 (java.lang.Integer)
    getstatic client gh:I
    imul
    iadd
    iload 1
    ldc 1995677465 (java.lang.Integer)
    getstatic client gi:I
    imul
    iadd
    iload 25
    iadd
    iload 23
    iconst_0
    invokevirtual hh o:(Ljava/lang/String;IIII)V
    goto L211
L99
    getstatic hg cn:Lhh;
    aload 22
    ldc 1273855029 (java.lang.Integer)
    getstatic client gh:I
    imul
    iload 0
    iadd
    iload 1
    getstatic client gi:I
    ldc 1995677465 (java.lang.Integer)
    imul
    iadd
    iload 23
    iconst_0
    ldc 1549434003 (java.lang.Integer)
    getstatic client gn:I
    imul
    invokevirtual hh s:(Ljava/lang/String;IIIII)V
    goto L98
L130
    goto L258
L215
    getstatic hg cn:Lhh;
    aload 22
    getstatic client gh:I
    ldc 1273855029 (java.lang.Integer)
    imul
    iload 0
    iadd
    ldc 1995677465 (java.lang.Integer)
    getstatic client gi:I
    imul
    iload 1
    iadd
    ldc 16776960 (java.lang.Integer)
    iconst_0
    invokevirtual hh o:(Ljava/lang/String;IIII)V
L258
    iinc 16 1
    goto L79
L80
    ldc 577949343 (java.lang.Integer)
    getstatic client aw:I
    imul
    iconst_2
    if_icmpeq L255
    iload 4
    ldc -844363041 (java.lang.Integer)
    if_icmpeq L259
    new java/lang/IllegalStateException
    dup
    invokespecial java/lang/IllegalStateException <init>:()V
    athrow
L259
    goto L260
L210
    getstatic client fa:[I
    iload 22
    iaload
    getstatic client fn:[I
    iload 22
    iaload
    isub
    iload 18
    if_icmpge L87
    iload 4
    ldc -844363041 (java.lang.Integer)
    if_icmpeq L261
    new java/lang/IllegalStateException
    dup
    invokespecial java/lang/IllegalStateException <init>:()V
    athrow
L256
    ldc 1273855029 (java.lang.Integer)
    getstatic client gh:I
    imul
    iconst_m1
    if_icmple L260
    iload 4
    ldc -844363041 (java.lang.Integer)
    if_icmpeq L262
    new java/lang/IllegalStateException
    dup
    invokespecial java/lang/IllegalStateException <init>:()V
    athrow
L202
    getstatic client fa:[I
    iload 16
    iaload
    istore 18
    goto L205
L263
    getstatic u es:[Lbh;
    iconst_0
    aaload
    iload 0
    ldc 1273855029 (java.lang.Integer)
    getstatic client gh:I
    imul
    iadd
    bipush 12
    isub
    ldc 1995677465 (java.lang.Integer)
    getstatic client gi:I
    imul
    iload 1
    iadd
    bipush 28
    isub
    invokevirtual bh h:(II)V
L260
    getstatic cp ap:Lce;
    checkcast cq
    getstatic client ew:I
    ldc 509485067 (java.lang.Integer)
    imul
    bipush 50
    invokevirtual cq q:(IB)V
L264
    getstatic client gd:I
    ldc -2018558187 (java.lang.Integer)
    imul
    iconst_1
    if_icmpne L102
    iload 4
    ldc -844363041 (java.lang.Integer)
    if_icmpeq L265
    new java/lang/IllegalStateException
    dup
    invokespecial java/lang/IllegalStateException <init>:()V
    athrow
L265
    getstatic e ei:[Lbh;
    ldc 1735718725 (java.lang.Integer)
    getstatic client gj:I
    imul
    bipush 100
    idiv
    aaload
    ldc 589722061 (java.lang.Integer)
    getstatic client gs:I
    imul
    bipush 8
    isub
    ldc -802496585 (java.lang.Integer)
    getstatic client gk:I
    imul
    bipush 8
    isub
    invokevirtual bh h:(II)V
    goto L102
L127
    getstatic fd hz:I
    ldc -837647185 (java.lang.Integer)
    imul
    istore 7
    goto L32
L104
    getstatic e ei:[Lbh;
    getstatic client gj:I
    ldc 1735718725 (java.lang.Integer)
    imul
    bipush 100
    idiv
    iconst_4
    iadd
    aaload
    getstatic client gs:I
    ldc 589722061 (java.lang.Integer)
    imul
    bipush 8
    isub
    ldc -802496585 (java.lang.Integer)
    getstatic client gk:I
    imul
    bipush 8
    isub
    invokevirtual bh h:(II)V
L103
    iconst_0
    putstatic client gc:I
L266
    getstatic hg hv:Ll;
    getfield l b:I
    ldc 1164900853 (java.lang.Integer)
    imul
    bipush 7
    ishr
    getstatic x cs:I
    ldc 616886125 (java.lang.Integer)
    imul
    iadd
    istore 14
L267
    getstatic co cz:I
    ldc 1317226893 (java.lang.Integer)
    imul
    ldc 109190397 (java.lang.Integer)
    getstatic hg hv:Ll;
    getfield l x:I
    imul
    bipush 7
    ishr
    iadd
    istore 15
    goto L268
L191
    getstatic client cf:[Lam;
    getstatic client cb:[I
    iload 16
    ldc 308668811 (java.lang.Integer)
    getstatic client hr:I
    imul
    isub
    iaload
    aaload
    astore 17
    goto L190
L220
    bipush 8
    getstatic client gr:[I
    iload 16
    iaload
    if_icmpne L230
    iload 4
    ldc -844363041 (java.lang.Integer)
    if_icmpeq L228
    new java/lang/IllegalStateException
    dup
    invokespecial java/lang/IllegalStateException <init>:()V
    athrow
L268
    iload 14
    sipush 3053
    if_icmplt L226
    iload 4
    ldc -844363041 (java.lang.Integer)
    if_icmpeq L269
    new java/lang/IllegalStateException
    dup
    invokespecial java/lang/IllegalStateException <init>:()V
    athrow
L227
    iload 15
    sipush 3136
    if_icmpgt L226
    ldc -629588363 (java.lang.Integer)
    putstatic client gc:I
L226
    iload 14
    sipush 3072
    if_icmplt L159
    iload 4
    ldc -844363041 (java.lang.Integer)
    if_icmpeq L158
    return
L269
    iload 14
    sipush 3156
    if_icmpgt L226
    iload 4
    ldc -844363041 (java.lang.Integer)
    if_icmpeq L225
    new java/lang/IllegalStateException
    dup
    invokespecial java/lang/IllegalStateException <init>:()V
    athrow
L160
    iload 15
    sipush 9492
    if_icmplt L159
    iload 15
    sipush 9535
    if_icmpgt L159
    iload 4
    ldc -844363041 (java.lang.Integer)
    if_icmpeq L270
    new java/lang/IllegalStateException
    dup
    invokespecial java/lang/IllegalStateException <init>:()V
    athrow
L270
    ldc -629588363 (java.lang.Integer)
    putstatic client gc:I
    goto L159
L57
    iconst_0
    putstatic cy bw:Z
    goto L177
L247
    iload 14
    sipush 3139
    if_icmplt L66
    iload 4
    ldc -844363041 (java.lang.Integer)
    if_icmpeq L271
    return
L271
    iload 14
    sipush 3199
    if_icmpgt L66
    iload 4
    ldc -844363041 (java.lang.Integer)
    if_icmpeq L272
    return
L272
    iload 15
    sipush 3008
    if_icmplt L66
    iload 4
    ldc -844363041 (java.lang.Integer)
    if_icmpeq L65
    new java/lang/IllegalStateException
    dup
    invokespecial java/lang/IllegalStateException <init>:()V
    athrow
L261
    getstatic client fa:[I
    iload 22
    iaload
    getstatic client fn:[I
    iload 22
    iaload
    isub
    istore 18
    goto L213
L67
    iconst_0
    putstatic client gc:I
    goto L66
L69
    getstatic ep m:I
    ldc 1563808941 (java.lang.Integer)
    imul
    istore 13
    goto L163
L171
    sipush 512
    iload 0
    iadd
    iconst_5
    isub
    istore 14
L273
    iload 1
    bipush 20
    iadd
    istore 15
L274
    getstatic gy co:Lhh;
    new java/lang/StringBuilder
    dup
    invokespecial java/lang/StringBuilder <init>:()V
    ldc "Fps:" (java.lang.String)
    invokevirtual java/lang/StringBuilder append:(Ljava/lang/String;)Ljava/lang/StringBuilder;
    ldc 397715793 (java.lang.Integer)
    getstatic client ph:I
    imul
    invokevirtual java/lang/StringBuilder append:(I)Ljava/lang/StringBuilder;
    invokevirtual java/lang/StringBuilder toString:()Ljava/lang/String;
    iload 14
    iload 15
    ldc 16776960 (java.lang.Integer)
    iconst_m1
    invokevirtual hh g:(Ljava/lang/String;IIII)V
L275
    iinc 15 15
L276
    invokestatic java/lang/Runtime getRuntime:()Ljava/lang/Runtime;
    astore 16
L277
    aload 16
    invokevirtual java/lang/Runtime totalMemory:()J
    aload 16
    invokevirtual java/lang/Runtime freeMemory:()J
    lsub
    ldc 1024 (java.lang.Long)
    ldiv
    l2i
    istore 17
L278
    ldc 16776960 (java.lang.Integer)
    istore 18
    goto L197
L221
    ldc 1549434003 (java.lang.Integer)
    getstatic client gn:I
    imul
    bipush 20
    irem
    bipush 10
    if_icmpge L224
    goto L222
L245
    getstatic client gq:[I
    iload 16
    iaload
    iconst_3
    if_icmpne L249
    iload 4
    ldc -844363041 (java.lang.Integer)
    if_icmpeq L248
    new java/lang/IllegalStateException
    dup
    invokespecial java/lang/IllegalStateException <init>:()V
    athrow
L200
    getstatic client hg:[Ll;
    getstatic client hd:I
    ldc 7317091 (java.lang.Integer)
    imul
    aaload
    iload 15
    iload 0
    iload 1
    iload 2
    iload 3
    bipush -32
    invokestatic ai at:(Lab;IIIIIB)V
    goto L199
L174
    iload 17
    ldc 65536 (java.lang.Integer)
    if_icmple L28
    iload 4
    ldc -844363041 (java.lang.Integer)
    if_icmpeq L279
    return
L279
    getstatic client h:Z
    ifne L28
    ldc 16711680 (java.lang.Integer)
    istore 18
    goto L28
L50
    ldc 1164900853 (java.lang.Integer)
    aload 7
    getfield am b:I
    imul
    iflt L49
    iload 4
    ldc -844363041 (java.lang.Integer)
    if_icmpeq L128
    new java/lang/IllegalStateException
    dup
    invokespecial java/lang/IllegalStateException <init>:()V
    athrow
L238
    getstatic client gq:[I
    iload 16
    iaload
    ifne L97
    iload 4
    ldc -844363041 (java.lang.Integer)
    if_icmpeq L244
    new java/lang/IllegalStateException
    dup
    invokespecial java/lang/IllegalStateException <init>:()V
    athrow
L132
    ldc -648340705 (java.lang.Integer)
    iload 7
    imul
    putstatic ev fj:I
L280
    ldc 1416962957 (java.lang.Integer)
    iload 8
    imul
    putstatic ev fz:I
L281
    ldc 1012303081 (java.lang.Integer)
    iload 9
    imul
    putstatic e fe:I
L282
    ldc 1391672555 (java.lang.Integer)
    iload 10
    imul
    putstatic s fb:I
L283
    iload 11
    ldc -381465019 (java.lang.Integer)
    imul
    putstatic ez fk:I
L284
    getstatic client d:Z
    ifeq L285
    iload 4
    ldc -844363041 (java.lang.Integer)
    if_icmpeq L286
    new java/lang/IllegalStateException
    dup
    invokespecial java/lang/IllegalStateException <init>:()V
    athrow
L286
    iconst_1
    iconst_0
    ldc 357423703 (java.lang.Integer)
    invokestatic em u:(ZZI)I
    ifne L285
    iconst_0
    putstatic client d:Z
L285
    getstatic client d:Z
    ifeq L37
L287
    iload 0
    iload 1
    iload 2
    iload 3
    iconst_0
    invokestatic bt cs:(IIIII)V
    goto L216
L190
    aload 17
    iload 16
    iload 0
    iload 1
    iload 2
    iload 3
    bipush -26
    invokestatic ai at:(Lab;IIIIIB)V
    goto L26
L262
    getstatic client b:I
    ldc -117546507 (java.lang.Integer)
    imul
    bipush 20
    irem
    bipush 10
    if_icmpge L260
    iload 4
    ldc -844363041 (java.lang.Integer)
    if_icmpeq L263
    new java/lang/IllegalStateException
    dup
    invokespecial java/lang/IllegalStateException <init>:()V
    athrow
L288
    new java/lang/StringBuilder
    dup
    invokespecial java/lang/StringBuilder <init>:()V
    ldc "y.ay(" (java.lang.String)
    invokevirtual java/lang/StringBuilder append:(Ljava/lang/String;)Ljava/lang/StringBuilder;
    ldc 41 (java.lang.Integer)
    invokevirtual java/lang/StringBuilder append:(C)Ljava/lang/StringBuilder;
    invokevirtual java/lang/StringBuilder toString:()Ljava/lang/String;
    invokestatic k a:(Ljava/lang/Throwable;Ljava/lang/String;)Lee;
    athrow
