y be (IIIIIIII)VL1
    iload 2
    iconst_1
    if_icmplt L2
    iload 7
    ldc -231276320 (java.lang.Integer)
    if_icmpgt L3
    new java/lang/IllegalStateException
    dup
    invokespecial java/lang/IllegalStateException <init>:()V
    athrow
L4
    iload 0
    istore 12
    goto L5
L6
    iload 2
    bipush 102
    if_icmpgt L2
    iload 7
    ldc -231276320 (java.lang.Integer)
    if_icmpgt L7
    new java/lang/IllegalStateException
    dup
    invokespecial java/lang/IllegalStateException <init>:()V
    athrow
L8
    getstatic n ds:Lcb;
    iload 0
    iload 2
    iload 3
    invokevirtual cb b:(III)V
    goto L9
L10
    getstatic client h:Z
    ifeq L11
    iload 7
    ldc -231276320 (java.lang.Integer)
    if_icmpgt L12
    new java/lang/IllegalStateException
    dup
    invokespecial java/lang/IllegalStateException <init>:()V
    athrow
L13
    getstatic n ds:Lcb;
    iload 0
    iload 2
    iload 3
    invokevirtual cb ai:(III)I
    istore 8
    goto L14
L15
    getstatic n ds:Lcb;
    iload 0
    iload 2
    iload 3
    invokevirtual cb q:(III)V
    goto L16
L11
    iconst_0
    istore 8
L17
    iconst_m1
    istore 9
    goto L18
L16
    iload 1
    iconst_2
    if_icmpne L19
    iload 7
    ldc -231276320 (java.lang.Integer)
    if_icmpgt L20
    return
L21
    iconst_0
    istore 11
    goto L22
L23
    return
L24
    getstatic n ds:Lcb;
    iload 0
    iload 2
    iload 3
    invokevirtual cb ax:(III)I
    istore 8
L25
    iconst_1
    iload 1
    if_icmpne L26
    iload 7
    ldc -231276320 (java.lang.Integer)
    if_icmpgt L27
    new java/lang/IllegalStateException
    dup
    invokespecial java/lang/IllegalStateException <init>:()V
    athrow
L27
    getstatic n ds:Lcb;
    iload 0
    iload 2
    iload 3
    invokevirtual cb ap:(III)I
    istore 8
L26
    iconst_2
    iload 1
    if_icmpne L28
    iload 7
    ldc -231276320 (java.lang.Integer)
    if_icmpgt L29
    return
L29
    getstatic n ds:Lcb;
    iload 0
    iload 2
    iload 3
    invokevirtual cb ao:(III)I
    istore 8
    goto L28
L30
    iinc 12 1
    goto L31
L32
    iconst_0
    iload 1
    if_icmpne L33
    iload 7
    ldc -231276320 (java.lang.Integer)
    if_icmpgt L34
    new java/lang/IllegalStateException
    dup
    invokespecial java/lang/IllegalStateException <init>:()V
    athrow
L14
    iconst_0
    iload 8
    if_icmpeq L35
    iload 7
    ldc -231276320 (java.lang.Integer)
    if_icmpgt L36
    new java/lang/IllegalStateException
    dup
    invokespecial java/lang/IllegalStateException <init>:()V
    athrow
L37
    ldc -1945821617 (java.lang.Integer)
    aload 13
    getfield ag q:I
    imul
    iconst_1
    if_icmpne L35
    iload 7
    ldc -231276320 (java.lang.Integer)
    if_icmpgt L38
    new java/lang/IllegalStateException
    dup
    invokespecial java/lang/IllegalStateException <init>:()V
    athrow
L39
    iload 8
    bipush 14
    ishr
    sipush 32767
    iand
    istore 9
    goto L40
L33
    iconst_1
    iload 1
    if_icmpne L16
    iload 7
    ldc -231276320 (java.lang.Integer)
    if_icmpgt L15
    new java/lang/IllegalStateException
    dup
    invokespecial java/lang/IllegalStateException <init>:()V
    athrow
L41
    iload 12
    bipush 6
    ishr
    iconst_3
    iand
    istore 11
    goto L32
L42
    iload 9
    bipush -5
    invokestatic m e:(IB)Lag;
    astore 13
    goto L43
L34
    getstatic n ds:Lcb;
    iload 0
    iload 2
    iload 3
    invokevirtual cb y:(III)V
    goto L42
L7
    iload 3
    bipush 102
    if_icmpgt L2
    iload 7
    ldc -231276320 (java.lang.Integer)
    if_icmpgt L10
    new java/lang/IllegalStateException
    dup
    invokespecial java/lang/IllegalStateException <init>:()V
    athrow
L12
    iload 0
    ldc -837647185 (java.lang.Integer)
    getstatic fd hz:I
    imul
    if_icmpeq L11
    iload 7
    ldc -231276320 (java.lang.Integer)
    if_icmpgt L23
    return
L44
    getstatic client w:[Lhk;
    iload 0
    aaload
    iload 2
    iload 3
    iload 10
    iload 11
    aload 13
    getfield ag d:Z
    ldc 214969881 (java.lang.Integer)
    invokevirtual hk i:(IIIIZI)V
    goto L33
L18
    iconst_0
    istore 10
    goto L21
L2
    return
L43
    aload 13
    getfield ag q:I
    ldc -1945821617 (java.lang.Integer)
    imul
    ifeq L33
    iload 7
    ldc -231276320 (java.lang.Integer)
    if_icmpgt L44
    return
L20
    getstatic n ds:Lcb;
    iload 0
    iload 2
    iload 3
    invokevirtual cb d:(III)V
L45
    iload 9
    bipush -48
    invokestatic m e:(IB)Lag;
    astore 13
L46
    aload 13
    getfield ag z:I
    ldc 1527764841 (java.lang.Integer)
    imul
    iload 2
    iadd
    bipush 103
    if_icmpgt L47
    iload 7
    ldc -231276320 (java.lang.Integer)
    if_icmpgt L48
    new java/lang/IllegalStateException
    dup
    invokespecial java/lang/IllegalStateException <init>:()V
    athrow
L38
    getstatic client w:[Lhk;
    iload 0
    aaload
    iload 2
    iload 3
    sipush -23439
    invokevirtual hk g:(IIS)V
    goto L35
L49
    ldc -1050702509 (java.lang.Integer)
    aload 13
    getfield ag y:I
    imul
    iload 2
    iadd
    bipush 103
    if_icmpgt L47
    iload 7
    ldc -231276320 (java.lang.Integer)
    if_icmpgt L50
    new java/lang/IllegalStateException
    dup
    invokespecial java/lang/IllegalStateException <init>:()V
    athrow
L50
    iload 3
    ldc -1050702509 (java.lang.Integer)
    aload 13
    getfield ag y:I
    imul
    iadd
    bipush 103
    if_icmple L51
    iload 7
    ldc -231276320 (java.lang.Integer)
    if_icmpgt L47
    new java/lang/IllegalStateException
    dup
    invokespecial java/lang/IllegalStateException <init>:()V
    athrow
L47
    return
L51
    iconst_0
    ldc -1945821617 (java.lang.Integer)
    aload 13
    getfield ag q:I
    imul
    if_icmpeq L19
    iload 7
    ldc -231276320 (java.lang.Integer)
    if_icmpgt L52
    new java/lang/IllegalStateException
    dup
    invokespecial java/lang/IllegalStateException <init>:()V
    athrow
L52
    getstatic client w:[Lhk;
    iload 0
    aaload
    iload 2
    iload 3
    ldc 1527764841 (java.lang.Integer)
    aload 13
    getfield ag z:I
    imul
    ldc -1050702509 (java.lang.Integer)
    aload 13
    getfield ag y:I
    imul
    iload 11
    aload 13
    getfield ag d:Z
    ldc 1972804238 (java.lang.Integer)
    invokevirtual hk r:(IIIIIZI)V
L19
    iload 1
    iconst_3
    if_icmpne L35
    iload 7
    ldc -231276320 (java.lang.Integer)
    if_icmpgt L8
    new java/lang/IllegalStateException
    dup
    invokespecial java/lang/IllegalStateException <init>:()V
    athrow
L22
    iload 1
    ifne L25
    iload 7
    ldc -231276320 (java.lang.Integer)
    if_icmpgt L24
    new java/lang/IllegalStateException
    dup
    invokespecial java/lang/IllegalStateException <init>:()V
    athrow
L9
    iload 9
    bipush -122
    invokestatic m e:(IB)Lag;
    astore 13
    goto L37
L36
    getstatic n ds:Lcb;
    iload 0
    iload 2
    iload 3
    iload 8
    invokevirtual cb aw:(IIII)I
    istore 12
    goto L39
L28
    iload 1
    iconst_3
    if_icmpne L14
    goto L13
L35
    iload 4
    iflt L2
    iload 7
    ldc -231276320 (java.lang.Integer)
    if_icmpgt L4
    new java/lang/IllegalStateException
    dup
    invokespecial java/lang/IllegalStateException <init>:()V
    athrow
L40
    iload 12
    bipush 31
    iand
    istore 10
    goto L41
L5
    iload 12
    iconst_3
    if_icmpge L31
    iload 7
    ldc -231276320 (java.lang.Integer)
    if_icmpgt L53
    new java/lang/IllegalStateException
    dup
    invokespecial java/lang/IllegalStateException <init>:()V
    athrow
L53
    getstatic w a:[[[B
    iconst_1
    aaload
    iload 2
    aaload
    iload 3
    baload
    iconst_2
    iand
    iconst_2
    if_icmpne L31
    iload 7
    ldc -231276320 (java.lang.Integer)
    if_icmpgt L30
    new java/lang/IllegalStateException
    dup
    invokespecial java/lang/IllegalStateException <init>:()V
    athrow
L48
    aload 13
    getfield ag z:I
    ldc 1527764841 (java.lang.Integer)
    imul
    iload 3
    iadd
    bipush 103
    if_icmpgt L47
    iload 7
    ldc -231276320 (java.lang.Integer)
    if_icmpgt L49
    return
L31
    iload 0
    iload 12
    iload 2
    iload 3
    iload 4
    iload 5
    iload 6
    getstatic n ds:Lcb;
    getstatic client w:[Lhk;
    iload 0
    aaload
    ldc 1922003277 (java.lang.Integer)
    invokestatic b z:(IIIIIIILcb;Lhk;I)V
    goto L2
L3
    iload 3
    iconst_1
    if_icmplt L2
    iload 7
    ldc -231276320 (java.lang.Integer)
    if_icmpgt L6
    new java/lang/IllegalStateException
    dup
    invokespecial java/lang/IllegalStateException <init>:()V
    athrow
L54
    new java/lang/StringBuilder
    dup
    invokespecial java/lang/StringBuilder <init>:()V
    ldc "y.be(" (java.lang.String)
    invokevirtual java/lang/StringBuilder append:(Ljava/lang/String;)Ljava/lang/StringBuilder;
    ldc 41 (java.lang.Integer)
    invokevirtual java/lang/StringBuilder append:(C)Ljava/lang/StringBuilder;
    invokevirtual java/lang/StringBuilder toString:()Ljava/lang/String;
    invokestatic k a:(Ljava/lang/Throwable;Ljava/lang/String;)Lee;
    athrow
