y dh (Ljava/lang/String;ZI)VL1
    aload 0
    ifnonnull L2
    iload 2
    ldc -423622872 (java.lang.Integer)
    if_icmpeq L3
    new java/lang/IllegalStateException
    dup
    invokespecial java/lang/IllegalStateException <init>:()V
    athrow
L4
    aload 6
    ifnull L5
    iload 2
    ldc -423622872 (java.lang.Integer)
    if_icmpeq L6
    new java/lang/IllegalStateException
    dup
    invokespecial java/lang/IllegalStateException <init>:()V
    athrow
L2
    ldc -1219831833 (java.lang.Integer)
    getstatic client oo:I
    imul
    bipush 100
    if_icmplt L7
    goto L8
L9
    return
L7
    ldc -1219831833 (java.lang.Integer)
    getstatic client oo:I
    imul
    sipush 400
    if_icmplt L10
    iload 2
    ldc -423622872 (java.lang.Integer)
    if_icmpeq L11
    new java/lang/IllegalStateException
    dup
    invokespecial java/lang/IllegalStateException <init>:()V
    athrow
L11
    bipush 31
    ldc "" (java.lang.String)
    getstatic et fw:Ljava/lang/String;
    ldc 2144312733 (java.lang.Integer)
    invokestatic c a:(ILjava/lang/String;Ljava/lang/String;I)V
    goto L9
L12
    getstatic client cd:Ldj;
    bipush 76
    ldc 593619274 (java.lang.Integer)
    invokevirtual dj hl:(II)V
    goto L13
L10
    aload 0
    getstatic dj g:Lge;
    ldc -731320525 (java.lang.Integer)
    invokestatic dp l:(Ljava/lang/CharSequence;Lge;I)Ljava/lang/String;
    astore 3
    goto L14
L3
    return
L15
    aload 7
    aload 3
    invokevirtual java/lang/String equals:(Ljava/lang/Object;)Z
    ifeq L16
    iload 2
    ldc -423622872 (java.lang.Integer)
    if_icmpeq L17
    return
L18
    iconst_0
    istore 4
L19
    iload 4
    getstatic client oo:I
    ldc -1219831833 (java.lang.Integer)
    imul
    if_icmpge L20
    iload 2
    ldc -423622872 (java.lang.Integer)
    if_icmpeq L21
    new java/lang/IllegalStateException
    dup
    invokespecial java/lang/IllegalStateException <init>:()V
    athrow
L21
    getstatic client oh:[Lr;
    iload 4
    aaload
    astore 5
    goto L22
L23
    return
L24
    aconst_null
    aload 6
    if_acmpeq L25
    iload 2
    ldc -423622872 (java.lang.Integer)
    if_icmpeq L26
    new java/lang/IllegalStateException
    dup
    invokespecial java/lang/IllegalStateException <init>:()V
    athrow
L5
    aload 5
    getfield z a:Ljava/lang/String;
    ifnull L27
    iload 2
    ldc -423622872 (java.lang.Integer)
    if_icmpeq L28
    new java/lang/IllegalStateException
    dup
    invokespecial java/lang/IllegalStateException <init>:()V
    athrow
L8
    iconst_1
    ldc -2040441443 (java.lang.Integer)
    getstatic client hq:I
    imul
    if_icmpne L11
    goto L7
L29
    return
L25
    aconst_null
    aload 5
    getfield r a:Ljava/lang/String;
    if_acmpeq L16
    iload 2
    ldc -423622872 (java.lang.Integer)
    if_icmpeq L30
    new java/lang/IllegalStateException
    dup
    invokespecial java/lang/IllegalStateException <init>:()V
    athrow
L30
    aload 5
    getfield r a:Ljava/lang/String;
    getstatic dj g:Lge;
    ldc -492585181 (java.lang.Integer)
    invokestatic dp l:(Ljava/lang/CharSequence;Lge;I)Ljava/lang/String;
    astore 7
L31
    aconst_null
    aload 7
    if_acmpeq L16
    goto L15
L32
    bipush 31
    ldc "" (java.lang.String)
    new java/lang/StringBuilder
    dup
    invokespecial java/lang/StringBuilder <init>:()V
    aload 0
    invokevirtual java/lang/StringBuilder append:(Ljava/lang/String;)Ljava/lang/StringBuilder;
    getstatic et fh:Ljava/lang/String;
    invokevirtual java/lang/StringBuilder append:(Ljava/lang/String;)Ljava/lang/StringBuilder;
    invokevirtual java/lang/StringBuilder toString:()Ljava/lang/String;
    ldc 302531361 (java.lang.Integer)
    invokestatic c a:(ILjava/lang/String;Ljava/lang/String;I)V
    goto L29
L17
    bipush 31
    ldc "" (java.lang.String)
    new java/lang/StringBuilder
    dup
    invokespecial java/lang/StringBuilder <init>:()V
    aload 0
    invokevirtual java/lang/StringBuilder append:(Ljava/lang/String;)Ljava/lang/StringBuilder;
    getstatic et fh:Ljava/lang/String;
    invokevirtual java/lang/StringBuilder append:(Ljava/lang/String;)Ljava/lang/StringBuilder;
    invokevirtual java/lang/StringBuilder toString:()Ljava/lang/String;
    ldc -53250068 (java.lang.Integer)
    invokestatic c a:(ILjava/lang/String;Ljava/lang/String;I)V
    goto L23
L26
    aload 6
    aload 3
    invokevirtual java/lang/String equals:(Ljava/lang/Object;)Z
    ifeq L25
    iload 2
    ldc -423622872 (java.lang.Integer)
    if_icmpeq L32
    new java/lang/IllegalStateException
    dup
    invokespecial java/lang/IllegalStateException <init>:()V
    athrow
L16
    iinc 4 1
    goto L19
L20
    iconst_0
    istore 4
L33
    iload 4
    ldc -78716921 (java.lang.Integer)
    getstatic client oi:I
    imul
    if_icmpge L34
    iload 2
    ldc -423622872 (java.lang.Integer)
    if_icmpeq L35
    new java/lang/IllegalStateException
    dup
    invokespecial java/lang/IllegalStateException <init>:()V
    athrow
L35
    getstatic client or:[Lz;
    iload 4
    aaload
    astore 5
    goto L36
L22
    aload 5
    getfield r e:Ljava/lang/String;
    getstatic dj g:Lge;
    ldc 1017448811 (java.lang.Integer)
    invokestatic dp l:(Ljava/lang/CharSequence;Lge;I)Ljava/lang/String;
    astore 6
    goto L24
L27
    iinc 4 1
    goto L33
L6
    aload 6
    aload 3
    invokevirtual java/lang/String equals:(Ljava/lang/Object;)Z
    ifeq L5
    iload 2
    ldc -423622872 (java.lang.Integer)
    if_icmpeq L37
    new java/lang/IllegalStateException
    dup
    invokespecial java/lang/IllegalStateException <init>:()V
    athrow
L36
    aload 5
    getfield z e:Ljava/lang/String;
    getstatic dj g:Lge;
    ldc -899911115 (java.lang.Integer)
    invokestatic dp l:(Ljava/lang/CharSequence;Lge;I)Ljava/lang/String;
    astore 6
    goto L4
L38
    return
L39
    aload 7
    ifnull L27
    iload 2
    ldc -423622872 (java.lang.Integer)
    if_icmpeq L40
    new java/lang/IllegalStateException
    dup
    invokespecial java/lang/IllegalStateException <init>:()V
    athrow
L28
    aload 5
    getfield z a:Ljava/lang/String;
    getstatic dj g:Lge;
    ldc 954700850 (java.lang.Integer)
    invokestatic dp l:(Ljava/lang/CharSequence;Lge;I)Ljava/lang/String;
    astore 7
    goto L39
L37
    bipush 31
    ldc "" (java.lang.String)
    new java/lang/StringBuilder
    dup
    invokespecial java/lang/StringBuilder <init>:()V
    getstatic et fr:Ljava/lang/String;
    invokevirtual java/lang/StringBuilder append:(Ljava/lang/String;)Ljava/lang/StringBuilder;
    aload 0
    invokevirtual java/lang/StringBuilder append:(Ljava/lang/String;)Ljava/lang/StringBuilder;
    getstatic et fm:Ljava/lang/String;
    invokevirtual java/lang/StringBuilder append:(Ljava/lang/String;)Ljava/lang/StringBuilder;
    invokevirtual java/lang/StringBuilder toString:()Ljava/lang/String;
    ldc 148088762 (java.lang.Integer)
    invokestatic c a:(ILjava/lang/String;Ljava/lang/String;I)V
    goto L38
L40
    aload 7
    aload 3
    invokevirtual java/lang/String equals:(Ljava/lang/Object;)Z
    ifeq L27
    iload 2
    ldc -423622872 (java.lang.Integer)
    if_icmpeq L41
    new java/lang/IllegalStateException
    dup
    invokespecial java/lang/IllegalStateException <init>:()V
    athrow
L41
    bipush 31
    ldc "" (java.lang.String)
    new java/lang/StringBuilder
    dup
    invokespecial java/lang/StringBuilder <init>:()V
    getstatic et fr:Ljava/lang/String;
    invokevirtual java/lang/StringBuilder append:(Ljava/lang/String;)Ljava/lang/StringBuilder;
    aload 0
    invokevirtual java/lang/StringBuilder append:(Ljava/lang/String;)Ljava/lang/StringBuilder;
    getstatic et fm:Ljava/lang/String;
    invokevirtual java/lang/StringBuilder append:(Ljava/lang/String;)Ljava/lang/StringBuilder;
    invokevirtual java/lang/StringBuilder toString:()Ljava/lang/String;
    ldc -1084937639 (java.lang.Integer)
    invokestatic c a:(ILjava/lang/String;Ljava/lang/String;I)V
L42
    return
L14
    aconst_null
    aload 3
    if_acmpne L18
    iload 2
    ldc -423622872 (java.lang.Integer)
    if_icmpeq L43
    new java/lang/IllegalStateException
    dup
    invokespecial java/lang/IllegalStateException <init>:()V
    athrow
L34
    getstatic hg hv:Ll;
    getfield l e:Ljava/lang/String;
    getstatic dj g:Lge;
    ldc 1812465745 (java.lang.Integer)
    invokestatic dp l:(Ljava/lang/CharSequence;Lge;I)Ljava/lang/String;
    aload 3
    invokevirtual java/lang/String equals:(Ljava/lang/Object;)Z
    ifeq L12
    iload 2
    ldc -423622872 (java.lang.Integer)
    if_icmpeq L44
    new java/lang/IllegalStateException
    dup
    invokespecial java/lang/IllegalStateException <init>:()V
    athrow
L43
    return
L45
    return
L44
    bipush 31
    ldc "" (java.lang.String)
    getstatic et fg:Ljava/lang/String;
    ldc -1424174433 (java.lang.Integer)
    invokestatic c a:(ILjava/lang/String;Ljava/lang/String;I)V
    goto L45
L13
    getstatic client cd:Ldj;
    astore 4
L46
    aload 0
    invokevirtual java/lang/String length:()I
    iconst_1
    iadd
    istore 5
L47
    aload 4
    iload 5
    bipush 14
    invokevirtual dj e:(IB)V
L48
    getstatic client cd:Ldj;
    aload 0
    sipush 502
    invokevirtual dj i:(Ljava/lang/String;S)V
L49
    return
L50
    new java/lang/StringBuilder
    dup
    invokespecial java/lang/StringBuilder <init>:()V
    ldc "y.dh(" (java.lang.String)
    invokevirtual java/lang/StringBuilder append:(Ljava/lang/String;)Ljava/lang/StringBuilder;
    ldc 41 (java.lang.Integer)
    invokevirtual java/lang/StringBuilder append:(C)Ljava/lang/StringBuilder;
    invokevirtual java/lang/StringBuilder toString:()Ljava/lang/String;
    invokestatic k a:(Ljava/lang/Throwable;Ljava/lang/String;)Lee;
    athrow
