y e (ZB)VL1
    aconst_null
    getstatic fz e:Leo;
    if_acmpne L2
    return
L2
    new dh
    dup
    iconst_4
    invokespecial dh <init>:(I)V
    astore 2
L3
    aload 2
    iload 0
    ifeq L4
    iload 1
    iconst_0
    if_icmplt L5
    new java/lang/IllegalStateException
    dup
    invokespecial java/lang/IllegalStateException <init>:()V
    athrow
L5
    iconst_2
    goto L6
L4
    iconst_3
L6
    bipush -54
    invokevirtual dh e:(IB)V
L7
    aload 2
    iconst_0
    bipush 88
    invokevirtual dh l:(IB)V
L8
    getstatic fz e:Leo;
    aload 2
    getfield dh e:[B
    iconst_0
    iconst_4
    ldc 1039821029 (java.lang.Integer)
    invokevirtual eo r:([BIII)V
L9
    goto L10
L11
    astore 2
L12
    getstatic fz e:Leo;
    bipush -128
    invokevirtual eo c:(B)V
L13
    goto L14
L15
    astore 3
L14
    getstatic fz v:I
    ldc -97197595 (java.lang.Integer)
    iadd
    putstatic fz v:I
L16
    aconst_null
    putstatic fz e:Leo;
L10
    return
L17
    new java/lang/StringBuilder
    dup
    invokespecial java/lang/StringBuilder <init>:()V
    ldc "y.e(" (java.lang.String)
    invokevirtual java/lang/StringBuilder append:(Ljava/lang/String;)Ljava/lang/StringBuilder;
    ldc 41 (java.lang.Integer)
    invokevirtual java/lang/StringBuilder append:(C)Ljava/lang/StringBuilder;
    invokevirtual java/lang/StringBuilder toString:()Ljava/lang/String;
    invokestatic k a:(Ljava/lang/Throwable;Ljava/lang/String;)Lee;
    athrow
